{
  "type": "Feature",
  "properties": {
    "gn:admin1_code":"SE",
    "gn:admin2_code":"9",
    "gn:asciiname":"Polom",
    "gn:country_code":"RS",
    "gn:dem":743,
    "gn:feature_class":"P",
    "gn:feature_code":"PPL",
    "gn:name":"Polom",
    "gn:population":0,
    "gn:timezone":"Europe/Belgrade",
    "iso:country":"RS",
    "name:srp_x_preferred":[
        "Polom"
    ],
    "wof:name":"Polom",
    "wof:placetype":"locality"
},
  "geometry": {"coordinates":[20.22663,44.12137],"type":"Point"}
}