{
  "type": "Feature",
  "properties": {
    "gn:admin1_code":"SE",
    "gn:admin2_code":"24",
    "gn:asciiname":"Karadacka Mahala",
    "gn:country_code":"RS",
    "gn:dem":360,
    "gn:feature_class":"P",
    "gn:feature_code":"PPL",
    "gn:name":"Karada\u010dka Mahala",
    "gn:population":0,
    "gn:timezone":"Europe/Belgrade",
    "iso:country":"RS",
    "wof:name":"Karadacka Mahala",
    "wof:placetype":"locality"
},
  "geometry": {"coordinates":[22.01059,42.60241],"type":"Point"}
}