{
  "type": "Feature",
  "properties": {
    "iso:country":"RS",
    "name:eng_x_preferred":[
        "Blok 7a"
    ],
    "name:srp_cyr_x_preferred":[
        "\u0431\u043b\u043e\u043a 7a"
    ],
    "name:srp_x_preferred":[
        "\u0431\u043b\u043e\u043a 7a"
    ],
    "wof:name":"Blok 7a",
    "wof:placetype":"neighbourhood"
},
  "geometry": {"coordinates":[20.40233143013926,44.83197917678994],"type":"Point"}
}