{
  "type": "Feature",
  "properties": {
    "gn:admin1_code":"SE",
    "gn:admin2_code":"20",
    "gn:asciiname":"Skorica",
    "gn:country_code":"RS",
    "gn:dem":274,
    "gn:feature_class":"P",
    "gn:feature_code":"PPL",
    "gn:name":"Skorica",
    "gn:population":0,
    "gn:timezone":"Europe/Belgrade",
    "iso:country":"RS",
    "name:ceb_x_preferred":[
        "Skorica"
    ],
    "name:fra_x_preferred":[
        "Skorica"
    ],
    "name:msa_x_preferred":[
        "Skorica"
    ],
    "name:por_x_preferred":[
        "Skorica"
    ],
    "name:slv_x_preferred":[
        "Skorica"
    ],
    "name:srp_x_preferred":[
        "Skorica"
    ],
    "name:srp_x_variant":[
        "\u0421\u043a\u043e\u0440\u0438\u0446\u0430"
    ],
    "wof:name":"Skorica",
    "wof:placetype":"locality"
},
  "geometry": {"coordinates":[21.56467,43.78907],"type":"Point"}
}