{
  "type": "Feature",
  "properties": {
    "gn:admin1_code":"SE",
    "gn:admin2_code":"18",
    "gn:asciiname":"Vranovina",
    "gn:country_code":"RS",
    "gn:dem":747,
    "gn:feature_class":"P",
    "gn:feature_code":"PPL",
    "gn:name":"Vranovina",
    "gn:population":0,
    "gn:timezone":"Europe/Belgrade",
    "iso:country":"RS",
    "name:bos_x_preferred":[
        "Vranovina"
    ],
    "name:fra_x_preferred":[
        "Vranovina"
    ],
    "name:hrv_x_preferred":[
        "Vranovina"
    ],
    "name:srp_x_preferred":[
        "Vranovina"
    ],
    "name:srp_x_variant":[
        "\u0412\u0440\u0430\u043d\u043e\u0432\u0438\u043d\u0430"
    ],
    "wof:name":"Vranovina",
    "wof:placetype":"locality"
},
  "geometry": {"coordinates":[20.43694,43.24243],"type":"Point"}
}