{
  "type": "Feature",
  "properties": {
    "gn:admin1_code":"SE",
    "gn:admin2_code":"24",
    "gn:asciiname":"Marinkovska Mahala",
    "gn:country_code":"RS",
    "gn:dem":1264,
    "gn:feature_class":"P",
    "gn:feature_code":"PPL",
    "gn:name":"Marinkovska Mahala",
    "gn:population":0,
    "gn:timezone":"Europe/Belgrade",
    "iso:country":"RS",
    "wof:name":"Marinkovska Mahala",
    "wof:placetype":"locality"
},
  "geometry": {"coordinates":[22.18673,42.60754],"type":"Point"}
}