{
  "type": "Feature",
  "properties": {
    "gn:admin1_code":"SE",
    "gn:admin2_code":"16",
    "gn:asciiname":"Brdo",
    "gn:country_code":"RS",
    "gn:dem":857,
    "gn:feature_class":"P",
    "gn:feature_code":"PPL",
    "gn:name":"Brdo",
    "gn:population":0,
    "gn:timezone":"Europe/Belgrade",
    "iso:country":"RS",
    "name:bos_x_preferred":[
        "Brdo"
    ],
    "name:ceb_x_preferred":[
        "Brdo"
    ],
    "name:ces_x_preferred":[
        "Brdo"
    ],
    "name:deu_x_preferred":[
        "Brdo"
    ],
    "name:fra_x_preferred":[
        "Brdo"
    ],
    "name:hrv_x_preferred":[
        "Brdo"
    ],
    "name:hun_x_preferred":[
        "Brdo"
    ],
    "name:nld_x_preferred":[
        "Brdo"
    ],
    "name:pol_x_preferred":[
        "Brdo"
    ],
    "name:slv_x_preferred":[
        "Brdo"
    ],
    "name:srp_x_preferred":[
        "Brdo"
    ],
    "name:srp_x_variant":[
        "\u0411\u0440\u0434\u043e"
    ],
    "name:swe_x_preferred":[
        "Brdo"
    ],
    "name:ukr_x_preferred":[
        "\u0411\u0440\u0434\u043e"
    ],
    "name:und_x_variant":[
        "Bojovi\u0107i"
    ],
    "wof:name":"Brdo",
    "wof:placetype":"locality"
},
  "geometry": {"coordinates":[19.90301,43.67559],"type":"Point"}
}