{
  "type": "Feature",
  "properties": {
    "gn:admin1_code":"SE",
    "gn:admin2_code":"8",
    "gn:asciiname":"Paskovac",
    "gn:country_code":"RS",
    "gn:dem":251,
    "gn:feature_class":"P",
    "gn:feature_code":"PPL",
    "gn:name":"Paskovac",
    "gn:population":0,
    "gn:timezone":"Europe/Belgrade",
    "iso:country":"RS",
    "name:ceb_x_preferred":[
        "Paskovac"
    ],
    "name:deu_x_preferred":[
        "Paskovac"
    ],
    "name:fra_x_preferred":[
        "Paskovac"
    ],
    "name:msa_x_preferred":[
        "Paskovac"
    ],
    "name:nld_x_preferred":[
        "Paskovac"
    ],
    "name:por_x_preferred":[
        "Paskovac"
    ],
    "name:slv_x_preferred":[
        "Paskovac"
    ],
    "name:srp_x_preferred":[
        "Paskovac"
    ],
    "name:srp_x_variant":[
        "\u041f\u0430\u0441\u043a\u043e\u0432\u0430\u0446"
    ],
    "name:und_x_variant":[
        "Paskova"
    ],
    "wof:name":"Paskovac",
    "wof:placetype":"locality"
},
  "geometry": {"coordinates":[19.23889,44.47539],"type":"Point"}
}