{
  "type": "Feature",
  "properties": {
    "gn:admin1_code":"SE",
    "gn:admin2_code":"8",
    "gn:asciiname":"Paskovac",
    "gn:country_code":"RS",
    "gn:dem":251,
    "gn:feature_class":"P",
    "gn:feature_code":"PPL",
    "gn:name":"Paskovac",
    "gn:population":0,
    "gn:timezone":"Europe/Belgrade",
    "iso:country":"RS",
    "name:srp_x_preferred":[
        "Paskovac"
    ],
    "name:und_x_variant":[
        "Paskova"
    ],
    "wof:name":"Paskovac",
    "wof:placetype":"locality"
},
  "geometry": {"coordinates":[19.23889,44.47539],"type":"Point"}
}