{
  "type": "Feature",
  "properties": {
    "gn:admin1_code":"SE",
    "gn:admin2_code":"11",
    "gn:asciiname":"Omanje",
    "gn:country_code":"RS",
    "gn:dem":715,
    "gn:feature_class":"P",
    "gn:feature_code":"PPLL",
    "gn:name":"Omanje",
    "gn:population":0,
    "gn:timezone":"Europe/Belgrade",
    "iso:country":"RS",
    "wof:name":"Omanje",
    "wof:placetype":"locality"
},
  "geometry": {"coordinates":[21.91895,44.17907],"type":"Point"}
}