{
  "type": "Feature",
  "properties": {
    "gn:admin1_code":"SE",
    "gn:admin2_code":"10",
    "gn:asciiname":"Staro Selo",
    "gn:country_code":"RS",
    "gn:dem":102,
    "gn:feature_class":"P",
    "gn:feature_code":"PPL",
    "gn:name":"Staro Selo",
    "gn:population":0,
    "gn:timezone":"Europe/Belgrade",
    "iso:country":"RS",
    "name:srp_x_preferred":[
        "Staro Selo"
    ],
    "name:und_x_variant":[
        "Stari Ad\u017eibegovac"
    ],
    "wof:name":"Staro Selo",
    "wof:placetype":"locality"
},
  "geometry": {"coordinates":[21.08867,44.29426],"type":"Point"}
}