{
  "type": "Feature",
  "properties": {
    "gn:admin1_code":"SE",
    "gn:admin2_code":"10",
    "gn:asciiname":"Staro Selo",
    "gn:country_code":"RS",
    "gn:dem":102,
    "gn:feature_class":"P",
    "gn:feature_code":"PPL",
    "gn:name":"Staro Selo",
    "gn:population":0,
    "gn:timezone":"Europe/Belgrade",
    "iso:country":"RS",
    "name:ceb_x_preferred":[
        "Staro Selo"
    ],
    "name:deu_x_preferred":[
        "Staro Selo"
    ],
    "name:fra_x_preferred":[
        "Staro Selo"
    ],
    "name:msa_x_preferred":[
        "Staro Selo"
    ],
    "name:por_x_preferred":[
        "Staro Selo"
    ],
    "name:slv_x_preferred":[
        "Staro Selo"
    ],
    "name:srp_x_preferred":[
        "Staro Selo"
    ],
    "name:srp_x_variant":[
        "\u0421\u0442\u0430\u0440\u043e \u0421\u0435\u043b\u043e"
    ],
    "name:und_x_variant":[
        "Stari Ad\u017eibegovac"
    ],
    "wof:name":"Staro Selo",
    "wof:placetype":"locality"
},
  "geometry": {"coordinates":[21.08867,44.29426],"type":"Point"}
}