{
  "type": "Feature",
  "properties": {
    "gn:admin1_code":"SE",
    "gn:admin2_code":"9",
    "gn:asciiname":"Deguric",
    "gn:country_code":"RS",
    "gn:dem":260,
    "gn:feature_class":"P",
    "gn:feature_code":"PPL",
    "gn:name":"Deguri\u0107",
    "gn:population":0,
    "gn:timezone":"Europe/Belgrade",
    "iso:country":"RS",
    "name:ceb_x_preferred":[
        "Deguri\u0107"
    ],
    "name:ell_x_preferred":[
        "\u039d\u03c4\u03ad\u03b3\u03ba\u03bf\u03c5\u03c1\u03b9\u03c4\u03c2"
    ],
    "name:fra_x_preferred":[
        "Deguri\u0107"
    ],
    "name:msa_x_preferred":[
        "Deguri\u0107"
    ],
    "name:nld_x_preferred":[
        "Deguri\u0107"
    ],
    "name:por_x_preferred":[
        "Deguri\u0107"
    ],
    "name:slv_x_preferred":[
        "Deguri\u0107"
    ],
    "name:srp_x_preferred":[
        "Deguri\u0107"
    ],
    "name:srp_x_variant":[
        "\u0414\u0435\u0433\u0443\u0440\u0438\u045b"
    ],
    "wof:name":"Deguric",
    "wof:placetype":"locality"
},
  "geometry": {"coordinates":[19.88851,44.23974000000001],"type":"Point"}
}