{
  "type": "Feature",
  "properties": {
    "gn:admin1_code":"SE",
    "gn:admin2_code":"23",
    "gn:asciiname":"Jelasnica",
    "gn:country_code":"RS",
    "gn:dem":232,
    "gn:feature_class":"P",
    "gn:feature_code":"PPL",
    "gn:name":"Jela\u0161nica",
    "gn:population":0,
    "gn:timezone":"Europe/Belgrade",
    "iso:country":"RS",
    "name:srp_x_preferred":[
        "Jela\u0161nica"
    ],
    "wof:name":"Jelasnica",
    "wof:placetype":"locality"
},
  "geometry": {"coordinates":[22.00901,43.04447],"type":"Point"}
}