{
  "type": "Feature",
  "properties": {
    "gn:admin1_code":"SE",
    "gn:admin2_code":"16",
    "gn:asciiname":"Stitari",
    "gn:country_code":"RS",
    "gn:dem":739,
    "gn:feature_class":"P",
    "gn:feature_code":"PPL",
    "gn:name":"\u0160titari",
    "gn:population":0,
    "gn:timezone":"Europe/Belgrade",
    "iso:country":"RS",
    "wof:name":"Stitari",
    "wof:placetype":"locality"
},
  "geometry": {"coordinates":[19.77722,43.90568],"type":"Point"}
}