{
  "type": "Feature",
  "properties": {
    "gn:country":"RS",
    "gn:fcode":"PPLL",
    "gn:pop":2,
    "iso:country":"RS",
    "name:eng_x_preferred":[
        "Progorelica"
    ],
    "name:fra_x_preferred":[
        "Progorelica"
    ],
    "name:msa_x_preferred":[
        "Progorelica"
    ],
    "name:nld_x_preferred":[
        "Progorelica"
    ],
    "name:por_x_preferred":[
        "Progorelica"
    ],
    "name:slv_x_preferred":[
        "Progorelica"
    ],
    "name:srp_x_preferred":[
        "Progorelica"
    ],
    "qs:name":"Progorelica",
    "qs:photos_9r":0,
    "qs:photos_sr":0,
    "qs:pop_sr":"1",
    "wd:wordcount":34,
    "wof:name":"Progorelica",
    "wof:placetype":"locality",
    "wof:population":2
},
  "geometry": {"coordinates":[20.57026,43.68441],"type":"Point"}
}