{
  "type": "Feature",
  "properties": {
    "gn:country":"RS",
    "gn:fcode":"PPLL",
    "gn:population":2,
    "iso:country":"RS",
    "name:ceb_x_preferred":[
        "Progorelica"
    ],
    "name:eng_x_preferred":[
        "Progorelica"
    ],
    "name:fas_x_preferred":[
        "\u067e\u0631\u0648\u06af\u0648\u0631\u0644\u06cc\u062a\u0633\u0627"
    ],
    "name:fra_x_preferred":[
        "Progorelica"
    ],
    "name:msa_x_preferred":[
        "Progorelica"
    ],
    "name:nld_x_preferred":[
        "Progorelica"
    ],
    "name:pol_x_preferred":[
        "Progorelica"
    ],
    "name:por_x_preferred":[
        "Progorelica"
    ],
    "name:slv_x_preferred":[
        "Progorelica"
    ],
    "name:srp_x_preferred":[
        "Progorelica"
    ],
    "name:srp_x_variant":[
        "\u041f\u0440\u043e\u0433\u043e\u0440\u0435\u043b\u0438\u0446\u0430"
    ],
    "qs:name":"Progorelica",
    "qs:photos_9r":0,
    "qs:photos_sr":0,
    "qs:pop_sr":"1",
    "wd:wordcount":34,
    "wof:name":"Progorelica",
    "wof:placetype":"locality",
    "wof:population":2
},
  "geometry": {"coordinates":[20.57026,43.68441],"type":"Point"}
}