{
  "type": "Feature",
  "properties": {
    "gn:admin1_code":"SE",
    "gn:admin2_code":"24",
    "gn:asciiname":"Cerevajka",
    "gn:country_code":"RS",
    "gn:dem":826,
    "gn:feature_class":"P",
    "gn:feature_code":"PPLL",
    "gn:name":"Cerevajka",
    "gn:population":0,
    "gn:timezone":"Europe/Belgrade",
    "iso:country":"RS",
    "name:bul_x_preferred":[
        "\u0426\u0435\u0440\u0435\u0432\u0430\u0439\u043a\u0430"
    ],
    "name:fra_x_preferred":[
        "Cerevajka"
    ],
    "name:msa_x_preferred":[
        "Cerevajka"
    ],
    "name:por_x_preferred":[
        "Cerevajka"
    ],
    "name:slv_x_preferred":[
        "Cerevajka"
    ],
    "name:sqi_x_preferred":[
        "Caravajka"
    ],
    "name:srp_x_preferred":[
        "Cerevajka"
    ],
    "name:srp_x_variant":[
        "\u0426\u0435\u0440\u0435\u0432\u0430\u0458\u043a\u0430"
    ],
    "name:und_x_variant":[
        "Carevajka"
    ],
    "wof:name":"Cerevajka",
    "wof:placetype":"locality"
},
  "geometry": {"coordinates":[21.57263,42.33637],"type":"Point"}
}