{
  "type": "Feature",
  "properties": {
    "gn:admin1_code":"SE",
    "gn:admin2_code":"23",
    "gn:asciiname":"Petrovac",
    "gn:country_code":"RS",
    "gn:dem":332,
    "gn:feature_class":"P",
    "gn:feature_code":"PPL",
    "gn:name":"Petrovac",
    "gn:population":0,
    "gn:timezone":"Europe/Belgrade",
    "iso:country":"RS",
    "name:bel_x_preferred":[
        "\u041f\u0435\u0442\u0440\u0430\u0432\u0430\u0446"
    ],
    "name:bos_x_preferred":[
        "Petrovac"
    ],
    "name:bul_x_preferred":[
        "\u041f\u0435\u0442\u0440\u043e\u0432\u0430\u0446"
    ],
    "name:ceb_x_preferred":[
        "Petrovac"
    ],
    "name:deu_x_preferred":[
        "Petrovac"
    ],
    "name:fra_x_preferred":[
        "Petrovac"
    ],
    "name:hrv_x_preferred":[
        "Petrovac"
    ],
    "name:ita_x_preferred":[
        "Petrovac"
    ],
    "name:kor_x_preferred":[
        "\ud398\ud2b8\ub85c\ubc14\uce20"
    ],
    "name:lit_x_preferred":[
        "Petrovacas"
    ],
    "name:nld_x_preferred":[
        "Petrovac"
    ],
    "name:nor_x_preferred":[
        "Petrovac"
    ],
    "name:pol_x_preferred":[
        "Petrovac"
    ],
    "name:por_x_preferred":[
        "Petrovac"
    ],
    "name:ron_x_preferred":[
        "Petrovac"
    ],
    "name:rus_x_preferred":[
        "\u041f\u0435\u0442\u0440\u043e\u0432\u0430\u0446"
    ],
    "name:slv_x_preferred":[
        "Petrovac"
    ],
    "name:spa_x_preferred":[
        "Petrovac"
    ],
    "name:srp_x_preferred":[
        "Petrovac"
    ],
    "name:srp_x_variant":[
        "\u041f\u0435\u0442\u0440\u043e\u0432\u0430\u0446"
    ],
    "name:swe_x_preferred":[
        "Petrovac"
    ],
    "wof:name":"Petrovac",
    "wof:placetype":"locality"
},
  "geometry": {"coordinates":[21.81887,43.0254],"type":"Point"}
}