{
  "type": "Feature",
  "properties": {
    "gn:admin1_code":"SE",
    "gn:admin2_code":"18",
    "gn:asciiname":"Brgani",
    "gn:country_code":"RS",
    "gn:dem":1024,
    "gn:feature_class":"P",
    "gn:feature_code":"PPLL",
    "gn:name":"Br\u0111ani",
    "gn:population":0,
    "gn:timezone":"Europe/Belgrade",
    "iso:country":"RS",
    "name:srp_x_preferred":[
        "Br\u0111ani"
    ],
    "name:und_x_variant":[
        "Br\u0111ane",
        "Bragjan"
    ],
    "wof:name":"Brgani",
    "wof:placetype":"locality"
},
  "geometry": {"coordinates":[20.60722,43.08861],"type":"Point"}
}