{
  "type": "Feature",
  "properties": {
    "gn:admin1_code":"SE",
    "gn:admin2_code":"16",
    "gn:asciiname":"Filipovici",
    "gn:country_code":"RS",
    "gn:dem":561,
    "gn:feature_class":"P",
    "gn:feature_code":"PPL",
    "gn:name":"Filipovi\u0107i",
    "gn:population":0,
    "gn:timezone":"Europe/Belgrade",
    "iso:country":"RS",
    "wof:name":"Filipovici",
    "wof:placetype":"locality"
},
  "geometry": {"coordinates":[19.83556,43.96056],"type":"Point"}
}