{
  "type": "Feature",
  "properties": {
    "gn:admin1_code":"SE",
    "gn:admin2_code":"10",
    "gn:asciiname":"Paucina",
    "gn:country_code":"RS",
    "gn:dem":177,
    "gn:feature_class":"P",
    "gn:feature_code":"PPL",
    "gn:name":"Pau\u010dina",
    "gn:population":0,
    "gn:timezone":"Europe/Belgrade",
    "iso:country":"RS",
    "wof:name":"Paucina",
    "wof:placetype":"locality"
},
  "geometry": {"coordinates":[21.02444,44.445],"type":"Point"}
}