{
  "type": "Feature",
  "properties": {
    "gn:admin1_code":"SE",
    "gn:admin2_code":"23",
    "gn:asciiname":"Vrapce",
    "gn:country_code":"RS",
    "gn:dem":789,
    "gn:feature_class":"P",
    "gn:feature_code":"PPLL",
    "gn:name":"Vrapce",
    "gn:population":0,
    "gn:timezone":"Europe/Belgrade",
    "iso:country":"RS",
    "name:srp_x_preferred":[
        "Vrapce"
    ],
    "name:und_x_variant":[
        "Vrapci"
    ],
    "wof:name":"Vrapce",
    "wof:placetype":"locality"
},
  "geometry": {"coordinates":[21.54412,42.74881],"type":"Point"}
}