{
  "type": "Feature",
  "properties": {
    "gn:admin1_code":"SE",
    "gn:admin2_code":"17",
    "gn:asciiname":"Bulije",
    "gn:country_code":"RS",
    "gn:dem":527,
    "gn:feature_class":"P",
    "gn:feature_code":"PPL",
    "gn:name":"Bulije",
    "gn:population":0,
    "gn:timezone":"Europe/Belgrade",
    "iso:country":"RS",
    "name:srp_x_preferred":[
        "Bulije"
    ],
    "wof:name":"Bulije",
    "wof:placetype":"locality"
},
  "geometry": {"coordinates":[20.25804,43.69966],"type":"Point"}
}