{
  "type": "Feature",
  "properties": {
    "gn:admin1_code":"SE",
    "gn:admin2_code":"24",
    "gn:asciiname":"Makina Mahala",
    "gn:country_code":"RS",
    "gn:dem":1321,
    "gn:feature_class":"P",
    "gn:feature_code":"PPL",
    "gn:name":"Makina Mahala",
    "gn:population":0,
    "gn:timezone":"Europe/Belgrade",
    "iso:country":"RS",
    "wof:name":"Makina Mahala",
    "wof:placetype":"locality"
},
  "geometry": {"coordinates":[22.38678,42.60297],"type":"Point"}
}