{
  "type": "Feature",
  "properties": {
    "gn:admin1_code":"SE",
    "gn:admin2_code":"24",
    "gn:asciiname":"Garinarci",
    "gn:country_code":"RS",
    "gn:dem":1223,
    "gn:feature_class":"P",
    "gn:feature_code":"PPL",
    "gn:name":"Garinarci",
    "gn:population":0,
    "gn:timezone":"Europe/Belgrade",
    "iso:country":"RS",
    "wof:name":"Garinarci",
    "wof:placetype":"locality"
},
  "geometry": {"coordinates":[22.35584,42.34839],"type":"Point"}
}