{
  "type": "Feature",
  "properties": {
    "gn:admin1_code":"SE",
    "gn:admin2_code":"24",
    "gn:asciiname":"Potresje",
    "gn:country_code":"RS",
    "gn:dem":1278,
    "gn:feature_class":"P",
    "gn:feature_code":"PPL",
    "gn:name":"Potresje",
    "gn:population":0,
    "gn:timezone":"Europe/Belgrade",
    "iso:country":"RS",
    "name:und_x_variant":[
        "Potresinska Mahala",
        "Potresje"
    ],
    "wof:name":"Potresje",
    "wof:placetype":"locality"
},
  "geometry": {"coordinates":[22.39035,42.57912],"type":"Point"}
}