{
  "type": "Feature",
  "properties": {
    "gn:admin1_code":"SE",
    "gn:admin2_code":"24",
    "gn:asciiname":"Prisoje",
    "gn:country_code":"RS",
    "gn:dem":1052,
    "gn:feature_class":"P",
    "gn:feature_code":"PPL",
    "gn:name":"Prisoje",
    "gn:population":0,
    "gn:timezone":"Europe/Belgrade",
    "iso:country":"RS",
    "wof:name":"Prisoje",
    "wof:placetype":"locality"
},
  "geometry": {"coordinates":[22.07694,42.4853],"type":"Point"}
}