{
  "type": "Feature",
  "properties": {
    "gn:admin1_code":"SE",
    "gn:admin2_code":"24",
    "gn:asciiname":"Vojinov Rid",
    "gn:country_code":"RS",
    "gn:dem":1354,
    "gn:feature_class":"P",
    "gn:feature_code":"PPL",
    "gn:name":"Vojinov Rid",
    "gn:population":0,
    "gn:timezone":"Europe/Belgrade",
    "iso:country":"RS",
    "wof:name":"Vojinov Rid",
    "wof:placetype":"locality"
},
  "geometry": {"coordinates":[22.24617000000001,42.6074],"type":"Point"}
}