{
  "type": "Feature",
  "properties": {
    "gn:admin1_code":"SE",
    "gn:admin2_code":"12",
    "gn:asciiname":"Ovsiste",
    "gn:country_code":"RS",
    "gn:dem":325,
    "gn:feature_class":"P",
    "gn:feature_code":"PPL",
    "gn:name":"Ovsi\u0161te",
    "gn:population":0,
    "gn:timezone":"Europe/Belgrade",
    "iso:country":"RS",
    "name:ceb_x_preferred":[
        "Ovsi\u0161te"
    ],
    "name:fra_x_preferred":[
        "Ovsi\u0161te"
    ],
    "name:msa_x_preferred":[
        "Ovsi\u0161te"
    ],
    "name:por_x_preferred":[
        "Ovsi\u0161te"
    ],
    "name:slv_x_preferred":[
        "Ovsi\u0161te"
    ],
    "name:srp_x_preferred":[
        "Ovsi\u0161te"
    ],
    "name:srp_x_variant":[
        "\u041e\u0432\u0441\u0438\u0448\u0442\u0435"
    ],
    "wof:name":"Ovsiste",
    "wof:placetype":"locality"
},
  "geometry": {"coordinates":[20.7194,44.19276],"type":"Point"}
}