{
  "type": "Feature",
  "properties": {
    "gn:admin1_code":"SE",
    "gn:admin2_code":"13",
    "gn:asciiname":"Bucar",
    "gn:country_code":"RS",
    "gn:dem":420,
    "gn:feature_class":"P",
    "gn:feature_code":"PPLL",
    "gn:name":"Bu\u010dar",
    "gn:population":0,
    "gn:timezone":"Europe/Belgrade",
    "iso:country":"RS",
    "wof:name":"Bucar",
    "wof:placetype":"locality"
},
  "geometry": {"coordinates":[21.55583,44.07056],"type":"Point"}
}