{
  "type": "Feature",
  "properties": {
    "gn:admin1_code":"SE",
    "gn:admin2_code":"19",
    "gn:asciiname":"Stanojcici",
    "gn:country_code":"RS",
    "gn:dem":1148,
    "gn:feature_class":"P",
    "gn:feature_code":"PPL",
    "gn:name":"Stanoj\u010di\u0107i",
    "gn:population":0,
    "gn:timezone":"Europe/Belgrade",
    "iso:country":"RS",
    "name:srp_x_preferred":[
        "Stanoj\u010di\u0107i"
    ],
    "wof:name":"Stanojcici",
    "wof:placetype":"locality"
},
  "geometry": {"coordinates":[20.84611,43.45944],"type":"Point"}
}