{
  "type": "Feature",
  "properties": {
    "gn:admin1_code":"SE",
    "gn:admin2_code":"18",
    "gn:asciiname":"Eleskovice",
    "gn:country_code":"RS",
    "gn:dem":722,
    "gn:feature_class":"P",
    "gn:feature_code":"PPL",
    "gn:name":"Eleskovi\u0107e",
    "gn:population":0,
    "gn:timezone":"Europe/Belgrade",
    "iso:country":"RS",
    "name:srp_x_preferred":[
        "Eleskovi\u0107e"
    ],
    "wof:name":"Eleskovice",
    "wof:placetype":"locality"
},
  "geometry": {"coordinates":[20.45419,42.96648],"type":"Point"}
}