{
  "type": "Feature",
  "properties": {
    "gn:admin1_code":"SE",
    "gn:admin2_code":"17",
    "gn:asciiname":"Lisice",
    "gn:country_code":"RS",
    "gn:dem":306,
    "gn:feature_class":"P",
    "gn:feature_code":"PPL",
    "gn:name":"Lisice",
    "gn:population":0,
    "gn:timezone":"Europe/Belgrade",
    "iso:country":"RS",
    "name:ceb_x_preferred":[
        "Lisice"
    ],
    "name:fra_x_preferred":[
        "Lisice"
    ],
    "name:hrv_x_preferred":[
        "Lisice"
    ],
    "name:nld_x_preferred":[
        "Lisice"
    ],
    "name:pol_x_preferred":[
        "Lisice"
    ],
    "name:srp_x_preferred":[
        "\u041b\u0438\u0441\u0438\u0446\u0435"
    ],
    "name:swe_x_preferred":[
        "Lisice"
    ],
    "name:ukr_x_preferred":[
        "\u041b\u0456\u0441\u0456\u0446\u0435"
    ],
    "wof:name":"Lisice",
    "wof:placetype":"locality"
},
  "geometry": {"coordinates":[20.15488,43.84764000000001],"type":"Point"}
}