{
  "type": "Feature",
  "properties": {
    "gn:admin1_code":"SE",
    "gn:admin2_code":"17",
    "gn:asciiname":"Lisice",
    "gn:country_code":"RS",
    "gn:dem":306,
    "gn:feature_class":"P",
    "gn:feature_code":"PPL",
    "gn:name":"Lisice",
    "gn:population":0,
    "gn:timezone":"Europe/Belgrade",
    "iso:country":"RS",
    "wof:name":"Lisice",
    "wof:placetype":"locality"
},
  "geometry": {"coordinates":[20.15488,43.84764000000001],"type":"Point"}
}