{
  "type": "Feature",
  "properties": {
    "gn:admin1_code":"SE",
    "gn:admin2_code":"16",
    "gn:asciiname":"Dukanici",
    "gn:country_code":"RS",
    "gn:dem":509,
    "gn:feature_class":"P",
    "gn:feature_code":"PPL",
    "gn:name":"Dukani\u0107i",
    "gn:population":0,
    "gn:timezone":"Europe/Belgrade",
    "iso:country":"RS",
    "name:srp_x_preferred":[
        "Dukani\u0107i"
    ],
    "wof:name":"Dukanici",
    "wof:placetype":"locality"
},
  "geometry": {"coordinates":[19.67145,43.94535],"type":"Point"}
}