{
  "type": "Feature",
  "properties": {
    "gn:admin1_code":"SE",
    "gn:admin2_code":"15",
    "gn:asciiname":"Janja",
    "gn:country_code":"RS",
    "gn:dem":595,
    "gn:feature_class":"P",
    "gn:feature_code":"PPL",
    "gn:name":"Janja",
    "gn:population":0,
    "gn:timezone":"Europe/Belgrade",
    "iso:country":"RS",
    "name:srp_x_preferred":[
        "Janja"
    ],
    "wof:name":"Janja",
    "wof:placetype":"locality"
},
  "geometry": {"coordinates":[22.51886,43.42907],"type":"Point"}
}