{
  "type": "Feature",
  "properties": {
    "gn:admin1_code":"SE",
    "gn:admin2_code":"23",
    "gn:asciiname":"Dobro Polje",
    "gn:country_code":"RS",
    "gn:dem":1167,
    "gn:feature_class":"P",
    "gn:feature_code":"PPL",
    "gn:name":"Dobro Polje",
    "gn:population":0,
    "gn:timezone":"Europe/Belgrade",
    "iso:country":"RS",
    "name:bos_x_preferred":[
        "Dobro Polje"
    ],
    "name:fra_x_preferred":[
        "Dobro Polje"
    ],
    "name:hrv_x_preferred":[
        "Dobro Polje"
    ],
    "name:srp_x_preferred":[
        "Dobro Polje"
    ],
    "name:srp_x_variant":[
        "\u0414\u043e\u0431\u0440\u043e \u041f\u043e\u0459\u0435"
    ],
    "wof:name":"Dobro Polje",
    "wof:placetype":"locality"
},
  "geometry": {"coordinates":[22.28072,42.89313],"type":"Point"}
}