{
  "type": "Feature",
  "properties": {
    "gn:admin1_code":"SE",
    "gn:admin2_code":"0",
    "gn:asciiname":"Glogonjski Rit",
    "gn:country_code":"RS",
    "gn:dem":70,
    "gn:feature_class":"P",
    "gn:feature_code":"PPL",
    "gn:name":"Glogonjski Rit",
    "gn:population":0,
    "gn:timezone":"Europe/Belgrade",
    "iso:country":"RS",
    "wof:name":"Glogonjski Rit",
    "wof:placetype":"locality"
},
  "geometry": {"coordinates":[20.47947000000001,44.93587],"type":"Point"}
}