{
  "type": "Feature",
  "properties": {
    "gn:admin1_code":"SE",
    "gn:admin2_code":"16",
    "gn:asciiname":"Potpece",
    "gn:country_code":"RS",
    "gn:dem":476,
    "gn:feature_class":"P",
    "gn:feature_code":"PPL",
    "gn:name":"Potpe\u0107e",
    "gn:population":0,
    "gn:timezone":"Europe/Belgrade",
    "iso:country":"RS",
    "name:ceb_x_preferred":[
        "Potpe\u0107e"
    ],
    "name:fra_x_preferred":[
        "Potpe\u0107e"
    ],
    "name:msa_x_preferred":[
        "Potpe\u0107e"
    ],
    "name:nld_x_preferred":[
        "Potpe\u0107e"
    ],
    "name:por_x_preferred":[
        "Potpe\u0107e"
    ],
    "name:slv_x_preferred":[
        "Potpe\u0107e"
    ],
    "name:srp_x_preferred":[
        "Potpe\u0107e"
    ],
    "name:srp_x_variant":[
        "\u041f\u043e\u0442\u043f\u0435\u045b\u0435"
    ],
    "wof:name":"Potpece",
    "wof:placetype":"locality"
},
  "geometry": {"coordinates":[19.93215,43.80052],"type":"Point"}
}