{
  "type": "Feature",
  "properties": {
    "gn:admin1_code":"SE",
    "gn:admin2_code":"23",
    "gn:asciiname":"Mala Lomnica",
    "gn:country_code":"RS",
    "gn:dem":511,
    "gn:feature_class":"P",
    "gn:feature_code":"PPL",
    "gn:name":"Mala Lomnica",
    "gn:population":0,
    "gn:timezone":"Europe/Belgrade",
    "iso:country":"RS",
    "name:bos_x_preferred":[
        "Gornja Lomnica"
    ],
    "name:fra_x_preferred":[
        "Gornja Lomnica"
    ],
    "name:hrv_x_preferred":[
        "Gornja Lomnica"
    ],
    "name:hun_x_preferred":[
        "Gornja Lomnica"
    ],
    "name:srp_x_preferred":[
        "Mala Lomnica"
    ],
    "name:und_x_variant":[
        "Gornja Lomnica"
    ],
    "wof:name":"Mala Lomnica",
    "wof:placetype":"locality"
},
  "geometry": {"coordinates":[22.14602,43.00748],"type":"Point"}
}