{
  "type": "Feature",
  "properties": {
    "gn:admin1_code":"SE",
    "gn:admin2_code":"23",
    "gn:asciiname":"Mala Kopasnica",
    "gn:country_code":"RS",
    "gn:dem":252,
    "gn:feature_class":"P",
    "gn:feature_code":"PPL",
    "gn:name":"Mala Kopa\u0161nica",
    "gn:population":0,
    "gn:timezone":"Europe/Belgrade",
    "iso:country":"RS",
    "name:ceb_x_preferred":[
        "Mala Kopa\u0161nica"
    ],
    "name:fra_x_preferred":[
        "Mala Kopa\u0161nica"
    ],
    "name:msa_x_preferred":[
        "Mala Kopa\u0161nica"
    ],
    "name:por_x_preferred":[
        "Mala Kopa\u0161nica"
    ],
    "name:slv_x_preferred":[
        "Mala Kopa\u0161nica"
    ],
    "name:srp_x_preferred":[
        "Mala Kopa\u0161nica"
    ],
    "name:srp_x_variant":[
        "\u041c\u0430\u043b\u0430 \u041a\u043e\u043f\u0430\u0448\u043d\u0438\u0446\u0430"
    ],
    "name:und_x_variant":[
        "Kopa\u0161nica Mala"
    ],
    "wof:name":"Mala Kopasnica",
    "wof:placetype":"locality"
},
  "geometry": {"coordinates":[22.04599,42.91455],"type":"Point"}
}