{
  "type": "Feature",
  "properties": {
    "gn:admin1_code":"SE",
    "gn:admin2_code":"8",
    "gn:asciiname":"Donja Mala",
    "gn:country_code":"RS",
    "gn:dem":218,
    "gn:feature_class":"P",
    "gn:feature_code":"PPL",
    "gn:name":"Donja Mala",
    "gn:population":0,
    "gn:timezone":"Europe/Belgrade",
    "iso:country":"RS",
    "name:und_x_variant":[
        "Donjo",
        "Donja Mala"
    ],
    "wof:name":"Donja Mala",
    "wof:placetype":"locality"
},
  "geometry": {"coordinates":[19.35144,44.49948],"type":"Point"}
}