{
  "type": "Feature",
  "properties": {
    "gn:admin1_code":"SE",
    "gn:admin2_code":"16",
    "gn:asciiname":"Pljesivac",
    "gn:country_code":"RS",
    "gn:dem":693,
    "gn:feature_class":"P",
    "gn:feature_code":"PPL",
    "gn:name":"Plje\u0161ivac",
    "gn:population":0,
    "gn:timezone":"Europe/Belgrade",
    "iso:country":"RS",
    "name:srp_x_preferred":[
        "Plje\u0161ivac"
    ],
    "wof:name":"Pljesivac",
    "wof:placetype":"locality"
},
  "geometry": {"coordinates":[20.07231,43.66496],"type":"Point"}
}