{
  "type": "Feature",
  "properties": {
    "gn:admin1_code":"SE",
    "gn:admin2_code":"16",
    "gn:asciiname":"Bagacice",
    "gn:country_code":"RS",
    "gn:dem":1041,
    "gn:feature_class":"P",
    "gn:feature_code":"PPL",
    "gn:name":"Baga\u010di\u0107e",
    "gn:population":0,
    "gn:timezone":"Europe/Belgrade",
    "iso:country":"RS",
    "name:srp_x_preferred":[
        "Baga\u010di\u0107e"
    ],
    "name:und_x_variant":[
        "Boga\u010di\u0107i"
    ],
    "wof:name":"Bagacice",
    "wof:placetype":"locality"
},
  "geometry": {"coordinates":[20.06134,43.29243],"type":"Point"}
}