{
  "type": "Feature",
  "properties": {
    "gn:admin1_code":"SE",
    "gn:admin2_code":"21",
    "gn:asciiname":"Cungula",
    "gn:country_code":"RS",
    "gn:dem":398,
    "gn:feature_class":"P",
    "gn:feature_code":"PPL",
    "gn:name":"\u010cungula",
    "gn:population":0,
    "gn:timezone":"Europe/Belgrade",
    "iso:country":"RS",
    "name:srp_x_preferred":[
        "\u010cungula"
    ],
    "wof:name":"Cungula",
    "wof:placetype":"locality"
},
  "geometry": {"coordinates":[21.30877000000001,43.24606],"type":"Point"}
}