{
  "type": "Feature",
  "properties": {
    "gn:admin1_code":"SE",
    "gn:admin2_code":"21",
    "gn:asciiname":"Cungula",
    "gn:country_code":"RS",
    "gn:dem":398,
    "gn:feature_class":"P",
    "gn:feature_code":"PPL",
    "gn:name":"\u010cungula",
    "gn:population":0,
    "gn:timezone":"Europe/Belgrade",
    "iso:country":"RS",
    "name:ceb_x_preferred":[
        "\u010cungula"
    ],
    "name:fra_x_preferred":[
        "\u010cungula"
    ],
    "name:msa_x_preferred":[
        "\u010cungula"
    ],
    "name:por_x_preferred":[
        "\u010cungula"
    ],
    "name:slv_x_preferred":[
        "\u010cungula"
    ],
    "name:sqi_x_preferred":[
        "\u00c7unglla"
    ],
    "name:srp_x_preferred":[
        "\u010cungula"
    ],
    "name:srp_x_variant":[
        "\u0427\u0443\u043d\u0433\u0443\u043b\u0430"
    ],
    "wof:name":"Cungula",
    "wof:placetype":"locality"
},
  "geometry": {"coordinates":[21.30877000000001,43.24606],"type":"Point"}
}