{
  "type": "Feature",
  "properties": {
    "iso:country":"RS",
    "name:eng_x_preferred":[
        "Mika Alas"
    ],
    "name:srp_cyr_x_preferred":[
        "\u041c\u0438\u043a\u0430 \u0410\u043b\u0430\u0441"
    ],
    "name:srp_x_preferred":[
        "\u041c\u0438\u043a\u0430 \u0410\u043b\u0430\u0441"
    ],
    "wof:name":"Mika Alas",
    "wof:placetype":"neighbourhood"
},
  "geometry": {"coordinates":[20.43049399072758,44.84746183308278],"type":"Point"}
}