{
  "type": "Feature",
  "properties": {
    "gn:admin1_code":"SE",
    "gn:admin2_code":"17",
    "gn:asciiname":"Kolesnica",
    "gn:country_code":"RS",
    "gn:dem":1438,
    "gn:feature_class":"P",
    "gn:feature_code":"PPL",
    "gn:name":"Kole\u0161nica",
    "gn:population":0,
    "gn:timezone":"Europe/Belgrade",
    "iso:country":"RS",
    "name:srp_x_preferred":[
        "Kole\u0161nica"
    ],
    "wof:name":"Kolesnica",
    "wof:placetype":"locality"
},
  "geometry": {"coordinates":[20.3231,43.31872],"type":"Point"}
}