{
  "type": "Feature",
  "properties": {
    "gn:admin1_code":"SE",
    "gn:admin2_code":"0",
    "gn:asciiname":"Siroki Rt",
    "gn:country_code":"RS",
    "gn:dem":298,
    "gn:feature_class":"P",
    "gn:feature_code":"PPL",
    "gn:name":"\u0160iroki Rt",
    "gn:population":0,
    "gn:timezone":"Europe/Belgrade",
    "iso:country":"RS",
    "wof:name":"Siroki Rt",
    "wof:placetype":"locality"
},
  "geometry": {"coordinates":[20.4625,44.61861],"type":"Point"}
}