{
  "type": "Feature",
  "properties": {
    "gn:admin1_code":"SE",
    "gn:admin2_code":"20",
    "gn:asciiname":"Kunovica",
    "gn:country_code":"RS",
    "gn:dem":539,
    "gn:feature_class":"P",
    "gn:feature_code":"PPL",
    "gn:name":"Kunovica",
    "gn:population":0,
    "gn:timezone":"Europe/Belgrade",
    "iso:country":"RS",
    "name:ell_x_preferred":[
        "\u039a\u03bf\u03c5\u03bd\u03cc\u03b2\u03b9\u03c4\u03c3\u03b1"
    ],
    "name:fra_x_preferred":[
        "Kunovica"
    ],
    "name:msa_x_preferred":[
        "Kunovica"
    ],
    "name:por_x_preferred":[
        "Kunovica"
    ],
    "name:slv_x_preferred":[
        "Kunovica"
    ],
    "name:srp_x_preferred":[
        "Kunovica"
    ],
    "name:srp_x_variant":[
        "\u041a\u0443\u043d\u043e\u0432\u0438\u0446\u0430"
    ],
    "wof:name":"Kunovica",
    "wof:placetype":"locality"
},
  "geometry": {"coordinates":[22.09652,43.3003],"type":"Point"}
}