{
  "type": "Feature",
  "properties": {
    "gn:admin1_code":"SE",
    "gn:admin2_code":"23",
    "gn:asciiname":"Marovce",
    "gn:country_code":"RS",
    "gn:dem":703,
    "gn:feature_class":"P",
    "gn:feature_code":"PPLL",
    "gn:name":"Marovce",
    "gn:population":0,
    "gn:timezone":"Europe/Belgrade",
    "iso:country":"RS",
    "name:srp_x_preferred":[
        "Marovce"
    ],
    "name:und_x_variant":[
        "Marovci"
    ],
    "wof:name":"Marovce",
    "wof:placetype":"locality"
},
  "geometry": {"coordinates":[21.68333,42.71667],"type":"Point"}
}