{
  "type": "Feature",
  "properties": {
    "gn:admin1_code":"SE",
    "gn:admin2_code":"16",
    "gn:asciiname":"Negbina",
    "gn:country_code":"RS",
    "gn:dem":989,
    "gn:feature_class":"P",
    "gn:feature_code":"PPL",
    "gn:name":"Negbina",
    "gn:population":0,
    "gn:timezone":"Europe/Belgrade",
    "iso:country":"RS",
    "wof:name":"Negbina",
    "wof:placetype":"locality"
},
  "geometry": {"coordinates":[19.80409,43.54172],"type":"Point"}
}