{
  "type": "Feature",
  "properties": {
    "gn:admin1_code":"SE",
    "gn:admin2_code":"12",
    "gn:asciiname":"Majstorovica Mala",
    "gn:country_code":"RS",
    "gn:dem":384,
    "gn:feature_class":"P",
    "gn:feature_code":"PPL",
    "gn:name":"Majstorovi\u0107a Mala",
    "gn:population":0,
    "gn:timezone":"Europe/Belgrade",
    "iso:country":"RS",
    "wof:name":"Majstorovica Mala",
    "wof:placetype":"locality"
},
  "geometry": {"coordinates":[20.83194,43.91889000000001],"type":"Point"}
}