{
  "type": "Feature",
  "properties": {
    "gn:admin1_code":"00",
    "gn:asciiname":"Crvsko",
    "gn:country_code":"RS",
    "gn:dem":1056,
    "gn:feature_class":"P",
    "gn:feature_code":"PPL",
    "gn:name":"Crvsko",
    "gn:population":0,
    "gn:timezone":"Europe/Belgrade",
    "iso:country":"RS",
    "name:srp_x_preferred":[
        "Crvsko"
    ],
    "wof:name":"Crvsko",
    "wof:placetype":"locality"
},
  "geometry": {"coordinates":[19.91362,43.10874],"type":"Point"}
}