{
  "type": "Feature",
  "properties": {
    "gn:admin1_code":"00",
    "gn:asciiname":"Crvsko",
    "gn:country_code":"RS",
    "gn:dem":1056,
    "gn:feature_class":"P",
    "gn:feature_code":"PPL",
    "gn:name":"Crvsko",
    "gn:population":0,
    "gn:timezone":"Europe/Belgrade",
    "iso:country":"RS",
    "name:ceb_x_preferred":[
        "Crvsko"
    ],
    "name:fra_x_preferred":[
        "Crvsko"
    ],
    "name:msa_x_preferred":[
        "Crvsko"
    ],
    "name:nld_x_preferred":[
        "Crvsko"
    ],
    "name:por_x_preferred":[
        "Crvsko"
    ],
    "name:slv_x_preferred":[
        "Crvsko"
    ],
    "name:srp_x_preferred":[
        "Crvsko"
    ],
    "name:srp_x_variant":[
        "\u0426\u0440\u0432\u0441\u043a\u043e"
    ],
    "wof:name":"Crvsko",
    "wof:placetype":"locality"
},
  "geometry": {"coordinates":[19.91362,43.10874],"type":"Point"}
}