{
  "type": "Feature",
  "properties": {
    "gn:admin1_code":"SE",
    "gn:admin2_code":"8",
    "gn:asciiname":"Podgaj",
    "gn:country_code":"RS",
    "gn:dem":305,
    "gn:feature_class":"P",
    "gn:feature_code":"PPL",
    "gn:name":"Podgaj",
    "gn:population":0,
    "gn:timezone":"Europe/Belgrade",
    "iso:country":"RS",
    "name:bos_x_preferred":[
        "Podgaj"
    ],
    "name:ceb_x_preferred":[
        "Podgaj"
    ],
    "name:fra_x_preferred":[
        "Podgaj"
    ],
    "name:hrv_x_preferred":[
        "Podgaj"
    ],
    "name:pol_x_preferred":[
        "Podgaj"
    ],
    "name:slv_x_preferred":[
        "Podgaj"
    ],
    "name:srp_x_preferred":[
        "Podgaj"
    ],
    "name:srp_x_variant":[
        "\u041f\u043e\u0434\u0433\u0430\u0458"
    ],
    "name:swe_x_preferred":[
        "Podgaj"
    ],
    "name:ukr_x_preferred":[
        "\u041f\u043e\u0434\u0491\u0430\u0439"
    ],
    "wof:name":"Podgaj",
    "wof:placetype":"locality"
},
  "geometry": {"coordinates":[19.24967,44.29413],"type":"Point"}
}