{
  "type": "Feature",
  "properties": {
    "gn:admin1_code":"SE",
    "gn:admin2_code":"8",
    "gn:asciiname":"Podgaj",
    "gn:country_code":"RS",
    "gn:dem":305,
    "gn:feature_class":"P",
    "gn:feature_code":"PPL",
    "gn:name":"Podgaj",
    "gn:population":0,
    "gn:timezone":"Europe/Belgrade",
    "iso:country":"RS",
    "name:srp_x_preferred":[
        "Podgaj"
    ],
    "wof:name":"Podgaj",
    "wof:placetype":"locality"
},
  "geometry": {"coordinates":[19.24967,44.29413],"type":"Point"}
}