{
  "type": "Feature",
  "properties": {
    "gn:country":"RS",
    "gn:fcode":"PPL",
    "gn:population":4,
    "iso:country":"RS",
    "name:srp_x_preferred":[
        "Kokin Brod"
    ],
    "qs:name":"Kokin Brod",
    "qs:photos_9r":0,
    "qs:photos_sr":0,
    "qs:pop_sr":"1",
    "wof:name":"Kokin Brod",
    "wof:placetype":"locality",
    "wof:population":4
},
  "geometry": {"coordinates":[19.80139,43.51444],"type":"Point"}
}