{
  "type": "Feature",
  "properties": {
    "gn:admin1_code":"SE",
    "gn:admin2_code":"17",
    "gn:asciiname":"Kaculice",
    "gn:country_code":"RS",
    "gn:dem":278,
    "gn:feature_class":"P",
    "gn:feature_code":"PPLL",
    "gn:name":"Ka\u010dulice",
    "gn:population":0,
    "gn:timezone":"Europe/Belgrade",
    "iso:country":"RS",
    "name:ceb_x_preferred":[
        "Ka\u010dulice"
    ],
    "name:fas_x_preferred":[
        "\u06a9\u0627\u0686\u0648\u0644\u06cc\u062a\u0633\u0647"
    ],
    "name:fra_x_preferred":[
        "Ka\u010dulice"
    ],
    "name:msa_x_preferred":[
        "Ka\u010dulice"
    ],
    "name:por_x_preferred":[
        "Ka\u010dulice"
    ],
    "name:slv_x_preferred":[
        "Ka\u010dulice"
    ],
    "name:srp_x_preferred":[
        "\u041a\u0430\u0447\u0443\u043b\u0438\u0446\u0435"
    ],
    "wof:name":"Kaculice",
    "wof:placetype":"locality"
},
  "geometry": {"coordinates":[20.4875,43.77417],"type":"Point"}
}