{
  "type": "Feature",
  "properties": {
    "gn:admin1_code":"SE",
    "gn:admin2_code":"17",
    "gn:asciiname":"Kaculice",
    "gn:country_code":"RS",
    "gn:dem":278,
    "gn:feature_class":"P",
    "gn:feature_code":"PPLL",
    "gn:name":"Ka\u010dulice",
    "gn:population":0,
    "gn:timezone":"Europe/Belgrade",
    "iso:country":"RS",
    "name:und_x_variant":[
        "Ka\u010dulice"
    ],
    "wof:name":"Kaculice",
    "wof:placetype":"locality"
},
  "geometry": {"coordinates":[20.4875,43.77417],"type":"Point"}
}