{
  "type": "Feature",
  "properties": {
    "gn:country":"RS",
    "gn:fcode":"PPL",
    "gn:pop":454,
    "iso:country":"RS",
    "name:srp_x_preferred":[
        "Ora\u0161ac"
    ],
    "qs:name":"Ora\u0161ac",
    "qs:photos_9r":0,
    "qs:photos_sr":0,
    "qs:pop_sr":"2",
    "wd:wordcount":52,
    "wof:name":"Ora\u0161ac",
    "wof:placetype":"locality",
    "wof:population":454
},
  "geometry": {"coordinates":[19.78954,44.73211],"type":"Point"}
}