{
  "type": "Feature",
  "properties": {
    "gn:admin1_code":"SE",
    "gn:admin2_code":"8",
    "gn:asciiname":"Gornja Orovica",
    "gn:country_code":"RS",
    "gn:dem":719,
    "gn:feature_class":"P",
    "gn:feature_code":"PPL",
    "gn:name":"Gornja Orovica",
    "gn:population":0,
    "gn:timezone":"Europe/Belgrade",
    "iso:country":"RS",
    "name:srp_x_preferred":[
        "Gornja Orovica"
    ],
    "wof:name":"Gornja Orovica",
    "wof:placetype":"locality"
},
  "geometry": {"coordinates":[19.53075,44.21625],"type":"Point"}
}