{
  "type": "Feature",
  "properties": {
    "gn:admin1_code":"SE",
    "gn:admin2_code":"8",
    "gn:asciiname":"Gornja Orovica",
    "gn:country_code":"RS",
    "gn:dem":719,
    "gn:feature_class":"P",
    "gn:feature_code":"PPL",
    "gn:name":"Gornja Orovica",
    "gn:population":0,
    "gn:timezone":"Europe/Belgrade",
    "iso:country":"RS",
    "name:ceb_x_preferred":[
        "Gornja Orovica"
    ],
    "name:fas_x_preferred":[
        "\u06af\u0648\u0631\u0646\u06cc\u0627 \u0627\u0648\u0631\u0648\u06cc\u062a\u0633\u0627"
    ],
    "name:fra_x_preferred":[
        "Gornja Orovica"
    ],
    "name:msa_x_preferred":[
        "Gornja Orovica"
    ],
    "name:nld_x_preferred":[
        "Gornja Orovica"
    ],
    "name:por_x_preferred":[
        "Gornja Orovica"
    ],
    "name:slv_x_preferred":[
        "Gornja Orovica"
    ],
    "name:srp_x_preferred":[
        "Gornja Orovica"
    ],
    "name:srp_x_variant":[
        "\u0413\u043e\u0440\u045a\u0430 \u041e\u0440\u043e\u0432\u0438\u0446\u0430"
    ],
    "wof:name":"Gornja Orovica",
    "wof:placetype":"locality"
},
  "geometry": {"coordinates":[19.53075,44.21625],"type":"Point"}
}