{
  "type": "Feature",
  "properties": {
    "gn:admin1_code":"SE",
    "gn:admin2_code":"19",
    "gn:asciiname":"Dertevci",
    "gn:country_code":"RS",
    "gn:dem":426,
    "gn:feature_class":"P",
    "gn:feature_code":"PPL",
    "gn:name":"Dertevci",
    "gn:population":0,
    "gn:timezone":"Europe/Belgrade",
    "iso:country":"RS",
    "name:srp_x_preferred":[
        "Dertevci"
    ],
    "wof:name":"Dertevci",
    "wof:placetype":"locality"
},
  "geometry": {"coordinates":[21.03169,43.38096],"type":"Point"}
}