{
  "type": "Feature",
  "properties": {
    "gn:admin1_code":"SE",
    "gn:admin2_code":"16",
    "gn:asciiname":"Galina Reka",
    "gn:country_code":"RS",
    "gn:dem":349,
    "gn:feature_class":"P",
    "gn:feature_code":"PPL",
    "gn:name":"Galina Reka",
    "gn:population":0,
    "gn:timezone":"Europe/Belgrade",
    "iso:country":"RS",
    "name:srp_x_preferred":[
        "Galina Reka"
    ],
    "wof:name":"Galina Reka",
    "wof:placetype":"locality"
},
  "geometry": {"coordinates":[19.66695,44.01661],"type":"Point"}
}