{
  "type": "Feature",
  "properties": {
    "gn:admin1_code":"SE",
    "gn:admin2_code":"0",
    "gn:admin3_code":"70092.0",
    "gn:asciiname":"Barajevo",
    "gn:country_code":"RS",
    "gn:dem":142,
    "gn:feature_class":"P",
    "gn:feature_code":"PPLA3",
    "gn:name":"Barajevo",
    "gn:population":0,
    "gn:timezone":"Europe/Belgrade",
    "iso:country":"RS",
    "name:ara_x_preferred":[
        "\u0628\u0627\u0631\u0627\u064a\u064a\u0641\u0648"
    ],
    "name:bul_x_preferred":[
        "\u0411\u0430\u0440\u0430\u0435\u0432\u043e"
    ],
    "name:ces_x_preferred":[
        "Barajevo"
    ],
    "name:deu_x_preferred":[
        "Barajevo"
    ],
    "name:ell_x_preferred":[
        "\u039c\u03c0\u03b1\u03c1\u03ac\u03b3\u03b9\u03b5\u03b2\u03bf"
    ],
    "name:fra_x_preferred":[
        "Barajevo"
    ],
    "name:hrv_x_preferred":[
        "Barajevo"
    ],
    "name:ind_x_preferred":[
        "Barajevo"
    ],
    "name:ita_x_preferred":[
        "Barajevo"
    ],
    "name:kor_x_preferred":[
        "\ubc14\ub77c\uc608\ubcf4"
    ],
    "name:msa_x_preferred":[
        "Barajevo"
    ],
    "name:nld_x_preferred":[
        "Barajevo"
    ],
    "name:nor_x_preferred":[
        "Barajevo"
    ],
    "name:pol_x_preferred":[
        "Barajevo"
    ],
    "name:por_x_preferred":[
        "Barajevo"
    ],
    "name:rus_x_preferred":[
        "\u0411\u0430\u0440\u0430\u0435\u0432\u043e"
    ],
    "name:slv_x_preferred":[
        "Barajevo"
    ],
    "name:spa_x_preferred":[
        "Barajevo"
    ],
    "name:srp_x_preferred":[
        "Barajevo"
    ],
    "name:srp_x_variant":[
        "\u0411\u0430\u0440\u0430\u0458\u0435\u0432\u043e"
    ],
    "name:tur_x_preferred":[
        "Barajevo"
    ],
    "name:zho_x_preferred":[
        "\u5df4\u62c9\u70ed\u7a9d"
    ],
    "wof:name":"Barajevo",
    "wof:placetype":"locality"
},
  "geometry": {"coordinates":[20.41583,44.57889],"type":"Point"}
}