{
  "type": "Feature",
  "properties": {
    "gn:admin1_code":"SE",
    "gn:admin2_code":"0",
    "gn:admin3_code":"70092.0",
    "gn:asciiname":"Barajevo",
    "gn:country_code":"RS",
    "gn:dem":142,
    "gn:feature_class":"P",
    "gn:feature_code":"PPLA3",
    "gn:name":"Barajevo",
    "gn:population":0,
    "gn:timezone":"Europe/Belgrade",
    "iso:country":"RS",
    "name:srp_x_preferred":[
        "Barajevo"
    ],
    "wof:name":"Barajevo",
    "wof:placetype":"locality"
},
  "geometry": {"coordinates":[20.41583,44.57889],"type":"Point"}
}