{
  "type": "Feature",
  "properties": {
    "gn:admin1_code":"SE",
    "gn:admin2_code":"13",
    "gn:asciiname":"Lomnica",
    "gn:country_code":"RS",
    "gn:dem":457,
    "gn:feature_class":"P",
    "gn:feature_code":"PPL",
    "gn:name":"Lomnica",
    "gn:population":0,
    "gn:timezone":"Europe/Belgrade",
    "iso:country":"RS",
    "name:fas_x_preferred":[
        "\u0644\u0648\u0645\u0646\u06cc\u062a\u0633\u0627"
    ],
    "name:fra_x_preferred":[
        "Lomnica"
    ],
    "name:msa_x_preferred":[
        "Lomnica"
    ],
    "name:por_x_preferred":[
        "Lomnica"
    ],
    "name:slv_x_preferred":[
        "Lomnica"
    ],
    "name:srp_x_preferred":[
        "Lomnica"
    ],
    "name:srp_x_variant":[
        "\u041b\u043e\u043c\u043d\u0438\u0446\u0430"
    ],
    "wof:name":"Lomnica",
    "wof:placetype":"locality"
},
  "geometry": {"coordinates":[21.47622,44.13928],"type":"Point"}
}