{
  "type": "Feature",
  "properties": {
    "gn:admin1_code":"SE",
    "gn:admin2_code":"13",
    "gn:asciiname":"Lomnica",
    "gn:country_code":"RS",
    "gn:dem":457,
    "gn:feature_class":"P",
    "gn:feature_code":"PPL",
    "gn:name":"Lomnica",
    "gn:population":0,
    "gn:timezone":"Europe/Belgrade",
    "iso:country":"RS",
    "name:srp_x_preferred":[
        "Lomnica"
    ],
    "wof:name":"Lomnica",
    "wof:placetype":"locality"
},
  "geometry": {"coordinates":[21.47622,44.13928],"type":"Point"}
}