{
  "type": "Feature",
  "properties": {
    "gn:admin1_code":"SE",
    "gn:admin2_code":"20",
    "gn:asciiname":"Oreovac",
    "gn:country_code":"RS",
    "gn:dem":566,
    "gn:feature_class":"P",
    "gn:feature_code":"PPL",
    "gn:name":"Oreovac",
    "gn:population":0,
    "gn:timezone":"Europe/Belgrade",
    "iso:country":"RS",
    "name:fra_x_preferred":[
        "Oreovac"
    ],
    "name:slv_x_preferred":[
        "Oreovac"
    ],
    "name:srp_x_preferred":[
        "Oreovac"
    ],
    "name:srp_x_variant":[
        "\u041e\u0440\u0435\u043e\u0432\u0430\u0446"
    ],
    "name:und_x_variant":[
        "Orevac"
    ],
    "wof:name":"Oreovac",
    "wof:placetype":"locality"
},
  "geometry": {"coordinates":[22.06941,43.36768],"type":"Point"}
}