{
  "type": "Feature",
  "properties": {
    "gn:admin1_code":"SE",
    "gn:admin2_code":"12",
    "gn:asciiname":"Minica Mala",
    "gn:country_code":"RS",
    "gn:dem":317,
    "gn:feature_class":"P",
    "gn:feature_code":"PPL",
    "gn:name":"Mini\u0107a Mala",
    "gn:population":0,
    "gn:timezone":"Europe/Belgrade",
    "iso:country":"RS",
    "wof:name":"Minica Mala",
    "wof:placetype":"locality"
},
  "geometry": {"coordinates":[20.81361,43.95944],"type":"Point"}
}