{
  "type": "Feature",
  "properties": {
    "gn:admin1_code":"SE",
    "gn:admin2_code":"20",
    "gn:asciiname":"Donje Dragovlje",
    "gn:country_code":"RS",
    "gn:dem":483,
    "gn:feature_class":"P",
    "gn:feature_code":"PPL",
    "gn:name":"Donje Dragovlje",
    "gn:population":0,
    "gn:timezone":"Europe/Belgrade",
    "iso:country":"RS",
    "name:ceb_x_preferred":[
        "Donje Dragovlje"
    ],
    "name:fra_x_preferred":[
        "Donje Dragovlje"
    ],
    "name:msa_x_preferred":[
        "Donje Dragovlje"
    ],
    "name:por_x_preferred":[
        "Donje Dragovlje"
    ],
    "name:slv_x_preferred":[
        "Donje Dragovlje"
    ],
    "name:srp_x_preferred":[
        "Donje Dragovlje"
    ],
    "name:srp_x_variant":[
        "\u0414\u043e\u045a\u0435 \u0414\u0440\u0430\u0433\u043e\u0432\u0459\u0435"
    ],
    "wof:name":"Donje Dragovlje",
    "wof:placetype":"locality"
},
  "geometry": {"coordinates":[22.11162,43.13893],"type":"Point"}
}