{
  "type": "Feature",
  "properties": {
    "gn:admin1_code":"SE",
    "gn:admin2_code":"9",
    "gn:asciiname":"Bosnjanovic",
    "gn:country_code":"RS",
    "gn:dem":212,
    "gn:feature_class":"P",
    "gn:feature_code":"PPL",
    "gn:name":"Bo\u0161njanovi\u0107",
    "gn:population":0,
    "gn:timezone":"Europe/Belgrade",
    "iso:country":"RS",
    "name:ceb_x_preferred":[
        "Bo\u0161njanovi\u0107"
    ],
    "name:fra_x_preferred":[
        "Bo\u0161njanovi\u0107"
    ],
    "name:msa_x_preferred":[
        "Bo\u0161njanovi\u0107"
    ],
    "name:por_x_preferred":[
        "Bo\u0161njanovi\u0107"
    ],
    "name:slv_x_preferred":[
        "Bo\u0161njanovi\u0107"
    ],
    "name:srp_x_preferred":[
        "Bo\u0161njanovi\u0107"
    ],
    "name:srp_x_variant":[
        "\u0411\u043e\u0448\u045a\u0430\u043d\u043e\u0432\u0438\u045b"
    ],
    "name:und_x_variant":[
        "Bo\u0161njanovi\u0107i"
    ],
    "wof:name":"Bosnjanovic",
    "wof:placetype":"locality"
},
  "geometry": {"coordinates":[20.20092,44.26236],"type":"Point"}
}