{
  "type": "Feature",
  "properties": {
    "gn:admin1_code":"SE",
    "gn:admin2_code":"21",
    "gn:asciiname":"Zalica",
    "gn:country_code":"RS",
    "gn:dem":1000,
    "gn:feature_class":"P",
    "gn:feature_code":"PPL",
    "gn:name":"\u017dalica",
    "gn:population":0,
    "gn:timezone":"Europe/Belgrade",
    "iso:country":"RS",
    "name:bul_x_preferred":[
        "\u0416\u0430\u043b\u0438\u0446\u0430"
    ],
    "name:fra_x_preferred":[
        "\u017dalica"
    ],
    "name:msa_x_preferred":[
        "\u017dalica"
    ],
    "name:por_x_preferred":[
        "\u017dalica"
    ],
    "name:slv_x_preferred":[
        "\u017dalica"
    ],
    "name:srp_x_preferred":[
        "\u017dalica"
    ],
    "name:srp_x_variant":[
        "\u0416\u0430\u043b\u0438\u0446\u0430"
    ],
    "wof:name":"Zalica",
    "wof:placetype":"locality"
},
  "geometry": {"coordinates":[21.02528,43.23222],"type":"Point"}
}