{
  "type": "Feature",
  "properties": {
    "gn:admin1_code":"SE",
    "gn:admin2_code":"12",
    "gn:asciiname":"Adrovac",
    "gn:country_code":"RS",
    "gn:dem":138,
    "gn:feature_class":"P",
    "gn:feature_code":"PPL",
    "gn:name":"Adrovac",
    "gn:population":0,
    "gn:timezone":"Europe/Belgrade",
    "iso:country":"RS",
    "name:srp_x_preferred":[
        "Adrovac"
    ],
    "wof:name":"Adrovac",
    "wof:placetype":"locality"
},
  "geometry": {"coordinates":[20.96281,44.23324],"type":"Point"}
}