{
  "type": "Feature",
  "properties": {
    "gn:admin1_code":"SE",
    "gn:admin2_code":"12",
    "gn:asciiname":"Adrovac",
    "gn:country_code":"RS",
    "gn:dem":138,
    "gn:feature_class":"P",
    "gn:feature_code":"PPL",
    "gn:name":"Adrovac",
    "gn:population":0,
    "gn:timezone":"Europe/Belgrade",
    "iso:country":"RS",
    "name:ceb_x_preferred":[
        "Adrovac"
    ],
    "name:fra_x_preferred":[
        "Adrovac"
    ],
    "name:msa_x_preferred":[
        "Adrovac"
    ],
    "name:por_x_preferred":[
        "Adrovac"
    ],
    "name:slv_x_preferred":[
        "Adrovac"
    ],
    "name:srp_x_preferred":[
        "Adrovac"
    ],
    "name:srp_x_variant":[
        "\u0410\u0434\u0440\u043e\u0432\u0430\u0446"
    ],
    "wof:name":"Adrovac",
    "wof:placetype":"locality"
},
  "geometry": {"coordinates":[20.96281,44.23324],"type":"Point"}
}