{
  "type": "Feature",
  "properties": {
    "gn:admin1_code":"00",
    "gn:asciiname":"Stupovi",
    "gn:country_code":"RS",
    "gn:dem":770,
    "gn:feature_class":"P",
    "gn:feature_code":"PPL",
    "gn:name":"Stupovi",
    "gn:population":0,
    "gn:timezone":"Europe/Belgrade",
    "iso:country":"RS",
    "name:srp_x_preferred":[
        "Stupovi"
    ],
    "wof:name":"Stupovi",
    "wof:placetype":"locality"
},
  "geometry": {"coordinates":[19.39972,43.56639000000001],"type":"Point"}
}