{
  "type": "Feature",
  "properties": {
    "gn:admin1_code":"SE",
    "gn:admin2_code":"14",
    "gn:asciiname":"Rtkovo",
    "gn:country_code":"RS",
    "gn:dem":65,
    "gn:feature_class":"P",
    "gn:feature_code":"PPL",
    "gn:name":"Rtkovo",
    "gn:population":0,
    "gn:timezone":"Europe/Belgrade",
    "iso:country":"RS",
    "name:ceb_x_preferred":[
        "Rtkovo"
    ],
    "name:deu_x_preferred":[
        "Rtkovo"
    ],
    "name:fra_x_preferred":[
        "Rtkovo"
    ],
    "name:mkd_x_preferred":[
        "\u0420\u0442\u043a\u043e\u0432\u043e"
    ],
    "name:msa_x_preferred":[
        "Rtkovo"
    ],
    "name:por_x_preferred":[
        "Rtkovo"
    ],
    "name:slv_x_preferred":[
        "Rtkovo"
    ],
    "name:srp_x_preferred":[
        "Rtkovo"
    ],
    "name:srp_x_variant":[
        "\u0420\u0442\u043a\u043e\u0432\u043e"
    ],
    "name:und_x_variant":[
        "Retkovo"
    ],
    "wof:name":"Rtkovo",
    "wof:placetype":"locality"
},
  "geometry": {"coordinates":[22.74309,44.5651],"type":"Point"}
}