{
  "type": "Feature",
  "properties": {
    "gn:country":"RS",
    "gn:fcode":"PPL",
    "gn:population":8,
    "iso:country":"RS",
    "qs:name":"Drcinci",
    "qs:photos_9r":0,
    "qs:photos_sr":0,
    "qs:pop_sr":"1",
    "wof:name":"Drcinci",
    "wof:placetype":"locality",
    "wof:population":8
},
  "geometry": {"coordinates":[22.18938,42.55191],"type":"Point"}
}