{
  "type": "Feature",
  "properties": {
    "gn:admin1_code":"SE",
    "gn:admin2_code":"14",
    "gn:asciiname":"Donji Milanovac",
    "gn:country_code":"RS",
    "gn:dem":81,
    "gn:feature_class":"P",
    "gn:feature_code":"PPL",
    "gn:name":"Donji Milanovac",
    "gn:population":2410,
    "gn:timezone":"Europe/Belgrade",
    "iso:country":"RS",
    "name:ara_x_preferred":[
        "\u062f\u0648\u0646\u064a\u064a \u0645\u064a\u0644\u0627\u0646\u0648\u0641\u0627\u062a\u0633"
    ],
    "name:bul_x_preferred":[
        "\u0414\u043e\u043b\u043d\u0438 \u041c\u0438\u043b\u0430\u043d\u043e\u0432\u0430\u0446"
    ],
    "name:ceb_x_preferred":[
        "Donji Milanovac"
    ],
    "name:ces_x_preferred":[
        "Donji Milanovac"
    ],
    "name:deu_x_preferred":[
        "Donji Milanovac"
    ],
    "name:fra_x_preferred":[
        "Donji Milanovac"
    ],
    "name:hrv_x_preferred":[
        "Donji Milanovac"
    ],
    "name:mkd_x_preferred":[
        "\u0414\u043e\u045a\u0438 \u041c\u0438\u043b\u0430\u043d\u043e\u0432\u0430\u0446"
    ],
    "name:msa_x_preferred":[
        "Donji Milanovac"
    ],
    "name:nor_x_preferred":[
        "Donji Milanovac"
    ],
    "name:por_x_preferred":[
        "Donji Milanovac"
    ],
    "name:slv_x_preferred":[
        "Donji Milanovac"
    ],
    "name:srp_x_preferred":[
        "\u0414\u043e\u043d\u044c\u0438 \u041c\u0438\u043b\u043e\u0432\u0430\u0446"
    ],
    "name:srp_x_variant":[
        "Donji Milanovac",
        "\u0414\u043e\u045a\u0438 \u041c\u0438\u043b\u0430\u043d\u043e\u0432\u0430\u0446"
    ],
    "name:swe_x_preferred":[
        "Donji Milanovac"
    ],
    "name:tur_x_preferred":[
        "Donji Milanovac"
    ],
    "name:zho_x_preferred":[
        "\u4e0b\u7c73\u62c9\u8afe\u74e6\u8328"
    ],
    "wof:name":"Donji Milanovac",
    "wof:placetype":"locality",
    "wof:population":2410
},
  "geometry": {"coordinates":[22.15217,44.46417],"type":"Point"}
}