{
  "type": "Feature",
  "properties": {
    "gn:admin1_code":"VO",
    "gn:admin2_code":"5",
    "gn:asciiname":"Veprovac",
    "gn:country_code":"RS",
    "gn:dem":85,
    "gn:feature_class":"P",
    "gn:feature_code":"PPL",
    "gn:name":"Veprovac",
    "gn:population":0,
    "gn:timezone":"Europe/Belgrade",
    "iso:country":"RS",
    "name:ceb_x_preferred":[
        "Veprovac"
    ],
    "name:deu_x_preferred":[
        "Kru\u0161\u010di\u0107"
    ],
    "name:epo_x_preferred":[
        "Kru\u015d\u0109icj"
    ],
    "name:fra_x_preferred":[
        "Kru\u0161\u010di\u0107"
    ],
    "name:hrv_x_preferred":[
        "Kru\u0161\u010di\u0107"
    ],
    "name:hun_x_preferred":[
        "Vepr\u0151d"
    ],
    "name:mkd_x_preferred":[
        "\u041a\u0440\u0443\u0448\u0447\u0438\u045c"
    ],
    "name:msa_x_preferred":[
        "Kru\u0161\u010di\u0107"
    ],
    "name:ron_x_preferred":[
        "Kru\u0161\u010di\u0107"
    ],
    "name:slv_x_preferred":[
        "Kru\u0161\u010di\u0107"
    ],
    "name:srp_x_preferred":[
        "Kru\u0161\u010di\u0107"
    ],
    "name:srp_x_variant":[
        "\u041a\u0440\u0443\u0448\u0447\u0438\u045b"
    ],
    "name:ukr_x_preferred":[
        "\u041a\u0440\u0443\u0448\u0447\u0438\u0447"
    ],
    "name:und_x_variant":[
        "Weprowatz",
        "Ebersdorf",
        "Veprovac",
        "Lipar",
        "Vepr\u0151d"
    ],
    "wof:name":"Veprovac",
    "wof:placetype":"locality"
},
  "geometry": {"coordinates":[19.36922,45.61386],"type":"Point"}
}