{
  "type": "Feature",
  "properties": {
    "gn:admin1_code":"VO",
    "gn:admin2_code":"6",
    "gn:asciiname":"Backo Novo Selo",
    "gn:country_code":"RS",
    "gn:dem":82,
    "gn:feature_class":"P",
    "gn:feature_code":"PPL",
    "gn:name":"Ba\u010dko Novo Selo",
    "gn:population":0,
    "gn:timezone":"Europe/Belgrade",
    "iso:country":"RS",
    "name:srp_x_preferred":[
        "Ba\u010dko Novo Selo"
    ],
    "name:und_x_variant":[
        "Neudorf an der Donau",
        "Ba\u010dko Novo Salo",
        "B\u00e1cs-Novoszelo",
        "Batsch-Neudorf",
        "B\u00e1cs\u00fajlak"
    ],
    "wof:name":"Backo Novo Selo",
    "wof:placetype":"locality"
},
  "geometry": {"coordinates":[19.14109,45.29337],"type":"Point"}
}