{
  "type": "Feature",
  "properties": {
    "gn:admin1_code":"VO",
    "gn:admin2_code":"6",
    "gn:asciiname":"Backo Novo Selo",
    "gn:country_code":"RS",
    "gn:dem":82,
    "gn:feature_class":"P",
    "gn:feature_code":"PPL",
    "gn:name":"Ba\u010dko Novo Selo",
    "gn:population":0,
    "gn:timezone":"Europe/Belgrade",
    "iso:country":"RS",
    "name:ceb_x_preferred":[
        "Ba\u010dko Novo Selo"
    ],
    "name:deu_x_preferred":[
        "Ba\u010dko Novo Selo"
    ],
    "name:epo_x_preferred":[
        "Ba\u0109ko Novo Selo"
    ],
    "name:fra_x_preferred":[
        "Ba\u010dko Novo Selo"
    ],
    "name:hrv_x_preferred":[
        "Novo Selo"
    ],
    "name:hun_x_preferred":[
        "B\u00e1cs\u00fajlak"
    ],
    "name:ita_x_preferred":[
        "Ba\u010dko Novo Selo"
    ],
    "name:msa_x_preferred":[
        "Ba\u010dko Novo Selo"
    ],
    "name:rus_x_preferred":[
        "\u0411\u0430\u0447\u043a\u043e-\u041d\u043e\u0432\u043e-\u0421\u0435\u043b\u043e"
    ],
    "name:slv_x_preferred":[
        "Ba\u010dko Novo Selo"
    ],
    "name:srp_x_preferred":[
        "Ba\u010dko Novo Selo"
    ],
    "name:srp_x_variant":[
        "\u0411\u0430\u0447\u043a\u043e \u041d\u043e\u0432\u043e \u0421\u0435\u043b\u043e"
    ],
    "name:ukr_x_preferred":[
        "\u0411\u0430\u0447\u043a\u043e-\u041d\u043e\u0432\u043e-\u0421\u0435\u043b\u043e"
    ],
    "name:und_x_variant":[
        "Neudorf an der Donau",
        "Ba\u010dko Novo Salo",
        "B\u00e1cs-Novoszelo",
        "Batsch-Neudorf"
    ],
    "wof:name":"Backo Novo Selo",
    "wof:placetype":"locality"
},
  "geometry": {"coordinates":[19.14109,45.29337],"type":"Point"}
}