{
  "type": "Feature",
  "properties": {
    "iso:country":"RS",
    "name:eng_x_preferred":[
        "Labudovo Brdo"
    ],
    "name:srp_cyr_x_preferred":[
        "\u041b\u0430\u0431\u0443\u0434\u043e\u0432\u043e \u0431\u0440\u0434\u043e"
    ],
    "name:srp_x_preferred":[
        "\u041b\u0430\u0431\u0443\u0434\u043e\u0432\u043e \u0431\u0440\u0434\u043e"
    ],
    "wof:name":"Labudovo Brdo",
    "wof:placetype":"neighbourhood"
},
  "geometry": {"coordinates":[20.42450334735761,44.72800827109835],"type":"Point"}
}