{
  "type": "Feature",
  "properties": {
    "gn:country":"RS",
    "gn:fcode":"PPL",
    "gn:population":680,
    "iso:country":"RS",
    "qs:name":"Lagja e Korbajve",
    "qs:photos_9r":0,
    "qs:photos_sr":0,
    "qs:pop_sr":"2",
    "wof:name":"Lagja e Korbajve",
    "wof:placetype":"locality",
    "wof:population":680
},
  "geometry": {"coordinates":[21.7434,42.38674],"type":"Point"}
}