{
  "type": "Feature",
  "properties": {
    "gn:admin1_code":"SE",
    "gn:admin2_code":"18",
    "gn:asciiname":"Gornje Sebecevo",
    "gn:country_code":"RS",
    "gn:dem":791,
    "gn:feature_class":"P",
    "gn:feature_code":"PPLL",
    "gn:name":"Gornje Sebe\u010devo",
    "gn:population":0,
    "gn:timezone":"Europe/Belgrade",
    "iso:country":"RS",
    "name:srp_x_preferred":[
        "Gornje Sebe\u010devo"
    ],
    "wof:name":"Gornje Sebecevo",
    "wof:placetype":"locality"
},
  "geometry": {"coordinates":[20.4075,43.08083],"type":"Point"}
}