{
  "type": "Feature",
  "properties": {
    "gn:admin1_code":"SE",
    "gn:admin2_code":"17",
    "gn:asciiname":"Ljubicici",
    "gn:country_code":"RS",
    "gn:dem":584,
    "gn:feature_class":"P",
    "gn:feature_code":"PPL",
    "gn:name":"Ljubi\u010di\u0107i",
    "gn:population":0,
    "gn:timezone":"Europe/Belgrade",
    "iso:country":"RS",
    "name:srp_x_preferred":[
        "Ljubi\u010di\u0107i"
    ],
    "wof:name":"Ljubicici",
    "wof:placetype":"locality"
},
  "geometry": {"coordinates":[20.20194,43.92556],"type":"Point"}
}