{
  "type": "Feature",
  "properties": {
    "gn:admin1_code":"SE",
    "gn:admin2_code":"16",
    "gn:asciiname":"Klupci",
    "gn:country_code":"RS",
    "gn:dem":968,
    "gn:feature_class":"P",
    "gn:feature_code":"PPL",
    "gn:name":"Klupci",
    "gn:population":0,
    "gn:timezone":"Europe/Belgrade",
    "iso:country":"RS",
    "name:ceb_x_preferred":[
        "Klupci"
    ],
    "name:fas_x_preferred":[
        "\u06a9\u0644\u0648\u067e\u062a\u0633\u06cc"
    ],
    "name:fra_x_preferred":[
        "Klupci"
    ],
    "name:msa_x_preferred":[
        "Klupci"
    ],
    "name:nld_x_preferred":[
        "Klupci"
    ],
    "name:pol_x_preferred":[
        "Klupci"
    ],
    "name:por_x_preferred":[
        "Klupci"
    ],
    "name:slv_x_preferred":[
        "Klupci"
    ],
    "name:srp_x_preferred":[
        "Klupci"
    ],
    "name:srp_x_variant":[
        "\u041a\u043b\u0443\u043f\u0446\u0438"
    ],
    "wof:name":"Klupci",
    "wof:placetype":"locality"
},
  "geometry": {"coordinates":[19.40526,43.44543],"type":"Point"}
}