{
  "type": "Feature",
  "properties": {
    "gn:admin1_code":"SE",
    "gn:admin2_code":"16",
    "gn:asciiname":"Klupci",
    "gn:country_code":"RS",
    "gn:dem":968,
    "gn:feature_class":"P",
    "gn:feature_code":"PPL",
    "gn:name":"Klupci",
    "gn:population":0,
    "gn:timezone":"Europe/Belgrade",
    "iso:country":"RS",
    "name:srp_x_preferred":[
        "Klupci"
    ],
    "wof:name":"Klupci",
    "wof:placetype":"locality"
},
  "geometry": {"coordinates":[19.40526,43.44543],"type":"Point"}
}