{
  "type": "Feature",
  "properties": {
    "gn:admin1_code":"SE",
    "gn:admin2_code":"20",
    "gn:asciiname":"Srezovac",
    "gn:country_code":"RS",
    "gn:dem":164,
    "gn:feature_class":"P",
    "gn:feature_code":"PPL",
    "gn:name":"Srezovac",
    "gn:population":0,
    "gn:timezone":"Europe/Belgrade",
    "iso:country":"RS",
    "name:ceb_x_preferred":[
        "Srezovac"
    ],
    "name:fra_x_preferred":[
        "Srezovac"
    ],
    "name:msa_x_preferred":[
        "Srezovac"
    ],
    "name:por_x_preferred":[
        "Srezovac"
    ],
    "name:slv_x_preferred":[
        "Srezovac"
    ],
    "name:srp_x_preferred":[
        "Srezovac"
    ],
    "name:srp_x_variant":[
        "\u0421\u0440\u0435\u0437\u043e\u0432\u0430\u0446"
    ],
    "wof:name":"Srezovac",
    "wof:placetype":"locality"
},
  "geometry": {"coordinates":[21.58472,43.57333],"type":"Point"}
}