{
  "type": "Feature",
  "properties": {
    "gn:admin1_code":"SE",
    "gn:admin2_code":"8",
    "gn:asciiname":"Vasarici",
    "gn:country_code":"RS",
    "gn:dem":476,
    "gn:feature_class":"P",
    "gn:feature_code":"PPL",
    "gn:name":"Vasari\u0107i",
    "gn:population":0,
    "gn:timezone":"Europe/Belgrade",
    "iso:country":"RS",
    "name:srp_x_preferred":[
        "Vasari\u0107i"
    ],
    "wof:name":"Vasarici",
    "wof:placetype":"locality"
},
  "geometry": {"coordinates":[19.36306,44.26111],"type":"Point"}
}