{
  "type": "Feature",
  "properties": {
    "gn:admin1_code":"SE",
    "gn:admin2_code":"23",
    "gn:asciiname":"Donja Jajina",
    "gn:country_code":"RS",
    "gn:dem":246,
    "gn:feature_class":"P",
    "gn:feature_code":"PPL",
    "gn:name":"Donja Jajina",
    "gn:population":0,
    "gn:timezone":"Europe/Belgrade",
    "iso:country":"RS",
    "name:srp_x_preferred":[
        "Donja Jajina"
    ],
    "wof:name":"Donja Jajina",
    "wof:placetype":"locality"
},
  "geometry": {"coordinates":[21.94193,42.97037],"type":"Point"}
}