{
  "type": "Feature",
  "properties": {
    "gn:admin1_code":"SE",
    "gn:admin2_code":"23",
    "gn:asciiname":"Donja Jajina",
    "gn:country_code":"RS",
    "gn:dem":246,
    "gn:feature_class":"P",
    "gn:feature_code":"PPL",
    "gn:name":"Donja Jajina",
    "gn:population":0,
    "gn:timezone":"Europe/Belgrade",
    "iso:country":"RS",
    "name:ceb_x_preferred":[
        "Donja Jajina"
    ],
    "name:fra_x_preferred":[
        "Donja Jajina"
    ],
    "name:msa_x_preferred":[
        "Donja Jajina"
    ],
    "name:por_x_preferred":[
        "Donja Jajina"
    ],
    "name:slv_x_preferred":[
        "Donja Jajina"
    ],
    "name:srp_x_preferred":[
        "Donja Jajina"
    ],
    "name:srp_x_variant":[
        "\u0414\u043e\u045a\u0430 \u0408\u0430\u0458\u0438\u043d\u0430"
    ],
    "wof:name":"Donja Jajina",
    "wof:placetype":"locality"
},
  "geometry": {"coordinates":[21.94193,42.97037],"type":"Point"}
}