{
  "type": "Feature",
  "properties": {
    "gn:admin1_code":"SE",
    "gn:admin2_code":"16",
    "gn:asciiname":"Divcevici",
    "gn:country_code":"RS",
    "gn:dem":508,
    "gn:feature_class":"P",
    "gn:feature_code":"PPL",
    "gn:name":"Div\u010devi\u0107i",
    "gn:population":0,
    "gn:timezone":"Europe/Belgrade",
    "iso:country":"RS",
    "name:srp_x_preferred":[
        "Div\u010devi\u0107i"
    ],
    "wof:name":"Divcevici",
    "wof:placetype":"locality"
},
  "geometry": {"coordinates":[19.9275,43.99361],"type":"Point"}
}