{
  "type": "Feature",
  "properties": {
    "gn:admin1_code":"SE",
    "gn:admin2_code":"0",
    "gn:asciiname":"Bozdarevac",
    "gn:country_code":"RS",
    "gn:dem":173,
    "gn:feature_class":"P",
    "gn:feature_code":"PPLL",
    "gn:name":"Bo\u017edarevac",
    "gn:population":0,
    "gn:timezone":"Europe/Belgrade",
    "iso:country":"RS",
    "wof:name":"Bozdarevac",
    "wof:placetype":"locality"
},
  "geometry": {"coordinates":[20.38099,44.55966],"type":"Point"}
}