{
  "type": "Feature",
  "properties": {
    "gn:admin1_code":"SE",
    "gn:admin2_code":"23",
    "gn:asciiname":"Varadin",
    "gn:country_code":"RS",
    "gn:dem":763,
    "gn:feature_class":"P",
    "gn:feature_code":"PPLL",
    "gn:name":"Varadin",
    "gn:population":0,
    "gn:timezone":"Europe/Belgrade",
    "iso:country":"RS",
    "name:fra_x_preferred":[
        "Varadin"
    ],
    "name:hun_x_preferred":[
        "Varadin"
    ],
    "name:msa_x_preferred":[
        "Varadin"
    ],
    "name:por_x_preferred":[
        "Varadin"
    ],
    "name:slv_x_preferred":[
        "Varadin"
    ],
    "name:sqi_x_preferred":[
        "Vardeniku"
    ],
    "name:srp_x_preferred":[
        "Varadin"
    ],
    "name:srp_x_variant":[
        "\u0412\u0430\u0440\u0430\u0434\u0438\u043d"
    ],
    "wof:name":"Varadin",
    "wof:placetype":"locality"
},
  "geometry": {"coordinates":[21.49679,42.84176],"type":"Point"}
}