{
  "type": "Feature",
  "properties": {
    "gn:admin1_code":"SE",
    "gn:admin2_code":"24",
    "gn:asciiname":"Sveti Ilija",
    "gn:country_code":"RS",
    "gn:dem":881,
    "gn:feature_class":"P",
    "gn:feature_code":"PPL",
    "gn:name":"Sveti Ilija",
    "gn:population":0,
    "gn:timezone":"Europe/Belgrade",
    "iso:country":"RS",
    "name:bos_x_preferred":[
        "Sveti Ilija"
    ],
    "name:deu_x_preferred":[
        "Sveti Ilija"
    ],
    "name:fra_x_preferred":[
        "Sveti Ilija"
    ],
    "name:hrv_x_preferred":[
        "Sveti Ilija"
    ],
    "name:hun_x_preferred":[
        "Sveti Ilija"
    ],
    "name:ita_x_preferred":[
        "Sveti Ilija"
    ],
    "name:nld_x_preferred":[
        "Sveti Ilija"
    ],
    "name:pol_x_preferred":[
        "Gmina Sveti Ilija"
    ],
    "name:ron_x_preferred":[
        "Comuna Sveti Ilija"
    ],
    "name:rus_x_preferred":[
        "\u0421\u0432\u0435\u0442\u0438-\u0418\u043b\u0438\u044f"
    ],
    "name:slv_x_preferred":[
        "Sveti Ilija"
    ],
    "name:spa_x_preferred":[
        "Sveti Ilija"
    ],
    "name:srp_x_preferred":[
        "\u0421\u0432\u0435\u0442\u0438 \u0418\u043b\u0438\u0458\u0430"
    ],
    "name:ukr_x_preferred":[
        "\u0421\u0432\u0435\u0442\u0438\u0439 \u0406\u043b\u0456\u044f"
    ],
    "name:war_x_preferred":[
        "Sveti Ilija"
    ],
    "wof:name":"Sveti Ilija",
    "wof:placetype":"locality"
},
  "geometry": {"coordinates":[22.4925,42.44056],"type":"Point"}
}