{
  "type": "Feature",
  "properties": {
    "gn:admin1_code":"SE",
    "gn:admin2_code":"24",
    "gn:asciiname":"Sveti Ilija",
    "gn:country_code":"RS",
    "gn:dem":881,
    "gn:feature_class":"P",
    "gn:feature_code":"PPL",
    "gn:name":"Sveti Ilija",
    "gn:population":0,
    "gn:timezone":"Europe/Belgrade",
    "iso:country":"RS",
    "wof:name":"Sveti Ilija",
    "wof:placetype":"locality"
},
  "geometry": {"coordinates":[22.4925,42.44056],"type":"Point"}
}