{
  "type": "Feature",
  "properties": {
    "gn:admin1_code":"SE",
    "gn:admin2_code":"0",
    "gn:asciiname":"Lestane",
    "gn:country_code":"RS",
    "gn:dem":95,
    "gn:feature_class":"P",
    "gn:feature_code":"PPL",
    "gn:name":"Le\u0161tane",
    "gn:population":0,
    "gn:timezone":"Europe/Belgrade",
    "iso:country":"RS",
    "name:srp_x_preferred":[
        "Le\u0161tane"
    ],
    "wof:name":"Lestane",
    "wof:placetype":"locality"
},
  "geometry": {"coordinates":[20.57571,44.73123],"type":"Point"}
}