{
  "type": "Feature",
  "properties": {
    "gn:admin1_code":"SE",
    "gn:admin2_code":"18",
    "gn:asciiname":"Sase",
    "gn:country_code":"RS",
    "gn:dem":1121,
    "gn:feature_class":"P",
    "gn:feature_code":"PPL",
    "gn:name":"Sase",
    "gn:population":0,
    "gn:timezone":"Europe/Belgrade",
    "iso:country":"RS",
    "name:srp_x_preferred":[
        "Sase"
    ],
    "wof:name":"Sase",
    "wof:placetype":"locality"
},
  "geometry": {"coordinates":[20.4575,43.33611],"type":"Point"}
}