{
  "type": "Feature",
  "properties": {
    "gn:admin1_code":"SE",
    "gn:admin2_code":"18",
    "gn:asciiname":"Gornje Zarce",
    "gn:country_code":"RS",
    "gn:dem":383,
    "gn:feature_class":"P",
    "gn:feature_code":"PPL",
    "gn:name":"Gornje \u017dar\u010de",
    "gn:population":0,
    "gn:timezone":"Europe/Belgrade",
    "iso:country":"RS",
    "name:srp_x_preferred":[
        "Gornje \u017dar\u010de"
    ],
    "wof:name":"Gornje Zarce",
    "wof:placetype":"locality"
},
  "geometry": {"coordinates":[20.64241,43.46295],"type":"Point"}
}