{
  "type": "Feature",
  "properties": {
    "gn:admin1_code":"SE",
    "gn:admin2_code":"16",
    "gn:asciiname":"Vrsjenice",
    "gn:country_code":"RS",
    "gn:dem":1089,
    "gn:feature_class":"P",
    "gn:feature_code":"PPL",
    "gn:name":"Vrsjenice",
    "gn:population":0,
    "gn:timezone":"Europe/Belgrade",
    "iso:country":"RS",
    "name:ceb_x_preferred":[
        "Vrsjenice"
    ],
    "name:fra_x_preferred":[
        "Vrsjenice"
    ],
    "name:msa_x_preferred":[
        "Vrsjenice"
    ],
    "name:nld_x_preferred":[
        "Vrsjenice"
    ],
    "name:por_x_preferred":[
        "Vrsjenice"
    ],
    "name:slv_x_preferred":[
        "Vrsjenice"
    ],
    "name:srp_x_preferred":[
        "Vrsjenice"
    ],
    "name:srp_x_variant":[
        "\u0412\u0440\u0441\u0458\u0435\u043d\u0438\u0446\u0435"
    ],
    "name:und_x_variant":[
        "Vrsenice"
    ],
    "wof:name":"Vrsjenice",
    "wof:placetype":"locality"
},
  "geometry": {"coordinates":[20.07346,43.21654],"type":"Point"}
}