{
  "type": "Feature",
  "properties": {
    "gn:admin1_code":"SE",
    "gn:admin2_code":"9",
    "gn:asciiname":"Balinovic",
    "gn:country_code":"RS",
    "gn:dem":442,
    "gn:feature_class":"P",
    "gn:feature_code":"PPLL",
    "gn:name":"Balinovi\u0107",
    "gn:population":0,
    "gn:timezone":"Europe/Belgrade",
    "iso:country":"RS",
    "name:srp_x_preferred":[
        "Balinovi\u0107"
    ],
    "wof:name":"Balinovic",
    "wof:placetype":"locality"
},
  "geometry": {"coordinates":[19.75812,44.26008],"type":"Point"}
}