{
  "type": "Feature",
  "properties": {
    "gn:admin1_code":"SE",
    "gn:admin2_code":"24",
    "gn:asciiname":"Bozinjevac",
    "gn:country_code":"RS",
    "gn:dem":432,
    "gn:feature_class":"P",
    "gn:feature_code":"PPL",
    "gn:name":"Bo\u017einjevac",
    "gn:population":0,
    "gn:timezone":"Europe/Belgrade",
    "iso:country":"RS",
    "name:bul_x_preferred":[
        "\u0411\u043e\u0436\u0438\u043d\u0435\u0432\u0430\u0446"
    ],
    "name:ceb_x_preferred":[
        "Bo\u017einjevac"
    ],
    "name:fra_x_preferred":[
        "Bo\u017einjevac"
    ],
    "name:hun_x_preferred":[
        "Bo\u017einjevac"
    ],
    "name:msa_x_preferred":[
        "Bo\u017einjevac"
    ],
    "name:por_x_preferred":[
        "Bo\u017einjevac"
    ],
    "name:slv_x_preferred":[
        "Bo\u017einjevac"
    ],
    "name:sqi_x_preferred":[
        "Bozhinjeci"
    ],
    "name:srp_x_preferred":[
        "Bo\u017einjevac"
    ],
    "name:srp_x_variant":[
        "\u0411\u043e\u0436\u0438\u045a\u0435\u0432\u0430\u0446"
    ],
    "name:und_x_variant":[
        "Bo\u017eenjevac"
    ],
    "wof:name":"Bozinjevac",
    "wof:placetype":"locality"
},
  "geometry": {"coordinates":[21.75979,42.43259000000001],"type":"Point"}
}