{
  "type": "Feature",
  "properties": {
    "gn:admin1_code":"SE",
    "gn:admin2_code":"24",
    "gn:asciiname":"Bozinjevac",
    "gn:country_code":"RS",
    "gn:dem":432,
    "gn:feature_class":"P",
    "gn:feature_code":"PPL",
    "gn:name":"Bo\u017einjevac",
    "gn:population":0,
    "gn:timezone":"Europe/Belgrade",
    "iso:country":"RS",
    "name:srp_x_preferred":[
        "Bo\u017einjevac"
    ],
    "name:und_x_variant":[
        "Bo\u017eenjevac"
    ],
    "wof:name":"Bozinjevac",
    "wof:placetype":"locality"
},
  "geometry": {"coordinates":[21.75979,42.43259000000001],"type":"Point"}
}