{
  "type": "Feature",
  "properties": {
    "gn:admin1_code":"SE",
    "gn:admin2_code":"8",
    "gn:asciiname":"Slatina",
    "gn:country_code":"RS",
    "gn:dem":146,
    "gn:feature_class":"P",
    "gn:feature_code":"PPLL",
    "gn:name":"Slatina",
    "gn:population":0,
    "gn:timezone":"Europe/Belgrade",
    "iso:country":"RS",
    "name:fra_x_preferred":[
        "Slatina"
    ],
    "name:msa_x_preferred":[
        "Slatina"
    ],
    "name:por_x_preferred":[
        "Slatina"
    ],
    "name:slv_x_preferred":[
        "Slatina"
    ],
    "name:srp_x_preferred":[
        "Slatina"
    ],
    "name:srp_x_variant":[
        "\u0421\u043b\u0430\u0442\u0438\u043d\u0430"
    ],
    "wof:name":"Slatina",
    "wof:placetype":"locality"
},
  "geometry": {"coordinates":[19.64811,44.65064],"type":"Point"}
}