{
  "type": "Feature",
  "properties": {
    "gn:admin1_code":"SE",
    "gn:admin2_code":"24",
    "gn:asciiname":"Softarci",
    "gn:country_code":"RS",
    "gn:dem":1291,
    "gn:feature_class":"P",
    "gn:feature_code":"PPL",
    "gn:name":"Softarci",
    "gn:population":0,
    "gn:timezone":"Europe/Belgrade",
    "iso:country":"RS",
    "wof:name":"Softarci",
    "wof:placetype":"locality"
},
  "geometry": {"coordinates":[22.34849,42.34669],"type":"Point"}
}