{
  "type": "Feature",
  "properties": {
    "gn:country":"RS",
    "gn:fcode":"PPL",
    "gn:pop":1950,
    "iso:country":"RS",
    "name:ceb_x_preferred":[
        "Jelen\u010da"
    ],
    "name:eng_x_preferred":[
        "Jelen\u010da"
    ],
    "name:fra_x_preferred":[
        "Jelen\u010da"
    ],
    "name:msa_x_preferred":[
        "Jelen\u010da"
    ],
    "name:nld_x_preferred":[
        "Jelen\u010da"
    ],
    "name:por_x_preferred":[
        "Jelen\u010da"
    ],
    "name:slv_x_preferred":[
        "Jelen\u010da"
    ],
    "name:srp_x_preferred":[
        "Jelen\u010da"
    ],
    "name:srp_x_variant":[
        "\u0408\u0435\u043b\u0435\u043d\u0447\u0430"
    ],
    "qs:name":"Jelen\u010da",
    "qs:photos_9r":0,
    "qs:photos_sr":0,
    "qs:pop_sr":"3",
    "wd:wordcount":60,
    "wof:name":"Jelen\u010da",
    "wof:placetype":"locality",
    "wof:population":1950
},
  "geometry": {"coordinates":[19.74738,44.72113],"type":"Point"}
}