{
  "type": "Feature",
  "properties": {
    "gn:admin1_code":"SE",
    "gn:admin2_code":"20",
    "gn:asciiname":"Pluzina",
    "gn:country_code":"RS",
    "gn:dem":505,
    "gn:feature_class":"P",
    "gn:feature_code":"PPL",
    "gn:name":"Plu\u017eina",
    "gn:population":0,
    "gn:timezone":"Europe/Belgrade",
    "iso:country":"RS",
    "name:srp_x_preferred":[
        "Plu\u017eina"
    ],
    "wof:name":"Pluzina",
    "wof:placetype":"locality"
},
  "geometry": {"coordinates":[22.07221,43.45593],"type":"Point"}
}