{
  "type": "Feature",
  "properties": {
    "gn:admin1_code":"SE",
    "gn:admin2_code":"24",
    "gn:asciiname":"Karadnik",
    "gn:country_code":"RS",
    "gn:dem":440,
    "gn:feature_class":"P",
    "gn:feature_code":"PPL",
    "gn:name":"Karadnik",
    "gn:population":0,
    "gn:timezone":"Europe/Belgrade",
    "iso:country":"RS",
    "name:srp_x_preferred":[
        "Karadnik"
    ],
    "wof:name":"Karadnik",
    "wof:placetype":"locality"
},
  "geometry": {"coordinates":[21.81452,42.48605],"type":"Point"}
}