{
  "type": "Feature",
  "properties": {
    "gn:admin1_code":"SE",
    "gn:admin2_code":"24",
    "gn:asciiname":"Reka",
    "gn:country_code":"RS",
    "gn:dem":763,
    "gn:feature_class":"P",
    "gn:feature_code":"PPL",
    "gn:name":"Reka",
    "gn:population":0,
    "gn:timezone":"Europe/Belgrade",
    "iso:country":"RS",
    "name:und_x_variant":[
        "Rjeka Mahala",
        "Reka"
    ],
    "wof:name":"Reka",
    "wof:placetype":"locality"
},
  "geometry": {"coordinates":[22.486,42.41542000000001],"type":"Point"}
}