{
  "type": "Feature",
  "properties": {
    "gn:admin1_code":"SE",
    "gn:admin2_code":"24",
    "gn:asciiname":"Reka",
    "gn:country_code":"RS",
    "gn:dem":763,
    "gn:feature_class":"P",
    "gn:feature_code":"PPL",
    "gn:name":"Reka",
    "gn:population":0,
    "gn:timezone":"Europe/Belgrade",
    "iso:country":"RS",
    "name:ceb_x_preferred":[
        "Reka"
    ],
    "name:ces_x_preferred":[
        "\u0158eka"
    ],
    "name:deu_x_preferred":[
        "Reka"
    ],
    "name:fra_x_preferred":[
        "Reka"
    ],
    "name:hrv_x_preferred":[
        "Reka"
    ],
    "name:hun_x_preferred":[
        "Reka"
    ],
    "name:nld_x_preferred":[
        "Reka"
    ],
    "name:por_x_preferred":[
        "Reka"
    ],
    "name:slv_x_preferred":[
        "Reka"
    ],
    "name:srp_x_preferred":[
        "\u0420\u0435\u043a\u0430"
    ],
    "name:swe_x_preferred":[
        "Reka"
    ],
    "name:und_x_variant":[
        "Rjeka Mahala"
    ],
    "wof:name":"Reka",
    "wof:placetype":"locality"
},
  "geometry": {"coordinates":[22.486,42.41542000000001],"type":"Point"}
}