{
  "type": "Feature",
  "properties": {
    "gn:admin1_code":"SE",
    "gn:admin2_code":"9",
    "gn:asciiname":"Zivanovici",
    "gn:country_code":"RS",
    "gn:dem":409,
    "gn:feature_class":"P",
    "gn:feature_code":"PPL",
    "gn:name":"\u017divanovi\u0107i",
    "gn:population":0,
    "gn:timezone":"Europe/Belgrade",
    "iso:country":"RS",
    "name:und_x_variant":[
        "Gornji Kraj",
        "\u017divanovi\u0107i"
    ],
    "wof:name":"Zivanovici",
    "wof:placetype":"locality"
},
  "geometry": {"coordinates":[19.72972,44.37583],"type":"Point"}
}