{
  "type": "Feature",
  "properties": {
    "gn:admin1_code":"SE",
    "gn:admin2_code":"12",
    "gn:asciiname":"Zirovnica",
    "gn:country_code":"RS",
    "gn:dem":154,
    "gn:feature_class":"P",
    "gn:feature_code":"PPL",
    "gn:name":"\u017dirovnica",
    "gn:population":0,
    "gn:timezone":"Europe/Belgrade",
    "iso:country":"RS",
    "name:srp_x_preferred":[
        "\u017dirovnica"
    ],
    "wof:name":"Zirovnica",
    "wof:placetype":"locality"
},
  "geometry": {"coordinates":[21.02611,44.11785],"type":"Point"}
}