{
  "type": "Feature",
  "properties": {
    "gn:admin1_code":"SE",
    "gn:admin2_code":"24",
    "gn:asciiname":"Zlatanovci",
    "gn:country_code":"RS",
    "gn:dem":1291,
    "gn:feature_class":"P",
    "gn:feature_code":"PPL",
    "gn:name":"Zlatanovci",
    "gn:population":0,
    "gn:timezone":"Europe/Belgrade",
    "iso:country":"RS",
    "name:srp_x_preferred":[
        "Zlatanovci"
    ],
    "wof:name":"Zlatanovci",
    "wof:placetype":"locality"
},
  "geometry": {"coordinates":[22.33715,42.34361],"type":"Point"}
}