{
  "type": "Feature",
  "properties": {
    "gn:admin1_code":"SE",
    "gn:admin2_code":"24",
    "gn:asciiname":"Klisura",
    "gn:country_code":"RS",
    "gn:dem":906,
    "gn:feature_class":"P",
    "gn:feature_code":"PPL",
    "gn:name":"Klisura",
    "gn:population":0,
    "gn:timezone":"Europe/Belgrade",
    "iso:country":"RS",
    "name:bos_x_preferred":[
        "Klisura"
    ],
    "name:bul_x_preferred":[
        "\u041a\u043b\u0438\u0441\u0443\u0440\u0430"
    ],
    "name:ceb_x_preferred":[
        "Klisura"
    ],
    "name:fra_x_preferred":[
        "Klisura"
    ],
    "name:hrv_x_preferred":[
        "Klisura"
    ],
    "name:mkd_x_preferred":[
        "\u041a\u043b\u0438\u0441\u0443\u0440\u0430"
    ],
    "name:por_x_preferred":[
        "Klisura"
    ],
    "name:ron_x_preferred":[
        "Klisura"
    ],
    "name:rus_x_preferred":[
        "\u041a\u043b\u0438\u0441\u0443\u0440\u0430"
    ],
    "name:slv_x_preferred":[
        "Klisura"
    ],
    "name:srp_x_preferred":[
        "Klisura"
    ],
    "name:srp_x_variant":[
        "\u041a\u043b\u0438\u0441\u0443\u0440\u0430"
    ],
    "name:swe_x_preferred":[
        "Klisura"
    ],
    "name:ukr_x_preferred":[
        "\u041a\u043b\u0456\u0441\u0443\u0440\u0430"
    ],
    "wof:name":"Klisura",
    "wof:placetype":"locality"
},
  "geometry": {"coordinates":[22.40771,42.75753],"type":"Point"}
}