{
  "type": "Feature",
  "properties": {
    "gn:admin1_code":"SE",
    "gn:admin2_code":"21",
    "gn:asciiname":"Stava",
    "gn:country_code":"RS",
    "gn:dem":856,
    "gn:feature_class":"P",
    "gn:feature_code":"PPLL",
    "gn:name":"\u0160tava",
    "gn:population":0,
    "gn:timezone":"Europe/Belgrade",
    "iso:country":"RS",
    "name:bul_x_preferred":[
        "\u0429\u0430\u0432\u0430"
    ],
    "name:ceb_x_preferred":[
        "\u0160tava"
    ],
    "name:fra_x_preferred":[
        "\u0160tava"
    ],
    "name:msa_x_preferred":[
        "\u0160tava"
    ],
    "name:por_x_preferred":[
        "\u0160tava"
    ],
    "name:slv_x_preferred":[
        "\u0160tava"
    ],
    "name:srp_x_preferred":[
        "\u0160tava"
    ],
    "name:srp_x_variant":[
        "\u0428\u0442\u0430\u0432\u0430"
    ],
    "wof:name":"Stava",
    "wof:placetype":"locality"
},
  "geometry": {"coordinates":[20.97243,43.17034],"type":"Point"}
}