{
  "type": "Feature",
  "properties": {
    "gn:admin1_code":"SE",
    "gn:admin2_code":"18",
    "gn:asciiname":"Zezena",
    "gn:country_code":"RS",
    "gn:dem":648,
    "gn:feature_class":"P",
    "gn:feature_code":"PPL",
    "gn:name":"\u017de\u017eena",
    "gn:population":0,
    "gn:timezone":"Europe/Belgrade",
    "iso:country":"RS",
    "name:srp_x_preferred":[
        "\u017de\u017eena"
    ],
    "wof:name":"Zezena",
    "wof:placetype":"locality"
},
  "geometry": {"coordinates":[20.67241,43.42717],"type":"Point"}
}