{
  "type": "Feature",
  "properties": {
    "gn:admin1_code":"SE",
    "gn:admin2_code":"12",
    "gn:asciiname":"Vuckovica",
    "gn:country_code":"RS",
    "gn:dem":333,
    "gn:feature_class":"P",
    "gn:feature_code":"PPLL",
    "gn:name":"Vu\u010dkovica",
    "gn:population":0,
    "gn:timezone":"Europe/Belgrade",
    "iso:country":"RS",
    "wof:name":"Vuckovica",
    "wof:placetype":"locality"
},
  "geometry": {"coordinates":[20.79064,43.94402],"type":"Point"}
}