{
  "type": "Feature",
  "properties": {
    "gn:admin1_code":"SE",
    "gn:admin2_code":"19",
    "gn:asciiname":"Bela Voda",
    "gn:country_code":"RS",
    "gn:dem":173,
    "gn:feature_class":"P",
    "gn:feature_code":"PPL",
    "gn:name":"Bela Voda",
    "gn:population":0,
    "gn:timezone":"Europe/Belgrade",
    "iso:country":"RS",
    "name:srp_x_preferred":[
        "Bela Voda"
    ],
    "wof:name":"Bela Voda",
    "wof:placetype":"locality"
},
  "geometry": {"coordinates":[21.19932,43.61722],"type":"Point"}
}