{
  "type": "Feature",
  "properties": {
    "gn:admin1_code":"SE",
    "gn:admin2_code":"19",
    "gn:asciiname":"Bela Voda",
    "gn:country_code":"RS",
    "gn:dem":173,
    "gn:feature_class":"P",
    "gn:feature_code":"PPL",
    "gn:name":"Bela Voda",
    "gn:population":0,
    "gn:timezone":"Europe/Belgrade",
    "iso:country":"RS",
    "name:deu_x_preferred":[
        "Bela Voda"
    ],
    "name:fra_x_preferred":[
        "Bela Voda"
    ],
    "name:msa_x_preferred":[
        "Bela Voda"
    ],
    "name:por_x_preferred":[
        "Bela Voda"
    ],
    "name:slv_x_preferred":[
        "Bela Voda"
    ],
    "name:srp_x_preferred":[
        "Bela Voda"
    ],
    "name:srp_x_variant":[
        "\u0411\u0435\u043b\u0430 \u0412\u043e\u0434\u0430"
    ],
    "wof:name":"Bela Voda",
    "wof:placetype":"locality"
},
  "geometry": {"coordinates":[21.19932,43.61722],"type":"Point"}
}