{
  "type": "Feature",
  "properties": {
    "gn:admin1_code":"VO",
    "gn:admin2_code":"6",
    "gn:asciiname":"Stara Pustara",
    "gn:country_code":"RS",
    "gn:dem":77,
    "gn:feature_class":"P",
    "gn:feature_code":"PPL",
    "gn:name":"Stara Pustara",
    "gn:population":0,
    "gn:timezone":"Europe/Belgrade",
    "iso:country":"RS",
    "name:srp_x_preferred":[
        "Stara Pustara"
    ],
    "wof:name":"Stara Pustara",
    "wof:placetype":"locality"
},
  "geometry": {"coordinates":[19.54222,45.40944],"type":"Point"}
}