{
  "type": "Feature",
  "properties": {
    "gn:country":"RS",
    "gn:fcode":"PPL",
    "gn:pop":1262,
    "iso:country":"RS",
    "name:dut_x_preferred":[
        "\u010coke\u0161ina"
    ],
    "name:eng_x_preferred":[
        "\u010coke\u0161ina"
    ],
    "name:fre_x_preferred":[
        "\u010coke\u0161ina"
    ],
    "name:hrv_x_preferred":[
        "\u010coke\u0161ina"
    ],
    "name:may_x_preferred":[
        "\u010coke\u0161ina"
    ],
    "name:por_x_preferred":[
        "\u010coke\u0161ina"
    ],
    "name:slv_x_preferred":[
        "\u010coke\u0161ina"
    ],
    "name:srp_x_preferred":[
        "\u010coke\u0161ina"
    ],
    "qs:name":"\u010coke\u0161ina",
    "qs:photos_9r":0,
    "qs:photos_sr":0,
    "qs:pop_sr":"3",
    "wd:wordcount":67,
    "wof:name":"\u010coke\u0161ina",
    "wof:placetype":"locality",
    "wof:population":1262
},
  "geometry": {"coordinates":[19.39016,44.65319],"type":"Point"}
}