{
  "type": "Feature",
  "properties": {
    "gn:country":"RS",
    "gn:fcode":"PPL",
    "gn:population":1262,
    "iso:country":"RS",
    "name:ceb_x_preferred":[
        "\u010coke\u0161ina"
    ],
    "name:eng_x_preferred":[
        "\u010coke\u0161ina"
    ],
    "name:fas_x_preferred":[
        "\u0686\u0648\u06a9\u0634\u06cc\u0646\u0627"
    ],
    "name:fra_x_preferred":[
        "\u010coke\u0161ina"
    ],
    "name:hrv_x_preferred":[
        "\u010coke\u0161ina"
    ],
    "name:msa_x_preferred":[
        "\u010coke\u0161ina"
    ],
    "name:nld_x_preferred":[
        "\u010coke\u0161ina"
    ],
    "name:pol_x_preferred":[
        "\u010coke\u0161ina"
    ],
    "name:por_x_preferred":[
        "\u010coke\u0161ina"
    ],
    "name:slv_x_preferred":[
        "\u010coke\u0161ina"
    ],
    "name:srp_x_preferred":[
        "\u010coke\u0161ina"
    ],
    "name:srp_x_variant":[
        "\u0427\u043e\u043a\u0435\u0448\u0438\u043d\u0430"
    ],
    "qs:name":"\u010coke\u0161ina",
    "qs:photos_9r":0,
    "qs:photos_sr":0,
    "qs:pop_sr":"3",
    "wd:wordcount":67,
    "wof:name":"\u010coke\u0161ina",
    "wof:placetype":"locality",
    "wof:population":1262
},
  "geometry": {"coordinates":[19.39016,44.65319],"type":"Point"}
}