{
  "type": "Feature",
  "properties": {
    "gn:admin1_code":"SE",
    "gn:admin2_code":"15",
    "gn:asciiname":"Meci Do",
    "gn:country_code":"RS",
    "gn:dem":492,
    "gn:feature_class":"P",
    "gn:feature_code":"PPL",
    "gn:name":"Me\u010di Do",
    "gn:population":0,
    "gn:timezone":"Europe/Belgrade",
    "iso:country":"RS",
    "name:fra_x_preferred":[
        "Me\u010dji Do"
    ],
    "name:msa_x_preferred":[
        "Me\u010dji Do"
    ],
    "name:por_x_preferred":[
        "Me\u010dji Do"
    ],
    "name:slv_x_preferred":[
        "Me\u010dji Do"
    ],
    "name:srp_x_preferred":[
        "\u041c\u0435\u0447\u0458\u0438 \u0414\u043e"
    ],
    "name:und_x_variant":[
        "Me\u010diji Dol",
        "Me\u010di Do"
    ],
    "wof:name":"Meci Do",
    "wof:placetype":"locality"
},
  "geometry": {"coordinates":[22.05483,43.5018],"type":"Point"}
}