{
  "type": "Feature",
  "properties": {
    "gn:admin1_code":"SE",
    "gn:admin2_code":"18",
    "gn:asciiname":"Torgevo",
    "gn:country_code":"RS",
    "gn:dem":1197,
    "gn:feature_class":"P",
    "gn:feature_code":"PPL",
    "gn:name":"Tor\u0111evo",
    "gn:population":0,
    "gn:timezone":"Europe/Belgrade",
    "iso:country":"RS",
    "name:srp_x_preferred":[
        "Tor\u0111evo"
    ],
    "wof:name":"Torgevo",
    "wof:placetype":"locality"
},
  "geometry": {"coordinates":[20.33028,43.24444],"type":"Point"}
}