{
  "type": "Feature",
  "properties": {
    "gn:admin1_code":"00",
    "gn:asciiname":"Kostadinovska Mahala",
    "gn:country_code":"RS",
    "gn:dem":1003,
    "gn:feature_class":"P",
    "gn:feature_code":"PPL",
    "gn:name":"Kostadinovska Mahala",
    "gn:population":0,
    "gn:timezone":"Europe/Belgrade",
    "iso:country":"RS",
    "name:und_x_variant":[
        "Prijos Mahala",
        "Kostadinovska Mahala"
    ],
    "wof:name":"Kostadinovska Mahala",
    "wof:placetype":"locality"
},
  "geometry": {"coordinates":[22.48563,42.53535],"type":"Point"}
}