{
  "type": "Feature",
  "properties": {
    "gn:admin1_code":"SE",
    "gn:admin2_code":"16",
    "gn:asciiname":"Tatinac",
    "gn:country_code":"RS",
    "gn:dem":663,
    "gn:feature_class":"P",
    "gn:feature_code":"PPL",
    "gn:name":"Tatinac",
    "gn:population":0,
    "gn:timezone":"Europe/Belgrade",
    "iso:country":"RS",
    "name:srp_x_preferred":[
        "Tatinac"
    ],
    "wof:name":"Tatinac",
    "wof:placetype":"locality"
},
  "geometry": {"coordinates":[19.86177,43.87134],"type":"Point"}
}