{
  "type": "Feature",
  "properties": {
    "gn:country":"RS",
    "gn:fcode":"PPL",
    "gn:pop":3075,
    "iso:country":"RS",
    "name:eng_x_preferred":[
        "Putinci"
    ],
    "name:epo_x_preferred":[
        "Putinci"
    ],
    "name:fra_x_preferred":[
        "Putinci"
    ],
    "name:hrv_x_preferred":[
        "Putinci"
    ],
    "name:hun_x_preferred":[
        "Putinci"
    ],
    "name:msa_x_preferred":[
        "Putinci"
    ],
    "name:nld_x_preferred":[
        "Putinci"
    ],
    "name:slv_x_preferred":[
        "Putinci"
    ],
    "name:srp_x_preferred":[
        "Putinci"
    ],
    "name:swe_x_preferred":[
        "Putinci"
    ],
    "name:unk_x_variant":[
        "Putincze"
    ],
    "qs:name":"Putinci",
    "qs:photos_9r":0,
    "qs:photos_sr":0,
    "qs:pop_sr":"4",
    "wd:wordcount":99,
    "wof:name":"Putinci",
    "wof:placetype":"locality",
    "wof:population":3075
},
  "geometry": {"coordinates":[19.97102,44.99259],"type":"Point"}
}