{
  "type": "Feature",
  "properties": {
    "gn:country":"RS",
    "gn:fcode":"PPL",
    "gn:population":3075,
    "iso:country":"RS",
    "name:ceb_x_preferred":[
        "Putinci"
    ],
    "name:deu_x_preferred":[
        "Putinci"
    ],
    "name:eng_x_preferred":[
        "Putinci"
    ],
    "name:epo_x_preferred":[
        "Putinci"
    ],
    "name:fas_x_preferred":[
        "\u067e\u0648\u062a\u06cc\u0646\u062a\u0633\u06cc"
    ],
    "name:fra_x_preferred":[
        "Putinci"
    ],
    "name:hrv_x_preferred":[
        "Putinci"
    ],
    "name:hun_x_preferred":[
        "Putinci"
    ],
    "name:msa_x_preferred":[
        "Putinci"
    ],
    "name:nld_x_preferred":[
        "Putinci"
    ],
    "name:pol_x_preferred":[
        "Putinci"
    ],
    "name:slv_x_preferred":[
        "Putinci"
    ],
    "name:srp_x_preferred":[
        "Putinci"
    ],
    "name:srp_x_variant":[
        "\u041f\u0443\u0442\u0438\u043d\u0446\u0438"
    ],
    "name:swe_x_preferred":[
        "Putinci"
    ],
    "name:ukr_x_preferred":[
        "\u041f\u0443\u0442\u0456\u043d\u0446\u0456"
    ],
    "name:und_x_variant":[
        "Putincze"
    ],
    "qs:name":"Putinci",
    "qs:photos_9r":0,
    "qs:photos_sr":0,
    "qs:pop_sr":"4",
    "wd:wordcount":99,
    "wof:name":"Putinci",
    "wof:placetype":"locality",
    "wof:population":3075
},
  "geometry": {"coordinates":[19.97102,44.99259],"type":"Point"}
}