{
  "type": "Feature",
  "properties": {
    "gn:admin1_code":"SE",
    "gn:admin2_code":"9",
    "gn:asciiname":"Gornji Mladenovici",
    "gn:country_code":"RS",
    "gn:dem":340,
    "gn:feature_class":"P",
    "gn:feature_code":"PPL",
    "gn:name":"Gornji Mladenovi\u0107i",
    "gn:population":0,
    "gn:timezone":"Europe/Belgrade",
    "iso:country":"RS",
    "wof:name":"Gornji Mladenovici",
    "wof:placetype":"locality"
},
  "geometry": {"coordinates":[19.61444,44.39417],"type":"Point"}
}