{
  "type": "Feature",
  "properties": {
    "gn:admin1_code":"SE",
    "gn:admin2_code":"23",
    "gn:asciiname":"Bacevina",
    "gn:country_code":"RS",
    "gn:dem":463,
    "gn:feature_class":"P",
    "gn:feature_code":"PPLL",
    "gn:name":"Ba\u010devina",
    "gn:population":0,
    "gn:timezone":"Europe/Belgrade",
    "iso:country":"RS",
    "name:srp_x_preferred":[
        "Ba\u010devina"
    ],
    "wof:name":"Bacevina",
    "wof:placetype":"locality"
},
  "geometry": {"coordinates":[21.62328,42.94757],"type":"Point"}
}