{
  "type": "Feature",
  "properties": {
    "gn:admin1_code":"SE",
    "gn:admin2_code":"19",
    "gn:asciiname":"Tulez",
    "gn:country_code":"RS",
    "gn:dem":364,
    "gn:feature_class":"P",
    "gn:feature_code":"PPL",
    "gn:name":"Tulez",
    "gn:population":0,
    "gn:timezone":"Europe/Belgrade",
    "iso:country":"RS",
    "name:ceb_x_preferred":[
        "Tulez"
    ],
    "name:fra_x_preferred":[
        "Tule\u0161"
    ],
    "name:hye_x_preferred":[
        "\u054f\u0578\u0582\u056c\u0565\u0577"
    ],
    "name:msa_x_preferred":[
        "Tule\u0161"
    ],
    "name:por_x_preferred":[
        "Tule\u0161"
    ],
    "name:slv_x_preferred":[
        "Tule\u0161"
    ],
    "name:spa_x_preferred":[
        "Tule\u0161"
    ],
    "name:srp_x_preferred":[
        "Tulez"
    ],
    "name:srp_x_variant":[
        "\u0422\u0443\u043b\u0435\u0448"
    ],
    "name:und_x_variant":[
        "Tule\u0161"
    ],
    "wof:name":"Tulez",
    "wof:placetype":"locality"
},
  "geometry": {"coordinates":[21.09623,43.49366],"type":"Point"}
}