{
  "type": "Feature",
  "properties": {
    "gn:admin1_code":"SE",
    "gn:admin2_code":"19",
    "gn:asciiname":"Turjak",
    "gn:country_code":"RS",
    "gn:dem":413,
    "gn:feature_class":"P",
    "gn:feature_code":"PPL",
    "gn:name":"Turjak",
    "gn:population":0,
    "gn:timezone":"Europe/Belgrade",
    "iso:country":"RS",
    "name:bos_x_preferred":[
        "Turjak"
    ],
    "name:ceb_x_preferred":[
        "Turjak"
    ],
    "name:fas_x_preferred":[
        "\u062a\u0648\u0631\u062c\u0627\u06a9"
    ],
    "name:nld_x_preferred":[
        "Turjak"
    ],
    "name:pol_x_preferred":[
        "Turjak"
    ],
    "name:ron_x_preferred":[
        "Turjak"
    ],
    "name:slv_x_preferred":[
        "Turjak"
    ],
    "name:srp_x_preferred":[
        "Turjak"
    ],
    "name:ukr_x_preferred":[
        "\u0422\u0443\u0440\u044f\u043a"
    ],
    "name:urd_x_preferred":[
        "\u062a\u0648\u0631\u062c\u0627\u06a9"
    ],
    "wof:name":"Turjak",
    "wof:placetype":"locality"
},
  "geometry": {"coordinates":[21.15037,43.37785],"type":"Point"}
}