{
  "type": "Feature",
  "properties": {
    "gn:admin1_code":"SE",
    "gn:admin2_code":"19",
    "gn:asciiname":"Turjak",
    "gn:country_code":"RS",
    "gn:dem":413,
    "gn:feature_class":"P",
    "gn:feature_code":"PPL",
    "gn:name":"Turjak",
    "gn:population":0,
    "gn:timezone":"Europe/Belgrade",
    "iso:country":"RS",
    "name:srp_x_preferred":[
        "Turjak"
    ],
    "wof:name":"Turjak",
    "wof:placetype":"locality"
},
  "geometry": {"coordinates":[21.15037,43.37785],"type":"Point"}
}