{
  "type": "Feature",
  "properties": {
    "gn:admin1_code":"00",
    "gn:asciiname":"Ljubicevac",
    "gn:country_code":"RS",
    "gn:dem":46,
    "gn:feature_class":"P",
    "gn:feature_code":"PPL",
    "gn:name":"Ljubi\u010devac",
    "gn:population":0,
    "gn:timezone":"Europe/Belgrade",
    "iso:country":"RS",
    "name:srp_x_preferred":[
        "Ljubi\u010devac"
    ],
    "wof:name":"Ljubicevac",
    "wof:placetype":"locality"
},
  "geometry": {"coordinates":[22.53775,44.48954000000001],"type":"Point"}
}