{
  "type": "Feature",
  "properties": {
    "gn:admin1_code":"00",
    "gn:asciiname":"Ljubicevac",
    "gn:country_code":"RS",
    "gn:dem":46,
    "gn:feature_class":"P",
    "gn:feature_code":"PPL",
    "gn:name":"Ljubi\u010devac",
    "gn:population":0,
    "gn:timezone":"Europe/Belgrade",
    "iso:country":"RS",
    "name:ceb_x_preferred":[
        "Ljubi\u010devac"
    ],
    "name:deu_x_preferred":[
        "Ljubi\u010devac"
    ],
    "name:fra_x_preferred":[
        "Ljubi\u010devac"
    ],
    "name:mkd_x_preferred":[
        "\u0409\u0443\u0431\u0438\u0447\u0435\u0432\u0430\u0446"
    ],
    "name:msa_x_preferred":[
        "Ljubi\u010devac"
    ],
    "name:por_x_preferred":[
        "Ljubi\u010devac"
    ],
    "name:slv_x_preferred":[
        "Ljubi\u010devac"
    ],
    "name:srp_x_preferred":[
        "Ljubi\u010devac"
    ],
    "name:srp_x_variant":[
        "\u0409\u0443\u0431\u0438\u0447\u0435\u0432\u0430\u0446"
    ],
    "wof:name":"Ljubicevac",
    "wof:placetype":"locality"
},
  "geometry": {"coordinates":[22.53775,44.48954000000001],"type":"Point"}
}