{
  "type": "Feature",
  "properties": {
    "gn:admin1_code":"SE",
    "gn:admin2_code":"23",
    "gn:admin3_code":"70815.0",
    "gn:asciiname":"Medvega",
    "gn:country_code":"RS",
    "gn:dem":367,
    "gn:feature_class":"P",
    "gn:feature_code":"PPLA3",
    "gn:name":"Medve\u0111a",
    "gn:population":0,
    "gn:timezone":"Europe/Belgrade",
    "iso:country":"RS",
    "name:bul_x_preferred":[
        "\u041c\u0435\u0434\u0432\u0435\u0434\u0436\u0430"
    ],
    "name:deu_x_preferred":[
        "Medve\u0111a"
    ],
    "name:fra_x_preferred":[
        "Medve\u0111a"
    ],
    "name:hbs_x_preferred":[
        "Op\u0161tina Medve\u0111a"
    ],
    "name:hrv_x_preferred":[
        "Medve\u0111a"
    ],
    "name:hun_x_preferred":[
        "Medve\u0111a"
    ],
    "name:ita_x_preferred":[
        "Medve\u0111a"
    ],
    "name:jpn_x_preferred":[
        "\u30e1\u30c9\u30f4\u30a7\u30b8\u30e3"
    ],
    "name:kor_x_preferred":[
        "\uba54\ub4dc\ubca0\uc790"
    ],
    "name:msa_x_preferred":[
        "Medve\u0111a"
    ],
    "name:nld_x_preferred":[
        "Medve\u0111a"
    ],
    "name:pnb_x_preferred":[
        "\u0645\u06cc\u062f\u0648\u06cc\u062f\u0627"
    ],
    "name:pol_x_preferred":[
        "Medve\u0111a"
    ],
    "name:por_x_preferred":[
        "Medve\u0111a"
    ],
    "name:slv_x_preferred":[
        "Medve\u0111a"
    ],
    "name:spa_x_preferred":[
        "Medve\u0111a"
    ],
    "name:sqi_x_preferred":[
        "Medvegja"
    ],
    "name:srp_x_preferred":[
        "Medve\u0111a"
    ],
    "name:srp_x_variant":[
        "\u041c\u0435\u0434\u0432\u0435\u0452\u0430"
    ],
    "name:tur_x_preferred":[
        "Medvece"
    ],
    "name:ukr_x_preferred":[
        "\u041c\u0435\u0434\u0432\u0435\u0434\u0436\u0430"
    ],
    "name:und_x_variant":[
        "Medvegj\u00eb",
        "Medvedja"
    ],
    "name:zho_x_preferred":[
        "\u6885\u5fb7\u97cb\u8cc8"
    ],
    "wof:name":"Medvega",
    "wof:placetype":"locality"
},
  "geometry": {"coordinates":[21.58333,42.84306],"type":"Point"}
}