{
  "type": "Feature",
  "properties": {
    "gn:country":"RS",
    "gn:fcode":"PPL",
    "gn:pop":2855,
    "iso:country":"RS",
    "name:ceb_x_preferred":[
        "Hrtkovci"
    ],
    "name:eng_x_preferred":[
        "Hrtkovci"
    ],
    "name:epo_x_preferred":[
        "Hrtkovci"
    ],
    "name:fra_x_preferred":[
        "Hrtkovci"
    ],
    "name:hrv_x_preferred":[
        "Hrtkovci"
    ],
    "name:hun_x_preferred":[
        "Herk\u00f3ca"
    ],
    "name:jpn_x_preferred":[
        "\u30d5\u30eb\u30c8\u30b3\u30f4\u30c4\u30a3"
    ],
    "name:msa_x_preferred":[
        "Hrtkovci"
    ],
    "name:nld_x_preferred":[
        "Hrtkovci"
    ],
    "name:slv_x_preferred":[
        "Hrtkovci"
    ],
    "name:sqi_x_preferred":[
        "H\u00ebrtkoci"
    ],
    "name:srp_x_preferred":[
        "Hrtkovci"
    ],
    "name:srp_x_variant":[
        "\u0425\u0440\u0442\u043a\u043e\u0432\u0446\u0438"
    ],
    "name:unk_x_variant":[
        "Srbislavci"
    ],
    "qs:name":"Hrtkovci",
    "qs:name_adm0":"Serbia",
    "qs:name_adm1":"Srem",
    "qs:photos_9k":1,
    "qs:photos_9r":1,
    "qs:photos_all":5,
    "qs:photos_sr":0,
    "qs:placetype":"Town",
    "qs:pop_sr":"4",
    "wd:wordcount":881,
    "wof:name":"Hrtkovci",
    "wof:placetype":"locality",
    "wof:population":2855
},
  "geometry": {"coordinates":[19.76374,44.88155],"type":"Point"}
}