{
  "type": "Feature",
  "properties": {
    "gn:admin1_code":"SE",
    "gn:admin2_code":"24",
    "gn:asciiname":"Popova Mahala",
    "gn:country_code":"RS",
    "gn:dem":1281,
    "gn:feature_class":"P",
    "gn:feature_code":"PPL",
    "gn:name":"Popova Mahala",
    "gn:population":0,
    "gn:timezone":"Europe/Belgrade",
    "iso:country":"RS",
    "name:srp_x_preferred":[
        "Popova Mahala"
    ],
    "name:und_x_variant":[
        "Popove Ko\u0161are"
    ],
    "wof:name":"Popova Mahala",
    "wof:placetype":"locality"
},
  "geometry": {"coordinates":[22.2031,42.57603],"type":"Point"}
}