{
  "type": "Feature",
  "properties": {
    "gn:admin1_code":"SE",
    "gn:admin2_code":"24",
    "gn:asciiname":"Car",
    "gn:country_code":"RS",
    "gn:dem":895,
    "gn:feature_class":"P",
    "gn:feature_code":"PPL",
    "gn:name":"\u010car",
    "gn:population":0,
    "gn:timezone":"Europe/Belgrade",
    "iso:country":"RS",
    "name:bul_x_preferred":[
        "\u0427\u0430\u0440"
    ],
    "name:ceb_x_preferred":[
        "\u010car"
    ],
    "name:fra_x_preferred":[
        "\u010car"
    ],
    "name:msa_x_preferred":[
        "\u010car"
    ],
    "name:por_x_preferred":[
        "\u010car"
    ],
    "name:slv_x_preferred":[
        "\u010car"
    ],
    "name:sqi_x_preferred":[
        "\u00c7arri"
    ],
    "name:srp_x_preferred":[
        "\u010car"
    ],
    "name:srp_x_variant":[
        "\u0427\u0430\u0440"
    ],
    "wof:name":"Car",
    "wof:placetype":"locality"
},
  "geometry": {"coordinates":[21.75211,42.5969],"type":"Point"}
}