{
  "type": "Feature",
  "properties": {
    "gn:country":"RS",
    "gn:fcode":"PPL",
    "gn:pop":2206,
    "iso:country":"RS",
    "name:dut_x_preferred":[
        "Ribari"
    ],
    "name:eng_x_preferred":[
        "Ribari"
    ],
    "name:fre_x_preferred":[
        "Ribari"
    ],
    "name:may_x_preferred":[
        "Ribari"
    ],
    "name:por_x_preferred":[
        "Ribari"
    ],
    "name:slv_x_preferred":[
        "Ribari"
    ],
    "name:srp_x_preferred":[
        "Ribari"
    ],
    "qs:name":"Ribari",
    "qs:photos_9r":0,
    "qs:photos_sr":0,
    "qs:pop_sr":"4",
    "wd:wordcount":27,
    "wof:name":"Ribari",
    "wof:placetype":"locality",
    "wof:population":2206
},
  "geometry": {"coordinates":[19.42472,44.70961],"type":"Point"}
}