{
  "type": "Feature",
  "properties": {
    "gn:admin1_code":"SE",
    "gn:admin2_code":"15",
    "gn:asciiname":"Sarbanovac",
    "gn:country_code":"RS",
    "gn:dem":508,
    "gn:feature_class":"P",
    "gn:feature_code":"PPL",
    "gn:name":"\u0160arbanovac",
    "gn:population":0,
    "gn:timezone":"Europe/Belgrade",
    "iso:country":"RS",
    "name:srp_x_preferred":[
        "\u0160arbanovac"
    ],
    "name:und_x_variant":[
        "\u0160arbanovovci"
    ],
    "wof:name":"Sarbanovac",
    "wof:placetype":"locality"
},
  "geometry": {"coordinates":[22.38398,43.60191],"type":"Point"}
}