{
  "type": "Feature",
  "properties": {
    "gn:admin1_code":"SE",
    "gn:admin2_code":"8",
    "gn:asciiname":"Poljane",
    "gn:country_code":"RS",
    "gn:dem":294,
    "gn:feature_class":"P",
    "gn:feature_code":"PPL",
    "gn:name":"Poljane",
    "gn:population":0,
    "gn:timezone":"Europe/Belgrade",
    "iso:country":"RS",
    "name:bos_x_preferred":[
        "Poljane"
    ],
    "name:ceb_x_preferred":[
        "Poljane"
    ],
    "name:fra_x_preferred":[
        "Poljane"
    ],
    "name:hrv_x_preferred":[
        "Poljane"
    ],
    "name:hun_x_preferred":[
        "Poljane"
    ],
    "name:nld_x_preferred":[
        "Poljane"
    ],
    "name:sco_x_preferred":[
        "Poljane"
    ],
    "name:slv_x_preferred":[
        "Poljane"
    ],
    "name:srp_x_preferred":[
        "Poljane"
    ],
    "name:srp_x_variant":[
        "\u041f\u043e\u0459\u0430\u043d\u0435"
    ],
    "name:swe_x_preferred":[
        "Poljane"
    ],
    "wof:name":"Poljane",
    "wof:placetype":"locality"
},
  "geometry": {"coordinates":[19.24617000000001,44.48311],"type":"Point"}
}