{
  "type": "Feature",
  "properties": {
    "gn:admin1_code":"SE",
    "gn:admin2_code":"8",
    "gn:asciiname":"Donja Sipulja",
    "gn:country_code":"RS",
    "gn:dem":233,
    "gn:feature_class":"P",
    "gn:feature_code":"PPLL",
    "gn:name":"Donja Sipulja",
    "gn:population":0,
    "gn:timezone":"Europe/Belgrade",
    "iso:country":"RS",
    "name:ceb_x_preferred":[
        "Donja Sipulja"
    ],
    "name:fra_x_preferred":[
        "Donja Sipulja"
    ],
    "name:hrv_x_preferred":[
        "Donja Sipulja"
    ],
    "name:msa_x_preferred":[
        "Donja Sipulja"
    ],
    "name:nld_x_preferred":[
        "Donja Sipulja"
    ],
    "name:por_x_preferred":[
        "Donja Sipulja"
    ],
    "name:slv_x_preferred":[
        "Donja Sipulja"
    ],
    "name:srp_x_preferred":[
        "Donja Sipulja"
    ],
    "name:srp_x_variant":[
        "\u0414\u043e\u045a\u0430 \u0421\u0438\u043f\u0443\u0459\u0430"
    ],
    "wof:name":"Donja Sipulja",
    "wof:placetype":"locality"
},
  "geometry": {"coordinates":[19.5125,44.50465],"type":"Point"}
}