{
  "type": "Feature",
  "properties": {
    "gn:admin1_code":"SE",
    "gn:admin2_code":"8",
    "gn:asciiname":"Donja Sipulja",
    "gn:country_code":"RS",
    "gn:dem":233,
    "gn:feature_class":"P",
    "gn:feature_code":"PPLL",
    "gn:name":"Donja Sipulja",
    "gn:population":0,
    "gn:timezone":"Europe/Belgrade",
    "iso:country":"RS",
    "name:srp_x_preferred":[
        "Donja Sipulja"
    ],
    "wof:name":"Donja Sipulja",
    "wof:placetype":"locality"
},
  "geometry": {"coordinates":[19.5125,44.50465],"type":"Point"}
}