{
  "type": "Feature",
  "properties": {
    "gn:admin1_code":"SE",
    "gn:admin2_code":"13",
    "gn:asciiname":"Velika Kaludra",
    "gn:country_code":"RS",
    "gn:dem":396,
    "gn:feature_class":"P",
    "gn:feature_code":"PPL",
    "gn:name":"Velika Kaludra",
    "gn:population":0,
    "gn:timezone":"Europe/Belgrade",
    "iso:country":"RS",
    "name:und_x_variant":[
        "Kaludra",
        "Velika Kaludra"
    ],
    "wof:name":"Velika Kaludra",
    "wof:placetype":"locality"
},
  "geometry": {"coordinates":[21.06463,43.76779000000001],"type":"Point"}
}