{
  "type": "Feature",
  "properties": {
    "gn:admin1_code":"00",
    "gn:asciiname":"Ribarci",
    "gn:country_code":"RS",
    "gn:dem":884,
    "gn:feature_class":"P",
    "gn:feature_code":"PPL",
    "gn:name":"Ribarci",
    "gn:population":0,
    "gn:timezone":"Europe/Belgrade",
    "iso:country":"RS",
    "name:srp_x_preferred":[
        "Ribarci"
    ],
    "wof:name":"Ribarci",
    "wof:placetype":"locality"
},
  "geometry": {"coordinates":[22.53042,42.42339000000001],"type":"Point"}
}