{
  "type": "Feature",
  "properties": {
    "gn:admin1_code":"SE",
    "gn:admin2_code":"18",
    "gn:asciiname":"Tolisnica",
    "gn:country_code":"RS",
    "gn:dem":728,
    "gn:feature_class":"P",
    "gn:feature_code":"PPLL",
    "gn:name":"Toli\u0161nica",
    "gn:population":0,
    "gn:timezone":"Europe/Belgrade",
    "iso:country":"RS",
    "name:srp_x_preferred":[
        "Toli\u0161nica"
    ],
    "wof:name":"Tolisnica",
    "wof:placetype":"locality"
},
  "geometry": {"coordinates":[20.42859,43.61739],"type":"Point"}
}