{
  "type": "Feature",
  "properties": {
    "gn:admin1_code":"SE",
    "gn:admin2_code":"18",
    "gn:asciiname":"Tolisnica",
    "gn:country_code":"RS",
    "gn:dem":728,
    "gn:feature_class":"P",
    "gn:feature_code":"PPLL",
    "gn:name":"Toli\u0161nica",
    "gn:population":0,
    "gn:timezone":"Europe/Belgrade",
    "iso:country":"RS",
    "name:ceb_x_preferred":[
        "Toli\u0161nica"
    ],
    "name:fra_x_preferred":[
        "Toli\u0161nica"
    ],
    "name:hun_x_preferred":[
        "Toli\u0161nica"
    ],
    "name:msa_x_preferred":[
        "Toli\u0161nica"
    ],
    "name:nld_x_preferred":[
        "Toli\u0161nica"
    ],
    "name:por_x_preferred":[
        "Toli\u0161nica"
    ],
    "name:slv_x_preferred":[
        "Toli\u0161nica"
    ],
    "name:srp_x_preferred":[
        "Toli\u0161nica"
    ],
    "name:srp_x_variant":[
        "\u0422\u043e\u043b\u0438\u0448\u043d\u0438\u0446\u0430"
    ],
    "wof:name":"Tolisnica",
    "wof:placetype":"locality"
},
  "geometry": {"coordinates":[20.42859,43.61739],"type":"Point"}
}