{
  "type": "Feature",
  "properties": {
    "gn:admin1_code":"SE",
    "gn:admin2_code":"9",
    "gn:asciiname":"Boskovici",
    "gn:country_code":"RS",
    "gn:dem":298,
    "gn:feature_class":"P",
    "gn:feature_code":"PPL",
    "gn:name":"Bo\u0161kovi\u0107i",
    "gn:population":0,
    "gn:timezone":"Europe/Belgrade",
    "iso:country":"RS",
    "name:srp_x_preferred":[
        "Bo\u0161kovi\u0107i"
    ],
    "wof:name":"Boskovici",
    "wof:placetype":"locality"
},
  "geometry": {"coordinates":[19.78633,44.27136],"type":"Point"}
}