{
  "type": "Feature",
  "properties": {
    "gn:admin1_code":"SE",
    "gn:admin2_code":"17",
    "gn:asciiname":"Zecevici",
    "gn:country_code":"RS",
    "gn:dem":977,
    "gn:feature_class":"P",
    "gn:feature_code":"PPL",
    "gn:name":"Ze\u010devi\u0107i",
    "gn:population":0,
    "gn:timezone":"Europe/Belgrade",
    "iso:country":"RS",
    "name:srp_x_preferred":[
        "Ze\u010devi\u0107i"
    ],
    "wof:name":"Zecevici",
    "wof:placetype":"locality"
},
  "geometry": {"coordinates":[20.09605,43.49427],"type":"Point"}
}