{
  "type": "Feature",
  "properties": {
    "gn:admin1_code":"SE",
    "gn:admin2_code":"24",
    "gn:asciiname":"Velkova Mahala",
    "gn:country_code":"RS",
    "gn:dem":1178,
    "gn:feature_class":"P",
    "gn:feature_code":"PPL",
    "gn:name":"Velkova Mahala",
    "gn:population":0,
    "gn:timezone":"Europe/Belgrade",
    "iso:country":"RS",
    "wof:name":"Velkova Mahala",
    "wof:placetype":"locality"
},
  "geometry": {"coordinates":[22.41435,42.71477],"type":"Point"}
}