{
  "type": "Feature",
  "properties": {
    "gn:admin1_code":"SE",
    "gn:admin2_code":"9",
    "gn:asciiname":"Donja Lukica Mala",
    "gn:country_code":"RS",
    "gn:dem":297,
    "gn:feature_class":"P",
    "gn:feature_code":"PPL",
    "gn:name":"Donja Luki\u0107a Mala",
    "gn:population":0,
    "gn:timezone":"Europe/Belgrade",
    "iso:country":"RS",
    "name:und_x_variant":[
        "Luki\u0107a Mahala",
        "Luki\u0107a",
        "Donja Luki\u0107a Mala"
    ],
    "wof:name":"Donja Lukica Mala",
    "wof:placetype":"locality"
},
  "geometry": {"coordinates":[19.5925,44.39222],"type":"Point"}
}