{
  "type": "Feature",
  "properties": {
    "gn:admin1_code":"SE",
    "gn:admin2_code":"8",
    "gn:asciiname":"Javor",
    "gn:country_code":"RS",
    "gn:dem":332,
    "gn:feature_class":"P",
    "gn:feature_code":"PPL",
    "gn:name":"Javor",
    "gn:population":0,
    "gn:timezone":"Europe/Belgrade",
    "iso:country":"RS",
    "name:bos_x_preferred":[
        "Javor"
    ],
    "name:ceb_x_preferred":[
        "Javor"
    ],
    "name:ces_x_preferred":[
        "Javor"
    ],
    "name:deu_x_preferred":[
        "Javor"
    ],
    "name:fra_x_preferred":[
        "Javor"
    ],
    "name:hrv_x_preferred":[
        "Javor"
    ],
    "name:hun_x_preferred":[
        "Javor"
    ],
    "name:nld_x_preferred":[
        "Javor"
    ],
    "name:pol_x_preferred":[
        "Javor"
    ],
    "name:slv_x_preferred":[
        "Javor"
    ],
    "name:srp_x_preferred":[
        "Javor"
    ],
    "name:swe_x_preferred":[
        "Javor"
    ],
    "name:ukr_x_preferred":[
        "\u042f\u0432\u0456\u0440"
    ],
    "wof:name":"Javor",
    "wof:placetype":"locality"
},
  "geometry": {"coordinates":[19.398,44.19406],"type":"Point"}
}