{
  "type": "Feature",
  "properties": {
    "gn:admin1_code":"SE",
    "gn:admin2_code":"20",
    "gn:asciiname":"Belotinac",
    "gn:country_code":"RS",
    "gn:dem":190,
    "gn:feature_class":"P",
    "gn:feature_code":"PPL",
    "gn:name":"Belotinac",
    "gn:population":0,
    "gn:timezone":"Europe/Belgrade",
    "iso:country":"RS",
    "name:ceb_x_preferred":[
        "Belotinac"
    ],
    "name:fra_x_preferred":[
        "Belotinac"
    ],
    "name:msa_x_preferred":[
        "Belotinac"
    ],
    "name:por_x_preferred":[
        "Belotinac"
    ],
    "name:slv_x_preferred":[
        "Belotinac"
    ],
    "name:sqi_x_preferred":[
        "Bellotinaca"
    ],
    "name:srp_x_preferred":[
        "Belotinac"
    ],
    "name:srp_x_variant":[
        "\u0411\u0435\u043b\u043e\u0442\u0438\u043d\u0430\u0446"
    ],
    "name:und_x_variant":[
        "Belotince"
    ],
    "wof:name":"Belotinac",
    "wof:placetype":"locality"
},
  "geometry": {"coordinates":[21.85252,43.26509],"type":"Point"}
}