{
  "type": "Feature",
  "properties": {
    "gn:admin1_code":"SE",
    "gn:admin2_code":"20",
    "gn:asciiname":"Belotinac",
    "gn:country_code":"RS",
    "gn:dem":190,
    "gn:feature_class":"P",
    "gn:feature_code":"PPL",
    "gn:name":"Belotinac",
    "gn:population":0,
    "gn:timezone":"Europe/Belgrade",
    "iso:country":"RS",
    "name:srp_x_preferred":[
        "Belotinac"
    ],
    "name:und_x_variant":[
        "Belotince"
    ],
    "wof:name":"Belotinac",
    "wof:placetype":"locality"
},
  "geometry": {"coordinates":[21.85252,43.26509],"type":"Point"}
}