{
  "type": "Feature",
  "properties": {
    "gn:admin1_code":"SE",
    "gn:admin2_code":"8",
    "gn:asciiname":"Milutinovici",
    "gn:country_code":"RS",
    "gn:dem":425,
    "gn:feature_class":"P",
    "gn:feature_code":"PPL",
    "gn:name":"Milutinovi\u0107i",
    "gn:population":0,
    "gn:timezone":"Europe/Belgrade",
    "iso:country":"RS",
    "name:srp_x_preferred":[
        "Milutinovi\u0107i"
    ],
    "wof:name":"Milutinovici",
    "wof:placetype":"locality"
},
  "geometry": {"coordinates":[19.44663,44.23441],"type":"Point"}
}