{
  "type": "Feature",
  "properties": {
    "gn:admin1_code":"SE",
    "gn:admin2_code":"23",
    "gn:asciiname":"Predejane",
    "gn:country_code":"RS",
    "gn:dem":289,
    "gn:feature_class":"P",
    "gn:feature_code":"PPL",
    "gn:name":"Predejane",
    "gn:population":0,
    "gn:timezone":"Europe/Belgrade",
    "iso:country":"RS",
    "name:srp_x_preferred":[
        "Predejane"
    ],
    "wof:name":"Predejane",
    "wof:placetype":"locality"
},
  "geometry": {"coordinates":[22.12914,42.83284],"type":"Point"}
}