{
  "type": "Feature",
  "properties": {
    "gn:admin1_code":"SE",
    "gn:admin2_code":"23",
    "gn:asciiname":"Predejane",
    "gn:country_code":"RS",
    "gn:dem":289,
    "gn:feature_class":"P",
    "gn:feature_code":"PPL",
    "gn:name":"Predejane",
    "gn:population":0,
    "gn:timezone":"Europe/Belgrade",
    "iso:country":"RS",
    "name:ceb_x_preferred":[
        "Predejane"
    ],
    "name:fra_x_preferred":[
        "Predejane"
    ],
    "name:msa_x_preferred":[
        "Predejane"
    ],
    "name:nld_x_preferred":[
        "Predejane"
    ],
    "name:por_x_preferred":[
        "Predejane"
    ],
    "name:slv_x_preferred":[
        "Predejane"
    ],
    "name:srp_x_preferred":[
        "Predejane"
    ],
    "name:srp_x_variant":[
        "\u041f\u0440\u0435\u0434\u0435\u0458\u0430\u043d\u0435"
    ],
    "wof:name":"Predejane",
    "wof:placetype":"locality"
},
  "geometry": {"coordinates":[22.12914,42.83284],"type":"Point"}
}