{
  "type": "Feature",
  "properties": {
    "gn:admin1_code":"SE",
    "gn:admin2_code":"23",
    "gn:asciiname":"Tulare",
    "gn:country_code":"RS",
    "gn:dem":534,
    "gn:feature_class":"P",
    "gn:feature_code":"PPL",
    "gn:name":"Tulare",
    "gn:population":0,
    "gn:timezone":"Europe/Belgrade",
    "iso:country":"RS",
    "name:cat_x_preferred":[
        "Tulare"
    ],
    "name:ceb_x_preferred":[
        "Tulare"
    ],
    "name:fra_x_preferred":[
        "Tulare"
    ],
    "name:ita_x_preferred":[
        "Tulare"
    ],
    "name:nld_x_preferred":[
        "Tulare"
    ],
    "name:pol_x_preferred":[
        "Tulare"
    ],
    "name:por_x_preferred":[
        "Tulare"
    ],
    "name:rus_x_preferred":[
        "\u0422\u0443\u043b\u0430\u0440\u0435"
    ],
    "name:slv_x_preferred":[
        "Tulare"
    ],
    "name:srp_x_preferred":[
        "Tulare"
    ],
    "name:srp_x_variant":[
        "\u0422\u0443\u043b\u0435\u0440\u0438"
    ],
    "name:und_x_variant":[
        "Tulari",
        "Tullar\u00eb"
    ],
    "name:vol_x_preferred":[
        "Tulare"
    ],
    "wof:name":"Tulare",
    "wof:placetype":"locality"
},
  "geometry": {"coordinates":[21.46054,42.79417],"type":"Point"}
}