{
  "type": "Feature",
  "properties": {
    "gn:admin1_code":"SE",
    "gn:admin2_code":"16",
    "gn:asciiname":"Kovacevici",
    "gn:country_code":"RS",
    "gn:dem":886,
    "gn:feature_class":"P",
    "gn:feature_code":"PPL",
    "gn:name":"Kova\u010devi\u0107i",
    "gn:population":0,
    "gn:timezone":"Europe/Belgrade",
    "iso:country":"RS",
    "name:und_x_variant":[
        "\u017di\u017eaci",
        "Kova\u010devi\u0107i"
    ],
    "wof:name":"Kovacevici",
    "wof:placetype":"locality"
},
  "geometry": {"coordinates":[19.93453,43.65013],"type":"Point"}
}