{
  "type": "Feature",
  "properties": {
    "gn:admin1_code":"SE",
    "gn:admin2_code":"21",
    "gn:asciiname":"Kolaci",
    "gn:country_code":"RS",
    "gn:dem":475,
    "gn:feature_class":"P",
    "gn:feature_code":"PPL",
    "gn:name":"Kolaci",
    "gn:population":0,
    "gn:timezone":"Europe/Belgrade",
    "iso:country":"RS",
    "name:und_x_variant":[
        "Kaludra",
        "Kolaci"
    ],
    "wof:name":"Kolaci",
    "wof:placetype":"locality"
},
  "geometry": {"coordinates":[21.30819,43.01758],"type":"Point"}
}