{
  "type": "Feature",
  "properties": {
    "gn:admin1_code":"SE",
    "gn:admin2_code":"21",
    "gn:asciiname":"Macan",
    "gn:country_code":"RS",
    "gn:dem":645,
    "gn:feature_class":"P",
    "gn:feature_code":"PPL",
    "gn:name":"Macan",
    "gn:population":0,
    "gn:timezone":"Europe/Belgrade",
    "iso:country":"RS",
    "name:deu_x_preferred":[
        "Macan"
    ],
    "wof:name":"Macan",
    "wof:placetype":"locality"
},
  "geometry": {"coordinates":[21.43806,43.14278],"type":"Point"}
}