{
  "type": "Feature",
  "properties": {
    "gn:admin1_code":"VO",
    "gn:admin2_code":"5",
    "gn:asciiname":"Rancevo",
    "gn:country_code":"RS",
    "gn:dem":85,
    "gn:feature_class":"P",
    "gn:feature_code":"PPL",
    "gn:name":"Ran\u010devo",
    "gn:population":0,
    "gn:timezone":"Europe/Belgrade",
    "iso:country":"RS",
    "name:srp_x_preferred":[
        "Ran\u010devo"
    ],
    "wof:name":"Rancevo",
    "wof:placetype":"locality"
},
  "geometry": {"coordinates":[19.11664,45.87799],"type":"Point"}
}