{
  "type": "Feature",
  "properties": {
    "gn:admin1_code":"SE",
    "gn:admin2_code":"8",
    "gn:asciiname":"Pavlovici",
    "gn:country_code":"RS",
    "gn:dem":515,
    "gn:feature_class":"P",
    "gn:feature_code":"PPL",
    "gn:name":"Pavlovi\u0107i",
    "gn:population":0,
    "gn:timezone":"Europe/Belgrade",
    "iso:country":"RS",
    "name:srp_x_preferred":[
        "Pavlovi\u0107i"
    ],
    "wof:name":"Pavlovici",
    "wof:placetype":"locality"
},
  "geometry": {"coordinates":[19.33988,44.2998],"type":"Point"}
}