{
  "type": "Feature",
  "properties": {
    "gn:admin1_code":"SE",
    "gn:admin2_code":"17",
    "gn:asciiname":"Sakovici",
    "gn:country_code":"RS",
    "gn:dem":1195,
    "gn:feature_class":"P",
    "gn:feature_code":"PPL",
    "gn:name":"Sakovi\u0107i",
    "gn:population":0,
    "gn:timezone":"Europe/Belgrade",
    "iso:country":"RS",
    "name:srp_x_preferred":[
        "Sakovi\u0107i"
    ],
    "wof:name":"Sakovici",
    "wof:placetype":"locality"
},
  "geometry": {"coordinates":[20.19073,43.34633],"type":"Point"}
}