{
  "type": "Feature",
  "properties": {
    "gn:admin1_code":"00",
    "gn:asciiname":"Tetrebica",
    "gn:country_code":"RS",
    "gn:dem":1106,
    "gn:feature_class":"P",
    "gn:feature_code":"PPL",
    "gn:name":"Tetrebica",
    "gn:population":0,
    "gn:timezone":"Europe/Belgrade",
    "iso:country":"RS",
    "name:srp_x_preferred":[
        "Tetrebica"
    ],
    "wof:name":"Tetrebica",
    "wof:placetype":"locality"
},
  "geometry": {"coordinates":[19.38217,43.81837],"type":"Point"}
}