{
  "type": "Feature",
  "properties": {
    "gn:country":"RS",
    "gn:fcode":"PPLA3",
    "gn:pop":4769,
    "iso:country":"RS",
    "name:bos_x_preferred":[
        "Opovo"
    ],
    "name:chi_x_preferred":[
        "\u5967\u6ce2\u6c83"
    ],
    "name:cze_x_preferred":[
        "Opovo"
    ],
    "name:dut_x_preferred":[
        "Opovo"
    ],
    "name:eng_x_preferred":[
        "Opovo"
    ],
    "name:epo_x_preferred":[
        "Opovo"
    ],
    "name:fre_x_preferred":[
        "Opovo"
    ],
    "name:gre_x_preferred":[
        "\u038c\u03c0\u03bf\u03b2\u03bf"
    ],
    "name:hbs_x_preferred":[
        "\u041e\u043f\u043e\u0432\u043e"
    ],
    "name:hrv_x_preferred":[
        "Opovo"
    ],
    "name:hun_x_preferred":[
        "\u00d3p\u00e1va"
    ],
    "name:ita_x_preferred":[
        "Opovo"
    ],
    "name:jpn_x_preferred":[
        "\u30aa\u30dd\u30f4\u30a9"
    ],
    "name:may_x_preferred":[
        "Opovo"
    ],
    "name:pnb_x_preferred":[
        "\u0627\u0648\u067e\u0648\u0648"
    ],
    "name:pol_x_preferred":[
        "Opovo"
    ],
    "name:rum_x_preferred":[
        "Opovo"
    ],
    "name:rus_x_preferred":[
        "\u041e\u043f\u043e\u0432\u043e"
    ],
    "name:slv_x_preferred":[
        "Opovo"
    ],
    "name:srp_x_preferred":[
        "Opovo"
    ],
    "name:srp_x_variant":[
        "\u041e\u043f\u043e\u0432\u043e"
    ],
    "name:tat_x_preferred":[
        "\u041e\u043f\u043e\u0432\u043e"
    ],
    "name:tur_x_preferred":[
        "Opovo"
    ],
    "name:unk_x_variant":[
        "K\u00f6nisdorf"
    ],
    "name:zho_x_preferred":[
        "\u5967\u6ce2\u6c83"
    ],
    "qs:name":"Opovo",
    "qs:photos_9r":0,
    "qs:photos_sr":0,
    "qs:pop_sr":"4",
    "wd:wordcount":665,
    "wof:name":"Opovo",
    "wof:placetype":"locality",
    "wof:population":4769
},
  "geometry": {"coordinates":[20.43028,45.05222],"type":"Point"}
}