{
  "type": "Feature",
  "properties": {
    "gn:admin1_code":"SE",
    "gn:admin2_code":"16",
    "gn:asciiname":"Ziokovici",
    "gn:country_code":"RS",
    "gn:dem":549,
    "gn:feature_class":"P",
    "gn:feature_code":"PPL",
    "gn:name":"Ziokovici",
    "gn:population":0,
    "gn:timezone":"Europe/Belgrade",
    "iso:country":"RS",
    "wof:name":"Ziokovici",
    "wof:placetype":"locality"
},
  "geometry": {"coordinates":[19.60306,43.61083],"type":"Point"}
}