{
  "type": "Feature",
  "properties": {
    "gn:admin1_code":"SE",
    "gn:admin2_code":"20",
    "gn:asciiname":"Arbanasce",
    "gn:country_code":"RS",
    "gn:dem":322,
    "gn:feature_class":"P",
    "gn:feature_code":"PPL",
    "gn:name":"Arbanasce",
    "gn:population":0,
    "gn:timezone":"Europe/Belgrade",
    "iso:country":"RS",
    "name:ceb_x_preferred":[
        "Arbanasce"
    ],
    "name:fra_x_preferred":[
        "Arbanasce"
    ],
    "name:msa_x_preferred":[
        "Arbanasce"
    ],
    "name:por_x_preferred":[
        "Arbanasce"
    ],
    "name:slv_x_preferred":[
        "Arbanasce"
    ],
    "name:sqi_x_preferred":[
        "Arbanashca"
    ],
    "name:srp_x_preferred":[
        "Arbanasce"
    ],
    "name:srp_x_variant":[
        "\u0410\u0440\u0431\u0430\u043d\u0430\u0441\u0446\u0435"
    ],
    "name:und_x_variant":[
        "Arbanasci"
    ],
    "wof:name":"Arbanasce",
    "wof:placetype":"locality"
},
  "geometry": {"coordinates":[21.63772,43.27399000000001],"type":"Point"}
}