{
  "type": "Feature",
  "properties": {
    "gn:admin1_code":"SE",
    "gn:admin2_code":"16",
    "gn:asciiname":"Ilici",
    "gn:country_code":"RS",
    "gn:dem":655,
    "gn:feature_class":"P",
    "gn:feature_code":"PPL",
    "gn:name":"Ili\u0107i",
    "gn:population":0,
    "gn:timezone":"Europe/Belgrade",
    "iso:country":"RS",
    "name:ceb_x_preferred":[
        "Ilici"
    ],
    "name:swe_x_preferred":[
        "Ilici"
    ],
    "wof:name":"Ilici",
    "wof:placetype":"locality"
},
  "geometry": {"coordinates":[19.77833,44.04778],"type":"Point"}
}