{
  "type": "Feature",
  "properties": {
    "gn:admin1_code":"SE",
    "gn:admin2_code":"19",
    "gn:asciiname":"Razbojna",
    "gn:country_code":"RS",
    "gn:dem":312,
    "gn:feature_class":"P",
    "gn:feature_code":"PPL",
    "gn:name":"Razbojna",
    "gn:population":0,
    "gn:timezone":"Europe/Belgrade",
    "iso:country":"RS",
    "name:srp_x_preferred":[
        "Razbojna"
    ],
    "wof:name":"Razbojna",
    "wof:placetype":"locality"
},
  "geometry": {"coordinates":[21.1659,43.3471],"type":"Point"}
}