{
  "type": "Feature",
  "properties": {
    "gn:admin1_code":"SE",
    "gn:admin2_code":"19",
    "gn:asciiname":"Razbojna",
    "gn:country_code":"RS",
    "gn:dem":312,
    "gn:feature_class":"P",
    "gn:feature_code":"PPL",
    "gn:name":"Razbojna",
    "gn:population":0,
    "gn:timezone":"Europe/Belgrade",
    "iso:country":"RS",
    "name:ceb_x_preferred":[
        "Razbojna"
    ],
    "name:fra_x_preferred":[
        "Razbojna"
    ],
    "name:msa_x_preferred":[
        "Razbojna"
    ],
    "name:nld_x_preferred":[
        "Razbojna"
    ],
    "name:por_x_preferred":[
        "Razbojna"
    ],
    "name:slv_x_preferred":[
        "Razbojna"
    ],
    "name:srp_x_preferred":[
        "Razbojna"
    ],
    "name:srp_x_variant":[
        "\u0420\u0430\u0437\u0431\u043e\u0458\u043d\u0430"
    ],
    "wof:name":"Razbojna",
    "wof:placetype":"locality"
},
  "geometry": {"coordinates":[21.1659,43.3471],"type":"Point"}
}