{
  "type": "Feature",
  "properties": {
    "gn:admin1_code":"VO",
    "gn:admin2_code":"7",
    "gn:asciiname":"Martinci",
    "gn:country_code":"RS",
    "gn:dem":79,
    "gn:feature_class":"P",
    "gn:feature_code":"PPL",
    "gn:name":"Martinci",
    "gn:population":0,
    "gn:timezone":"Europe/Belgrade",
    "iso:country":"RS",
    "name:cat_x_preferred":[
        "Martinci"
    ],
    "name:ceb_x_preferred":[
        "Martinci"
    ],
    "name:epo_x_preferred":[
        "Martinci"
    ],
    "name:fra_x_preferred":[
        "Martinci"
    ],
    "name:hun_x_preferred":[
        "Sz\u00e1vaszentm\u00e1rton"
    ],
    "name:hye_x_preferred":[
        "\u0544\u0561\u0580\u057f\u056b\u0576\u0581\u056b"
    ],
    "name:msa_x_preferred":[
        "Martinci"
    ],
    "name:rus_x_preferred":[
        "\u041c\u0430\u0440\u0442\u0438\u043d\u0446\u0438"
    ],
    "name:slv_x_preferred":[
        "Martinci"
    ],
    "name:spa_x_preferred":[
        "Martinci"
    ],
    "name:srp_x_preferred":[
        "Martinci"
    ],
    "name:srp_x_variant":[
        "\u041c\u0430\u0440\u0442\u0438\u043d\u0446\u0438"
    ],
    "name:swe_x_preferred":[
        "Martinci"
    ],
    "wof:name":"Martinci",
    "wof:placetype":"locality"
},
  "geometry": {"coordinates":[19.45974,45.01116],"type":"Point"}
}