{
  "type": "Feature",
  "properties": {
    "gn:admin1_code":"SE",
    "gn:admin2_code":"18",
    "gn:asciiname":"Mrkonje",
    "gn:country_code":"RS",
    "gn:dem":922,
    "gn:feature_class":"P",
    "gn:feature_code":"PPL",
    "gn:name":"Mrkonje",
    "gn:population":0,
    "gn:timezone":"Europe/Belgrade",
    "iso:country":"RS",
    "name:fra_x_preferred":[
        "Mrkonje"
    ],
    "name:msa_x_preferred":[
        "Mrkonje"
    ],
    "name:por_x_preferred":[
        "Mrkonje"
    ],
    "name:slv_x_preferred":[
        "Mrkonje"
    ],
    "name:sqi_x_preferred":[
        "M\u00ebrkoja"
    ],
    "name:srp_x_preferred":[
        "Mrkonje"
    ],
    "name:srp_x_variant":[
        "\u041c\u0440\u043a\u043e\u045a\u0435"
    ],
    "wof:name":"Mrkonje",
    "wof:placetype":"locality"
},
  "geometry": {"coordinates":[20.43068,43.00353],"type":"Point"}
}