{
  "type": "Feature",
  "properties": {
    "gn:admin1_code":"SE",
    "gn:admin2_code":"9",
    "gn:asciiname":"Bobova",
    "gn:country_code":"RS",
    "gn:dem":461,
    "gn:feature_class":"P",
    "gn:feature_code":"PPLL",
    "gn:name":"Bobova",
    "gn:population":0,
    "gn:timezone":"Europe/Belgrade",
    "iso:country":"RS",
    "name:ceb_x_preferred":[
        "Bobova"
    ],
    "name:ell_x_preferred":[
        "\u039c\u03c0\u03cc\u03bc\u03c0\u03bf\u03b2\u03b1"
    ],
    "name:fra_x_preferred":[
        "Bobova"
    ],
    "name:msa_x_preferred":[
        "Bobova"
    ],
    "name:nld_x_preferred":[
        "Bobova"
    ],
    "name:por_x_preferred":[
        "Bobova"
    ],
    "name:slv_x_preferred":[
        "Bobova"
    ],
    "name:srp_x_preferred":[
        "Bobova"
    ],
    "name:srp_x_variant":[
        "\u0411\u043e\u0431\u043e\u0432\u0430"
    ],
    "name:und_x_variant":[
        "Bobov"
    ],
    "wof:name":"Bobova",
    "wof:placetype":"locality"
},
  "geometry": {"coordinates":[19.71305,44.2556],"type":"Point"}
}