{
  "type": "Feature",
  "properties": {
    "gn:admin1_code":"SE",
    "gn:admin2_code":"0",
    "gn:asciiname":"Mali Crljeni",
    "gn:country_code":"RS",
    "gn:dem":189,
    "gn:feature_class":"P",
    "gn:feature_code":"PPL",
    "gn:name":"Mali Crljeni",
    "gn:population":0,
    "gn:timezone":"Europe/Belgrade",
    "iso:country":"RS",
    "name:srp_x_preferred":[
        "Mali Crljeni"
    ],
    "name:und_x_variant":[
        "Crljeni",
        "Mali Crljenci"
    ],
    "wof:name":"Mali Crljeni",
    "wof:placetype":"locality"
},
  "geometry": {"coordinates":[20.37873,44.3849],"type":"Point"}
}