{
  "type": "Feature",
  "properties": {
    "gn:admin1_code":"SE",
    "gn:admin2_code":"8",
    "gn:asciiname":"Makevici",
    "gn:country_code":"RS",
    "gn:dem":165,
    "gn:feature_class":"P",
    "gn:feature_code":"PPL",
    "gn:name":"Makevi\u0107i",
    "gn:population":0,
    "gn:timezone":"Europe/Belgrade",
    "iso:country":"RS",
    "name:srp_x_preferred":[
        "Makevi\u0107i"
    ],
    "wof:name":"Makevici",
    "wof:placetype":"locality"
},
  "geometry": {"coordinates":[19.63862,44.60931],"type":"Point"}
}