{
  "type": "Feature",
  "properties": {
    "gn:admin1_code":"SE",
    "gn:admin2_code":"18",
    "gn:asciiname":"Trostica",
    "gn:country_code":"RS",
    "gn:dem":1032,
    "gn:feature_class":"P",
    "gn:feature_code":"PPL",
    "gn:name":"Tro\u0161tica",
    "gn:population":0,
    "gn:timezone":"Europe/Belgrade",
    "iso:country":"RS",
    "name:srp_x_preferred":[
        "Tro\u0161tica"
    ],
    "wof:name":"Trostica",
    "wof:placetype":"locality"
},
  "geometry": {"coordinates":[20.31838,43.2333],"type":"Point"}
}