{
  "type": "Feature",
  "properties": {
    "gn:admin1_code":"SE",
    "gn:admin2_code":"16",
    "gn:asciiname":"Zaseoci",
    "gn:country_code":"RS",
    "gn:dem":681,
    "gn:feature_class":"P",
    "gn:feature_code":"PPL",
    "gn:name":"Zaseoci",
    "gn:population":0,
    "gn:timezone":"Europe/Belgrade",
    "iso:country":"RS",
    "wof:name":"Zaseoci",
    "wof:placetype":"locality"
},
  "geometry": {"coordinates":[19.30444,43.48861],"type":"Point"}
}