{
  "type": "Feature",
  "properties": {
    "gn:admin1_code":"SE",
    "gn:admin2_code":"20",
    "gn:asciiname":"Aleksinacki Rudnici Uglja",
    "gn:country_code":"RS",
    "gn:dem":206,
    "gn:feature_class":"P",
    "gn:feature_code":"PPL",
    "gn:name":"Aleksina\u010dki Rudnici Uglja",
    "gn:population":0,
    "gn:timezone":"Europe/Belgrade",
    "iso:country":"RS",
    "name:srp_x_preferred":[
        "Aleksina\u010dki Rudnici Uglja"
    ],
    "wof:name":"Aleksinacki Rudnici Uglja",
    "wof:placetype":"locality"
},
  "geometry": {"coordinates":[21.69139,43.55806],"type":"Point"}
}