{
  "type": "Feature",
  "properties": {
    "gn:country":"RS",
    "gn:fcode":"PPL",
    "gn:pop":3192,
    "iso:country":"RS",
    "name:deu_x_preferred":[
        "\u010centa"
    ],
    "name:eng_x_preferred":[
        "\u010centa"
    ],
    "name:epo_x_preferred":[
        "\u0108enta"
    ],
    "name:fra_x_preferred":[
        "\u010centa"
    ],
    "name:hrv_x_preferred":[
        "\u010centa"
    ],
    "name:hun_x_preferred":[
        "Csenta"
    ],
    "name:msa_x_preferred":[
        "\u010centa"
    ],
    "name:nld_x_preferred":[
        "\u010centa"
    ],
    "name:ron_x_preferred":[
        "\u010centa"
    ],
    "name:rus_x_preferred":[
        "\u0427\u0435\u043d\u0442\u0430"
    ],
    "name:slv_x_preferred":[
        "\u010centa"
    ],
    "name:srp_x_preferred":[
        "\u010centa"
    ],
    "name:unk_x_variant":[
        "Leopoldova"
    ],
    "qs:name":"\u010centa",
    "qs:name_adm0":"Serbia",
    "qs:name_adm1":"Beograd",
    "qs:photos_9r":0,
    "qs:photos_sr":0,
    "qs:placetype":"Town",
    "qs:pop_sr":"4",
    "wd:wordcount":99,
    "wof:name":"\u010centa",
    "wof:placetype":"locality",
    "wof:population":3192
},
  "geometry": {"coordinates":[20.38946,45.10814],"type":"Point"}
}