{
  "type": "Feature",
  "properties": {
    "gn:country":"RS",
    "gn:fcode":"PPLA3",
    "gn:population":32229,
    "iso:country":"RS",
    "name:bel_x_preferred":[
        "\u0413\u043e\u0440\u0430\u0434 \u0420\u0443\u043c\u0430"
    ],
    "name:bel_x_variant":[
        "\u0420\u0443\u043c\u0430"
    ],
    "name:bos_x_preferred":[
        "Ruma"
    ],
    "name:ceb_x_preferred":[
        "Ruma"
    ],
    "name:ces_x_preferred":[
        "Ruma"
    ],
    "name:ckb_x_preferred":[
        "\u0695\u0648\u0645\u0627"
    ],
    "name:deu_x_preferred":[
        "Ruma"
    ],
    "name:ell_x_preferred":[
        "\u03a1\u03bf\u03cd\u03bc\u03b1"
    ],
    "name:eng_x_preferred":[
        "Ruma"
    ],
    "name:epo_x_preferred":[
        "Ruma"
    ],
    "name:fas_x_preferred":[
        "\u0631\u0648\u0645\u0627"
    ],
    "name:fin_x_preferred":[
        "Ruma"
    ],
    "name:fra_x_preferred":[
        "Ruma"
    ],
    "name:heb_x_preferred":[
        "\u05e8\u05d5\u05de\u05d4"
    ],
    "name:hrv_x_preferred":[
        "Ruma"
    ],
    "name:hun_x_preferred":[
        "\u00c1rpatarl\u00f3"
    ],
    "name:hun_x_variant":[
        "Ruma"
    ],
    "name:ita_x_preferred":[
        "Ruma"
    ],
    "name:jpn_x_preferred":[
        "\u30eb\u30de"
    ],
    "name:kor_x_preferred":[
        "\ub8e8\ub9c8"
    ],
    "name:lit_x_preferred":[
        "Ruma"
    ],
    "name:mkd_x_preferred":[
        "\u0420\u0443\u043c\u0430"
    ],
    "name:msa_x_preferred":[
        "Ruma"
    ],
    "name:nld_x_preferred":[
        "Ruma"
    ],
    "name:pnb_x_preferred":[
        "\u0631\u0648\u0645\u0627 \u060c\u0633\u0631\u0628\u06cc\u0627"
    ],
    "name:pol_x_preferred":[
        "Ruma"
    ],
    "name:por_x_preferred":[
        "Ruma"
    ],
    "name:rus_x_preferred":[
        "\u0420\u0443\u043c\u0430"
    ],
    "name:slv_x_preferred":[
        "Ruma"
    ],
    "name:spa_x_preferred":[
        "Ruma"
    ],
    "name:srp_x_preferred":[
        "Ruma"
    ],
    "name:srp_x_variant":[
        "\u0420\u0443\u043c\u0430"
    ],
    "name:swe_x_preferred":[
        "Ruma"
    ],
    "name:tha_x_preferred":[
        "\u0e23\u0e39\u0e21\u0e32"
    ],
    "name:tur_x_preferred":[
        "Ruma"
    ],
    "name:vie_x_preferred":[
        "Ruma"
    ],
    "name:zho_x_preferred":[
        "\u9b6f\u99ac"
    ],
    "qs:name":"Ruma",
    "qs:photos_9r":0,
    "qs:photos_sr":0,
    "qs:pop_sr":"7",
    "wd:wordcount":881,
    "wof:name":"Ruma",
    "wof:placetype":"locality",
    "wof:population":32229
},
  "geometry": {"coordinates":[19.82222,45.00806],"type":"Point"}
}