{
  "type": "Feature",
  "properties": {
    "gn:admin1_code":"SE",
    "gn:admin2_code":"21",
    "gn:asciiname":"Donja Rasica",
    "gn:country_code":"RS",
    "gn:dem":468,
    "gn:feature_class":"P",
    "gn:feature_code":"PPL",
    "gn:name":"Donja Ra\u0161ica",
    "gn:population":0,
    "gn:timezone":"Europe/Belgrade",
    "iso:country":"RS",
    "name:srp_x_preferred":[
        "Donja Ra\u0161ica"
    ],
    "name:und_x_variant":[
        "D\u017eukela"
    ],
    "wof:name":"Donja Rasica",
    "wof:placetype":"locality"
},
  "geometry": {"coordinates":[21.22612,43.28282],"type":"Point"}
}