{
  "type": "Feature",
  "properties": {
    "gn:admin1_code":"SE",
    "gn:admin2_code":"21",
    "gn:asciiname":"Lukomir",
    "gn:country_code":"RS",
    "gn:dem":271,
    "gn:feature_class":"P",
    "gn:feature_code":"PPL",
    "gn:name":"Lukomir",
    "gn:population":0,
    "gn:timezone":"Europe/Belgrade",
    "iso:country":"RS",
    "name:srp_x_preferred":[
        "Lukomir"
    ],
    "wof:name":"Lukomir",
    "wof:placetype":"locality"
},
  "geometry": {"coordinates":[21.6693,43.195],"type":"Point"}
}