{
  "type": "Feature",
  "properties": {
    "gn:admin1_code":"SE",
    "gn:admin2_code":"21",
    "gn:asciiname":"Lukomir",
    "gn:country_code":"RS",
    "gn:dem":271,
    "gn:feature_class":"P",
    "gn:feature_code":"PPL",
    "gn:name":"Lukomir",
    "gn:population":0,
    "gn:timezone":"Europe/Belgrade",
    "iso:country":"RS",
    "name:ara_x_preferred":[
        "\u0644\u0648\u0643\u0648\u0645\u064a\u0631"
    ],
    "name:bos_x_preferred":[
        "Lukomir"
    ],
    "name:deu_x_preferred":[
        "Lukomir"
    ],
    "name:fas_x_preferred":[
        "\u0644\u0648\u06a9\u0648\u0645\u06cc\u0631"
    ],
    "name:fra_x_preferred":[
        "Lukomir"
    ],
    "name:hrv_x_preferred":[
        "Lukomir"
    ],
    "name:srp_x_preferred":[
        "Lukomir"
    ],
    "name:srp_x_variant":[
        "\u041b\u0443\u043a\u043e\u043c\u0438\u0440"
    ],
    "wof:name":"Lukomir",
    "wof:placetype":"locality"
},
  "geometry": {"coordinates":[21.6693,43.195],"type":"Point"}
}