{
  "type": "Feature",
  "properties": {
    "gn:admin1_code":"SE",
    "gn:admin2_code":"11",
    "gn:admin3_code":"70521.0",
    "gn:asciiname":"Aleksandrovac",
    "gn:country_code":"RS",
    "gn:dem":96,
    "gn:feature_class":"P",
    "gn:feature_code":"PPL",
    "gn:name":"Aleksandrovac",
    "gn:population":0,
    "gn:timezone":"Europe/Belgrade",
    "iso:country":"RS",
    "name:ceb_x_preferred":[
        "Aleksandrovac"
    ],
    "name:fas_x_preferred":[
        "\u0627\u0644\u06a9\u0633\u0627\u0646\u062f\u0631\u0627\u0648\u0627\u06a9"
    ],
    "name:fra_x_preferred":[
        "Aleksandrovac"
    ],
    "name:msa_x_preferred":[
        "Aleksandrovac"
    ],
    "name:por_x_preferred":[
        "Aleksandrovac"
    ],
    "name:slv_x_preferred":[
        "Aleksandrovac"
    ],
    "name:srp_x_preferred":[
        "Aleksandrovac"
    ],
    "name:srp_x_variant":[
        "\u0410\u043b\u0435\u043a\u0441\u0430\u043d\u0434\u0440\u043e\u0432\u0430\u0446"
    ],
    "name:und_x_variant":[
        "Prhovo"
    ],
    "wof:name":"Aleksandrovac",
    "wof:placetype":"locality"
},
  "geometry": {"coordinates":[21.2131,44.44925],"type":"Point"}
}