{
  "type": "Feature",
  "properties": {
    "gn:admin1_code":"SE",
    "gn:admin2_code":"11",
    "gn:admin3_code":"70521.0",
    "gn:asciiname":"Aleksandrovac",
    "gn:country_code":"RS",
    "gn:dem":96,
    "gn:feature_class":"P",
    "gn:feature_code":"PPL",
    "gn:name":"Aleksandrovac",
    "gn:population":0,
    "gn:timezone":"Europe/Belgrade",
    "iso:country":"RS",
    "name:srp_x_preferred":[
        "Aleksandrovac"
    ],
    "name:und_x_variant":[
        "Prhovo"
    ],
    "wof:name":"Aleksandrovac",
    "wof:placetype":"locality"
},
  "geometry": {"coordinates":[21.2131,44.44925],"type":"Point"}
}