{
  "type": "Feature",
  "properties": {
    "gn:country":"RS",
    "gn:fcode":"PPLL",
    "gn:pop":141,
    "iso:country":"RS",
    "name:ceb_x_preferred":[
        "Gornja Beja\u0161nica"
    ],
    "name:eng_x_preferred":[
        "Gornja Beja\u0161nica"
    ],
    "name:fra_x_preferred":[
        "Gornja Beja\u0161nica"
    ],
    "name:msa_x_preferred":[
        "Gornja Beja\u0161nica"
    ],
    "name:nld_x_preferred":[
        "Gornja Beja\u0161nica"
    ],
    "name:por_x_preferred":[
        "Gornja Beja\u0161nica"
    ],
    "name:slv_x_preferred":[
        "Gornja Beja\u0161nica"
    ],
    "name:sqi_x_preferred":[
        "Bajishtica e Ep\u00ebrme"
    ],
    "name:srp_x_preferred":[
        "Gornja Beja\u0161nica"
    ],
    "name:srp_x_variant":[
        "\u0413\u043e\u0440\u045a\u0430 \u0411\u0435\u0458\u0430\u0448\u043d\u0438\u0446\u0430"
    ],
    "name:unk_x_variant":[
        "Gornja Beja\u0161ica"
    ],
    "qs:name":"Gornja Beja\u0161nica",
    "qs:photos_9r":0,
    "qs:photos_sr":0,
    "qs:pop_sr":"1",
    "wd:wordcount":70,
    "wof:name":"Gornja Beja\u0161nica",
    "wof:placetype":"locality",
    "wof:population":141
},
  "geometry": {"coordinates":[21.46498,43.17417],"type":"Point"}
}