{
  "type": "Feature",
  "properties": {
    "gn:admin1_code":"SE",
    "gn:admin2_code":"8",
    "gn:asciiname":"Vlascic",
    "gn:country_code":"RS",
    "gn:dem":339,
    "gn:feature_class":"P",
    "gn:feature_code":"PPL",
    "gn:name":"Vla\u0161\u010di\u0107",
    "gn:population":0,
    "gn:timezone":"Europe/Belgrade",
    "iso:country":"RS",
    "name:srp_x_preferred":[
        "Vla\u0161\u010di\u0107"
    ],
    "wof:name":"Vlascic",
    "wof:placetype":"locality"
},
  "geometry": {"coordinates":[19.7726,44.4277],"type":"Point"}
}