{
  "type": "Feature",
  "properties": {
    "gn:admin1_code":"SE",
    "gn:admin2_code":"18",
    "gn:asciiname":"Detane",
    "gn:country_code":"RS",
    "gn:dem":970,
    "gn:feature_class":"P",
    "gn:feature_code":"PPL",
    "gn:name":"Detane",
    "gn:population":0,
    "gn:timezone":"Europe/Belgrade",
    "iso:country":"RS",
    "name:ceb_x_preferred":[
        "Detane"
    ],
    "name:fra_x_preferred":[
        "Detane"
    ],
    "name:hun_x_preferred":[
        "Detane"
    ],
    "name:msa_x_preferred":[
        "Detane"
    ],
    "name:nld_x_preferred":[
        "Detane"
    ],
    "name:por_x_preferred":[
        "Detane"
    ],
    "name:slv_x_preferred":[
        "Detane"
    ],
    "name:srp_x_preferred":[
        "Detane"
    ],
    "name:srp_x_variant":[
        "\u0414\u0435\u0442\u0430\u043d\u0435"
    ],
    "name:und_x_variant":[
        "De\u0161ane"
    ],
    "wof:name":"Detane",
    "wof:placetype":"locality"
},
  "geometry": {"coordinates":[20.27923,42.96892],"type":"Point"}
}