{
  "type": "Feature",
  "properties": {
    "gn:admin1_code":"SE",
    "gn:admin2_code":"17",
    "gn:asciiname":"Puhovo",
    "gn:country_code":"RS",
    "gn:dem":407,
    "gn:feature_class":"P",
    "gn:feature_code":"PPL",
    "gn:name":"Puhovo",
    "gn:population":0,
    "gn:timezone":"Europe/Belgrade",
    "iso:country":"RS",
    "name:bos_x_preferred":[
        "Puhovo"
    ],
    "name:fra_x_preferred":[
        "Puhovo"
    ],
    "name:hun_x_preferred":[
        "Puhovo"
    ],
    "name:slv_x_preferred":[
        "Puhovo"
    ],
    "name:srp_x_preferred":[
        "Puhovo"
    ],
    "wof:name":"Puhovo",
    "wof:placetype":"locality"
},
  "geometry": {"coordinates":[20.1981,43.82612],"type":"Point"}
}