{
  "type": "Feature",
  "properties": {
    "gn:admin1_code":"SE",
    "gn:admin2_code":"24",
    "gn:asciiname":"Kopitarce",
    "gn:country_code":"RS",
    "gn:dem":668,
    "gn:feature_class":"P",
    "gn:feature_code":"PPL",
    "gn:name":"Kopitarce",
    "gn:population":0,
    "gn:timezone":"Europe/Belgrade",
    "iso:country":"RS",
    "name:srp_x_preferred":[
        "Kopitarce"
    ],
    "wof:name":"Kopitarce",
    "wof:placetype":"locality"
},
  "geometry": {"coordinates":[22.10663,42.77541],"type":"Point"}
}