{
  "type": "Feature",
  "properties": {
    "gn:admin1_code":"SE",
    "gn:admin2_code":"24",
    "gn:asciiname":"Kolarska Mahala",
    "gn:country_code":"RS",
    "gn:dem":780,
    "gn:feature_class":"P",
    "gn:feature_code":"PPL",
    "gn:name":"Kolarska Mahala",
    "gn:population":0,
    "gn:timezone":"Europe/Belgrade",
    "iso:country":"RS",
    "name:srp_x_preferred":[
        "Kolarska Mahala"
    ],
    "wof:name":"Kolarska Mahala",
    "wof:placetype":"locality"
},
  "geometry": {"coordinates":[22.00981,42.52833],"type":"Point"}
}