{
  "type": "Feature",
  "properties": {
    "gn:admin1_code":"SE",
    "gn:admin2_code":"24",
    "gn:asciiname":"Kovacevska Mahala",
    "gn:country_code":"RS",
    "gn:dem":645,
    "gn:feature_class":"P",
    "gn:feature_code":"PPL",
    "gn:name":"Kova\u010devska Mahala",
    "gn:population":0,
    "gn:timezone":"Europe/Belgrade",
    "iso:country":"RS",
    "wof:name":"Kovacevska Mahala",
    "wof:placetype":"locality"
},
  "geometry": {"coordinates":[21.8558,42.38317],"type":"Point"}
}