{
  "type": "Feature",
  "properties": {
    "iso:country":"RS",
    "name:eng_x_preferred":[
        "Bulbulder"
    ],
    "name:srp_cyr_x_preferred":[
        "\u0411\u0443\u043b\u0431\u0443\u043b\u0434\u0435\u0440"
    ],
    "name:srp_lat_x_variant":[
        "Bulbuder"
    ],
    "wof:name":"Bulbulder",
    "wof:placetype":"neighbourhood"
},
  "geometry": {"coordinates":[20.4923612138252,44.80332975770526],"type":"Point"}
}