{
  "type": "Feature",
  "properties": {
    "gn:admin1_code":"SE",
    "gn:admin2_code":"0",
    "gn:asciiname":"Vlaska",
    "gn:country_code":"RS",
    "gn:dem":254,
    "gn:feature_class":"P",
    "gn:feature_code":"PPL",
    "gn:name":"Vla\u0161ka",
    "gn:population":0,
    "gn:timezone":"Europe/Belgrade",
    "iso:country":"RS",
    "name:srp_x_preferred":[
        "Vla\u0161ka"
    ],
    "wof:name":"Vlaska",
    "wof:placetype":"locality"
},
  "geometry": {"coordinates":[20.6873,44.50032],"type":"Point"}
}