{
  "type": "Feature",
  "properties": {
    "gn:admin1_code":"VO",
    "gn:admin2_code":"7",
    "gn:asciiname":"Prnjavor",
    "gn:country_code":"RS",
    "gn:dem":202,
    "gn:feature_class":"P",
    "gn:feature_code":"PPL",
    "gn:name":"Prnjavor",
    "gn:population":35,
    "gn:timezone":"Europe/Belgrade",
    "iso:country":"RS",
    "name:srp_x_preferred":[
        "Prnjavor"
    ],
    "name:und_x_variant":[
        "Kru\u0161edol Prnjavor",
        "Kru\u0161edolski Prnjavor",
        "Krushedol",
        "Krussedol"
    ],
    "wof:name":"Prnjavor",
    "wof:placetype":"locality",
    "wof:population":35
},
  "geometry": {"coordinates":[19.93631,45.11937],"type":"Point"}
}