{
  "type": "Feature",
  "properties": {
    "gn:admin1_code":"VO",
    "gn:admin2_code":"7",
    "gn:asciiname":"Prnjavor",
    "gn:country_code":"RS",
    "gn:dem":202,
    "gn:feature_class":"P",
    "gn:feature_code":"PPL",
    "gn:name":"Prnjavor",
    "gn:population":35,
    "gn:timezone":"Europe/Belgrade",
    "iso:country":"RS",
    "name:epo_x_preferred":[
        "Kru\u015dedol Prnjavor"
    ],
    "name:fra_x_preferred":[
        "Kru\u0161edol Prnjavor"
    ],
    "name:hun_x_preferred":[
        "Kru\u0161edol Prnjavor"
    ],
    "name:msa_x_preferred":[
        "Kru\u0161edol Prnjavor"
    ],
    "name:rus_x_preferred":[
        "\u041a\u0440\u0443\u0448\u0435\u0434\u043e\u043b-\u041f\u0440\u043d\u044f\u0432\u043e\u0440"
    ],
    "name:slv_x_preferred":[
        "Kru\u0161edol Prnjavor"
    ],
    "name:srp_x_preferred":[
        "Prnjavor"
    ],
    "name:srp_x_variant":[
        "\u041a\u0440\u0443\u0448\u0435\u0434\u043e\u043b \u041f\u0440\u045a\u0430\u0432\u043e\u0440"
    ],
    "name:und_x_variant":[
        "Kru\u0161edolski Prnjavor",
        "Krushedol",
        "Krussedol"
    ],
    "wof:name":"Prnjavor",
    "wof:placetype":"locality",
    "wof:population":35
},
  "geometry": {"coordinates":[19.93631,45.11937],"type":"Point"}
}