{
  "type": "Feature",
  "properties": {
    "gn:admin1_code":"SE",
    "gn:admin2_code":"17",
    "gn:asciiname":"Kostici",
    "gn:country_code":"RS",
    "gn:dem":556,
    "gn:feature_class":"P",
    "gn:feature_code":"PPL",
    "gn:name":"Kosti\u0107i",
    "gn:population":0,
    "gn:timezone":"Europe/Belgrade",
    "iso:country":"RS",
    "name:srp_x_preferred":[
        "Kosti\u0107i"
    ],
    "wof:name":"Kostici",
    "wof:placetype":"locality"
},
  "geometry": {"coordinates":[20.23444,43.74194],"type":"Point"}
}