{
  "type": "Feature",
  "properties": {
    "gn:country":"RS",
    "gn:fcode":"PPL",
    "gn:population":5,
    "iso:country":"RS",
    "name:srp_x_preferred":[
        "Garina"
    ],
    "qs:name":"Garina",
    "qs:photos_9r":0,
    "qs:photos_sr":0,
    "qs:pop_sr":"1",
    "wof:name":"Garina",
    "wof:placetype":"locality",
    "wof:population":5
},
  "geometry": {"coordinates":[20.44222,43.52278],"type":"Point"}
}