{
  "type": "Feature",
  "properties": {
    "gn:admin1_code":"SE",
    "gn:admin2_code":"24",
    "gn:asciiname":"Grncari",
    "gn:country_code":"RS",
    "gn:dem":1340,
    "gn:feature_class":"P",
    "gn:feature_code":"PPL",
    "gn:name":"Grn\u010dari",
    "gn:population":0,
    "gn:timezone":"Europe/Belgrade",
    "iso:country":"RS",
    "wof:name":"Grncari",
    "wof:placetype":"locality"
},
  "geometry": {"coordinates":[22.27628,42.45913],"type":"Point"}
}