{
  "type": "Feature",
  "properties": {
    "gn:admin1_code":"SE",
    "gn:admin2_code":"17",
    "gn:asciiname":"Gornja Glegica",
    "gn:country_code":"RS",
    "gn:dem":970,
    "gn:feature_class":"P",
    "gn:feature_code":"PPLL",
    "gn:name":"Gornja Gle\u0111ica",
    "gn:population":0,
    "gn:timezone":"Europe/Belgrade",
    "iso:country":"RS",
    "name:srp_x_preferred":[
        "Gornja Gle\u0111ica"
    ],
    "wof:name":"Gornja Glegica",
    "wof:placetype":"locality"
},
  "geometry": {"coordinates":[20.2409,43.41421],"type":"Point"}
}