{
  "type": "Feature",
  "properties": {
    "gn:admin1_code":"SE",
    "gn:admin2_code":"16",
    "gn:asciiname":"Brezak",
    "gn:country_code":"RS",
    "gn:dem":666,
    "gn:feature_class":"P",
    "gn:feature_code":"PPL",
    "gn:name":"Brezak",
    "gn:population":0,
    "gn:timezone":"Europe/Belgrade",
    "iso:country":"RS",
    "name:srp_x_preferred":[
        "Brezak"
    ],
    "wof:name":"Brezak",
    "wof:placetype":"locality"
},
  "geometry": {"coordinates":[19.72778,43.78639],"type":"Point"}
}