{
  "type": "Feature",
  "properties": {
    "gn:admin1_code":"SE",
    "gn:admin2_code":"18",
    "gn:asciiname":"Plavkovo",
    "gn:country_code":"RS",
    "gn:dem":554,
    "gn:feature_class":"P",
    "gn:feature_code":"PPLL",
    "gn:name":"Plavkovo",
    "gn:population":0,
    "gn:timezone":"Europe/Belgrade",
    "iso:country":"RS",
    "name:fra_x_preferred":[
        "Plavkovo"
    ],
    "name:msa_x_preferred":[
        "Plavkovo"
    ],
    "name:nld_x_preferred":[
        "Plavkovo"
    ],
    "name:por_x_preferred":[
        "Plavkovo"
    ],
    "name:slv_x_preferred":[
        "Plavkovo"
    ],
    "name:srp_x_preferred":[
        "Plavkovo"
    ],
    "name:srp_x_variant":[
        "\u041f\u043b\u0430\u0432\u043a\u043e\u0432\u043e"
    ],
    "wof:name":"Plavkovo",
    "wof:placetype":"locality"
},
  "geometry": {"coordinates":[20.66959,43.22711],"type":"Point"}
}