{
  "type": "Feature",
  "properties": {
    "gn:admin1_code":"SE",
    "gn:admin2_code":"14",
    "gn:asciiname":"Vlaole",
    "gn:country_code":"RS",
    "gn:dem":435,
    "gn:feature_class":"P",
    "gn:feature_code":"PPL",
    "gn:name":"Vlaole",
    "gn:population":0,
    "gn:timezone":"Europe/Belgrade",
    "iso:country":"RS",
    "name:srp_x_preferred":[
        "Vlaole"
    ],
    "wof:name":"Vlaole",
    "wof:placetype":"locality"
},
  "geometry": {"coordinates":[21.9847,44.26822],"type":"Point"}
}