{
  "type": "Feature",
  "properties": {
    "gn:admin1_code":"SE",
    "gn:admin2_code":"23",
    "gn:asciiname":"Rajcetina",
    "gn:country_code":"RS",
    "gn:dem":1072,
    "gn:feature_class":"P",
    "gn:feature_code":"PPL",
    "gn:name":"Raj\u010detina",
    "gn:population":0,
    "gn:timezone":"Europe/Belgrade",
    "iso:country":"RS",
    "name:srp_x_preferred":[
        "Raj\u010detina"
    ],
    "wof:name":"Rajcetina",
    "wof:placetype":"locality"
},
  "geometry": {"coordinates":[22.24133,42.83641],"type":"Point"}
}