{
  "type": "Feature",
  "properties": {
    "gn:admin1_code":"SE",
    "gn:admin2_code":"8",
    "gn:asciiname":"Beljin",
    "gn:country_code":"RS",
    "gn:dem":80,
    "gn:feature_class":"P",
    "gn:feature_code":"PPLL",
    "gn:name":"Beljin",
    "gn:population":0,
    "gn:timezone":"Europe/Belgrade",
    "iso:country":"RS",
    "name:srp_x_preferred":[
        "Beljin"
    ],
    "wof:name":"Beljin",
    "wof:placetype":"locality"
},
  "geometry": {"coordinates":[19.96167,44.6271],"type":"Point"}
}