{
  "type": "Feature",
  "properties": {
    "gn:admin1_code":"SE",
    "gn:admin2_code":"8",
    "gn:asciiname":"Jelasine",
    "gn:country_code":"RS",
    "gn:dem":332,
    "gn:feature_class":"P",
    "gn:feature_code":"PPL",
    "gn:name":"Jela\u0161ine",
    "gn:population":0,
    "gn:timezone":"Europe/Belgrade",
    "iso:country":"RS",
    "wof:name":"Jelasine",
    "wof:placetype":"locality"
},
  "geometry": {"coordinates":[19.50861,44.12111],"type":"Point"}
}