{
  "type": "Feature",
  "properties": {
    "gn:admin1_code":"SE",
    "gn:admin2_code":"16",
    "gn:asciiname":"Prijevici",
    "gn:country_code":"RS",
    "gn:dem":760,
    "gn:feature_class":"P",
    "gn:feature_code":"PPL",
    "gn:name":"Prijevi\u0107i",
    "gn:population":0,
    "gn:timezone":"Europe/Belgrade",
    "iso:country":"RS",
    "wof:name":"Prijevici",
    "wof:placetype":"locality"
},
  "geometry": {"coordinates":[19.81352,43.82399],"type":"Point"}
}