{
  "type": "Feature",
  "properties": {
    "gn:admin1_code":"SE",
    "gn:admin2_code":"16",
    "gn:asciiname":"Malo Pacadzije",
    "gn:country_code":"RS",
    "gn:dem":454,
    "gn:feature_class":"P",
    "gn:feature_code":"PPL",
    "gn:name":"Malo Pacad\u017eije",
    "gn:population":0,
    "gn:timezone":"Europe/Belgrade",
    "iso:country":"RS",
    "wof:name":"Malo Pacadzije",
    "wof:placetype":"locality"
},
  "geometry": {"coordinates":[19.65194,43.94028],"type":"Point"}
}