{
  "type": "Feature",
  "properties": {
    "gn:admin1_code":"VO",
    "gn:admin2_code":"7",
    "gn:asciiname":"Maradik",
    "gn:country_code":"RS",
    "gn:dem":161,
    "gn:feature_class":"P",
    "gn:feature_code":"PPL",
    "gn:name":"Maradik",
    "gn:population":0,
    "gn:timezone":"Europe/Belgrade",
    "iso:country":"RS",
    "name:srp_x_preferred":[
        "Maradik"
    ],
    "name:und_x_variant":[
        "Marad\u00e9k"
    ],
    "wof:name":"Maradik",
    "wof:placetype":"locality"
},
  "geometry": {"coordinates":[19.99284,45.10142000000001],"type":"Point"}
}