{
  "type": "Feature",
  "properties": {
    "gn:admin1_code":"VO",
    "gn:admin2_code":"7",
    "gn:asciiname":"Maradik",
    "gn:country_code":"RS",
    "gn:dem":161,
    "gn:feature_class":"P",
    "gn:feature_code":"PPL",
    "gn:name":"Maradik",
    "gn:population":0,
    "gn:timezone":"Europe/Belgrade",
    "iso:country":"RS",
    "name:ceb_x_preferred":[
        "Maradik"
    ],
    "name:epo_x_preferred":[
        "Maradik"
    ],
    "name:fra_x_preferred":[
        "Maradik"
    ],
    "name:hrv_x_preferred":[
        "Maradik"
    ],
    "name:hun_x_preferred":[
        "Marad\u00e9k"
    ],
    "name:msa_x_preferred":[
        "Maradik"
    ],
    "name:rus_x_preferred":[
        "\u041c\u0430\u0440\u0430\u0434\u0438\u043a"
    ],
    "name:slv_x_preferred":[
        "Maradik"
    ],
    "name:srp_x_preferred":[
        "Maradik"
    ],
    "name:srp_x_variant":[
        "\u041c\u0430\u0440\u0430\u0434\u0438\u043a"
    ],
    "wof:name":"Maradik",
    "wof:placetype":"locality"
},
  "geometry": {"coordinates":[19.99284,45.10142000000001],"type":"Point"}
}