{
  "type": "Feature",
  "properties": {
    "gn:admin1_code":"SE",
    "gn:admin2_code":"14",
    "gn:asciiname":"Urovica",
    "gn:country_code":"RS",
    "gn:dem":84,
    "gn:feature_class":"P",
    "gn:feature_code":"PPL",
    "gn:name":"Urovica",
    "gn:population":0,
    "gn:timezone":"Europe/Belgrade",
    "iso:country":"RS",
    "name:ceb_x_preferred":[
        "Urovica"
    ],
    "name:deu_x_preferred":[
        "Urovica"
    ],
    "name:fra_x_preferred":[
        "Urovica"
    ],
    "name:msa_x_preferred":[
        "Urovica"
    ],
    "name:por_x_preferred":[
        "Urovica"
    ],
    "name:slv_x_preferred":[
        "Urovica"
    ],
    "name:srp_x_preferred":[
        "Urovica"
    ],
    "name:srp_x_variant":[
        "\u0423\u0440\u043e\u0432\u0438\u0446\u0430"
    ],
    "wof:name":"Urovica",
    "wof:placetype":"locality"
},
  "geometry": {"coordinates":[22.40111,44.40028],"type":"Point"}
}