{
  "type": "Feature",
  "properties": {
    "gn:admin1_code":"SE",
    "gn:admin2_code":"17",
    "gn:asciiname":"Cetenovici",
    "gn:country_code":"RS",
    "gn:dem":1005,
    "gn:feature_class":"P",
    "gn:feature_code":"PPL",
    "gn:name":"Cetenovi\u0107i",
    "gn:population":0,
    "gn:timezone":"Europe/Belgrade",
    "iso:country":"RS",
    "name:srp_x_preferred":[
        "Cetenovi\u0107i"
    ],
    "wof:name":"Cetenovici",
    "wof:placetype":"locality"
},
  "geometry": {"coordinates":[20.10997,43.40598],"type":"Point"}
}