{
  "type": "Feature",
  "properties": {
    "gn:admin1_code":"SE",
    "gn:admin2_code":"23",
    "gn:asciiname":"Macedonce Retkocersko",
    "gn:country_code":"RS",
    "gn:dem":741,
    "gn:feature_class":"P",
    "gn:feature_code":"PPLL",
    "gn:name":"Ma\u0107edonce Retkocersko",
    "gn:population":0,
    "gn:timezone":"Europe/Belgrade",
    "iso:country":"RS",
    "name:srp_x_preferred":[
        "Ma\u0107edonce Retkocersko"
    ],
    "name:und_x_variant":[
        "Retkocer"
    ],
    "wof:name":"Macedonce Retkocersko",
    "wof:placetype":"locality"
},
  "geometry": {"coordinates":[21.52,42.83417],"type":"Point"}
}