{
  "type": "Feature",
  "properties": {
    "gn:admin1_code":"SE",
    "gn:admin2_code":"20",
    "gn:asciiname":"Sopotnica",
    "gn:country_code":"RS",
    "gn:dem":539,
    "gn:feature_class":"P",
    "gn:feature_code":"PPL",
    "gn:name":"Sopotnica",
    "gn:population":0,
    "gn:timezone":"Europe/Belgrade",
    "iso:country":"RS",
    "name:bos_x_preferred":[
        "Sopotnica"
    ],
    "name:bul_x_preferred":[
        "\u0421\u043e\u043f\u043e\u0442\u043d\u0438\u0446\u0430"
    ],
    "name:ceb_x_preferred":[
        "Sopotnica"
    ],
    "name:deu_x_preferred":[
        "Sopotnica"
    ],
    "name:fra_x_preferred":[
        "Sopotnica"
    ],
    "name:hrv_x_preferred":[
        "Sopotnica"
    ],
    "name:nld_x_preferred":[
        "Sopotnica"
    ],
    "name:pol_x_preferred":[
        "Sopotnica"
    ],
    "name:slk_x_preferred":[
        "Sopotnica"
    ],
    "name:slv_x_preferred":[
        "Sopotnica"
    ],
    "name:srp_x_preferred":[
        "Sopotnica"
    ],
    "name:srp_x_variant":[
        "\u0421\u043e\u043f\u043e\u0442\u043d\u0438\u0446\u0430"
    ],
    "name:swe_x_preferred":[
        "Sopotnica"
    ],
    "wof:name":"Sopotnica",
    "wof:placetype":"locality"
},
  "geometry": {"coordinates":[22.13592,43.16036],"type":"Point"}
}