{
  "type": "Feature",
  "properties": {
    "gn:admin1_code":"SE",
    "gn:admin2_code":"20",
    "gn:asciiname":"Sopotnica",
    "gn:country_code":"RS",
    "gn:dem":539,
    "gn:feature_class":"P",
    "gn:feature_code":"PPL",
    "gn:name":"Sopotnica",
    "gn:population":0,
    "gn:timezone":"Europe/Belgrade",
    "iso:country":"RS",
    "name:srp_x_preferred":[
        "Sopotnica"
    ],
    "wof:name":"Sopotnica",
    "wof:placetype":"locality"
},
  "geometry": {"coordinates":[22.13592,43.16036],"type":"Point"}
}