{
  "type": "Feature",
  "properties": {
    "gn:admin1_code":"SE",
    "gn:admin2_code":"12",
    "gn:asciiname":"Kokica Kraj",
    "gn:country_code":"RS",
    "gn:dem":337,
    "gn:feature_class":"P",
    "gn:feature_code":"PPL",
    "gn:name":"Koki\u0107a Kraj",
    "gn:population":0,
    "gn:timezone":"Europe/Belgrade",
    "iso:country":"RS",
    "wof:name":"Kokica Kraj",
    "wof:placetype":"locality"
},
  "geometry": {"coordinates":[20.64764,43.97523],"type":"Point"}
}