{
  "type": "Feature",
  "properties": {
    "gn:admin1_code":"SE",
    "gn:admin2_code":"10",
    "gn:asciiname":"Cagljevo",
    "gn:country_code":"RS",
    "gn:dem":166,
    "gn:feature_class":"P",
    "gn:feature_code":"PPL",
    "gn:name":"\u010cagljevo",
    "gn:population":0,
    "gn:timezone":"Europe/Belgrade",
    "iso:country":"RS",
    "wof:name":"Cagljevo",
    "wof:placetype":"locality"
},
  "geometry": {"coordinates":[21.04806,44.39417],"type":"Point"}
}