{
  "type": "Feature",
  "properties": {
    "gn:admin1_code":"SE",
    "gn:admin2_code":"18",
    "gn:asciiname":"Gradac",
    "gn:country_code":"RS",
    "gn:dem":1231,
    "gn:feature_class":"P",
    "gn:feature_code":"PPL",
    "gn:name":"Gradac",
    "gn:population":0,
    "gn:timezone":"Europe/Belgrade",
    "iso:country":"RS",
    "name:srp_x_preferred":[
        "Gradac"
    ],
    "wof:name":"Gradac",
    "wof:placetype":"locality"
},
  "geometry": {"coordinates":[20.14267000000001,43.07052],"type":"Point"}
}