{
  "type": "Feature",
  "properties": {
    "gn:admin1_code":"SE",
    "gn:admin2_code":"18",
    "gn:asciiname":"Gradac",
    "gn:country_code":"RS",
    "gn:dem":1231,
    "gn:feature_class":"P",
    "gn:feature_code":"PPL",
    "gn:name":"Gradac",
    "gn:population":0,
    "gn:timezone":"Europe/Belgrade",
    "iso:country":"RS",
    "name:bos_x_preferred":[
        "Gradac"
    ],
    "name:cat_x_preferred":[
        "Gradac"
    ],
    "name:ceb_x_preferred":[
        "Gradac"
    ],
    "name:deu_x_preferred":[
        "Gradac"
    ],
    "name:fra_x_preferred":[
        "Gradac"
    ],
    "name:hrv_x_preferred":[
        "Gradac"
    ],
    "name:hun_x_preferred":[
        "Gradac"
    ],
    "name:nld_x_preferred":[
        "Gradac"
    ],
    "name:pol_x_preferred":[
        "Gradac"
    ],
    "name:ron_x_preferred":[
        "Gradac"
    ],
    "name:rus_x_preferred":[
        "\u0413\u0440\u0430\u0434\u0430\u0446"
    ],
    "name:slv_x_preferred":[
        "Gradac"
    ],
    "name:srp_x_preferred":[
        "Gradac"
    ],
    "name:srp_x_variant":[
        "\u0413\u0440\u0430\u0434\u0430\u0446"
    ],
    "name:swe_x_preferred":[
        "Gradac"
    ],
    "wof:name":"Gradac",
    "wof:placetype":"locality"
},
  "geometry": {"coordinates":[20.14267000000001,43.07052],"type":"Point"}
}