{
  "type": "Feature",
  "properties": {
    "gn:admin1_code":"SE",
    "gn:admin2_code":"12",
    "gn:asciiname":"Kutlovo",
    "gn:country_code":"RS",
    "gn:dem":367,
    "gn:feature_class":"P",
    "gn:feature_code":"PPL",
    "gn:name":"Kutlovo",
    "gn:population":0,
    "gn:timezone":"Europe/Belgrade",
    "iso:country":"RS",
    "name:srp_x_preferred":[
        "Kutlovo"
    ],
    "wof:name":"Kutlovo",
    "wof:placetype":"locality"
},
  "geometry": {"coordinates":[20.75771,44.04792],"type":"Point"}
}