{
  "type": "Feature",
  "properties": {
    "gn:admin1_code":"SE",
    "gn:admin2_code":"16",
    "gn:asciiname":"Ploska",
    "gn:country_code":"RS",
    "gn:dem":812,
    "gn:feature_class":"P",
    "gn:feature_code":"PPL",
    "gn:name":"Ploska",
    "gn:population":0,
    "gn:timezone":"Europe/Belgrade",
    "iso:country":"RS",
    "name:srp_x_preferred":[
        "Ploska"
    ],
    "wof:name":"Ploska",
    "wof:placetype":"locality"
},
  "geometry": {"coordinates":[19.73357,44.08679],"type":"Point"}
}