{
  "type": "Feature",
  "properties": {
    "gn:admin1_code":"SE",
    "gn:admin2_code":"0",
    "gn:asciiname":"Mecak",
    "gn:country_code":"RS",
    "gn:dem":180,
    "gn:feature_class":"P",
    "gn:feature_code":"PPL",
    "gn:name":"Me\u010dak",
    "gn:population":0,
    "gn:timezone":"Europe/Belgrade",
    "iso:country":"RS",
    "wof:name":"Mecak",
    "wof:placetype":"locality"
},
  "geometry": {"coordinates":[20.41796,44.50622],"type":"Point"}
}