{
  "type": "Feature",
  "properties": {
    "gn:admin1_code":"SE",
    "gn:admin2_code":"19",
    "gn:asciiname":"Duboke",
    "gn:country_code":"RS",
    "gn:dem":1123,
    "gn:feature_class":"P",
    "gn:feature_code":"PPL",
    "gn:name":"Duboke",
    "gn:population":0,
    "gn:timezone":"Europe/Belgrade",
    "iso:country":"RS",
    "name:srp_x_preferred":[
        "Duboke"
    ],
    "wof:name":"Duboke",
    "wof:placetype":"locality"
},
  "geometry": {"coordinates":[20.83618,43.44112],"type":"Point"}
}