{
  "type": "Feature",
  "properties": {
    "iso:country":"RS",
    "name:eng_x_preferred":[
        "Beli Potok"
    ],
    "name:srp_cyr_x_preferred":[
        "\u0411\u0435\u043b\u0438 \u041f\u043e\u0442\u043e\u043a)"
    ],
    "name:srp_x_preferred":[
        "\u0411\u0435\u043b\u0438 \u041f\u043e\u0442\u043e\u043a)"
    ],
    "wof:name":"Beli Potok",
    "wof:placetype":"neighbourhood"
},
  "geometry": {"coordinates":[20.51962585176931,44.70643761599099],"type":"Point"}
}