{
  "type": "Feature",
  "properties": {
    "gn:admin1_code":"SE",
    "gn:admin2_code":"8",
    "gn:asciiname":"Petrovici",
    "gn:country_code":"RS",
    "gn:dem":479,
    "gn:feature_class":"P",
    "gn:feature_code":"PPL",
    "gn:name":"Petrovi\u0107i",
    "gn:population":0,
    "gn:timezone":"Europe/Belgrade",
    "iso:country":"RS",
    "name:srp_x_preferred":[
        "Petrovi\u0107i"
    ],
    "name:und_x_variant":[
        "Veselinovi\u0107i"
    ],
    "wof:name":"Petrovici",
    "wof:placetype":"locality"
},
  "geometry": {"coordinates":[19.1849,44.34792],"type":"Point"}
}