{
  "type": "Feature",
  "properties": {
    "gn:admin1_code":"SE",
    "gn:admin2_code":"23",
    "gn:asciiname":"Orane",
    "gn:country_code":"RS",
    "gn:dem":482,
    "gn:feature_class":"P",
    "gn:feature_code":"PPL",
    "gn:name":"Orane",
    "gn:population":0,
    "gn:timezone":"Europe/Belgrade",
    "iso:country":"RS",
    "name:ceb_x_preferred":[
        "Orane"
    ],
    "name:fra_x_preferred":[
        "Orane"
    ],
    "name:msa_x_preferred":[
        "Orane"
    ],
    "name:por_x_preferred":[
        "Orane"
    ],
    "name:slv_x_preferred":[
        "Orane"
    ],
    "name:sqi_x_preferred":[
        "Orana"
    ],
    "name:srp_x_preferred":[
        "Orane"
    ],
    "name:srp_x_variant":[
        "\u041e\u0440\u0430\u043d\u0435"
    ],
    "wof:name":"Orane",
    "wof:placetype":"locality"
},
  "geometry": {"coordinates":[21.62785,42.98629],"type":"Point"}
}