{
  "type": "Feature",
  "properties": {
    "gn:admin1_code":"SE",
    "gn:admin2_code":"20",
    "gn:asciiname":"Rosica",
    "gn:country_code":"RS",
    "gn:dem":285,
    "gn:feature_class":"P",
    "gn:feature_code":"PPL",
    "gn:name":"Rosica",
    "gn:population":0,
    "gn:timezone":"Europe/Belgrade",
    "iso:country":"RS",
    "name:fra_x_preferred":[
        "Rosica"
    ],
    "name:msa_x_preferred":[
        "Rosica"
    ],
    "name:por_x_preferred":[
        "Rosica"
    ],
    "name:slv_x_preferred":[
        "Rosica"
    ],
    "name:srp_x_preferred":[
        "Rosica"
    ],
    "name:srp_x_variant":[
        "\u0420\u043e\u0441\u0438\u0446\u0430"
    ],
    "wof:name":"Rosica",
    "wof:placetype":"locality"
},
  "geometry": {"coordinates":[21.5581,43.43808],"type":"Point"}
}