{
  "type": "Feature",
  "properties": {
    "iso:country":"RS",
    "name:eng_x_preferred":[
        "Blok 4"
    ],
    "name:srp_cyr_x_preferred":[
        "\u0431\u043b\u043e\u043a 4"
    ],
    "wof:name":"Blok 4",
    "wof:placetype":"neighbourhood"
},
  "geometry": {"coordinates":[20.40072925648156,44.82763700958325],"type":"Point"}
}