{
  "type": "Feature",
  "properties": {
    "gn:admin1_code":"SE",
    "gn:admin2_code":"22",
    "gn:asciiname":"Ilinci",
    "gn:country_code":"RS",
    "gn:dem":412,
    "gn:feature_class":"P",
    "gn:feature_code":"PPL",
    "gn:name":"Ilinci",
    "gn:population":0,
    "gn:timezone":"Europe/Belgrade",
    "iso:country":"RS",
    "name:srp_x_preferred":[
        "Ilinci"
    ],
    "wof:name":"Ilinci",
    "wof:placetype":"locality"
},
  "geometry": {"coordinates":[22.28321,43.26147],"type":"Point"}
}