{
  "type": "Feature",
  "properties": {
    "gn:admin1_code":"SE",
    "gn:admin2_code":"22",
    "gn:asciiname":"Ilinci",
    "gn:country_code":"RS",
    "gn:dem":412,
    "gn:feature_class":"P",
    "gn:feature_code":"PPL",
    "gn:name":"Ilinci",
    "gn:population":0,
    "gn:timezone":"Europe/Belgrade",
    "iso:country":"RS",
    "name:ceb_x_preferred":[
        "Ilinci"
    ],
    "name:epo_x_preferred":[
        "Ilinci"
    ],
    "name:fra_x_preferred":[
        "Ilinci"
    ],
    "name:hrv_x_preferred":[
        "Ilinci"
    ],
    "name:hun_x_preferred":[
        "Ilinci"
    ],
    "name:msa_x_preferred":[
        "Ilinci"
    ],
    "name:rus_x_preferred":[
        "\u0418\u043b\u0438\u043d\u0446\u0438"
    ],
    "name:slv_x_preferred":[
        "Ilinci"
    ],
    "name:srp_x_preferred":[
        "Ilinci"
    ],
    "name:srp_x_variant":[
        "\u0418\u043b\u0438\u043d\u0446\u0438"
    ],
    "wof:name":"Ilinci",
    "wof:placetype":"locality"
},
  "geometry": {"coordinates":[22.28321,43.26147],"type":"Point"}
}