{
  "type": "Feature",
  "properties": {
    "gn:admin1_code":"SE",
    "gn:admin2_code":"24",
    "gn:asciiname":"Jasikarnik",
    "gn:country_code":"RS",
    "gn:dem":1359,
    "gn:feature_class":"P",
    "gn:feature_code":"PPL",
    "gn:name":"Jasikarnik",
    "gn:population":0,
    "gn:timezone":"Europe/Belgrade",
    "iso:country":"RS",
    "wof:name":"Jasikarnik",
    "wof:placetype":"locality"
},
  "geometry": {"coordinates":[22.34185,42.39468],"type":"Point"}
}