{
  "type": "Feature",
  "properties": {
    "iso:country":"RS",
    "name:aze_x_preferred":[
        "Vra\u00e7ar"
    ],
    "name:bel_x_preferred":[
        "\u0430\u0431\u0448\u0447\u044b\u043d\u0430 \u0412\u0440\u0430\u0447\u0430\u0440"
    ],
    "name:bul_x_preferred":[
        "\u0412\u0440\u0430\u0447\u0430\u0440"
    ],
    "name:cat_x_preferred":[
        "Vra\u010dar"
    ],
    "name:ceb_x_preferred":[
        "Op\u0161tina Beograd-Vra\u010dar"
    ],
    "name:ces_x_preferred":[
        "Vra\u010dar"
    ],
    "name:deu_x_preferred":[
        "Vra\u010dar"
    ],
    "name:ell_x_preferred":[
        "\u0392\u03c1\u03ac\u03c4\u03c3\u03b1\u03c1"
    ],
    "name:eng_x_preferred":[
        "Vra\u010dar"
    ],
    "name:est_x_preferred":[
        "Vra\u010dar"
    ],
    "name:fra_x_preferred":[
        "Vra\u010dar"
    ],
    "name:hrv_x_preferred":[
        "Vra\u010dar"
    ],
    "name:ind_x_preferred":[
        "Vra\u010dar"
    ],
    "name:ita_x_preferred":[
        "Vra\u010dar"
    ],
    "name:jpn_x_preferred":[
        "\u30f4\u30e9\u30c1\u30e3\u30eb"
    ],
    "name:kat_x_preferred":[
        "\u10d5\u10e0\u10d0\u10e9\u10d0\u10e0\u10d8\u10e1 \u10d7\u10d4\u10db\u10d8"
    ],
    "name:kat_x_variant":[
        "\u10d5\u10e0\u10d0\u10e9\u10d0\u10e0\u10d8\u10e1 \u10db\u10e3\u10dc\u10d8\u10ea\u10d8\u10de\u10d0\u10da\u10d8\u10e2\u10d4\u10e2\u10d8"
    ],
    "name:kor_x_preferred":[
        "\ube0c\ub77c\ucc28\ub974"
    ],
    "name:nld_x_preferred":[
        "Vra\u010dar"
    ],
    "name:nob_x_preferred":[
        "Vra\u010dar"
    ],
    "name:nor_x_preferred":[
        "Vra\u010dar"
    ],
    "name:pol_x_preferred":[
        "Vra\u010dar"
    ],
    "name:por_x_preferred":[
        "Vra\u010dar"
    ],
    "name:rus_x_preferred":[
        "\u0412\u0440\u0430\u0447\u0430\u0440"
    ],
    "name:spa_x_preferred":[
        "Vra\u010dar"
    ],
    "name:srp_cyr_x_preferred":[
        "\u0412\u0440\u0430\u0447\u0430\u0440"
    ],
    "name:srp_lat_x_preferred":[
        "Vra\u010dar"
    ],
    "name:tur_x_preferred":[
        "Vra\u010dar"
    ],
    "name:und_x_colloquial":[
        "Vracar"
    ],
    "name:uzb_x_preferred":[
        "Vra\u010dar"
    ],
    "name:zho_x_preferred":[
        "\u5f17\u62c9\u67e5\u5c14"
    ],
    "qs:gn_adm0_cc":"RS",
    "qs:gn_local":792680,
    "qs:local_max":14947,
    "qs:local_sum":25281,
    "qs:localhoods":8,
    "qs:name":"Vra\u010dar",
    "qs:name_adm0":"Serbia",
    "qs:name_adm1":"Beograd",
    "qs:name_local":"Beograd",
    "qs:photo_max":543,
    "qs:photo_sum":4230,
    "qs:placetype":"Suburb",
    "qs:quad_count":122,
    "qs:woe_adm0":20069818,
    "qs:woe_adm1":29389217,
    "qs:woe_adm2":0,
    "qs:woe_lau":0,
    "qs:woe_local":532697,
    "qs:woe_ver":"7.10.0",
    "wd:wordcount":1459,
    "wof:name":"Vra\u010dar",
    "wof:placetype":"neighbourhood"
},
  "geometry": {"coordinates":[20.472332,44.801597],"type":"Point"}
}