{
  "type": "Feature",
  "properties": {
    "gn:admin1_code":"SE",
    "gn:admin2_code":"17",
    "gn:asciiname":"Markovici",
    "gn:country_code":"RS",
    "gn:dem":901,
    "gn:feature_class":"P",
    "gn:feature_code":"PPL",
    "gn:name":"Markovi\u0107i",
    "gn:population":0,
    "gn:timezone":"Europe/Belgrade",
    "iso:country":"RS",
    "name:srp_x_preferred":[
        "Markovi\u0107i"
    ],
    "wof:name":"Markovici",
    "wof:placetype":"locality"
},
  "geometry": {"coordinates":[20.36772,43.46768],"type":"Point"}
}