{
  "type": "Feature",
  "properties": {
    "iso:country":"RS",
    "name:eng_x_preferred":[
        "Irgot"
    ],
    "name:srp_cyr_x_preferred":[
        "\u0418\u0440\u0433\u043e\u0442"
    ],
    "name:srp_x_preferred":[
        "\u0418\u0440\u0433\u043e\u0442"
    ],
    "wof:name":"Irgot",
    "wof:placetype":"neighbourhood"
},
  "geometry": {"coordinates":[20.45200676471612,44.86642224373198],"type":"Point"}
}