{
  "type": "Feature",
  "properties": {
    "gn:admin1_code":"SE",
    "gn:admin2_code":"12",
    "gn:asciiname":"Rankovici",
    "gn:country_code":"RS",
    "gn:dem":321,
    "gn:feature_class":"P",
    "gn:feature_code":"PPL",
    "gn:name":"Rankovi\u0107i",
    "gn:population":0,
    "gn:timezone":"Europe/Belgrade",
    "iso:country":"RS",
    "wof:name":"Rankovici",
    "wof:placetype":"locality"
},
  "geometry": {"coordinates":[20.80611,43.86806],"type":"Point"}
}