{
  "type": "Feature",
  "properties": {
    "gn:admin1_code":"SE",
    "gn:admin2_code":"16",
    "gn:asciiname":"Stevanovici",
    "gn:country_code":"RS",
    "gn:dem":1027,
    "gn:feature_class":"P",
    "gn:feature_code":"PPL",
    "gn:name":"Stevanovi\u0107i",
    "gn:population":0,
    "gn:timezone":"Europe/Belgrade",
    "iso:country":"RS",
    "wof:name":"Stevanovici",
    "wof:placetype":"locality"
},
  "geometry": {"coordinates":[19.95472,43.62222],"type":"Point"}
}