{
  "type": "Feature",
  "properties": {
    "gn:admin1_code":"SE",
    "gn:admin2_code":"17",
    "gn:asciiname":"Semedraz",
    "gn:country_code":"RS",
    "gn:dem":403,
    "gn:feature_class":"P",
    "gn:feature_code":"PPLL",
    "gn:name":"Semedra\u017e",
    "gn:population":0,
    "gn:timezone":"Europe/Belgrade",
    "iso:country":"RS",
    "name:srp_x_preferred":[
        "Semedra\u017e"
    ],
    "wof:name":"Semedraz",
    "wof:placetype":"locality"
},
  "geometry": {"coordinates":[20.40714,44.0072],"type":"Point"}
}