{
  "type": "Feature",
  "properties": {
    "gn:country":"RS",
    "gn:fcode":"PPL",
    "gn:pop":5,
    "iso:country":"RS",
    "qs:name":"Vesovici",
    "qs:photos_9r":0,
    "qs:photos_sr":0,
    "qs:pop_sr":"1",
    "wof:name":"Vesovici",
    "wof:placetype":"locality",
    "wof:population":5
},
  "geometry": {"coordinates":[20.46375,43.72587],"type":"Point"}
}