{
  "type": "Feature",
  "properties": {
    "gn:country":"RS",
    "gn:fcode":"PPL",
    "gn:population":1538,
    "iso:country":"RS",
    "name:bel_x_preferred":[
        "\u0421\u0430\u043b\u0430\u0448 \u0426\u0440\u043d\u043e\u0431\u0430\u0440\u0441\u043a\u0456"
    ],
    "name:ceb_x_preferred":[
        "Sala\u0161 Crnobarski"
    ],
    "name:eng_x_preferred":[
        "Sala\u0161 Crnobarski"
    ],
    "name:fra_x_preferred":[
        "Sala\u0161 Crnobarski"
    ],
    "name:msa_x_preferred":[
        "Sala\u0161 Crnobarski"
    ],
    "name:nld_x_preferred":[
        "Sala\u0161 Crnobarski"
    ],
    "name:por_x_preferred":[
        "Sala\u0161 Crnobarski"
    ],
    "name:slv_x_preferred":[
        "Sala\u0161 Crnobarski"
    ],
    "name:srp_x_preferred":[
        "Sala\u0161 Crnobarski"
    ],
    "name:srp_x_variant":[
        "\u0421\u0430\u043b\u0430\u0448 \u0426\u0440\u043d\u043e\u0431\u0430\u0440\u0441\u043a\u0438"
    ],
    "name:und_x_variant":[
        "Crnobarski Sala\u0161"
    ],
    "qs:name":"Sala\u0161 Crnobarski",
    "qs:photos_9r":0,
    "qs:photos_sr":0,
    "qs:pop_sr":"3",
    "wd:wordcount":66,
    "wof:name":"Sala\u0161 Crnobarski",
    "wof:placetype":"locality",
    "wof:population":1538
},
  "geometry": {"coordinates":[19.39437,44.82843],"type":"Point"}
}