{
  "type": "Feature",
  "properties": {
    "gn:admin1_code":"SE",
    "gn:admin2_code":"8",
    "gn:asciiname":"Srednja Mala",
    "gn:country_code":"RS",
    "gn:dem":142,
    "gn:feature_class":"P",
    "gn:feature_code":"PPL",
    "gn:name":"Srednja Mala",
    "gn:population":0,
    "gn:timezone":"Europe/Belgrade",
    "iso:country":"RS",
    "name:srp_x_preferred":[
        "Srednja Mala"
    ],
    "wof:name":"Srednja Mala",
    "wof:placetype":"locality"
},
  "geometry": {"coordinates":[19.65873,44.63061],"type":"Point"}
}