{
  "type": "Feature",
  "properties": {
    "gn:admin1_code":"VO",
    "gn:admin2_code":"6",
    "gn:asciiname":"Ledinci",
    "gn:country_code":"RS",
    "gn:dem":169,
    "gn:feature_class":"P",
    "gn:feature_code":"PPL",
    "gn:name":"Ledinci",
    "gn:population":0,
    "gn:timezone":"Europe/Belgrade",
    "iso:country":"RS",
    "name:epo_x_preferred":[
        "Ledinci"
    ],
    "name:fra_x_preferred":[
        "Ledinci"
    ],
    "name:hun_x_preferred":[
        "Ledince"
    ],
    "name:msa_x_preferred":[
        "Ledinci"
    ],
    "name:slv_x_preferred":[
        "Ledinci"
    ],
    "name:srp_x_preferred":[
        "Ledinci"
    ],
    "name:srp_x_variant":[
        "\u041b\u0435\u0434\u0438\u043d\u0446\u0438"
    ],
    "name:ukr_x_preferred":[
        "\u041b\u0435\u0434\u0438\u043d\u0446\u0456"
    ],
    "name:und_x_variant":[
        "Novi Ledinci"
    ],
    "wof:name":"Ledinci",
    "wof:placetype":"locality"
},
  "geometry": {"coordinates":[19.80554,45.18697],"type":"Point"}
}