{
  "type": "Feature",
  "properties": {
    "gn:admin1_code":"SE",
    "gn:admin2_code":"23",
    "gn:asciiname":"Bistrica",
    "gn:country_code":"RS",
    "gn:dem":673,
    "gn:feature_class":"P",
    "gn:feature_code":"PPL",
    "gn:name":"Bistrica",
    "gn:population":0,
    "gn:timezone":"Europe/Belgrade",
    "iso:country":"RS",
    "name:srp_x_preferred":[
        "Bistrica"
    ],
    "name:und_x_variant":[
        "Gornje Bistrica",
        "Gornja Bistrica"
    ],
    "wof:name":"Bistrica",
    "wof:placetype":"locality"
},
  "geometry": {"coordinates":[22.07219,42.84145],"type":"Point"}
}