{
  "type": "Feature",
  "properties": {
    "gn:admin1_code":"SE",
    "gn:admin2_code":"23",
    "gn:asciiname":"Bistrica",
    "gn:country_code":"RS",
    "gn:dem":673,
    "gn:feature_class":"P",
    "gn:feature_code":"PPL",
    "gn:name":"Bistrica",
    "gn:population":0,
    "gn:timezone":"Europe/Belgrade",
    "iso:country":"RS",
    "name:bos_x_preferred":[
        "Bistrica"
    ],
    "name:bul_x_preferred":[
        "\u0411\u0438\u0441\u0442\u0440\u0438\u0446\u0430"
    ],
    "name:ceb_x_preferred":[
        "Bistrica"
    ],
    "name:deu_x_preferred":[
        "Bistrica"
    ],
    "name:ell_x_preferred":[
        "\u0392\u03af\u03c3\u03c4\u03c1\u03b9\u03c4\u03c3\u03b1"
    ],
    "name:fra_x_preferred":[
        "Bistrica"
    ],
    "name:hrv_x_preferred":[
        "Bistrica"
    ],
    "name:hun_x_preferred":[
        "Bistrica"
    ],
    "name:ita_x_preferred":[
        "Bistrica"
    ],
    "name:lat_x_preferred":[
        "Bistrica"
    ],
    "name:lit_x_preferred":[
        "Bistrica"
    ],
    "name:mkd_x_preferred":[
        "\u0411\u0438\u0441\u0442\u0440\u0438\u0446\u0430"
    ],
    "name:nld_x_preferred":[
        "Bistrica"
    ],
    "name:pol_x_preferred":[
        "Bistrica"
    ],
    "name:rus_x_preferred":[
        "\u0411\u0438\u0441\u0442\u0440\u0438\u0446\u0430"
    ],
    "name:slv_x_preferred":[
        "Bistrica"
    ],
    "name:sqi_x_preferred":[
        "Bistrica"
    ],
    "name:srp_x_preferred":[
        "Bistrica"
    ],
    "name:srp_x_variant":[
        "\u0411\u0438\u0441\u0442\u0440\u0438\u0446\u0430"
    ],
    "name:swe_x_preferred":[
        "Bistrica"
    ],
    "name:und_x_variant":[
        "Gornje Bistrica",
        "Gornja Bistrica"
    ],
    "wof:name":"Bistrica",
    "wof:placetype":"locality"
},
  "geometry": {"coordinates":[22.07219,42.84145],"type":"Point"}
}