{
  "type": "Feature",
  "properties": {
    "gn:admin1_code":"SE",
    "gn:admin2_code":"8",
    "gn:asciiname":"Rakici",
    "gn:country_code":"RS",
    "gn:dem":580,
    "gn:feature_class":"P",
    "gn:feature_code":"PPL",
    "gn:name":"Raki\u0107i",
    "gn:population":0,
    "gn:timezone":"Europe/Belgrade",
    "iso:country":"RS",
    "name:srp_x_preferred":[
        "Raki\u0107i"
    ],
    "wof:name":"Rakici",
    "wof:placetype":"locality"
},
  "geometry": {"coordinates":[19.37105,44.29994],"type":"Point"}
}