{
  "type": "Feature",
  "properties": {
    "gn:admin1_code":"SE",
    "gn:admin2_code":"16",
    "gn:asciiname":"Rukocki Bunari",
    "gn:country_code":"RS",
    "gn:dem":1298,
    "gn:feature_class":"P",
    "gn:feature_code":"PPL",
    "gn:name":"Ruko\u010dki Bunari",
    "gn:population":0,
    "gn:timezone":"Europe/Belgrade",
    "iso:country":"RS",
    "name:srp_x_preferred":[
        "Ruko\u010dki Bunari"
    ],
    "wof:name":"Rukocki Bunari",
    "wof:placetype":"locality"
},
  "geometry": {"coordinates":[20.05417000000001,43.16667],"type":"Point"}
}