{
  "type": "Feature",
  "properties": {
    "iso:country":"RS",
    "name:eng_x_preferred":[
        "Stari Zeleznik"
    ],
    "name:srp_cyr_x_preferred":[
        "\u0421\u0442\u0430\u0440\u0438 \u0416\u0435\u043b\u0435\u0437\u043d\u0438\u043a"
    ],
    "name:srp_lat_x_preferred":[
        "Stari \u017deleznik"
    ],
    "name:srp_x_preferred":[
        "\u0421\u0442\u0430\u0440\u0438 \u0416\u0435\u043b\u0435\u0437\u043d\u0438\u043a"
    ],
    "wof:name":"Stari Zeleznik",
    "wof:placetype":"neighbourhood"
},
  "geometry": {"coordinates":[20.37573718665137,44.7260645396787],"type":"Point"}
}