{
  "type": "Feature",
  "properties": {
    "gn:admin1_code":"SE",
    "gn:admin2_code":"23",
    "gn:asciiname":"Bajinci",
    "gn:country_code":"RS",
    "gn:dem":1312,
    "gn:feature_class":"P",
    "gn:feature_code":"PPL",
    "gn:name":"Bajinci",
    "gn:population":0,
    "gn:timezone":"Europe/Belgrade",
    "iso:country":"RS",
    "name:fra_x_preferred":[
        "Bajinci"
    ],
    "name:hun_x_preferred":[
        "Bajinci"
    ],
    "name:msa_x_preferred":[
        "Bajinci"
    ],
    "name:nld_x_preferred":[
        "Bajinci"
    ],
    "name:por_x_preferred":[
        "Bajinci"
    ],
    "name:slv_x_preferred":[
        "Bajinci"
    ],
    "name:srp_x_preferred":[
        "Bajinci"
    ],
    "name:srp_x_variant":[
        "\u0411\u0430\u0458\u0438\u043d\u0446\u0438"
    ],
    "wof:name":"Bajinci",
    "wof:placetype":"locality"
},
  "geometry": {"coordinates":[22.25381,42.78618],"type":"Point"}
}