{
  "type": "Feature",
  "properties": {
    "gn:admin1_code":"SE",
    "gn:admin2_code":"17",
    "gn:asciiname":"Kotraza",
    "gn:country_code":"RS",
    "gn:dem":503,
    "gn:feature_class":"P",
    "gn:feature_code":"PPLL",
    "gn:name":"Kotra\u017ea",
    "gn:population":0,
    "gn:timezone":"Europe/Belgrade",
    "iso:country":"RS",
    "name:srp_x_preferred":[
        "Kotra\u017ea"
    ],
    "name:und_x_variant":[
        "Kotra\u017ea Vu\u010dkavica"
    ],
    "wof:name":"Kotraza",
    "wof:placetype":"locality"
},
  "geometry": {"coordinates":[20.22408,43.7008],"type":"Point"}
}