{
  "type": "Feature",
  "properties": {
    "gn:admin1_code":"SE",
    "gn:admin2_code":"8",
    "gn:asciiname":"Jokici",
    "gn:country_code":"RS",
    "gn:dem":90,
    "gn:feature_class":"P",
    "gn:feature_code":"PPL",
    "gn:name":"Joki\u0107i",
    "gn:population":0,
    "gn:timezone":"Europe/Belgrade",
    "iso:country":"RS",
    "name:srp_x_preferred":[
        "Joki\u0107i"
    ],
    "wof:name":"Jokici",
    "wof:placetype":"locality"
},
  "geometry": {"coordinates":[19.40806,44.74139],"type":"Point"}
}