{
  "type": "Feature",
  "properties": {
    "gn:admin1_code":"SE",
    "gn:admin2_code":"16",
    "gn:asciiname":"Mazici",
    "gn:country_code":"RS",
    "gn:dem":892,
    "gn:feature_class":"P",
    "gn:feature_code":"PPLL",
    "gn:name":"Ma\u017ei\u0107i",
    "gn:population":0,
    "gn:timezone":"Europe/Belgrade",
    "iso:country":"RS",
    "name:ceb_x_preferred":[
        "Ma\u017ei\u0107i"
    ],
    "name:fra_x_preferred":[
        "Ma\u017ei\u0107i"
    ],
    "name:msa_x_preferred":[
        "Ma\u017ei\u0107i"
    ],
    "name:nld_x_preferred":[
        "Ma\u017ei\u0107i"
    ],
    "name:por_x_preferred":[
        "Ma\u017ei\u0107i"
    ],
    "name:slv_x_preferred":[
        "Ma\u017ei\u0107i"
    ],
    "name:srp_x_preferred":[
        "Ma\u017ei\u0107i"
    ],
    "name:srp_x_variant":[
        "\u041c\u0430\u0436\u0438\u045b\u0438"
    ],
    "name:und_x_variant":[
        "Mar\u017ei\u0107i"
    ],
    "wof:name":"Mazici",
    "wof:placetype":"locality"
},
  "geometry": {"coordinates":[19.56716,43.50174000000001],"type":"Point"}
}