{
  "type": "Feature",
  "properties": {
    "gn:admin1_code":"SE",
    "gn:admin2_code":"23",
    "gn:asciiname":"Klajic",
    "gn:country_code":"RS",
    "gn:dem":617,
    "gn:feature_class":"P",
    "gn:feature_code":"PPL",
    "gn:name":"Klaji\u0107",
    "gn:population":0,
    "gn:timezone":"Europe/Belgrade",
    "iso:country":"RS",
    "name:ceb_x_preferred":[
        "Klaji\u0107"
    ],
    "name:fra_x_preferred":[
        "Klaji\u0107"
    ],
    "name:msa_x_preferred":[
        "Klaji\u0107"
    ],
    "name:por_x_preferred":[
        "Klaji\u0107"
    ],
    "name:slv_x_preferred":[
        "Klaji\u0107"
    ],
    "name:sqi_x_preferred":[
        "Klaiqi"
    ],
    "name:srp_x_preferred":[
        "Klaji\u0107"
    ],
    "name:srp_x_variant":[
        "\u041a\u043b\u0430\u0458\u0438\u045b"
    ],
    "name:und_x_variant":[
        "Klai\u0107i"
    ],
    "wof:name":"Klajic",
    "wof:placetype":"locality"
},
  "geometry": {"coordinates":[21.73128,42.82371],"type":"Point"}
}