{
  "type": "Feature",
  "properties": {
    "gn:admin1_code":"SE",
    "gn:admin2_code":"23",
    "gn:asciiname":"Klajic",
    "gn:country_code":"RS",
    "gn:dem":617,
    "gn:feature_class":"P",
    "gn:feature_code":"PPL",
    "gn:name":"Klaji\u0107",
    "gn:population":0,
    "gn:timezone":"Europe/Belgrade",
    "iso:country":"RS",
    "name:srp_x_preferred":[
        "Klaji\u0107"
    ],
    "name:und_x_variant":[
        "Klai\u0107i"
    ],
    "wof:name":"Klajic",
    "wof:placetype":"locality"
},
  "geometry": {"coordinates":[21.73128,42.82371],"type":"Point"}
}