{
  "type": "Feature",
  "properties": {
    "gn:admin1_code":"SE",
    "gn:admin2_code":"16",
    "gn:asciiname":"Kozla",
    "gn:country_code":"RS",
    "gn:dem":620,
    "gn:feature_class":"P",
    "gn:feature_code":"PPL",
    "gn:name":"Kozla",
    "gn:population":0,
    "gn:timezone":"Europe/Belgrade",
    "iso:country":"RS",
    "name:srp_x_preferred":[
        "Kozla"
    ],
    "wof:name":"Kozla",
    "wof:placetype":"locality"
},
  "geometry": {"coordinates":[19.35001,43.95592],"type":"Point"}
}