{
  "type": "Feature",
  "properties": {
    "gn:admin1_code":"SE",
    "gn:admin2_code":"16",
    "gn:asciiname":"Drazevice",
    "gn:country_code":"RS",
    "gn:dem":1143,
    "gn:feature_class":"P",
    "gn:feature_code":"PPL",
    "gn:name":"Dra\u017eevi\u0107e",
    "gn:population":0,
    "gn:timezone":"Europe/Belgrade",
    "iso:country":"RS",
    "name:srp_x_preferred":[
        "Dra\u017eevi\u0107e"
    ],
    "name:und_x_variant":[
        "Dra\u017eevi\u0107i"
    ],
    "wof:name":"Drazevice",
    "wof:placetype":"locality"
},
  "geometry": {"coordinates":[20.19923,43.23471],"type":"Point"}
}