{
  "type": "Feature",
  "properties": {
    "gn:admin1_code":"SE",
    "gn:admin2_code":"16",
    "gn:asciiname":"Drazevice",
    "gn:country_code":"RS",
    "gn:dem":1143,
    "gn:feature_class":"P",
    "gn:feature_code":"PPL",
    "gn:name":"Dra\u017eevi\u0107e",
    "gn:population":0,
    "gn:timezone":"Europe/Belgrade",
    "iso:country":"RS",
    "name:ceb_x_preferred":[
        "Dra\u017eevi\u0107e"
    ],
    "name:fra_x_preferred":[
        "Dra\u017eevi\u0107e"
    ],
    "name:msa_x_preferred":[
        "Dra\u017eevi\u0107e"
    ],
    "name:nld_x_preferred":[
        "Dra\u017eevi\u0107e"
    ],
    "name:por_x_preferred":[
        "Dra\u017eevi\u0107e"
    ],
    "name:slv_x_preferred":[
        "Dra\u017eevi\u0107e"
    ],
    "name:srp_x_preferred":[
        "Dra\u017eevi\u0107e"
    ],
    "name:srp_x_variant":[
        "\u0414\u0440\u0430\u0436\u0435\u0432\u0438\u045b\u0435"
    ],
    "name:und_x_variant":[
        "Dra\u017eevi\u0107i"
    ],
    "wof:name":"Drazevice",
    "wof:placetype":"locality"
},
  "geometry": {"coordinates":[20.19923,43.23471],"type":"Point"}
}