{
  "type": "Feature",
  "properties": {
    "gn:admin1_code":"SE",
    "gn:admin2_code":"17",
    "gn:asciiname":"Druzetici",
    "gn:country_code":"RS",
    "gn:dem":591,
    "gn:feature_class":"P",
    "gn:feature_code":"PPL",
    "gn:name":"Dru\u017eeti\u0107i",
    "gn:population":0,
    "gn:timezone":"Europe/Belgrade",
    "iso:country":"RS",
    "name:srp_x_preferred":[
        "Dru\u017eeti\u0107i"
    ],
    "wof:name":"Druzetici",
    "wof:placetype":"locality"
},
  "geometry": {"coordinates":[20.13546,44.0236],"type":"Point"}
}