{
  "type": "Feature",
  "properties": {
    "gn:admin1_code":"SE",
    "gn:admin2_code":"16",
    "gn:asciiname":"Ljeskovac",
    "gn:country_code":"RS",
    "gn:dem":944,
    "gn:feature_class":"P",
    "gn:feature_code":"PPLL",
    "gn:name":"Ljeskovac",
    "gn:population":0,
    "gn:timezone":"Europe/Belgrade",
    "iso:country":"RS",
    "name:bos_x_preferred":[
        "Ljeskovac"
    ],
    "name:ceb_x_preferred":[
        "Ljeskovac"
    ],
    "name:fra_x_preferred":[
        "Ljeskovac"
    ],
    "name:hrv_x_preferred":[
        "Ljeskovac"
    ],
    "name:rus_x_preferred":[
        "\u041b\u0435\u0441\u043a\u043e\u0432\u0430\u0446"
    ],
    "name:slv_x_preferred":[
        "Ljeskovac"
    ],
    "name:srp_x_preferred":[
        "\u0409\u0435\u0441\u043a\u043e\u0432\u0430\u0446"
    ],
    "name:swe_x_preferred":[
        "Ljeskovac"
    ],
    "wof:name":"Ljeskovac",
    "wof:placetype":"locality"
},
  "geometry": {"coordinates":[19.59528,43.40556],"type":"Point"}
}