{
  "type": "Feature",
  "properties": {
    "gn:admin1_code":"SE",
    "gn:admin2_code":"11",
    "gn:asciiname":"Klicevac",
    "gn:country_code":"RS",
    "gn:dem":83,
    "gn:feature_class":"P",
    "gn:feature_code":"PPL",
    "gn:name":"Kli\u010devac",
    "gn:population":0,
    "gn:timezone":"Europe/Belgrade",
    "iso:country":"RS",
    "name:ceb_x_preferred":[
        "Kli\u010devac"
    ],
    "name:fra_x_preferred":[
        "Kli\u010devac"
    ],
    "name:msa_x_preferred":[
        "Kli\u010devac"
    ],
    "name:por_x_preferred":[
        "Kli\u010devac"
    ],
    "name:ron_x_preferred":[
        "Kli\u010devac"
    ],
    "name:slv_x_preferred":[
        "Kli\u010devac"
    ],
    "name:srp_x_preferred":[
        "Kli\u010devac"
    ],
    "name:srp_x_variant":[
        "\u041a\u043b\u0438\u0447\u0435\u0432\u0430\u0446"
    ],
    "wof:name":"Klicevac",
    "wof:placetype":"locality"
},
  "geometry": {"coordinates":[21.29044,44.75933],"type":"Point"}
}