{
  "type": "Feature",
  "properties": {
    "gn:admin1_code":"SE",
    "gn:admin2_code":"22",
    "gn:asciiname":"Pokrevenik",
    "gn:country_code":"RS",
    "gn:dem":795,
    "gn:feature_class":"P",
    "gn:feature_code":"PPL",
    "gn:name":"Pokrevenik",
    "gn:population":0,
    "gn:timezone":"Europe/Belgrade",
    "iso:country":"RS",
    "name:ceb_x_preferred":[
        "Pokrevenik"
    ],
    "name:fra_x_preferred":[
        "Pokrevenik"
    ],
    "name:msa_x_preferred":[
        "Pokrevenik"
    ],
    "name:por_x_preferred":[
        "Pokrevenik"
    ],
    "name:slv_x_preferred":[
        "Pokrevenik"
    ],
    "name:srp_x_preferred":[
        "Pokrevenik"
    ],
    "name:srp_x_variant":[
        "\u041f\u043e\u043a\u0440\u0435\u0432\u0435\u043d\u0438\u043a"
    ],
    "name:und_x_variant":[
        "Pokrovenik",
        "Pokrvenik"
    ],
    "wof:name":"Pokrevenik",
    "wof:placetype":"locality"
},
  "geometry": {"coordinates":[22.61733,43.25458],"type":"Point"}
}