{
  "type": "Feature",
  "properties": {
    "gn:admin1_code":"SE",
    "gn:admin2_code":"24",
    "gn:asciiname":"Trnovksa Maala",
    "gn:country_code":"RS",
    "gn:dem":472,
    "gn:feature_class":"P",
    "gn:feature_code":"PPL",
    "gn:name":"Trnovksa Maala",
    "gn:population":0,
    "gn:timezone":"Europe/Belgrade",
    "iso:country":"RS",
    "name:sqi_x_preferred":[
        "Mahalla Ternovcalive"
    ],
    "wof:name":"Trnovksa Maala",
    "wof:placetype":"locality"
},
  "geometry": {"coordinates":[21.74373,42.38997],"type":"Point"}
}