{
  "type": "Feature",
  "properties": {
    "gn:admin1_code":"SE",
    "gn:admin2_code":"19",
    "gn:asciiname":"Isailova Mala",
    "gn:country_code":"RS",
    "gn:dem":207,
    "gn:feature_class":"P",
    "gn:feature_code":"PPL",
    "gn:name":"Isailova Mala",
    "gn:population":0,
    "gn:timezone":"Europe/Belgrade",
    "iso:country":"RS",
    "wof:name":"Isailova Mala",
    "wof:placetype":"locality"
},
  "geometry": {"coordinates":[21.12864,43.66349],"type":"Point"}
}