{
  "type": "Feature",
  "properties": {
    "gn:admin1_code":"SE",
    "gn:admin2_code":"18",
    "gn:asciiname":"Zutice",
    "gn:country_code":"RS",
    "gn:dem":476,
    "gn:feature_class":"P",
    "gn:feature_code":"PPL",
    "gn:name":"\u017dutice",
    "gn:population":0,
    "gn:timezone":"Europe/Belgrade",
    "iso:country":"RS",
    "name:srp_x_preferred":[
        "\u017dutice"
    ],
    "wof:name":"Zutice",
    "wof:placetype":"locality"
},
  "geometry": {"coordinates":[20.65769,43.36135],"type":"Point"}
}