{
  "type": "Feature",
  "properties": {
    "gn:country":"RS",
    "gn:fcode":"PPL",
    "gn:population":1695,
    "iso:country":"RS",
    "name:ceb_x_preferred":[
        "Donji Dobri\u0107"
    ],
    "name:eng_x_preferred":[
        "Donji Dobri\u0107"
    ],
    "name:fra_x_preferred":[
        "Donji Dobri\u0107"
    ],
    "name:hrv_x_preferred":[
        "Donji Dobri\u0107"
    ],
    "name:msa_x_preferred":[
        "Donji Dobri\u0107"
    ],
    "name:nld_x_preferred":[
        "Donji Dobri\u0107"
    ],
    "name:por_x_preferred":[
        "Donji Dobri\u0107"
    ],
    "name:slv_x_preferred":[
        "Gornji Dobri\u0107"
    ],
    "name:srp_x_preferred":[
        "Donji Dobri\u0107"
    ],
    "name:srp_x_variant":[
        "\u0414\u043e\u045a\u0438 \u0414\u043e\u0431\u0440\u0438\u045b"
    ],
    "qs:name":"Donji Dobri\u0107",
    "qs:photos_9r":0,
    "qs:photos_sr":0,
    "qs:pop_sr":"3",
    "wd:wordcount":68,
    "wof:name":"Donji Dobri\u0107",
    "wof:placetype":"locality",
    "wof:population":1695
},
  "geometry": {"coordinates":[19.33109,44.61183],"type":"Point"}
}