{
  "type": "Feature",
  "properties": {
    "gn:country":"RS",
    "gn:fcode":"PPL",
    "gn:pop":1695,
    "iso:country":"RS",
    "name:srp_x_preferred":[
        "Donji Dobri\u0107"
    ],
    "qs:name":"Donji Dobri\u0107",
    "qs:photos_9r":0,
    "qs:photos_sr":0,
    "qs:pop_sr":"3",
    "wd:wordcount":68,
    "wof:name":"Donji Dobri\u0107",
    "wof:placetype":"locality",
    "wof:population":1695
},
  "geometry": {"coordinates":[19.33109,44.61183],"type":"Point"}
}