{
  "type": "Feature",
  "properties": {
    "gn:admin1_code":"SE",
    "gn:admin2_code":"8",
    "gn:asciiname":"Sevarice",
    "gn:country_code":"RS",
    "gn:dem":140,
    "gn:feature_class":"P",
    "gn:feature_code":"PPL",
    "gn:name":"\u0160evarice",
    "gn:population":0,
    "gn:timezone":"Europe/Belgrade",
    "iso:country":"RS",
    "name:und_x_variant":[
        "Severice",
        "\u0160evarice"
    ],
    "wof:name":"Sevarice",
    "wof:placetype":"locality"
},
  "geometry": {"coordinates":[19.69937,44.60126],"type":"Point"}
}