{
  "type": "Feature",
  "properties": {
    "gn:country":"RS",
    "gn:fcode":"PPL",
    "gn:pop":4,
    "iso:country":"RS",
    "qs:name":"Drenovak",
    "qs:photos_9r":0,
    "qs:photos_sr":0,
    "qs:pop_sr":"1",
    "wof:name":"Drenovak",
    "wof:placetype":"locality",
    "wof:population":4
},
  "geometry": {"coordinates":[21.59263,43.50997],"type":"Point"}
}