{
  "type": "Feature",
  "properties": {
    "gn:admin1_code":"SE",
    "gn:admin2_code":"24",
    "gn:asciiname":"Sedmacka Mahala",
    "gn:country_code":"RS",
    "gn:dem":721,
    "gn:feature_class":"P",
    "gn:feature_code":"PPL",
    "gn:name":"Sedma\u010dka Mahala",
    "gn:population":0,
    "gn:timezone":"Europe/Belgrade",
    "iso:country":"RS",
    "wof:name":"Sedmacka Mahala",
    "wof:placetype":"locality"
},
  "geometry": {"coordinates":[21.79417,42.32393],"type":"Point"}
}