{
  "type": "Feature",
  "properties": {
    "gn:admin1_code":"SE",
    "gn:admin2_code":"16",
    "gn:asciiname":"Mackat",
    "gn:country_code":"RS",
    "gn:dem":680,
    "gn:feature_class":"P",
    "gn:feature_code":"PPL",
    "gn:name":"Ma\u010dkat",
    "gn:population":0,
    "gn:timezone":"Europe/Belgrade",
    "iso:country":"RS",
    "name:srp_x_preferred":[
        "Ma\u010dkat"
    ],
    "wof:name":"Mackat",
    "wof:placetype":"locality"
},
  "geometry": {"coordinates":[19.78196,43.79183],"type":"Point"}
}