{
  "type": "Feature",
  "properties": {
    "gn:admin1_code":"SE",
    "gn:admin2_code":"24",
    "gn:asciiname":"Mrtvica",
    "gn:country_code":"RS",
    "gn:dem":568,
    "gn:feature_class":"P",
    "gn:feature_code":"PPLL",
    "gn:name":"Mrtvica",
    "gn:population":0,
    "gn:timezone":"Europe/Belgrade",
    "iso:country":"RS",
    "name:bul_x_preferred":[
        "\u041c\u044a\u0440\u0442\u0432\u0438\u0446\u0430"
    ],
    "name:fra_x_preferred":[
        "Mrtvica"
    ],
    "name:nld_x_preferred":[
        "Mrtvica"
    ],
    "name:por_x_preferred":[
        "Mrtvica"
    ],
    "name:slv_x_preferred":[
        "Mrtvica"
    ],
    "name:srp_x_preferred":[
        "Mrtvica"
    ],
    "name:srp_x_variant":[
        "\u041c\u0440\u0442\u0432\u0438\u0446\u0430"
    ],
    "wof:name":"Mrtvica",
    "wof:placetype":"locality"
},
  "geometry": {"coordinates":[22.07309,42.7809],"type":"Point"}
}