{
  "type": "Feature",
  "properties": {
    "gn:admin1_code":"SE",
    "gn:admin2_code":"24",
    "gn:asciiname":"Mrtvica",
    "gn:country_code":"RS",
    "gn:dem":568,
    "gn:feature_class":"P",
    "gn:feature_code":"PPLL",
    "gn:name":"Mrtvica",
    "gn:population":0,
    "gn:timezone":"Europe/Belgrade",
    "iso:country":"RS",
    "name:srp_x_preferred":[
        "Mrtvica"
    ],
    "wof:name":"Mrtvica",
    "wof:placetype":"locality"
},
  "geometry": {"coordinates":[22.07309,42.7809],"type":"Point"}
}