{
  "type": "Feature",
  "properties": {
    "gn:admin1_code":"SE",
    "gn:admin2_code":"20",
    "gn:asciiname":"Knez-Selo",
    "gn:country_code":"RS",
    "gn:dem":457,
    "gn:feature_class":"P",
    "gn:feature_code":"PPL",
    "gn:name":"Knez-Selo",
    "gn:population":0,
    "gn:timezone":"Europe/Belgrade",
    "iso:country":"RS",
    "name:srp_x_preferred":[
        "Knez-Selo"
    ],
    "wof:name":"Knez-Selo",
    "wof:placetype":"locality"
},
  "geometry": {"coordinates":[22.00124,43.36566],"type":"Point"}
}