{
  "type": "Feature",
  "properties": {
    "gn:admin1_code":"00",
    "gn:asciiname":"Gvozdacko Polje",
    "gn:country_code":"RS",
    "gn:dem":224,
    "gn:feature_class":"P",
    "gn:feature_code":"PPLL",
    "gn:name":"Gvozda\u010dko Polje",
    "gn:population":0,
    "gn:timezone":"Europe/Belgrade",
    "iso:country":"RS",
    "name:srp_x_preferred":[
        "Gvozda\u010dko Polje"
    ],
    "wof:name":"Gvozdacko Polje",
    "wof:placetype":"locality"
},
  "geometry": {"coordinates":[19.60556,44.05768],"type":"Point"}
}