{
  "type": "Feature",
  "properties": {
    "gn:admin1_code":"SE",
    "gn:admin2_code":"24",
    "gn:asciiname":"Slivlje",
    "gn:country_code":"RS",
    "gn:dem":1119,
    "gn:feature_class":"P",
    "gn:feature_code":"PPL",
    "gn:name":"Slivlje",
    "gn:population":0,
    "gn:timezone":"Europe/Belgrade",
    "iso:country":"RS",
    "name:und_x_variant":[
        "Slivije Mala",
        "Slivlje"
    ],
    "wof:name":"Slivlje",
    "wof:placetype":"locality"
},
  "geometry": {"coordinates":[22.30436,42.50949],"type":"Point"}
}