{
  "type": "Feature",
  "properties": {
    "gn:admin1_code":"SE",
    "gn:admin2_code":"23",
    "gn:asciiname":"Svoge",
    "gn:country_code":"RS",
    "gn:dem":313,
    "gn:feature_class":"P",
    "gn:feature_code":"PPL",
    "gn:name":"Svo\u0111e",
    "gn:population":0,
    "gn:timezone":"Europe/Belgrade",
    "iso:country":"RS",
    "name:srp_x_preferred":[
        "Svo\u0111e"
    ],
    "name:und_x_variant":[
        "Svodj",
        "Svogj",
        "Svodje"
    ],
    "wof:name":"Svoge",
    "wof:placetype":"locality"
},
  "geometry": {"coordinates":[22.26562,42.97732],"type":"Point"}
}