{
  "type": "Feature",
  "properties": {
    "gn:admin1_code":"SE",
    "gn:admin2_code":"24",
    "gn:asciiname":"Brezovec",
    "gn:country_code":"RS",
    "gn:dem":1318,
    "gn:feature_class":"P",
    "gn:feature_code":"PPL",
    "gn:name":"Brezovec",
    "gn:population":0,
    "gn:timezone":"Europe/Belgrade",
    "iso:country":"RS",
    "name:bos_x_preferred":[
        "Brezovec"
    ],
    "name:ceb_x_preferred":[
        "Brezovec"
    ],
    "name:ces_x_preferred":[
        "Brezovec"
    ],
    "name:deu_x_preferred":[
        "Brezovec"
    ],
    "name:epo_x_preferred":[
        "Brezovec"
    ],
    "name:eus_x_preferred":[
        "Brezovec"
    ],
    "name:hrv_x_preferred":[
        "Brezovec"
    ],
    "name:hun_x_preferred":[
        "Brezovec"
    ],
    "name:nld_x_preferred":[
        "Brezovec"
    ],
    "name:rus_x_preferred":[
        "\u0411\u0440\u0435\u0437\u043e\u0432\u0435\u0446"
    ],
    "name:slk_x_preferred":[
        "Brezovec"
    ],
    "name:slv_x_preferred":[
        "Brezovec"
    ],
    "name:srp_x_preferred":[
        "Brezovec"
    ],
    "name:srp_x_variant":[
        "\u0411\u0440\u0435\u0437\u043e\u0432\u0435\u0446"
    ],
    "name:swe_x_preferred":[
        "Brezovec"
    ],
    "wof:name":"Brezovec",
    "wof:placetype":"locality"
},
  "geometry": {"coordinates":[22.41737,42.42647],"type":"Point"}
}