{
  "type": "Feature",
  "properties": {
    "gn:admin1_code":"SE",
    "gn:admin2_code":"17",
    "gn:asciiname":"Trbusani",
    "gn:country_code":"RS",
    "gn:dem":244,
    "gn:feature_class":"P",
    "gn:feature_code":"PPL",
    "gn:name":"Trbu\u0161ani",
    "gn:population":0,
    "gn:timezone":"Europe/Belgrade",
    "iso:country":"RS",
    "name:ceb_x_preferred":[
        "Trbu\u0161ani"
    ],
    "name:fra_x_preferred":[
        "Trbu\u0161ani"
    ],
    "name:msa_x_preferred":[
        "Trbu\u0161ani"
    ],
    "name:por_x_preferred":[
        "Trbu\u0161ani"
    ],
    "name:slv_x_preferred":[
        "Trbu\u0161ani"
    ],
    "name:srp_x_preferred":[
        "Trbu\u0161ani"
    ],
    "name:srp_x_variant":[
        "\u0422\u0440\u0431\u0443\u0448\u0430\u043d\u0438"
    ],
    "wof:name":"Trbusani",
    "wof:placetype":"locality"
},
  "geometry": {"coordinates":[20.31183,43.90802],"type":"Point"}
}