{
  "type": "Feature",
  "properties": {
    "gn:admin1_code":"SE",
    "gn:admin2_code":"9",
    "gn:asciiname":"Krcmar",
    "gn:country_code":"RS",
    "gn:dem":485,
    "gn:feature_class":"P",
    "gn:feature_code":"PPL",
    "gn:name":"Kr\u010dmar",
    "gn:population":0,
    "gn:timezone":"Europe/Belgrade",
    "iso:country":"RS",
    "name:srp_x_preferred":[
        "Kr\u010dmar"
    ],
    "name:und_x_variant":[
        "Kr\u010dmari"
    ],
    "wof:name":"Krcmar",
    "wof:placetype":"locality"
},
  "geometry": {"coordinates":[19.98189,44.16391],"type":"Point"}
}