{
  "type": "Feature",
  "properties": {
    "gn:admin1_code":"SE",
    "gn:admin2_code":"9",
    "gn:asciiname":"Krcmar",
    "gn:country_code":"RS",
    "gn:dem":485,
    "gn:feature_class":"P",
    "gn:feature_code":"PPL",
    "gn:name":"Kr\u010dmar",
    "gn:population":0,
    "gn:timezone":"Europe/Belgrade",
    "iso:country":"RS",
    "name:ceb_x_preferred":[
        "Kr\u010dmar"
    ],
    "name:fas_x_preferred":[
        "\u06a9\u0631\u0686\u0645\u0627\u0631"
    ],
    "name:fra_x_preferred":[
        "Kr\u010dmar"
    ],
    "name:msa_x_preferred":[
        "Kr\u010dmar"
    ],
    "name:por_x_preferred":[
        "Kr\u010dmar"
    ],
    "name:slv_x_preferred":[
        "Kr\u010dmar"
    ],
    "name:srp_x_preferred":[
        "Kr\u010dmar"
    ],
    "name:srp_x_variant":[
        "\u041a\u0440\u0447\u043c\u0430\u0440"
    ],
    "name:und_x_variant":[
        "Kr\u010dmari"
    ],
    "wof:name":"Krcmar",
    "wof:placetype":"locality"
},
  "geometry": {"coordinates":[19.98189,44.16391],"type":"Point"}
}