{
  "type": "Feature",
  "properties": {
    "gn:admin1_code":"SE",
    "gn:admin2_code":"9",
    "gn:asciiname":"Andrici",
    "gn:country_code":"RS",
    "gn:dem":386,
    "gn:feature_class":"P",
    "gn:feature_code":"PPL",
    "gn:name":"Andri\u0107i",
    "gn:population":0,
    "gn:timezone":"Europe/Belgrade",
    "iso:country":"RS",
    "name:srp_x_preferred":[
        "Andri\u0107i"
    ],
    "wof:name":"Andrici",
    "wof:placetype":"locality"
},
  "geometry": {"coordinates":[19.69787,44.39093],"type":"Point"}
}