{
  "type": "Feature",
  "properties": {
    "gn:admin1_code":"SE",
    "gn:admin2_code":"21",
    "gn:asciiname":"Mala Vlasa",
    "gn:country_code":"RS",
    "gn:dem":962,
    "gn:feature_class":"P",
    "gn:feature_code":"PPL",
    "gn:name":"Mala Vlasa",
    "gn:population":0,
    "gn:timezone":"Europe/Belgrade",
    "iso:country":"RS",
    "name:und_x_variant":[
        "Vlasa",
        "Mala Vlasa"
    ],
    "wof:name":"Mala Vlasa",
    "wof:placetype":"locality"
},
  "geometry": {"coordinates":[21.48108,43.0483],"type":"Point"}
}