{
  "type": "Feature",
  "properties": {
    "gn:admin1_code":"SE",
    "gn:admin2_code":"16",
    "gn:asciiname":"Koraci",
    "gn:country_code":"RS",
    "gn:dem":1262,
    "gn:feature_class":"P",
    "gn:feature_code":"PPL",
    "gn:name":"Kora\u0107i",
    "gn:population":0,
    "gn:timezone":"Europe/Belgrade",
    "iso:country":"RS",
    "name:srp_x_preferred":[
        "Kora\u0107i"
    ],
    "wof:name":"Koraci",
    "wof:placetype":"locality"
},
  "geometry": {"coordinates":[19.87138,43.23192],"type":"Point"}
}