{
  "type": "Feature",
  "properties": {
    "gn:admin1_code":"SE",
    "gn:admin2_code":"16",
    "gn:asciiname":"Godljevo",
    "gn:country_code":"RS",
    "gn:dem":575,
    "gn:feature_class":"P",
    "gn:feature_code":"PPL",
    "gn:name":"Godljevo",
    "gn:population":0,
    "gn:timezone":"Europe/Belgrade",
    "iso:country":"RS",
    "name:ceb_x_preferred":[
        "Godljevo"
    ],
    "name:fra_x_preferred":[
        "Godljevo"
    ],
    "name:msa_x_preferred":[
        "Godljevo"
    ],
    "name:nld_x_preferred":[
        "Godljevo"
    ],
    "name:por_x_preferred":[
        "Godljevo"
    ],
    "name:slv_x_preferred":[
        "Godljevo"
    ],
    "name:srp_x_preferred":[
        "Godljevo"
    ],
    "name:srp_x_variant":[
        "\u0413\u043e\u0434\u0459\u0435\u0432\u043e"
    ],
    "wof:name":"Godljevo",
    "wof:placetype":"locality"
},
  "geometry": {"coordinates":[19.83823,44.02966],"type":"Point"}
}