{
  "type": "Feature",
  "properties": {
    "gn:admin1_code":"SE",
    "gn:admin2_code":"21",
    "gn:asciiname":"Krompiriste",
    "gn:country_code":"RS",
    "gn:dem":748,
    "gn:feature_class":"P",
    "gn:feature_code":"PPL",
    "gn:name":"Krompiri\u0161te",
    "gn:population":0,
    "gn:timezone":"Europe/Belgrade",
    "iso:country":"RS",
    "name:srp_x_preferred":[
        "Krompiri\u0161te"
    ],
    "wof:name":"Krompiriste",
    "wof:placetype":"locality"
},
  "geometry": {"coordinates":[21.34961,43.06799],"type":"Point"}
}