{
  "type": "Feature",
  "properties": {
    "gn:country":"RS",
    "gn:fcode":"PPLL",
    "gn:pop":192,
    "iso:country":"RS",
    "name:dut_x_preferred":[
        "Miljkovica"
    ],
    "name:eng_x_preferred":[
        "Miljkovica"
    ],
    "name:fre_x_preferred":[
        "Miljkovica"
    ],
    "name:may_x_preferred":[
        "Miljkovica"
    ],
    "name:por_x_preferred":[
        "Miljkovica"
    ],
    "name:slv_x_preferred":[
        "Miljkovica"
    ],
    "name:srp_x_preferred":[
        "Miljkovica"
    ],
    "qs:name":"Miljkovica",
    "qs:photos_9r":0,
    "qs:photos_sr":0,
    "qs:pop_sr":"1",
    "wd:wordcount":69,
    "wof:name":"Miljkovica",
    "wof:placetype":"locality",
    "wof:population":192
},
  "geometry": {"coordinates":[21.49167,43.19472],"type":"Point"}
}