{
  "type": "Feature",
  "properties": {
    "gn:country":"RS",
    "gn:fcode":"PPLL",
    "gn:population":192,
    "iso:country":"RS",
    "name:ceb_x_preferred":[
        "Miljkovica"
    ],
    "name:eng_x_preferred":[
        "Miljkovica"
    ],
    "name:fas_x_preferred":[
        "\u0645\u06cc\u06cc\u06a9\u0648\u0648\u06cc\u062a\u0633\u0627"
    ],
    "name:fra_x_preferred":[
        "Miljkovica"
    ],
    "name:msa_x_preferred":[
        "Miljkovica"
    ],
    "name:nld_x_preferred":[
        "Miljkovica"
    ],
    "name:pol_x_preferred":[
        "Miljkovica"
    ],
    "name:por_x_preferred":[
        "Miljkovica"
    ],
    "name:slv_x_preferred":[
        "Miljkovica"
    ],
    "name:srp_x_preferred":[
        "Miljkovica"
    ],
    "name:srp_x_variant":[
        "\u041c\u0438\u0459\u043a\u043e\u0432\u0438\u0446\u0430"
    ],
    "qs:name":"Miljkovica",
    "qs:photos_9r":0,
    "qs:photos_sr":0,
    "qs:pop_sr":"1",
    "wd:wordcount":69,
    "wof:name":"Miljkovica",
    "wof:placetype":"locality",
    "wof:population":192
},
  "geometry": {"coordinates":[21.49167,43.19472],"type":"Point"}
}