{
  "type": "Feature",
  "properties": {
    "gn:admin1_code":"SE",
    "gn:admin2_code":"16",
    "gn:asciiname":"Suvo Polje",
    "gn:country_code":"RS",
    "gn:dem":600,
    "gn:feature_class":"P",
    "gn:feature_code":"PPL",
    "gn:name":"Suvo Polje",
    "gn:population":0,
    "gn:timezone":"Europe/Belgrade",
    "iso:country":"RS",
    "name:srp_x_preferred":[
        "Suvo Polje"
    ],
    "wof:name":"Suvo Polje",
    "wof:placetype":"locality"
},
  "geometry": {"coordinates":[19.57941,43.53417],"type":"Point"}
}