{
  "type": "Feature",
  "properties": {
    "gn:admin1_code":"SE",
    "gn:admin2_code":"24",
    "gn:asciiname":"Rakov Dol",
    "gn:country_code":"RS",
    "gn:dem":991,
    "gn:feature_class":"P",
    "gn:feature_code":"PPL",
    "gn:name":"Rakov Dol",
    "gn:population":0,
    "gn:timezone":"Europe/Belgrade",
    "iso:country":"RS",
    "name:fra_x_preferred":[
        "Rakov Dol"
    ],
    "name:hun_x_preferred":[
        "Rakov Dol"
    ],
    "name:msa_x_preferred":[
        "Rakov Dol"
    ],
    "name:por_x_preferred":[
        "Rakov Dol"
    ],
    "name:slv_x_preferred":[
        "Rakov Dol"
    ],
    "name:srp_x_preferred":[
        "\u0420\u0430\u043a\u043e\u0432 \u0414\u043e\u043b"
    ],
    "wof:name":"Rakov Dol",
    "wof:placetype":"locality"
},
  "geometry": {"coordinates":[22.44307,42.40779000000001],"type":"Point"}
}