{
  "type": "Feature",
  "properties": {
    "gn:admin1_code":"SE",
    "gn:admin2_code":"16",
    "gn:asciiname":"Opancine",
    "gn:country_code":"RS",
    "gn:dem":787,
    "gn:feature_class":"P",
    "gn:feature_code":"PPLL",
    "gn:name":"Opan\u010dine",
    "gn:population":0,
    "gn:timezone":"Europe/Belgrade",
    "iso:country":"RS",
    "name:srp_x_preferred":[
        "Opan\u010dine"
    ],
    "wof:name":"Opancine",
    "wof:placetype":"locality"
},
  "geometry": {"coordinates":[19.65152,43.22461],"type":"Point"}
}