{
  "type": "Feature",
  "properties": {
    "gn:admin1_code":"00",
    "gn:asciiname":"Kovaceva Mahala",
    "gn:country_code":"RS",
    "gn:dem":1127,
    "gn:feature_class":"P",
    "gn:feature_code":"PPL",
    "gn:name":"Kova\u010deva Mahala",
    "gn:population":0,
    "gn:timezone":"Europe/Belgrade",
    "iso:country":"RS",
    "name:und_x_variant":[
        "Mahala Kova\u010devci",
        "Kova\u010deva Mahala"
    ],
    "wof:name":"Kovaceva Mahala",
    "wof:placetype":"locality"
},
  "geometry": {"coordinates":[22.48052,42.54794],"type":"Point"}
}