{
  "type": "Feature",
  "properties": {
    "gn:admin1_code":"VO",
    "gn:admin2_code":"5",
    "gn:asciiname":"Aleksa Santic",
    "gn:country_code":"RS",
    "gn:dem":119,
    "gn:feature_class":"P",
    "gn:feature_code":"PPL",
    "gn:name":"Aleksa \u0160anti\u0107",
    "gn:population":0,
    "gn:timezone":"Europe/Belgrade",
    "iso:country":"RS",
    "name:srp_x_preferred":[
        "Aleksa \u0160anti\u0107"
    ],
    "wof:name":"Aleksa Santic",
    "wof:placetype":"locality"
},
  "geometry": {"coordinates":[19.33252,45.92843],"type":"Point"}
}