{
  "type": "Feature",
  "properties": {
    "gn:admin1_code":"SE",
    "gn:admin2_code":"23",
    "gn:asciiname":"Cukovac",
    "gn:country_code":"RS",
    "gn:dem":283,
    "gn:feature_class":"P",
    "gn:feature_code":"PPL",
    "gn:name":"\u010cukovac",
    "gn:population":0,
    "gn:timezone":"Europe/Belgrade",
    "iso:country":"RS",
    "name:srp_x_preferred":[
        "\u010cukovac"
    ],
    "wof:name":"Cukovac",
    "wof:placetype":"locality"
},
  "geometry": {"coordinates":[21.73682,43.08312],"type":"Point"}
}