{
  "type": "Feature",
  "properties": {
    "gn:admin1_code":"SE",
    "gn:admin2_code":"18",
    "gn:asciiname":"Bukovica",
    "gn:country_code":"RS",
    "gn:dem":331,
    "gn:feature_class":"P",
    "gn:feature_code":"PPLL",
    "gn:name":"Bukovica",
    "gn:population":0,
    "gn:timezone":"Europe/Belgrade",
    "iso:country":"RS",
    "name:srp_x_preferred":[
        "Bukovica"
    ],
    "wof:name":"Bukovica",
    "wof:placetype":"locality"
},
  "geometry": {"coordinates":[20.53812000000001,43.72919],"type":"Point"}
}