{
  "type": "Feature",
  "properties": {
    "gn:admin1_code":"SE",
    "gn:admin2_code":"10",
    "gn:asciiname":"Seone",
    "gn:country_code":"RS",
    "gn:dem":168,
    "gn:feature_class":"P",
    "gn:feature_code":"PPL",
    "gn:name":"Seone",
    "gn:population":0,
    "gn:timezone":"Europe/Belgrade",
    "iso:country":"RS",
    "name:ceb_x_preferred":[
        "Seone"
    ],
    "name:fra_x_preferred":[
        "Seone"
    ],
    "name:msa_x_preferred":[
        "Seone"
    ],
    "name:por_x_preferred":[
        "Seone"
    ],
    "name:slv_x_preferred":[
        "Seone"
    ],
    "name:srp_x_preferred":[
        "Seone"
    ],
    "name:srp_x_variant":[
        "\u0421\u0435\u043e\u043d\u0435"
    ],
    "name:und_x_variant":[
        "Seona"
    ],
    "wof:name":"Seone",
    "wof:placetype":"locality"
},
  "geometry": {"coordinates":[20.81785,44.63595],"type":"Point"}
}