{
  "type": "Feature",
  "properties": {
    "gn:admin1_code":"SE",
    "gn:admin2_code":"18",
    "gn:asciiname":"Bogicevici",
    "gn:country_code":"RS",
    "gn:dem":917,
    "gn:feature_class":"P",
    "gn:feature_code":"PPL",
    "gn:name":"Bogi\u010devi\u0107i",
    "gn:population":0,
    "gn:timezone":"Europe/Belgrade",
    "iso:country":"RS",
    "name:srp_x_preferred":[
        "Bogi\u010devi\u0107i"
    ],
    "wof:name":"Bogicevici",
    "wof:placetype":"locality"
},
  "geometry": {"coordinates":[20.37296,43.49627],"type":"Point"}
}