{
  "type": "Feature",
  "properties": {
    "gn:admin1_code":"SE",
    "gn:admin2_code":"9",
    "gn:asciiname":"Beomuzevic",
    "gn:country_code":"RS",
    "gn:dem":331,
    "gn:feature_class":"P",
    "gn:feature_code":"PPL",
    "gn:name":"Beomu\u017eevi\u0107",
    "gn:population":0,
    "gn:timezone":"Europe/Belgrade",
    "iso:country":"RS",
    "name:ceb_x_preferred":[
        "Beomu\u017eevi\u0107"
    ],
    "name:fra_x_preferred":[
        "Beomu\u017eevi\u0107"
    ],
    "name:msa_x_preferred":[
        "Beomu\u017eevi\u0107"
    ],
    "name:nld_x_preferred":[
        "Beomu\u017eevi\u0107"
    ],
    "name:por_x_preferred":[
        "Beomu\u017eevi\u0107"
    ],
    "name:slv_x_preferred":[
        "Beomu\u017eevi\u0107"
    ],
    "name:srp_x_preferred":[
        "Beomu\u017eevi\u0107"
    ],
    "name:srp_x_variant":[
        "\u0411\u0435\u043e\u043c\u0443\u0436\u0435\u0432\u0438\u045b"
    ],
    "wof:name":"Beomuzevic",
    "wof:placetype":"locality"
},
  "geometry": {"coordinates":[19.75588,44.30588],"type":"Point"}
}