{
  "type": "Feature",
  "properties": {
    "gn:admin1_code":"SE",
    "gn:admin2_code":"24",
    "gn:asciiname":"Dancina Mahala",
    "gn:country_code":"RS",
    "gn:dem":1238,
    "gn:feature_class":"P",
    "gn:feature_code":"PPL",
    "gn:name":"Dan\u010dina Mahala",
    "gn:population":0,
    "gn:timezone":"Europe/Belgrade",
    "iso:country":"RS",
    "wof:name":"Dancina Mahala",
    "wof:placetype":"locality"
},
  "geometry": {"coordinates":[22.36179,42.58026],"type":"Point"}
}