{
  "type": "Feature",
  "properties": {
    "gn:admin1_code":"SE",
    "gn:admin2_code":"16",
    "gn:asciiname":"Zarici",
    "gn:country_code":"RS",
    "gn:dem":705,
    "gn:feature_class":"P",
    "gn:feature_code":"PPL",
    "gn:name":"Zari\u0107i",
    "gn:population":0,
    "gn:timezone":"Europe/Belgrade",
    "iso:country":"RS",
    "name:srp_x_preferred":[
        "Zari\u0107i"
    ],
    "wof:name":"Zarici",
    "wof:placetype":"locality"
},
  "geometry": {"coordinates":[19.75665,43.80534],"type":"Point"}
}