{
  "type": "Feature",
  "properties": {
    "gn:admin1_code":"SE",
    "gn:admin2_code":"24",
    "gn:asciiname":"Ivkovci",
    "gn:country_code":"RS",
    "gn:dem":732,
    "gn:feature_class":"P",
    "gn:feature_code":"PPL",
    "gn:name":"Ivkovci",
    "gn:population":0,
    "gn:timezone":"Europe/Belgrade",
    "iso:country":"RS",
    "wof:name":"Ivkovci",
    "wof:placetype":"locality"
},
  "geometry": {"coordinates":[22.03185,42.72979],"type":"Point"}
}