{
  "type": "Feature",
  "properties": {
    "gn:admin1_code":"SE",
    "gn:admin2_code":"18",
    "gn:asciiname":"Boturovina",
    "gn:country_code":"RS",
    "gn:dem":584,
    "gn:feature_class":"P",
    "gn:feature_code":"PPLL",
    "gn:name":"Boturovina",
    "gn:population":0,
    "gn:timezone":"Europe/Belgrade",
    "iso:country":"RS",
    "name:ceb_x_preferred":[
        "Boturovina"
    ],
    "name:fra_x_preferred":[
        "Boturovina"
    ],
    "name:hun_x_preferred":[
        "Boturovina"
    ],
    "name:msa_x_preferred":[
        "Boturovina"
    ],
    "name:nld_x_preferred":[
        "Boturovina"
    ],
    "name:por_x_preferred":[
        "Boturovina"
    ],
    "name:slv_x_preferred":[
        "Boturovina"
    ],
    "name:srp_x_preferred":[
        "Boturovina"
    ],
    "name:srp_x_variant":[
        "\u0411\u043e\u0442\u0443\u0440\u043e\u0432\u0438\u043d\u0430"
    ],
    "wof:name":"Boturovina",
    "wof:placetype":"locality"
},
  "geometry": {"coordinates":[20.48389,43.17889],"type":"Point"}
}