{
  "type": "Feature",
  "properties": {
    "gn:admin1_code":"SE",
    "gn:admin2_code":"24",
    "gn:asciiname":"Stanojinci",
    "gn:country_code":"RS",
    "gn:dem":1179,
    "gn:feature_class":"P",
    "gn:feature_code":"PPL",
    "gn:name":"Stanojinci",
    "gn:population":0,
    "gn:timezone":"Europe/Belgrade",
    "iso:country":"RS",
    "name:srp_x_preferred":[
        "Stanojinci"
    ],
    "wof:name":"Stanojinci",
    "wof:placetype":"locality"
},
  "geometry": {"coordinates":[22.20631,42.34268],"type":"Point"}
}