{
  "type": "Feature",
  "properties": {
    "gn:admin1_code":"SE",
    "gn:admin2_code":"16",
    "gn:asciiname":"Vujadinovici",
    "gn:country_code":"RS",
    "gn:dem":807,
    "gn:feature_class":"P",
    "gn:feature_code":"PPL",
    "gn:name":"Vujadinovi\u0107i",
    "gn:population":0,
    "gn:timezone":"Europe/Belgrade",
    "iso:country":"RS",
    "wof:name":"Vujadinovici",
    "wof:placetype":"locality"
},
  "geometry": {"coordinates":[19.9775,43.65444],"type":"Point"}
}