{
  "type": "Feature",
  "properties": {
    "gn:admin1_code":"SE",
    "gn:admin2_code":"13",
    "gn:asciiname":"Kovanica",
    "gn:country_code":"RS",
    "gn:dem":341,
    "gn:feature_class":"P",
    "gn:feature_code":"PPL",
    "gn:name":"Kovanica",
    "gn:population":0,
    "gn:timezone":"Europe/Belgrade",
    "iso:country":"RS",
    "name:ceb_x_preferred":[
        "Kovanica"
    ],
    "name:fas_x_preferred":[
        "\u06a9\u0648\u0648\u0627\u0646\u06cc\u0633\u062a\u0627"
    ],
    "name:fra_x_preferred":[
        "Kovanica"
    ],
    "name:msa_x_preferred":[
        "Kovanica"
    ],
    "name:por_x_preferred":[
        "Kovanica"
    ],
    "name:slv_x_preferred":[
        "Kovanica"
    ],
    "name:srp_x_preferred":[
        "Kovanica"
    ],
    "name:srp_x_variant":[
        "\u041a\u043e\u0432\u0430\u043d\u0438\u0446\u0430"
    ],
    "wof:name":"Kovanica",
    "wof:placetype":"locality"
},
  "geometry": {"coordinates":[21.49749,44.03267],"type":"Point"}
}