{
  "type": "Feature",
  "properties": {
    "gn:admin1_code":"SE",
    "gn:admin2_code":"13",
    "gn:asciiname":"Kovanica",
    "gn:country_code":"RS",
    "gn:dem":341,
    "gn:feature_class":"P",
    "gn:feature_code":"PPL",
    "gn:name":"Kovanica",
    "gn:population":0,
    "gn:timezone":"Europe/Belgrade",
    "iso:country":"RS",
    "name:srp_x_preferred":[
        "Kovanica"
    ],
    "wof:name":"Kovanica",
    "wof:placetype":"locality"
},
  "geometry": {"coordinates":[21.49749,44.03267],"type":"Point"}
}