{
  "type": "Feature",
  "properties": {
    "gn:admin1_code":"SE",
    "gn:admin2_code":"15",
    "gn:asciiname":"Vrbovac",
    "gn:country_code":"RS",
    "gn:dem":300,
    "gn:feature_class":"P",
    "gn:feature_code":"PPL",
    "gn:name":"Vrbovac",
    "gn:population":0,
    "gn:timezone":"Europe/Belgrade",
    "iso:country":"RS",
    "name:bos_x_preferred":[
        "Vrbovac"
    ],
    "name:ceb_x_preferred":[
        "Vrbovac"
    ],
    "name:deu_x_preferred":[
        "Vrbovac"
    ],
    "name:fra_x_preferred":[
        "Vrbovac"
    ],
    "name:hrv_x_preferred":[
        "Vrbovac"
    ],
    "name:hun_x_preferred":[
        "Vrbovac"
    ],
    "name:nld_x_preferred":[
        "Vrbovac"
    ],
    "name:slv_x_preferred":[
        "Vrbovac"
    ],
    "name:srp_x_preferred":[
        "Vrbovac"
    ],
    "name:srp_x_variant":[
        "\u0412\u0440\u0431\u043e\u0432\u0430\u0446"
    ],
    "name:swe_x_preferred":[
        "Vrbovac"
    ],
    "wof:name":"Vrbovac",
    "wof:placetype":"locality"
},
  "geometry": {"coordinates":[22.09456,43.81269],"type":"Point"}
}