{
  "type": "Feature",
  "properties": {
    "gn:country":"RS",
    "gn:fcode":"PPL",
    "gn:pop":3541,
    "iso:country":"RS",
    "name:dut_x_preferred":[
        "\u0160ajka\u0161"
    ],
    "name:eng_x_preferred":[
        "\u0160ajka\u0161"
    ],
    "name:epo_x_preferred":[
        "\u015cajka\u015d"
    ],
    "name:fre_x_preferred":[
        "\u0160ajka\u0161"
    ],
    "name:hrv_x_preferred":[
        "\u0160ajka\u0161"
    ],
    "name:hun_x_preferred":[
        "Sajk\u00e1sszentiv\u00e1n"
    ],
    "name:may_x_preferred":[
        "\u0160ajka\u0161"
    ],
    "name:pol_x_preferred":[
        "\u0160ajka\u0161"
    ],
    "name:slv_x_preferred":[
        "\u0160ajka\u0161"
    ],
    "name:srp_x_preferred":[
        "\u0160ajka\u0161"
    ],
    "name:unk_x_variant":[
        "Kovil-Szent-Iv\u00e1n"
    ],
    "qs:name":"Sajkas",
    "qs:name_adm0":"Serbia",
    "qs:name_adm1":"Juzhna Bachka",
    "qs:photos_9r":0,
    "qs:photos_sr":0,
    "qs:placetype":"Town",
    "qs:pop_sr":"4",
    "wof:name":"Sajkas",
    "wof:placetype":"locality",
    "wof:population":3541
},
  "geometry": {"coordinates":[20.09051,45.27315],"type":"Point"}
}