{
  "type": "Feature",
  "properties": {
    "gn:admin1_code":"SE",
    "gn:admin2_code":"18",
    "gn:asciiname":"Raduhovce",
    "gn:country_code":"RS",
    "gn:dem":925,
    "gn:feature_class":"P",
    "gn:feature_code":"PPL",
    "gn:name":"Raduhovce",
    "gn:population":0,
    "gn:timezone":"Europe/Belgrade",
    "iso:country":"RS",
    "name:ceb_x_preferred":[
        "Raduhovce"
    ],
    "name:fra_x_preferred":[
        "Raduhovce"
    ],
    "name:msa_x_preferred":[
        "Raduhovce"
    ],
    "name:nld_x_preferred":[
        "Raduhovce"
    ],
    "name:por_x_preferred":[
        "Raduhovce"
    ],
    "name:slv_x_preferred":[
        "Raduhovce"
    ],
    "name:sqi_x_preferred":[
        "Raduhoci"
    ],
    "name:srp_x_preferred":[
        "Raduhovce"
    ],
    "name:srp_x_variant":[
        "\u0420\u0430\u0434\u0443\u0445\u043e\u0432\u0446\u0435"
    ],
    "name:und_x_variant":[
        "Raduovci"
    ],
    "wof:name":"Raduhovce",
    "wof:placetype":"locality"
},
  "geometry": {"coordinates":[20.41176,43.03932],"type":"Point"}
}