{
  "type": "Feature",
  "properties": {
    "gn:admin1_code":"SE",
    "gn:admin2_code":"18",
    "gn:asciiname":"Lipovac",
    "gn:country_code":"RS",
    "gn:dem":786,
    "gn:feature_class":"P",
    "gn:feature_code":"PPL",
    "gn:name":"Lipovac",
    "gn:population":0,
    "gn:timezone":"Europe/Belgrade",
    "iso:country":"RS",
    "name:bos_x_preferred":[
        "Lipovac"
    ],
    "name:ceb_x_preferred":[
        "Lipovac"
    ],
    "name:deu_x_preferred":[
        "Lipovac"
    ],
    "name:fra_x_preferred":[
        "Lipovac"
    ],
    "name:hrv_x_preferred":[
        "Lipovac"
    ],
    "name:hun_x_preferred":[
        "Lipovac"
    ],
    "name:nld_x_preferred":[
        "Lipovac"
    ],
    "name:slv_x_preferred":[
        "Lipovac"
    ],
    "name:spa_x_preferred":[
        "Lipovac"
    ],
    "name:srp_x_preferred":[
        "Lipovac"
    ],
    "name:srp_x_variant":[
        "\u041b\u0438\u043f\u043e\u0432\u0430\u0446"
    ],
    "name:swe_x_preferred":[
        "Lipovac"
    ],
    "wof:name":"Lipovac",
    "wof:placetype":"locality"
},
  "geometry": {"coordinates":[20.53722,43.45806],"type":"Point"}
}