{
  "type": "Feature",
  "properties": {
    "gn:admin1_code":"SE",
    "gn:admin2_code":"8",
    "gn:asciiname":"Samardzici",
    "gn:country_code":"RS",
    "gn:dem":688,
    "gn:feature_class":"P",
    "gn:feature_code":"PPL",
    "gn:name":"Samard\u017ei\u0107i",
    "gn:population":0,
    "gn:timezone":"Europe/Belgrade",
    "iso:country":"RS",
    "name:srp_x_preferred":[
        "Samard\u017ei\u0107i"
    ],
    "wof:name":"Samardzici",
    "wof:placetype":"locality"
},
  "geometry": {"coordinates":[19.25083,44.33778],"type":"Point"}
}