{
  "type": "Feature",
  "properties": {
    "gn:admin1_code":"SE",
    "gn:admin2_code":"24",
    "gn:asciiname":"Malikina Mahala",
    "gn:country_code":"RS",
    "gn:dem":1105,
    "gn:feature_class":"P",
    "gn:feature_code":"PPL",
    "gn:name":"Malikina Mahala",
    "gn:population":0,
    "gn:timezone":"Europe/Belgrade",
    "iso:country":"RS",
    "wof:name":"Malikina Mahala",
    "wof:placetype":"locality"
},
  "geometry": {"coordinates":[22.23532,42.72683],"type":"Point"}
}