{
  "type": "Feature",
  "properties": {
    "gn:admin1_code":"SE",
    "gn:admin2_code":"17",
    "gn:asciiname":"Osredak",
    "gn:country_code":"RS",
    "gn:dem":828,
    "gn:feature_class":"P",
    "gn:feature_code":"PPL",
    "gn:name":"Osredak",
    "gn:population":0,
    "gn:timezone":"Europe/Belgrade",
    "iso:country":"RS",
    "name:bos_x_preferred":[
        "Osredak"
    ],
    "name:ceb_x_preferred":[
        "Osredak"
    ],
    "name:fra_x_preferred":[
        "Osredak"
    ],
    "name:hrv_x_preferred":[
        "Osredak"
    ],
    "name:srp_x_preferred":[
        "Osredak"
    ],
    "name:srp_x_variant":[
        "\u041e\u0441\u0440\u0435\u0434\u0430\u043a"
    ],
    "name:swe_x_preferred":[
        "Osredak"
    ],
    "wof:name":"Osredak",
    "wof:placetype":"locality"
},
  "geometry": {"coordinates":[20.05472,43.55306],"type":"Point"}
}