{
  "type": "Feature",
  "properties": {
    "iso:country":"RS",
    "name:eng_x_preferred":[
        "Blok 3"
    ],
    "name:srp_cyr_x_preferred":[
        "\u0431\u043b\u043e\u043a 3"
    ],
    "name:srp_x_preferred":[
        "\u0431\u043b\u043e\u043a 3"
    ],
    "wof:name":"Blok 3",
    "wof:placetype":"neighbourhood"
},
  "geometry": {"coordinates":[20.40513523404024,44.8256484312859],"type":"Point"}
}