{
  "type": "Feature",
  "properties": {
    "gn:admin1_code":"SE",
    "gn:admin2_code":"11",
    "gn:asciiname":"Dragovac",
    "gn:country_code":"RS",
    "gn:dem":76,
    "gn:feature_class":"P",
    "gn:feature_code":"PPL",
    "gn:name":"Dragovac",
    "gn:population":0,
    "gn:timezone":"Europe/Belgrade",
    "iso:country":"RS",
    "name:bos_x_preferred":[
        "Dragovac"
    ],
    "name:ceb_x_preferred":[
        "Dragovac"
    ],
    "name:fra_x_preferred":[
        "Dragovac"
    ],
    "name:hrv_x_preferred":[
        "Dragovac"
    ],
    "name:nld_x_preferred":[
        "Dragovac"
    ],
    "name:ron_x_preferred":[
        "Dragovac"
    ],
    "name:slv_x_preferred":[
        "Dragovac"
    ],
    "name:sqi_x_preferred":[
        "Dragoci"
    ],
    "name:srp_x_preferred":[
        "Dragovac"
    ],
    "name:srp_x_variant":[
        "\u0414\u0440\u0430\u0433\u043e\u0432\u0430\u0446"
    ],
    "name:swe_x_preferred":[
        "Dragovac"
    ],
    "wof:name":"Dragovac",
    "wof:placetype":"locality"
},
  "geometry": {"coordinates":[21.10361,44.61845],"type":"Point"}
}