{
  "type": "Feature",
  "properties": {
    "gn:admin1_code":"SE",
    "gn:admin2_code":"9",
    "gn:asciiname":"Topalovici",
    "gn:country_code":"RS",
    "gn:dem":581,
    "gn:feature_class":"P",
    "gn:feature_code":"PPL",
    "gn:name":"Topalovi\u0107i",
    "gn:population":0,
    "gn:timezone":"Europe/Belgrade",
    "iso:country":"RS",
    "name:srp_x_preferred":[
        "Topalovi\u0107i"
    ],
    "wof:name":"Topalovici",
    "wof:placetype":"locality"
},
  "geometry": {"coordinates":[19.48746,44.29095],"type":"Point"}
}