{
  "type": "Feature",
  "properties": {
    "gn:admin1_code":"SE",
    "gn:admin2_code":"15",
    "gn:asciiname":"Trnovac",
    "gn:country_code":"RS",
    "gn:dem":232,
    "gn:feature_class":"P",
    "gn:feature_code":"PPL",
    "gn:name":"Trnovac",
    "gn:population":0,
    "gn:timezone":"Europe/Belgrade",
    "iso:country":"RS",
    "name:srp_x_preferred":[
        "Trnovac"
    ],
    "wof:name":"Trnovac",
    "wof:placetype":"locality"
},
  "geometry": {"coordinates":[22.2615,43.67965],"type":"Point"}
}