{
  "type": "Feature",
  "properties": {
    "gn:admin1_code":"SE",
    "gn:admin2_code":"15",
    "gn:asciiname":"Trnovac",
    "gn:country_code":"RS",
    "gn:dem":232,
    "gn:feature_class":"P",
    "gn:feature_code":"PPL",
    "gn:name":"Trnovac",
    "gn:population":0,
    "gn:timezone":"Europe/Belgrade",
    "iso:country":"RS",
    "name:bos_x_preferred":[
        "Trnovac"
    ],
    "name:ceb_x_preferred":[
        "Trnovac"
    ],
    "name:fra_x_preferred":[
        "Trnovac"
    ],
    "name:hrv_x_preferred":[
        "Trnovac"
    ],
    "name:hun_x_preferred":[
        "Trnovac"
    ],
    "name:nld_x_preferred":[
        "Trnovac"
    ],
    "name:slv_x_preferred":[
        "Trnovac"
    ],
    "name:srp_x_preferred":[
        "Trnovac"
    ],
    "name:srp_x_variant":[
        "\u0422\u0440\u043d\u043e\u0432\u0430\u0446"
    ],
    "name:swe_x_preferred":[
        "Trnovac"
    ],
    "name:ukr_x_preferred":[
        "\u0422\u0440\u043d\u043e\u0432\u0430\u0446\u044c"
    ],
    "wof:name":"Trnovac",
    "wof:placetype":"locality"
},
  "geometry": {"coordinates":[22.2615,43.67965],"type":"Point"}
}