{
  "type": "Feature",
  "properties": {
    "gn:admin1_code":"SE",
    "gn:admin2_code":"17",
    "gn:asciiname":"Komadine",
    "gn:country_code":"RS",
    "gn:dem":882,
    "gn:feature_class":"P",
    "gn:feature_code":"PPLL",
    "gn:name":"Komadine",
    "gn:population":0,
    "gn:timezone":"Europe/Belgrade",
    "iso:country":"RS",
    "name:srp_x_preferred":[
        "Komadine"
    ],
    "wof:name":"Komadine",
    "wof:placetype":"locality"
},
  "geometry": {"coordinates":[20.25721,43.50155],"type":"Point"}
}