{
  "type": "Feature",
  "properties": {
    "gn:admin1_code":"SE",
    "gn:admin2_code":"17",
    "gn:asciiname":"Komadine",
    "gn:country_code":"RS",
    "gn:dem":882,
    "gn:feature_class":"P",
    "gn:feature_code":"PPLL",
    "gn:name":"Komadine",
    "gn:population":0,
    "gn:timezone":"Europe/Belgrade",
    "iso:country":"RS",
    "name:ceb_x_preferred":[
        "Komadine"
    ],
    "name:fas_x_preferred":[
        "\u06af\u0648\u0645\u0627\u062f\u06cc\u0646\u0647"
    ],
    "name:fra_x_preferred":[
        "Komadine"
    ],
    "name:msa_x_preferred":[
        "Komadine"
    ],
    "name:por_x_preferred":[
        "Komadine"
    ],
    "name:slv_x_preferred":[
        "Komadine"
    ],
    "name:srp_x_preferred":[
        "Komadine"
    ],
    "name:srp_x_variant":[
        "\u041a\u043e\u043c\u0430\u0434\u0438\u043d\u0435"
    ],
    "wof:name":"Komadine",
    "wof:placetype":"locality"
},
  "geometry": {"coordinates":[20.25721,43.50155],"type":"Point"}
}