{
  "type": "Feature",
  "properties": {
    "gn:admin1_code":"SE",
    "gn:admin2_code":"17",
    "gn:asciiname":"Koprivnica",
    "gn:country_code":"RS",
    "gn:dem":896,
    "gn:feature_class":"P",
    "gn:feature_code":"PPL",
    "gn:name":"Koprivnica",
    "gn:population":0,
    "gn:timezone":"Europe/Belgrade",
    "iso:country":"RS",
    "name:srp_x_preferred":[
        "Koprivnica"
    ],
    "wof:name":"Koprivnica",
    "wof:placetype":"locality"
},
  "geometry": {"coordinates":[20.11752000000001,43.51559],"type":"Point"}
}