{
  "type": "Feature",
  "properties": {
    "gn:admin1_code":"SE",
    "gn:admin2_code":"23",
    "gn:asciiname":"Velika Grabovnica",
    "gn:country_code":"RS",
    "gn:dem":258,
    "gn:feature_class":"P",
    "gn:feature_code":"PPL",
    "gn:name":"Velika Grabovnica",
    "gn:population":0,
    "gn:timezone":"Europe/Belgrade",
    "iso:country":"RS",
    "name:ceb_x_preferred":[
        "Velika Grabovnica"
    ],
    "name:fas_x_preferred":[
        "\u0648\u0644\u06cc\u06a9\u0627 \u06af\u0631\u0628\u0648\u0646\u06cc\u06a9\u0627"
    ],
    "name:fra_x_preferred":[
        "Velika Grabovnica"
    ],
    "name:msa_x_preferred":[
        "Velika Grabovnica"
    ],
    "name:por_x_preferred":[
        "Velika Grabovnica"
    ],
    "name:slv_x_preferred":[
        "Velika Grabovnica"
    ],
    "name:srp_x_preferred":[
        "Velika Grabovnica"
    ],
    "name:srp_x_variant":[
        "\u0412\u0435\u043b\u0438\u043a\u0430 \u0413\u0440\u0430\u0431\u043e\u0432\u043d\u0438\u0446\u0430"
    ],
    "name:und_x_variant":[
        "Velika Grabnica"
    ],
    "wof:name":"Velika Grabovnica",
    "wof:placetype":"locality"
},
  "geometry": {"coordinates":[22.01135,42.92463],"type":"Point"}
}