{
  "type": "Feature",
  "properties": {
    "gn:admin1_code":"SE",
    "gn:admin2_code":"19",
    "gn:asciiname":"Gajici",
    "gn:country_code":"RS",
    "gn:dem":783,
    "gn:feature_class":"P",
    "gn:feature_code":"PPL",
    "gn:name":"Gaji\u0107i",
    "gn:population":0,
    "gn:timezone":"Europe/Belgrade",
    "iso:country":"RS",
    "name:srp_x_preferred":[
        "Gaji\u0107i"
    ],
    "wof:name":"Gajici",
    "wof:placetype":"locality"
},
  "geometry": {"coordinates":[20.95167,43.24417],"type":"Point"}
}