{
  "type": "Feature",
  "properties": {
    "gn:admin1_code":"SE",
    "gn:admin2_code":"17",
    "gn:asciiname":"Rascici",
    "gn:country_code":"RS",
    "gn:dem":578,
    "gn:feature_class":"P",
    "gn:feature_code":"PPLL",
    "gn:name":"Ra\u0161\u010di\u0107i",
    "gn:population":0,
    "gn:timezone":"Europe/Belgrade",
    "iso:country":"RS",
    "name:srp_x_preferred":[
        "Ra\u0161\u010di\u0107i"
    ],
    "wof:name":"Rascici",
    "wof:placetype":"locality"
},
  "geometry": {"coordinates":[20.23857000000001,43.62206],"type":"Point"}
}