{
  "type": "Feature",
  "properties": {
    "gn:admin1_code":"SE",
    "gn:admin2_code":"20",
    "gn:asciiname":"Ostrovica",
    "gn:country_code":"RS",
    "gn:dem":343,
    "gn:feature_class":"P",
    "gn:feature_code":"PPL",
    "gn:name":"Ostrovica",
    "gn:population":0,
    "gn:timezone":"Europe/Belgrade",
    "iso:country":"RS",
    "name:bos_x_preferred":[
        "Ostrovica"
    ],
    "name:bul_x_preferred":[
        "\u041e\u0441\u0442\u0440\u043e\u0432\u0438\u0446\u0430"
    ],
    "name:ceb_x_preferred":[
        "Ostrovica"
    ],
    "name:deu_x_preferred":[
        "Ostrovica"
    ],
    "name:fra_x_preferred":[
        "Ostrovica"
    ],
    "name:hrv_x_preferred":[
        "Ostrovica"
    ],
    "name:nld_x_preferred":[
        "Ostrovica"
    ],
    "name:slv_x_preferred":[
        "Ostrovica"
    ],
    "name:srp_x_preferred":[
        "Ostrovica"
    ],
    "name:srp_x_variant":[
        "\u041e\u0441\u0442\u0440\u043e\u0432\u0438\u0446\u0430"
    ],
    "name:swe_x_preferred":[
        "Ostrovica"
    ],
    "wof:name":"Ostrovica",
    "wof:placetype":"locality"
},
  "geometry": {"coordinates":[22.12446,43.31485],"type":"Point"}
}