{
  "type": "Feature",
  "properties": {
    "gn:admin1_code":"SE",
    "gn:admin2_code":"20",
    "gn:asciiname":"Ostrovica",
    "gn:country_code":"RS",
    "gn:dem":343,
    "gn:feature_class":"P",
    "gn:feature_code":"PPL",
    "gn:name":"Ostrovica",
    "gn:population":0,
    "gn:timezone":"Europe/Belgrade",
    "iso:country":"RS",
    "name:srp_x_preferred":[
        "Ostrovica"
    ],
    "wof:name":"Ostrovica",
    "wof:placetype":"locality"
},
  "geometry": {"coordinates":[22.12446,43.31485],"type":"Point"}
}