{
  "type": "Feature",
  "properties": {
    "iso:country":"RS",
    "name:eng_x_preferred":[
        "Ostruznica"
    ],
    "name:srp_cyr_x_preferred":[
        "\u041e\u0441\u0442\u0440\u0443\u0436\u043d\u0438\u0446\u0430"
    ],
    "name:srp_lat_x_preferred":[
        "Ostru\u017enica"
    ],
    "name:srp_x_preferred":[
        "\u041e\u0441\u0442\u0440\u0443\u0436\u043d\u0438\u0446\u0430"
    ],
    "wof:name":"Ostruznica",
    "wof:placetype":"neighbourhood"
},
  "geometry": {"coordinates":[20.31963249838797,44.72826997170105],"type":"Point"}
}