{
  "type": "Feature",
  "properties": {
    "gn:admin1_code":"SE",
    "gn:admin2_code":"8",
    "gn:asciiname":"Krnic",
    "gn:country_code":"RS",
    "gn:dem":180,
    "gn:feature_class":"P",
    "gn:feature_code":"PPL",
    "gn:name":"Krni\u0107",
    "gn:population":0,
    "gn:timezone":"Europe/Belgrade",
    "iso:country":"RS",
    "name:srp_x_preferred":[
        "Krni\u0107"
    ],
    "wof:name":"Krnic",
    "wof:placetype":"locality"
},
  "geometry": {"coordinates":[19.86231,44.58944],"type":"Point"}
}