{
  "type": "Feature",
  "properties": {
    "gn:admin1_code":"SE",
    "gn:admin2_code":"20",
    "gn:asciiname":"Donja Pescanica",
    "gn:country_code":"RS",
    "gn:dem":199,
    "gn:feature_class":"P",
    "gn:feature_code":"PPL",
    "gn:name":"Donja Pe\u0161\u010danica",
    "gn:population":0,
    "gn:timezone":"Europe/Belgrade",
    "iso:country":"RS",
    "name:srp_x_preferred":[
        "Donja Pe\u0161\u010danica"
    ],
    "wof:name":"Donja Pescanica",
    "wof:placetype":"locality"
},
  "geometry": {"coordinates":[21.60395,43.53713],"type":"Point"}
}