{
  "type": "Feature",
  "properties": {
    "gn:admin1_code":"SE",
    "gn:admin2_code":"20",
    "gn:asciiname":"Donja Pescanica",
    "gn:country_code":"RS",
    "gn:dem":199,
    "gn:feature_class":"P",
    "gn:feature_code":"PPL",
    "gn:name":"Donja Pe\u0161\u010danica",
    "gn:population":0,
    "gn:timezone":"Europe/Belgrade",
    "iso:country":"RS",
    "name:ceb_x_preferred":[
        "Donja Pe\u0161\u010danica"
    ],
    "name:fra_x_preferred":[
        "Donja Pe\u0161\u010danica"
    ],
    "name:msa_x_preferred":[
        "Donja Pe\u0161\u010danica"
    ],
    "name:por_x_preferred":[
        "Donja Pe\u0161\u010danica"
    ],
    "name:slv_x_preferred":[
        "Donja Pe\u0161\u010danica"
    ],
    "name:srp_x_preferred":[
        "Donja Pe\u0161\u010danica"
    ],
    "name:srp_x_variant":[
        "\u0414\u043e\u045a\u0430 \u041f\u0435\u0448\u0447\u0430\u043d\u0438\u0446\u0430"
    ],
    "wof:name":"Donja Pescanica",
    "wof:placetype":"locality"
},
  "geometry": {"coordinates":[21.60395,43.53713],"type":"Point"}
}