{
  "type": "Feature",
  "properties": {
    "gn:admin1_code":"SE",
    "gn:admin2_code":"17",
    "gn:asciiname":"Krivaca",
    "gn:country_code":"RS",
    "gn:dem":460,
    "gn:feature_class":"P",
    "gn:feature_code":"PPLL",
    "gn:name":"Kriva\u010da",
    "gn:population":0,
    "gn:timezone":"Europe/Belgrade",
    "iso:country":"RS",
    "name:srp_x_preferred":[
        "Kriva\u010da"
    ],
    "wof:name":"Krivaca",
    "wof:placetype":"locality"
},
  "geometry": {"coordinates":[20.27193,43.73967],"type":"Point"}
}