{
  "type": "Feature",
  "properties": {
    "gn:admin1_code":"SE",
    "gn:admin2_code":"18",
    "gn:asciiname":"Grabovik",
    "gn:country_code":"RS",
    "gn:dem":906,
    "gn:feature_class":"P",
    "gn:feature_code":"PPL",
    "gn:name":"Grabovik",
    "gn:population":0,
    "gn:timezone":"Europe/Belgrade",
    "iso:country":"RS",
    "name:srp_x_preferred":[
        "Grabovik"
    ],
    "name:und_x_variant":[
        "Grabovnik"
    ],
    "wof:name":"Grabovik",
    "wof:placetype":"locality"
},
  "geometry": {"coordinates":[20.50889,43.37528],"type":"Point"}
}