{
  "type": "Feature",
  "properties": {
    "gn:admin1_code":"00",
    "gn:asciiname":"Velika Reka",
    "gn:country_code":"RS",
    "gn:dem":167,
    "gn:feature_class":"P",
    "gn:feature_code":"PPL",
    "gn:name":"Velika Reka",
    "gn:population":0,
    "gn:timezone":"Europe/Belgrade",
    "iso:country":"RS",
    "name:srp_x_preferred":[
        "Velika Reka"
    ],
    "name:und_x_variant":[
        "Ivanovi\u0107i"
    ],
    "wof:name":"Velika Reka",
    "wof:placetype":"locality"
},
  "geometry": {"coordinates":[19.22813,44.27001],"type":"Point"}
}