{
  "type": "Feature",
  "properties": {
    "gn:admin1_code":"00",
    "gn:asciiname":"Velika Reka",
    "gn:country_code":"RS",
    "gn:dem":167,
    "gn:feature_class":"P",
    "gn:feature_code":"PPL",
    "gn:name":"Velika Reka",
    "gn:population":0,
    "gn:timezone":"Europe/Belgrade",
    "iso:country":"RS",
    "name:ceb_x_preferred":[
        "Velika Reka"
    ],
    "name:fas_x_preferred":[
        "\u0648\u0644\u06cc\u06a9\u0627 \u0631\u06a9\u0627"
    ],
    "name:fra_x_preferred":[
        "Velika Reka"
    ],
    "name:msa_x_preferred":[
        "Velika Reka"
    ],
    "name:nld_x_preferred":[
        "Velika Reka"
    ],
    "name:por_x_preferred":[
        "Velika Reka"
    ],
    "name:slv_x_preferred":[
        "Velika Reka"
    ],
    "name:srp_x_preferred":[
        "Velika Reka"
    ],
    "name:srp_x_variant":[
        "\u0412\u0435\u043b\u0438\u043a\u0430 \u0420\u0435\u043a\u0430"
    ],
    "name:und_x_variant":[
        "Ivanovi\u0107i"
    ],
    "wof:name":"Velika Reka",
    "wof:placetype":"locality"
},
  "geometry": {"coordinates":[19.22813,44.27001],"type":"Point"}
}