{
  "type": "Feature",
  "properties": {
    "iso:country":"RS",
    "name:eng_x_preferred":[
        "London"
    ],
    "name:srp_cyr_x_preferred":[
        "\u041b\u043e\u043d\u0434\u043e\u043d)"
    ],
    "name:srp_x_preferred":[
        "\u041b\u043e\u043d\u0434\u043e\u043d)"
    ],
    "wof:name":"London",
    "wof:placetype":"neighbourhood"
},
  "geometry": {"coordinates":[20.46337737889858,44.80805628167479],"type":"Point"}
}