{
  "type": "Feature",
  "properties": {
    "iso:country":"RS",
    "name:ben_x_preferred":[
        "\u09b2\u09a8\u09cd\u09a1\u09a8"
    ],
    "name:ell_x_preferred":[
        "\u039b\u03cc\u03bd\u03c4\u03bf\u03bd"
    ],
    "name:eng_x_preferred":[
        "London"
    ],
    "name:heb_x_preferred":[
        "\u05dc\u05d5\u05e0\u05d3\u05d5\u05df"
    ],
    "name:hin_x_preferred":[
        "\u0932\u0902\u0926\u0928"
    ],
    "name:ind_x_preferred":[
        "London"
    ],
    "name:kor_x_preferred":[
        "\ub7f0\ub358"
    ],
    "name:srp_cyr_x_preferred":[
        "\u041b\u043e\u043d\u0434\u043e\u043d)"
    ],
    "name:srp_x_preferred":[
        "\u041b\u043e\u043d\u0434\u043e\u043d)"
    ],
    "name:vie_x_preferred":[
        "London"
    ],
    "wof:name":"London",
    "wof:placetype":"neighbourhood"
},
  "geometry": {"coordinates":[20.463377,44.808056],"type":"Point"}
}