{
  "type": "Feature",
  "properties": {
    "gn:admin1_code":"SE",
    "gn:admin2_code":"18",
    "gn:asciiname":"Zamcanja",
    "gn:country_code":"RS",
    "gn:dem":268,
    "gn:feature_class":"P",
    "gn:feature_code":"PPL",
    "gn:name":"Zam\u010danja",
    "gn:population":0,
    "gn:timezone":"Europe/Belgrade",
    "iso:country":"RS",
    "wof:name":"Zamcanja",
    "wof:placetype":"locality"
},
  "geometry": {"coordinates":[20.58,43.66028],"type":"Point"}
}