{
  "type": "Feature",
  "properties": {
    "gn:admin1_code":"SE",
    "gn:admin2_code":"16",
    "gn:asciiname":"Vucicevici",
    "gn:country_code":"RS",
    "gn:dem":637,
    "gn:feature_class":"P",
    "gn:feature_code":"PPL",
    "gn:name":"Vu\u010di\u010devi\u0107i",
    "gn:population":0,
    "gn:timezone":"Europe/Belgrade",
    "iso:country":"RS",
    "name:srp_x_preferred":[
        "Vu\u010di\u010devi\u0107i"
    ],
    "wof:name":"Vucicevici",
    "wof:placetype":"locality"
},
  "geometry": {"coordinates":[19.8975,43.96722000000001],"type":"Point"}
}