{
  "type": "Feature",
  "properties": {
    "gn:admin1_code":"SE",
    "gn:admin2_code":"13",
    "gn:asciiname":"Glozane",
    "gn:country_code":"RS",
    "gn:dem":130,
    "gn:feature_class":"P",
    "gn:feature_code":"PPL",
    "gn:name":"Glo\u017eane",
    "gn:population":0,
    "gn:timezone":"Europe/Belgrade",
    "iso:country":"RS",
    "name:srp_x_preferred":[
        "Glo\u017eane"
    ],
    "wof:name":"Glozane",
    "wof:placetype":"locality"
},
  "geometry": {"coordinates":[21.18456,44.1686],"type":"Point"}
}