{
  "type": "Feature",
  "properties": {
    "gn:admin1_code":"SE",
    "gn:admin2_code":"17",
    "gn:asciiname":"Grab",
    "gn:country_code":"RS",
    "gn:dem":398,
    "gn:feature_class":"P",
    "gn:feature_code":"PPL",
    "gn:name":"Grab",
    "gn:population":0,
    "gn:timezone":"Europe/Belgrade",
    "iso:country":"RS",
    "name:srp_x_preferred":[
        "Grab"
    ],
    "wof:name":"Grab",
    "wof:placetype":"locality"
},
  "geometry": {"coordinates":[20.25402,43.80917],"type":"Point"}
}