{
  "type": "Feature",
  "properties": {
    "gn:admin1_code":"SE",
    "gn:admin2_code":"0",
    "gn:asciiname":"Todorovica Kraj",
    "gn:country_code":"RS",
    "gn:dem":108,
    "gn:feature_class":"P",
    "gn:feature_code":"PPL",
    "gn:name":"Todorovi\u0107a Kraj",
    "gn:population":0,
    "gn:timezone":"Europe/Belgrade",
    "iso:country":"RS",
    "wof:name":"Todorovica Kraj",
    "wof:placetype":"locality"
},
  "geometry": {"coordinates":[20.11139,44.59444000000001],"type":"Point"}
}