{
  "type": "Feature",
  "properties": {
    "gn:admin1_code":"SE",
    "gn:admin2_code":"24",
    "gn:asciiname":"Dumbija",
    "gn:country_code":"RS",
    "gn:dem":968,
    "gn:feature_class":"P",
    "gn:feature_code":"PPLL",
    "gn:name":"Dumbija",
    "gn:population":0,
    "gn:timezone":"Europe/Belgrade",
    "iso:country":"RS",
    "wof:name":"Dumbija",
    "wof:placetype":"locality"
},
  "geometry": {"coordinates":[22.0247,42.35667],"type":"Point"}
}