{
  "type": "Feature",
  "properties": {
    "gn:admin1_code":"SE",
    "gn:admin2_code":"16",
    "gn:asciiname":"Rudine",
    "gn:country_code":"RS",
    "gn:dem":973,
    "gn:feature_class":"P",
    "gn:feature_code":"PPL",
    "gn:name":"Rudine",
    "gn:population":0,
    "gn:timezone":"Europe/Belgrade",
    "iso:country":"RS",
    "name:bos_x_preferred":[
        "Rudine"
    ],
    "name:ceb_x_preferred":[
        "\u0420\u0443\u0434\u0438\u043d\u0435"
    ],
    "name:fra_x_preferred":[
        "Rudine"
    ],
    "name:hrv_x_preferred":[
        "Rudine"
    ],
    "name:hun_x_preferred":[
        "Rudine"
    ],
    "name:slv_x_preferred":[
        "Rudine"
    ],
    "name:srp_x_preferred":[
        "\u0420\u0443\u0434\u0438\u043d\u0435"
    ],
    "wof:name":"Rudine",
    "wof:placetype":"locality"
},
  "geometry": {"coordinates":[19.68528,43.29167],"type":"Point"}
}