{
  "type": "Feature",
  "properties": {
    "gn:admin1_code":"SE",
    "gn:admin2_code":"8",
    "gn:asciiname":"Burmazi",
    "gn:country_code":"RS",
    "gn:dem":408,
    "gn:feature_class":"P",
    "gn:feature_code":"PPL",
    "gn:name":"Burmazi",
    "gn:population":0,
    "gn:timezone":"Europe/Belgrade",
    "iso:country":"RS",
    "name:srp_x_preferred":[
        "Burmazi"
    ],
    "wof:name":"Burmazi",
    "wof:placetype":"locality"
},
  "geometry": {"coordinates":[19.40682,44.44806],"type":"Point"}
}