{
  "type": "Feature",
  "properties": {
    "gn:admin1_code":"SE",
    "gn:admin2_code":"23",
    "gn:asciiname":"Kukulovce",
    "gn:country_code":"RS",
    "gn:dem":258,
    "gn:feature_class":"P",
    "gn:feature_code":"PPL",
    "gn:name":"Kukulovce",
    "gn:population":0,
    "gn:timezone":"Europe/Belgrade",
    "iso:country":"RS",
    "name:ceb_x_preferred":[
        "Kukulovce"
    ],
    "name:fra_x_preferred":[
        "Kukulovce"
    ],
    "name:msa_x_preferred":[
        "Kukulovce"
    ],
    "name:por_x_preferred":[
        "Kukulovce"
    ],
    "name:slv_x_preferred":[
        "Kukulovce"
    ],
    "name:srp_x_preferred":[
        "Kukulovce"
    ],
    "name:srp_x_variant":[
        "\u041a\u0443\u043a\u0443\u043b\u043e\u0432\u0446\u0435"
    ],
    "name:und_x_variant":[
        "Kukolovce"
    ],
    "wof:name":"Kukulovce",
    "wof:placetype":"locality"
},
  "geometry": {"coordinates":[21.90001,42.93913],"type":"Point"}
}