{
  "type": "Feature",
  "properties": {
    "gn:admin1_code":"SE",
    "gn:admin2_code":"15",
    "gn:asciiname":"Gornja Mala",
    "gn:country_code":"RS",
    "gn:dem":554,
    "gn:feature_class":"P",
    "gn:feature_code":"PPL",
    "gn:name":"Gornja Mala",
    "gn:population":0,
    "gn:timezone":"Europe/Belgrade",
    "iso:country":"RS",
    "name:fra_x_preferred":[
        "Kni\u0107"
    ],
    "name:ita_x_preferred":[
        "Kni\u0107"
    ],
    "name:nld_x_preferred":[
        "Kni\u0107"
    ],
    "name:srp_x_preferred":[
        "Gornja Mala"
    ],
    "name:srp_x_variant":[
        "\u041a\u043d\u0438\u045b"
    ],
    "wof:name":"Gornja Mala",
    "wof:placetype":"locality"
},
  "geometry": {"coordinates":[21.82694,43.71583],"type":"Point"}
}