{
  "type": "Feature",
  "properties": {
    "gn:admin1_code":"SE",
    "gn:admin2_code":"20",
    "gn:asciiname":"Sabazovica",
    "gn:country_code":"RS",
    "gn:dem":271,
    "gn:feature_class":"P",
    "gn:feature_code":"PPL",
    "gn:name":"Sabazovica",
    "gn:population":0,
    "gn:timezone":"Europe/Belgrade",
    "iso:country":"RS",
    "wof:name":"Sabazovica",
    "wof:placetype":"locality"
},
  "geometry": {"coordinates":[21.55611,43.665],"type":"Point"}
}