{
  "type": "Feature",
  "properties": {
    "gn:admin1_code":"SE",
    "gn:admin2_code":"8",
    "gn:asciiname":"Vasici",
    "gn:country_code":"RS",
    "gn:dem":501,
    "gn:feature_class":"P",
    "gn:feature_code":"PPL",
    "gn:name":"Vasi\u0107i",
    "gn:population":0,
    "gn:timezone":"Europe/Belgrade",
    "iso:country":"RS",
    "name:srp_x_preferred":[
        "Vasi\u0107i"
    ],
    "wof:name":"Vasici",
    "wof:placetype":"locality"
},
  "geometry": {"coordinates":[19.34227000000001,44.42661],"type":"Point"}
}