{
  "type": "Feature",
  "properties": {
    "gn:admin1_code":"SE",
    "gn:admin2_code":"17",
    "gn:asciiname":"Rokci",
    "gn:country_code":"RS",
    "gn:dem":727,
    "gn:feature_class":"P",
    "gn:feature_code":"PPLL",
    "gn:name":"Rokci",
    "gn:population":0,
    "gn:timezone":"Europe/Belgrade",
    "iso:country":"RS",
    "name:srp_x_preferred":[
        "Rokci"
    ],
    "wof:name":"Rokci",
    "wof:placetype":"locality"
},
  "geometry": {"coordinates":[20.20697,43.53307],"type":"Point"}
}