{
  "type": "Feature",
  "properties": {
    "gn:admin1_code":"SE",
    "gn:admin2_code":"8",
    "gn:asciiname":"Gornja Vranjaca",
    "gn:country_code":"RS",
    "gn:dem":479,
    "gn:feature_class":"P",
    "gn:feature_code":"PPL",
    "gn:name":"Gornja Vranja\u010da",
    "gn:population":0,
    "gn:timezone":"Europe/Belgrade",
    "iso:country":"RS",
    "name:srp_x_preferred":[
        "Gornja Vranja\u010da"
    ],
    "wof:name":"Gornja Vranjaca",
    "wof:placetype":"locality"
},
  "geometry": {"coordinates":[19.2625,44.28917],"type":"Point"}
}