{
  "type": "Feature",
  "properties": {
    "gn:admin1_code":"VO",
    "gn:admin2_code":"6",
    "gn:asciiname":"Bogani",
    "gn:country_code":"RS",
    "gn:dem":83,
    "gn:feature_class":"P",
    "gn:feature_code":"PPL",
    "gn:name":"Bo\u0111ani",
    "gn:population":0,
    "gn:timezone":"Europe/Belgrade",
    "iso:country":"RS",
    "name:ceb_x_preferred":[
        "Bo\u0111ani"
    ],
    "name:epo_x_preferred":[
        "Bodjani"
    ],
    "name:fra_x_preferred":[
        "Bo\u0111ani"
    ],
    "name:hrv_x_preferred":[
        "Bo\u0111ani"
    ],
    "name:hun_x_preferred":[
        "Bogy\u00e1n"
    ],
    "name:ita_x_preferred":[
        "Bo\u0111ani"
    ],
    "name:msa_x_preferred":[
        "Bo\u0111ani"
    ],
    "name:rus_x_preferred":[
        "\u0411\u043e\u0434\u0436\u044f\u043d\u0438"
    ],
    "name:slv_x_preferred":[
        "Bo\u0111ani"
    ],
    "name:srp_x_preferred":[
        "Bo\u0111ani"
    ],
    "name:srp_x_variant":[
        "\u0411\u043e\u0452\u0430\u043d\u0438"
    ],
    "name:swe_x_preferred":[
        "Bo\u0111ani"
    ],
    "name:ukr_x_preferred":[
        "\u0411\u043e\u0436\u044f\u043d\u0438"
    ],
    "name:und_x_variant":[
        "Batschka Bodjani",
        "Bodgy\u00e1n"
    ],
    "wof:name":"Bogani",
    "wof:placetype":"locality"
},
  "geometry": {"coordinates":[19.10665,45.38958],"type":"Point"}
}