{
  "type": "Feature",
  "properties": {
    "gn:admin1_code":"SE",
    "gn:admin2_code":"20",
    "gn:asciiname":"Sicevo",
    "gn:country_code":"RS",
    "gn:dem":366,
    "gn:feature_class":"P",
    "gn:feature_code":"PPL",
    "gn:name":"Si\u0107evo",
    "gn:population":0,
    "gn:timezone":"Europe/Belgrade",
    "iso:country":"RS",
    "name:srp_x_preferred":[
        "Si\u0107evo"
    ],
    "wof:name":"Sicevo",
    "wof:placetype":"locality"
},
  "geometry": {"coordinates":[22.08411,43.34093],"type":"Point"}
}