{
  "type": "Feature",
  "properties": {
    "iso:country":"RS",
    "name:eng_x_preferred":[
        "Kumodraz"
    ],
    "name:srp_cyr_x_preferred":[
        "\u041a\u0443\u043c\u043e\u0434\u0440\u0430\u0436"
    ],
    "name:srp_lat_x_preferred":[
        "Kumodra\u017e"
    ],
    "wof:name":"Kumodraz",
    "wof:placetype":"neighbourhood"
},
  "geometry": {"coordinates":[20.50816268071839,44.74156390257392],"type":"Point"}
}