{
  "type": "Feature",
  "properties": {
    "gn:admin1_code":"SE",
    "gn:admin2_code":"17",
    "gn:asciiname":"Boljkovci",
    "gn:country_code":"RS",
    "gn:dem":278,
    "gn:feature_class":"P",
    "gn:feature_code":"PPL",
    "gn:name":"Boljkovci",
    "gn:population":0,
    "gn:timezone":"Europe/Belgrade",
    "iso:country":"RS",
    "name:ceb_x_preferred":[
        "Boljkovci"
    ],
    "name:fas_x_preferred":[
        "\u0628\u0648\u0644\u06cc\u06a9\u0648\u0648\u0686\u06cc"
    ],
    "name:fra_x_preferred":[
        "Boljkovci"
    ],
    "name:msa_x_preferred":[
        "Boljkovci"
    ],
    "name:por_x_preferred":[
        "Boljkovci"
    ],
    "name:slv_x_preferred":[
        "Boljkovci"
    ],
    "name:srp_x_preferred":[
        "Boljkovci"
    ],
    "name:srp_x_variant":[
        "\u0411\u043e\u0459\u043a\u043e\u0432\u0446\u0438"
    ],
    "wof:name":"Boljkovci",
    "wof:placetype":"locality"
},
  "geometry": {"coordinates":[20.34556,44.14355],"type":"Point"}
}