{
  "type": "Feature",
  "properties": {
    "gn:admin1_code":"SE",
    "gn:admin2_code":"24",
    "gn:asciiname":"Donji Ramni Del",
    "gn:country_code":"RS",
    "gn:dem":1072,
    "gn:feature_class":"P",
    "gn:feature_code":"PPL",
    "gn:name":"Donji Ramni Del",
    "gn:population":0,
    "gn:timezone":"Europe/Belgrade",
    "iso:country":"RS",
    "wof:name":"Donji Ramni Del",
    "wof:placetype":"locality"
},
  "geometry": {"coordinates":[22.16771,42.48815],"type":"Point"}
}