{
  "type": "Feature",
  "properties": {
    "gn:admin1_code":"SE",
    "gn:admin2_code":"16",
    "gn:asciiname":"Palez",
    "gn:country_code":"RS",
    "gn:dem":1120,
    "gn:feature_class":"P",
    "gn:feature_code":"PPL",
    "gn:name":"Pale\u017e",
    "gn:population":0,
    "gn:timezone":"Europe/Belgrade",
    "iso:country":"RS",
    "name:srp_x_preferred":[
        "Pale\u017e"
    ],
    "wof:name":"Palez",
    "wof:placetype":"locality"
},
  "geometry": {"coordinates":[19.97866,43.47723],"type":"Point"}
}