{
  "type": "Feature",
  "properties": {
    "gn:admin1_code":"SE",
    "gn:admin2_code":"19",
    "gn:asciiname":"Pajsak",
    "gn:country_code":"RS",
    "gn:dem":300,
    "gn:feature_class":"P",
    "gn:feature_code":"PPL",
    "gn:name":"Pajsak",
    "gn:population":0,
    "gn:timezone":"Europe/Belgrade",
    "iso:country":"RS",
    "name:fra_x_preferred":[
        "Pajsak"
    ],
    "name:hye_x_preferred":[
        "\u054a\u0561\u0575\u057d\u0561\u056f"
    ],
    "name:msa_x_preferred":[
        "Pajsak"
    ],
    "name:por_x_preferred":[
        "Pajsak"
    ],
    "name:slv_x_preferred":[
        "Pajsak"
    ],
    "name:srp_x_preferred":[
        "\u041f\u0430\u0458\u0441\u0430\u043a"
    ],
    "wof:name":"Pajsak",
    "wof:placetype":"locality"
},
  "geometry": {"coordinates":[21.09396,43.53155],"type":"Point"}
}