{
  "type": "Feature",
  "properties": {
    "iso:country":"RS",
    "name:eng_x_preferred":[
        "Kosancicev Venac"
    ],
    "name:srp_cyr_x_preferred":[
        "\u041a\u043e\u0441\u0430\u043d\u0447\u0438\u045b\u0435\u0432 \u0412\u0435\u043d\u0430\u0446"
    ],
    "name:srp_lat_x_preferred":[
        "Kosan\u010di\u0107ev Venac"
    ],
    "name:srp_x_preferred":[
        "\u041a\u043e\u0441\u0430\u043d\u0447\u0438\u045b\u0435\u0432 \u0412\u0435\u043d\u0430\u0446"
    ],
    "wof:name":"Kosancicev Venac",
    "wof:placetype":"neighbourhood"
},
  "geometry": {"coordinates":[20.45256679388681,44.81728395553375],"type":"Point"}
}