{
  "type": "Feature",
  "properties": {
    "gn:admin1_code":"SE",
    "gn:admin2_code":"19",
    "gn:asciiname":"Trubarevo",
    "gn:country_code":"RS",
    "gn:dem":151,
    "gn:feature_class":"P",
    "gn:feature_code":"PPL",
    "gn:name":"Trubarevo",
    "gn:population":0,
    "gn:timezone":"Europe/Belgrade",
    "iso:country":"RS",
    "name:ceb_x_preferred":[
        "Trubarevo"
    ],
    "name:ell_x_preferred":[
        "\u03a4\u03c1\u03bf\u03c5\u03bc\u03c0\u03ac\u03c1\u03b5\u03b2\u03bf"
    ],
    "name:fas_x_preferred":[
        "\u062a\u0631\u0648\u0628\u0627\u0631\u0648\u0648"
    ],
    "name:fra_x_preferred":[
        "Trubarevo"
    ],
    "name:msa_x_preferred":[
        "Trubarevo"
    ],
    "name:por_x_preferred":[
        "Trubarevo"
    ],
    "name:slv_x_preferred":[
        "Trubarevo"
    ],
    "name:srp_x_preferred":[
        "Trubarevo"
    ],
    "name:srp_x_variant":[
        "\u0422\u0440\u0443\u0431\u0430\u0440\u0435\u0432\u043e"
    ],
    "wof:name":"Trubarevo",
    "wof:placetype":"locality"
},
  "geometry": {"coordinates":[21.4846,43.60946],"type":"Point"}
}