{
  "type": "Feature",
  "properties": {
    "gn:admin1_code":"SE",
    "gn:admin2_code":"10",
    "gn:asciiname":"Visevac",
    "gn:country_code":"RS",
    "gn:dem":223,
    "gn:feature_class":"P",
    "gn:feature_code":"PPLL",
    "gn:name":"Vi\u0161evac",
    "gn:population":0,
    "gn:timezone":"Europe/Belgrade",
    "iso:country":"RS",
    "name:ceb_x_preferred":[
        "Vi\u0161evac"
    ],
    "name:ell_x_preferred":[
        "\u0392\u03af\u03c3\u03b5\u03b2\u03b1\u03c4\u03c2"
    ],
    "name:fra_x_preferred":[
        "Vi\u0161evac"
    ],
    "name:msa_x_preferred":[
        "Vi\u0161evac"
    ],
    "name:por_x_preferred":[
        "Vi\u0161evac"
    ],
    "name:slv_x_preferred":[
        "Vi\u0161evac"
    ],
    "name:srp_x_preferred":[
        "Vi\u0161evac"
    ],
    "name:srp_x_variant":[
        "\u0412\u0438\u0448\u0435\u0432\u0430\u0446"
    ],
    "wof:name":"Visevac",
    "wof:placetype":"locality"
},
  "geometry": {"coordinates":[20.92365,44.25513],"type":"Point"}
}