{
  "type": "Feature",
  "properties": {
    "gn:admin1_code":"SE",
    "gn:admin2_code":"24",
    "gn:asciiname":"Ornice",
    "gn:country_code":"RS",
    "gn:dem":1354,
    "gn:feature_class":"P",
    "gn:feature_code":"PPL",
    "gn:name":"Orni\u010de",
    "gn:population":0,
    "gn:timezone":"Europe/Belgrade",
    "iso:country":"RS",
    "name:bos_x_preferred":[
        "Ornice"
    ],
    "name:hrv_x_preferred":[
        "Ornice"
    ],
    "name:hun_x_preferred":[
        "Ornice"
    ],
    "name:nld_x_preferred":[
        "Ornice"
    ],
    "name:slv_x_preferred":[
        "Ornice"
    ],
    "name:spa_x_preferred":[
        "Ornice"
    ],
    "name:srp_x_preferred":[
        "\u041e\u0440\u043d\u0438\u0446\u0435"
    ],
    "name:ukr_x_preferred":[
        "\u041e\u0440\u043d\u0438\u0446\u0435"
    ],
    "wof:name":"Ornice",
    "wof:placetype":"locality"
},
  "geometry": {"coordinates":[22.26517,42.43746],"type":"Point"}
}