{
  "type": "Feature",
  "properties": {
    "gn:admin1_code":"SE",
    "gn:admin2_code":"16",
    "gn:asciiname":"Gornja Mahala",
    "gn:country_code":"RS",
    "gn:dem":1118,
    "gn:feature_class":"P",
    "gn:feature_code":"PPL",
    "gn:name":"Gornja Mahala",
    "gn:population":0,
    "gn:timezone":"Europe/Belgrade",
    "iso:country":"RS",
    "name:srp_x_preferred":[
        "Gornja Mahala"
    ],
    "wof:name":"Gornja Mahala",
    "wof:placetype":"locality"
},
  "geometry": {"coordinates":[20.20361,43.20389],"type":"Point"}
}