{
  "type": "Feature",
  "properties": {
    "gn:admin1_code":"SE",
    "gn:admin2_code":"16",
    "gn:asciiname":"Prlo",
    "gn:country_code":"RS",
    "gn:dem":434,
    "gn:feature_class":"P",
    "gn:feature_code":"PPL",
    "gn:name":"Prlo",
    "gn:population":0,
    "gn:timezone":"Europe/Belgrade",
    "iso:country":"RS",
    "name:srp_x_preferred":[
        "Prlo"
    ],
    "wof:name":"Prlo",
    "wof:placetype":"locality"
},
  "geometry": {"coordinates":[19.59654,43.94142],"type":"Point"}
}