{
  "type": "Feature",
  "properties": {
    "gn:admin1_code":"SE",
    "gn:admin2_code":"24",
    "gn:asciiname":"Dolinska Mahala",
    "gn:country_code":"RS",
    "gn:dem":1394,
    "gn:feature_class":"P",
    "gn:feature_code":"PPL",
    "gn:name":"Dolinska Mahala",
    "gn:population":0,
    "gn:timezone":"Europe/Belgrade",
    "iso:country":"RS",
    "name:und_x_variant":[
        "Dolinska Mala",
        "Dolinska Mahala"
    ],
    "wof:name":"Dolinska Mahala",
    "wof:placetype":"locality"
},
  "geometry": {"coordinates":[22.28221,42.59134],"type":"Point"}
}