{
  "type": "Feature",
  "properties": {
    "gn:admin1_code":"SE",
    "gn:admin2_code":"17",
    "gn:asciiname":"Mace",
    "gn:country_code":"RS",
    "gn:dem":932,
    "gn:feature_class":"P",
    "gn:feature_code":"PPLL",
    "gn:name":"Ma\u0107e",
    "gn:population":0,
    "gn:timezone":"Europe/Belgrade",
    "iso:country":"RS",
    "name:ceb_x_preferred":[
        "Mace"
    ],
    "name:deu_x_preferred":[
        "Mace"
    ],
    "name:ita_x_preferred":[
        "Mace"
    ],
    "name:jpn_x_preferred":[
        "\u30e1\u30fc\u30b9"
    ],
    "name:kor_x_preferred":[
        "\uba54\uc774\uc2a4"
    ],
    "name:nld_x_preferred":[
        "Mac\u00e9"
    ],
    "name:por_x_preferred":[
        "Mace"
    ],
    "name:srp_x_preferred":[
        "Ma\u0107e"
    ],
    "name:swe_x_preferred":[
        "Mace"
    ],
    "wof:name":"Mace",
    "wof:placetype":"locality"
},
  "geometry": {"coordinates":[20.0978,43.57588],"type":"Point"}
}