{
  "type": "Feature",
  "properties": {
    "gn:admin1_code":"SE",
    "gn:admin2_code":"17",
    "gn:asciiname":"Mace",
    "gn:country_code":"RS",
    "gn:dem":932,
    "gn:feature_class":"P",
    "gn:feature_code":"PPLL",
    "gn:name":"Ma\u0107e",
    "gn:population":0,
    "gn:timezone":"Europe/Belgrade",
    "iso:country":"RS",
    "name:srp_x_preferred":[
        "Ma\u0107e"
    ],
    "wof:name":"Mace",
    "wof:placetype":"locality"
},
  "geometry": {"coordinates":[20.0978,43.57588],"type":"Point"}
}