{
  "type": "Feature",
  "properties": {
    "gn:admin1_code":"SE",
    "gn:admin2_code":"23",
    "gn:asciiname":"Tupale",
    "gn:country_code":"RS",
    "gn:dem":640,
    "gn:feature_class":"P",
    "gn:feature_code":"PPLL",
    "gn:name":"Tupale",
    "gn:population":0,
    "gn:timezone":"Europe/Belgrade",
    "iso:country":"RS",
    "name:fra_x_preferred":[
        "Tupale"
    ],
    "name:msa_x_preferred":[
        "Tupale"
    ],
    "name:por_x_preferred":[
        "Tupale"
    ],
    "name:slv_x_preferred":[
        "Tupale"
    ],
    "name:sqi_x_preferred":[
        "Tupalla"
    ],
    "name:srp_x_preferred":[
        "Tupale"
    ],
    "name:srp_x_variant":[
        "\u0422\u0443\u043f\u0430\u043b\u0435"
    ],
    "wof:name":"Tupale",
    "wof:placetype":"locality"
},
  "geometry": {"coordinates":[21.60632,42.82233],"type":"Point"}
}