{
  "type": "Feature",
  "properties": {
    "gn:admin1_code":"SE",
    "gn:admin2_code":"11",
    "gn:asciiname":"Vukovic",
    "gn:country_code":"RS",
    "gn:dem":141,
    "gn:feature_class":"P",
    "gn:feature_code":"PPL",
    "gn:name":"Vukovi\u0107",
    "gn:population":0,
    "gn:timezone":"Europe/Belgrade",
    "iso:country":"RS",
    "name:srp_x_preferred":[
        "Vukovi\u0107"
    ],
    "wof:name":"Vukovic",
    "wof:placetype":"locality"
},
  "geometry": {"coordinates":[21.57816,44.5668],"type":"Point"}
}