{
  "type": "Feature",
  "properties": {
    "iso:country":"RS",
    "name:eng_x_preferred":[
        "Retenzija"
    ],
    "name:srp_cyr_x_preferred":[
        "\u0420\u0435\u0442\u0435\u043d\u0437\u0438\u0458\u0430"
    ],
    "name:srp_cyr_x_variant":[
        "\u0431\u043b\u043e\u043a 9\u0431"
    ],
    "name:srp_lat.b_x_preferred":[
        "Blok 9b"
    ],
    "name:srp_x_preferred":[
        "\u0420\u0435\u0442\u0435\u043d\u0437\u0438\u0458\u0430"
    ],
    "wof:name":"Retenzija",
    "wof:placetype":"neighbourhood"
},
  "geometry": {"coordinates":[20.4127741691582,44.83577323174229],"type":"Point"}
}