{
  "type": "Feature",
  "properties": {
    "gn:country":"RS",
    "gn:fcode":"PPL",
    "gn:pop":4,
    "iso:country":"RS",
    "name:cze_x_preferred":[
        "Karavukovo"
    ],
    "name:dut_x_preferred":[
        "Karavukovo"
    ],
    "name:eng_x_preferred":[
        "Karavukovo"
    ],
    "name:epo_x_preferred":[
        "Karavukovo"
    ],
    "name:fre_x_preferred":[
        "Karavukovo"
    ],
    "name:ger_x_preferred":[
        "Karavukovo"
    ],
    "name:hrv_x_preferred":[
        "Karavukovo"
    ],
    "name:hun_x_preferred":[
        "B\u00e1csordas"
    ],
    "name:may_x_preferred":[
        "Karavukovo"
    ],
    "name:rum_x_preferred":[
        "Karavukovo"
    ],
    "name:slv_x_preferred":[
        "Karavukovo"
    ],
    "name:srp_x_preferred":[
        "Karavukovo"
    ],
    "name:unk_x_variant":[
        "Wolfingen"
    ],
    "qs:name":"Karavukovo",
    "qs:photos_9r":0,
    "qs:photos_sr":0,
    "qs:pop_sr":"1",
    "wd:wordcount":124,
    "wof:name":"Karavukovo",
    "wof:placetype":"locality",
    "wof:population":4
},
  "geometry": {"coordinates":[19.19415,45.49829],"type":"Point"}
}