{
  "type": "Feature",
  "properties": {
    "gn:country":"RS",
    "gn:fcode":"PPL",
    "gn:population":4,
    "iso:country":"RS",
    "name:ceb_x_preferred":[
        "Karavukovo"
    ],
    "name:ces_x_preferred":[
        "Karavukovo"
    ],
    "name:deu_x_preferred":[
        "Karavukovo"
    ],
    "name:eng_x_preferred":[
        "Karavukovo"
    ],
    "name:epo_x_preferred":[
        "Karavukovo"
    ],
    "name:fas_x_preferred":[
        "\u06a9\u0627\u0631\u0627\u0648\u0648\u06a9\u0648\u0648\u0648"
    ],
    "name:fra_x_preferred":[
        "Karavukovo"
    ],
    "name:hrv_x_preferred":[
        "Karavukovo"
    ],
    "name:hun_x_preferred":[
        "B\u00e1csordas"
    ],
    "name:msa_x_preferred":[
        "Karavukovo"
    ],
    "name:nld_x_preferred":[
        "Karavukovo"
    ],
    "name:pol_x_preferred":[
        "Karavukovo"
    ],
    "name:ron_x_preferred":[
        "Karavukovo"
    ],
    "name:rus_x_preferred":[
        "\u041a\u0430\u0440\u0430\u0432\u0443\u043a\u043e\u0432\u043e"
    ],
    "name:slv_x_preferred":[
        "Karavukovo"
    ],
    "name:spa_x_preferred":[
        "Karavukovo"
    ],
    "name:srp_x_preferred":[
        "Karavukovo"
    ],
    "name:srp_x_variant":[
        "\u041a\u0430\u0440\u0430\u0432\u0443\u043a\u043e\u0432\u043e"
    ],
    "name:ukr_x_preferred":[
        "\u041a\u0430\u0440\u0430\u0432\u0443\u043a\u043e\u0432\u043e"
    ],
    "name:und_x_variant":[
        "Wolfingen"
    ],
    "qs:name":"Karavukovo",
    "qs:photos_9r":0,
    "qs:photos_sr":0,
    "qs:pop_sr":"1",
    "wd:wordcount":124,
    "wof:name":"Karavukovo",
    "wof:placetype":"locality",
    "wof:population":4
},
  "geometry": {"coordinates":[19.19415,45.49829],"type":"Point"}
}