{
  "type": "Feature",
  "properties": {
    "gn:admin1_code":"SE",
    "gn:admin2_code":"24",
    "gn:asciiname":"Jankova Mahala",
    "gn:country_code":"RS",
    "gn:dem":1203,
    "gn:feature_class":"P",
    "gn:feature_code":"PPL",
    "gn:name":"Jankova Mahala",
    "gn:population":0,
    "gn:timezone":"Europe/Belgrade",
    "iso:country":"RS",
    "wof:name":"Jankova Mahala",
    "wof:placetype":"locality"
},
  "geometry": {"coordinates":[22.31146,42.65816],"type":"Point"}
}