{
  "type": "Feature",
  "properties": {
    "gn:admin1_code":"SE",
    "gn:admin2_code":"24",
    "gn:asciiname":"Sobina",
    "gn:country_code":"RS",
    "gn:dem":592,
    "gn:feature_class":"P",
    "gn:feature_code":"PPL",
    "gn:name":"Sobina",
    "gn:population":0,
    "gn:timezone":"Europe/Belgrade",
    "iso:country":"RS",
    "name:srp_x_preferred":[
        "Sobina"
    ],
    "wof:name":"Sobina",
    "wof:placetype":"locality"
},
  "geometry": {"coordinates":[21.88083,42.55979],"type":"Point"}
}