{
  "type": "Feature",
  "properties": {
    "gn:admin1_code":"SE",
    "gn:admin2_code":"21",
    "gn:asciiname":"Vasiljevac",
    "gn:country_code":"RS",
    "gn:dem":719,
    "gn:feature_class":"P",
    "gn:feature_code":"PPLL",
    "gn:name":"Vasiljevac",
    "gn:population":0,
    "gn:timezone":"Europe/Belgrade",
    "iso:country":"RS",
    "name:bul_x_preferred":[
        "\u0412\u0430\u0441\u0438\u043b\u0435\u0432\u0430\u0446"
    ],
    "name:fas_x_preferred":[
        "\u0648\u0633\u06cc\u0644\u062c\u0648\u06a9"
    ],
    "name:fra_x_preferred":[
        "Vasiljevac"
    ],
    "name:msa_x_preferred":[
        "Vasiljevac"
    ],
    "name:por_x_preferred":[
        "Vasiljevac"
    ],
    "name:slv_x_preferred":[
        "Vasiljevac"
    ],
    "name:sqi_x_preferred":[
        "Vasileci"
    ],
    "name:srp_x_preferred":[
        "Vasiljevac"
    ],
    "name:srp_x_variant":[
        "\u0412\u0430\u0441\u0438\u0459\u0435\u0432\u0430\u0446"
    ],
    "wof:name":"Vasiljevac",
    "wof:placetype":"locality"
},
  "geometry": {"coordinates":[21.28308,42.91547],"type":"Point"}
}