{
  "type": "Feature",
  "properties": {
    "gn:admin1_code":"SE",
    "gn:admin2_code":"18",
    "gn:asciiname":"Oholje",
    "gn:country_code":"RS",
    "gn:dem":728,
    "gn:feature_class":"P",
    "gn:feature_code":"PPLL",
    "gn:name":"Oholje",
    "gn:population":0,
    "gn:timezone":"Europe/Belgrade",
    "iso:country":"RS",
    "name:ceb_x_preferred":[
        "Oholje"
    ],
    "name:fra_x_preferred":[
        "Oholje"
    ],
    "name:hun_x_preferred":[
        "Oholje"
    ],
    "name:msa_x_preferred":[
        "Oholje"
    ],
    "name:nld_x_preferred":[
        "Oholje"
    ],
    "name:por_x_preferred":[
        "Oholje"
    ],
    "name:slv_x_preferred":[
        "Oholje"
    ],
    "name:srp_x_preferred":[
        "Oholje"
    ],
    "name:srp_x_variant":[
        "\u041e\u0445\u043e\u0459\u0435"
    ],
    "name:und_x_variant":[
        "Ohoje"
    ],
    "wof:name":"Oholje",
    "wof:placetype":"locality"
},
  "geometry": {"coordinates":[20.49389,43.09587],"type":"Point"}
}