{
  "type": "Feature",
  "properties": {
    "gn:country":"RS",
    "gn:fcode":"PPL",
    "gn:pop":1509,
    "iso:country":"RS",
    "name:ceb_x_preferred":[
        "Lok"
    ],
    "name:deu_x_preferred":[
        "Lok"
    ],
    "name:eng_x_preferred":[
        "Lok"
    ],
    "name:epo_x_preferred":[
        "Lok"
    ],
    "name:fra_x_preferred":[
        "Lok"
    ],
    "name:hrv_x_preferred":[
        "Lok"
    ],
    "name:hun_x_preferred":[
        "Sajk\u00e1slak"
    ],
    "name:msa_x_preferred":[
        "Lok"
    ],
    "name:nld_x_preferred":[
        "Lok"
    ],
    "name:slv_x_preferred":[
        "Lok"
    ],
    "name:srp_x_preferred":[
        "Lok"
    ],
    "name:srp_x_variant":[
        "\u041b\u043e\u043a"
    ],
    "name:ukr_x_preferred":[
        "\u041b\u043e\u043a"
    ],
    "name:unk_x_variant":[
        "Sajk\u00e1slak"
    ],
    "qs:name":"Lok",
    "qs:photos_9r":0,
    "qs:photos_sr":0,
    "qs:pop_sr":"3",
    "wd:wordcount":260,
    "wof:name":"Lok",
    "wof:placetype":"locality",
    "wof:population":1509
},
  "geometry": {"coordinates":[20.21222,45.21583],"type":"Point"}
}