{
  "type": "Feature",
  "properties": {
    "iso:country":"RS",
    "name:eng_x_preferred":[
        "Savski Venac"
    ],
    "name:srp_cyr_x_preferred":[
        "\u0421\u0430\u0432\u0441\u043a\u0438 \u0412\u0435\u043d\u0430\u0446"
    ],
    "name:srp_x_preferred":[
        "\u0421\u0430\u0432\u0441\u043a\u0438 \u0412\u0435\u043d\u0430\u0446"
    ],
    "wof:name":"Savski Venac",
    "wof:placetype":"neighbourhood"
},
  "geometry": {"coordinates":[20.45329422569104,44.80147702761487],"type":"Point"}
}