{
  "type": "Feature",
  "properties": {
    "gn:country":"RS",
    "gn:fcode":"PPL",
    "gn:population":5476,
    "iso:country":"RS",
    "name:ceb_x_preferred":[
        "Stani\u0161i\u0107"
    ],
    "name:deu_x_preferred":[
        "Stani\u0161i\u0107"
    ],
    "name:ell_x_preferred":[
        "\u03a3\u03c4\u03ac\u03bd\u03b9\u03c3\u03b9\u03c4\u03c2"
    ],
    "name:eng_x_preferred":[
        "Stani\u0161i\u0107"
    ],
    "name:epo_x_preferred":[
        "Stani\u015di\u0109"
    ],
    "name:fas_x_preferred":[
        "\u0633\u062a\u0627\u0646\u06cc\u0634\u06cc\u0686"
    ],
    "name:fra_x_preferred":[
        "Stani\u0161i\u0107"
    ],
    "name:heb_x_preferred":[
        "\u05e1\u05d8\u05d0\u05e0\u05d9\u05e9\u05d9\u05e5'"
    ],
    "name:hrv_x_preferred":[
        "Stani\u0161i\u0107"
    ],
    "name:hun_x_preferred":[
        "\u0150rsz\u00e1ll\u00e1s"
    ],
    "name:msa_x_preferred":[
        "Stani\u0161i\u0107"
    ],
    "name:nld_x_preferred":[
        "Stani\u0161i\u0107"
    ],
    "name:pol_x_preferred":[
        "Stani\u0161i\u0107"
    ],
    "name:slv_x_preferred":[
        "Stani\u0161i\u0107"
    ],
    "name:spa_x_preferred":[
        "Stani\u0161i\u0107"
    ],
    "name:srp_x_preferred":[
        "Stani\u0161i\u0107"
    ],
    "name:srp_x_variant":[
        "\u0421\u0442\u0430\u043d\u0438\u0448\u0438\u045b"
    ],
    "name:ukr_x_preferred":[
        "\u0421\u0442\u0430\u043d\u0438\u0448\u0438\u0447"
    ],
    "name:und_x_variant":[
        "Deutschwachenheim"
    ],
    "qs:name":"Stani\u0161i\u0107",
    "qs:name_adm0":"Serbia",
    "qs:name_adm1":"Zapadna Bachka",
    "qs:photos_9r":0,
    "qs:photos_sr":0,
    "qs:placetype":"Town",
    "qs:pop_sr":"5",
    "wd:wordcount":16,
    "wof:name":"Stani\u0161i\u0107",
    "wof:placetype":"locality",
    "wof:population":5476
},
  "geometry": {"coordinates":[19.16709,45.93895],"type":"Point"}
}