{
  "type": "Feature",
  "properties": {
    "gn:admin1_code":"SE",
    "gn:admin2_code":"24",
    "gn:asciiname":"Ilince",
    "gn:country_code":"RS",
    "gn:dem":747,
    "gn:feature_class":"P",
    "gn:feature_code":"PPLL",
    "gn:name":"Ilince",
    "gn:population":0,
    "gn:timezone":"Europe/Belgrade",
    "iso:country":"RS",
    "name:bul_x_preferred":[
        "\u0418\u043b\u0438\u043d\u0446\u0435"
    ],
    "name:ceb_x_preferred":[
        "Ilince"
    ],
    "name:fra_x_preferred":[
        "Ilince"
    ],
    "name:mkd_x_preferred":[
        "\u0418\u043b\u0438\u043d\u0446\u0435"
    ],
    "name:msa_x_preferred":[
        "Ilince"
    ],
    "name:por_x_preferred":[
        "Ilince"
    ],
    "name:slv_x_preferred":[
        "Ilince"
    ],
    "name:sqi_x_preferred":[
        "Ilinca"
    ],
    "name:srp_x_preferred":[
        "Ilince"
    ],
    "name:srp_x_variant":[
        "\u0418\u043b\u0438\u043d\u0446\u0435"
    ],
    "wof:name":"Ilince",
    "wof:placetype":"locality"
},
  "geometry": {"coordinates":[21.59617,42.35241],"type":"Point"}
}