{
  "type": "Feature",
  "properties": {
    "gn:country":"RS",
    "gn:fcode":"PPL",
    "gn:pop":7805,
    "iso:country":"RS",
    "name:dut_x_preferred":[
        "Novo Milo\u0161evo"
    ],
    "name:eng_x_preferred":[
        "Novo Milo\u0161evo"
    ],
    "name:epo_x_preferred":[
        "Novo Milo\u015devo"
    ],
    "name:fre_x_preferred":[
        "Novo Milo\u0161evo"
    ],
    "name:ger_x_preferred":[
        "Novo Milo\u0161evo"
    ],
    "name:hrv_x_preferred":[
        "Novo Milo\u0161evo"
    ],
    "name:hun_x_preferred":[
        "Beodra"
    ],
    "name:may_x_preferred":[
        "Novo Milo\u0161evo"
    ],
    "name:pol_x_preferred":[
        "Novo Milo\u0161evo"
    ],
    "name:rum_x_preferred":[
        "Novo Milo\u0161evo"
    ],
    "name:slv_x_preferred":[
        "Novo Milo\u0161evo"
    ],
    "name:srp_x_preferred":[
        "Novo Milo\u0161evo"
    ],
    "name:unk_x_variant":[
        "Beodra"
    ],
    "qs:name":"Novo Milo\u0161evo",
    "qs:photos_9r":0,
    "qs:photos_sr":0,
    "qs:pop_sr":"5",
    "wd:wordcount":283,
    "wof:name":"Novo Milo\u0161evo",
    "wof:placetype":"locality",
    "wof:population":7805
},
  "geometry": {"coordinates":[20.30364,45.71916],"type":"Point"}
}