{
  "type": "Feature",
  "properties": {
    "gn:country":"RS",
    "gn:fcode":"PPL",
    "gn:population":7805,
    "iso:country":"RS",
    "name:ceb_x_preferred":[
        "Novo Milo\u0161evo"
    ],
    "name:deu_x_preferred":[
        "Novo Milo\u0161evo"
    ],
    "name:eng_x_preferred":[
        "Novo Milo\u0161evo"
    ],
    "name:epo_x_preferred":[
        "Novo Milo\u015devo"
    ],
    "name:fas_x_preferred":[
        "\u0646\u0648\u0648\u0648 \u0645\u06cc\u0644\u0648\u0634\u0648\u0648"
    ],
    "name:fra_x_preferred":[
        "Novo Milo\u0161evo"
    ],
    "name:heb_x_preferred":[
        "\u05e0\u05d5\u05d1\u05d5 \u05de\u05d9\u05dc\u05d5\u05e9\u05d1\u05d5"
    ],
    "name:hrv_x_preferred":[
        "Novo Milo\u0161evo"
    ],
    "name:hun_x_preferred":[
        "Beodra"
    ],
    "name:msa_x_preferred":[
        "Novo Milo\u0161evo"
    ],
    "name:nld_x_preferred":[
        "Novo Milo\u0161evo"
    ],
    "name:pol_x_preferred":[
        "Novo Milo\u0161evo"
    ],
    "name:ron_x_preferred":[
        "Novo Milo\u0161evo"
    ],
    "name:rus_x_preferred":[
        "\u041d\u043e\u0432\u043e-\u041c\u0438\u043b\u043e\u0448\u0435\u0432\u043e"
    ],
    "name:slv_x_preferred":[
        "Novo Milo\u0161evo"
    ],
    "name:spa_x_preferred":[
        "Novo Milo\u0161evo"
    ],
    "name:srp_x_preferred":[
        "Novo Milo\u0161evo"
    ],
    "name:srp_x_variant":[
        "\u041c\u0430\u043b\u0430 \u041c\u043e\u0448\u0442\u0430\u043d\u0438\u0446\u0430",
        "\u041d\u043e\u0432\u043e \u041c\u0438\u043b\u043e\u0448\u0435\u0432\u043e"
    ],
    "qs:name":"Novo Milo\u0161evo",
    "qs:photos_9r":0,
    "qs:photos_sr":0,
    "qs:pop_sr":"5",
    "wd:wordcount":283,
    "wof:name":"Novo Milo\u0161evo",
    "wof:placetype":"locality",
    "wof:population":7805
},
  "geometry": {"coordinates":[20.30364,45.71916],"type":"Point"}
}