{
  "type": "Feature",
  "properties": {
    "gn:admin1_code":"SE",
    "gn:admin2_code":"19",
    "gn:asciiname":"Ugrinici",
    "gn:country_code":"RS",
    "gn:dem":956,
    "gn:feature_class":"P",
    "gn:feature_code":"PPL",
    "gn:name":"Ugrini\u0107i",
    "gn:population":0,
    "gn:timezone":"Europe/Belgrade",
    "iso:country":"RS",
    "name:srp_x_preferred":[
        "Ugrini\u0107i"
    ],
    "wof:name":"Ugrinici",
    "wof:placetype":"locality"
},
  "geometry": {"coordinates":[20.80656,43.40962],"type":"Point"}
}