{
  "type": "Feature",
  "properties": {
    "gn:admin1_code":"SE",
    "gn:admin2_code":"12",
    "gn:asciiname":"Trgoviste",
    "gn:country_code":"RS",
    "gn:dem":558,
    "gn:feature_class":"P",
    "gn:feature_code":"PPL",
    "gn:name":"Trgovi\u0161te",
    "gn:population":0,
    "gn:timezone":"Europe/Belgrade",
    "iso:country":"RS",
    "wof:name":"Trgoviste",
    "wof:placetype":"locality"
},
  "geometry": {"coordinates":[20.70536,43.80424],"type":"Point"}
}