{
  "type": "Feature",
  "properties": {
    "gn:admin1_code":"SE",
    "gn:admin2_code":"18",
    "gn:asciiname":"Leskova",
    "gn:country_code":"RS",
    "gn:dem":1229,
    "gn:feature_class":"P",
    "gn:feature_code":"PPL",
    "gn:name":"Leskova",
    "gn:population":0,
    "gn:timezone":"Europe/Belgrade",
    "iso:country":"RS",
    "name:ceb_x_preferred":[
        "Leskova"
    ],
    "name:fra_x_preferred":[
        "Leskova"
    ],
    "name:msa_x_preferred":[
        "Leskova"
    ],
    "name:nld_x_preferred":[
        "Leskova"
    ],
    "name:por_x_preferred":[
        "Leskova"
    ],
    "name:slv_x_preferred":[
        "Leskova"
    ],
    "name:sqi_x_preferred":[
        "Leskova"
    ],
    "name:srp_x_preferred":[
        "Leskova"
    ],
    "name:srp_x_variant":[
        "\u041b\u0435\u0441\u043a\u043e\u0432\u0430"
    ],
    "wof:name":"Leskova",
    "wof:placetype":"locality"
},
  "geometry": {"coordinates":[20.17835,43.06159],"type":"Point"}
}