{
  "type": "Feature",
  "properties": {
    "gn:admin1_code":"SE",
    "gn:admin2_code":"16",
    "gn:asciiname":"Zunici",
    "gn:country_code":"RS",
    "gn:dem":1036,
    "gn:feature_class":"P",
    "gn:feature_code":"PPL",
    "gn:name":"\u017duni\u0107i",
    "gn:population":0,
    "gn:timezone":"Europe/Belgrade",
    "iso:country":"RS",
    "wof:name":"Zunici",
    "wof:placetype":"locality"
},
  "geometry": {"coordinates":[19.92528,43.58556],"type":"Point"}
}