{
  "type": "Feature",
  "properties": {
    "gn:admin1_code":"SE",
    "gn:admin2_code":"0",
    "gn:asciiname":"Mali Borak",
    "gn:country_code":"RS",
    "gn:dem":111,
    "gn:feature_class":"P",
    "gn:feature_code":"PPL",
    "gn:name":"Mali Borak",
    "gn:population":0,
    "gn:timezone":"Europe/Belgrade",
    "iso:country":"RS",
    "name:fas_x_preferred":[
        "\u0645\u0627\u0644\u06cc \u0628\u0648\u0631\u0627\u06a9"
    ],
    "name:fra_x_preferred":[
        "Mali Borak"
    ],
    "name:msa_x_preferred":[
        "Mali Borak"
    ],
    "name:nld_x_preferred":[
        "Mali Borak"
    ],
    "name:por_x_preferred":[
        "Mali Borak"
    ],
    "name:slv_x_preferred":[
        "Lajkovac"
    ],
    "name:srp_x_preferred":[
        "Mali Borak"
    ],
    "name:srp_x_variant":[
        "\u041c\u0430\u043b\u0438 \u0411\u043e\u0440\u0430\u043a"
    ],
    "wof:name":"Mali Borak",
    "wof:placetype":"locality"
},
  "geometry": {"coordinates":[20.22748,44.47843],"type":"Point"}
}