{
  "type": "Feature",
  "properties": {
    "gn:admin1_code":"SE",
    "gn:admin2_code":"0",
    "gn:asciiname":"Mali Borak",
    "gn:country_code":"RS",
    "gn:dem":111,
    "gn:feature_class":"P",
    "gn:feature_code":"PPL",
    "gn:name":"Mali Borak",
    "gn:population":0,
    "gn:timezone":"Europe/Belgrade",
    "iso:country":"RS",
    "name:srp_x_preferred":[
        "Mali Borak"
    ],
    "wof:name":"Mali Borak",
    "wof:placetype":"locality"
},
  "geometry": {"coordinates":[20.22748,44.47843],"type":"Point"}
}