{
  "type": "Feature",
  "properties": {
    "gn:admin1_code":"SE",
    "gn:admin2_code":"20",
    "gn:asciiname":"Prokopova Kutina",
    "gn:country_code":"RS",
    "gn:dem":301,
    "gn:feature_class":"P",
    "gn:feature_code":"PPL",
    "gn:name":"Prokopova Kutina",
    "gn:population":0,
    "gn:timezone":"Europe/Belgrade",
    "iso:country":"RS",
    "name:srp_x_preferred":[
        "Prokopova Kutina"
    ],
    "wof:name":"Prokopova Kutina",
    "wof:placetype":"locality"
},
  "geometry": {"coordinates":[22.0409,43.22496],"type":"Point"}
}