{
  "type": "Feature",
  "properties": {
    "iso:country":"RS",
    "name:eng_x_preferred":[
        "Zrenjaninski Put"
    ],
    "name:srp_cyr_x_preferred":[
        "\u0417\u0440\u0435\u045a\u0430\u043d\u0438\u043d\u0441\u043a\u0438 \u043f\u0443\u0442"
    ],
    "name:srp_x_preferred":[
        "\u0417\u0440\u0435\u045a\u0430\u043d\u0438\u043d\u0441\u043a\u0438 \u043f\u0443\u0442"
    ],
    "wof:name":"Zrenjaninski Put",
    "wof:placetype":"neighbourhood"
},
  "geometry": {"coordinates":[20.46166272202815,44.88700033559535],"type":"Point"}
}