{
  "type": "Feature",
  "properties": {
    "gn:admin1_code":"SE",
    "gn:admin2_code":"20",
    "gn:asciiname":"Vrcenovica",
    "gn:country_code":"RS",
    "gn:dem":253,
    "gn:feature_class":"P",
    "gn:feature_code":"PPL",
    "gn:name":"Vr\u0107enovica",
    "gn:population":0,
    "gn:timezone":"Europe/Belgrade",
    "iso:country":"RS",
    "name:srp_x_preferred":[
        "Vr\u0107enovica"
    ],
    "wof:name":"Vrcenovica",
    "wof:placetype":"locality"
},
  "geometry": {"coordinates":[21.67008,43.43117],"type":"Point"}
}