{
  "type": "Feature",
  "properties": {
    "gn:admin1_code":"SE",
    "gn:admin2_code":"17",
    "gn:asciiname":"Milicevici",
    "gn:country_code":"RS",
    "gn:dem":673,
    "gn:feature_class":"P",
    "gn:feature_code":"PPL",
    "gn:name":"Milicevi\u0107i",
    "gn:population":0,
    "gn:timezone":"Europe/Belgrade",
    "iso:country":"RS",
    "name:srp_x_preferred":[
        "Milicevi\u0107i"
    ],
    "wof:name":"Milicevici",
    "wof:placetype":"locality"
},
  "geometry": {"coordinates":[20.24361,43.63306],"type":"Point"}
}