{
  "type": "Feature",
  "properties": {
    "gn:admin1_code":"SE",
    "gn:admin2_code":"16",
    "gn:asciiname":"Ritosici",
    "gn:country_code":"RS",
    "gn:dem":980,
    "gn:feature_class":"P",
    "gn:feature_code":"PPLL",
    "gn:name":"Rito\u0161i\u0107i",
    "gn:population":0,
    "gn:timezone":"Europe/Belgrade",
    "iso:country":"RS",
    "wof:name":"Ritosici",
    "wof:placetype":"locality"
},
  "geometry": {"coordinates":[19.2925,43.45389],"type":"Point"}
}