{
  "type": "Feature",
  "properties": {
    "gn:admin1_code":"SE",
    "gn:admin2_code":"16",
    "gn:asciiname":"Orovac",
    "gn:country_code":"RS",
    "gn:dem":726,
    "gn:feature_class":"P",
    "gn:feature_code":"PPLL",
    "gn:name":"Orovac",
    "gn:population":0,
    "gn:timezone":"Europe/Belgrade",
    "iso:country":"RS",
    "name:srp_x_preferred":[
        "Orovac"
    ],
    "wof:name":"Orovac",
    "wof:placetype":"locality"
},
  "geometry": {"coordinates":[19.5954,43.382],"type":"Point"}
}