{
  "type": "Feature",
  "properties": {
    "gn:admin1_code":"SE",
    "gn:admin2_code":"24",
    "gn:asciiname":"Usinovci",
    "gn:country_code":"RS",
    "gn:dem":1401,
    "gn:feature_class":"P",
    "gn:feature_code":"PPL",
    "gn:name":"U\u0161inovci",
    "gn:population":0,
    "gn:timezone":"Europe/Belgrade",
    "iso:country":"RS",
    "wof:name":"Usinovci",
    "wof:placetype":"locality"
},
  "geometry": {"coordinates":[22.30965,42.46917],"type":"Point"}
}