{
  "type": "Feature",
  "properties": {
    "iso:country":"RS",
    "name:eng_x_preferred":[
        "Centar V"
    ],
    "name:srp_cyr_x_preferred":[
        "\u0426\u0435\u043d\u0442\u0430\u0440 V"
    ],
    "name:srp_x_preferred":[
        "\u0426\u0435\u043d\u0442\u0430\u0440 V"
    ],
    "wof:name":"Centar V",
    "wof:placetype":"neighbourhood"
},
  "geometry": {"coordinates":[20.45542568886067,44.88762871323039],"type":"Point"}
}