{
  "type": "Feature",
  "properties": {
    "gn:admin1_code":"SE",
    "gn:admin2_code":"16",
    "gn:asciiname":"Glog",
    "gn:country_code":"RS",
    "gn:dem":1035,
    "gn:feature_class":"P",
    "gn:feature_code":"PPL",
    "gn:name":"Glog",
    "gn:population":0,
    "gn:timezone":"Europe/Belgrade",
    "iso:country":"RS",
    "name:ceb_x_preferred":[
        "Glog"
    ],
    "name:srp_x_preferred":[
        "Glog"
    ],
    "name:swe_x_preferred":[
        "Glog"
    ],
    "wof:name":"Glog",
    "wof:placetype":"locality"
},
  "geometry": {"coordinates":[19.36401,43.45065],"type":"Point"}
}