{
  "type": "Feature",
  "properties": {
    "gn:admin1_code":"SE",
    "gn:admin2_code":"18",
    "gn:asciiname":"Zabrge",
    "gn:country_code":"RS",
    "gn:dem":1016,
    "gn:feature_class":"P",
    "gn:feature_code":"PPL",
    "gn:name":"Zabr\u0111e",
    "gn:population":0,
    "gn:timezone":"Europe/Belgrade",
    "iso:country":"RS",
    "name:srp_x_preferred":[
        "Zabr\u0111e"
    ],
    "wof:name":"Zabrge",
    "wof:placetype":"locality"
},
  "geometry": {"coordinates":[20.38922,43.13584],"type":"Point"}
}