{
  "type": "Feature",
  "properties": {
    "gn:admin1_code":"SE",
    "gn:admin2_code":"16",
    "gn:asciiname":"Seliste",
    "gn:country_code":"RS",
    "gn:dem":713,
    "gn:feature_class":"P",
    "gn:feature_code":"PPL",
    "gn:name":"Seli\u0161te",
    "gn:population":0,
    "gn:timezone":"Europe/Belgrade",
    "iso:country":"RS",
    "name:srp_x_preferred":[
        "Seli\u0161te"
    ],
    "wof:name":"Seliste",
    "wof:placetype":"locality"
},
  "geometry": {"coordinates":[19.73188,44.05481],"type":"Point"}
}