{
  "type": "Feature",
  "properties": {
    "gn:admin1_code":"SE",
    "gn:admin2_code":"16",
    "gn:asciiname":"Seliste",
    "gn:country_code":"RS",
    "gn:dem":713,
    "gn:feature_class":"P",
    "gn:feature_code":"PPL",
    "gn:name":"Seli\u0161te",
    "gn:population":0,
    "gn:timezone":"Europe/Belgrade",
    "iso:country":"RS",
    "name:ceb_x_preferred":[
        "Seliste"
    ],
    "name:est_x_preferred":[
        "Seliste"
    ],
    "name:hye_x_preferred":[
        "\u054d\u0565\u056c\u056b\u057d\u057f\u0565"
    ],
    "name:pol_x_preferred":[
        "Seliste"
    ],
    "name:srp_x_preferred":[
        "Seli\u0161te"
    ],
    "name:ukr_x_preferred":[
        "\u0421\u0435\u043b\u0456\u0441\u0442\u0435"
    ],
    "name:vol_x_preferred":[
        "Seliste"
    ],
    "wof:name":"Seliste",
    "wof:placetype":"locality"
},
  "geometry": {"coordinates":[19.73188,44.05481],"type":"Point"}
}