{
  "type": "Feature",
  "properties": {
    "gn:admin1_code":"SE",
    "gn:admin2_code":"24",
    "gn:asciiname":"Gornja Trnica",
    "gn:country_code":"RS",
    "gn:dem":1141,
    "gn:feature_class":"P",
    "gn:feature_code":"PPLL",
    "gn:name":"Gornja Trnica",
    "gn:population":0,
    "gn:timezone":"Europe/Belgrade",
    "iso:country":"RS",
    "name:bul_x_preferred":[
        "\u0413\u043e\u0440\u043d\u0430 \u0422\u044a\u0440\u043d\u0438\u0446\u0430"
    ],
    "name:fra_x_preferred":[
        "Gornja Trnica"
    ],
    "name:msa_x_preferred":[
        "Gornja Trnica"
    ],
    "name:por_x_preferred":[
        "Gornja Trnica"
    ],
    "name:slv_x_preferred":[
        "Gornja Trnica"
    ],
    "name:srp_x_preferred":[
        "Gornja Trnica"
    ],
    "name:srp_x_variant":[
        "\u0413\u043e\u0440\u045a\u0430 \u0422\u0440\u043d\u0438\u0446\u0430"
    ],
    "wof:name":"Gornja Trnica",
    "wof:placetype":"locality"
},
  "geometry": {"coordinates":[22.14882,42.35546],"type":"Point"}
}