{
  "type": "Feature",
  "properties": {
    "gn:admin1_code":"SE",
    "gn:admin2_code":"20",
    "gn:asciiname":"Mali Drenovac",
    "gn:country_code":"RS",
    "gn:dem":250,
    "gn:feature_class":"P",
    "gn:feature_code":"PPL",
    "gn:name":"Mali Drenovac",
    "gn:population":0,
    "gn:timezone":"Europe/Belgrade",
    "iso:country":"RS",
    "name:srp_x_preferred":[
        "Mali Drenovac"
    ],
    "wof:name":"Mali Drenovac",
    "wof:placetype":"locality"
},
  "geometry": {"coordinates":[21.67419,43.4567],"type":"Point"}
}