{
  "type": "Feature",
  "properties": {
    "gn:admin1_code":"SE",
    "gn:admin2_code":"18",
    "gn:asciiname":"Perose",
    "gn:country_code":"RS",
    "gn:dem":768,
    "gn:feature_class":"P",
    "gn:feature_code":"PPL",
    "gn:name":"Pero\u0161e",
    "gn:population":0,
    "gn:timezone":"Europe/Belgrade",
    "iso:country":"RS",
    "name:srp_x_preferred":[
        "Pero\u0161e"
    ],
    "wof:name":"Perose",
    "wof:placetype":"locality"
},
  "geometry": {"coordinates":[20.49141,42.97108],"type":"Point"}
}