{
  "type": "Feature",
  "properties": {
    "gn:admin1_code":"SE",
    "gn:admin2_code":"19",
    "gn:asciiname":"Starci",
    "gn:country_code":"RS",
    "gn:dem":583,
    "gn:feature_class":"P",
    "gn:feature_code":"PPL",
    "gn:name":"Starci",
    "gn:population":0,
    "gn:timezone":"Europe/Belgrade",
    "iso:country":"RS",
    "name:srp_x_preferred":[
        "Starci"
    ],
    "wof:name":"Starci",
    "wof:placetype":"locality"
},
  "geometry": {"coordinates":[21.00873,43.46403],"type":"Point"}
}