{
  "type": "Feature",
  "properties": {
    "gn:admin1_code":"SE",
    "gn:admin2_code":"19",
    "gn:asciiname":"Starci",
    "gn:country_code":"RS",
    "gn:dem":583,
    "gn:feature_class":"P",
    "gn:feature_code":"PPL",
    "gn:name":"Starci",
    "gn:population":0,
    "gn:timezone":"Europe/Belgrade",
    "iso:country":"RS",
    "name:fra_x_preferred":[
        "Starci"
    ],
    "name:hye_x_preferred":[
        "\u054d\u057f\u0561\u0580\u0581\u056b"
    ],
    "name:msa_x_preferred":[
        "Starci"
    ],
    "name:por_x_preferred":[
        "Starci"
    ],
    "name:slv_x_preferred":[
        "Starci"
    ],
    "name:spa_x_preferred":[
        "Starci"
    ],
    "name:srp_x_preferred":[
        "Starci"
    ],
    "name:srp_x_variant":[
        "\u0421\u0442\u0430\u0440\u0446\u0438"
    ],
    "wof:name":"Starci",
    "wof:placetype":"locality"
},
  "geometry": {"coordinates":[21.00873,43.46403],"type":"Point"}
}