{
  "type": "Feature",
  "properties": {
    "gn:admin1_code":"SE",
    "gn:admin2_code":"13",
    "gn:asciiname":"Donje Medare",
    "gn:country_code":"RS",
    "gn:dem":281,
    "gn:feature_class":"P",
    "gn:feature_code":"PPLL",
    "gn:name":"Donje Medare",
    "gn:population":0,
    "gn:timezone":"Europe/Belgrade",
    "iso:country":"RS",
    "wof:name":"Donje Medare",
    "wof:placetype":"locality"
},
  "geometry": {"coordinates":[21.4575,44.0075],"type":"Point"}
}