{
  "type": "Feature",
  "properties": {
    "gn:admin1_code":"SE",
    "gn:admin2_code":"18",
    "gn:asciiname":"Batrage",
    "gn:country_code":"RS",
    "gn:dem":842,
    "gn:feature_class":"P",
    "gn:feature_code":"PPL",
    "gn:name":"Batrage",
    "gn:population":0,
    "gn:timezone":"Europe/Belgrade",
    "iso:country":"RS",
    "name:srp_x_preferred":[
        "Batrage"
    ],
    "name:und_x_variant":[
        "Batra\u010de"
    ],
    "wof:name":"Batrage",
    "wof:placetype":"locality"
},
  "geometry": {"coordinates":[20.39442,42.93662],"type":"Point"}
}