{
  "type": "Feature",
  "properties": {
    "gn:admin1_code":"SE",
    "gn:admin2_code":"13",
    "gn:asciiname":"Gornji Dubic",
    "gn:country_code":"RS",
    "gn:dem":683,
    "gn:feature_class":"P",
    "gn:feature_code":"PPL",
    "gn:name":"Gornji Dubi\u010d",
    "gn:population":0,
    "gn:timezone":"Europe/Belgrade",
    "iso:country":"RS",
    "name:srp_x_preferred":[
        "Gornji Dubi\u010d"
    ],
    "wof:name":"Gornji Dubic",
    "wof:placetype":"locality"
},
  "geometry": {"coordinates":[21.00639,43.73833],"type":"Point"}
}