{
  "type": "Feature",
  "properties": {
    "gn:admin1_code":"SE",
    "gn:admin2_code":"13",
    "gn:asciiname":"Gornji Dubic",
    "gn:country_code":"RS",
    "gn:dem":683,
    "gn:feature_class":"P",
    "gn:feature_code":"PPL",
    "gn:name":"Gornji Dubi\u010d",
    "gn:population":0,
    "gn:timezone":"Europe/Belgrade",
    "iso:country":"RS",
    "name:ceb_x_preferred":[
        "Gornji Dubi\u010d"
    ],
    "name:fra_x_preferred":[
        "Gornji Dubi\u010d"
    ],
    "name:msa_x_preferred":[
        "Gornji Dubi\u010d"
    ],
    "name:por_x_preferred":[
        "Gornji Dubi\u010d"
    ],
    "name:slv_x_preferred":[
        "Gornji Dubi\u010d"
    ],
    "name:srp_x_preferred":[
        "Gornji Dubi\u010d"
    ],
    "name:srp_x_variant":[
        "\u0413\u043e\u0440\u045a\u0438 \u0414\u0443\u0431\u0438\u0447"
    ],
    "wof:name":"Gornji Dubic",
    "wof:placetype":"locality"
},
  "geometry": {"coordinates":[21.00639,43.73833],"type":"Point"}
}