{
  "type": "Feature",
  "properties": {
    "gn:admin1_code":"SE",
    "gn:admin2_code":"19",
    "gn:asciiname":"Grkljane",
    "gn:country_code":"RS",
    "gn:dem":226,
    "gn:feature_class":"P",
    "gn:feature_code":"PPL",
    "gn:name":"Grkljane",
    "gn:population":0,
    "gn:timezone":"Europe/Belgrade",
    "iso:country":"RS",
    "name:ceb_x_preferred":[
        "Grkljane"
    ],
    "name:fra_x_preferred":[
        "Grkljane"
    ],
    "name:msa_x_preferred":[
        "Grkljane"
    ],
    "name:por_x_preferred":[
        "Grkljane"
    ],
    "name:slv_x_preferred":[
        "Grkljane"
    ],
    "name:srp_x_preferred":[
        "Grkljane"
    ],
    "name:srp_x_variant":[
        "\u0413\u0440\u043a\u0459\u0430\u043d\u0435"
    ],
    "wof:name":"Grkljane",
    "wof:placetype":"locality"
},
  "geometry": {"coordinates":[21.22875,43.43473],"type":"Point"}
}