{
  "type": "Feature",
  "properties": {
    "gn:admin1_code":"SE",
    "gn:admin2_code":"18",
    "gn:asciiname":"Borikovac",
    "gn:country_code":"RS",
    "gn:dem":885,
    "gn:feature_class":"P",
    "gn:feature_code":"PPL",
    "gn:name":"Borikovac",
    "gn:population":0,
    "gn:timezone":"Europe/Belgrade",
    "iso:country":"RS",
    "name:srp_x_preferred":[
        "Borikovac"
    ],
    "wof:name":"Borikovac",
    "wof:placetype":"locality"
},
  "geometry": {"coordinates":[20.55642000000001,43.07328],"type":"Point"}
}