{
  "type": "Feature",
  "properties": {
    "gn:admin1_code":"SE",
    "gn:admin2_code":"0",
    "gn:asciiname":"Brestovi",
    "gn:country_code":"RS",
    "gn:dem":166,
    "gn:feature_class":"P",
    "gn:feature_code":"PPL",
    "gn:name":"Brestovi",
    "gn:population":0,
    "gn:timezone":"Europe/Belgrade",
    "iso:country":"RS",
    "wof:name":"Brestovi",
    "wof:placetype":"locality"
},
  "geometry": {"coordinates":[20.64439,44.57052],"type":"Point"}
}