{
  "type": "Feature",
  "properties": {
    "gn:admin1_code":"SE",
    "gn:admin2_code":"22",
    "gn:asciiname":"Provaljenik",
    "gn:country_code":"RS",
    "gn:dem":568,
    "gn:feature_class":"P",
    "gn:feature_code":"PPL",
    "gn:name":"Provaljenik",
    "gn:population":0,
    "gn:timezone":"Europe/Belgrade",
    "iso:country":"RS",
    "name:ceb_x_preferred":[
        "Provaljenik"
    ],
    "name:fra_x_preferred":[
        "Provaljenik"
    ],
    "name:hun_x_preferred":[
        "Provaljenik"
    ],
    "name:msa_x_preferred":[
        "Provaljenik"
    ],
    "name:por_x_preferred":[
        "Provaljenik"
    ],
    "name:slv_x_preferred":[
        "Provaljenik"
    ],
    "name:srp_x_preferred":[
        "Provaljenik"
    ],
    "name:srp_x_variant":[
        "\u041f\u0440\u043e\u0432\u0430\u0459\u0435\u043d\u0438\u043a"
    ],
    "wof:name":"Provaljenik",
    "wof:placetype":"locality"
},
  "geometry": {"coordinates":[22.37666,43.0877],"type":"Point"}
}