{
  "type": "Feature",
  "properties": {
    "gn:admin1_code":"SE",
    "gn:admin2_code":"11",
    "gn:asciiname":"Oreskovica",
    "gn:country_code":"RS",
    "gn:dem":180,
    "gn:feature_class":"P",
    "gn:feature_code":"PPL",
    "gn:name":"Ore\u0161kovica",
    "gn:population":0,
    "gn:timezone":"Europe/Belgrade",
    "iso:country":"RS",
    "name:ceb_x_preferred":[
        "Ore\u0161kovica"
    ],
    "name:fra_x_preferred":[
        "Ore\u0161kovica"
    ],
    "name:msa_x_preferred":[
        "Ore\u0161kovica"
    ],
    "name:nld_x_preferred":[
        "Ore\u0161kovica"
    ],
    "name:por_x_preferred":[
        "Ore\u0161kovica"
    ],
    "name:slv_x_preferred":[
        "Ore\u0161kovica"
    ],
    "name:srp_x_preferred":[
        "Ore\u0161kovica"
    ],
    "name:srp_x_variant":[
        "\u041e\u0440\u0435\u0448\u043a\u043e\u0432\u0438\u0446\u0430"
    ],
    "wof:name":"Oreskovica",
    "wof:placetype":"locality"
},
  "geometry": {"coordinates":[21.32513,44.3171],"type":"Point"}
}