{
  "type": "Feature",
  "properties": {
    "gn:admin1_code":"SE",
    "gn:admin2_code":"11",
    "gn:asciiname":"Oreskovica",
    "gn:country_code":"RS",
    "gn:dem":180,
    "gn:feature_class":"P",
    "gn:feature_code":"PPL",
    "gn:name":"Ore\u0161kovica",
    "gn:population":0,
    "gn:timezone":"Europe/Belgrade",
    "iso:country":"RS",
    "name:srp_x_preferred":[
        "Ore\u0161kovica"
    ],
    "wof:name":"Oreskovica",
    "wof:placetype":"locality"
},
  "geometry": {"coordinates":[21.32513,44.3171],"type":"Point"}
}