{
  "type": "Feature",
  "properties": {
    "gn:admin1_code":"SE",
    "gn:admin2_code":"17",
    "gn:asciiname":"Vujovici",
    "gn:country_code":"RS",
    "gn:dem":371,
    "gn:feature_class":"P",
    "gn:feature_code":"PPL",
    "gn:name":"Vujovi\u0107i",
    "gn:population":0,
    "gn:timezone":"Europe/Belgrade",
    "iso:country":"RS",
    "name:srp_x_preferred":[
        "Vujovi\u0107i"
    ],
    "wof:name":"Vujovici",
    "wof:placetype":"locality"
},
  "geometry": {"coordinates":[20.36833,43.95167],"type":"Point"}
}