{
  "type": "Feature",
  "properties": {
    "gn:admin1_code":"SE",
    "gn:admin2_code":"0",
    "gn:asciiname":"Ljubinic",
    "gn:country_code":"RS",
    "gn:dem":119,
    "gn:feature_class":"P",
    "gn:feature_code":"PPL",
    "gn:name":"Ljubini\u0107",
    "gn:population":0,
    "gn:timezone":"Europe/Belgrade",
    "iso:country":"RS",
    "name:ceb_x_preferred":[
        "Ljubini\u0107"
    ],
    "name:ell_x_preferred":[
        "\u039b\u03b9\u03bf\u03cd\u03bc\u03c0\u03b9\u03bd\u03b9\u03c4\u03c2"
    ],
    "name:fra_x_preferred":[
        "Ljubini\u0107"
    ],
    "name:msa_x_preferred":[
        "Ljubini\u0107"
    ],
    "name:por_x_preferred":[
        "Ljubini\u0107"
    ],
    "name:slv_x_preferred":[
        "Ljubini\u0107"
    ],
    "name:srp_x_preferred":[
        "Ljubini\u0107"
    ],
    "name:srp_x_variant":[
        "\u0409\u0443\u0431\u0438\u043d\u0438\u045b"
    ],
    "wof:name":"Ljubinic",
    "wof:placetype":"locality"
},
  "geometry": {"coordinates":[20.05851,44.54159],"type":"Point"}
}