{
  "type": "Feature",
  "properties": {
    "gn:admin1_code":"SE",
    "gn:admin2_code":"0",
    "gn:asciiname":"Ljubinic",
    "gn:country_code":"RS",
    "gn:dem":119,
    "gn:feature_class":"P",
    "gn:feature_code":"PPL",
    "gn:name":"Ljubini\u0107",
    "gn:population":0,
    "gn:timezone":"Europe/Belgrade",
    "iso:country":"RS",
    "name:srp_x_preferred":[
        "Ljubini\u0107"
    ],
    "wof:name":"Ljubinic",
    "wof:placetype":"locality"
},
  "geometry": {"coordinates":[20.05851,44.54159],"type":"Point"}
}