{
  "type": "Feature",
  "properties": {
    "gn:admin1_code":"SE",
    "gn:admin2_code":"16",
    "gn:asciiname":"Pralja",
    "gn:country_code":"RS",
    "gn:dem":1161,
    "gn:feature_class":"P",
    "gn:feature_code":"PPLL",
    "gn:name":"Pralja",
    "gn:population":0,
    "gn:timezone":"Europe/Belgrade",
    "iso:country":"RS",
    "name:fra_x_preferred":[
        "Pralja"
    ],
    "name:msa_x_preferred":[
        "Pralja"
    ],
    "name:nld_x_preferred":[
        "Pralja"
    ],
    "name:por_x_preferred":[
        "Pralja"
    ],
    "name:slv_x_preferred":[
        "Pralja"
    ],
    "name:srp_x_preferred":[
        "Pralja"
    ],
    "name:srp_x_variant":[
        "\u041f\u0440\u0430\u0459\u0430"
    ],
    "name:und_x_variant":[
        "Prolea"
    ],
    "wof:name":"Pralja",
    "wof:placetype":"locality"
},
  "geometry": {"coordinates":[19.89223,43.26475],"type":"Point"}
}