{
  "type": "Feature",
  "properties": {
    "gn:admin1_code":"SE",
    "gn:admin2_code":"17",
    "gn:asciiname":"Preljina",
    "gn:country_code":"RS",
    "gn:dem":279,
    "gn:feature_class":"P",
    "gn:feature_code":"PPLL",
    "gn:name":"Preljina",
    "gn:population":0,
    "gn:timezone":"Europe/Belgrade",
    "iso:country":"RS",
    "wof:name":"Preljina",
    "wof:placetype":"locality"
},
  "geometry": {"coordinates":[20.42914,43.91351],"type":"Point"}
}