{
  "type": "Feature",
  "properties": {
    "gn:admin1_code":"SE",
    "gn:admin2_code":"17",
    "gn:asciiname":"Preljina",
    "gn:country_code":"RS",
    "gn:dem":279,
    "gn:feature_class":"P",
    "gn:feature_code":"PPLL",
    "gn:name":"Preljina",
    "gn:population":0,
    "gn:timezone":"Europe/Belgrade",
    "iso:country":"RS",
    "name:ceb_x_preferred":[
        "Preljina"
    ],
    "name:ces_x_preferred":[
        "Preljina"
    ],
    "name:fas_x_preferred":[
        "\u067e\u0631\u0644\u0626\u06cc\u0646\u0627"
    ],
    "name:fra_x_preferred":[
        "Preljina"
    ],
    "name:msa_x_preferred":[
        "Preljina"
    ],
    "name:nld_x_preferred":[
        "Preljina"
    ],
    "name:por_x_preferred":[
        "Preljina"
    ],
    "name:slv_x_preferred":[
        "Preljina"
    ],
    "name:srp_x_preferred":[
        "\u041f\u0440\u0435\u0459\u0438\u043d\u0430"
    ],
    "wof:name":"Preljina",
    "wof:placetype":"locality"
},
  "geometry": {"coordinates":[20.42914,43.91351],"type":"Point"}
}