{
  "type": "Feature",
  "properties": {
    "gn:admin1_code":"SE",
    "gn:admin2_code":"16",
    "gn:asciiname":"Obodnja",
    "gn:country_code":"RS",
    "gn:dem":522,
    "gn:feature_class":"P",
    "gn:feature_code":"PPL",
    "gn:name":"Obodnja",
    "gn:population":0,
    "gn:timezone":"Europe/Belgrade",
    "iso:country":"RS",
    "name:srp_x_preferred":[
        "Obodnja"
    ],
    "wof:name":"Obodnja",
    "wof:placetype":"locality"
},
  "geometry": {"coordinates":[19.63266,44.07787],"type":"Point"}
}