{
  "type": "Feature",
  "properties": {
    "gn:admin1_code":"SE",
    "gn:admin2_code":"24",
    "gn:asciiname":"Linca Mahala",
    "gn:country_code":"RS",
    "gn:dem":586,
    "gn:feature_class":"P",
    "gn:feature_code":"PPL",
    "gn:name":"Lin\u010da Mahala",
    "gn:population":0,
    "gn:timezone":"Europe/Belgrade",
    "iso:country":"RS",
    "wof:name":"Linca Mahala",
    "wof:placetype":"locality"
},
  "geometry": {"coordinates":[21.84722,42.42611],"type":"Point"}
}