{
  "type": "Feature",
  "properties": {
    "gn:admin1_code":"SE",
    "gn:admin2_code":"23",
    "gn:asciiname":"Gornja Lapastica",
    "gn:country_code":"RS",
    "gn:dem":593,
    "gn:feature_class":"P",
    "gn:feature_code":"PPL",
    "gn:name":"Gornja Lapa\u0161tica",
    "gn:population":0,
    "gn:timezone":"Europe/Belgrade",
    "iso:country":"RS",
    "name:srp_x_preferred":[
        "Gornja Lapa\u0161tica"
    ],
    "name:und_x_variant":[
        "Lapa\u0161tica"
    ],
    "wof:name":"Gornja Lapastica",
    "wof:placetype":"locality"
},
  "geometry": {"coordinates":[21.67066,42.85833],"type":"Point"}
}