{
  "type": "Feature",
  "properties": {
    "gn:admin1_code":"SE",
    "gn:admin2_code":"23",
    "gn:asciiname":"Gornja Lapastica",
    "gn:country_code":"RS",
    "gn:dem":593,
    "gn:feature_class":"P",
    "gn:feature_code":"PPL",
    "gn:name":"Gornja Lapa\u0161tica",
    "gn:population":0,
    "gn:timezone":"Europe/Belgrade",
    "iso:country":"RS",
    "name:ceb_x_preferred":[
        "Gornja Lapa\u0161tica"
    ],
    "name:fra_x_preferred":[
        "Gornja Lapa\u0161tica"
    ],
    "name:hun_x_preferred":[
        "Gornja Lapa\u0161tica"
    ],
    "name:msa_x_preferred":[
        "Gornja Lapa\u0161tica"
    ],
    "name:por_x_preferred":[
        "Gornja Lapa\u0161tica"
    ],
    "name:slv_x_preferred":[
        "Donja Lapa\u0161tica"
    ],
    "name:sqi_x_preferred":[
        "Llapashtica e Ep\u00ebrme"
    ],
    "name:srp_x_preferred":[
        "Gornja Lapa\u0161tica"
    ],
    "name:srp_x_variant":[
        "\u0413\u043e\u0440\u045a\u0430 \u041b\u0430\u043f\u0430\u0448\u0442\u0438\u0446\u0430"
    ],
    "name:und_x_variant":[
        "Lapa\u0161tica"
    ],
    "wof:name":"Gornja Lapastica",
    "wof:placetype":"locality"
},
  "geometry": {"coordinates":[21.67066,42.85833],"type":"Point"}
}