{
  "type": "Feature",
  "properties": {
    "gn:admin1_code":"SE",
    "gn:admin2_code":"8",
    "gn:asciiname":"Lazici",
    "gn:country_code":"RS",
    "gn:dem":183,
    "gn:feature_class":"P",
    "gn:feature_code":"PPL",
    "gn:name":"Lazi\u0107i",
    "gn:population":0,
    "gn:timezone":"Europe/Belgrade",
    "iso:country":"RS",
    "name:srp_x_preferred":[
        "Lazi\u0107i"
    ],
    "wof:name":"Lazici",
    "wof:placetype":"locality"
},
  "geometry": {"coordinates":[19.41163,44.5282],"type":"Point"}
}