{
  "type": "Feature",
  "properties": {
    "gn:admin1_code":"SE",
    "gn:admin2_code":"8",
    "gn:asciiname":"Recane",
    "gn:country_code":"RS",
    "gn:dem":171,
    "gn:feature_class":"P",
    "gn:feature_code":"PPL",
    "gn:name":"Re\u010dane",
    "gn:population":0,
    "gn:timezone":"Europe/Belgrade",
    "iso:country":"RS",
    "name:srp_x_preferred":[
        "Re\u010dane"
    ],
    "wof:name":"Recane",
    "wof:placetype":"locality"
},
  "geometry": {"coordinates":[19.71455,44.46588],"type":"Point"}
}