{
  "type": "Feature",
  "properties": {
    "gn:admin1_code":"SE",
    "gn:admin2_code":"13",
    "gn:asciiname":"Stubica",
    "gn:country_code":"RS",
    "gn:dem":321,
    "gn:feature_class":"P",
    "gn:feature_code":"PPL",
    "gn:name":"Stubica",
    "gn:population":0,
    "gn:timezone":"Europe/Belgrade",
    "iso:country":"RS",
    "name:bos_x_preferred":[
        "Stubica"
    ],
    "name:ceb_x_preferred":[
        "Stubica"
    ],
    "name:fra_x_preferred":[
        "Stubica"
    ],
    "name:hrv_x_preferred":[
        "Stubica"
    ],
    "name:hun_x_preferred":[
        "Stubica"
    ],
    "name:slv_x_preferred":[
        "Stubica"
    ],
    "name:srp_x_preferred":[
        "Stubica"
    ],
    "name:srp_x_variant":[
        "\u0421\u0442\u0443\u0431\u0438\u0446\u0430"
    ],
    "name:swe_x_preferred":[
        "Stubica"
    ],
    "wof:name":"Stubica",
    "wof:placetype":"locality"
},
  "geometry": {"coordinates":[21.49715,43.94102],"type":"Point"}
}