{
  "type": "Feature",
  "properties": {
    "gn:admin1_code":"SE",
    "gn:admin2_code":"13",
    "gn:asciiname":"Stubica",
    "gn:country_code":"RS",
    "gn:dem":321,
    "gn:feature_class":"P",
    "gn:feature_code":"PPL",
    "gn:name":"Stubica",
    "gn:population":0,
    "gn:timezone":"Europe/Belgrade",
    "iso:country":"RS",
    "name:srp_x_preferred":[
        "Stubica"
    ],
    "wof:name":"Stubica",
    "wof:placetype":"locality"
},
  "geometry": {"coordinates":[21.49715,43.94102],"type":"Point"}
}