{
  "type": "Feature",
  "properties": {
    "gn:country":"RS",
    "gn:fcode":"PPL",
    "gn:population":4,
    "iso:country":"RS",
    "name:ceb_x_preferred":[
        "Vajska"
    ],
    "name:eng_x_preferred":[
        "Vajska"
    ],
    "name:epo_x_preferred":[
        "Vajska"
    ],
    "name:fas_x_preferred":[
        "\u0648\u0627\u06cc\u0633\u06a9\u0627"
    ],
    "name:fra_x_preferred":[
        "Vajska"
    ],
    "name:hrv_x_preferred":[
        "Vajska"
    ],
    "name:hun_x_preferred":[
        "Vajszka"
    ],
    "name:ita_x_preferred":[
        "Vajska"
    ],
    "name:msa_x_preferred":[
        "Vajska"
    ],
    "name:nld_x_preferred":[
        "Vajska"
    ],
    "name:pol_x_preferred":[
        "Vajska"
    ],
    "name:slv_x_preferred":[
        "Vajska"
    ],
    "name:spa_x_preferred":[
        "Vajska"
    ],
    "name:srp_x_preferred":[
        "Vajska"
    ],
    "name:srp_x_variant":[
        "\u0412\u0430\u0458\u0441\u043a\u0430"
    ],
    "name:ukr_x_preferred":[
        "\u0412\u0430\u0439\u0441\u044c\u043a\u0430"
    ],
    "qs:name":"Vajska",
    "qs:photos_9r":0,
    "qs:photos_sr":0,
    "qs:pop_sr":"1",
    "wd:wordcount":155,
    "wof:name":"Vajska",
    "wof:placetype":"locality",
    "wof:population":4
},
  "geometry": {"coordinates":[19.11194,45.4108],"type":"Point"}
}