{
  "type": "Feature",
  "properties": {
    "gn:admin1_code":"SE",
    "gn:admin2_code":"24",
    "gn:asciiname":"Bogdanska Mahala",
    "gn:country_code":"RS",
    "gn:dem":1138,
    "gn:feature_class":"P",
    "gn:feature_code":"PPL",
    "gn:name":"Bogdanska Mahala",
    "gn:population":0,
    "gn:timezone":"Europe/Belgrade",
    "iso:country":"RS",
    "wof:name":"Bogdanska Mahala",
    "wof:placetype":"locality"
},
  "geometry": {"coordinates":[22.06196,42.44511],"type":"Point"}
}