{
  "type": "Feature",
  "properties": {
    "gn:admin1_code":"SE",
    "gn:admin2_code":"19",
    "gn:asciiname":"Mali Siljegovac",
    "gn:country_code":"RS",
    "gn:dem":326,
    "gn:feature_class":"P",
    "gn:feature_code":"PPL",
    "gn:name":"Mali \u0160iljegovac",
    "gn:population":0,
    "gn:timezone":"Europe/Belgrade",
    "iso:country":"RS",
    "name:ceb_x_preferred":[
        "Mali \u0160iljegovac"
    ],
    "name:fra_x_preferred":[
        "Mali \u0160iljegovac"
    ],
    "name:msa_x_preferred":[
        "Mali \u0160iljegovac"
    ],
    "name:por_x_preferred":[
        "Mali \u0160iljegovac"
    ],
    "name:slv_x_preferred":[
        "Mali \u0160iljegovac"
    ],
    "name:srp_x_preferred":[
        "Mali \u0160iljegovac"
    ],
    "name:srp_x_variant":[
        "\u041c\u0430\u043b\u0438 \u0428\u0438\u0459\u0435\u0433\u043e\u0432\u0430\u0446"
    ],
    "wof:name":"Mali Siljegovac",
    "wof:placetype":"locality"
},
  "geometry": {"coordinates":[21.44165,43.55021],"type":"Point"}
}