{
  "type": "Feature",
  "properties": {
    "gn:admin1_code":"SE",
    "gn:admin2_code":"19",
    "gn:asciiname":"Mali Siljegovac",
    "gn:country_code":"RS",
    "gn:dem":326,
    "gn:feature_class":"P",
    "gn:feature_code":"PPL",
    "gn:name":"Mali \u0160iljegovac",
    "gn:population":0,
    "gn:timezone":"Europe/Belgrade",
    "iso:country":"RS",
    "name:srp_x_preferred":[
        "Mali \u0160iljegovac"
    ],
    "wof:name":"Mali Siljegovac",
    "wof:placetype":"locality"
},
  "geometry": {"coordinates":[21.44165,43.55021],"type":"Point"}
}