{
  "type": "Feature",
  "properties": {
    "gn:admin1_code":"SE",
    "gn:admin2_code":"18",
    "gn:asciiname":"Pilareta",
    "gn:country_code":"RS",
    "gn:dem":654,
    "gn:feature_class":"P",
    "gn:feature_code":"PPLL",
    "gn:name":"Pilareta",
    "gn:population":0,
    "gn:timezone":"Europe/Belgrade",
    "iso:country":"RS",
    "name:fra_x_preferred":[
        "Pilareta"
    ],
    "name:hun_x_preferred":[
        "Pilareta"
    ],
    "name:msa_x_preferred":[
        "Pilareta"
    ],
    "name:nld_x_preferred":[
        "Pilareta"
    ],
    "name:por_x_preferred":[
        "Pilareta"
    ],
    "name:slv_x_preferred":[
        "Pilareta"
    ],
    "name:srp_x_preferred":[
        "Pilareta"
    ],
    "name:srp_x_variant":[
        "\u041f\u0438\u043b\u0430\u0440\u0435\u0442\u0430"
    ],
    "name:und_x_variant":[
        "Pilereta"
    ],
    "wof:name":"Pilareta",
    "wof:placetype":"locality"
},
  "geometry": {"coordinates":[20.52764,43.21586],"type":"Point"}
}