{
  "type": "Feature",
  "properties": {
    "iso:country":"RS",
    "name:eng_x_preferred":[
        "Mirijevo I"
    ],
    "name:srp_cyr_x_preferred":[
        "\u041c\u0438\u0440\u0438\u0458\u0435\u0432\u043e I"
    ],
    "name:srp_lat_x_variant":[
        "Staro Mirijevo"
    ],
    "name:srp_x_preferred":[
        "\u041c\u0438\u0440\u0438\u0458\u0435\u0432\u043e I"
    ],
    "wof:name":"Mirijevo I",
    "wof:placetype":"neighbourhood"
},
  "geometry": {"coordinates":[20.52442001389558,44.79519838174899],"type":"Point"}
}