{
  "type": "Feature",
  "properties": {
    "gn:admin1_code":"SE",
    "gn:admin2_code":"9",
    "gn:asciiname":"Ba",
    "gn:country_code":"RS",
    "gn:dem":317,
    "gn:feature_class":"P",
    "gn:feature_code":"PPL",
    "gn:name":"Ba",
    "gn:population":0,
    "gn:timezone":"Europe/Belgrade",
    "iso:country":"RS",
    "name:srp_x_preferred":[
        "Ba"
    ],
    "wof:name":"Ba",
    "wof:placetype":"locality"
},
  "geometry": {"coordinates":[20.19203,44.15803],"type":"Point"}
}