{
  "type": "Feature",
  "properties": {
    "gn:admin1_code":"SE",
    "gn:admin2_code":"9",
    "gn:asciiname":"Ba",
    "gn:country_code":"RS",
    "gn:dem":317,
    "gn:feature_class":"P",
    "gn:feature_code":"PPL",
    "gn:name":"Ba",
    "gn:population":0,
    "gn:timezone":"Europe/Belgrade",
    "iso:country":"RS",
    "name:ara_x_preferred":[
        "\u0628\u0627"
    ],
    "name:ben_x_preferred":[
        "\u09ac\u09be"
    ],
    "name:deu_x_preferred":[
        "Ba"
    ],
    "name:ell_x_preferred":[
        "\u039c\u03c0\u03b1"
    ],
    "name:fas_x_preferred":[
        "\u0628\u0627"
    ],
    "name:fra_x_preferred":[
        "Bajiang River"
    ],
    "name:heb_x_preferred":[
        "\u05d1\u05d4"
    ],
    "name:hin_x_preferred":[
        "\u092c\u093e"
    ],
    "name:hun_x_preferred":[
        "Ba"
    ],
    "name:ind_x_preferred":[
        "Ba"
    ],
    "name:ita_x_preferred":[
        "Ba"
    ],
    "name:jpn_x_preferred":[
        "\u30d0\u5ddd"
    ],
    "name:kor_x_preferred":[
        "\ubc14"
    ],
    "name:nld_x_preferred":[
        "Ba"
    ],
    "name:pol_x_preferred":[
        "Ba"
    ],
    "name:por_x_preferred":[
        "Ba"
    ],
    "name:rus_x_preferred":[
        "\u0411\u0430"
    ],
    "name:spa_x_preferred":[
        "Ba"
    ],
    "name:srp_x_preferred":[
        "Ba"
    ],
    "name:swe_x_preferred":[
        "Ba"
    ],
    "name:tur_x_preferred":[
        "Ba"
    ],
    "name:ukr_x_preferred":[
        "\u0411\u0430"
    ],
    "name:urd_x_preferred":[
        "\u0628\u0627"
    ],
    "name:vie_x_preferred":[
        "S\u00f4ng Ba"
    ],
    "name:zho_cn_x_preferred":[
        "\u5df4\u6cb3"
    ],
    "name:zho_tw_x_preferred":[
        "\u5df4\u6cb3"
    ],
    "wof:name":"Ba",
    "wof:placetype":"locality"
},
  "geometry": {"coordinates":[20.19203,44.15803],"type":"Point"}
}