{
  "type": "Feature",
  "properties": {
    "gn:admin1_code":"SE",
    "gn:admin2_code":"20",
    "gn:asciiname":"Korman",
    "gn:country_code":"RS",
    "gn:dem":168,
    "gn:feature_class":"P",
    "gn:feature_code":"PPL",
    "gn:name":"Korman",
    "gn:population":0,
    "gn:timezone":"Europe/Belgrade",
    "iso:country":"RS",
    "name:ceb_x_preferred":[
        "Korman"
    ],
    "name:deu_x_preferred":[
        "Korman"
    ],
    "name:fra_x_preferred":[
        "Korman"
    ],
    "name:nds_x_preferred":[
        "Korman"
    ],
    "name:rus_x_preferred":[
        "\u041a\u043e\u0440\u043c\u0430\u043d"
    ],
    "name:slv_x_preferred":[
        "Korman"
    ],
    "name:srp_x_preferred":[
        "Korman"
    ],
    "name:srp_x_variant":[
        "\u041a\u043e\u0440\u043c\u0430\u043d"
    ],
    "name:swe_x_preferred":[
        "Korman"
    ],
    "wof:name":"Korman",
    "wof:placetype":"locality"
},
  "geometry": {"coordinates":[21.60958,43.55088],"type":"Point"}
}