{
  "type": "Feature",
  "properties": {
    "gn:admin1_code":"SE",
    "gn:admin2_code":"18",
    "gn:asciiname":"Donji Gradac",
    "gn:country_code":"RS",
    "gn:dem":598,
    "gn:feature_class":"P",
    "gn:feature_code":"PPL",
    "gn:name":"Donji Gradac",
    "gn:population":0,
    "gn:timezone":"Europe/Belgrade",
    "iso:country":"RS",
    "name:srp_x_preferred":[
        "Donji Gradac"
    ],
    "wof:name":"Donji Gradac",
    "wof:placetype":"locality"
},
  "geometry": {"coordinates":[20.56722,43.36333],"type":"Point"}
}