{
  "type": "Feature",
  "properties": {
    "gn:admin1_code":"SE",
    "gn:admin2_code":"17",
    "gn:asciiname":"Gornja Gorevnica",
    "gn:country_code":"RS",
    "gn:dem":361,
    "gn:feature_class":"P",
    "gn:feature_code":"PPL",
    "gn:name":"Gornja Gorevnica",
    "gn:population":0,
    "gn:timezone":"Europe/Belgrade",
    "iso:country":"RS",
    "name:ceb_x_preferred":[
        "Gornja Gorevnica"
    ],
    "name:fra_x_preferred":[
        "Gornja Gorevnica"
    ],
    "name:msa_x_preferred":[
        "Gornja Gorevnica"
    ],
    "name:por_x_preferred":[
        "Gornja Gorevnica"
    ],
    "name:slv_x_preferred":[
        "Gornja Gorevnica"
    ],
    "name:srp_x_preferred":[
        "Gornja Gorevnica"
    ],
    "name:srp_x_variant":[
        "\u0413\u043e\u0440\u045a\u0430 \u0413\u043e\u0440\u0435\u0432\u043d\u0438\u0446\u0430"
    ],
    "name:und_x_variant":[
        "Gornja Gorijevnica"
    ],
    "wof:name":"Gornja Gorevnica",
    "wof:placetype":"locality"
},
  "geometry": {"coordinates":[20.28869,43.96341],"type":"Point"}
}