{
  "type": "Feature",
  "properties": {
    "gn:admin1_code":"SE",
    "gn:admin2_code":"24",
    "gn:asciiname":"Nazarica",
    "gn:country_code":"RS",
    "gn:dem":1378,
    "gn:feature_class":"P",
    "gn:feature_code":"PPLL",
    "gn:name":"Nazarica",
    "gn:population":0,
    "gn:timezone":"Europe/Belgrade",
    "iso:country":"RS",
    "name:bul_x_preferred":[
        "\u041d\u0430\u0437\u044a\u0440\u0438\u0446\u0430"
    ],
    "name:fra_x_preferred":[
        "Nazarica"
    ],
    "name:msa_x_preferred":[
        "Nazarica"
    ],
    "name:nld_x_preferred":[
        "Nazarica"
    ],
    "name:por_x_preferred":[
        "Nazarica"
    ],
    "name:slv_x_preferred":[
        "Nazarica"
    ],
    "name:srp_x_preferred":[
        "Nazarica"
    ],
    "name:srp_x_variant":[
        "\u041d\u0430\u0437\u0430\u0440\u0438\u0446\u0430"
    ],
    "name:und_x_variant":[
        "Nazorica"
    ],
    "wof:name":"Nazarica",
    "wof:placetype":"locality"
},
  "geometry": {"coordinates":[22.3566,42.40855],"type":"Point"}
}