{
  "type": "Feature",
  "properties": {
    "gn:admin1_code":"SE",
    "gn:admin2_code":"16",
    "gn:asciiname":"Dumljane",
    "gn:country_code":"RS",
    "gn:dem":584,
    "gn:feature_class":"P",
    "gn:feature_code":"PPL",
    "gn:name":"Dumljane",
    "gn:population":0,
    "gn:timezone":"Europe/Belgrade",
    "iso:country":"RS",
    "name:srp_x_preferred":[
        "Dumljane"
    ],
    "name:und_x_variant":[
        "Dum Jani"
    ],
    "wof:name":"Dumljane",
    "wof:placetype":"locality"
},
  "geometry": {"coordinates":[19.63554,43.32115],"type":"Point"}
}