{
  "type": "Feature",
  "properties": {
    "gn:admin1_code":"SE",
    "gn:admin2_code":"22",
    "gn:asciiname":"Babin Kal",
    "gn:country_code":"RS",
    "gn:dem":686,
    "gn:feature_class":"P",
    "gn:feature_code":"PPL",
    "gn:name":"Babin Kal",
    "gn:population":0,
    "gn:timezone":"Europe/Belgrade",
    "iso:country":"RS",
    "name:srp_x_preferred":[
        "Babin Kal"
    ],
    "wof:name":"Babin Kal",
    "wof:placetype":"locality"
},
  "geometry": {"coordinates":[22.37866,43.29391],"type":"Point"}
}