{
  "type": "Feature",
  "properties": {
    "gn:admin1_code":"SE",
    "gn:admin2_code":"15",
    "gn:asciiname":"Resnik",
    "gn:country_code":"RS",
    "gn:dem":372,
    "gn:feature_class":"P",
    "gn:feature_code":"PPL",
    "gn:name":"Resnik",
    "gn:population":0,
    "gn:timezone":"Europe/Belgrade",
    "iso:country":"RS",
    "name:bel_x_preferred":[
        "\u0420\u044d\u0437\u043d\u0456\u043a"
    ],
    "name:bos_x_preferred":[
        "Resnik"
    ],
    "name:ceb_x_preferred":[
        "Resnik"
    ],
    "name:deu_x_preferred":[
        "Resnik"
    ],
    "name:fra_x_preferred":[
        "Resnik"
    ],
    "name:heb_x_preferred":[
        "\u05e8\u05d6\u05e0\u05d9\u05e7"
    ],
    "name:hrv_x_preferred":[
        "Resnik"
    ],
    "name:ita_x_preferred":[
        "Resnik"
    ],
    "name:nld_x_preferred":[
        "Resnik"
    ],
    "name:rus_x_preferred":[
        "\u0420\u0435\u0437\u043d\u0438\u043a"
    ],
    "name:slv_x_preferred":[
        "Resnik"
    ],
    "name:srp_x_preferred":[
        "Resnik"
    ],
    "name:srp_x_variant":[
        "\u0420\u0435\u0441\u043d\u0438\u043a"
    ],
    "name:swe_x_preferred":[
        "Resnik"
    ],
    "name:ukr_x_preferred":[
        "\u0420\u0454\u0437\u043d\u0438\u043a"
    ],
    "wof:name":"Resnik",
    "wof:placetype":"locality"
},
  "geometry": {"coordinates":[21.81547,43.63766],"type":"Point"}
}