{
  "type": "Feature",
  "properties": {
    "gn:admin1_code":"SE",
    "gn:admin2_code":"15",
    "gn:asciiname":"Resnik",
    "gn:country_code":"RS",
    "gn:dem":372,
    "gn:feature_class":"P",
    "gn:feature_code":"PPL",
    "gn:name":"Resnik",
    "gn:population":0,
    "gn:timezone":"Europe/Belgrade",
    "iso:country":"RS",
    "name:srp_x_preferred":[
        "Resnik"
    ],
    "wof:name":"Resnik",
    "wof:placetype":"locality"
},
  "geometry": {"coordinates":[21.81547,43.63766],"type":"Point"}
}