{
  "type": "Feature",
  "properties": {
    "gn:country":"RS",
    "gn:fcode":"PPL",
    "gn:pop":769,
    "iso:country":"RS",
    "name:eng_x_preferred":[
        "Beloljin"
    ],
    "name:fra_x_preferred":[
        "Beloljin"
    ],
    "name:msa_x_preferred":[
        "Beloljin"
    ],
    "name:nld_x_preferred":[
        "Beloljin"
    ],
    "name:por_x_preferred":[
        "Beloljin"
    ],
    "name:slv_x_preferred":[
        "Beloljin"
    ],
    "name:sqi_x_preferred":[
        "Bellolin"
    ],
    "name:sqi_x_variant":[
        "Bullaini"
    ],
    "name:srp_x_preferred":[
        "Beloljin"
    ],
    "name:unk_x_variant":[
        "Belonjin"
    ],
    "qs:name":"Beloljin",
    "qs:photos_9r":0,
    "qs:photos_sr":0,
    "qs:pop_sr":"2",
    "wd:wordcount":69,
    "wof:name":"Beloljin",
    "wof:placetype":"locality",
    "wof:population":769
},
  "geometry": {"coordinates":[21.39673,43.23846],"type":"Point"}
}