{
  "type": "Feature",
  "properties": {
    "gn:admin1_code":"SE",
    "gn:admin2_code":"19",
    "gn:asciiname":"Rokci",
    "gn:country_code":"RS",
    "gn:dem":923,
    "gn:feature_class":"P",
    "gn:feature_code":"PPLL",
    "gn:name":"Rokci",
    "gn:population":0,
    "gn:timezone":"Europe/Belgrade",
    "iso:country":"RS",
    "name:ceb_x_preferred":[
        "Rokci"
    ],
    "name:fra_x_preferred":[
        "Rokci"
    ],
    "name:hye_x_preferred":[
        "\u054c\u0578\u056f\u0581\u056b"
    ],
    "name:msa_x_preferred":[
        "Rokci"
    ],
    "name:por_x_preferred":[
        "Rokci"
    ],
    "name:slv_x_preferred":[
        "Rokci"
    ],
    "name:spa_x_preferred":[
        "Rokci"
    ],
    "name:srp_x_preferred":[
        "Rokci"
    ],
    "name:srp_x_variant":[
        "\u0420\u043e\u043a\u0446\u0438"
    ],
    "wof:name":"Rokci",
    "wof:placetype":"locality"
},
  "geometry": {"coordinates":[20.85924,43.42423],"type":"Point"}
}