{
  "type": "Feature",
  "properties": {
    "gn:admin1_code":"SE",
    "gn:admin2_code":"24",
    "gn:asciiname":"Crni Lug",
    "gn:country_code":"RS",
    "gn:dem":412,
    "gn:feature_class":"P",
    "gn:feature_code":"PPL",
    "gn:name":"Crni Lug",
    "gn:population":0,
    "gn:timezone":"Europe/Belgrade",
    "iso:country":"RS",
    "name:bul_x_preferred":[
        "\u0426\u044a\u0440\u043d\u0438 \u041b\u0443\u0433"
    ],
    "name:ceb_x_preferred":[
        "Crni Lug"
    ],
    "name:fra_x_preferred":[
        "Crni Lug"
    ],
    "name:msa_x_preferred":[
        "Crni Lug"
    ],
    "name:por_x_preferred":[
        "Crni Lug"
    ],
    "name:slv_x_preferred":[
        "Crni Lug"
    ],
    "name:srp_x_preferred":[
        "Crni Lug"
    ],
    "name:srp_x_variant":[
        "\u0426\u0440\u043d\u0438 \u041b\u0443\u0433"
    ],
    "wof:name":"Crni Lug",
    "wof:placetype":"locality"
},
  "geometry": {"coordinates":[21.88353,42.47168],"type":"Point"}
}