{
  "type": "Feature",
  "properties": {
    "gn:admin1_code":"SE",
    "gn:admin2_code":"24",
    "gn:asciiname":"Crni Lug",
    "gn:country_code":"RS",
    "gn:dem":412,
    "gn:feature_class":"P",
    "gn:feature_code":"PPL",
    "gn:name":"Crni Lug",
    "gn:population":0,
    "gn:timezone":"Europe/Belgrade",
    "iso:country":"RS",
    "name:srp_x_preferred":[
        "Crni Lug"
    ],
    "wof:name":"Crni Lug",
    "wof:placetype":"locality"
},
  "geometry": {"coordinates":[21.88353,42.47168],"type":"Point"}
}