{
  "type": "Feature",
  "properties": {
    "gn:admin1_code":"SE",
    "gn:admin2_code":"12",
    "gn:asciiname":"Bosuta",
    "gn:country_code":"RS",
    "gn:dem":306,
    "gn:feature_class":"P",
    "gn:feature_code":"PPL",
    "gn:name":"Bosuta",
    "gn:population":0,
    "gn:timezone":"Europe/Belgrade",
    "iso:country":"RS",
    "name:fra_x_preferred":[
        "Bosuta"
    ],
    "name:msa_x_preferred":[
        "Bosuta"
    ],
    "name:por_x_preferred":[
        "Bosuta"
    ],
    "name:slv_x_preferred":[
        "Bosuta"
    ],
    "name:srp_x_preferred":[
        "Bosuta"
    ],
    "name:srp_x_variant":[
        "\u0411\u043e\u0441\u0443\u0442\u0430"
    ],
    "wof:name":"Bosuta",
    "wof:placetype":"locality"
},
  "geometry": {"coordinates":[20.46676,44.23011],"type":"Point"}
}