{
  "type": "Feature",
  "properties": {
    "gn:country":"RS",
    "gn:fcode":"PPL",
    "gn:pop":2877,
    "iso:country":"RS",
    "name:dut_x_preferred":[
        "Kr\u010dedin"
    ],
    "name:eng_x_preferred":[
        "Kr\u010dedin"
    ],
    "name:epo_x_preferred":[
        "Kr\u0109edin"
    ],
    "name:fre_x_preferred":[
        "Kr\u010dedin"
    ],
    "name:ger_x_preferred":[
        "Kr\u010dedin"
    ],
    "name:hrv_x_preferred":[
        "Kr\u010dedin"
    ],
    "name:hun_x_preferred":[
        "Kereked"
    ],
    "name:jpn_x_preferred":[
        "\u30af\u30eb\u30c1\u30a7\u30c7\u30a3\u30f3"
    ],
    "name:may_x_preferred":[
        "Kr\u010dedin"
    ],
    "name:rus_x_preferred":[
        "\u041a\u0440\u0447\u0435\u0434\u0438\u043d"
    ],
    "name:slv_x_preferred":[
        "Kr\u010dedin"
    ],
    "name:srp_x_preferred":[
        "Kr\u010dedin"
    ],
    "qs:name":"Kr\u010dedin",
    "qs:name_adm0":"Serbia",
    "qs:name_adm1":"Srem",
    "qs:photos":70,
    "qs:photos_1k":14,
    "qs:photos_9k":1,
    "qs:photos_9r":2,
    "qs:photos_all":70,
    "qs:photos_sr":2,
    "qs:placetype":"Town",
    "qs:pop_sr":"4",
    "wd:wordcount":106,
    "wof:name":"Kr\u010dedin",
    "wof:placetype":"locality",
    "wof:population":2877
},
  "geometry": {"coordinates":[20.13308,45.13872],"type":"Point"}
}