{
  "type": "Feature",
  "properties": {
    "gn:admin1_code":"SE",
    "gn:admin2_code":"18",
    "gn:asciiname":"Luznjani",
    "gn:country_code":"RS",
    "gn:dem":674,
    "gn:feature_class":"P",
    "gn:feature_code":"PPL",
    "gn:name":"Lu\u017enjani",
    "gn:population":0,
    "gn:timezone":"Europe/Belgrade",
    "iso:country":"RS",
    "name:srp_x_preferred":[
        "Lu\u017enjani"
    ],
    "wof:name":"Luznjani",
    "wof:placetype":"locality"
},
  "geometry": {"coordinates":[20.75934,43.38261],"type":"Point"}
}