{
  "type": "Feature",
  "properties": {
    "gn:admin1_code":"SE",
    "gn:admin2_code":"8",
    "gn:asciiname":"Prekorecka Mala",
    "gn:country_code":"RS",
    "gn:dem":291,
    "gn:feature_class":"P",
    "gn:feature_code":"PPL",
    "gn:name":"Prekore\u010dka Mala",
    "gn:population":0,
    "gn:timezone":"Europe/Belgrade",
    "iso:country":"RS",
    "name:srp_x_preferred":[
        "Prekore\u010dka Mala"
    ],
    "wof:name":"Prekorecka Mala",
    "wof:placetype":"locality"
},
  "geometry": {"coordinates":[19.30839,44.46856],"type":"Point"}
}