{
  "type": "Feature",
  "properties": {
    "gn:admin1_code":"SE",
    "gn:admin2_code":"8",
    "gn:asciiname":"Mojkovic",
    "gn:country_code":"RS",
    "gn:dem":170,
    "gn:feature_class":"P",
    "gn:feature_code":"PPLL",
    "gn:name":"Mojkovi\u0107",
    "gn:population":0,
    "gn:timezone":"Europe/Belgrade",
    "iso:country":"RS",
    "name:srp_x_preferred":[
        "Mojkovi\u0107"
    ],
    "wof:name":"Mojkovic",
    "wof:placetype":"locality"
},
  "geometry": {"coordinates":[19.47925,44.43078],"type":"Point"}
}