{
  "type": "Feature",
  "properties": {
    "gn:admin1_code":"SE",
    "gn:admin2_code":"24",
    "gn:asciiname":"Vladovce",
    "gn:country_code":"RS",
    "gn:dem":659,
    "gn:feature_class":"P",
    "gn:feature_code":"PPLL",
    "gn:name":"Vladovce",
    "gn:population":0,
    "gn:timezone":"Europe/Belgrade",
    "iso:country":"RS",
    "wof:name":"Vladovce",
    "wof:placetype":"locality"
},
  "geometry": {"coordinates":[21.96276,42.38622],"type":"Point"}
}