{
  "type": "Feature",
  "properties": {
    "gn:admin1_code":"SE",
    "gn:admin2_code":"24",
    "gn:asciiname":"Vladovce",
    "gn:country_code":"RS",
    "gn:dem":659,
    "gn:feature_class":"P",
    "gn:feature_code":"PPLL",
    "gn:name":"Vladovce",
    "gn:population":0,
    "gn:timezone":"Europe/Belgrade",
    "iso:country":"RS",
    "name:bul_x_preferred":[
        "\u0412\u043b\u0430\u0434\u043e\u0432\u0446\u0435"
    ],
    "name:fra_x_preferred":[
        "Vladovce"
    ],
    "name:msa_x_preferred":[
        "Vladovce"
    ],
    "name:por_x_preferred":[
        "Vladovce"
    ],
    "name:slv_x_preferred":[
        "Vladovce"
    ],
    "name:srp_x_preferred":[
        "\u0412\u043b\u0430\u0434\u043e\u0432\u0446\u0435"
    ],
    "wof:name":"Vladovce",
    "wof:placetype":"locality"
},
  "geometry": {"coordinates":[21.96276,42.38622],"type":"Point"}
}