{
  "type": "Feature",
  "properties": {
    "gn:admin1_code":"SE",
    "gn:admin2_code":"24",
    "gn:asciiname":"Korbska Maala",
    "gn:country_code":"RS",
    "gn:dem":470,
    "gn:feature_class":"P",
    "gn:feature_code":"PPL",
    "gn:name":"Korbska Maala",
    "gn:population":0,
    "gn:timezone":"Europe/Belgrade",
    "iso:country":"RS",
    "name:sqi_x_preferred":[
        "Lagja Korbajve"
    ],
    "name:srp_x_preferred":[
        "Korbska Maala"
    ],
    "wof:name":"Korbska Maala",
    "wof:placetype":"locality"
},
  "geometry": {"coordinates":[21.74352,42.38674],"type":"Point"}
}