{
  "type": "Feature",
  "properties": {
    "gn:admin1_code":"SE",
    "gn:admin2_code":"16",
    "gn:asciiname":"Brezovac",
    "gn:country_code":"RS",
    "gn:dem":1064,
    "gn:feature_class":"P",
    "gn:feature_code":"PPL",
    "gn:name":"Brezovac",
    "gn:population":0,
    "gn:timezone":"Europe/Belgrade",
    "iso:country":"RS",
    "name:bos_x_preferred":[
        "Brezovac"
    ],
    "name:ceb_x_preferred":[
        "Brezovac"
    ],
    "name:fra_x_preferred":[
        "Brezovac"
    ],
    "name:hrv_x_preferred":[
        "Brezovac"
    ],
    "name:hun_x_preferred":[
        "Brezovac"
    ],
    "name:nld_x_preferred":[
        "Brezovac"
    ],
    "name:slv_x_preferred":[
        "Brezovac"
    ],
    "name:srp_x_preferred":[
        "Brezovac"
    ],
    "name:srp_x_variant":[
        "\u0411\u0440\u0435\u0437\u043e\u0432\u0430\u0446"
    ],
    "name:swe_x_preferred":[
        "Brezovac"
    ],
    "wof:name":"Brezovac",
    "wof:placetype":"locality"
},
  "geometry": {"coordinates":[19.52958,43.68293],"type":"Point"}
}