{
  "type": "Feature",
  "properties": {
    "gn:country":"RS",
    "gn:fcode":"PPL",
    "gn:pop":4,
    "iso:country":"RS",
    "name:ceb_x_preferred":[
        "Ratina"
    ],
    "name:eng_x_preferred":[
        "Ratina"
    ],
    "name:fra_x_preferred":[
        "Ratina"
    ],
    "name:hun_x_preferred":[
        "Ratina"
    ],
    "name:msa_x_preferred":[
        "Ratina"
    ],
    "name:nld_x_preferred":[
        "Ratina"
    ],
    "name:por_x_preferred":[
        "Ratina"
    ],
    "name:slv_x_preferred":[
        "Ratina"
    ],
    "name:srp_x_preferred":[
        "Ratina"
    ],
    "name:srp_x_variant":[
        "\u0420\u0430\u0442\u0438\u043d\u0430"
    ],
    "qs:name":"Ratina",
    "qs:photos_9r":0,
    "qs:photos_sr":0,
    "qs:pop_sr":"1",
    "wd:wordcount":44,
    "wof:name":"Ratina",
    "wof:placetype":"locality",
    "wof:population":4
},
  "geometry": {"coordinates":[20.75157,43.70144],"type":"Point"}
}