{
  "type": "Feature",
  "properties": {
    "gn:admin1_code":"SE",
    "gn:admin2_code":"19",
    "gn:asciiname":"Majdevo",
    "gn:country_code":"RS",
    "gn:dem":251,
    "gn:feature_class":"P",
    "gn:feature_code":"PPL",
    "gn:name":"Majdevo",
    "gn:population":0,
    "gn:timezone":"Europe/Belgrade",
    "iso:country":"RS",
    "name:ceb_x_preferred":[
        "Majdevo"
    ],
    "name:deu_x_preferred":[
        "Majdevo"
    ],
    "name:fra_x_preferred":[
        "Majdevo"
    ],
    "name:msa_x_preferred":[
        "Majdevo"
    ],
    "name:por_x_preferred":[
        "Majdevo"
    ],
    "name:slv_x_preferred":[
        "Majdevo"
    ],
    "name:srp_x_preferred":[
        "Majdevo"
    ],
    "name:srp_x_variant":[
        "\u041c\u0430\u0458\u0434\u0435\u0432\u043e"
    ],
    "wof:name":"Majdevo",
    "wof:placetype":"locality"
},
  "geometry": {"coordinates":[21.20797,43.43567],"type":"Point"}
}