{
  "type": "Feature",
  "properties": {
    "gn:admin1_code":"SE",
    "gn:admin2_code":"11",
    "gn:asciiname":"Kucajna",
    "gn:country_code":"RS",
    "gn:dem":189,
    "gn:feature_class":"P",
    "gn:feature_code":"PPL",
    "gn:name":"Ku\u010dajna",
    "gn:population":0,
    "gn:timezone":"Europe/Belgrade",
    "iso:country":"RS",
    "name:ceb_x_preferred":[
        "Ku\u010dajna"
    ],
    "name:fra_x_preferred":[
        "Ku\u010dajna"
    ],
    "name:msa_x_preferred":[
        "Ku\u010dajna"
    ],
    "name:por_x_preferred":[
        "Ku\u010dajna"
    ],
    "name:slv_x_preferred":[
        "Ku\u010dajna"
    ],
    "name:srp_x_preferred":[
        "Ku\u010dajna"
    ],
    "name:srp_x_variant":[
        "\u041a\u0443\u0447\u0430\u0458\u043d\u0430"
    ],
    "wof:name":"Kucajna",
    "wof:placetype":"locality"
},
  "geometry": {"coordinates":[21.65252000000001,44.44865],"type":"Point"}
}