{
  "type": "Feature",
  "properties": {
    "gn:admin1_code":"SE",
    "gn:admin2_code":"16",
    "gn:asciiname":"Panici",
    "gn:country_code":"RS",
    "gn:dem":738,
    "gn:feature_class":"P",
    "gn:feature_code":"PPL",
    "gn:name":"Pani\u0107i",
    "gn:population":0,
    "gn:timezone":"Europe/Belgrade",
    "iso:country":"RS",
    "name:srp_x_preferred":[
        "Pani\u0107i"
    ],
    "wof:name":"Panici",
    "wof:placetype":"locality"
},
  "geometry": {"coordinates":[19.79111,43.86222],"type":"Point"}
}