{
  "type": "Feature",
  "properties": {
    "gn:admin1_code":"SE",
    "gn:admin2_code":"16",
    "gn:asciiname":"Srednje Selo",
    "gn:country_code":"RS",
    "gn:dem":534,
    "gn:feature_class":"P",
    "gn:feature_code":"PPL",
    "gn:name":"Srednje Selo",
    "gn:population":0,
    "gn:timezone":"Europe/Belgrade",
    "iso:country":"RS",
    "name:bos_x_preferred":[
        "Srednje Selo"
    ],
    "name:ceb_x_preferred":[
        "Srednje Selo"
    ],
    "name:hrv_x_preferred":[
        "Srednje Selo"
    ],
    "name:nld_x_preferred":[
        "Srednje Selo"
    ],
    "name:slv_x_preferred":[
        "Srednje Selo"
    ],
    "name:spa_x_preferred":[
        "Srednje Selo"
    ],
    "name:srp_x_preferred":[
        "\u0421\u0440\u0435\u0434\u045a\u0435 \u0421\u0435\u043b\u043e"
    ],
    "name:swe_x_preferred":[
        "Srednje Selo"
    ],
    "name:ukr_x_preferred":[
        "\u0421\u0440\u0435\u0434\u043d\u0454 \u0421\u0435\u043b\u043e"
    ],
    "wof:name":"Srednje Selo",
    "wof:placetype":"locality"
},
  "geometry": {"coordinates":[19.9625,43.92972],"type":"Point"}
}