{
  "type": "Feature",
  "properties": {
    "gn:admin1_code":"SE",
    "gn:admin2_code":"17",
    "gn:asciiname":"Jancici",
    "gn:country_code":"RS",
    "gn:dem":678,
    "gn:feature_class":"P",
    "gn:feature_code":"PPLL",
    "gn:name":"Jan\u010di\u0107i",
    "gn:population":0,
    "gn:timezone":"Europe/Belgrade",
    "iso:country":"RS",
    "name:ceb_x_preferred":[
        "Jan\u010di\u0107i"
    ],
    "name:fra_x_preferred":[
        "Jan\u010di\u0107i"
    ],
    "name:msa_x_preferred":[
        "Jan\u010di\u0107i"
    ],
    "name:por_x_preferred":[
        "Jan\u010di\u0107i"
    ],
    "name:slv_x_preferred":[
        "Jan\u010di\u0107i"
    ],
    "name:srp_x_preferred":[
        "Jan\u010di\u0107i"
    ],
    "name:srp_x_variant":[
        "\u0408\u0430\u043d\u0447\u0438\u045b\u0438"
    ],
    "name:urd_x_preferred":[
        "\u062c\u0646\u0686\u0627\u0633\u0627"
    ],
    "wof:name":"Jancici",
    "wof:placetype":"locality"
},
  "geometry": {"coordinates":[20.14861,43.95847],"type":"Point"}
}