{
  "type": "Feature",
  "properties": {
    "gn:admin1_code":"SE",
    "gn:admin2_code":"23",
    "gn:asciiname":"Kastavar",
    "gn:country_code":"RS",
    "gn:dem":252,
    "gn:feature_class":"P",
    "gn:feature_code":"PPL",
    "gn:name":"Ka\u0161tavar",
    "gn:population":0,
    "gn:timezone":"Europe/Belgrade",
    "iso:country":"RS",
    "name:srp_x_preferred":[
        "Ka\u0161tavar"
    ],
    "wof:name":"Kastavar",
    "wof:placetype":"locality"
},
  "geometry": {"coordinates":[21.89972,43.07333],"type":"Point"}
}