{
  "type": "Feature",
  "properties": {
    "gn:admin1_code":"SE",
    "gn:admin2_code":"23",
    "gn:asciiname":"Kastavar",
    "gn:country_code":"RS",
    "gn:dem":252,
    "gn:feature_class":"P",
    "gn:feature_code":"PPL",
    "gn:name":"Ka\u0161tavar",
    "gn:population":0,
    "gn:timezone":"Europe/Belgrade",
    "iso:country":"RS",
    "name:fra_x_preferred":[
        "Ka\u0161tavar"
    ],
    "name:msa_x_preferred":[
        "Ka\u0161tavar"
    ],
    "name:por_x_preferred":[
        "Ka\u0161tavar"
    ],
    "name:slv_x_preferred":[
        "Ka\u0161tavar"
    ],
    "name:srp_x_preferred":[
        "Ka\u0161tavar"
    ],
    "name:srp_x_variant":[
        "\u041a\u0430\u0448\u0442\u0430\u0432\u0430\u0440"
    ],
    "wof:name":"Kastavar",
    "wof:placetype":"locality"
},
  "geometry": {"coordinates":[21.89972,43.07333],"type":"Point"}
}