{
  "type": "Feature",
  "properties": {
    "gn:admin1_code":"SE",
    "gn:admin2_code":"8",
    "gn:asciiname":"Orid",
    "gn:country_code":"RS",
    "gn:dem":74,
    "gn:feature_class":"P",
    "gn:feature_code":"PPL",
    "gn:name":"Orid",
    "gn:population":0,
    "gn:timezone":"Europe/Belgrade",
    "iso:country":"RS",
    "name:srp_x_preferred":[
        "Orid"
    ],
    "wof:name":"Orid",
    "wof:placetype":"locality"
},
  "geometry": {"coordinates":[19.79975,44.71026],"type":"Point"}
}