{
  "type": "Feature",
  "properties": {
    "gn:admin1_code":"SE",
    "gn:admin2_code":"8",
    "gn:asciiname":"Pantici",
    "gn:country_code":"RS",
    "gn:dem":409,
    "gn:feature_class":"P",
    "gn:feature_code":"PPL",
    "gn:name":"Panti\u0107i",
    "gn:population":0,
    "gn:timezone":"Europe/Belgrade",
    "iso:country":"RS",
    "name:srp_x_preferred":[
        "Panti\u0107i"
    ],
    "wof:name":"Pantici",
    "wof:placetype":"locality"
},
  "geometry": {"coordinates":[19.33858,44.44332],"type":"Point"}
}