{
  "type": "Feature",
  "properties": {
    "gn:admin1_code":"SE",
    "gn:admin2_code":"16",
    "gn:asciiname":"Puzovici",
    "gn:country_code":"RS",
    "gn:dem":819,
    "gn:feature_class":"P",
    "gn:feature_code":"PPL",
    "gn:name":"Puzovi\u0107i",
    "gn:population":0,
    "gn:timezone":"Europe/Belgrade",
    "iso:country":"RS",
    "wof:name":"Puzovici",
    "wof:placetype":"locality"
},
  "geometry": {"coordinates":[19.66639,43.36111],"type":"Point"}
}