{
  "type": "Feature",
  "properties": {
    "gn:admin1_code":"SE",
    "gn:admin2_code":"16",
    "gn:asciiname":"Kacer",
    "gn:country_code":"RS",
    "gn:dem":654,
    "gn:feature_class":"P",
    "gn:feature_code":"PPL",
    "gn:name":"Ka\u010der",
    "gn:population":0,
    "gn:timezone":"Europe/Belgrade",
    "iso:country":"RS",
    "name:ceb_x_preferred":[
        "Ka\u010der"
    ],
    "name:fra_x_preferred":[
        "Ka\u010der"
    ],
    "name:msa_x_preferred":[
        "Ka\u010der"
    ],
    "name:nld_x_preferred":[
        "Ka\u010der"
    ],
    "name:por_x_preferred":[
        "Ka\u010der"
    ],
    "name:slv_x_preferred":[
        "Ka\u010der"
    ],
    "name:srp_x_preferred":[
        "Ka\u010der"
    ],
    "name:srp_x_variant":[
        "\u041a\u0430\u0447\u0435\u0440"
    ],
    "wof:name":"Kacer",
    "wof:placetype":"locality"
},
  "geometry": {"coordinates":[19.74654,43.81528],"type":"Point"}
}