{
  "type": "Feature",
  "properties": {
    "iso:country":"RS",
    "name:eng_x_preferred":[
        "Profesorska Kolonija"
    ],
    "name:srp_cyr_x_preferred":[
        "\u041f\u0440\u043e\u0444\u0435\u0441\u043e\u0440\u0441\u043a\u0430 \u043a\u043e\u043b\u043e\u043d\u0438\u0458\u0430"
    ],
    "name:srp_lat_x_variant":[
        "Jovan Cviji\u0107"
    ],
    "name:srp_x_preferred":[
        "\u041f\u0440\u043e\u0444\u0435\u0441\u043e\u0440\u0441\u043a\u0430 \u043a\u043e\u043b\u043e\u043d\u0438\u0458\u0430"
    ],
    "wof:name":"Profesorska Kolonija",
    "wof:placetype":"neighbourhood"
},
  "geometry": {"coordinates":[20.47994679728713,44.81458177047459],"type":"Point"}
}