{
  "type": "Feature",
  "properties": {
    "gn:admin1_code":"VO",
    "gn:admin2_code":"2",
    "gn:asciiname":"Zlatica",
    "gn:country_code":"RS",
    "gn:dem":77,
    "gn:feature_class":"P",
    "gn:feature_code":"PPL",
    "gn:name":"Zlatica",
    "gn:population":0,
    "gn:timezone":"Europe/Belgrade",
    "iso:country":"RS",
    "name:srp_x_preferred":[
        "Zlatica"
    ],
    "name:und_x_variant":[
        "Bremova Odaja"
    ],
    "wof:name":"Zlatica",
    "wof:placetype":"locality"
},
  "geometry": {"coordinates":[20.58272,45.3862],"type":"Point"}
}