{
  "type": "Feature",
  "properties": {
    "gn:admin1_code":"SE",
    "gn:admin2_code":"8",
    "gn:asciiname":"Nenadovici",
    "gn:country_code":"RS",
    "gn:dem":345,
    "gn:feature_class":"P",
    "gn:feature_code":"PPL",
    "gn:name":"Nenadovi\u0107i",
    "gn:population":0,
    "gn:timezone":"Europe/Belgrade",
    "iso:country":"RS",
    "name:srp_x_preferred":[
        "Nenadovi\u0107i"
    ],
    "wof:name":"Nenadovici",
    "wof:placetype":"locality"
},
  "geometry": {"coordinates":[19.43615,44.41036],"type":"Point"}
}