{
  "type": "Feature",
  "properties": {
    "gn:admin1_code":"SE",
    "gn:admin2_code":"8",
    "gn:asciiname":"Vasilici",
    "gn:country_code":"RS",
    "gn:dem":269,
    "gn:feature_class":"P",
    "gn:feature_code":"PPL",
    "gn:name":"Vasili\u0107i",
    "gn:population":0,
    "gn:timezone":"Europe/Belgrade",
    "iso:country":"RS",
    "name:srp_x_preferred":[
        "Vasili\u0107i"
    ],
    "wof:name":"Vasilici",
    "wof:placetype":"locality"
},
  "geometry": {"coordinates":[19.43323,44.46262],"type":"Point"}
}