{
  "type": "Feature",
  "properties": {
    "gn:admin1_code":"SE",
    "gn:admin2_code":"18",
    "gn:asciiname":"Gornja Bekova",
    "gn:country_code":"RS",
    "gn:dem":1016,
    "gn:feature_class":"P",
    "gn:feature_code":"PPL",
    "gn:name":"Gornja Bekova",
    "gn:population":0,
    "gn:timezone":"Europe/Belgrade",
    "iso:country":"RS",
    "name:srp_x_preferred":[
        "Gornja Bekova"
    ],
    "wof:name":"Gornja Bekova",
    "wof:placetype":"locality"
},
  "geometry": {"coordinates":[20.47361,43.27167],"type":"Point"}
}