{
  "type": "Feature",
  "properties": {
    "gn:admin1_code":"SE",
    "gn:admin2_code":"15",
    "gn:asciiname":"Vrmdza",
    "gn:country_code":"RS",
    "gn:dem":468,
    "gn:feature_class":"P",
    "gn:feature_code":"PPL",
    "gn:name":"Vrmd\u017ea",
    "gn:population":0,
    "gn:timezone":"Europe/Belgrade",
    "iso:country":"RS",
    "name:srp_x_preferred":[
        "Vrmd\u017ea"
    ],
    "wof:name":"Vrmdza",
    "wof:placetype":"locality"
},
  "geometry": {"coordinates":[21.81856,43.71372],"type":"Point"}
}