{
  "type": "Feature",
  "properties": {
    "gn:admin1_code":"SE",
    "gn:admin2_code":"24",
    "gn:asciiname":"Stankovci",
    "gn:country_code":"RS",
    "gn:dem":1279,
    "gn:feature_class":"P",
    "gn:feature_code":"PPL",
    "gn:name":"Stankovci",
    "gn:population":0,
    "gn:timezone":"Europe/Belgrade",
    "iso:country":"RS",
    "name:bos_x_preferred":[
        "Stankovci"
    ],
    "name:ces_x_preferred":[
        "Stankovci"
    ],
    "name:deu_x_preferred":[
        "Stankovci"
    ],
    "name:fra_x_preferred":[
        "Stankovci"
    ],
    "name:hrv_x_preferred":[
        "Stankovci"
    ],
    "name:hun_x_preferred":[
        "Stankovci"
    ],
    "name:ita_x_preferred":[
        "Stancovazzo"
    ],
    "name:nld_x_preferred":[
        "Stankovci"
    ],
    "name:pol_x_preferred":[
        "Gmina Stankovci"
    ],
    "name:por_x_preferred":[
        "Stankovci"
    ],
    "name:ron_x_preferred":[
        "Comuna Stankovci"
    ],
    "name:slv_x_preferred":[
        "Stankovci"
    ],
    "name:srp_x_preferred":[
        "\u0421\u0442\u0430\u043d\u043a\u043e\u0432\u0446\u0438"
    ],
    "name:ukr_x_preferred":[
        "\u0421\u0442\u0430\u043d\u043a\u043e\u0432\u0446\u0456"
    ],
    "name:war_x_preferred":[
        "Stankovci"
    ],
    "wof:name":"Stankovci",
    "wof:placetype":"locality"
},
  "geometry": {"coordinates":[22.36078,42.69233],"type":"Point"}
}