{
  "type": "Feature",
  "properties": {
    "gn:admin1_code":"SE",
    "gn:admin2_code":"15",
    "gn:asciiname":"Kandalica",
    "gn:country_code":"RS",
    "gn:dem":391,
    "gn:feature_class":"P",
    "gn:feature_code":"PPL",
    "gn:name":"Kandalica",
    "gn:population":0,
    "gn:timezone":"Europe/Belgrade",
    "iso:country":"RS",
    "name:fra_x_preferred":[
        "Kandalica"
    ],
    "name:msa_x_preferred":[
        "Kandalica"
    ],
    "name:por_x_preferred":[
        "Kandalica"
    ],
    "name:slv_x_preferred":[
        "Kandalica"
    ],
    "name:srp_x_preferred":[
        "Kandalica"
    ],
    "name:srp_x_variant":[
        "\u041a\u0430\u043d\u0434\u0430\u043b\u0438\u0446\u0430"
    ],
    "wof:name":"Kandalica",
    "wof:placetype":"locality"
},
  "geometry": {"coordinates":[22.33215,43.54082],"type":"Point"}
}