{
  "type": "Feature",
  "properties": {
    "gn:admin1_code":"SE",
    "gn:admin2_code":"16",
    "gn:asciiname":"Kolari",
    "gn:country_code":"RS",
    "gn:dem":439,
    "gn:feature_class":"P",
    "gn:feature_code":"PPL",
    "gn:name":"Kolari",
    "gn:population":0,
    "gn:timezone":"Europe/Belgrade",
    "iso:country":"RS",
    "name:bak_x_preferred":[
        "\u041a\u043e\u043b\u0430\u0440\u0438"
    ],
    "name:ceb_x_preferred":[
        "Kolari"
    ],
    "name:ces_x_preferred":[
        "Kolari"
    ],
    "name:deu_x_preferred":[
        "Kolari"
    ],
    "name:epo_x_preferred":[
        "Kolari"
    ],
    "name:est_x_preferred":[
        "Kolari vald"
    ],
    "name:eus_x_preferred":[
        "Kolari"
    ],
    "name:fin_x_preferred":[
        "Kolari"
    ],
    "name:fra_x_preferred":[
        "Kolari"
    ],
    "name:glg_x_preferred":[
        "Kolari"
    ],
    "name:hun_x_preferred":[
        "Kolari"
    ],
    "name:ita_x_preferred":[
        "Kolari"
    ],
    "name:lat_x_preferred":[
        "Kolari"
    ],
    "name:nld_x_preferred":[
        "Kolari"
    ],
    "name:nor_x_preferred":[
        "Kolari"
    ],
    "name:pol_x_preferred":[
        "Kolari"
    ],
    "name:ron_x_preferred":[
        "Kolari"
    ],
    "name:rus_x_preferred":[
        "\u041a\u043e\u043b\u0430\u0440\u0438"
    ],
    "name:sme_x_preferred":[
        "Kolari"
    ],
    "name:spa_x_preferred":[
        "Kolari"
    ],
    "name:sqi_x_preferred":[
        "Kolari"
    ],
    "name:srp_x_preferred":[
        "Kolari"
    ],
    "name:swe_x_preferred":[
        "Kolari kommun"
    ],
    "name:tur_x_preferred":[
        "Kolari"
    ],
    "name:vie_x_preferred":[
        "Kolari"
    ],
    "name:zho_x_preferred":[
        "\u79d1\u62c9\u91cc"
    ],
    "wof:name":"Kolari",
    "wof:placetype":"locality"
},
  "geometry": {"coordinates":[19.57724,43.94736],"type":"Point"}
}