{
  "type": "Feature",
  "properties": {
    "gn:admin1_code":"SE",
    "gn:admin2_code":"16",
    "gn:asciiname":"Kolari",
    "gn:country_code":"RS",
    "gn:dem":439,
    "gn:feature_class":"P",
    "gn:feature_code":"PPL",
    "gn:name":"Kolari",
    "gn:population":0,
    "gn:timezone":"Europe/Belgrade",
    "iso:country":"RS",
    "name:srp_x_preferred":[
        "Kolari"
    ],
    "wof:name":"Kolari",
    "wof:placetype":"locality"
},
  "geometry": {"coordinates":[19.57724,43.94736],"type":"Point"}
}