{
  "type": "Feature",
  "properties": {
    "gn:admin1_code":"SE",
    "gn:admin2_code":"16",
    "gn:asciiname":"Ducevci",
    "gn:country_code":"RS",
    "gn:dem":738,
    "gn:feature_class":"P",
    "gn:feature_code":"PPL",
    "gn:name":"Du\u010devci",
    "gn:population":0,
    "gn:timezone":"Europe/Belgrade",
    "iso:country":"RS",
    "wof:name":"Ducevci",
    "wof:placetype":"locality"
},
  "geometry": {"coordinates":[19.83,43.78944],"type":"Point"}
}