{
  "type": "Feature",
  "properties": {
    "gn:admin1_code":"SE",
    "gn:admin2_code":"21",
    "gn:asciiname":"Galibare",
    "gn:country_code":"RS",
    "gn:dem":567,
    "gn:feature_class":"P",
    "gn:feature_code":"PPL",
    "gn:name":"Galibare",
    "gn:population":0,
    "gn:timezone":"Europe/Belgrade",
    "iso:country":"RS",
    "name:srp_x_preferred":[
        "Galibare"
    ],
    "wof:name":"Galibare",
    "wof:placetype":"locality"
},
  "geometry": {"coordinates":[21.40171,43.12453],"type":"Point"}
}