{
  "type": "Feature",
  "properties": {
    "gn:admin1_code":"SE",
    "gn:admin2_code":"8",
    "gn:asciiname":"Tomanici",
    "gn:country_code":"RS",
    "gn:dem":231,
    "gn:feature_class":"P",
    "gn:feature_code":"PPL",
    "gn:name":"Tomani\u0107i",
    "gn:population":0,
    "gn:timezone":"Europe/Belgrade",
    "iso:country":"RS",
    "name:srp_x_preferred":[
        "Tomani\u0107i"
    ],
    "wof:name":"Tomanici",
    "wof:placetype":"locality"
},
  "geometry": {"coordinates":[19.30167,44.50778],"type":"Point"}
}