{
  "type": "Feature",
  "properties": {
    "gn:admin1_code":"SE",
    "gn:admin2_code":"19",
    "gn:asciiname":"Braljina",
    "gn:country_code":"RS",
    "gn:dem":146,
    "gn:feature_class":"P",
    "gn:feature_code":"PPL",
    "gn:name":"Braljina",
    "gn:population":0,
    "gn:timezone":"Europe/Belgrade",
    "iso:country":"RS",
    "name:srp_x_preferred":[
        "Braljina"
    ],
    "wof:name":"Braljina",
    "wof:placetype":"locality"
},
  "geometry": {"coordinates":[21.46664,43.65384],"type":"Point"}
}