{
  "type": "Feature",
  "properties": {
    "gn:admin1_code":"VO",
    "gn:admin2_code":"5",
    "gn:asciiname":"Magarsko Selo",
    "gn:country_code":"RS",
    "gn:dem":119,
    "gn:feature_class":"P",
    "gn:feature_code":"PPL",
    "gn:name":"Ma\u0111arsko Selo",
    "gn:population":0,
    "gn:timezone":"Europe/Belgrade",
    "iso:country":"RS",
    "name:srp_x_preferred":[
        "Ma\u0111arsko Selo"
    ],
    "wof:name":"Magarsko Selo",
    "wof:placetype":"locality"
},
  "geometry": {"coordinates":[19.31472,45.9425],"type":"Point"}
}