{
  "type": "Feature",
  "properties": {
    "gn:admin1_code":"SE",
    "gn:admin2_code":"11",
    "gn:asciiname":"Dorgevici",
    "gn:country_code":"RS",
    "gn:dem":122,
    "gn:feature_class":"P",
    "gn:feature_code":"PPL",
    "gn:name":"\u00d0or\u0111evi\u0107i",
    "gn:population":0,
    "gn:timezone":"Europe/Belgrade",
    "iso:country":"RS",
    "wof:name":"Dorgevici",
    "wof:placetype":"locality"
},
  "geometry": {"coordinates":[21.33963,44.47394],"type":"Point"}
}