{
  "type": "Feature",
  "properties": {
    "gn:admin1_code":"SE",
    "gn:admin2_code":"16",
    "gn:asciiname":"Tupaje",
    "gn:country_code":"RS",
    "gn:dem":885,
    "gn:feature_class":"P",
    "gn:feature_code":"PPL",
    "gn:name":"Tupaje",
    "gn:population":0,
    "gn:timezone":"Europe/Belgrade",
    "iso:country":"RS",
    "wof:name":"Tupaje",
    "wof:placetype":"locality"
},
  "geometry": {"coordinates":[19.72935,43.86877],"type":"Point"}
}