{
  "type": "Feature",
  "properties": {
    "gn:admin1_code":"SE",
    "gn:admin2_code":"19",
    "gn:asciiname":"Orasje",
    "gn:country_code":"RS",
    "gn:dem":179,
    "gn:feature_class":"P",
    "gn:feature_code":"PPL",
    "gn:name":"Ora\u0161je",
    "gn:population":0,
    "gn:timezone":"Europe/Belgrade",
    "iso:country":"RS",
    "name:srp_x_preferred":[
        "Ora\u0161je"
    ],
    "wof:name":"Orasje",
    "wof:placetype":"locality"
},
  "geometry": {"coordinates":[21.2695,43.74288],"type":"Point"}
}