{
  "type": "Feature",
  "properties": {
    "gn:admin1_code":"SE",
    "gn:admin2_code":"8",
    "gn:asciiname":"Runjani",
    "gn:country_code":"RS",
    "gn:dem":113,
    "gn:feature_class":"P",
    "gn:feature_code":"PPLL",
    "gn:name":"Runjani",
    "gn:population":0,
    "gn:timezone":"Europe/Belgrade",
    "iso:country":"RS",
    "name:srp_x_preferred":[
        "Runjani"
    ],
    "wof:name":"Runjani",
    "wof:placetype":"locality"
},
  "geometry": {"coordinates":[19.25791,44.563],"type":"Point"}
}