{
  "type": "Feature",
  "properties": {
    "gn:admin1_code":"SE",
    "gn:admin2_code":"18",
    "gn:asciiname":"Radosice",
    "gn:country_code":"RS",
    "gn:dem":703,
    "gn:feature_class":"P",
    "gn:feature_code":"PPLL",
    "gn:name":"Rado\u0161i\u0107e",
    "gn:population":0,
    "gn:timezone":"Europe/Belgrade",
    "iso:country":"RS",
    "name:srp_x_preferred":[
        "Rado\u0161i\u0107e"
    ],
    "name:und_x_variant":[
        "Rade"
    ],
    "wof:name":"Radosice",
    "wof:placetype":"locality"
},
  "geometry": {"coordinates":[20.67268,43.30232],"type":"Point"}
}