{
  "type": "Feature",
  "properties": {
    "gn:admin1_code":"SE",
    "gn:admin2_code":"12",
    "gn:asciiname":"Mali Senj",
    "gn:country_code":"RS",
    "gn:dem":308,
    "gn:feature_class":"P",
    "gn:feature_code":"PPL",
    "gn:name":"Mali \u0160enj",
    "gn:population":0,
    "gn:timezone":"Europe/Belgrade",
    "iso:country":"RS",
    "name:fra_x_preferred":[
        "Mali \u0160enj"
    ],
    "name:msa_x_preferred":[
        "Mali \u0160enj"
    ],
    "name:por_x_preferred":[
        "Mali \u0160enj"
    ],
    "name:slv_x_preferred":[
        "Mali \u0160enj"
    ],
    "name:srp_x_preferred":[
        "Mali \u0160enj"
    ],
    "name:srp_x_variant":[
        "\u041c\u0430\u043b\u0438 \u0428\u0435\u045a"
    ],
    "wof:name":"Mali Senj",
    "wof:placetype":"locality"
},
  "geometry": {"coordinates":[20.78662000000001,44.10705],"type":"Point"}
}