{
  "type": "Feature",
  "properties": {
    "gn:admin1_code":"SE",
    "gn:admin2_code":"10",
    "gn:asciiname":"Azanja",
    "gn:country_code":"RS",
    "gn:dem":167,
    "gn:feature_class":"P",
    "gn:feature_code":"PPL",
    "gn:name":"Azanja",
    "gn:population":0,
    "gn:timezone":"Europe/Belgrade",
    "iso:country":"RS",
    "name:srp_x_preferred":[
        "Azanja"
    ],
    "wof:name":"Azanja",
    "wof:placetype":"locality"
},
  "geometry": {"coordinates":[20.87972,44.43306],"type":"Point"}
}