{
  "type": "Feature",
  "properties": {
    "gn:admin1_code":"SE",
    "gn:admin2_code":"10",
    "gn:asciiname":"Azanja",
    "gn:country_code":"RS",
    "gn:dem":167,
    "gn:feature_class":"P",
    "gn:feature_code":"PPL",
    "gn:name":"Azanja",
    "gn:population":0,
    "gn:timezone":"Europe/Belgrade",
    "iso:country":"RS",
    "name:ara_x_preferred":[
        "\u0623\u0632\u0627\u0646\u064a\u0627"
    ],
    "name:ceb_x_preferred":[
        "Azanja"
    ],
    "name:fra_x_preferred":[
        "Azanja"
    ],
    "name:msa_x_preferred":[
        "Azanja"
    ],
    "name:por_x_preferred":[
        "Azanja"
    ],
    "name:slv_x_preferred":[
        "Azanja"
    ],
    "name:srp_x_preferred":[
        "Azanja"
    ],
    "name:srp_x_variant":[
        "\u0410\u0437\u0430\u045a\u0430"
    ],
    "wof:name":"Azanja",
    "wof:placetype":"locality"
},
  "geometry": {"coordinates":[20.87972,44.43306],"type":"Point"}
}