{
  "type": "Feature",
  "properties": {
    "gn:admin1_code":"SE",
    "gn:admin2_code":"17",
    "gn:asciiname":"Kukici",
    "gn:country_code":"RS",
    "gn:dem":393,
    "gn:feature_class":"P",
    "gn:feature_code":"PPL",
    "gn:name":"Kuki\u0107i",
    "gn:population":0,
    "gn:timezone":"Europe/Belgrade",
    "iso:country":"RS",
    "wof:name":"Kukici",
    "wof:placetype":"locality"
},
  "geometry": {"coordinates":[20.16833,43.84278],"type":"Point"}
}