{
  "type": "Feature",
  "properties": {
    "gn:admin1_code":"SE",
    "gn:admin2_code":"20",
    "gn:admin3_code":"71285.0",
    "gn:asciiname":"Niska Banja",
    "gn:country_code":"RS",
    "gn:dem":234,
    "gn:feature_class":"P",
    "gn:feature_code":"PPLA3",
    "gn:name":"Ni\u0161ka Banja",
    "gn:population":0,
    "gn:timezone":"Europe/Belgrade",
    "iso:country":"RS",
    "name:bul_x_preferred":[
        "\u041d\u0438\u0448\u043a\u0430 \u0411\u0430\u043d\u044f"
    ],
    "name:bul_x_variant":[
        "\u041d\u0438\u0448\u043a\u0430 \u0431\u0430\u043d\u044f"
    ],
    "name:ces_x_preferred":[
        "Ni\u0161ka Banja"
    ],
    "name:deu_x_preferred":[
        "Ni\u0161ka Banja"
    ],
    "name:fra_x_preferred":[
        "Ni\u0161ka Banja"
    ],
    "name:hbs_x_preferred":[
        "\u041d\u0438\u0448\u043a\u0430 \u0411\u0430\u045a\u0430"
    ],
    "name:hrv_x_preferred":[
        "Ni\u0161ka Banja"
    ],
    "name:msa_x_preferred":[
        "Ni\u0161ka Banja"
    ],
    "name:nld_x_preferred":[
        "Ni\u0161ka Banja"
    ],
    "name:pol_x_preferred":[
        "Ni\u0161ka Banja"
    ],
    "name:por_x_preferred":[
        "Ni\u0161ka Banja"
    ],
    "name:slv_x_preferred":[
        "Ni\u0161ka Banja"
    ],
    "name:srp_x_preferred":[
        "\u041d\u0438\u0448\u043a\u0430 \u0411\u0430\u045a\u0430"
    ],
    "name:zho_x_preferred":[
        "\u5c3c\u4ec0\u7926\u6cc9\u6751"
    ],
    "wof:name":"Niska Banja",
    "wof:placetype":"locality"
},
  "geometry": {"coordinates":[22.0057,43.29507],"type":"Point"}
}