{
  "type": "Feature",
  "properties": {
    "gn:admin1_code":"SE",
    "gn:admin2_code":"15",
    "gn:asciiname":"Inovo",
    "gn:country_code":"RS",
    "gn:dem":368,
    "gn:feature_class":"P",
    "gn:feature_code":"PPL",
    "gn:name":"Inovo",
    "gn:population":0,
    "gn:timezone":"Europe/Belgrade",
    "iso:country":"RS",
    "name:srp_x_preferred":[
        "Inovo"
    ],
    "wof:name":"Inovo",
    "wof:placetype":"locality"
},
  "geometry": {"coordinates":[22.44077,43.40946],"type":"Point"}
}