{
  "type": "Feature",
  "properties": {
    "gn:admin1_code":"SE",
    "gn:admin2_code":"17",
    "gn:asciiname":"Kumanica",
    "gn:country_code":"RS",
    "gn:dem":896,
    "gn:feature_class":"P",
    "gn:feature_code":"PPLL",
    "gn:name":"Kumanica",
    "gn:population":0,
    "gn:timezone":"Europe/Belgrade",
    "iso:country":"RS",
    "name:ceb_x_preferred":[
        "Kumanica"
    ],
    "name:fas_x_preferred":[
        "\u06a9\u0648\u0645\u0627\u0646\u06cc\u062a\u0633\u0627"
    ],
    "name:fra_x_preferred":[
        "Kumanica"
    ],
    "name:msa_x_preferred":[
        "Kumanica"
    ],
    "name:nld_x_preferred":[
        "Kumanica"
    ],
    "name:por_x_preferred":[
        "Kumanica"
    ],
    "name:slv_x_preferred":[
        "Kumanica"
    ],
    "name:srp_x_preferred":[
        "Kumanica"
    ],
    "name:srp_x_variant":[
        "\u041a\u0443\u043c\u0430\u043d\u0438\u0446\u0430"
    ],
    "wof:name":"Kumanica",
    "wof:placetype":"locality"
},
  "geometry": {"coordinates":[20.22447,43.47009],"type":"Point"}
}