{
  "type": "Feature",
  "properties": {
    "gn:admin1_code":"SE",
    "gn:admin2_code":"17",
    "gn:asciiname":"Kumanica",
    "gn:country_code":"RS",
    "gn:dem":896,
    "gn:feature_class":"P",
    "gn:feature_code":"PPLL",
    "gn:name":"Kumanica",
    "gn:population":0,
    "gn:timezone":"Europe/Belgrade",
    "iso:country":"RS",
    "name:srp_x_preferred":[
        "Kumanica"
    ],
    "wof:name":"Kumanica",
    "wof:placetype":"locality"
},
  "geometry": {"coordinates":[20.22447,43.47009],"type":"Point"}
}