{
  "type": "Feature",
  "properties": {
    "gn:admin1_code":"SE",
    "gn:admin2_code":"24",
    "gn:asciiname":"Drazina Mahala",
    "gn:country_code":"RS",
    "gn:dem":1265,
    "gn:feature_class":"P",
    "gn:feature_code":"PPL",
    "gn:name":"Dra\u017eina Mahala",
    "gn:population":0,
    "gn:timezone":"Europe/Belgrade",
    "iso:country":"RS",
    "name:srp_x_preferred":[
        "Dra\u017eina Mahala"
    ],
    "wof:name":"Drazina Mahala",
    "wof:placetype":"locality"
},
  "geometry": {"coordinates":[22.37677,42.72022],"type":"Point"}
}