{
  "type": "Feature",
  "properties": {
    "gn:admin1_code":"SE",
    "gn:admin2_code":"24",
    "gn:asciiname":"Graovska Mahala",
    "gn:country_code":"RS",
    "gn:dem":811,
    "gn:feature_class":"P",
    "gn:feature_code":"PPL",
    "gn:name":"Graovska Mahala",
    "gn:population":0,
    "gn:timezone":"Europe/Belgrade",
    "iso:country":"RS",
    "wof:name":"Graovska Mahala",
    "wof:placetype":"locality"
},
  "geometry": {"coordinates":[22.46931,42.43937],"type":"Point"}
}