{
  "type": "Feature",
  "properties": {
    "gn:admin1_code":"SE",
    "gn:admin2_code":"24",
    "gn:asciiname":"Stara Maala",
    "gn:country_code":"RS",
    "gn:dem":732,
    "gn:feature_class":"P",
    "gn:feature_code":"PPL",
    "gn:name":"Stara Maala",
    "gn:population":0,
    "gn:timezone":"Europe/Belgrade",
    "iso:country":"RS",
    "name:srp_x_preferred":[
        "Stara Maala"
    ],
    "name:und_x_variant":[
        "Stara Mala"
    ],
    "wof:name":"Stara Maala",
    "wof:placetype":"locality"
},
  "geometry": {"coordinates":[21.79294,42.3812],"type":"Point"}
}