{
  "type": "Feature",
  "properties": {
    "gn:admin1_code":"SE",
    "gn:admin2_code":"19",
    "gn:asciiname":"Blazici",
    "gn:country_code":"RS",
    "gn:dem":815,
    "gn:feature_class":"P",
    "gn:feature_code":"PPL",
    "gn:name":"Bla\u017ei\u0107i",
    "gn:population":0,
    "gn:timezone":"Europe/Belgrade",
    "iso:country":"RS",
    "name:srp_x_preferred":[
        "Bla\u017ei\u0107i"
    ],
    "wof:name":"Blazici",
    "wof:placetype":"locality"
},
  "geometry": {"coordinates":[20.93721,43.4307],"type":"Point"}
}