{
  "type": "Feature",
  "properties": {
    "gn:admin1_code":"SE",
    "gn:admin2_code":"16",
    "gn:asciiname":"Kulize",
    "gn:country_code":"RS",
    "gn:dem":815,
    "gn:feature_class":"P",
    "gn:feature_code":"PPL",
    "gn:name":"Kulize",
    "gn:population":0,
    "gn:timezone":"Europe/Belgrade",
    "iso:country":"RS",
    "wof:name":"Kulize",
    "wof:placetype":"locality"
},
  "geometry": {"coordinates":[19.35639,43.49444],"type":"Point"}
}