{
  "type": "Feature",
  "properties": {
    "gn:admin1_code":"SE",
    "gn:admin2_code":"14",
    "gn:asciiname":"Krivelj",
    "gn:country_code":"RS",
    "gn:dem":325,
    "gn:feature_class":"P",
    "gn:feature_code":"PPL",
    "gn:name":"Krivelj",
    "gn:population":0,
    "gn:timezone":"Europe/Belgrade",
    "iso:country":"RS",
    "name:bos_x_preferred":[
        "Krivelj"
    ],
    "name:ceb_x_preferred":[
        "Krivelj"
    ],
    "name:deu_x_preferred":[
        "Krivelj"
    ],
    "name:fra_x_preferred":[
        "Krivelj"
    ],
    "name:msa_x_preferred":[
        "Krivelj"
    ],
    "name:nld_x_preferred":[
        "Krivelj"
    ],
    "name:por_x_preferred":[
        "Krivelj"
    ],
    "name:slv_x_preferred":[
        "Krivelj"
    ],
    "name:srp_x_preferred":[
        "Krivelj"
    ],
    "name:srp_x_variant":[
        "\u041a\u0440\u0438\u0432\u0435\u0459"
    ],
    "name:und_x_variant":[
        "Kriveij"
    ],
    "wof:name":"Krivelj",
    "wof:placetype":"locality"
},
  "geometry": {"coordinates":[22.09611,44.12944],"type":"Point"}
}