{
  "type": "Feature",
  "properties": {
    "gn:country":"RS",
    "gn:fcode":"PPLL",
    "gn:pop":605,
    "iso:country":"RS",
    "name:srp_x_preferred":[
        "Suvi Do"
    ],
    "qs:name":"Suvi Do",
    "qs:photos_9r":0,
    "qs:photos_sr":0,
    "qs:pop_sr":"2",
    "wd:wordcount":83,
    "wof:name":"Suvi Do",
    "wof:placetype":"locality",
    "wof:population":605
},
  "geometry": {"coordinates":[21.33269,43.25829],"type":"Point"}
}