{
  "type": "Feature",
  "properties": {
    "gn:admin1_code":"SE",
    "gn:admin2_code":"8",
    "gn:asciiname":"Novakovica Mala",
    "gn:country_code":"RS",
    "gn:dem":187,
    "gn:feature_class":"P",
    "gn:feature_code":"PPL",
    "gn:name":"Novakovi\u0107a Mala",
    "gn:population":0,
    "gn:timezone":"Europe/Belgrade",
    "iso:country":"RS",
    "wof:name":"Novakovica Mala",
    "wof:placetype":"locality"
},
  "geometry": {"coordinates":[19.53861,44.44556],"type":"Point"}
}