{
  "type": "Feature",
  "properties": {
    "gn:admin1_code":"SE",
    "gn:admin2_code":"14",
    "gn:asciiname":"Manastirica",
    "gn:country_code":"RS",
    "gn:dem":184,
    "gn:feature_class":"P",
    "gn:feature_code":"PPL",
    "gn:name":"Manastirica",
    "gn:population":0,
    "gn:timezone":"Europe/Belgrade",
    "iso:country":"RS",
    "name:srp_x_preferred":[
        "Manastirica"
    ],
    "wof:name":"Manastirica",
    "wof:placetype":"locality"
},
  "geometry": {"coordinates":[22.4996,44.62099],"type":"Point"}
}