{
  "type": "Feature",
  "properties": {
    "gn:admin1_code":"SE",
    "gn:admin2_code":"8",
    "gn:asciiname":"Jovicici",
    "gn:country_code":"RS",
    "gn:dem":333,
    "gn:feature_class":"P",
    "gn:feature_code":"PPL",
    "gn:name":"Jovi\u010di\u0107i",
    "gn:population":0,
    "gn:timezone":"Europe/Belgrade",
    "iso:country":"RS",
    "name:srp_x_preferred":[
        "Jovi\u010di\u0107i"
    ],
    "wof:name":"Jovicici",
    "wof:placetype":"locality"
},
  "geometry": {"coordinates":[19.39478,44.44549],"type":"Point"}
}