{
  "type": "Feature",
  "properties": {
    "gn:country":"RS",
    "gn:fcode":"PPL",
    "gn:pop":5764,
    "iso:country":"RS",
    "name:ara_x_preferred":[
        "\u0628\u0627\u062a\u0634\u0643\u0648 \u063a\u0631\u0627\u062f\u064a\u0634\u062a\u064a"
    ],
    "name:dut_x_preferred":[
        "Ba\u010dko Gradi\u0161te"
    ],
    "name:eng_x_preferred":[
        "Ba\u010dko Gradi\u0161te"
    ],
    "name:epo_x_preferred":[
        "Ba\u0109ko Gradi\u015dte"
    ],
    "name:fre_x_preferred":[
        "Ba\u010dko Gradi\u0161te"
    ],
    "name:ger_x_preferred":[
        "Ba\u010dko Gradi\u0161te"
    ],
    "name:hrv_x_preferred":[
        "Ba\u010dko Gradi\u0161te"
    ],
    "name:hun_x_preferred":[
        "Tisza-F\u00f6ldv\u00e1r"
    ],
    "name:hun_x_variant":[
        "B\u00e1csf\u00f6ldv\u00e1r",
        "F\u00f6ldv\u00e1r"
    ],
    "name:may_x_preferred":[
        "Ba\u010dko Gradi\u0161te"
    ],
    "name:slv_x_preferred":[
        "Ba\u010dko Gradi\u0161te"
    ],
    "name:srp_x_preferred":[
        "Ba\u010dko Gradi\u0161te"
    ],
    "name:unk_x_variant":[
        "B\u00e1csf\u00f6ldv\u00e1r"
    ],
    "qs:name":"Ba\u010dko Gradi\u0161te",
    "qs:photos_9r":0,
    "qs:photos_sr":0,
    "qs:pop_sr":"5",
    "wd:wordcount":554,
    "wof:name":"Ba\u010dko Gradi\u0161te",
    "wof:placetype":"locality",
    "wof:population":5764
},
  "geometry": {"coordinates":[20.03082,45.53271],"type":"Point"}
}