{
  "type": "Feature",
  "properties": {
    "gn:admin1_code":"SE",
    "gn:admin2_code":"16",
    "gn:asciiname":"Jasik",
    "gn:country_code":"RS",
    "gn:dem":652,
    "gn:feature_class":"P",
    "gn:feature_code":"PPL",
    "gn:name":"Jasik",
    "gn:population":0,
    "gn:timezone":"Europe/Belgrade",
    "iso:country":"RS",
    "name:bos_x_preferred":[
        "Jasik"
    ],
    "name:ceb_x_preferred":[
        "Jasik"
    ],
    "name:fra_x_preferred":[
        "Jasik"
    ],
    "name:hrv_x_preferred":[
        "Jasik"
    ],
    "name:nld_x_preferred":[
        "Jasik"
    ],
    "name:srp_x_preferred":[
        "Jasik"
    ],
    "name:srp_x_variant":[
        "\u0408\u0430\u0441\u0438\u043a"
    ],
    "name:swe_x_preferred":[
        "Jasik"
    ],
    "name:und_x_variant":[
        "Jasikovac"
    ],
    "wof:name":"Jasik",
    "wof:placetype":"locality"
},
  "geometry": {"coordinates":[19.56871,44.10509],"type":"Point"}
}