{
  "type": "Feature",
  "properties": {
    "gn:admin1_code":"SE",
    "gn:admin2_code":"22",
    "gn:asciiname":"Pajez",
    "gn:country_code":"RS",
    "gn:dem":739,
    "gn:feature_class":"P",
    "gn:feature_code":"PPL",
    "gn:name":"Paje\u017e",
    "gn:population":0,
    "gn:timezone":"Europe/Belgrade",
    "iso:country":"RS",
    "name:fra_x_preferred":[
        "Paje\u017e"
    ],
    "name:msa_x_preferred":[
        "Paje\u017e"
    ],
    "name:por_x_preferred":[
        "Paje\u017e"
    ],
    "name:slv_x_preferred":[
        "Paje\u017e"
    ],
    "name:srp_x_preferred":[
        "Paje\u017e"
    ],
    "name:srp_x_variant":[
        "\u041f\u0430\u0458\u0435\u0436"
    ],
    "wof:name":"Pajez",
    "wof:placetype":"locality"
},
  "geometry": {"coordinates":[22.3983,43.34099000000001],"type":"Point"}
}