{
  "type": "Feature",
  "properties": {
    "gn:admin1_code":"SE",
    "gn:admin2_code":"17",
    "gn:asciiname":"Pakovrace",
    "gn:country_code":"RS",
    "gn:dem":292,
    "gn:feature_class":"P",
    "gn:feature_code":"PPL",
    "gn:name":"Pakovra\u010de",
    "gn:population":0,
    "gn:timezone":"Europe/Belgrade",
    "iso:country":"RS",
    "name:ceb_x_preferred":[
        "Pakovra\u010de"
    ],
    "name:fra_x_preferred":[
        "Pakovra\u0107e"
    ],
    "name:msa_x_preferred":[
        "Pakovra\u0107e"
    ],
    "name:nld_x_preferred":[
        "Pakovra\u0107e"
    ],
    "name:por_x_preferred":[
        "Pakovra\u0107e"
    ],
    "name:slv_x_preferred":[
        "Pakovra\u0107e"
    ],
    "name:srp_x_preferred":[
        "Pakovra\u010de"
    ],
    "name:srp_x_variant":[
        "\u041f\u0430\u043a\u043e\u0432\u0440\u0430\u045b\u0435"
    ],
    "wof:name":"Pakovrace",
    "wof:placetype":"locality"
},
  "geometry": {"coordinates":[20.26474,43.89548],"type":"Point"}
}