{
  "type": "Feature",
  "properties": {
    "gn:admin1_code":"SE",
    "gn:admin2_code":"17",
    "gn:asciiname":"Pakovrace",
    "gn:country_code":"RS",
    "gn:dem":292,
    "gn:feature_class":"P",
    "gn:feature_code":"PPL",
    "gn:name":"Pakovra\u010de",
    "gn:population":0,
    "gn:timezone":"Europe/Belgrade",
    "iso:country":"RS",
    "name:srp_x_preferred":[
        "Pakovra\u010de"
    ],
    "wof:name":"Pakovrace",
    "wof:placetype":"locality"
},
  "geometry": {"coordinates":[20.26474,43.89548],"type":"Point"}
}