{
  "type": "Feature",
  "properties": {
    "gn:admin1_code":"SE",
    "gn:admin2_code":"23",
    "gn:asciiname":"Kalugerce",
    "gn:country_code":"RS",
    "gn:dem":743,
    "gn:feature_class":"P",
    "gn:feature_code":"PPL",
    "gn:name":"Kalu\u0111erce",
    "gn:population":0,
    "gn:timezone":"Europe/Belgrade",
    "iso:country":"RS",
    "name:ceb_x_preferred":[
        "Kalu\u0111erce"
    ],
    "name:fra_x_preferred":[
        "Kalu\u0111erce"
    ],
    "name:msa_x_preferred":[
        "Kalu\u0111erce"
    ],
    "name:por_x_preferred":[
        "Kalu\u0111erce"
    ],
    "name:slv_x_preferred":[
        "Kalu\u0111erce"
    ],
    "name:sqi_x_preferred":[
        "Kallugjerica"
    ],
    "name:srp_x_preferred":[
        "Kalu\u0111erce"
    ],
    "name:srp_x_variant":[
        "\u041a\u0430\u043b\u0443\u0452\u0435\u0440\u0446\u0435"
    ],
    "name:und_x_variant":[
        "Kaluderica"
    ],
    "wof:name":"Kalugerce",
    "wof:placetype":"locality"
},
  "geometry": {"coordinates":[21.8401,42.81011],"type":"Point"}
}