{
  "type": "Feature",
  "properties": {
    "gn:admin1_code":"SE",
    "gn:admin2_code":"23",
    "gn:asciiname":"Kalugerce",
    "gn:country_code":"RS",
    "gn:dem":743,
    "gn:feature_class":"P",
    "gn:feature_code":"PPL",
    "gn:name":"Kalu\u0111erce",
    "gn:population":0,
    "gn:timezone":"Europe/Belgrade",
    "iso:country":"RS",
    "name:srp_x_preferred":[
        "Kalu\u0111erce"
    ],
    "name:und_x_variant":[
        "Kaluderica"
    ],
    "wof:name":"Kalugerce",
    "wof:placetype":"locality"
},
  "geometry": {"coordinates":[21.8401,42.81011],"type":"Point"}
}