{
  "type": "Feature",
  "properties": {
    "gn:admin1_code":"SE",
    "gn:admin2_code":"17",
    "gn:asciiname":"Donji Dubac",
    "gn:country_code":"RS",
    "gn:dem":787,
    "gn:feature_class":"P",
    "gn:feature_code":"PPL",
    "gn:name":"Donji Dubac",
    "gn:population":0,
    "gn:timezone":"Europe/Belgrade",
    "iso:country":"RS",
    "name:srp_x_preferred":[
        "Donji Dubac"
    ],
    "wof:name":"Donji Dubac",
    "wof:placetype":"locality"
},
  "geometry": {"coordinates":[20.34312000000001,43.67091],"type":"Point"}
}