{
  "type": "Feature",
  "properties": {
    "gn:admin1_code":"SE",
    "gn:admin2_code":"18",
    "gn:asciiname":"Donja Katrga",
    "gn:country_code":"RS",
    "gn:dem":208,
    "gn:feature_class":"P",
    "gn:feature_code":"PPL",
    "gn:name":"Donja Katrga",
    "gn:population":0,
    "gn:timezone":"Europe/Belgrade",
    "iso:country":"RS",
    "wof:name":"Donja Katrga",
    "wof:placetype":"locality"
},
  "geometry": {"coordinates":[20.56639,43.81972],"type":"Point"}
}