{
  "type": "Feature",
  "properties": {
    "gn:admin1_code":"SE",
    "gn:admin2_code":"0",
    "gn:asciiname":"Mala Ivanca",
    "gn:country_code":"RS",
    "gn:dem":248,
    "gn:feature_class":"P",
    "gn:feature_code":"PPL",
    "gn:name":"Mala Ivan\u010da",
    "gn:population":0,
    "gn:timezone":"Europe/Belgrade",
    "iso:country":"RS",
    "name:srp_x_preferred":[
        "Mala Ivan\u010da"
    ],
    "wof:name":"Mala Ivanca",
    "wof:placetype":"locality"
},
  "geometry": {"coordinates":[20.61634,44.58961],"type":"Point"}
}