{
  "type": "Feature",
  "properties": {
    "gn:admin1_code":"SE",
    "gn:admin2_code":"8",
    "gn:asciiname":"Vladicica",
    "gn:country_code":"RS",
    "gn:dem":187,
    "gn:feature_class":"P",
    "gn:feature_code":"PPL",
    "gn:name":"Vladi\u010dica",
    "gn:population":0,
    "gn:timezone":"Europe/Belgrade",
    "iso:country":"RS",
    "name:srp_x_preferred":[
        "Vladi\u010dica"
    ],
    "wof:name":"Vladicica",
    "wof:placetype":"locality"
},
  "geometry": {"coordinates":[19.38074,44.19669],"type":"Point"}
}