{
  "type": "Feature",
  "properties": {
    "gn:admin1_code":"SE",
    "gn:admin2_code":"16",
    "gn:asciiname":"Brekovo",
    "gn:country_code":"RS",
    "gn:dem":880,
    "gn:feature_class":"P",
    "gn:feature_code":"PPLL",
    "gn:name":"Brekovo",
    "gn:population":0,
    "gn:timezone":"Europe/Belgrade",
    "iso:country":"RS",
    "name:ceb_x_preferred":[
        "Brekovo"
    ],
    "name:fra_x_preferred":[
        "Brekovo"
    ],
    "name:ita_x_preferred":[
        "Brekovo"
    ],
    "name:msa_x_preferred":[
        "Brekovo"
    ],
    "name:nld_x_preferred":[
        "Brekovo"
    ],
    "name:por_x_preferred":[
        "Brekovo"
    ],
    "name:slv_x_preferred":[
        "Brekovo"
    ],
    "name:srp_x_preferred":[
        "Brekovo"
    ],
    "name:srp_x_variant":[
        "\u0411\u0440\u0435\u043a\u043e\u0432\u043e"
    ],
    "wof:name":"Brekovo",
    "wof:placetype":"locality"
},
  "geometry": {"coordinates":[20.0115,43.64529],"type":"Point"}
}