{
  "type": "Feature",
  "properties": {
    "gn:admin1_code":"SE",
    "gn:admin2_code":"11",
    "gn:asciiname":"Vrbnica",
    "gn:country_code":"RS",
    "gn:dem":113,
    "gn:feature_class":"P",
    "gn:feature_code":"PPL",
    "gn:name":"Vrbnica",
    "gn:population":0,
    "gn:timezone":"Europe/Belgrade",
    "iso:country":"RS",
    "name:srp_x_preferred":[
        "Vrbnica"
    ],
    "wof:name":"Vrbnica",
    "wof:placetype":"locality"
},
  "geometry": {"coordinates":[21.29363,44.47401],"type":"Point"}
}