{
  "type": "Feature",
  "properties": {
    "gn:admin1_code":"SE",
    "gn:admin2_code":"11",
    "gn:asciiname":"Vrbnica",
    "gn:country_code":"RS",
    "gn:dem":113,
    "gn:feature_class":"P",
    "gn:feature_code":"PPL",
    "gn:name":"Vrbnica",
    "gn:population":0,
    "gn:timezone":"Europe/Belgrade",
    "iso:country":"RS",
    "name:cat_x_preferred":[
        "Vrbnica"
    ],
    "name:deu_x_preferred":[
        "Vrbnica"
    ],
    "name:epo_x_preferred":[
        "Vrbnica"
    ],
    "name:eus_x_preferred":[
        "Vrbnica"
    ],
    "name:fra_x_preferred":[
        "Vrbnica"
    ],
    "name:hun_x_preferred":[
        "F\u00fczes\u00e9r"
    ],
    "name:ita_x_preferred":[
        "Vrbnica"
    ],
    "name:msa_x_preferred":[
        "Vrbnica"
    ],
    "name:nld_x_preferred":[
        "Vrbnica"
    ],
    "name:pol_x_preferred":[
        "Vrbnica"
    ],
    "name:ron_x_preferred":[
        "Vrbnica"
    ],
    "name:slk_x_preferred":[
        "Vrbnica"
    ],
    "name:spa_x_preferred":[
        "Vrbnica"
    ],
    "name:srp_x_preferred":[
        "Vrbnica"
    ],
    "name:srp_x_variant":[
        "\u0412\u0440\u0431\u045a\u0438\u0446\u0430"
    ],
    "name:ukr_x_preferred":[
        "\u0412\u0440\u0431\u043d\u0456\u0446\u0430"
    ],
    "name:war_x_preferred":[
        "Vrbnica"
    ],
    "wof:name":"Vrbnica",
    "wof:placetype":"locality"
},
  "geometry": {"coordinates":[21.29363,44.47401],"type":"Point"}
}