{
  "type": "Feature",
  "properties": {
    "gn:admin1_code":"SE",
    "gn:admin2_code":"24",
    "gn:asciiname":"Novi Glog",
    "gn:country_code":"RS",
    "gn:dem":1242,
    "gn:feature_class":"P",
    "gn:feature_code":"PPL",
    "gn:name":"Novi Glog",
    "gn:population":0,
    "gn:timezone":"Europe/Belgrade",
    "iso:country":"RS",
    "name:bos_x_preferred":[
        "Novi Glog"
    ],
    "name:fra_x_preferred":[
        "Novi Glog"
    ],
    "name:hun_x_preferred":[
        "Novi Glog"
    ],
    "name:slv_x_preferred":[
        "Novi Glog"
    ],
    "name:srp_x_preferred":[
        "Novi Glog"
    ],
    "wof:name":"Novi Glog",
    "wof:placetype":"locality"
},
  "geometry": {"coordinates":[22.12556,42.44472],"type":"Point"}
}