{
  "type": "Feature",
  "properties": {
    "gn:country":"RS",
    "gn:fcode":"PPL",
    "gn:population":1372,
    "iso:country":"RS",
    "name:ceb_x_preferred":[
        "Jano\u0161ik"
    ],
    "name:eng_x_preferred":[
        "Jano\u0161ik"
    ],
    "name:epo_x_preferred":[
        "Jano\u015dik"
    ],
    "name:fra_x_preferred":[
        "Jano\u0161ik"
    ],
    "name:hrv_x_preferred":[
        "Jano\u0161ik"
    ],
    "name:hun_x_preferred":[
        "\u00dajs\u00e1ndorfalva"
    ],
    "name:ita_x_preferred":[
        "Jano\u0161ik"
    ],
    "name:msa_x_preferred":[
        "Jano\u0161ik"
    ],
    "name:nld_x_preferred":[
        "Jano\u0161ik"
    ],
    "name:ron_x_preferred":[
        "Jano\u0161ik"
    ],
    "name:rus_x_preferred":[
        "\u042f\u043d\u043e\u0448\u0438\u043a"
    ],
    "name:slk_x_preferred":[
        "J\u00e1no\u0161\u00edk"
    ],
    "name:slv_x_preferred":[
        "Jano\u0161ik"
    ],
    "name:srp_x_preferred":[
        "Jano\u0161ik"
    ],
    "name:srp_x_variant":[
        "\u0408\u0430\u043d\u043e\u0448\u0438\u043a"
    ],
    "name:und_x_variant":[
        "Slova\u010dki-Aleksandrovac"
    ],
    "name:urd_x_preferred":[
        "\u062c\u0627\u0646\u0648\u0634\u0627\u06a9"
    ],
    "qs:name":"Jano\u0161ik",
    "qs:photos_9r":0,
    "qs:photos_sr":0,
    "qs:pop_sr":"3",
    "wd:wordcount":208,
    "wof:name":"Jano\u0161ik",
    "wof:placetype":"locality",
    "wof:population":1372
},
  "geometry": {"coordinates":[21.00658,45.17141],"type":"Point"}
}