{
  "type": "Feature",
  "properties": {
    "gn:admin1_code":"SE",
    "gn:admin2_code":"16",
    "gn:asciiname":"Drenovci",
    "gn:country_code":"RS",
    "gn:dem":613,
    "gn:feature_class":"P",
    "gn:feature_code":"PPL",
    "gn:name":"Drenovci",
    "gn:population":0,
    "gn:timezone":"Europe/Belgrade",
    "iso:country":"RS",
    "name:srp_x_preferred":[
        "Drenovci"
    ],
    "wof:name":"Drenovci",
    "wof:placetype":"locality"
},
  "geometry": {"coordinates":[19.87701,44.07899999999999],"type":"Point"}
}