{
  "type": "Feature",
  "properties": {
    "gn:admin1_code":"SE",
    "gn:admin2_code":"8",
    "gn:asciiname":"Bobija",
    "gn:country_code":"RS",
    "gn:dem":260,
    "gn:feature_class":"P",
    "gn:feature_code":"PPL",
    "gn:name":"Bobija",
    "gn:population":0,
    "gn:timezone":"Europe/Belgrade",
    "iso:country":"RS",
    "name:srp_x_preferred":[
        "\u0411\u043e\u0431\u0438\u0458\u0430"
    ],
    "wof:name":"Bobija",
    "wof:placetype":"locality"
},
  "geometry": {"coordinates":[19.63821,44.52142],"type":"Point"}
}