{
  "type": "Feature",
  "properties": {
    "gn:admin1_code":"SE",
    "gn:admin2_code":"19",
    "gn:asciiname":"Bukovci",
    "gn:country_code":"RS",
    "gn:dem":405,
    "gn:feature_class":"P",
    "gn:feature_code":"PPL",
    "gn:name":"Bukovci",
    "gn:population":0,
    "gn:timezone":"Europe/Belgrade",
    "iso:country":"RS",
    "name:bos_x_preferred":[
        "Bukovci"
    ],
    "name:fra_x_preferred":[
        "Bukovci"
    ],
    "name:srp_x_preferred":[
        "Bukovci"
    ],
    "wof:name":"Bukovci",
    "wof:placetype":"locality"
},
  "geometry": {"coordinates":[21.12763,43.38306],"type":"Point"}
}