{
  "type": "Feature",
  "properties": {
    "gn:admin1_code":"SE",
    "gn:admin2_code":"15",
    "gn:asciiname":"Raskrsje",
    "gn:country_code":"RS",
    "gn:dem":668,
    "gn:feature_class":"P",
    "gn:feature_code":"PPL",
    "gn:name":"Raskrsje",
    "gn:population":0,
    "gn:timezone":"Europe/Belgrade",
    "iso:country":"RS",
    "name:srp_x_preferred":[
        "Raskrsje"
    ],
    "wof:name":"Raskrsje",
    "wof:placetype":"locality"
},
  "geometry": {"coordinates":[22.2175,43.50333],"type":"Point"}
}