{
  "type": "Feature",
  "properties": {
    "gn:country":"RS",
    "gn:fcode":"PPL",
    "gn:pop":0,
    "iso:country":"RS",
    "name:eng_x_preferred":[
        "Dobra"
    ],
    "name:fra_x_preferred":[
        "Dobra"
    ],
    "name:msa_x_preferred":[
        "Dobra"
    ],
    "name:nld_x_preferred":[
        "Dobra"
    ],
    "name:por_x_preferred":[
        "Dobra"
    ],
    "name:slv_x_preferred":[
        "Dobra"
    ],
    "name:srp_x_preferred":[
        "Dobra"
    ],
    "name:srp_x_variant":[
        "\u0414\u043e\u0431\u0440\u0430"
    ],
    "qs:name":"Dobra",
    "qs:name_adm0":"Serbia",
    "qs:name_adm1":"Branichevo",
    "qs:photos":27,
    "qs:photos_1k":5,
    "qs:photos_9k":1,
    "qs:photos_9r":2,
    "qs:photos_all":27,
    "qs:photos_sr":2,
    "qs:placetype":"Town",
    "qs:pop_sr":"0",
    "wd:wordcount":328,
    "wof:name":"Dobra",
    "wof:placetype":"locality",
    "wof:population":0
},
  "geometry": {"coordinates":[21.90826,44.63602],"type":"Point"}
}