{
  "type": "Feature",
  "properties": {
    "gn:admin1_code":"SE",
    "gn:admin2_code":"18",
    "gn:asciiname":"Smiljanici",
    "gn:country_code":"RS",
    "gn:dem":1264,
    "gn:feature_class":"P",
    "gn:feature_code":"PPL",
    "gn:name":"Smiljani\u0107i",
    "gn:population":0,
    "gn:timezone":"Europe/Belgrade",
    "iso:country":"RS",
    "name:srp_x_preferred":[
        "Smiljani\u0107i"
    ],
    "wof:name":"Smiljanici",
    "wof:placetype":"locality"
},
  "geometry": {"coordinates":[20.43472,43.38139],"type":"Point"}
}