{
  "type": "Feature",
  "properties": {
    "gn:admin1_code":"SE",
    "gn:admin2_code":"10",
    "gn:asciiname":"Veliko Orasje",
    "gn:country_code":"RS",
    "gn:dem":95,
    "gn:feature_class":"P",
    "gn:feature_code":"PPL",
    "gn:name":"Veliko Ora\u0161je",
    "gn:population":0,
    "gn:timezone":"Europe/Belgrade",
    "iso:country":"RS",
    "name:ceb_x_preferred":[
        "Veliko Ora\u0161je"
    ],
    "name:fas_x_preferred":[
        "\u0648\u0644\u06cc\u06a9\u0648 \u0627\u0631\u0634\u062c"
    ],
    "name:fra_x_preferred":[
        "Veliko Ora\u0161je"
    ],
    "name:msa_x_preferred":[
        "Veliko Ora\u0161je"
    ],
    "name:por_x_preferred":[
        "Veliko Ora\u0161je"
    ],
    "name:slv_x_preferred":[
        "Veliko Ora\u0161je"
    ],
    "name:srp_x_preferred":[
        "Veliko Ora\u0161je"
    ],
    "name:srp_x_variant":[
        "\u0412\u0435\u043b\u0438\u043a\u043e \u041e\u0440\u0430\u0448\u0458\u0435"
    ],
    "name:und_x_variant":[
        "Ora\u0161je"
    ],
    "wof:name":"Veliko Orasje",
    "wof:placetype":"locality"
},
  "geometry": {"coordinates":[21.0879,44.37107],"type":"Point"}
}