{
  "type": "Feature",
  "properties": {
    "gn:admin1_code":"SE",
    "gn:admin2_code":"10",
    "gn:asciiname":"Veliko Orasje",
    "gn:country_code":"RS",
    "gn:dem":95,
    "gn:feature_class":"P",
    "gn:feature_code":"PPL",
    "gn:name":"Veliko Ora\u0161je",
    "gn:population":0,
    "gn:timezone":"Europe/Belgrade",
    "iso:country":"RS",
    "name:srp_x_preferred":[
        "Veliko Ora\u0161je"
    ],
    "name:und_x_variant":[
        "Ora\u0161je"
    ],
    "wof:name":"Veliko Orasje",
    "wof:placetype":"locality"
},
  "geometry": {"coordinates":[21.0879,44.37107],"type":"Point"}
}