{
  "type": "Feature",
  "properties": {
    "gn:admin1_code":"SE",
    "gn:admin2_code":"16",
    "gn:asciiname":"Nincici",
    "gn:country_code":"RS",
    "gn:dem":652,
    "gn:feature_class":"P",
    "gn:feature_code":"PPL",
    "gn:name":"Nin\u010di\u0107i",
    "gn:population":0,
    "gn:timezone":"Europe/Belgrade",
    "iso:country":"RS",
    "name:srp_x_preferred":[
        "Nin\u010di\u0107i"
    ],
    "wof:name":"Nincici",
    "wof:placetype":"locality"
},
  "geometry": {"coordinates":[19.69249,43.46618],"type":"Point"}
}