{
  "type": "Feature",
  "properties": {
    "gn:admin1_code":"SE",
    "gn:admin2_code":"20",
    "gn:asciiname":"Suric",
    "gn:country_code":"RS",
    "gn:dem":245,
    "gn:feature_class":"P",
    "gn:feature_code":"PPL",
    "gn:name":"\u0160uri\u0107",
    "gn:population":0,
    "gn:timezone":"Europe/Belgrade",
    "iso:country":"RS",
    "name:srp_x_preferred":[
        "\u0160uri\u0107"
    ],
    "wof:name":"Suric",
    "wof:placetype":"locality"
},
  "geometry": {"coordinates":[21.64873,43.44488],"type":"Point"}
}