{
  "type": "Feature",
  "properties": {
    "gn:admin1_code":"SE",
    "gn:admin2_code":"9",
    "gn:asciiname":"Tosici",
    "gn:country_code":"RS",
    "gn:dem":836,
    "gn:feature_class":"P",
    "gn:feature_code":"PPL",
    "gn:name":"To\u0161i\u0107i",
    "gn:population":0,
    "gn:timezone":"Europe/Belgrade",
    "iso:country":"RS",
    "name:srp_x_preferred":[
        "To\u0161i\u0107i"
    ],
    "wof:name":"Tosici",
    "wof:placetype":"locality"
},
  "geometry": {"coordinates":[19.72888,44.15801],"type":"Point"}
}