{
  "type": "Feature",
  "properties": {
    "gn:admin1_code":"SE",
    "gn:admin2_code":"16",
    "gn:asciiname":"Potoci",
    "gn:country_code":"RS",
    "gn:dem":1027,
    "gn:feature_class":"P",
    "gn:feature_code":"PPL",
    "gn:name":"Potoci",
    "gn:population":0,
    "gn:timezone":"Europe/Belgrade",
    "iso:country":"RS",
    "name:bos_x_preferred":[
        "Potoci"
    ],
    "name:ceb_x_preferred":[
        "Potoci"
    ],
    "name:deu_x_preferred":[
        "Potoci"
    ],
    "name:fra_x_preferred":[
        "Potoci"
    ],
    "name:hrv_x_preferred":[
        "Potoci"
    ],
    "name:rus_x_preferred":[
        "\u041f\u043e\u0442\u043e\u0446\u0438"
    ],
    "name:slv_x_preferred":[
        "Potoci"
    ],
    "name:srp_x_preferred":[
        "\u041f\u043e\u0442\u043e\u0446\u0438"
    ],
    "name:swe_x_preferred":[
        "Potoci"
    ],
    "wof:name":"Potoci",
    "wof:placetype":"locality"
},
  "geometry": {"coordinates":[19.72889,43.73444],"type":"Point"}
}