{
  "type": "Feature",
  "properties": {
    "gn:admin1_code":"SE",
    "gn:admin2_code":"8",
    "gn:asciiname":"Petlovaca",
    "gn:country_code":"RS",
    "gn:dem":90,
    "gn:feature_class":"P",
    "gn:feature_code":"PPL",
    "gn:name":"Petlova\u010da",
    "gn:population":0,
    "gn:timezone":"Europe/Belgrade",
    "iso:country":"RS",
    "name:srp_x_preferred":[
        "Petlova\u010da"
    ],
    "wof:name":"Petlovaca",
    "wof:placetype":"locality"
},
  "geometry": {"coordinates":[19.44673,44.72224],"type":"Point"}
}