{
  "type": "Feature",
  "properties": {
    "gn:admin1_code":"SE",
    "gn:admin2_code":"19",
    "gn:asciiname":"Trsanovci",
    "gn:country_code":"RS",
    "gn:dem":394,
    "gn:feature_class":"P",
    "gn:feature_code":"PPL",
    "gn:name":"Tr\u0161anovci",
    "gn:population":0,
    "gn:timezone":"Europe/Belgrade",
    "iso:country":"RS",
    "name:ceb_x_preferred":[
        "Tr\u0161anovci"
    ],
    "name:fas_x_preferred":[
        "\u062a\u0631\u0634\u0627\u0646\u0648\u06a9\u06cc"
    ],
    "name:fra_x_preferred":[
        "Tr\u0161anovci"
    ],
    "name:msa_x_preferred":[
        "Tr\u0161anovci"
    ],
    "name:nld_x_preferred":[
        "Tr\u0161anovci"
    ],
    "name:por_x_preferred":[
        "Tr\u0161anovci"
    ],
    "name:slv_x_preferred":[
        "Tr\u0161anovci"
    ],
    "name:srp_x_preferred":[
        "Tr\u0161anovci"
    ],
    "name:srp_x_variant":[
        "\u0422\u0440\u0448\u0430\u043d\u043e\u0432\u0446\u0438"
    ],
    "wof:name":"Trsanovci",
    "wof:placetype":"locality"
},
  "geometry": {"coordinates":[21.04773,43.37498],"type":"Point"}
}