{
  "type": "Feature",
  "properties": {
    "gn:admin1_code":"SE",
    "gn:admin2_code":"16",
    "gn:asciiname":"Mitrovac",
    "gn:country_code":"RS",
    "gn:dem":572,
    "gn:feature_class":"P",
    "gn:feature_code":"PPL",
    "gn:name":"Mitrovac",
    "gn:population":0,
    "gn:timezone":"Europe/Belgrade",
    "iso:country":"RS",
    "name:bos_x_preferred":[
        "Mitrovac"
    ],
    "name:fra_x_preferred":[
        "Mitrovac"
    ],
    "name:hrv_x_preferred":[
        "Mitrovac"
    ],
    "name:nld_x_preferred":[
        "Mitrovac"
    ],
    "name:slv_x_preferred":[
        "Mitrovac"
    ],
    "name:srp_x_preferred":[
        "\u041c\u0438\u0442\u0440\u043e\u0432\u0430\u0446"
    ],
    "wof:name":"Mitrovac",
    "wof:placetype":"locality"
},
  "geometry": {"coordinates":[19.64306,43.43333],"type":"Point"}
}