{
  "type": "Feature",
  "properties": {
    "gn:country":"RS",
    "gn:fcode":"PPL",
    "gn:pop":566,
    "iso:country":"RS",
    "name:ceb_x_preferred":[
        "Banatska Dubica"
    ],
    "name:eng_x_preferred":[
        "Banatska Dubica"
    ],
    "name:epo_x_preferred":[
        "Banatska Dubica"
    ],
    "name:fra_x_preferred":[
        "Banatska Dubica"
    ],
    "name:hrv_x_preferred":[
        "Margitica"
    ],
    "name:hun_x_preferred":[
        "Kismargita"
    ],
    "name:msa_x_preferred":[
        "Banatska Dubica"
    ],
    "name:nld_x_preferred":[
        "Banatska Dubica"
    ],
    "name:ron_x_preferred":[
        "Banatska Dubica"
    ],
    "name:slv_x_preferred":[
        "Banatska Dubica"
    ],
    "name:srp_x_preferred":[
        "Banatska Dubica"
    ],
    "name:srp_x_variant":[
        "\u0411\u0430\u043d\u0430\u0442\u0441\u043a\u0430 \u0414\u0443\u0431\u0438\u0446\u0430"
    ],
    "name:unk_x_variant":[
        "Dubica"
    ],
    "qs:name":"Banatska Dubica",
    "qs:photos_9r":0,
    "qs:photos_sr":0,
    "qs:pop_sr":"2",
    "wd:wordcount":71,
    "wof:name":"Banatska Dubica",
    "wof:placetype":"locality",
    "wof:population":566
},
  "geometry": {"coordinates":[20.82833,45.27146],"type":"Point"}
}