{
  "type": "Feature",
  "properties": {
    "gn:admin1_code":"SE",
    "gn:admin2_code":"12",
    "gn:asciiname":"Golocelo",
    "gn:country_code":"RS",
    "gn:dem":342,
    "gn:feature_class":"P",
    "gn:feature_code":"PPLL",
    "gn:name":"Golo\u010delo",
    "gn:population":0,
    "gn:timezone":"Europe/Belgrade",
    "iso:country":"RS",
    "wof:name":"Golocelo",
    "wof:placetype":"locality"
},
  "geometry": {"coordinates":[20.80831,43.93903],"type":"Point"}
}