{
  "type": "Feature",
  "properties": {
    "gn:admin1_code":"SE",
    "gn:admin2_code":"24",
    "gn:asciiname":"Rajkovica",
    "gn:country_code":"RS",
    "gn:dem":1284,
    "gn:feature_class":"P",
    "gn:feature_code":"PPL",
    "gn:name":"Rajkovica",
    "gn:population":0,
    "gn:timezone":"Europe/Belgrade",
    "iso:country":"RS",
    "wof:name":"Rajkovica",
    "wof:placetype":"locality"
},
  "geometry": {"coordinates":[22.24879,42.44313],"type":"Point"}
}