{
  "type": "Feature",
  "properties": {
    "gn:admin1_code":"SE",
    "gn:admin2_code":"21",
    "gn:asciiname":"Kare",
    "gn:country_code":"RS",
    "gn:dem":307,
    "gn:feature_class":"P",
    "gn:feature_code":"PPL",
    "gn:name":"Kare",
    "gn:population":0,
    "gn:timezone":"Europe/Belgrade",
    "iso:country":"RS",
    "name:srp_x_preferred":[
        "Kare"
    ],
    "wof:name":"Kare",
    "wof:placetype":"locality"
},
  "geometry": {"coordinates":[21.72758,43.1074],"type":"Point"}
}