{
  "type": "Feature",
  "properties": {
    "gn:admin1_code":"SE",
    "gn:admin2_code":"24",
    "gn:asciiname":"Donja Mahala",
    "gn:country_code":"RS",
    "gn:dem":695,
    "gn:feature_class":"P",
    "gn:feature_code":"PPL",
    "gn:name":"Donja Mahala",
    "gn:population":0,
    "gn:timezone":"Europe/Belgrade",
    "iso:country":"RS",
    "wof:name":"Donja Mahala",
    "wof:placetype":"locality"
},
  "geometry": {"coordinates":[22.01127,42.50734],"type":"Point"}
}