{
  "type": "Feature",
  "properties": {
    "iso:country":"RS",
    "name:eng_x_preferred":[
        "Blok 62"
    ],
    "name:srp_cyr_x_preferred":[
        "\u0431\u043b\u043e\u043a 62"
    ],
    "name:srp_x_preferred":[
        "\u0431\u043b\u043e\u043a 62"
    ],
    "wof:name":"Blok 62",
    "wof:placetype":"neighbourhood"
},
  "geometry": {"coordinates":[20.37626749795774,44.804439427383],"type":"Point"}
}