{
  "type": "Feature",
  "properties": {
    "gn:country":"RS",
    "gn:fcode":"PPL",
    "gn:population":5,
    "iso:country":"RS",
    "name:srp_x_preferred":[
        "Drenova\u010da"
    ],
    "qs:name":"Drenova\u010da",
    "qs:photos_9r":0,
    "qs:photos_sr":0,
    "qs:pop_sr":"1",
    "wof:name":"Drenova\u010da",
    "wof:placetype":"locality",
    "wof:population":5
},
  "geometry": {"coordinates":[20.94044,43.5435],"type":"Point"}
}