{
  "type": "Feature",
  "properties": {
    "gn:admin1_code":"SE",
    "gn:admin2_code":"24",
    "gn:asciiname":"Babina Poljana",
    "gn:country_code":"RS",
    "gn:dem":1110,
    "gn:feature_class":"P",
    "gn:feature_code":"PPL",
    "gn:name":"Babina Poljana",
    "gn:population":0,
    "gn:timezone":"Europe/Belgrade",
    "iso:country":"RS",
    "name:hrv_x_preferred":[
        "Babina Poljana"
    ],
    "name:slv_x_preferred":[
        "Babina Poljana"
    ],
    "name:srp_x_preferred":[
        "\u0411\u0430\u0431\u0438\u043d\u0430 \u041f\u043e\u0459\u0430\u043d\u0430"
    ],
    "wof:name":"Babina Poljana",
    "wof:placetype":"locality"
},
  "geometry": {"coordinates":[22.18398,42.51117],"type":"Point"}
}