{
  "type": "Feature",
  "properties": {
    "gn:admin1_code":"SE",
    "gn:admin2_code":"24",
    "gn:asciiname":"Gruinci",
    "gn:country_code":"RS",
    "gn:dem":1315,
    "gn:feature_class":"P",
    "gn:feature_code":"PPL",
    "gn:name":"Gruinci",
    "gn:population":0,
    "gn:timezone":"Europe/Belgrade",
    "iso:country":"RS",
    "name:srp_x_preferred":[
        "Gruinci"
    ],
    "name:und_x_variant":[
        "Ko\u010danska Mahala"
    ],
    "wof:name":"Gruinci",
    "wof:placetype":"locality"
},
  "geometry": {"coordinates":[22.22552,42.45685],"type":"Point"}
}