{
  "type": "Feature",
  "properties": {
    "gn:admin1_code":"SE",
    "gn:admin2_code":"10",
    "gn:asciiname":"Osipaonica",
    "gn:country_code":"RS",
    "gn:dem":83,
    "gn:feature_class":"P",
    "gn:feature_code":"PPL",
    "gn:name":"Osipaonica",
    "gn:population":0,
    "gn:timezone":"Europe/Belgrade",
    "iso:country":"RS",
    "name:srp_x_preferred":[
        "Osipaonica"
    ],
    "wof:name":"Osipaonica",
    "wof:placetype":"locality"
},
  "geometry": {"coordinates":[21.05479,44.54608],"type":"Point"}
}