{
  "type": "Feature",
  "properties": {
    "gn:admin1_code":"SE",
    "gn:admin2_code":"24",
    "gn:asciiname":"Bogdanova Mahala",
    "gn:country_code":"RS",
    "gn:dem":1241,
    "gn:feature_class":"P",
    "gn:feature_code":"PPL",
    "gn:name":"Bogdanova Mahala",
    "gn:population":0,
    "gn:timezone":"Europe/Belgrade",
    "iso:country":"RS",
    "wof:name":"Bogdanova Mahala",
    "wof:placetype":"locality"
},
  "geometry": {"coordinates":[22.3156,42.66845],"type":"Point"}
}