{
  "type": "Feature",
  "properties": {
    "gn:admin1_code":"SE",
    "gn:admin2_code":"8",
    "gn:asciiname":"Citluk",
    "gn:country_code":"RS",
    "gn:dem":380,
    "gn:feature_class":"P",
    "gn:feature_code":"PPLL",
    "gn:name":"\u010citluk",
    "gn:population":0,
    "gn:timezone":"Europe/Belgrade",
    "iso:country":"RS",
    "name:srp_x_preferred":[
        "\u010citluk"
    ],
    "wof:name":"Citluk",
    "wof:placetype":"locality"
},
  "geometry": {"coordinates":[19.37273,44.21407],"type":"Point"}
}