{
  "type": "Feature",
  "properties": {
    "gn:admin1_code":"SE",
    "gn:admin2_code":"18",
    "gn:asciiname":"Gornji Crnis",
    "gn:country_code":"RS",
    "gn:dem":1278,
    "gn:feature_class":"P",
    "gn:feature_code":"PPLL",
    "gn:name":"Gornji Crni\u0161",
    "gn:population":0,
    "gn:timezone":"Europe/Belgrade",
    "iso:country":"RS",
    "name:fra_x_preferred":[
        "Gornji Crni\u0161"
    ],
    "name:hun_x_preferred":[
        "Gornji Crni\u0161"
    ],
    "name:msa_x_preferred":[
        "Gornji Crni\u0161"
    ],
    "name:nld_x_preferred":[
        "Gornji Crni\u0161"
    ],
    "name:por_x_preferred":[
        "Gornji Crni\u0161"
    ],
    "name:slv_x_preferred":[
        "Gornji Crni\u0161"
    ],
    "name:srp_x_preferred":[
        "Gornji Crni\u0161"
    ],
    "name:srp_x_variant":[
        "\u0413\u043e\u0440\u045a\u0438 \u0426\u0440\u043d\u0438\u0448"
    ],
    "wof:name":"Gornji Crnis",
    "wof:placetype":"locality"
},
  "geometry": {"coordinates":[20.4193,42.97952],"type":"Point"}
}