{
  "type": "Feature",
  "properties": {
    "gn:admin1_code":"SE",
    "gn:admin2_code":"21",
    "gn:asciiname":"Kutlovac",
    "gn:country_code":"RS",
    "gn:dem":478,
    "gn:feature_class":"P",
    "gn:feature_code":"PPL",
    "gn:name":"Kutlovac",
    "gn:population":0,
    "gn:timezone":"Europe/Belgrade",
    "iso:country":"RS",
    "name:ceb_x_preferred":[
        "Kutlovac"
    ],
    "name:fra_x_preferred":[
        "Kutlovac"
    ],
    "name:msa_x_preferred":[
        "Kutlovac"
    ],
    "name:por_x_preferred":[
        "Kutlovac"
    ],
    "name:slv_x_preferred":[
        "Kutlovac"
    ],
    "name:sqi_x_preferred":[
        "Kutlloci"
    ],
    "name:srp_x_preferred":[
        "Kutlovac"
    ],
    "name:srp_x_variant":[
        "\u041a\u0443\u0442\u043b\u043e\u0432\u0430\u0446"
    ],
    "wof:name":"Kutlovac",
    "wof:placetype":"locality"
},
  "geometry": {"coordinates":[21.24028,43.24778],"type":"Point"}
}