{
  "type": "Feature",
  "properties": {
    "gn:admin1_code":"SE",
    "gn:admin2_code":"21",
    "gn:asciiname":"Kutlovac",
    "gn:country_code":"RS",
    "gn:dem":478,
    "gn:feature_class":"P",
    "gn:feature_code":"PPL",
    "gn:name":"Kutlovac",
    "gn:population":0,
    "gn:timezone":"Europe/Belgrade",
    "iso:country":"RS",
    "name:srp_x_preferred":[
        "Kutlovac"
    ],
    "wof:name":"Kutlovac",
    "wof:placetype":"locality"
},
  "geometry": {"coordinates":[21.24028,43.24778],"type":"Point"}
}