{
  "type": "Feature",
  "properties": {
    "gn:admin1_code":"SE",
    "gn:admin2_code":"23",
    "gn:asciiname":"Sisince",
    "gn:country_code":"RS",
    "gn:dem":254,
    "gn:feature_class":"P",
    "gn:feature_code":"PPL",
    "gn:name":"\u0160i\u0161ince",
    "gn:population":0,
    "gn:timezone":"Europe/Belgrade",
    "iso:country":"RS",
    "name:ceb_x_preferred":[
        "\u0160i\u0161ince"
    ],
    "name:fra_x_preferred":[
        "\u0160i\u0161ince"
    ],
    "name:msa_x_preferred":[
        "\u0160i\u0161ince"
    ],
    "name:por_x_preferred":[
        "\u0160i\u0161ince"
    ],
    "name:slv_x_preferred":[
        "\u0160i\u0161ince"
    ],
    "name:sqi_x_preferred":[
        "Shishinca"
    ],
    "name:srp_x_preferred":[
        "\u0160i\u0161ince"
    ],
    "name:srp_x_variant":[
        "\u0428\u0438\u0448\u0438\u043d\u0446\u0435"
    ],
    "wof:name":"Sisince",
    "wof:placetype":"locality"
},
  "geometry": {"coordinates":[21.91814,42.95888],"type":"Point"}
}