{
  "type": "Feature",
  "properties": {
    "gn:admin1_code":"SE",
    "gn:admin2_code":"24",
    "gn:asciiname":"Bliznaci",
    "gn:country_code":"RS",
    "gn:dem":1237,
    "gn:feature_class":"P",
    "gn:feature_code":"PPL",
    "gn:name":"Bliznaci",
    "gn:population":0,
    "gn:timezone":"Europe/Belgrade",
    "iso:country":"RS",
    "wof:name":"Bliznaci",
    "wof:placetype":"locality"
},
  "geometry": {"coordinates":[22.28045,42.70147],"type":"Point"}
}