{
  "type": "Feature",
  "properties": {
    "gn:country":"RS",
    "gn:fcode":"PPL",
    "gn:pop":406,
    "iso:country":"RS",
    "name:deu_x_preferred":[
        "\u0160urjan"
    ],
    "name:eng_x_preferred":[
        "\u0160urjan"
    ],
    "name:epo_x_preferred":[
        "\u015curjan"
    ],
    "name:fra_x_preferred":[
        "\u0160urjan"
    ],
    "name:hrv_x_preferred":[
        "\u0160urjan"
    ],
    "name:hun_x_preferred":[
        "Surj\u00e1n"
    ],
    "name:msa_x_preferred":[
        "\u0160urjan"
    ],
    "name:nld_x_preferred":[
        "\u0160urjan"
    ],
    "name:ron_x_preferred":[
        "\u0160urjan"
    ],
    "name:slv_x_preferred":[
        "\u0160urjan"
    ],
    "name:srp_x_preferred":[
        "\u0160urjan"
    ],
    "name:unk_x_variant":[
        "Surj\u00e1n"
    ],
    "qs:name":"\u0160urjan",
    "qs:photos_9r":0,
    "qs:photos_sr":0,
    "qs:pop_sr":"2",
    "wd:elevation":82.0,
    "wd:wordcount":102,
    "wof:name":"\u0160urjan",
    "wof:placetype":"locality",
    "wof:population":406
},
  "geometry": {"coordinates":[20.87474,45.39956],"type":"Point"}
}