{
  "type": "Feature",
  "properties": {
    "gn:admin1_code":"SE",
    "gn:admin2_code":"8",
    "gn:asciiname":"Bobovik",
    "gn:country_code":"RS",
    "gn:dem":118,
    "gn:feature_class":"P",
    "gn:feature_code":"PPL",
    "gn:name":"Bobovik",
    "gn:population":0,
    "gn:timezone":"Europe/Belgrade",
    "iso:country":"RS",
    "name:ceb_x_preferred":[
        "Bobovik"
    ],
    "name:fra_x_preferred":[
        "Bobovik"
    ],
    "name:msa_x_preferred":[
        "Bobovik"
    ],
    "name:nld_x_preferred":[
        "Bobovik"
    ],
    "name:por_x_preferred":[
        "Bobovik"
    ],
    "name:slv_x_preferred":[
        "Bobovik"
    ],
    "name:srp_x_preferred":[
        "\u0411\u043e\u0431\u043e\u0432\u0438\u043a"
    ],
    "name:srp_x_variant":[
        "\u0411\u043e\u0431\u043e\u0432\u0438\u043a"
    ],
    "wof:name":"Bobovik",
    "wof:placetype":"locality"
},
  "geometry": {"coordinates":[19.79611,44.62361],"type":"Point"}
}