{
  "type": "Feature",
  "properties": {
    "gn:admin1_code":"SE",
    "gn:admin2_code":"23",
    "gn:asciiname":"Milanovo",
    "gn:country_code":"RS",
    "gn:dem":261,
    "gn:feature_class":"P",
    "gn:feature_code":"PPL",
    "gn:name":"Milanovo",
    "gn:population":0,
    "gn:timezone":"Europe/Belgrade",
    "iso:country":"RS",
    "name:bul_x_preferred":[
        "\u041c\u0438\u043b\u0430\u043d\u043e\u0432\u043e"
    ],
    "name:ceb_x_preferred":[
        "Milanovo"
    ],
    "name:fra_x_preferred":[
        "Milanovo"
    ],
    "name:hrv_x_preferred":[
        "Milanovo"
    ],
    "name:ron_x_preferred":[
        "Milanovo"
    ],
    "name:rus_x_preferred":[
        "\u041c\u0438\u043b\u0430\u043d\u043e\u0432\u043e"
    ],
    "name:slv_x_preferred":[
        "Milanovo"
    ],
    "name:srp_x_preferred":[
        "Milanovo"
    ],
    "name:srp_x_variant":[
        "\u041c\u0438\u043b\u0430\u043d\u043e\u0432\u043e"
    ],
    "name:swe_x_preferred":[
        "Milanovo"
    ],
    "name:ukr_x_preferred":[
        "\u041c\u0438\u043b\u0430\u043d\u043e\u0432\u043e"
    ],
    "wof:name":"Milanovo",
    "wof:placetype":"locality"
},
  "geometry": {"coordinates":[21.86936,43.01752000000001],"type":"Point"}
}