{
  "type": "Feature",
  "properties": {
    "iso:country":"RS",
    "name:eng_x_preferred":[
        "Centar I"
    ],
    "name:srp_cyr_x_preferred":[
        "\u0426\u0435\u043d\u0442\u0430\u0440 \u0399"
    ],
    "name:srp_x_preferred":[
        "\u0426\u0435\u043d\u0442\u0430\u0440 \u0399"
    ],
    "wof:name":"Centar I",
    "wof:placetype":"neighbourhood"
},
  "geometry": {"coordinates":[20.4609903812968,44.87147114649813],"type":"Point"}
}