{
  "type": "Feature",
  "properties": {
    "gn:admin1_code":"SE",
    "gn:admin2_code":"13",
    "gn:asciiname":"Dragocvet",
    "gn:country_code":"RS",
    "gn:dem":141,
    "gn:feature_class":"P",
    "gn:feature_code":"PPL",
    "gn:name":"Dragocvet",
    "gn:population":0,
    "gn:timezone":"Europe/Belgrade",
    "iso:country":"RS",
    "name:srp_x_preferred":[
        "Dragocvet"
    ],
    "wof:name":"Dragocvet",
    "wof:placetype":"locality"
},
  "geometry": {"coordinates":[21.21394,43.94035],"type":"Point"}
}