{
  "type": "Feature",
  "properties": {
    "gn:admin1_code":"SE",
    "gn:admin2_code":"13",
    "gn:asciiname":"Dragocvet",
    "gn:country_code":"RS",
    "gn:dem":141,
    "gn:feature_class":"P",
    "gn:feature_code":"PPL",
    "gn:name":"Dragocvet",
    "gn:population":0,
    "gn:timezone":"Europe/Belgrade",
    "iso:country":"RS",
    "name:ceb_x_preferred":[
        "Dragocvet"
    ],
    "name:fas_x_preferred":[
        "\u062f\u0631\u0627\u06af\u0648\u062a\u0633\u0648\u062a"
    ],
    "name:fra_x_preferred":[
        "Dragocvet"
    ],
    "name:msa_x_preferred":[
        "Dragocvet"
    ],
    "name:por_x_preferred":[
        "Dragocvet"
    ],
    "name:slv_x_preferred":[
        "Dragocvet"
    ],
    "name:srp_x_preferred":[
        "Dragocvet"
    ],
    "name:srp_x_variant":[
        "\u0414\u0440\u0430\u0433\u043e\u0446\u0432\u0435\u0442"
    ],
    "wof:name":"Dragocvet",
    "wof:placetype":"locality"
},
  "geometry": {"coordinates":[21.21394,43.94035],"type":"Point"}
}