{
  "type": "Feature",
  "properties": {
    "gn:admin1_code":"SE",
    "gn:admin2_code":"8",
    "gn:asciiname":"Celije",
    "gn:country_code":"RS",
    "gn:dem":143,
    "gn:feature_class":"P",
    "gn:feature_code":"PPL",
    "gn:name":"\u010celije",
    "gn:population":0,
    "gn:timezone":"Europe/Belgrade",
    "iso:country":"RS",
    "wof:name":"Celije",
    "wof:placetype":"locality"
},
  "geometry": {"coordinates":[19.81972,44.59],"type":"Point"}
}