{
  "type": "Feature",
  "properties": {
    "gn:admin1_code":"SE",
    "gn:admin2_code":"16",
    "gn:asciiname":"Drenova",
    "gn:country_code":"RS",
    "gn:dem":869,
    "gn:feature_class":"P",
    "gn:feature_code":"PPL",
    "gn:name":"Drenova",
    "gn:population":0,
    "gn:timezone":"Europe/Belgrade",
    "iso:country":"RS",
    "name:srp_x_preferred":[
        "Drenova"
    ],
    "name:und_x_variant":[
        "Drenovo"
    ],
    "wof:name":"Drenova",
    "wof:placetype":"locality"
},
  "geometry": {"coordinates":[19.83923,43.64773],"type":"Point"}
}