{
  "type": "Feature",
  "properties": {
    "gn:admin1_code":"SE",
    "gn:admin2_code":"11",
    "gn:admin3_code":"70807.0",
    "gn:asciiname":"Malo Crnice",
    "gn:country_code":"RS",
    "gn:dem":85,
    "gn:feature_class":"P",
    "gn:feature_code":"PPLA3",
    "gn:name":"Malo Crni\u0107e",
    "gn:population":0,
    "gn:timezone":"Europe/Belgrade",
    "iso:country":"RS",
    "name:fra_x_preferred":[
        "Malo Crni\u0107e"
    ],
    "name:hrv_x_preferred":[
        "Malo Crni\u0107e"
    ],
    "name:ita_x_preferred":[
        "Malo Crni\u0107e"
    ],
    "name:msa_x_preferred":[
        "Malo Crni\u0107e"
    ],
    "name:nld_x_preferred":[
        "Malo Crni\u0107e"
    ],
    "name:pnb_x_preferred":[
        "\u0645\u0627\u0644\u0648 \u0686\u0631\u0646\u06cc\u0633\u06d2"
    ],
    "name:por_x_preferred":[
        "Malo Crni\u0107e"
    ],
    "name:slv_x_preferred":[
        "Malo Crni\u0107e"
    ],
    "name:spa_x_preferred":[
        "Malo Crni\u0107e"
    ],
    "name:srp_x_preferred":[
        "Malo Crni\u0107e"
    ],
    "name:srp_x_variant":[
        "\u041c\u0430\u043b\u043e \u0426\u0440\u043d\u0438\u045b\u0435"
    ],
    "name:tur_x_preferred":[
        "Malo Crni\u0107e"
    ],
    "name:und_x_variant":[
        "Malo Crnu\u0107e"
    ],
    "wof:name":"Malo Crnice",
    "wof:placetype":"locality"
},
  "geometry": {"coordinates":[21.28556,44.55611],"type":"Point"}
}