{
  "type": "Feature",
  "properties": {
    "gn:admin1_code":"SE",
    "gn:admin2_code":"17",
    "gn:asciiname":"Donja Bresnica",
    "gn:country_code":"RS",
    "gn:dem":241,
    "gn:feature_class":"P",
    "gn:feature_code":"PPL",
    "gn:name":"Donja Bresnica",
    "gn:population":0,
    "gn:timezone":"Europe/Belgrade",
    "iso:country":"RS",
    "name:ceb_x_preferred":[
        "Donja Bresnica"
    ],
    "name:fra_x_preferred":[
        "Donja Bresnica"
    ],
    "name:msa_x_preferred":[
        "Donja Bresnica"
    ],
    "name:por_x_preferred":[
        "Donja Bresnica"
    ],
    "name:slv_x_preferred":[
        "Donja Bresnica"
    ],
    "name:sqi_x_preferred":[
        "Breznica e Poshtme"
    ],
    "name:srp_x_preferred":[
        "\u0414\u043e\u045a\u0430 \u0411\u0440\u0435\u0441\u043d\u0438\u0446\u0430"
    ],
    "wof:name":"Donja Bresnica",
    "wof:placetype":"locality"
},
  "geometry": {"coordinates":[20.59261,43.86635],"type":"Point"}
}