{
  "type": "Feature",
  "properties": {
    "gn:admin1_code":"SE",
    "gn:admin2_code":"16",
    "gn:asciiname":"Vukotici",
    "gn:country_code":"RS",
    "gn:dem":902,
    "gn:feature_class":"P",
    "gn:feature_code":"PPL",
    "gn:name":"Vukoti\u0107i",
    "gn:population":0,
    "gn:timezone":"Europe/Belgrade",
    "iso:country":"RS",
    "wof:name":"Vukotici",
    "wof:placetype":"locality"
},
  "geometry": {"coordinates":[19.97667,43.62778],"type":"Point"}
}