{
  "type": "Feature",
  "properties": {
    "gn:admin1_code":"SE",
    "gn:admin2_code":"17",
    "gn:asciiname":"Varjace",
    "gn:country_code":"RS",
    "gn:dem":601,
    "gn:feature_class":"P",
    "gn:feature_code":"PPL",
    "gn:name":"Varja\u010de",
    "gn:population":0,
    "gn:timezone":"Europe/Belgrade",
    "iso:country":"RS",
    "name:srp_x_preferred":[
        "Varja\u010de"
    ],
    "wof:name":"Varjace",
    "wof:placetype":"locality"
},
  "geometry": {"coordinates":[20.15375,43.61421],"type":"Point"}
}