{
  "type": "Feature",
  "properties": {
    "gn:admin1_code":"SE",
    "gn:admin2_code":"10",
    "gn:asciiname":"Mala Krsna",
    "gn:country_code":"RS",
    "gn:dem":81,
    "gn:feature_class":"P",
    "gn:feature_code":"PPL",
    "gn:name":"Mala Krsna",
    "gn:population":0,
    "gn:timezone":"Europe/Belgrade",
    "iso:country":"RS",
    "name:ceb_x_preferred":[
        "Mala Krsna"
    ],
    "name:ces_x_preferred":[
        "Mala Krsna"
    ],
    "name:fra_x_preferred":[
        "Mala Krsna"
    ],
    "name:msa_x_preferred":[
        "Mala Krsna"
    ],
    "name:por_x_preferred":[
        "Mala Krsna"
    ],
    "name:slv_x_preferred":[
        "Mala Krsna"
    ],
    "name:srp_x_preferred":[
        "Mala Krsna"
    ],
    "name:srp_x_variant":[
        "\u041c\u0430\u043b\u0430 \u041a\u0440\u0441\u043d\u0430"
    ],
    "wof:name":"Mala Krsna",
    "wof:placetype":"locality"
},
  "geometry": {"coordinates":[21.00744,44.58617],"type":"Point"}
}