{
  "type": "Feature",
  "properties": {
    "gn:admin1_code":"SE",
    "gn:admin2_code":"19",
    "gn:asciiname":"Garevina",
    "gn:country_code":"RS",
    "gn:dem":239,
    "gn:feature_class":"P",
    "gn:feature_code":"PPL",
    "gn:name":"Garevina",
    "gn:population":0,
    "gn:timezone":"Europe/Belgrade",
    "iso:country":"RS",
    "name:srp_x_preferred":[
        "Garevina"
    ],
    "wof:name":"Garevina",
    "wof:placetype":"locality"
},
  "geometry": {"coordinates":[21.18046,43.46072],"type":"Point"}
}