{
  "type": "Feature",
  "properties": {
    "gn:admin1_code":"SE",
    "gn:admin2_code":"19",
    "gn:asciiname":"Garevina",
    "gn:country_code":"RS",
    "gn:dem":239,
    "gn:feature_class":"P",
    "gn:feature_code":"PPL",
    "gn:name":"Garevina",
    "gn:population":0,
    "gn:timezone":"Europe/Belgrade",
    "iso:country":"RS",
    "name:fra_x_preferred":[
        "Garevina"
    ],
    "name:hye_x_preferred":[
        "\u0533\u0561\u0580\u0587\u056b\u0576\u0561"
    ],
    "name:msa_x_preferred":[
        "Garevina"
    ],
    "name:por_x_preferred":[
        "Garevina"
    ],
    "name:slv_x_preferred":[
        "Garevina"
    ],
    "name:spa_x_preferred":[
        "Garevina"
    ],
    "name:srp_x_preferred":[
        "Garevina"
    ],
    "name:srp_x_variant":[
        "\u0413\u0430\u0440\u0435\u0432\u0438\u043d\u0430"
    ],
    "wof:name":"Garevina",
    "wof:placetype":"locality"
},
  "geometry": {"coordinates":[21.18046,43.46072],"type":"Point"}
}