{
  "type": "Feature",
  "properties": {
    "gn:admin1_code":"SE",
    "gn:admin2_code":"23",
    "gn:asciiname":"Zivkovo",
    "gn:country_code":"RS",
    "gn:dem":234,
    "gn:feature_class":"P",
    "gn:feature_code":"PPL",
    "gn:name":"\u017divkovo",
    "gn:population":0,
    "gn:timezone":"Europe/Belgrade",
    "iso:country":"RS",
    "name:ceb_x_preferred":[
        "\u017divkovo"
    ],
    "name:fra_x_preferred":[
        "\u017divkovo"
    ],
    "name:msa_x_preferred":[
        "\u017divkovo"
    ],
    "name:por_x_preferred":[
        "\u017divkovo"
    ],
    "name:slv_x_preferred":[
        "\u017divkovo"
    ],
    "name:srp_x_preferred":[
        "\u017divkovo"
    ],
    "name:srp_x_variant":[
        "\u0416\u0438\u0432\u043a\u043e\u0432\u043e"
    ],
    "wof:name":"Zivkovo",
    "wof:placetype":"locality"
},
  "geometry": {"coordinates":[21.93539,43.07448],"type":"Point"}
}