{
  "type": "Feature",
  "properties": {
    "gn:admin1_code":"SE",
    "gn:admin2_code":"23",
    "gn:asciiname":"Zivkovo",
    "gn:country_code":"RS",
    "gn:dem":234,
    "gn:feature_class":"P",
    "gn:feature_code":"PPL",
    "gn:name":"\u017divkovo",
    "gn:population":0,
    "gn:timezone":"Europe/Belgrade",
    "iso:country":"RS",
    "name:srp_x_preferred":[
        "\u017divkovo"
    ],
    "wof:name":"Zivkovo",
    "wof:placetype":"locality"
},
  "geometry": {"coordinates":[21.93539,43.07448],"type":"Point"}
}