{
  "type": "Feature",
  "properties": {
    "gn:admin1_code":"SE",
    "gn:admin2_code":"8",
    "gn:asciiname":"Zukve",
    "gn:country_code":"RS",
    "gn:dem":202,
    "gn:feature_class":"P",
    "gn:feature_code":"PPL",
    "gn:name":"Zukve",
    "gn:population":0,
    "gn:timezone":"Europe/Belgrade",
    "iso:country":"RS",
    "name:srp_x_preferred":[
        "Zukve"
    ],
    "wof:name":"Zukve",
    "wof:placetype":"locality"
},
  "geometry": {"coordinates":[19.85267,44.47219000000001],"type":"Point"}
}