{
  "type": "Feature",
  "properties": {
    "gn:admin1_code":"SE",
    "gn:admin2_code":"10",
    "gn:asciiname":"Pocevica",
    "gn:country_code":"RS",
    "gn:dem":146,
    "gn:feature_class":"P",
    "gn:feature_code":"PPLL",
    "gn:name":"Po\u010devica",
    "gn:population":0,
    "gn:timezone":"Europe/Belgrade",
    "iso:country":"RS",
    "name:srp_x_preferred":[
        "Po\u010devica"
    ],
    "wof:name":"Pocevica",
    "wof:placetype":"locality"
},
  "geometry": {"coordinates":[20.84644,44.38367],"type":"Point"}
}