{
  "type": "Feature",
  "properties": {
    "gn:admin1_code":"SE",
    "gn:admin2_code":"19",
    "gn:asciiname":"Vencac",
    "gn:country_code":"RS",
    "gn:dem":325,
    "gn:feature_class":"P",
    "gn:feature_code":"PPL",
    "gn:name":"Ven\u010dac",
    "gn:population":0,
    "gn:timezone":"Europe/Belgrade",
    "iso:country":"RS",
    "name:rus_x_preferred":[
        "\u0412\u0435\u043d\u0447\u0430\u0446"
    ],
    "name:srp_x_preferred":[
        "Ven\u010dac"
    ],
    "name:srp_x_variant":[
        "\u0412\u0435\u043d\u0447\u0430\u0446"
    ],
    "wof:name":"Vencac",
    "wof:placetype":"locality"
},
  "geometry": {"coordinates":[21.10647,43.44614],"type":"Point"}
}