{
  "type": "Feature",
  "properties": {
    "gn:admin1_code":"SE",
    "gn:admin2_code":"8",
    "gn:asciiname":"Ciganlija",
    "gn:country_code":"RS",
    "gn:dem":85,
    "gn:feature_class":"P",
    "gn:feature_code":"PPL",
    "gn:name":"Ciganlija",
    "gn:population":0,
    "gn:timezone":"Europe/Belgrade",
    "iso:country":"RS",
    "name:srp_x_preferred":[
        "Ciganlija"
    ],
    "wof:name":"Ciganlija",
    "wof:placetype":"locality"
},
  "geometry": {"coordinates":[19.43413,44.79728],"type":"Point"}
}