{
  "type": "Feature",
  "properties": {
    "gn:admin1_code":"SE",
    "gn:admin2_code":"17",
    "gn:asciiname":"Nevade",
    "gn:country_code":"RS",
    "gn:dem":362,
    "gn:feature_class":"P",
    "gn:feature_code":"PPL",
    "gn:name":"Nevade",
    "gn:population":0,
    "gn:timezone":"Europe/Belgrade",
    "iso:country":"RS",
    "name:ceb_x_preferred":[
        "Nevade"
    ],
    "name:fas_x_preferred":[
        "\u0646\u0648\u0627\u062f\u0647"
    ],
    "name:fra_x_preferred":[
        "Nevade"
    ],
    "name:msa_x_preferred":[
        "Nevade"
    ],
    "name:por_x_preferred":[
        "Nevade"
    ],
    "name:slv_x_preferred":[
        "Nevade"
    ],
    "name:srp_x_preferred":[
        "Nevade"
    ],
    "name:srp_x_variant":[
        "\u041d\u0435\u0432\u0430\u0434\u0435"
    ],
    "wof:name":"Nevade",
    "wof:placetype":"locality"
},
  "geometry": {"coordinates":[20.49621,44.04676],"type":"Point"}
}