{
  "type": "Feature",
  "properties": {
    "gn:admin1_code":"SE",
    "gn:admin2_code":"17",
    "gn:asciiname":"Nevade",
    "gn:country_code":"RS",
    "gn:dem":362,
    "gn:feature_class":"P",
    "gn:feature_code":"PPL",
    "gn:name":"Nevade",
    "gn:population":0,
    "gn:timezone":"Europe/Belgrade",
    "iso:country":"RS",
    "name:srp_x_preferred":[
        "Nevade"
    ],
    "wof:name":"Nevade",
    "wof:placetype":"locality"
},
  "geometry": {"coordinates":[20.49621,44.04676],"type":"Point"}
}