{
  "type": "Feature",
  "properties": {
    "gn:admin1_code":"SE",
    "gn:admin2_code":"8",
    "gn:asciiname":"Boljavina",
    "gn:country_code":"RS",
    "gn:dem":380,
    "gn:feature_class":"P",
    "gn:feature_code":"PPLL",
    "gn:name":"Boljavina",
    "gn:population":0,
    "gn:timezone":"Europe/Belgrade",
    "iso:country":"RS",
    "name:srp_x_preferred":[
        "Boljavina"
    ],
    "wof:name":"Boljavina",
    "wof:placetype":"locality"
},
  "geometry": {"coordinates":[19.41148,44.23177],"type":"Point"}
}