{
  "type": "Feature",
  "properties": {
    "gn:admin1_code":"SE",
    "gn:admin2_code":"16",
    "gn:asciiname":"Barice",
    "gn:country_code":"RS",
    "gn:dem":1108,
    "gn:feature_class":"P",
    "gn:feature_code":"PPL",
    "gn:name":"Barice",
    "gn:population":0,
    "gn:timezone":"Europe/Belgrade",
    "iso:country":"RS",
    "name:srp_x_preferred":[
        "Barice"
    ],
    "wof:name":"Barice",
    "wof:placetype":"locality"
},
  "geometry": {"coordinates":[19.58109,43.40968],"type":"Point"}
}