{
  "type": "Feature",
  "properties": {
    "gn:admin1_code":"SE",
    "gn:admin2_code":"15",
    "gn:asciiname":"Potrkanje",
    "gn:country_code":"RS",
    "gn:dem":252,
    "gn:feature_class":"P",
    "gn:feature_code":"PPL",
    "gn:name":"Potrkanje",
    "gn:population":0,
    "gn:timezone":"Europe/Belgrade",
    "iso:country":"RS",
    "name:srp_x_preferred":[
        "Potrkanje"
    ],
    "wof:name":"Potrkanje",
    "wof:placetype":"locality"
},
  "geometry": {"coordinates":[22.25482,43.62683],"type":"Point"}
}