{
  "type": "Feature",
  "properties": {
    "gn:admin1_code":"SE",
    "gn:admin2_code":"8",
    "gn:asciiname":"Dovraski Sor",
    "gn:country_code":"RS",
    "gn:dem":89,
    "gn:feature_class":"P",
    "gn:feature_code":"PPL",
    "gn:name":"Dovraski \u0160or",
    "gn:population":0,
    "gn:timezone":"Europe/Belgrade",
    "iso:country":"RS",
    "name:srp_x_preferred":[
        "Dovraski \u0160or"
    ],
    "wof:name":"Dovraski Sor",
    "wof:placetype":"locality"
},
  "geometry": {"coordinates":[19.45684,44.74598],"type":"Point"}
}