{
  "type": "Feature",
  "properties": {
    "gn:admin1_code":"SE",
    "gn:admin2_code":"17",
    "gn:asciiname":"Krdzici",
    "gn:country_code":"RS",
    "gn:dem":722,
    "gn:feature_class":"P",
    "gn:feature_code":"PPL",
    "gn:name":"Krd\u017ei\u0107i",
    "gn:population":0,
    "gn:timezone":"Europe/Belgrade",
    "iso:country":"RS",
    "name:srp_x_preferred":[
        "Krd\u017ei\u0107i"
    ],
    "wof:name":"Krdzici",
    "wof:placetype":"locality"
},
  "geometry": {"coordinates":[20.3075,43.64111],"type":"Point"}
}