{
  "type": "Feature",
  "properties": {
    "gn:admin1_code":"SE",
    "gn:admin2_code":"21",
    "gn:asciiname":"Pasjaca",
    "gn:country_code":"RS",
    "gn:dem":878,
    "gn:feature_class":"P",
    "gn:feature_code":"PPL",
    "gn:name":"Pasja\u010da",
    "gn:population":0,
    "gn:timezone":"Europe/Belgrade",
    "iso:country":"RS",
    "name:srp_x_preferred":[
        "Pasja\u010da"
    ],
    "wof:name":"Pasjaca",
    "wof:placetype":"locality"
},
  "geometry": {"coordinates":[21.62227,43.1408],"type":"Point"}
}