{
  "type": "Feature",
  "properties": {
    "gn:admin1_code":"SE",
    "gn:admin2_code":"16",
    "gn:asciiname":"Bosnjaci",
    "gn:country_code":"RS",
    "gn:dem":434,
    "gn:feature_class":"P",
    "gn:feature_code":"PPL",
    "gn:name":"Bo\u0161njaci",
    "gn:population":0,
    "gn:timezone":"Europe/Belgrade",
    "iso:country":"RS",
    "name:srp_x_preferred":[
        "Bo\u0161njaci"
    ],
    "wof:name":"Bosnjaci",
    "wof:placetype":"locality"
},
  "geometry": {"coordinates":[19.97918,43.8984],"type":"Point"}
}