{
  "type": "Feature",
  "properties": {
    "gn:admin1_code":"VO",
    "gn:admin2_code":"5",
    "gn:asciiname":"Mali Stapar",
    "gn:country_code":"RS",
    "gn:dem":84,
    "gn:feature_class":"P",
    "gn:feature_code":"PPL",
    "gn:name":"Mali Stapar",
    "gn:population":0,
    "gn:timezone":"Europe/Belgrade",
    "iso:country":"RS",
    "name:srp_x_preferred":[
        "Mali Stapar"
    ],
    "wof:name":"Mali Stapar",
    "wof:placetype":"locality"
},
  "geometry": {"coordinates":[19.32157,45.69946],"type":"Point"}
}