{
  "type": "Feature",
  "properties": {
    "gn:admin1_code":"SE",
    "gn:admin2_code":"24",
    "gn:asciiname":"Kumicina Mahala",
    "gn:country_code":"RS",
    "gn:dem":1164,
    "gn:feature_class":"P",
    "gn:feature_code":"PPL",
    "gn:name":"Kumi\u010dina Mahala",
    "gn:population":0,
    "gn:timezone":"Europe/Belgrade",
    "iso:country":"RS",
    "name:srp_x_preferred":[
        "Kumi\u010dina Mahala"
    ],
    "wof:name":"Kumicina Mahala",
    "wof:placetype":"locality"
},
  "geometry": {"coordinates":[22.34697,42.5824],"type":"Point"}
}