{
  "type": "Feature",
  "properties": {
    "gn:country":"RS",
    "gn:fcode":"PPL",
    "gn:pop":409,
    "iso:country":"RS",
    "name:dut_x_preferred":[
        "Sena"
    ],
    "name:eng_x_preferred":[
        "Sena"
    ],
    "name:fre_x_preferred":[
        "Sena"
    ],
    "name:may_x_preferred":[
        "Sena"
    ],
    "name:por_x_preferred":[
        "Sena"
    ],
    "name:slv_x_preferred":[
        "Sena"
    ],
    "name:srp_x_preferred":[
        "Sena"
    ],
    "qs:name":"Sena",
    "qs:photos_9r":0,
    "qs:photos_sr":0,
    "qs:pop_sr":"2",
    "wd:wordcount":150,
    "wof:name":"Sena",
    "wof:placetype":"locality",
    "wof:population":409
},
  "geometry": {"coordinates":[21.60387,44.5205],"type":"Point"}
}