{
  "type": "Feature",
  "properties": {
    "gn:admin1_code":"SE",
    "gn:admin2_code":"19",
    "gn:asciiname":"Bosicane",
    "gn:country_code":"RS",
    "gn:dem":245,
    "gn:feature_class":"P",
    "gn:feature_code":"PPL",
    "gn:name":"Bosi\u010dane",
    "gn:population":0,
    "gn:timezone":"Europe/Belgrade",
    "iso:country":"RS",
    "name:srp_x_preferred":[
        "Bosi\u010dane"
    ],
    "wof:name":"Bosicane",
    "wof:placetype":"locality"
},
  "geometry": {"coordinates":[21.20043,43.42359],"type":"Point"}
}