{
  "type": "Feature",
  "properties": {
    "gn:admin1_code":"SE",
    "gn:admin2_code":"24",
    "gn:asciiname":"Drajcina Mahala",
    "gn:country_code":"RS",
    "gn:dem":1217,
    "gn:feature_class":"P",
    "gn:feature_code":"PPL",
    "gn:name":"Draj\u010dina Mahala",
    "gn:population":0,
    "gn:timezone":"Europe/Belgrade",
    "iso:country":"RS",
    "wof:name":"Drajcina Mahala",
    "wof:placetype":"locality"
},
  "geometry": {"coordinates":[22.3965,42.59833],"type":"Point"}
}