{
  "type": "Feature",
  "properties": {
    "gn:admin1_code":"SE",
    "gn:admin2_code":"19",
    "gn:asciiname":"Magovo",
    "gn:country_code":"RS",
    "gn:dem":739,
    "gn:feature_class":"P",
    "gn:feature_code":"PPL",
    "gn:name":"Magovo",
    "gn:population":0,
    "gn:timezone":"Europe/Belgrade",
    "iso:country":"RS",
    "name:bul_x_preferred":[
        "\u041c\u0430\u0433\u043e\u0432\u043e"
    ],
    "name:fra_x_preferred":[
        "Magovo"
    ],
    "name:msa_x_preferred":[
        "Magovo"
    ],
    "name:por_x_preferred":[
        "Magovo"
    ],
    "name:slv_x_preferred":[
        "Magovo"
    ],
    "name:sqi_x_preferred":[
        "Magova"
    ],
    "name:srp_x_preferred":[
        "Magovo"
    ],
    "name:srp_x_variant":[
        "\u041c\u0430\u0433\u043e\u0432\u043e"
    ],
    "wof:name":"Magovo",
    "wof:placetype":"locality"
},
  "geometry": {"coordinates":[21.05662,43.26204],"type":"Point"}
}