{
  "type": "Feature",
  "properties": {
    "gn:admin1_code":"SE",
    "gn:admin2_code":"19",
    "gn:asciiname":"Magovo",
    "gn:country_code":"RS",
    "gn:dem":739,
    "gn:feature_class":"P",
    "gn:feature_code":"PPL",
    "gn:name":"Magovo",
    "gn:population":0,
    "gn:timezone":"Europe/Belgrade",
    "iso:country":"RS",
    "name:srp_x_preferred":[
        "Magovo"
    ],
    "wof:name":"Magovo",
    "wof:placetype":"locality"
},
  "geometry": {"coordinates":[21.05662,43.26204],"type":"Point"}
}