{
  "type": "Feature",
  "properties": {
    "gn:admin1_code":"SE",
    "gn:admin2_code":"8",
    "gn:asciiname":"Vrsic",
    "gn:country_code":"RS",
    "gn:dem":504,
    "gn:feature_class":"P",
    "gn:feature_code":"PPL",
    "gn:name":"Vr\u0161i\u0107",
    "gn:population":0,
    "gn:timezone":"Europe/Belgrade",
    "iso:country":"RS",
    "name:srp_x_preferred":[
        "Vr\u0161i\u0107"
    ],
    "wof:name":"Vrsic",
    "wof:placetype":"locality"
},
  "geometry": {"coordinates":[19.46264,44.17827],"type":"Point"}
}