{
  "type": "Feature",
  "properties": {
    "gn:admin1_code":"SE",
    "gn:admin2_code":"16",
    "gn:asciiname":"Lesevici",
    "gn:country_code":"RS",
    "gn:dem":1110,
    "gn:feature_class":"P",
    "gn:feature_code":"PPL",
    "gn:name":"Le\u0161evi\u0107i",
    "gn:population":0,
    "gn:timezone":"Europe/Belgrade",
    "iso:country":"RS",
    "name:srp_x_preferred":[
        "Le\u0161evi\u0107i"
    ],
    "name:und_x_variant":[
        "Le\u0161ovi\u0107i"
    ],
    "wof:name":"Lesevici",
    "wof:placetype":"locality"
},
  "geometry": {"coordinates":[19.84985,43.52241],"type":"Point"}
}