{
  "type": "Feature",
  "properties": {
    "gn:admin1_code":"SE",
    "gn:admin2_code":"18",
    "gn:asciiname":"Mur",
    "gn:country_code":"RS",
    "gn:dem":556,
    "gn:feature_class":"P",
    "gn:feature_code":"PPL",
    "gn:name":"Mur",
    "gn:population":0,
    "gn:timezone":"Europe/Belgrade",
    "iso:country":"RS",
    "name:bel_x_preferred":[
        "\u041c\u0443\u0440"
    ],
    "name:bre_x_preferred":[
        "Mur"
    ],
    "name:bul_x_preferred":[
        "\u041c\u0443\u0440"
    ],
    "name:cat_x_preferred":[
        "Mur"
    ],
    "name:ceb_x_preferred":[
        "Mur"
    ],
    "name:dan_x_preferred":[
        "Mur"
    ],
    "name:deu_x_preferred":[
        "Mur"
    ],
    "name:eus_x_preferred":[
        "Mur"
    ],
    "name:fra_x_preferred":[
        "Mur"
    ],
    "name:heb_x_preferred":[
        "\u05de\u05d5\u05e8"
    ],
    "name:hun_x_preferred":[
        "Mur"
    ],
    "name:nld_x_preferred":[
        "Mur"
    ],
    "name:nor_x_preferred":[
        "Mur"
    ],
    "name:pol_x_preferred":[
        "Mur"
    ],
    "name:por_x_preferred":[
        "Mur"
    ],
    "name:ron_x_preferred":[
        "Mur"
    ],
    "name:rus_x_preferred":[
        "\u041c\u0443\u0440"
    ],
    "name:srp_x_preferred":[
        "Mur"
    ],
    "name:srp_x_variant":[
        "\u041c\u0443\u0440"
    ],
    "name:ukr_x_preferred":[
        "\u041c\u0443\u0440"
    ],
    "wof:name":"Mur",
    "wof:placetype":"locality"
},
  "geometry": {"coordinates":[20.48373,43.111],"type":"Point"}
}