{
  "type": "Feature",
  "properties": {
    "gn:admin1_code":"SE",
    "gn:admin2_code":"18",
    "gn:asciiname":"Mur",
    "gn:country_code":"RS",
    "gn:dem":556,
    "gn:feature_class":"P",
    "gn:feature_code":"PPL",
    "gn:name":"Mur",
    "gn:population":0,
    "gn:timezone":"Europe/Belgrade",
    "iso:country":"RS",
    "name:srp_x_preferred":[
        "Mur"
    ],
    "wof:name":"Mur",
    "wof:placetype":"locality"
},
  "geometry": {"coordinates":[20.48373,43.111],"type":"Point"}
}