{
  "type": "Feature",
  "properties": {
    "gn:country":"RS",
    "gn:fcode":"PPLL",
    "gn:pop":200,
    "iso:country":"RS",
    "name:dut_x_preferred":[
        "Dobra Voda"
    ],
    "name:eng_x_preferred":[
        "Dobra Voda"
    ],
    "name:fre_x_preferred":[
        "Dobra Voda"
    ],
    "name:may_x_preferred":[
        "Dobra Voda"
    ],
    "name:por_x_preferred":[
        "Dobra Voda"
    ],
    "name:slv_x_preferred":[
        "Dobra Voda"
    ],
    "name:srp_x_preferred":[
        "Dobra Voda"
    ],
    "qs:name":"Dobra Voda",
    "qs:photos_9r":0,
    "qs:photos_sr":0,
    "qs:pop_sr":"1",
    "wd:wordcount":128,
    "wof:name":"Dobra Voda",
    "wof:placetype":"locality",
    "wof:population":200
},
  "geometry": {"coordinates":[21.54334,43.02951],"type":"Point"}
}