{
  "type": "Feature",
  "properties": {
    "gn:country":"RS",
    "gn:fcode":"PPL",
    "gn:pop":0,
    "iso:country":"RS",
    "name:dut_x_preferred":[
        "Zjdrelo"
    ],
    "name:eng_x_preferred":[
        "\u017ddrelo"
    ],
    "name:fre_x_preferred":[
        "\u017ddrelo"
    ],
    "name:may_x_preferred":[
        "\u017ddrelo"
    ],
    "name:por_x_preferred":[
        "\u017ddrelo"
    ],
    "name:slv_x_preferred":[
        "\u017ddrelo"
    ],
    "name:srp_x_preferred":[
        "\u017ddrelo"
    ],
    "qs:name":"\u017ddrelo",
    "qs:name_adm0":"Serbia",
    "qs:name_adm1":"Branichevo",
    "qs:photos":6,
    "qs:photos_1k":1,
    "qs:photos_9k":1,
    "qs:photos_9r":1,
    "qs:photos_all":6,
    "qs:photos_sr":1,
    "qs:placetype":"Town",
    "qs:pop_sr":"0",
    "wd:wordcount":36,
    "wof:name":"\u017ddrelo",
    "wof:placetype":"locality",
    "wof:population":0
},
  "geometry": {"coordinates":[21.50376,44.29537],"type":"Point"}
}