{
  "type": "Feature",
  "properties": {
    "gn:country":"RS",
    "gn:fcode":"PPL",
    "gn:population":0,
    "iso:country":"RS",
    "name:ceb_x_preferred":[
        "\u017ddrelo"
    ],
    "name:che_x_preferred":[
        "\u0416\u0434\u0440\u0435\u043b\u043e"
    ],
    "name:eng_x_preferred":[
        "\u017ddrelo"
    ],
    "name:fas_x_preferred":[
        "\u0698\u062f\u0631\u0644\u0648"
    ],
    "name:fra_x_preferred":[
        "\u017ddrelo"
    ],
    "name:mkd_x_preferred":[
        "\u0416\u0434\u0440\u0435\u043b\u043e"
    ],
    "name:msa_x_preferred":[
        "\u017ddrelo"
    ],
    "name:nld_x_preferred":[
        "Zjdrelo"
    ],
    "name:pol_x_preferred":[
        "\u017ddrelo"
    ],
    "name:por_x_preferred":[
        "\u017ddrelo"
    ],
    "name:ron_x_preferred":[
        "\u017ddrelo"
    ],
    "name:slv_x_preferred":[
        "\u017ddrelo"
    ],
    "name:spa_x_preferred":[
        "\u017ddrelo"
    ],
    "name:srp_x_preferred":[
        "\u017ddrelo"
    ],
    "name:srp_x_variant":[
        "\u0416\u0434\u0440\u0435\u043b\u043e"
    ],
    "name:tat_x_preferred":[
        "\u0416\u0434\u0440\u0435\u043b\u043e"
    ],
    "qs:name":"\u017ddrelo",
    "qs:name_adm0":"Serbia",
    "qs:name_adm1":"Branichevo",
    "qs:photos":6,
    "qs:photos_1k":1,
    "qs:photos_9k":1,
    "qs:photos_9r":1,
    "qs:photos_all":6,
    "qs:photos_sr":1,
    "qs:placetype":"Town",
    "qs:pop_sr":"0",
    "wd:wordcount":36,
    "wof:name":"\u017ddrelo",
    "wof:placetype":"locality",
    "wof:population":0
},
  "geometry": {"coordinates":[21.50376,44.29537],"type":"Point"}
}