{
  "type": "Feature",
  "properties": {
    "gn:country":"RS",
    "gn:fcode":"PPL",
    "gn:population":1203,
    "iso:country":"RS",
    "name:arz_x_preferred":[
        "\u0627\u062f\u0648\u0631\u0686\u0627\u0646"
    ],
    "name:ceb_x_preferred":[
        "Adorjan"
    ],
    "name:eng_x_preferred":[
        "Adorjan"
    ],
    "name:epo_x_preferred":[
        "Adorjan"
    ],
    "name:fas_x_preferred":[
        "\u0627\u062f\u0648\u0631\u062c\u0627\u0646"
    ],
    "name:fra_x_preferred":[
        "Adorjan"
    ],
    "name:hun_x_preferred":[
        "Adorj\u00e1n"
    ],
    "name:msa_x_preferred":[
        "Adorjan"
    ],
    "name:nld_x_preferred":[
        "Adorjan"
    ],
    "name:pol_x_preferred":[
        "Adorjan"
    ],
    "name:ron_x_preferred":[
        "Adorjan"
    ],
    "name:rus_x_preferred":[
        "\u0410\u0434\u043e\u0440\u044f\u043d"
    ],
    "name:slv_x_preferred":[
        "Adorjan"
    ],
    "name:srp_x_preferred":[
        "Adorjan"
    ],
    "name:srp_x_variant":[
        "\u0410\u0434\u043e\u0440\u0458\u0430\u043d"
    ],
    "name:ukr_x_preferred":[
        "\u0410\u0434\u043e\u0440\u044f\u043d"
    ],
    "name:und_x_variant":[
        "Nadrljan"
    ],
    "qs:name":"Adorjan",
    "qs:photos_9r":0,
    "qs:photos_sr":0,
    "qs:pop_sr":"3",
    "wd:wordcount":72,
    "wof:name":"Adorjan",
    "wof:placetype":"locality",
    "wof:population":1203
},
  "geometry": {"coordinates":[20.04007,46.00333],"type":"Point"}
}