{
  "type": "Feature",
  "properties": {
    "gn:admin1_code":"SE",
    "gn:admin2_code":"13",
    "gn:admin3_code":"70491.0",
    "gn:asciiname":"Beljajka",
    "gn:country_code":"RS",
    "gn:dem":217,
    "gn:feature_class":"P",
    "gn:feature_code":"PPL",
    "gn:name":"Beljajka",
    "gn:population":0,
    "gn:timezone":"Europe/Belgrade",
    "iso:country":"RS",
    "name:srp_x_preferred":[
        "Beljajka"
    ],
    "wof:name":"Beljajka",
    "wof:placetype":"locality"
},
  "geometry": {"coordinates":[21.44118,44.06007],"type":"Point"}
}