{
  "type": "Feature",
  "properties": {
    "gn:admin1_code":"SE",
    "gn:admin2_code":"13",
    "gn:admin3_code":"70491.0",
    "gn:asciiname":"Beljajka",
    "gn:country_code":"RS",
    "gn:dem":217,
    "gn:feature_class":"P",
    "gn:feature_code":"PPL",
    "gn:name":"Beljajka",
    "gn:population":0,
    "gn:timezone":"Europe/Belgrade",
    "iso:country":"RS",
    "name:ceb_x_preferred":[
        "Beljajka"
    ],
    "name:fas_x_preferred":[
        "\u0628\u0644\u06cc\u0627\u06cc\u06a9\u0627"
    ],
    "name:fra_x_preferred":[
        "Beljajka"
    ],
    "name:msa_x_preferred":[
        "Beljajka"
    ],
    "name:por_x_preferred":[
        "Beljajka"
    ],
    "name:slv_x_preferred":[
        "Beljajka"
    ],
    "name:srp_x_preferred":[
        "Beljajka"
    ],
    "name:srp_x_variant":[
        "\u0411\u0435\u0459\u0430\u0458\u043a\u0430"
    ],
    "wof:name":"Beljajka",
    "wof:placetype":"locality"
},
  "geometry": {"coordinates":[21.44118,44.06007],"type":"Point"}
}