{
  "type": "Feature",
  "properties": {
    "gn:admin1_code":"SE",
    "gn:admin2_code":"16",
    "gn:asciiname":"Medare",
    "gn:country_code":"RS",
    "gn:dem":1049,
    "gn:feature_class":"P",
    "gn:feature_code":"PPLL",
    "gn:name":"Medare",
    "gn:population":0,
    "gn:timezone":"Europe/Belgrade",
    "iso:country":"RS",
    "name:srp_x_preferred":[
        "Medare"
    ],
    "wof:name":"Medare",
    "wof:placetype":"locality"
},
  "geometry": {"coordinates":[20.02612,43.25395],"type":"Point"}
}