{
  "type": "Feature",
  "properties": {
    "gn:admin1_code":"SE",
    "gn:admin2_code":"15",
    "gn:asciiname":"Veliki Izvor",
    "gn:country_code":"RS",
    "gn:dem":149,
    "gn:feature_class":"P",
    "gn:feature_code":"PPL",
    "gn:name":"Veliki Izvor",
    "gn:population":0,
    "gn:timezone":"Europe/Belgrade",
    "iso:country":"RS",
    "name:srp_x_preferred":[
        "Veliki Izvor"
    ],
    "wof:name":"Veliki Izvor",
    "wof:placetype":"locality"
},
  "geometry": {"coordinates":[22.33293,43.91838],"type":"Point"}
}