{
  "type": "Feature",
  "properties": {
    "gn:admin1_code":"SE",
    "gn:admin2_code":"15",
    "gn:asciiname":"Veliki Izvor",
    "gn:country_code":"RS",
    "gn:dem":149,
    "gn:feature_class":"P",
    "gn:feature_code":"PPL",
    "gn:name":"Veliki Izvor",
    "gn:population":0,
    "gn:timezone":"Europe/Belgrade",
    "iso:country":"RS",
    "name:bul_x_preferred":[
        "\u0412\u0435\u043b\u0438\u043a\u0438 \u0418\u0437\u0432\u043e\u0440"
    ],
    "name:ceb_x_preferred":[
        "Veliki Izvor"
    ],
    "name:fas_x_preferred":[
        "\u0648\u0644\u06cc\u06a9\u06cc \u0627\u06cc\u0632\u0648\u0631"
    ],
    "name:fra_x_preferred":[
        "Veliki Izvor"
    ],
    "name:msa_x_preferred":[
        "Veliki Izvor"
    ],
    "name:nld_x_preferred":[
        "Veliki Izvor"
    ],
    "name:por_x_preferred":[
        "Veliki Izvor"
    ],
    "name:slv_x_preferred":[
        "Veliki Izvor"
    ],
    "name:srp_x_preferred":[
        "Veliki Izvor"
    ],
    "name:srp_x_variant":[
        "\u0412\u0435\u043b\u0438\u043a\u0438 \u0418\u0437\u0432\u043e\u0440"
    ],
    "wof:name":"Veliki Izvor",
    "wof:placetype":"locality"
},
  "geometry": {"coordinates":[22.33293,43.91838],"type":"Point"}
}