{
  "type": "Feature",
  "properties": {
    "gn:admin1_code":"SE",
    "gn:admin2_code":"22",
    "gn:asciiname":"Rakita",
    "gn:country_code":"RS",
    "gn:dem":778,
    "gn:feature_class":"P",
    "gn:feature_code":"PPL",
    "gn:name":"Rakita",
    "gn:population":0,
    "gn:timezone":"Europe/Belgrade",
    "iso:country":"RS",
    "name:srp_x_preferred":[
        "Rakita"
    ],
    "wof:name":"Rakita",
    "wof:placetype":"locality"
},
  "geometry": {"coordinates":[22.55845,42.91368],"type":"Point"}
}