{
  "type": "Feature",
  "properties": {
    "gn:admin1_code":"SE",
    "gn:admin2_code":"15",
    "gn:asciiname":"Krenta",
    "gn:country_code":"RS",
    "gn:dem":634,
    "gn:feature_class":"P",
    "gn:feature_code":"PPL",
    "gn:name":"Krenta",
    "gn:population":0,
    "gn:timezone":"Europe/Belgrade",
    "iso:country":"RS",
    "name:ceb_x_preferred":[
        "Krenta"
    ],
    "name:fra_x_preferred":[
        "Krenta"
    ],
    "name:msa_x_preferred":[
        "Krenta"
    ],
    "name:por_x_preferred":[
        "Krenta"
    ],
    "name:slv_x_preferred":[
        "Krenta"
    ],
    "name:srp_x_preferred":[
        "Krenta"
    ],
    "name:srp_x_variant":[
        "\u041a\u0440\u0435\u043d\u0442\u0430"
    ],
    "wof:name":"Krenta",
    "wof:placetype":"locality"
},
  "geometry": {"coordinates":[22.26244,43.48016],"type":"Point"}
}