{
  "type": "Feature",
  "properties": {
    "gn:admin1_code":"SE",
    "gn:admin2_code":"22",
    "gn:asciiname":"Gornji Rinj",
    "gn:country_code":"RS",
    "gn:dem":812,
    "gn:feature_class":"P",
    "gn:feature_code":"PPL",
    "gn:name":"Gornji Rinj",
    "gn:population":0,
    "gn:timezone":"Europe/Belgrade",
    "iso:country":"RS",
    "name:fra_x_preferred":[
        "Gornji Rinj"
    ],
    "name:msa_x_preferred":[
        "Gornji Rinj"
    ],
    "name:por_x_preferred":[
        "Gornji Rinj"
    ],
    "name:slv_x_preferred":[
        "Gornji Rinj"
    ],
    "name:srp_x_preferred":[
        "Gornji Rinj"
    ],
    "name:srp_x_variant":[
        "\u0413\u043e\u0440\u045a\u0438 \u0420\u0438\u045a"
    ],
    "wof:name":"Gornji Rinj",
    "wof:placetype":"locality"
},
  "geometry": {"coordinates":[22.2965,43.30656],"type":"Point"}
}