{
  "type": "Feature",
  "properties": {
    "gn:admin1_code":"SE",
    "gn:admin2_code":"18",
    "gn:asciiname":"Donja Reka",
    "gn:country_code":"RS",
    "gn:dem":332,
    "gn:feature_class":"P",
    "gn:feature_code":"PPL",
    "gn:name":"Donja Reka",
    "gn:population":0,
    "gn:timezone":"Europe/Belgrade",
    "iso:country":"RS",
    "name:bos_x_preferred":[
        "Donja Reka"
    ],
    "name:hrv_x_preferred":[
        "Donja Reka"
    ],
    "name:hun_x_preferred":[
        "Donja Reka"
    ],
    "name:nld_x_preferred":[
        "Donja Reka"
    ],
    "name:slv_x_preferred":[
        "Donja Reka"
    ],
    "name:srp_x_preferred":[
        "\u0414\u043e\u045a\u0430 \u0420\u0435\u043a\u0430"
    ],
    "name:ukr_x_preferred":[
        "\u0414\u043e\u043d\u044f \u0420\u0435\u043a\u0430"
    ],
    "wof:name":"Donja Reka",
    "wof:placetype":"locality"
},
  "geometry": {"coordinates":[20.845,43.76903],"type":"Point"}
}