{
  "type": "Feature",
  "properties": {
    "gn:admin1_code":"SE",
    "gn:admin2_code":"23",
    "gn:asciiname":"Vlase",
    "gn:country_code":"RS",
    "gn:dem":243,
    "gn:feature_class":"P",
    "gn:feature_code":"PPL",
    "gn:name":"Vlase",
    "gn:population":0,
    "gn:timezone":"Europe/Belgrade",
    "iso:country":"RS",
    "name:srp_x_preferred":[
        "Vlase"
    ],
    "wof:name":"Vlase",
    "wof:placetype":"locality"
},
  "geometry": {"coordinates":[21.87695,42.95515],"type":"Point"}
}