{
  "type": "Feature",
  "properties": {
    "gn:country":"RS",
    "gn:fcode":"PPL",
    "gn:pop":417,
    "iso:country":"RS",
    "name:deu_x_preferred":[
        "Vatin"
    ],
    "name:eng_x_preferred":[
        "Vatin"
    ],
    "name:epo_x_preferred":[
        "Vatin"
    ],
    "name:fas_x_preferred":[
        "\u0648\u062a\u06cc\u0646"
    ],
    "name:fra_x_preferred":[
        "Vatin"
    ],
    "name:hun_x_preferred":[
        "Versecv\u00e1t"
    ],
    "name:msa_x_preferred":[
        "Vatin"
    ],
    "name:nld_x_preferred":[
        "Vatin"
    ],
    "name:ron_x_preferred":[
        "Vatin"
    ],
    "name:rus_x_preferred":[
        "\u0412\u0430\u0442\u0438\u043d"
    ],
    "name:slv_x_preferred":[
        "Vatin"
    ],
    "name:srp_x_preferred":[
        "Vatin"
    ],
    "name:unk_x_variant":[
        "Versecv\u00e1t"
    ],
    "qs:name":"Vatin",
    "qs:photos_9r":0,
    "qs:photos_sr":0,
    "qs:pop_sr":"2",
    "wd:elevation":82.0,
    "wd:wordcount":147,
    "wof:name":"Vatin",
    "wof:placetype":"locality",
    "wof:population":417
},
  "geometry": {"coordinates":[21.24395,45.23277],"type":"Point"}
}