{
  "type": "Feature",
  "properties": {
    "gn:admin1_code":"SE",
    "gn:admin2_code":"20",
    "gn:asciiname":"Gornje Dragovlje",
    "gn:country_code":"RS",
    "gn:dem":494,
    "gn:feature_class":"P",
    "gn:feature_code":"PPLL",
    "gn:name":"Gornje Dragovlje",
    "gn:population":0,
    "gn:timezone":"Europe/Belgrade",
    "iso:country":"RS",
    "name:srp_x_preferred":[
        "Gornje Dragovlje"
    ],
    "wof:name":"Gornje Dragovlje",
    "wof:placetype":"locality"
},
  "geometry": {"coordinates":[22.1246,43.12004],"type":"Point"}
}