{
  "type": "Feature",
  "properties": {
    "gn:admin1_code":"SE",
    "gn:admin2_code":"20",
    "gn:asciiname":"Gornje Dragovlje",
    "gn:country_code":"RS",
    "gn:dem":494,
    "gn:feature_class":"P",
    "gn:feature_code":"PPLL",
    "gn:name":"Gornje Dragovlje",
    "gn:population":0,
    "gn:timezone":"Europe/Belgrade",
    "iso:country":"RS",
    "name:ceb_x_preferred":[
        "Gornje Dragovlje"
    ],
    "name:fra_x_preferred":[
        "Gornje Dragovlje"
    ],
    "name:msa_x_preferred":[
        "Gornje Dragovlje"
    ],
    "name:por_x_preferred":[
        "Gornje Dragovlje"
    ],
    "name:slv_x_preferred":[
        "Gornje Dragovlje"
    ],
    "name:srp_x_preferred":[
        "Gornje Dragovlje"
    ],
    "name:srp_x_variant":[
        "\u0413\u043e\u0440\u045a\u0435 \u0414\u0440\u0430\u0433\u043e\u0432\u0459\u0435"
    ],
    "wof:name":"Gornje Dragovlje",
    "wof:placetype":"locality"
},
  "geometry": {"coordinates":[22.1246,43.12004],"type":"Point"}
}