{
  "type": "Feature",
  "properties": {
    "gn:admin1_code":"SE",
    "gn:admin2_code":"19",
    "gn:asciiname":"Gornja Crnisava",
    "gn:country_code":"RS",
    "gn:dem":257,
    "gn:feature_class":"P",
    "gn:feature_code":"PPL",
    "gn:name":"Gornja Crni\u0161ava",
    "gn:population":0,
    "gn:timezone":"Europe/Belgrade",
    "iso:country":"RS",
    "name:ceb_x_preferred":[
        "Gornja Crni\u0161ava"
    ],
    "name:fra_x_preferred":[
        "Gornja Crni\u0161ava"
    ],
    "name:msa_x_preferred":[
        "Gornja Crni\u0161ava"
    ],
    "name:por_x_preferred":[
        "Gornja Crni\u0161ava"
    ],
    "name:rus_x_preferred":[
        "\u0413\u043e\u0440\u043d\u044f-\u0426\u0440\u043d\u0438\u0448\u0430\u0432\u0430"
    ],
    "name:slv_x_preferred":[
        "Gornja Crni\u0161ava"
    ],
    "name:srp_x_preferred":[
        "Gornja Crni\u0161ava"
    ],
    "name:srp_x_variant":[
        "\u0413\u043e\u0440\u045a\u0430 \u0426\u0440\u043d\u0438\u0448\u0430\u0432\u0430"
    ],
    "wof:name":"Gornja Crnisava",
    "wof:placetype":"locality"
},
  "geometry": {"coordinates":[21.00548,43.56629],"type":"Point"}
}