{
  "type": "Feature",
  "properties": {
    "gn:admin1_code":"SE",
    "gn:admin2_code":"19",
    "gn:asciiname":"Gornja Crnisava",
    "gn:country_code":"RS",
    "gn:dem":257,
    "gn:feature_class":"P",
    "gn:feature_code":"PPL",
    "gn:name":"Gornja Crni\u0161ava",
    "gn:population":0,
    "gn:timezone":"Europe/Belgrade",
    "iso:country":"RS",
    "name:srp_x_preferred":[
        "Gornja Crni\u0161ava"
    ],
    "wof:name":"Gornja Crnisava",
    "wof:placetype":"locality"
},
  "geometry": {"coordinates":[21.00548,43.56629],"type":"Point"}
}