{
  "type": "Feature",
  "properties": {
    "gn:admin1_code":"SE",
    "gn:admin2_code":"24",
    "gn:asciiname":"Novoselci",
    "gn:country_code":"RS",
    "gn:dem":1059,
    "gn:feature_class":"P",
    "gn:feature_code":"PPL",
    "gn:name":"Novoselci",
    "gn:population":0,
    "gn:timezone":"Europe/Belgrade",
    "iso:country":"RS",
    "name:bos_x_preferred":[
        "Novoselci"
    ],
    "name:bul_x_preferred":[
        "\u041d\u043e\u0432\u043e\u0441\u0435\u043b\u0446\u0438"
    ],
    "name:ceb_x_preferred":[
        "Novoselci"
    ],
    "name:fra_x_preferred":[
        "Novoselci"
    ],
    "name:hrv_x_preferred":[
        "Novoselci"
    ],
    "name:hun_x_preferred":[
        "Novoselci"
    ],
    "name:mkd_x_preferred":[
        "\u041d\u043e\u0432\u043e\u0441\u0435\u043b\u0446\u0438"
    ],
    "name:nld_x_preferred":[
        "Novoselci"
    ],
    "name:slv_x_preferred":[
        "Novoselci"
    ],
    "name:spa_x_preferred":[
        "Novoselci"
    ],
    "name:srp_x_preferred":[
        "\u041d\u043e\u0432\u043e\u0441\u0435\u043b\u0446\u0438"
    ],
    "name:swe_x_preferred":[
        "Novoselci"
    ],
    "wof:name":"Novoselci",
    "wof:placetype":"locality"
},
  "geometry": {"coordinates":[22.24743,42.68057],"type":"Point"}
}