{
  "type": "Feature",
  "properties": {
    "gn:admin1_code":"SE",
    "gn:admin2_code":"24",
    "gn:asciiname":"Ivanovci",
    "gn:country_code":"RS",
    "gn:dem":1046,
    "gn:feature_class":"P",
    "gn:feature_code":"PPL",
    "gn:name":"Ivanovci",
    "gn:population":0,
    "gn:timezone":"Europe/Belgrade",
    "iso:country":"RS",
    "name:bos_x_preferred":[
        "Ivanovci"
    ],
    "name:fra_x_preferred":[
        "Ivanovci"
    ],
    "name:hrv_x_preferred":[
        "Ivanovci"
    ],
    "name:nld_x_preferred":[
        "Ivanovci"
    ],
    "name:slv_x_preferred":[
        "Ivanovci"
    ],
    "name:srp_x_preferred":[
        "\u0418\u0432\u0430\u043d\u043e\u0432\u0446\u0438"
    ],
    "wof:name":"Ivanovci",
    "wof:placetype":"locality"
},
  "geometry": {"coordinates":[22.17333,42.41556],"type":"Point"}
}