{
  "type": "Feature",
  "properties": {
    "gn:admin1_code":"VO",
    "gn:admin2_code":"4",
    "gn:asciiname":"Jabuka",
    "gn:country_code":"RS",
    "gn:dem":74,
    "gn:feature_class":"P",
    "gn:feature_code":"PPL",
    "gn:name":"Jabuka",
    "gn:population":0,
    "gn:timezone":"Europe/Belgrade",
    "iso:country":"RS",
    "name:bul_x_preferred":[
        "\u042f\u0431\u0443\u043a\u0430"
    ],
    "name:mkd_x_preferred":[
        "\u0408\u0430\u0431\u0443\u043a\u0430"
    ],
    "name:ron_x_preferred":[
        "Iabuca"
    ],
    "name:srp_x_preferred":[
        "Jabuka"
    ],
    "name:srp_x_variant":[
        "\u0408\u0430\u0431\u0443\u043a\u0430"
    ],
    "name:und_x_variant":[
        "Apfeldorf",
        "Toront\u00e1lalm\u00e1s"
    ],
    "name:urd_x_preferred":[
        "\u062c\u0628\u06a9\u06c1"
    ],
    "wof:name":"Jabuka",
    "wof:placetype":"locality"
},
  "geometry": {"coordinates":[20.59981,44.94922],"type":"Point"}
}