{
  "type": "Feature",
  "properties": {
    "iso:country":"RS",
    "name:eng_x_preferred":[
        "Valiko Selo"
    ],
    "name:srp_cyr_x_preferred":[
        "\u0412\u0435\u043b\u0438\u043a\u043e \u0421\u0435\u043b\u043e"
    ],
    "wof:name":"Valiko Selo",
    "wof:placetype":"neighbourhood"
},
  "geometry": {"coordinates":[20.60005277045937,44.81100347441654],"type":"Point"}
}