{
  "type": "Feature",
  "properties": {
    "gn:admin1_code":"SE",
    "gn:admin2_code":"18",
    "gn:asciiname":"Vrapce",
    "gn:country_code":"RS",
    "gn:dem":1016,
    "gn:feature_class":"P",
    "gn:feature_code":"PPL",
    "gn:name":"Vrap\u010de",
    "gn:population":0,
    "gn:timezone":"Europe/Belgrade",
    "iso:country":"RS",
    "name:fra_x_preferred":[
        "Vrap\u010de"
    ],
    "name:hun_x_preferred":[
        "Vrap\u010de"
    ],
    "name:msa_x_preferred":[
        "Vrap\u010de"
    ],
    "name:nld_x_preferred":[
        "Vrap\u010de"
    ],
    "name:por_x_preferred":[
        "Vrap\u010de"
    ],
    "name:slv_x_preferred":[
        "Vrap\u010de"
    ],
    "name:srp_x_preferred":[
        "Vrap\u010de"
    ],
    "name:srp_x_variant":[
        "\u0412\u0440\u0430\u043f\u0447\u0435"
    ],
    "wof:name":"Vrapce",
    "wof:placetype":"locality"
},
  "geometry": {"coordinates":[20.46854,42.99368],"type":"Point"}
}