{
  "type": "Feature",
  "properties": {
    "gn:admin1_code":"SE",
    "gn:admin2_code":"24",
    "gn:asciiname":"Suvi Dol",
    "gn:country_code":"RS",
    "gn:dem":427,
    "gn:feature_class":"P",
    "gn:feature_code":"PPL",
    "gn:name":"Suvi Dol",
    "gn:population":0,
    "gn:timezone":"Europe/Belgrade",
    "iso:country":"RS",
    "wof:name":"Suvi Dol",
    "wof:placetype":"locality"
},
  "geometry": {"coordinates":[21.93193,42.55244],"type":"Point"}
}