{
  "type": "Feature",
  "properties": {
    "gn:country":"RS",
    "gn:fcode":"PPL",
    "gn:population":4,
    "iso:country":"RS",
    "name:ceb_x_preferred":[
        "Milutovac"
    ],
    "name:eng_x_preferred":[
        "Milutovac"
    ],
    "name:fas_x_preferred":[
        "\u0645\u06cc\u0644\u0648\u062a\u0648\u0648\u0627\u062a\u0633"
    ],
    "name:fra_x_preferred":[
        "Milutovac"
    ],
    "name:jpn_x_preferred":[
        "\u30df\u30eb\u30c8\u30f4\u30a1\u30c4"
    ],
    "name:msa_x_preferred":[
        "Milutovac"
    ],
    "name:nld_x_preferred":[
        "Milutovac"
    ],
    "name:pol_x_preferred":[
        "Milutovac"
    ],
    "name:por_x_preferred":[
        "Milutovac"
    ],
    "name:slv_x_preferred":[
        "Milutovac"
    ],
    "name:srp_x_preferred":[
        "Milutovac"
    ],
    "name:srp_x_variant":[
        "\u041c\u0438\u043b\u0443\u0442\u043e\u0432\u0430\u0446"
    ],
    "qs:name":"Milutovac",
    "qs:photos_9r":0,
    "qs:photos_sr":0,
    "qs:pop_sr":"1",
    "wd:wordcount":69,
    "wof:name":"Milutovac",
    "wof:placetype":"locality",
    "wof:population":4
},
  "geometry": {"coordinates":[21.12914,43.68752],"type":"Point"}
}