{
  "type": "Feature",
  "properties": {
    "gn:admin1_code":"SE",
    "gn:admin2_code":"16",
    "gn:asciiname":"Parlog",
    "gn:country_code":"RS",
    "gn:dem":515,
    "gn:feature_class":"P",
    "gn:feature_code":"PPL",
    "gn:name":"Parlog",
    "gn:population":0,
    "gn:timezone":"Europe/Belgrade",
    "iso:country":"RS",
    "name:spa_x_preferred":[
        "Parlog"
    ],
    "wof:name":"Parlog",
    "wof:placetype":"locality"
},
  "geometry": {"coordinates":[19.60361,43.49667],"type":"Point"}
}