{
  "type": "Feature",
  "properties": {
    "gn:admin1_code":"SE",
    "gn:admin2_code":"16",
    "gn:asciiname":"Gracanica",
    "gn:country_code":"RS",
    "gn:dem":875,
    "gn:feature_class":"P",
    "gn:feature_code":"PPL",
    "gn:name":"Gra\u010danica",
    "gn:population":0,
    "gn:timezone":"Europe/Belgrade",
    "iso:country":"RS",
    "wof:name":"Gracanica",
    "wof:placetype":"locality"
},
  "geometry": {"coordinates":[19.59401,43.55694],"type":"Point"}
}