{
  "type": "Feature",
  "properties": {
    "gn:admin1_code":"SE",
    "gn:admin2_code":"16",
    "gn:asciiname":"Novakovici",
    "gn:country_code":"RS",
    "gn:dem":540,
    "gn:feature_class":"P",
    "gn:feature_code":"PPL",
    "gn:name":"Novakovi\u0107i",
    "gn:population":0,
    "gn:timezone":"Europe/Belgrade",
    "iso:country":"RS",
    "name:srp_x_preferred":[
        "Novakovi\u0107i"
    ],
    "wof:name":"Novakovici",
    "wof:placetype":"locality"
},
  "geometry": {"coordinates":[20.07778,43.70417],"type":"Point"}
}