{
  "type": "Feature",
  "properties": {
    "gn:admin1_code":"SE",
    "gn:admin2_code":"21",
    "gn:asciiname":"Ceruvica",
    "gn:country_code":"RS",
    "gn:dem":635,
    "gn:feature_class":"P",
    "gn:feature_code":"PPL",
    "gn:name":"Ceruvica",
    "gn:population":0,
    "gn:timezone":"Europe/Belgrade",
    "iso:country":"RS",
    "name:srp_x_preferred":[
        "Ceruvica"
    ],
    "wof:name":"Ceruvica",
    "wof:placetype":"locality"
},
  "geometry": {"coordinates":[21.17151,43.25585],"type":"Point"}
}