{
  "type": "Feature",
  "properties": {
    "gn:admin1_code":"SE",
    "gn:admin2_code":"0",
    "gn:asciiname":"Parcani",
    "gn:country_code":"RS",
    "gn:dem":245,
    "gn:feature_class":"P",
    "gn:feature_code":"PPL",
    "gn:name":"Parcani",
    "gn:population":0,
    "gn:timezone":"Europe/Belgrade",
    "iso:country":"RS",
    "name:ceb_x_preferred":[
        "Parcani"
    ],
    "name:fra_x_preferred":[
        "Parcani"
    ],
    "name:msa_x_preferred":[
        "Parcani"
    ],
    "name:nld_x_preferred":[
        "Parcani"
    ],
    "name:por_x_preferred":[
        "Parcani"
    ],
    "name:slv_x_preferred":[
        "Parcani"
    ],
    "name:srp_x_preferred":[
        "Parcani"
    ],
    "name:srp_x_variant":[
        "\u041f\u0430\u0440\u0446\u0430\u043d\u0438"
    ],
    "wof:name":"Parcani",
    "wof:placetype":"locality"
},
  "geometry": {"coordinates":[20.52668,44.56726],"type":"Point"}
}