{
  "type": "Feature",
  "properties": {
    "gn:admin1_code":"SE",
    "gn:admin2_code":"16",
    "gn:asciiname":"Zdravcici",
    "gn:country_code":"RS",
    "gn:dem":439,
    "gn:feature_class":"P",
    "gn:feature_code":"PPLL",
    "gn:name":"Zdrav\u010di\u0107i",
    "gn:population":0,
    "gn:timezone":"Europe/Belgrade",
    "iso:country":"RS",
    "name:srp_x_preferred":[
        "Zdrav\u010di\u0107i"
    ],
    "wof:name":"Zdravcici",
    "wof:placetype":"locality"
},
  "geometry": {"coordinates":[19.95412,43.85138],"type":"Point"}
}