{
  "type": "Feature",
  "properties": {
    "gn:admin1_code":"SE",
    "gn:admin2_code":"16",
    "gn:asciiname":"Podjavorje",
    "gn:country_code":"RS",
    "gn:dem":1032,
    "gn:feature_class":"P",
    "gn:feature_code":"PPLL",
    "gn:name":"Podjavorje",
    "gn:population":0,
    "gn:timezone":"Europe/Belgrade",
    "iso:country":"RS",
    "name:srp_x_preferred":[
        "Podjavorje"
    ],
    "wof:name":"Podjavorje",
    "wof:placetype":"locality"
},
  "geometry": {"coordinates":[19.30435,43.56514],"type":"Point"}
}