{
  "type": "Feature",
  "properties": {
    "gn:country":"RS",
    "gn:fcode":"PPLL",
    "gn:population":133,
    "iso:country":"RS",
    "name:bos_x_preferred":[
        "Kru\u0161evica"
    ],
    "name:bul_x_preferred":[
        "\u041a\u0440\u0443\u0448\u0435\u0432\u0438\u0446\u0430"
    ],
    "name:ceb_x_preferred":[
        "Kru\u0161evica"
    ],
    "name:eng_x_preferred":[
        "Kru\u0161evica"
    ],
    "name:fra_x_preferred":[
        "Kru\u0161evica"
    ],
    "name:hrv_x_preferred":[
        "Kru\u0161evica"
    ],
    "name:nld_x_preferred":[
        "Kru\u0161evica"
    ],
    "name:slv_x_preferred":[
        "Kru\u0161evica"
    ],
    "name:srp_x_preferred":[
        "Kru\u0161evica"
    ],
    "name:srp_x_variant":[
        "\u041a\u0440\u0443\u0448\u0435\u0432\u0438\u0446\u0430"
    ],
    "name:swe_x_preferred":[
        "Kru\u0161evica"
    ],
    "qs:name":"Kru\u0161evica",
    "qs:photos_9r":0,
    "qs:photos_sr":0,
    "qs:pop_sr":"1",
    "wd:wordcount":76,
    "wof:name":"Kru\u0161evica",
    "wof:placetype":"locality",
    "wof:population":133
},
  "geometry": {"coordinates":[21.44524,43.12708],"type":"Point"}
}