{
  "type": "Feature",
  "properties": {
    "gn:country":"RS",
    "gn:fcode":"PPLL",
    "gn:pop":133,
    "iso:country":"RS",
    "name:srp_x_preferred":[
        "Kru\u0161evica"
    ],
    "qs:name":"Kru\u0161evica",
    "qs:photos_9r":0,
    "qs:photos_sr":0,
    "qs:pop_sr":"1",
    "wd:wordcount":76,
    "wof:name":"Kru\u0161evica",
    "wof:placetype":"locality",
    "wof:population":133
},
  "geometry": {"coordinates":[21.44524,43.12708],"type":"Point"}
}