{
  "type": "Feature",
  "properties": {
    "gn:admin1_code":"SE",
    "gn:admin2_code":"16",
    "gn:asciiname":"Starcevici",
    "gn:country_code":"RS",
    "gn:dem":749,
    "gn:feature_class":"P",
    "gn:feature_code":"PPL",
    "gn:name":"Star\u010devi\u0107i",
    "gn:population":0,
    "gn:timezone":"Europe/Belgrade",
    "iso:country":"RS",
    "name:srp_x_preferred":[
        "Star\u010devi\u0107i"
    ],
    "wof:name":"Starcevici",
    "wof:placetype":"locality"
},
  "geometry": {"coordinates":[19.81951,43.93717],"type":"Point"}
}