{
  "type": "Feature",
  "properties": {
    "gn:country":"RS",
    "gn:fcode":"PPL",
    "gn:population":2483,
    "iso:country":"RS",
    "name:ceb_x_preferred":[
        "Mo\u0161orin"
    ],
    "name:ces_x_preferred":[
        "Mo\u0161orin"
    ],
    "name:deu_x_preferred":[
        "Mo\u0161orin"
    ],
    "name:eng_x_preferred":[
        "Mo\u0161orin"
    ],
    "name:epo_x_preferred":[
        "Mo\u015dorin"
    ],
    "name:fra_x_preferred":[
        "Mo\u0161orin"
    ],
    "name:heb_x_preferred":[
        "\u05de\u05d5\u05e9\u05d5\u05e8\u05d9\u05df"
    ],
    "name:hrv_x_preferred":[
        "Mo\u0161orin"
    ],
    "name:hun_x_preferred":[
        "Mozsor"
    ],
    "name:hye_x_preferred":[
        "\u0544\u0578\u0577\u0578\u0580\u056b\u0576"
    ],
    "name:msa_x_preferred":[
        "Mo\u0161orin"
    ],
    "name:nld_x_preferred":[
        "Mo\u0161orin"
    ],
    "name:pol_x_preferred":[
        "Mo\u0161orin"
    ],
    "name:rus_x_preferred":[
        "\u041c\u043e\u0448\u043e\u0440\u0438\u043d"
    ],
    "name:slv_x_preferred":[
        "Mo\u0161orin"
    ],
    "name:spa_x_preferred":[
        "Mo\u0161orin"
    ],
    "name:srp_x_preferred":[
        "Mo\u0161orin"
    ],
    "name:srp_x_variant":[
        "\u041c\u043e\u0448\u043e\u0440\u0438\u043d"
    ],
    "name:ukr_x_preferred":[
        "\u041c\u043e\u0448\u043e\u0440\u0438\u043d"
    ],
    "name:und_x_variant":[
        "Moschorin"
    ],
    "qs:name":"Mo\u00b5orin",
    "qs:name_adm0":"Serbia",
    "qs:name_adm1":"Juzhna Bachka",
    "qs:photos_9r":0,
    "qs:photos_sr":0,
    "qs:placetype":"Town",
    "qs:pop_sr":"4",
    "wof:name":"Mo\u00b5orin",
    "wof:placetype":"locality",
    "wof:population":2483
},
  "geometry": {"coordinates":[20.16919,45.30196],"type":"Point"}
}