{
  "type": "Feature",
  "properties": {
    "gn:country":"RS",
    "gn:fcode":"PPL",
    "gn:pop":65,
    "iso:country":"RS",
    "name:eng_x_preferred":[
        "Staro Selo"
    ],
    "name:fra_x_preferred":[
        "Staro Selo"
    ],
    "name:msa_x_preferred":[
        "Staro Selo"
    ],
    "name:nld_x_preferred":[
        "Staro Selo"
    ],
    "name:por_x_preferred":[
        "Staro Selo"
    ],
    "name:slv_x_preferred":[
        "Staro Selo"
    ],
    "name:sqi_x_preferred":[
        "Starasella"
    ],
    "name:srp_x_preferred":[
        "Staro Selo"
    ],
    "name:srp_x_variant":[
        "\u0421\u0442\u0430\u0440\u043e \u0421\u0435\u043b\u043e"
    ],
    "qs:name":"Staro Selo",
    "qs:photos_9r":0,
    "qs:photos_sr":0,
    "qs:pop_sr":"1",
    "wd:wordcount":127,
    "wof:name":"Staro Selo",
    "wof:placetype":"locality",
    "wof:population":65
},
  "geometry": {"coordinates":[21.55212,43.09824],"type":"Point"}
}