{
  "type": "Feature",
  "properties": {
    "gn:admin1_code":"VO",
    "gn:admin2_code":"1",
    "gn:asciiname":"Durgin",
    "gn:country_code":"RS",
    "gn:dem":109,
    "gn:feature_class":"P",
    "gn:feature_code":"PPL",
    "gn:name":"\u00d0ur\u0111in",
    "gn:population":0,
    "gn:timezone":"Europe/Belgrade",
    "iso:country":"RS",
    "name:srp_x_preferred":[
        "\u00d0ur\u0111in"
    ],
    "wof:name":"Durgin",
    "wof:placetype":"locality"
},
  "geometry": {"coordinates":[19.53934,45.94614],"type":"Point"}
}