{
  "type": "Feature",
  "properties": {
    "gn:admin1_code":"SE",
    "gn:admin2_code":"20",
    "gn:asciiname":"Pirkovac",
    "gn:country_code":"RS",
    "gn:dem":382,
    "gn:feature_class":"P",
    "gn:feature_code":"PPL",
    "gn:name":"Pirkovac",
    "gn:population":0,
    "gn:timezone":"Europe/Belgrade",
    "iso:country":"RS",
    "name:fra_x_preferred":[
        "Pirkovac"
    ],
    "name:msa_x_preferred":[
        "Pirkovac"
    ],
    "name:por_x_preferred":[
        "Pirkovac"
    ],
    "name:slv_x_preferred":[
        "Pirkovac"
    ],
    "name:srp_x_preferred":[
        "Pirkovac"
    ],
    "name:srp_x_variant":[
        "\u041f\u0438\u0440\u043a\u043e\u0432\u0430\u0446"
    ],
    "wof:name":"Pirkovac",
    "wof:placetype":"locality"
},
  "geometry": {"coordinates":[21.96157,43.48339],"type":"Point"}
}