{
  "type": "Feature",
  "properties": {
    "gn:admin1_code":"SE",
    "gn:admin2_code":"19",
    "gn:asciiname":"Jankovici",
    "gn:country_code":"RS",
    "gn:dem":1217,
    "gn:feature_class":"P",
    "gn:feature_code":"PPL",
    "gn:name":"Jankovi\u0107i",
    "gn:population":0,
    "gn:timezone":"Europe/Belgrade",
    "iso:country":"RS",
    "name:srp_x_preferred":[
        "Jankovi\u0107i"
    ],
    "wof:name":"Jankovici",
    "wof:placetype":"locality"
},
  "geometry": {"coordinates":[20.87972,43.36139],"type":"Point"}
}