{
  "type": "Feature",
  "properties": {
    "gn:admin1_code":"SE",
    "gn:admin2_code":"21",
    "gn:asciiname":"Klisurica",
    "gn:country_code":"RS",
    "gn:dem":534,
    "gn:feature_class":"P",
    "gn:feature_code":"PPL",
    "gn:name":"Klisurica",
    "gn:population":0,
    "gn:timezone":"Europe/Belgrade",
    "iso:country":"RS",
    "name:bul_x_preferred":[
        "\u041a\u043b\u0438\u0441\u0443\u0440\u0438\u0446\u0430"
    ],
    "name:ell_x_preferred":[
        "\u039a\u03bb\u03b5\u03b9\u03c3\u03bf\u03c5\u03c1\u03af\u03c4\u03c3\u03b1"
    ],
    "name:fra_x_preferred":[
        "Klisurica"
    ],
    "name:hrv_x_preferred":[
        "Klisurica"
    ],
    "name:slv_x_preferred":[
        "Klisurica"
    ],
    "name:srp_x_preferred":[
        "Klisurica"
    ],
    "name:srp_x_variant":[
        "\u041a\u043b\u0438\u0441\u0443\u0440\u0438\u0446\u0430"
    ],
    "wof:name":"Klisurica",
    "wof:placetype":"locality"
},
  "geometry": {"coordinates":[21.57741,43.34451],"type":"Point"}
}