{
  "type": "Feature",
  "properties": {
    "gn:admin1_code":"SE",
    "gn:admin2_code":"18",
    "gn:asciiname":"Kovaci",
    "gn:country_code":"RS",
    "gn:dem":228,
    "gn:feature_class":"P",
    "gn:feature_code":"PPLL",
    "gn:name":"Kova\u010di",
    "gn:population":0,
    "gn:timezone":"Europe/Belgrade",
    "iso:country":"RS",
    "name:srp_x_preferred":[
        "Kova\u010di"
    ],
    "wof:name":"Kovaci",
    "wof:placetype":"locality"
},
  "geometry": {"coordinates":[20.67603,43.69818],"type":"Point"}
}