{
  "type": "Feature",
  "properties": {
    "gn:admin1_code":"SE",
    "gn:admin2_code":"19",
    "gn:asciiname":"Parcane",
    "gn:country_code":"RS",
    "gn:dem":247,
    "gn:feature_class":"P",
    "gn:feature_code":"PPL",
    "gn:name":"Parcane",
    "gn:population":0,
    "gn:timezone":"Europe/Belgrade",
    "iso:country":"RS",
    "name:srp_x_preferred":[
        "Parcane"
    ],
    "wof:name":"Parcane",
    "wof:placetype":"locality"
},
  "geometry": {"coordinates":[21.21243,43.69353],"type":"Point"}
}