{
  "type": "Feature",
  "properties": {
    "gn:admin1_code":"SE",
    "gn:admin2_code":"19",
    "gn:asciiname":"Parcane",
    "gn:country_code":"RS",
    "gn:dem":247,
    "gn:feature_class":"P",
    "gn:feature_code":"PPL",
    "gn:name":"Parcane",
    "gn:population":0,
    "gn:timezone":"Europe/Belgrade",
    "iso:country":"RS",
    "name:ceb_x_preferred":[
        "Parcane"
    ],
    "name:fra_x_preferred":[
        "Parcane"
    ],
    "name:msa_x_preferred":[
        "Parcane"
    ],
    "name:por_x_preferred":[
        "Parcane"
    ],
    "name:slv_x_preferred":[
        "Parcane"
    ],
    "name:srp_x_preferred":[
        "Parcane"
    ],
    "name:srp_x_variant":[
        "\u041f\u0430\u0440\u0446\u0430\u043d\u0435"
    ],
    "wof:name":"Parcane",
    "wof:placetype":"locality"
},
  "geometry": {"coordinates":[21.21243,43.69353],"type":"Point"}
}