{
  "type": "Feature",
  "properties": {
    "gn:admin1_code":"SE",
    "gn:admin2_code":"15",
    "gn:asciiname":"Bulinovac",
    "gn:country_code":"RS",
    "gn:dem":339,
    "gn:feature_class":"P",
    "gn:feature_code":"PPL",
    "gn:name":"Bulinovac",
    "gn:population":0,
    "gn:timezone":"Europe/Belgrade",
    "iso:country":"RS",
    "name:ceb_x_preferred":[
        "Bulinovac"
    ],
    "name:deu_x_preferred":[
        "Bulinovac"
    ],
    "name:fra_x_preferred":[
        "Bulinovac"
    ],
    "name:msa_x_preferred":[
        "Bulinovac"
    ],
    "name:por_x_preferred":[
        "Bulinovac"
    ],
    "name:slv_x_preferred":[
        "Bulinovac"
    ],
    "name:srp_x_preferred":[
        "Bulinovac"
    ],
    "name:srp_x_variant":[
        "\u0411\u0443\u043b\u0438\u043d\u043e\u0432\u0430\u0446"
    ],
    "wof:name":"Bulinovac",
    "wof:placetype":"locality"
},
  "geometry": {"coordinates":[22.18222,43.60389],"type":"Point"}
}