{
  "type": "Feature",
  "properties": {
    "gn:admin1_code":"SE",
    "gn:admin2_code":"20",
    "gn:asciiname":"Palilula",
    "gn:country_code":"RS",
    "gn:dem":200,
    "gn:feature_class":"P",
    "gn:feature_code":"PPL",
    "gn:name":"Palilula",
    "gn:population":0,
    "gn:timezone":"Europe/Belgrade",
    "iso:country":"RS",
    "name:bul_x_preferred":[
        "\u041f\u0430\u043b\u0438\u043b\u0443\u043b\u0430"
    ],
    "name:fra_x_preferred":[
        "Palilula"
    ],
    "name:hrv_x_preferred":[
        "Palilula"
    ],
    "name:ita_x_preferred":[
        "Palilula"
    ],
    "name:ron_x_preferred":[
        "Palilula"
    ],
    "name:rus_x_preferred":[
        "\u041f\u0430\u043b\u0438\u043b\u0443\u043b\u0430"
    ],
    "name:srp_x_preferred":[
        "Palilula"
    ],
    "name:srp_x_variant":[
        "\u041f\u0430\u043b\u0438\u043b\u0443\u043b\u0430"
    ],
    "name:swe_x_preferred":[
        "Palilula"
    ],
    "name:tur_x_preferred":[
        "Palilula"
    ],
    "wof:name":"Palilula",
    "wof:placetype":"locality"
},
  "geometry": {"coordinates":[21.71611,43.54],"type":"Point"}
}