{
  "type": "Feature",
  "properties": {
    "gn:admin1_code":"SE",
    "gn:admin2_code":"16",
    "gn:asciiname":"Seoce",
    "gn:country_code":"RS",
    "gn:dem":652,
    "gn:feature_class":"P",
    "gn:feature_code":"PPL",
    "gn:name":"Seoce",
    "gn:population":0,
    "gn:timezone":"Europe/Belgrade",
    "iso:country":"RS",
    "name:bos_x_preferred":[
        "Seoce"
    ],
    "name:fra_x_preferred":[
        "Seoce"
    ],
    "name:hrv_x_preferred":[
        "Seoce"
    ],
    "name:nld_x_preferred":[
        "Seoce"
    ],
    "name:slv_x_preferred":[
        "Seoce"
    ],
    "name:srp_x_preferred":[
        "\u0421\u0435\u043e\u0446\u0435"
    ],
    "wof:name":"Seoce",
    "wof:placetype":"locality"
},
  "geometry": {"coordinates":[19.67056,43.31417],"type":"Point"}
}