{
  "type": "Feature",
  "properties": {
    "gn:admin1_code":"SE",
    "gn:admin2_code":"0",
    "gn:asciiname":"Beljina",
    "gn:country_code":"RS",
    "gn:dem":176,
    "gn:feature_class":"P",
    "gn:feature_code":"PPL",
    "gn:name":"Beljina",
    "gn:population":0,
    "gn:timezone":"Europe/Belgrade",
    "iso:country":"RS",
    "wof:name":"Beljina",
    "wof:placetype":"locality"
},
  "geometry": {"coordinates":[20.40596,44.51534],"type":"Point"}
}