{
  "type": "Feature",
  "properties": {
    "gn:admin1_code":"SE",
    "gn:admin2_code":"16",
    "gn:asciiname":"Rocnjak",
    "gn:country_code":"RS",
    "gn:dem":649,
    "gn:feature_class":"P",
    "gn:feature_code":"PPL",
    "gn:name":"Ro\u010dnjak",
    "gn:population":0,
    "gn:timezone":"Europe/Belgrade",
    "iso:country":"RS",
    "name:und_x_variant":[
        "Ra\u010dnjak",
        "Ro\u010dnjak"
    ],
    "wof:name":"Rocnjak",
    "wof:placetype":"locality"
},
  "geometry": {"coordinates":[19.68387,43.86408],"type":"Point"}
}