{
  "type": "Feature",
  "properties": {
    "gn:admin1_code":"SE",
    "gn:admin2_code":"11",
    "gn:asciiname":"Tribrode",
    "gn:country_code":"RS",
    "gn:dem":85,
    "gn:feature_class":"P",
    "gn:feature_code":"PPL",
    "gn:name":"Tribrode",
    "gn:population":0,
    "gn:timezone":"Europe/Belgrade",
    "iso:country":"RS",
    "name:srp_x_preferred":[
        "Tribrode"
    ],
    "name:und_x_variant":[
        "Tribrod"
    ],
    "wof:name":"Tribrode",
    "wof:placetype":"locality"
},
  "geometry": {"coordinates":[21.52213,44.69712],"type":"Point"}
}