{
  "type": "Feature",
  "properties": {
    "gn:admin1_code":"SE",
    "gn:admin2_code":"19",
    "gn:asciiname":"Milicevici",
    "gn:country_code":"RS",
    "gn:dem":1098,
    "gn:feature_class":"P",
    "gn:feature_code":"PPL",
    "gn:name":"Mili\u0107evi\u0107i",
    "gn:population":0,
    "gn:timezone":"Europe/Belgrade",
    "iso:country":"RS",
    "name:srp_x_preferred":[
        "Mili\u0107evi\u0107i"
    ],
    "wof:name":"Milicevici",
    "wof:placetype":"locality"
},
  "geometry": {"coordinates":[20.87218,43.44097],"type":"Point"}
}