{
  "type": "Feature",
  "properties": {
    "gn:admin1_code":"SE",
    "gn:admin2_code":"16",
    "gn:asciiname":"Podstolac",
    "gn:country_code":"RS",
    "gn:dem":667,
    "gn:feature_class":"P",
    "gn:feature_code":"PPL",
    "gn:name":"Podstolac",
    "gn:population":0,
    "gn:timezone":"Europe/Belgrade",
    "iso:country":"RS",
    "name:srp_x_preferred":[
        "Podstolac"
    ],
    "wof:name":"Podstolac",
    "wof:placetype":"locality"
},
  "geometry": {"coordinates":[19.43772,43.79584000000001],"type":"Point"}
}