{
  "type": "Feature",
  "properties": {
    "gn:admin1_code":"SE",
    "gn:admin2_code":"23",
    "gn:asciiname":"Gornji Gajtan",
    "gn:country_code":"RS",
    "gn:dem":954,
    "gn:feature_class":"P",
    "gn:feature_code":"PPLL",
    "gn:name":"Gornji Gajtan",
    "gn:population":0,
    "gn:timezone":"Europe/Belgrade",
    "iso:country":"RS",
    "name:srp_x_preferred":[
        "Gornji Gajtan"
    ],
    "wof:name":"Gornji Gajtan",
    "wof:placetype":"locality"
},
  "geometry": {"coordinates":[21.48401,42.98331],"type":"Point"}
}