{
  "type": "Feature",
  "properties": {
    "gn:admin1_code":"SE",
    "gn:admin2_code":"23",
    "gn:asciiname":"Gornji Gajtan",
    "gn:country_code":"RS",
    "gn:dem":954,
    "gn:feature_class":"P",
    "gn:feature_code":"PPLL",
    "gn:name":"Gornji Gajtan",
    "gn:population":0,
    "gn:timezone":"Europe/Belgrade",
    "iso:country":"RS",
    "name:fra_x_preferred":[
        "Gornji Gajtan"
    ],
    "name:msa_x_preferred":[
        "Gornji Gajtan"
    ],
    "name:por_x_preferred":[
        "Gornji Gajtan"
    ],
    "name:slv_x_preferred":[
        "Donji Gajtan"
    ],
    "name:srp_x_preferred":[
        "Gornji Gajtan"
    ],
    "name:srp_x_variant":[
        "\u0413\u043e\u0440\u045a\u0438 \u0413\u0430\u0458\u0442\u0430\u043d"
    ],
    "wof:name":"Gornji Gajtan",
    "wof:placetype":"locality"
},
  "geometry": {"coordinates":[21.48401,42.98331],"type":"Point"}
}