{
  "type": "Feature",
  "properties": {
    "gn:country":"RS",
    "gn:fcode":"PPL",
    "gn:pop":5,
    "iso:country":"RS",
    "name:srp_x_preferred":[
        "So\u0161anica"
    ],
    "qs:name":"So\u010danica",
    "qs:name_adm0":"Serbia",
    "qs:name_adm1":"Kosovska Mitrovica",
    "qs:photos_9r":0,
    "qs:photos_sr":0,
    "qs:placetype":"Town",
    "qs:pop_sr":"1",
    "wof:name":"So\u010danica",
    "wof:placetype":"locality",
    "wof:population":5
},
  "geometry": {"coordinates":[20.64388,43.58058],"type":"Point"}
}