{
  "type": "Feature",
  "properties": {
    "gn:admin1_code":"SE",
    "gn:admin2_code":"16",
    "gn:asciiname":"Gornji Zvijezd",
    "gn:country_code":"RS",
    "gn:dem":1068,
    "gn:feature_class":"P",
    "gn:feature_code":"PPLL",
    "gn:name":"Gornji Zvijezd",
    "gn:population":0,
    "gn:timezone":"Europe/Belgrade",
    "iso:country":"RS",
    "wof:name":"Gornji Zvijezd",
    "wof:placetype":"locality"
},
  "geometry": {"coordinates":[19.54861,43.36389000000001],"type":"Point"}
}