{
  "type": "Feature",
  "properties": {
    "gn:admin1_code":"SE",
    "gn:admin2_code":"11",
    "gn:asciiname":"Kasidol",
    "gn:country_code":"RS",
    "gn:dem":120,
    "gn:feature_class":"P",
    "gn:feature_code":"PPL",
    "gn:name":"Kasidol",
    "gn:population":0,
    "gn:timezone":"Europe/Belgrade",
    "iso:country":"RS",
    "name:bul_x_preferred":[
        "\u041a\u0430\u0441\u0438\u0434\u043e\u043b"
    ],
    "name:ceb_x_preferred":[
        "Kasidol"
    ],
    "name:fra_x_preferred":[
        "Kasidol"
    ],
    "name:msa_x_preferred":[
        "Kasidol"
    ],
    "name:por_x_preferred":[
        "Kasidol"
    ],
    "name:ron_x_preferred":[
        "Kasidol"
    ],
    "name:slv_x_preferred":[
        "Kasidol"
    ],
    "name:srp_x_preferred":[
        "Kasidol"
    ],
    "name:srp_x_variant":[
        "\u041a\u0430\u0441\u0438\u0434\u043e\u043b"
    ],
    "wof:name":"Kasidol",
    "wof:placetype":"locality"
},
  "geometry": {"coordinates":[21.32357,44.63399],"type":"Point"}
}