{
  "type": "Feature",
  "properties": {
    "gn:admin1_code":"SE",
    "gn:admin2_code":"9",
    "gn:asciiname":"Savici",
    "gn:country_code":"RS",
    "gn:dem":566,
    "gn:feature_class":"P",
    "gn:feature_code":"PPL",
    "gn:name":"Savi\u0107i",
    "gn:population":0,
    "gn:timezone":"Europe/Belgrade",
    "iso:country":"RS",
    "name:srp_x_preferred":[
        "Savi\u0107i"
    ],
    "wof:name":"Savici",
    "wof:placetype":"locality"
},
  "geometry": {"coordinates":[19.66389,44.24611],"type":"Point"}
}