{
  "type": "Feature",
  "properties": {
    "gn:admin1_code":"SE",
    "gn:admin2_code":"24",
    "gn:asciiname":"Mandzina Mahala",
    "gn:country_code":"RS",
    "gn:dem":1386,
    "gn:feature_class":"P",
    "gn:feature_code":"PPL",
    "gn:name":"Mand\u017eina Mahala",
    "gn:population":0,
    "gn:timezone":"Europe/Belgrade",
    "iso:country":"RS",
    "name:srp_x_preferred":[
        "Mand\u017eina Mahala"
    ],
    "name:und_x_variant":[
        "Mancina Mahala"
    ],
    "wof:name":"Mandzina Mahala",
    "wof:placetype":"locality"
},
  "geometry": {"coordinates":[22.30415,42.71253],"type":"Point"}
}