{
  "type": "Feature",
  "properties": {
    "gn:admin1_code":"SE",
    "gn:admin2_code":"21",
    "gn:asciiname":"Drobnjaci",
    "gn:country_code":"RS",
    "gn:dem":617,
    "gn:feature_class":"P",
    "gn:feature_code":"PPL",
    "gn:name":"Drobnjaci",
    "gn:population":0,
    "gn:timezone":"Europe/Belgrade",
    "iso:country":"RS",
    "wof:name":"Drobnjaci",
    "wof:placetype":"locality"
},
  "geometry": {"coordinates":[21.42111,43.11167],"type":"Point"}
}