{
  "type": "Feature",
  "properties": {
    "gn:admin1_code":"SE",
    "gn:admin2_code":"21",
    "gn:asciiname":"Drobnjaci",
    "gn:country_code":"RS",
    "gn:dem":617,
    "gn:feature_class":"P",
    "gn:feature_code":"PPL",
    "gn:name":"Drobnjaci",
    "gn:population":0,
    "gn:timezone":"Europe/Belgrade",
    "iso:country":"RS",
    "name:srp_x_preferred":[
        "\u0414\u0440\u043e\u0431\u045a\u0430\u0446\u0438"
    ],
    "wof:name":"Drobnjaci",
    "wof:placetype":"locality"
},
  "geometry": {"coordinates":[21.42111,43.11167],"type":"Point"}
}