{
  "type": "Feature",
  "properties": {
    "gn:admin1_code":"SE",
    "gn:admin2_code":"9",
    "gn:asciiname":"Tabanovic",
    "gn:country_code":"RS",
    "gn:dem":190,
    "gn:feature_class":"P",
    "gn:feature_code":"PPL",
    "gn:name":"Tabanovi\u0107",
    "gn:population":0,
    "gn:timezone":"Europe/Belgrade",
    "iso:country":"RS",
    "name:srp_x_preferred":[
        "Tabanovi\u0107"
    ],
    "wof:name":"Tabanovic",
    "wof:placetype":"locality"
},
  "geometry": {"coordinates":[20.07087000000001,44.28892000000001],"type":"Point"}
}