{
  "type": "Feature",
  "properties": {
    "gn:admin1_code":"SE",
    "gn:admin2_code":"19",
    "gn:asciiname":"Domisevina",
    "gn:country_code":"RS",
    "gn:dem":848,
    "gn:feature_class":"P",
    "gn:feature_code":"PPL",
    "gn:name":"Domi\u0161evina",
    "gn:population":0,
    "gn:timezone":"Europe/Belgrade",
    "iso:country":"RS",
    "name:srp_x_preferred":[
        "Domi\u0161evina"
    ],
    "name:und_x_variant":[
        "Domi\u0161ane"
    ],
    "wof:name":"Domisevina",
    "wof:placetype":"locality"
},
  "geometry": {"coordinates":[20.92056,43.2098],"type":"Point"}
}