{
  "type": "Feature",
  "properties": {
    "gn:admin1_code":"SE",
    "gn:admin2_code":"8",
    "gn:asciiname":"Lice",
    "gn:country_code":"RS",
    "gn:dem":431,
    "gn:feature_class":"P",
    "gn:feature_code":"PPL",
    "gn:name":"Lice",
    "gn:population":0,
    "gn:timezone":"Europe/Belgrade",
    "iso:country":"RS",
    "name:srp_x_preferred":[
        "Lice"
    ],
    "wof:name":"Lice",
    "wof:placetype":"locality"
},
  "geometry": {"coordinates":[19.44607,44.31848],"type":"Point"}
}