{
  "type": "Feature",
  "properties": {
    "gn:admin1_code":"SE",
    "gn:admin2_code":"15",
    "gn:asciiname":"Valevac",
    "gn:country_code":"RS",
    "gn:dem":281,
    "gn:feature_class":"P",
    "gn:feature_code":"PPL",
    "gn:name":"Valevac",
    "gn:population":0,
    "gn:timezone":"Europe/Belgrade",
    "iso:country":"RS",
    "name:ceb_x_preferred":[
        "Valevac"
    ],
    "name:fra_x_preferred":[
        "Valevac"
    ],
    "name:msa_x_preferred":[
        "Valevac"
    ],
    "name:por_x_preferred":[
        "Valevac"
    ],
    "name:slv_x_preferred":[
        "Valevac"
    ],
    "name:srp_x_preferred":[
        "Valevac"
    ],
    "name:srp_x_variant":[
        "\u0412\u0430\u043b\u0435\u0432\u0430\u0446"
    ],
    "wof:name":"Valevac",
    "wof:placetype":"locality"
},
  "geometry": {"coordinates":[22.21222,43.62167],"type":"Point"}
}