{
  "type": "Feature",
  "properties": {
    "gn:admin1_code":"SE",
    "gn:admin2_code":"11",
    "gn:asciiname":"Josanica",
    "gn:country_code":"RS",
    "gn:dem":326,
    "gn:feature_class":"P",
    "gn:feature_code":"PPL",
    "gn:name":"Jo\u0161anica",
    "gn:population":0,
    "gn:timezone":"Europe/Belgrade",
    "iso:country":"RS",
    "name:srp_x_preferred":[
        "Jo\u0161anica"
    ],
    "wof:name":"Josanica",
    "wof:placetype":"locality"
},
  "geometry": {"coordinates":[21.71282,44.27856],"type":"Point"}
}