{
  "type": "Feature",
  "properties": {
    "gn:admin1_code":"SE",
    "gn:admin2_code":"21",
    "gn:asciiname":"Trn",
    "gn:country_code":"RS",
    "gn:dem":809,
    "gn:feature_class":"P",
    "gn:feature_code":"PPL",
    "gn:name":"Trn",
    "gn:population":0,
    "gn:timezone":"Europe/Belgrade",
    "iso:country":"RS",
    "name:srp_x_preferred":[
        "Trn"
    ],
    "wof:name":"Trn",
    "wof:placetype":"locality"
},
  "geometry": {"coordinates":[21.38395,42.89433],"type":"Point"}
}