{
  "type": "Feature",
  "properties": {
    "gn:admin1_code":"SE",
    "gn:admin2_code":"24",
    "gn:asciiname":"Gornja Mahala",
    "gn:country_code":"RS",
    "gn:dem":1044,
    "gn:feature_class":"P",
    "gn:feature_code":"PPL",
    "gn:name":"Gornja Mahala",
    "gn:population":0,
    "gn:timezone":"Europe/Belgrade",
    "iso:country":"RS",
    "wof:name":"Gornja Mahala",
    "wof:placetype":"locality"
},
  "geometry": {"coordinates":[22.11195,42.5136],"type":"Point"}
}