{
  "type": "Feature",
  "properties": {
    "gn:admin1_code":"SE",
    "gn:admin2_code":"0",
    "gn:asciiname":"Senaja",
    "gn:country_code":"RS",
    "gn:dem":174,
    "gn:feature_class":"P",
    "gn:feature_code":"PPL",
    "gn:name":"Senaja",
    "gn:population":0,
    "gn:timezone":"Europe/Belgrade",
    "iso:country":"RS",
    "name:srp_x_preferred":[
        "Senaja"
    ],
    "wof:name":"Senaja",
    "wof:placetype":"locality"
},
  "geometry": {"coordinates":[20.66958,44.54488],"type":"Point"}
}