{
  "type": "Feature",
  "properties": {
    "gn:admin1_code":"SE",
    "gn:admin2_code":"0",
    "gn:asciiname":"Senaja",
    "gn:country_code":"RS",
    "gn:dem":174,
    "gn:feature_class":"P",
    "gn:feature_code":"PPL",
    "gn:name":"Senaja",
    "gn:population":0,
    "gn:timezone":"Europe/Belgrade",
    "iso:country":"RS",
    "name:ceb_x_preferred":[
        "Senaja"
    ],
    "name:fra_x_preferred":[
        "Senaja"
    ],
    "name:msa_x_preferred":[
        "Senaja"
    ],
    "name:nld_x_preferred":[
        "Senaja"
    ],
    "name:por_x_preferred":[
        "Senaja"
    ],
    "name:slv_x_preferred":[
        "Senaja"
    ],
    "name:srp_x_preferred":[
        "Senaja"
    ],
    "name:srp_x_variant":[
        "\u0421\u0435\u043d\u0430\u0458\u0430"
    ],
    "wof:name":"Senaja",
    "wof:placetype":"locality"
},
  "geometry": {"coordinates":[20.66958,44.54488],"type":"Point"}
}