{
  "type": "Feature",
  "properties": {
    "gn:admin1_code":"SE",
    "gn:admin2_code":"18",
    "gn:asciiname":"Nis",
    "gn:country_code":"RS",
    "gn:dem":1101,
    "gn:feature_class":"P",
    "gn:feature_code":"PPL",
    "gn:name":"Ni\u0161",
    "gn:population":0,
    "gn:timezone":"Europe/Belgrade",
    "iso:country":"RS",
    "name:srp_x_preferred":[
        "Ni\u0161"
    ],
    "wof:name":"Nis",
    "wof:placetype":"locality"
},
  "geometry": {"coordinates":[20.59824,43.02506],"type":"Point"}
}