{
  "type": "Feature",
  "properties": {
    "gn:admin1_code":"SE",
    "gn:admin2_code":"18",
    "gn:asciiname":"Koznik",
    "gn:country_code":"RS",
    "gn:dem":969,
    "gn:feature_class":"P",
    "gn:feature_code":"PPL",
    "gn:name":"Koznik",
    "gn:population":0,
    "gn:timezone":"Europe/Belgrade",
    "iso:country":"RS",
    "name:bul_x_preferred":[
        "\u041a\u043e\u0437\u044a\u043b"
    ],
    "name:mkd_x_preferred":[
        "\u0422\u0432\u0440\u0434\u0438\u043d\u0430 \u041a\u043e\u0437\u043d\u0438\u043a"
    ],
    "name:nno_x_preferred":[
        "Koznik"
    ],
    "name:srp_x_preferred":[
        "Koznik"
    ],
    "name:srp_x_variant":[
        "\u0422\u0432\u0440\u0452\u0430\u0432\u0430 \u041a\u043e\u0437\u043d\u0438\u043a"
    ],
    "wof:name":"Koznik",
    "wof:placetype":"locality"
},
  "geometry": {"coordinates":[20.55626,43.06936],"type":"Point"}
}