{
  "type": "Feature",
  "properties": {
    "gn:admin1_code":"SE",
    "gn:admin2_code":"15",
    "gn:asciiname":"Nenedica",
    "gn:country_code":"RS",
    "gn:dem":236,
    "gn:feature_class":"P",
    "gn:feature_code":"PPL",
    "gn:name":"Nenedica",
    "gn:population":0,
    "gn:timezone":"Europe/Belgrade",
    "iso:country":"RS",
    "name:srp_x_preferred":[
        "Nenedica"
    ],
    "wof:name":"Nenedica",
    "wof:placetype":"locality"
},
  "geometry": {"coordinates":[22.31639,43.74182],"type":"Point"}
}