{
  "type": "Feature",
  "properties": {
    "gn:admin1_code":"VO",
    "gn:admin2_code":"7",
    "gn:asciiname":"Prnjavor Jazacki",
    "gn:country_code":"RS",
    "gn:dem":201,
    "gn:feature_class":"P",
    "gn:feature_code":"PPL",
    "gn:name":"Prnjavor Jaza\u010dki",
    "gn:population":0,
    "gn:timezone":"Europe/Belgrade",
    "iso:country":"RS",
    "name:und_x_variant":[
        "Jaza\u010dki Prnjavor",
        "Prnjavor Jaza\u010dki"
    ],
    "wof:name":"Prnjavor Jazacki",
    "wof:placetype":"locality"
},
  "geometry": {"coordinates":[19.76622,45.11734000000001],"type":"Point"}
}