{
  "type": "Feature",
  "properties": {
    "gn:admin1_code":"SE",
    "gn:admin2_code":"19",
    "gn:asciiname":"Zlatari",
    "gn:country_code":"RS",
    "gn:dem":288,
    "gn:feature_class":"P",
    "gn:feature_code":"PPL",
    "gn:name":"Zlatari",
    "gn:population":0,
    "gn:timezone":"Europe/Belgrade",
    "iso:country":"RS",
    "name:ceb_x_preferred":[
        "Zlatari"
    ],
    "name:fra_x_preferred":[
        "Zlatari"
    ],
    "name:msa_x_preferred":[
        "Zlatari"
    ],
    "name:nld_x_preferred":[
        "Zlatari"
    ],
    "name:por_x_preferred":[
        "Zlatari"
    ],
    "name:slv_x_preferred":[
        "Zlatari"
    ],
    "name:srp_x_preferred":[
        "Zlatari"
    ],
    "name:srp_x_variant":[
        "\u0417\u043b\u0430\u0442\u0430\u0440\u0438"
    ],
    "wof:name":"Zlatari",
    "wof:placetype":"locality"
},
  "geometry": {"coordinates":[21.15806,43.38694],"type":"Point"}
}