{
  "type": "Feature",
  "properties": {
    "gn:admin1_code":"SE",
    "gn:admin2_code":"24",
    "gn:asciiname":"Breza",
    "gn:country_code":"RS",
    "gn:dem":985,
    "gn:feature_class":"P",
    "gn:feature_code":"PPL",
    "gn:name":"Breza",
    "gn:population":0,
    "gn:timezone":"Europe/Belgrade",
    "iso:country":"RS",
    "name:bos_x_preferred":[
        "Breza"
    ],
    "name:bul_x_preferred":[
        "\u0411\u0440\u0435\u0437\u0430"
    ],
    "name:ceb_x_preferred":[
        "Breza"
    ],
    "name:deu_x_preferred":[
        "Breza"
    ],
    "name:epo_x_preferred":[
        "Breza"
    ],
    "name:fra_x_preferred":[
        "Breza"
    ],
    "name:hrv_x_preferred":[
        "Breza"
    ],
    "name:hun_x_preferred":[
        "Breza"
    ],
    "name:nld_x_preferred":[
        "Breza"
    ],
    "name:rus_x_preferred":[
        "\u0411\u0440\u0435\u0437\u0430"
    ],
    "name:slk_x_preferred":[
        "Breza"
    ],
    "name:slv_x_preferred":[
        "Breza"
    ],
    "name:sqi_x_preferred":[
        "Breza"
    ],
    "name:srp_x_preferred":[
        "\u0411\u0440\u0435\u0437\u0430"
    ],
    "name:swe_x_preferred":[
        "Breza"
    ],
    "wof:name":"Breza",
    "wof:placetype":"locality"
},
  "geometry": {"coordinates":[22.00121,42.74226],"type":"Point"}
}