{
  "type": "Feature",
  "properties": {
    "gn:admin1_code":"SE",
    "gn:admin2_code":"11",
    "gn:asciiname":"Rabrovo",
    "gn:country_code":"RS",
    "gn:dem":126,
    "gn:feature_class":"P",
    "gn:feature_code":"PPL",
    "gn:name":"Rabrovo",
    "gn:population":0,
    "gn:timezone":"Europe/Belgrade",
    "iso:country":"RS",
    "name:ceb_x_preferred":[
        "Rabrovo"
    ],
    "name:fra_x_preferred":[
        "Rabrovo"
    ],
    "name:msa_x_preferred":[
        "Rabrovo"
    ],
    "name:por_x_preferred":[
        "Rabrovo"
    ],
    "name:slv_x_preferred":[
        "Rabrovo"
    ],
    "name:srp_x_preferred":[
        "Rabrovo"
    ],
    "name:srp_x_variant":[
        "\u0420\u0430\u0431\u0440\u043e\u0432\u043e"
    ],
    "wof:name":"Rabrovo",
    "wof:placetype":"locality"
},
  "geometry": {"coordinates":[21.51375,44.57641],"type":"Point"}
}