{
  "type": "Feature",
  "properties": {
    "gn:admin1_code":"SE",
    "gn:admin2_code":"16",
    "gn:asciiname":"Strane",
    "gn:country_code":"RS",
    "gn:dem":754,
    "gn:feature_class":"P",
    "gn:feature_code":"PPL",
    "gn:name":"Strane",
    "gn:population":0,
    "gn:timezone":"Europe/Belgrade",
    "iso:country":"RS",
    "name:bos_x_preferred":[
        "Strane"
    ],
    "name:hrv_x_preferred":[
        "Strane"
    ],
    "name:nld_x_preferred":[
        "Strane"
    ],
    "name:pol_x_preferred":[
        "Strane"
    ],
    "name:ron_x_preferred":[
        "Strane"
    ],
    "name:slv_x_preferred":[
        "Strane"
    ],
    "name:srp_x_preferred":[
        "Strane"
    ],
    "name:ukr_x_preferred":[
        "\u0421\u0442\u0440\u0430\u043d\u0435"
    ],
    "wof:name":"Strane",
    "wof:placetype":"locality"
},
  "geometry": {"coordinates":[19.80836,43.16702],"type":"Point"}
}