{
  "type": "Feature",
  "properties": {
    "gn:admin1_code":"SE",
    "gn:admin2_code":"17",
    "gn:asciiname":"Sabanovici",
    "gn:country_code":"RS",
    "gn:dem":1098,
    "gn:feature_class":"P",
    "gn:feature_code":"PPL",
    "gn:name":"\u0160abanovi\u0107i",
    "gn:population":0,
    "gn:timezone":"Europe/Belgrade",
    "iso:country":"RS",
    "name:srp_x_preferred":[
        "\u0160abanovi\u0107i"
    ],
    "wof:name":"Sabanovici",
    "wof:placetype":"locality"
},
  "geometry": {"coordinates":[20.05337,43.40749],"type":"Point"}
}