{
  "type": "Feature",
  "properties": {
    "gn:admin1_code":"SE",
    "gn:admin2_code":"24",
    "gn:asciiname":"Golocevac",
    "gn:country_code":"RS",
    "gn:dem":1103,
    "gn:feature_class":"P",
    "gn:feature_code":"PPLL",
    "gn:name":"Golo\u010devac",
    "gn:population":0,
    "gn:timezone":"Europe/Belgrade",
    "iso:country":"RS",
    "name:srp_x_preferred":[
        "Golo\u010devac"
    ],
    "name:und_x_variant":[
        "Golo\u010devce"
    ],
    "wof:name":"Golocevac",
    "wof:placetype":"locality"
},
  "geometry": {"coordinates":[22.1327,42.40162],"type":"Point"}
}