{
  "type": "Feature",
  "properties": {
    "gn:admin1_code":"SE",
    "gn:admin2_code":"8",
    "gn:asciiname":"Kujavica",
    "gn:country_code":"RS",
    "gn:dem":116,
    "gn:feature_class":"P",
    "gn:feature_code":"PPL",
    "gn:name":"Kujavica",
    "gn:population":0,
    "gn:timezone":"Europe/Belgrade",
    "iso:country":"RS",
    "name:ceb_x_preferred":[
        "Kujavica"
    ],
    "name:fra_x_preferred":[
        "Kujavica"
    ],
    "name:msa_x_preferred":[
        "Kujavica"
    ],
    "name:nld_x_preferred":[
        "Kujavica"
    ],
    "name:por_x_preferred":[
        "Kujavica"
    ],
    "name:slv_x_preferred":[
        "Kujavica"
    ],
    "name:srp_x_preferred":[
        "Kujavica"
    ],
    "name:srp_x_variant":[
        "\u041a\u0443\u0458\u0430\u0432\u0438\u0446\u0430"
    ],
    "wof:name":"Kujavica",
    "wof:placetype":"locality"
},
  "geometry": {"coordinates":[19.80373,44.68041],"type":"Point"}
}