{
  "type": "Feature",
  "properties": {
    "gn:admin1_code":"SE",
    "gn:admin2_code":"20",
    "gn:asciiname":"Crni Kao",
    "gn:country_code":"RS",
    "gn:dem":398,
    "gn:feature_class":"P",
    "gn:feature_code":"PPL",
    "gn:name":"Crni Kao",
    "gn:population":0,
    "gn:timezone":"Europe/Belgrade",
    "iso:country":"RS",
    "name:srp_x_preferred":[
        "Crni Kao"
    ],
    "wof:name":"Crni Kao",
    "wof:placetype":"locality"
},
  "geometry": {"coordinates":[21.62172,43.66517],"type":"Point"}
}