{
  "type": "Feature",
  "properties": {
    "gn:admin1_code":"SE",
    "gn:admin2_code":"0",
    "gn:asciiname":"Trudbenik",
    "gn:country_code":"RS",
    "gn:dem":75,
    "gn:feature_class":"P",
    "gn:feature_code":"PPL",
    "gn:name":"Trudbenik",
    "gn:population":0,
    "gn:timezone":"Europe/Belgrade",
    "iso:country":"RS",
    "wof:name":"Trudbenik",
    "wof:placetype":"locality"
},
  "geometry": {"coordinates":[20.16004,44.67333],"type":"Point"}
}