{
  "type": "Feature",
  "properties": {
    "gn:admin1_code":"SE",
    "gn:admin2_code":"11",
    "gn:admin3_code":"70912.0",
    "gn:asciiname":"Veliko Laole",
    "gn:country_code":"RS",
    "gn:dem":147,
    "gn:feature_class":"P",
    "gn:feature_code":"PPL",
    "gn:name":"Veliko Laole",
    "gn:population":0,
    "gn:timezone":"Europe/Belgrade",
    "iso:country":"RS",
    "name:ceb_x_preferred":[
        "Veliko Laole"
    ],
    "name:fas_x_preferred":[
        "\u0648\u0644\u06cc\u06a9\u0648 \u0644\u0644"
    ],
    "name:fra_x_preferred":[
        "Veliko Laole"
    ],
    "name:msa_x_preferred":[
        "Veliko Laole"
    ],
    "name:por_x_preferred":[
        "Veliko Laole"
    ],
    "name:slv_x_preferred":[
        "Veliko Laole"
    ],
    "name:srp_x_preferred":[
        "Veliko Laole"
    ],
    "name:srp_x_variant":[
        "\u0412\u0435\u043b\u0438\u043a\u043e \u041b\u0430\u043e\u043b\u0435"
    ],
    "wof:name":"Veliko Laole",
    "wof:placetype":"locality"
},
  "geometry": {"coordinates":[21.43122,44.31947],"type":"Point"}
}