{
  "type": "Feature",
  "properties": {
    "gn:country":"RS",
    "gn:fcode":"PPL",
    "gn:pop":5,
    "iso:country":"RS",
    "name:srp_x_preferred":[
        "Rudine"
    ],
    "qs:name":"Rudine",
    "qs:photos_9r":0,
    "qs:photos_sr":0,
    "qs:pop_sr":"1",
    "wd:wordcount":69,
    "wof:name":"Rudine",
    "wof:placetype":"locality",
    "wof:population":5
},
  "geometry": {"coordinates":[20.40669,43.52347],"type":"Point"}
}