{
  "type": "Feature",
  "properties": {
    "gn:country":"RS",
    "gn:fcode":"PPL",
    "gn:population":5,
    "iso:country":"RS",
    "name:bos_x_preferred":[
        "Rudine"
    ],
    "name:ceb_x_preferred":[
        "\u0420\u0443\u0434\u0438\u043d\u0435"
    ],
    "name:eng_x_preferred":[
        "Rudine"
    ],
    "name:fra_x_preferred":[
        "Rudine"
    ],
    "name:hrv_x_preferred":[
        "Rudine"
    ],
    "name:hun_x_preferred":[
        "Rudine"
    ],
    "name:nld_x_preferred":[
        "Rudine"
    ],
    "name:slv_x_preferred":[
        "Rudine"
    ],
    "name:srp_x_preferred":[
        "Rudine"
    ],
    "name:srp_x_variant":[
        "\u0420\u0443\u0434\u0438\u043d\u0435"
    ],
    "name:swe_x_preferred":[
        "Rudine"
    ],
    "qs:name":"Rudine",
    "qs:photos_9r":0,
    "qs:photos_sr":0,
    "qs:pop_sr":"1",
    "wd:wordcount":69,
    "wof:name":"Rudine",
    "wof:placetype":"locality",
    "wof:population":5
},
  "geometry": {"coordinates":[20.40669,43.52347],"type":"Point"}
}