{
  "type": "Feature",
  "properties": {
    "gn:admin1_code":"SE",
    "gn:admin2_code":"22",
    "gn:asciiname":"Strbovac",
    "gn:country_code":"RS",
    "gn:dem":818,
    "gn:feature_class":"P",
    "gn:feature_code":"PPL",
    "gn:name":"\u0160trbovac",
    "gn:population":0,
    "gn:timezone":"Europe/Belgrade",
    "iso:country":"RS",
    "name:ceb_x_preferred":[
        "\u0160trbovac"
    ],
    "name:fra_x_preferred":[
        "\u0160trbovac"
    ],
    "name:hun_x_preferred":[
        "\u0160trbovac"
    ],
    "name:msa_x_preferred":[
        "\u0160trbovac"
    ],
    "name:por_x_preferred":[
        "\u0160trbovac"
    ],
    "name:slv_x_preferred":[
        "\u0160trbovac"
    ],
    "name:srp_x_preferred":[
        "\u0160trbovac"
    ],
    "name:srp_x_variant":[
        "\u0428\u0442\u0440\u0431\u043e\u0432\u0430\u0446"
    ],
    "wof:name":"Strbovac",
    "wof:placetype":"locality"
},
  "geometry": {"coordinates":[22.26052,43.08978],"type":"Point"}
}