{
  "type": "Feature",
  "properties": {
    "gn:admin1_code":"SE",
    "gn:admin2_code":"9",
    "gn:asciiname":"Savatici",
    "gn:country_code":"RS",
    "gn:dem":516,
    "gn:feature_class":"P",
    "gn:feature_code":"PPL",
    "gn:name":"Savati\u0107i",
    "gn:population":0,
    "gn:timezone":"Europe/Belgrade",
    "iso:country":"RS",
    "name:srp_x_preferred":[
        "Savati\u0107i"
    ],
    "wof:name":"Savatici",
    "wof:placetype":"locality"
},
  "geometry": {"coordinates":[19.55903,44.27487],"type":"Point"}
}