{
  "type": "Feature",
  "properties": {
    "gn:admin1_code":"SE",
    "gn:admin2_code":"23",
    "gn:asciiname":"Srednji Bucumet",
    "gn:country_code":"RS",
    "gn:dem":524,
    "gn:feature_class":"P",
    "gn:feature_code":"PPL",
    "gn:name":"Srednji Bu\u010dumet",
    "gn:population":0,
    "gn:timezone":"Europe/Belgrade",
    "iso:country":"RS",
    "name:ceb_x_preferred":[
        "Srednji Bu\u010dumet"
    ],
    "name:fra_x_preferred":[
        "Srednji Bu\u010dumet"
    ],
    "name:msa_x_preferred":[
        "Srednji Bu\u010dumet"
    ],
    "name:por_x_preferred":[
        "Srednji Bu\u010dumet"
    ],
    "name:slv_x_preferred":[
        "Srednji Bu\u010dumet"
    ],
    "name:srp_x_preferred":[
        "Srednji Bu\u010dumet"
    ],
    "name:srp_x_variant":[
        "\u0421\u0440\u0435\u0434\u045a\u0438 \u0411\u0443\u0447\u0443\u043c\u0435\u0442"
    ],
    "wof:name":"Srednji Bucumet",
    "wof:placetype":"locality"
},
  "geometry": {"coordinates":[21.61077,42.92131],"type":"Point"}
}