{
  "type": "Feature",
  "properties": {
    "gn:admin1_code":"SE",
    "gn:admin2_code":"9",
    "gn:asciiname":"Pridvorica",
    "gn:country_code":"RS",
    "gn:dem":135,
    "gn:feature_class":"P",
    "gn:feature_code":"PPL",
    "gn:name":"Pridvorica",
    "gn:population":0,
    "gn:timezone":"Europe/Belgrade",
    "iso:country":"RS",
    "name:bos_x_preferred":[
        "Pridvorica"
    ],
    "name:ceb_x_preferred":[
        "Pridvorica"
    ],
    "name:fra_x_preferred":[
        "Pridvorica"
    ],
    "name:hrv_x_preferred":[
        "Pridvorica"
    ],
    "name:slv_x_preferred":[
        "Pridvorica"
    ],
    "name:srp_x_preferred":[
        "Pridvorica"
    ],
    "name:srp_x_variant":[
        "\u041f\u0440\u0438\u0434\u0432\u043e\u0440\u0438\u0446\u0430"
    ],
    "name:swe_x_preferred":[
        "Pridvorica"
    ],
    "wof:name":"Pridvorica",
    "wof:placetype":"locality"
},
  "geometry": {"coordinates":[20.12893,44.33355],"type":"Point"}
}