{
  "type": "Feature",
  "properties": {
    "gn:admin1_code":"SE",
    "gn:admin2_code":"23",
    "gn:asciiname":"Gornje Vranovce",
    "gn:country_code":"RS",
    "gn:dem":321,
    "gn:feature_class":"P",
    "gn:feature_code":"PPL",
    "gn:name":"Gornje Vranovce",
    "gn:population":0,
    "gn:timezone":"Europe/Belgrade",
    "iso:country":"RS",
    "name:ceb_x_preferred":[
        "Gornje Vranovce"
    ],
    "name:fra_x_preferred":[
        "Gornje Vranovce"
    ],
    "name:msa_x_preferred":[
        "Gornje Vranovce"
    ],
    "name:por_x_preferred":[
        "Gornje Vranovce"
    ],
    "name:slv_x_preferred":[
        "Donje Vranovce"
    ],
    "name:srp_x_preferred":[
        "Gornje Vranovce"
    ],
    "name:srp_x_variant":[
        "\u0413\u043e\u0440\u045a\u0435 \u0412\u0440\u0430\u043d\u043e\u0432\u0446\u0435"
    ],
    "name:und_x_variant":[
        "Vranovce"
    ],
    "wof:name":"Gornje Vranovce",
    "wof:placetype":"locality"
},
  "geometry": {"coordinates":[21.76056,42.88193],"type":"Point"}
}