{
  "type": "Feature",
  "properties": {
    "gn:admin1_code":"SE",
    "gn:admin2_code":"11",
    "gn:asciiname":"Makce",
    "gn:country_code":"RS",
    "gn:dem":209,
    "gn:feature_class":"P",
    "gn:feature_code":"PPL",
    "gn:name":"Makce",
    "gn:population":0,
    "gn:timezone":"Europe/Belgrade",
    "iso:country":"RS",
    "name:ceb_x_preferred":[
        "Makce"
    ],
    "name:fra_x_preferred":[
        "Makce"
    ],
    "name:msa_x_preferred":[
        "Makce"
    ],
    "name:por_x_preferred":[
        "Makce"
    ],
    "name:slv_x_preferred":[
        "Makce"
    ],
    "name:srp_x_preferred":[
        "Makce"
    ],
    "name:srp_x_variant":[
        "\u041c\u0430\u043a\u0446\u0435"
    ],
    "name:und_x_variant":[
        "Makci"
    ],
    "wof:name":"Makce",
    "wof:placetype":"locality"
},
  "geometry": {"coordinates":[21.46652000000001,44.57702000000001],"type":"Point"}
}