{
  "type": "Feature",
  "properties": {
    "gn:admin1_code":"SE",
    "gn:admin2_code":"17",
    "gn:asciiname":"Ravna Gora",
    "gn:country_code":"RS",
    "gn:dem":932,
    "gn:feature_class":"P",
    "gn:feature_code":"PPLL",
    "gn:name":"Ravna Gora",
    "gn:population":0,
    "gn:timezone":"Europe/Belgrade",
    "iso:country":"RS",
    "name:fas_x_preferred":[
        "\u06cc\u0627\u0648\u0648\u0631\u0633\u06a9\u0627 \u0631\u0627\u0648\u0646\u0627 \u06af\u0648\u0631\u0627"
    ],
    "name:fra_x_preferred":[
        "Javorska Ravna Gora"
    ],
    "name:msa_x_preferred":[
        "Javorska Ravna Gora"
    ],
    "name:por_x_preferred":[
        "Javorska Ravna Gora"
    ],
    "name:slv_x_preferred":[
        "Javorska Ravna Gora"
    ],
    "name:srp_x_preferred":[
        "Ravna Gora"
    ],
    "name:srp_x_variant":[
        "\u0408\u0430\u0432\u043e\u0440\u0441\u043a\u0430 \u0420\u0430\u0432\u043d\u0430 \u0413\u043e\u0440\u0430"
    ],
    "name:und_x_variant":[
        "Javorska Ravna Gora"
    ],
    "name:urd_x_preferred":[
        "\u062c\u0648\u0648\u0631\u0633\u06a9\u0627 \u0631\u0648\u0646\u0627 \u06af\u0648\u0631\u0627"
    ],
    "wof:name":"Ravna Gora",
    "wof:placetype":"locality"
},
  "geometry": {"coordinates":[20.10251,43.47063],"type":"Point"}
}