{
  "type": "Feature",
  "properties": {
    "gn:admin1_code":"SE",
    "gn:admin2_code":"17",
    "gn:asciiname":"Ravna Gora",
    "gn:country_code":"RS",
    "gn:dem":932,
    "gn:feature_class":"P",
    "gn:feature_code":"PPLL",
    "gn:name":"Ravna Gora",
    "gn:population":0,
    "gn:timezone":"Europe/Belgrade",
    "iso:country":"RS",
    "name:srp_x_preferred":[
        "Ravna Gora"
    ],
    "name:und_x_variant":[
        "Javorska Ravna Gora"
    ],
    "wof:name":"Ravna Gora",
    "wof:placetype":"locality"
},
  "geometry": {"coordinates":[20.10251,43.47063],"type":"Point"}
}