{
  "type": "Feature",
  "properties": {
    "gn:admin1_code":"SE",
    "gn:admin2_code":"16",
    "gn:asciiname":"Biskupici",
    "gn:country_code":"RS",
    "gn:dem":1323,
    "gn:feature_class":"P",
    "gn:feature_code":"PPL",
    "gn:name":"Biskupi\u0107i",
    "gn:population":0,
    "gn:timezone":"Europe/Belgrade",
    "iso:country":"RS",
    "name:fra_x_preferred":[
        "Biskupi\u0107i"
    ],
    "name:nld_x_preferred":[
        "Biskupi\u0107i"
    ],
    "name:por_x_preferred":[
        "Biskupi\u0107i"
    ],
    "name:slv_x_preferred":[
        "Biskupi\u0107i"
    ],
    "name:srp_x_preferred":[
        "Biskupi\u0107i"
    ],
    "name:srp_x_variant":[
        "\u0411\u0438\u0441\u043a\u0443\u043f\u0438\u045b\u0438"
    ],
    "wof:name":"Biskupici",
    "wof:placetype":"locality"
},
  "geometry": {"coordinates":[19.78333,43.36583],"type":"Point"}
}