{
  "type": "Feature",
  "properties": {
    "gn:admin1_code":"SE",
    "gn:admin2_code":"14",
    "gn:asciiname":"Brza Palanka",
    "gn:country_code":"RS",
    "gn:dem":78,
    "gn:feature_class":"P",
    "gn:feature_code":"PPL",
    "gn:name":"Brza Palanka",
    "gn:population":0,
    "gn:timezone":"Europe/Belgrade",
    "iso:country":"RS",
    "name:ara_x_preferred":[
        "\u0628\u0631\u0632\u0627 \u0628\u0627\u0644\u0627\u0646\u0643\u0627"
    ],
    "name:bul_x_preferred":[
        "\u0411\u044a\u0440\u0437\u0430 \u043f\u0430\u043b\u0430\u043d\u043a\u0430"
    ],
    "name:ceb_x_preferred":[
        "Brza Palanka"
    ],
    "name:deu_x_preferred":[
        "Brza Palanka"
    ],
    "name:fra_x_preferred":[
        "Brza Palanka"
    ],
    "name:mkd_x_preferred":[
        "\u0411\u0440\u0437\u0430 \u041f\u0430\u043b\u0430\u043d\u043a\u0430"
    ],
    "name:msa_x_preferred":[
        "Brza Palanka"
    ],
    "name:por_x_preferred":[
        "Brza Palanka"
    ],
    "name:ron_x_preferred":[
        "Brza Palanka"
    ],
    "name:rus_x_preferred":[
        "\u0411\u0440\u0437\u0430-\u041f\u0430\u043b\u0430\u043d\u043a\u0430"
    ],
    "name:slv_x_preferred":[
        "Brza Palanka"
    ],
    "name:srp_x_preferred":[
        "Brza Palanka"
    ],
    "name:srp_x_variant":[
        "\u0411\u0440\u0437\u0430 \u041f\u0430\u043b\u0430\u043d\u043a\u0430"
    ],
    "wof:name":"Brza Palanka",
    "wof:placetype":"locality"
},
  "geometry": {"coordinates":[22.4462,44.4702],"type":"Point"}
}