{
  "type": "Feature",
  "properties": {
    "gn:admin1_code":"SE",
    "gn:admin2_code":"21",
    "gn:asciiname":"Gornji Petrovac",
    "gn:country_code":"RS",
    "gn:dem":499,
    "gn:feature_class":"P",
    "gn:feature_code":"PPL",
    "gn:name":"Gornji Petrovac",
    "gn:population":0,
    "gn:timezone":"Europe/Belgrade",
    "iso:country":"RS",
    "wof:name":"Gornji Petrovac",
    "wof:placetype":"locality"
},
  "geometry": {"coordinates":[21.56972,43.32806],"type":"Point"}
}