{
  "type": "Feature",
  "properties": {
    "gn:admin1_code":"SE",
    "gn:admin2_code":"19",
    "gn:asciiname":"Mudrakovac",
    "gn:country_code":"RS",
    "gn:dem":170,
    "gn:feature_class":"P",
    "gn:feature_code":"PPL",
    "gn:name":"Mudrakovac",
    "gn:population":0,
    "gn:timezone":"Europe/Belgrade",
    "iso:country":"RS",
    "name:ceb_x_preferred":[
        "Mudrakovac"
    ],
    "name:fra_x_preferred":[
        "Mudrakovac"
    ],
    "name:msa_x_preferred":[
        "Mudrakovac"
    ],
    "name:por_x_preferred":[
        "Mudrakovac"
    ],
    "name:slv_x_preferred":[
        "Mudrakovac"
    ],
    "name:srp_x_preferred":[
        "Mudrakovac"
    ],
    "name:srp_x_variant":[
        "\u041c\u0443\u0434\u0440\u0430\u043a\u043e\u0432\u0430\u0446"
    ],
    "wof:name":"Mudrakovac",
    "wof:placetype":"locality"
},
  "geometry": {"coordinates":[21.33916,43.55134],"type":"Point"}
}