{
  "type": "Feature",
  "properties": {
    "gn:admin1_code":"SE",
    "gn:admin2_code":"23",
    "gn:asciiname":"Stubla",
    "gn:country_code":"RS",
    "gn:dem":711,
    "gn:feature_class":"P",
    "gn:feature_code":"PPLL",
    "gn:name":"Stubla",
    "gn:population":0,
    "gn:timezone":"Europe/Belgrade",
    "iso:country":"RS",
    "name:ceb_x_preferred":[
        "Stubla"
    ],
    "name:fra_x_preferred":[
        "Stubla"
    ],
    "name:hrv_x_preferred":[
        "Stubla"
    ],
    "name:slv_x_preferred":[
        "Stubla"
    ],
    "name:srp_x_preferred":[
        "Stubla"
    ],
    "name:srp_x_variant":[
        "\u0421\u0442\u0443\u0431\u043b\u0430"
    ],
    "name:swe_x_preferred":[
        "Stubla"
    ],
    "wof:name":"Stubla",
    "wof:placetype":"locality"
},
  "geometry": {"coordinates":[21.49019,42.88421],"type":"Point"}
}