{
  "type": "Feature",
  "properties": {
    "gn:admin1_code":"SE",
    "gn:admin2_code":"16",
    "gn:asciiname":"Cubraci",
    "gn:country_code":"RS",
    "gn:dem":841,
    "gn:feature_class":"P",
    "gn:feature_code":"PPLL",
    "gn:name":"\u010cubraci",
    "gn:population":0,
    "gn:timezone":"Europe/Belgrade",
    "iso:country":"RS",
    "name:srp_x_preferred":[
        "\u010cubraci"
    ],
    "wof:name":"Cubraci",
    "wof:placetype":"locality"
},
  "geometry": {"coordinates":[19.89429,43.61697],"type":"Point"}
}