{
  "type": "Feature",
  "properties": {
    "gn:admin1_code":"SE",
    "gn:admin2_code":"11",
    "gn:asciiname":"Dubocka",
    "gn:country_code":"RS",
    "gn:dem":193,
    "gn:feature_class":"P",
    "gn:feature_code":"PPL",
    "gn:name":"Dubo\u010dka",
    "gn:population":0,
    "gn:timezone":"Europe/Belgrade",
    "iso:country":"RS",
    "name:ceb_x_preferred":[
        "Dubo\u010dka"
    ],
    "name:fra_x_preferred":[
        "Dubo\u010dka"
    ],
    "name:msa_x_preferred":[
        "Dubo\u010dka"
    ],
    "name:por_x_preferred":[
        "Dubo\u010dka"
    ],
    "name:slv_x_preferred":[
        "Dubo\u010dka"
    ],
    "name:srp_x_preferred":[
        "Dubo\u010dka"
    ],
    "name:srp_x_variant":[
        "\u0414\u0443\u0431\u043e\u0447\u043a\u0430"
    ],
    "wof:name":"Dubocka",
    "wof:placetype":"locality"
},
  "geometry": {"coordinates":[21.37204,44.44468],"type":"Point"}
}