{
  "type": "Feature",
  "properties": {
    "gn:admin1_code":"SE",
    "gn:admin2_code":"17",
    "gn:asciiname":"Popovici",
    "gn:country_code":"RS",
    "gn:dem":1051,
    "gn:feature_class":"P",
    "gn:feature_code":"PPL",
    "gn:name":"Popovi\u0107i",
    "gn:population":0,
    "gn:timezone":"Europe/Belgrade",
    "iso:country":"RS",
    "name:heb_x_preferred":[
        "\u05e4\u05d5\u05e4\u05d5\u05d1\u05d9\u05e5'"
    ],
    "name:srp_x_preferred":[
        "Popovi\u0107i"
    ],
    "wof:name":"Popovici",
    "wof:placetype":"locality"
},
  "geometry": {"coordinates":[20.11739,43.45682],"type":"Point"}
}