{
  "type": "Feature",
  "properties": {
    "gn:admin1_code":"SE",
    "gn:admin2_code":"16",
    "gn:asciiname":"Donje Zaselje",
    "gn:country_code":"RS",
    "gn:dem":373,
    "gn:feature_class":"P",
    "gn:feature_code":"PPL",
    "gn:name":"Donje Zaselje",
    "gn:population":0,
    "gn:timezone":"Europe/Belgrade",
    "iso:country":"RS",
    "name:srp_x_preferred":[
        "Donje Zaselje"
    ],
    "name:und_x_variant":[
        "Donje Selo"
    ],
    "wof:name":"Donje Zaselje",
    "wof:placetype":"locality"
},
  "geometry": {"coordinates":[19.98389,43.91861],"type":"Point"}
}