{
  "type": "Feature",
  "properties": {
    "gn:admin1_code":"SE",
    "gn:admin2_code":"16",
    "gn:asciiname":"Milekici",
    "gn:country_code":"RS",
    "gn:dem":960,
    "gn:feature_class":"P",
    "gn:feature_code":"PPL",
    "gn:name":"Mileki\u0107i",
    "gn:population":0,
    "gn:timezone":"Europe/Belgrade",
    "iso:country":"RS",
    "name:srp_x_preferred":[
        "Mileki\u0107i"
    ],
    "wof:name":"Milekici",
    "wof:placetype":"locality"
},
  "geometry": {"coordinates":[19.40172,43.88689],"type":"Point"}
}