{
  "type": "Feature",
  "properties": {
    "gn:admin1_code":"SE",
    "gn:admin2_code":"24",
    "gn:asciiname":"Nesvrta",
    "gn:country_code":"RS",
    "gn:dem":1242,
    "gn:feature_class":"P",
    "gn:feature_code":"PPL",
    "gn:name":"Nesvrta",
    "gn:population":0,
    "gn:timezone":"Europe/Belgrade",
    "iso:country":"RS",
    "name:srp_x_preferred":[
        "Nesvrta"
    ],
    "wof:name":"Nesvrta",
    "wof:placetype":"locality"
},
  "geometry": {"coordinates":[22.13509,42.58173],"type":"Point"}
}