{
  "type": "Feature",
  "properties": {
    "gn:admin1_code":"SE",
    "gn:admin2_code":"9",
    "gn:asciiname":"Klasnic",
    "gn:country_code":"RS",
    "gn:dem":181,
    "gn:feature_class":"P",
    "gn:feature_code":"PPL",
    "gn:name":"Kla\u0161ni\u0107",
    "gn:population":0,
    "gn:timezone":"Europe/Belgrade",
    "iso:country":"RS",
    "name:ceb_x_preferred":[
        "Kla\u0161ni\u0107"
    ],
    "name:fra_x_preferred":[
        "Kla\u0161ni\u0107"
    ],
    "name:msa_x_preferred":[
        "Kla\u0161ni\u0107"
    ],
    "name:por_x_preferred":[
        "Kla\u0161ni\u0107"
    ],
    "name:slv_x_preferred":[
        "Kla\u0161ni\u0107"
    ],
    "name:srp_x_preferred":[
        "\u041a\u043b\u0430\u0448\u043d\u0438\u045b"
    ],
    "wof:name":"Klasnic",
    "wof:placetype":"locality"
},
  "geometry": {"coordinates":[20.03767,44.28068],"type":"Point"}
}