{
  "type": "Feature",
  "properties": {
    "gn:admin1_code":"SE",
    "gn:admin2_code":"9",
    "gn:asciiname":"Klasnic",
    "gn:country_code":"RS",
    "gn:dem":181,
    "gn:feature_class":"P",
    "gn:feature_code":"PPL",
    "gn:name":"Kla\u0161ni\u0107",
    "gn:population":0,
    "gn:timezone":"Europe/Belgrade",
    "iso:country":"RS",
    "name:und_x_variant":[
        "Kla\u0161ni\u0107"
    ],
    "wof:name":"Klasnic",
    "wof:placetype":"locality"
},
  "geometry": {"coordinates":[20.03767,44.28068],"type":"Point"}
}