{
  "type": "Feature",
  "properties": {
    "gn:admin1_code":"SE",
    "gn:admin2_code":"19",
    "gn:asciiname":"Sarenica",
    "gn:country_code":"RS",
    "gn:dem":662,
    "gn:feature_class":"P",
    "gn:feature_code":"PPL",
    "gn:name":"\u0160arenica",
    "gn:population":0,
    "gn:timezone":"Europe/Belgrade",
    "iso:country":"RS",
    "name:srp_x_preferred":[
        "\u0160arenica"
    ],
    "wof:name":"Sarenica",
    "wof:placetype":"locality"
},
  "geometry": {"coordinates":[21.04111,43.31306],"type":"Point"}
}