{
  "type": "Feature",
  "properties": {
    "gn:admin1_code":"SE",
    "gn:admin2_code":"18",
    "gn:asciiname":"Popova Reka",
    "gn:country_code":"RS",
    "gn:dem":631,
    "gn:feature_class":"P",
    "gn:feature_code":"PPLL",
    "gn:name":"Popova Reka",
    "gn:population":0,
    "gn:timezone":"Europe/Belgrade",
    "iso:country":"RS",
    "name:srp_x_preferred":[
        "Popova Reka"
    ],
    "wof:name":"Popova Reka",
    "wof:placetype":"locality"
},
  "geometry": {"coordinates":[20.65778,43.49556],"type":"Point"}
}