{
  "type": "Feature",
  "properties": {
    "gn:admin1_code":"SE",
    "gn:admin2_code":"18",
    "gn:asciiname":"Goc",
    "gn:country_code":"RS",
    "gn:dem":1028,
    "gn:feature_class":"P",
    "gn:feature_code":"PPL",
    "gn:name":"Go\u010d",
    "gn:population":0,
    "gn:timezone":"Europe/Belgrade",
    "iso:country":"RS",
    "name:srp_x_preferred":[
        "Go\u010d"
    ],
    "wof:name":"Goc",
    "wof:placetype":"locality"
},
  "geometry": {"coordinates":[20.82723,43.53844],"type":"Point"}
}