{
  "type": "Feature",
  "properties": {
    "iso:country":"RS",
    "name:eng_x_preferred":[
        "Skadarlija"
    ],
    "name:srp_cyr_x_preferred":[
        "\u0421\u043a\u0430\u0434\u0430\u0440\u043b\u0438\u0458\u0430"
    ],
    "name:srp_x_preferred":[
        "\u0421\u043a\u0430\u0434\u0430\u0440\u043b\u0438\u0458\u0430"
    ],
    "wof:name":"Skadarlija",
    "wof:placetype":"neighbourhood"
},
  "geometry": {"coordinates":[20.46439917332313,44.81812473851062],"type":"Point"}
}