{
  "type": "Feature",
  "properties": {
    "gn:admin1_code":"SE",
    "gn:admin2_code":"15",
    "gn:asciiname":"Vlasko Selo",
    "gn:country_code":"RS",
    "gn:dem":492,
    "gn:feature_class":"P",
    "gn:feature_code":"PPL",
    "gn:name":"Vla\u0161ko Selo",
    "gn:population":0,
    "gn:timezone":"Europe/Belgrade",
    "iso:country":"RS",
    "wof:name":"Vlasko Selo",
    "wof:placetype":"locality"
},
  "geometry": {"coordinates":[21.80648,43.72104],"type":"Point"}
}