{
  "type": "Feature",
  "properties": {
    "gn:admin1_code":"SE",
    "gn:admin2_code":"24",
    "gn:asciiname":"Crni Vrh",
    "gn:country_code":"RS",
    "gn:dem":1181,
    "gn:feature_class":"P",
    "gn:feature_code":"PPL",
    "gn:name":"Crni Vrh",
    "gn:population":0,
    "gn:timezone":"Europe/Belgrade",
    "iso:country":"RS",
    "name:bos_x_preferred":[
        "Crni vrh"
    ],
    "name:ceb_x_preferred":[
        "Crni Vrh"
    ],
    "name:deu_x_preferred":[
        "Crni Vrh"
    ],
    "name:fra_x_preferred":[
        "Crni Vrh"
    ],
    "name:hrv_x_preferred":[
        "Crni Vrh"
    ],
    "name:slv_x_preferred":[
        "Crni Vrh"
    ],
    "name:srp_x_preferred":[
        "Crni Vrh"
    ],
    "name:srp_x_variant":[
        "\u0426\u0440\u043d\u0438 \u0412\u0440\u0445"
    ],
    "name:swe_x_preferred":[
        "Crni Vrh"
    ],
    "wof:name":"Crni Vrh",
    "wof:placetype":"locality"
},
  "geometry": {"coordinates":[22.13382,42.5187],"type":"Point"}
}