{
  "type": "Feature",
  "properties": {
    "gn:admin1_code":"SE",
    "gn:admin2_code":"24",
    "gn:asciiname":"Bobajaninci",
    "gn:country_code":"RS",
    "gn:dem":1187,
    "gn:feature_class":"P",
    "gn:feature_code":"PPL",
    "gn:name":"Bobajaninci",
    "gn:population":0,
    "gn:timezone":"Europe/Belgrade",
    "iso:country":"RS",
    "wof:name":"Bobajaninci",
    "wof:placetype":"locality"
},
  "geometry": {"coordinates":[22.135,42.4375],"type":"Point"}
}