{
  "type": "Feature",
  "properties": {
    "gn:admin1_code":"SE",
    "gn:admin2_code":"17",
    "gn:asciiname":"Vlasteljice",
    "gn:country_code":"RS",
    "gn:dem":564,
    "gn:feature_class":"P",
    "gn:feature_code":"PPLL",
    "gn:name":"Vlasteljice",
    "gn:population":0,
    "gn:timezone":"Europe/Belgrade",
    "iso:country":"RS",
    "name:ceb_x_preferred":[
        "Vlasteljice"
    ],
    "name:fra_x_preferred":[
        "Vlasteljice"
    ],
    "name:msa_x_preferred":[
        "Vlasteljice"
    ],
    "name:por_x_preferred":[
        "Vlasteljice"
    ],
    "name:slv_x_preferred":[
        "Vlasteljice"
    ],
    "name:srp_x_preferred":[
        "Vlasteljice"
    ],
    "name:srp_x_variant":[
        "\u0412\u043b\u0430\u0441\u0442\u0435\u0459\u0438\u0446\u0435"
    ],
    "wof:name":"Vlasteljice",
    "wof:placetype":"locality"
},
  "geometry": {"coordinates":[20.40004,43.71689],"type":"Point"}
}