{
  "type": "Feature",
  "properties": {
    "gn:country":"RS",
    "gn:fcode":"PPL",
    "gn:population":1227,
    "iso:country":"RS",
    "name:eng_x_preferred":[
        "Petkovica"
    ],
    "name:fra_x_preferred":[
        "Petkovica"
    ],
    "name:msa_x_preferred":[
        "Petkovica"
    ],
    "name:por_x_preferred":[
        "Petkovica"
    ],
    "name:slv_x_preferred":[
        "Petkovica"
    ],
    "name:srp_x_preferred":[
        "Petkovica"
    ],
    "name:srp_x_variant":[
        "\u041f\u0435\u0442\u043a\u043e\u0432\u0438\u0446\u0430"
    ],
    "qs:name":"Petkovica",
    "qs:photos_9r":0,
    "qs:photos_sr":0,
    "qs:pop_sr":"3",
    "wof:name":"Petkovica",
    "wof:placetype":"locality",
    "wof:population":1227
},
  "geometry": {"coordinates":[19.43923,44.66627],"type":"Point"}
}