{
  "type": "Feature",
  "properties": {
    "gn:admin1_code":"SE",
    "gn:admin2_code":"8",
    "gn:asciiname":"Jevtici",
    "gn:country_code":"RS",
    "gn:dem":295,
    "gn:feature_class":"P",
    "gn:feature_code":"PPL",
    "gn:name":"Jevti\u0107i",
    "gn:population":0,
    "gn:timezone":"Europe/Belgrade",
    "iso:country":"RS",
    "name:srp_x_preferred":[
        "Jevti\u0107i"
    ],
    "wof:name":"Jevtici",
    "wof:placetype":"locality"
},
  "geometry": {"coordinates":[19.43806,44.43167],"type":"Point"}
}