{
  "type": "Feature",
  "properties": {
    "gn:admin1_code":"VO",
    "gn:admin2_code":"5",
    "gn:asciiname":"Lugomerci",
    "gn:country_code":"RS",
    "gn:dem":84,
    "gn:feature_class":"P",
    "gn:feature_code":"PPL",
    "gn:name":"Lugomerci",
    "gn:population":0,
    "gn:timezone":"Europe/Belgrade",
    "iso:country":"RS",
    "name:srp_x_preferred":[
        "Lugomerci"
    ],
    "name:und_x_variant":[
        "Lugumerci"
    ],
    "wof:name":"Lugomerci",
    "wof:placetype":"locality"
},
  "geometry": {"coordinates":[19.15471,45.72333],"type":"Point"}
}