{
  "type": "Feature",
  "properties": {
    "gn:asciiname":"Rabe",
    "gn:country_code":"RS",
    "gn:dem":76,
    "gn:feature_class":"P",
    "gn:feature_code":"PPL",
    "gn:name":"Rabe",
    "gn:population":0,
    "gn:timezone":"Europe/Belgrade",
    "iso:country":"RS",
    "name:deu_x_preferred":[
        "Rabe"
    ],
    "name:fra_x_preferred":[
        "Corbeau"
    ],
    "name:hun_x_preferred":[
        "R\u00e1b\u00e9"
    ],
    "name:ita_x_preferred":[
        "Rabe"
    ],
    "name:jpn_x_preferred":[
        "\u30e9\u30fc\u30d9"
    ],
    "name:nno_x_preferred":[
        "Rabe"
    ],
    "name:pol_x_preferred":[
        "Rabe"
    ],
    "name:por_x_preferred":[
        "Rabe"
    ],
    "name:rus_x_preferred":[
        "\u0420\u0430\u0431\u0435"
    ],
    "name:ukr_x_preferred":[
        "\u0420\u0430\u0431\u0435"
    ],
    "wof:name":"Rabe",
    "wof:placetype":"locality"
},
  "geometry": {"coordinates":[20.25381,46.11121],"type":"Point"}
}