{
  "type": "Feature",
  "properties": {
    "gn:admin1_code":"SE",
    "gn:admin2_code":"24",
    "gn:asciiname":"Seliste",
    "gn:country_code":"RS",
    "gn:dem":1304,
    "gn:feature_class":"P",
    "gn:feature_code":"PPL",
    "gn:name":"Seli\u0161te",
    "gn:population":0,
    "gn:timezone":"Europe/Belgrade",
    "iso:country":"RS",
    "wof:name":"Seliste",
    "wof:placetype":"locality"
},
  "geometry": {"coordinates":[22.1868,42.45167],"type":"Point"}
}