{
  "type": "Feature",
  "properties": {
    "gn:admin1_code":"SE",
    "gn:admin2_code":"20",
    "gn:asciiname":"Zubovac",
    "gn:country_code":"RS",
    "gn:dem":380,
    "gn:feature_class":"P",
    "gn:feature_code":"PPL",
    "gn:name":"Zubovac",
    "gn:population":0,
    "gn:timezone":"Europe/Belgrade",
    "iso:country":"RS",
    "name:ceb_x_preferred":[
        "Zubovac"
    ],
    "name:fra_x_preferred":[
        "Zubovac"
    ],
    "name:msa_x_preferred":[
        "Zubovac"
    ],
    "name:por_x_preferred":[
        "Zubovac"
    ],
    "name:slv_x_preferred":[
        "Zubovac"
    ],
    "name:srp_x_preferred":[
        "Zubovac"
    ],
    "name:srp_x_variant":[
        "\u0417\u0443\u0431\u043e\u0432\u0430\u0446"
    ],
    "wof:name":"Zubovac",
    "wof:placetype":"locality"
},
  "geometry": {"coordinates":[21.55088,43.45176],"type":"Point"}
}