{
  "type": "Feature",
  "properties": {
    "gn:admin1_code":"SE",
    "gn:admin2_code":"16",
    "gn:asciiname":"Milovici",
    "gn:country_code":"RS",
    "gn:dem":586,
    "gn:feature_class":"P",
    "gn:feature_code":"PPL",
    "gn:name":"Milovi\u0107i",
    "gn:population":0,
    "gn:timezone":"Europe/Belgrade",
    "iso:country":"RS",
    "name:srp_x_preferred":[
        "Milovi\u0107i"
    ],
    "name:und_x_variant":[
        "Milovi\u0107"
    ],
    "wof:name":"Milovici",
    "wof:placetype":"locality"
},
  "geometry": {"coordinates":[19.88611,43.96833],"type":"Point"}
}