{
  "type": "Feature",
  "properties": {
    "gn:admin1_code":"SE",
    "gn:admin2_code":"24",
    "gn:asciiname":"Stropsko",
    "gn:country_code":"RS",
    "gn:dem":495,
    "gn:feature_class":"P",
    "gn:feature_code":"PPL",
    "gn:name":"Stropsko",
    "gn:population":0,
    "gn:timezone":"Europe/Belgrade",
    "iso:country":"RS",
    "name:bul_x_preferred":[
        "\u0421\u0442\u0440\u043e\u043f\u0441\u043a\u043e"
    ],
    "name:ceb_x_preferred":[
        "Stropsko"
    ],
    "name:fra_x_preferred":[
        "Stropsko"
    ],
    "name:msa_x_preferred":[
        "Stropsko"
    ],
    "name:por_x_preferred":[
        "Stropsko"
    ],
    "name:slv_x_preferred":[
        "Stropsko"
    ],
    "name:sqi_x_preferred":[
        "Stopska"
    ],
    "name:srp_x_preferred":[
        "Stropsko"
    ],
    "name:srp_x_variant":[
        "\u0421\u0442\u0440\u043e\u043f\u0441\u043a\u043e"
    ],
    "wof:name":"Stropsko",
    "wof:placetype":"locality"
},
  "geometry": {"coordinates":[21.8605,42.53186],"type":"Point"}
}