{
  "type": "Feature",
  "properties": {
    "gn:admin1_code":"SE",
    "gn:admin2_code":"17",
    "gn:asciiname":"Disici",
    "gn:country_code":"RS",
    "gn:dem":1141,
    "gn:feature_class":"P",
    "gn:feature_code":"PPL",
    "gn:name":"Disi\u0107i",
    "gn:population":0,
    "gn:timezone":"Europe/Belgrade",
    "iso:country":"RS",
    "name:srp_x_preferred":[
        "Disi\u0107i"
    ],
    "wof:name":"Disici",
    "wof:placetype":"locality"
},
  "geometry": {"coordinates":[20.21854,43.38965],"type":"Point"}
}