{
  "type": "Feature",
  "properties": {
    "gn:admin1_code":"SE",
    "gn:admin2_code":"19",
    "gn:asciiname":"Stevanac",
    "gn:country_code":"RS",
    "gn:dem":170,
    "gn:feature_class":"P",
    "gn:feature_code":"PPL",
    "gn:name":"Stevanac",
    "gn:population":0,
    "gn:timezone":"Europe/Belgrade",
    "iso:country":"RS",
    "name:srp_x_preferred":[
        "Stevanac"
    ],
    "wof:name":"Stevanac",
    "wof:placetype":"locality"
},
  "geometry": {"coordinates":[21.42431,43.65072],"type":"Point"}
}