{
  "type": "Feature",
  "properties": {
    "gn:admin1_code":"SE",
    "gn:admin2_code":"17",
    "gn:asciiname":"Ratari",
    "gn:country_code":"RS",
    "gn:dem":1105,
    "gn:feature_class":"P",
    "gn:feature_code":"PPL",
    "gn:name":"Ratari",
    "gn:population":0,
    "gn:timezone":"Europe/Belgrade",
    "iso:country":"RS",
    "name:fra_x_preferred":[
        "Ratari"
    ],
    "name:slv_x_preferred":[
        "Ratari"
    ],
    "name:srp_x_preferred":[
        "Ratari"
    ],
    "name:srp_x_variant":[
        "\u0420\u0430\u0442\u0430\u0440\u0438"
    ],
    "wof:name":"Ratari",
    "wof:placetype":"locality"
},
  "geometry": {"coordinates":[20.38651,43.38159],"type":"Point"}
}