{
  "type": "Feature",
  "properties": {
    "gn:country":"RS",
    "gn:fcode":"PPL",
    "gn:population":4343,
    "iso:country":"RS",
    "name:ara_x_preferred":[
        "\u0641\u0648\u062c\u0643\u0627\u060c \u0633\u0631\u064a\u0645"
    ],
    "name:ara_x_variant":[
        "\u0641\u0648\u062c\u0643\u0627"
    ],
    "name:arz_x_preferred":[
        "\u0641\u0648\u062c\u0643\u0627"
    ],
    "name:cat_x_preferred":[
        "Vojka"
    ],
    "name:ceb_x_preferred":[
        "Vojka"
    ],
    "name:eng_x_preferred":[
        "Vojka"
    ],
    "name:epo_x_preferred":[
        "Vojka"
    ],
    "name:fas_x_preferred":[
        "\u0648\u0648\u06cc\u06a9\u0627"
    ],
    "name:fin_x_preferred":[
        "Vojka"
    ],
    "name:fra_x_preferred":[
        "Vojka"
    ],
    "name:hrv_x_preferred":[
        "Vojka"
    ],
    "name:hun_x_preferred":[
        "Vajka"
    ],
    "name:msa_x_preferred":[
        "Vojka"
    ],
    "name:nld_x_preferred":[
        "Vojka"
    ],
    "name:pol_x_preferred":[
        "Vojka"
    ],
    "name:slv_x_preferred":[
        "Vojka"
    ],
    "name:spa_x_preferred":[
        "Vojka"
    ],
    "name:srp_x_preferred":[
        "Vojka"
    ],
    "name:srp_x_variant":[
        "\u0412\u043e\u0458\u043a\u0430"
    ],
    "qs:name":"Vojka",
    "qs:name_adm0":"Serbia",
    "qs:name_adm1":"Srem",
    "qs:photos_9k":1,
    "qs:photos_9r":1,
    "qs:photos_all":10,
    "qs:photos_sr":0,
    "qs:placetype":"Town",
    "qs:pop_sr":"4",
    "wd:wordcount":30,
    "wof:name":"Vojka",
    "wof:placetype":"locality",
    "wof:population":4343
},
  "geometry": {"coordinates":[20.15236,44.93713],"type":"Point"}
}