{
  "type": "Feature",
  "properties": {
    "gn:admin1_code":"SE",
    "gn:admin2_code":"16",
    "gn:asciiname":"Branosevac",
    "gn:country_code":"RS",
    "gn:dem":1051,
    "gn:feature_class":"P",
    "gn:feature_code":"PPL",
    "gn:name":"Brano\u0161evac",
    "gn:population":0,
    "gn:timezone":"Europe/Belgrade",
    "iso:country":"RS",
    "name:srp_x_preferred":[
        "Brano\u0161evac"
    ],
    "name:und_x_variant":[
        "Brene\u0161evac"
    ],
    "wof:name":"Branosevac",
    "wof:placetype":"locality"
},
  "geometry": {"coordinates":[19.82964,43.46106],"type":"Point"}
}