{
  "type": "Feature",
  "properties": {
    "gn:admin1_code":"SE",
    "gn:admin2_code":"12",
    "gn:asciiname":"Ramaca",
    "gn:country_code":"RS",
    "gn:dem":487,
    "gn:feature_class":"P",
    "gn:feature_code":"PPL",
    "gn:name":"Rama\u0107a",
    "gn:population":0,
    "gn:timezone":"Europe/Belgrade",
    "iso:country":"RS",
    "name:ceb_x_preferred":[
        "Rama\u0107a"
    ],
    "name:fra_x_preferred":[
        "Rama\u0107a"
    ],
    "name:msa_x_preferred":[
        "Rama\u0107a"
    ],
    "name:por_x_preferred":[
        "Rama\u0107a"
    ],
    "name:slv_x_preferred":[
        "Rama\u0107a"
    ],
    "name:srp_x_preferred":[
        "Rama\u0107a"
    ],
    "name:srp_x_variant":[
        "\u0420\u0430\u043c\u0430\u045b\u0430"
    ],
    "wof:name":"Ramaca",
    "wof:placetype":"locality"
},
  "geometry": {"coordinates":[20.66834,44.08717],"type":"Point"}
}