{
  "type": "Feature",
  "properties": {
    "gn:admin1_code":"VO",
    "gn:admin2_code":"6",
    "gn:asciiname":"Berava",
    "gn:country_code":"RS",
    "gn:dem":79,
    "gn:feature_class":"P",
    "gn:feature_code":"PPL",
    "gn:name":"Berava",
    "gn:population":0,
    "gn:timezone":"Europe/Belgrade",
    "iso:country":"RS",
    "name:ceb_x_preferred":[
        "Berava"
    ],
    "name:srp_x_preferred":[
        "Berava"
    ],
    "name:swe_x_preferred":[
        "Berava"
    ],
    "wof:name":"Berava",
    "wof:placetype":"locality"
},
  "geometry": {"coordinates":[19.07327,45.38966],"type":"Point"}
}