{
  "type": "Feature",
  "properties": {
    "gn:admin1_code":"SE",
    "gn:admin2_code":"24",
    "gn:asciiname":"Crepinova Mahala",
    "gn:country_code":"RS",
    "gn:dem":1338,
    "gn:feature_class":"P",
    "gn:feature_code":"PPL",
    "gn:name":"Crepinova Mahala",
    "gn:population":0,
    "gn:timezone":"Europe/Belgrade",
    "iso:country":"RS",
    "wof:name":"Crepinova Mahala",
    "wof:placetype":"locality"
},
  "geometry": {"coordinates":[22.32563,42.45667],"type":"Point"}
}