{
  "type": "Feature",
  "properties": {
    "gn:admin1_code":"SE",
    "gn:admin2_code":"17",
    "gn:asciiname":"Bele Vode",
    "gn:country_code":"RS",
    "gn:dem":1334,
    "gn:feature_class":"P",
    "gn:feature_code":"PPL",
    "gn:name":"Bele Vode",
    "gn:population":0,
    "gn:timezone":"Europe/Belgrade",
    "iso:country":"RS",
    "name:srp_x_preferred":[
        "Bele Vode"
    ],
    "wof:name":"Bele Vode",
    "wof:placetype":"locality"
},
  "geometry": {"coordinates":[20.28528,43.40611],"type":"Point"}
}