{
  "type": "Feature",
  "properties": {
    "gn:admin1_code":"VO",
    "gn:admin2_code":"7",
    "gn:asciiname":"Lacarak",
    "gn:country_code":"RS",
    "gn:dem":78,
    "gn:feature_class":"P",
    "gn:feature_code":"PPL",
    "gn:name":"La\u0107arak",
    "gn:population":0,
    "gn:timezone":"Europe/Belgrade",
    "iso:country":"RS",
    "name:srp_x_preferred":[
        "La\u0107arak"
    ],
    "name:und_x_variant":[
        "Pa\u0107arak",
        "Ladjarak"
    ],
    "wof:name":"Lacarak",
    "wof:placetype":"locality"
},
  "geometry": {"coordinates":[19.56987,44.99703],"type":"Point"}
}