{
  "type": "Feature",
  "properties": {
    "gn:admin1_code":"VO",
    "gn:admin2_code":"7",
    "gn:asciiname":"Lacarak",
    "gn:country_code":"RS",
    "gn:dem":78,
    "gn:feature_class":"P",
    "gn:feature_code":"PPL",
    "gn:name":"La\u0107arak",
    "gn:population":0,
    "gn:timezone":"Europe/Belgrade",
    "iso:country":"RS",
    "name:ceb_x_preferred":[
        "La\u0107arak"
    ],
    "name:epo_x_preferred":[
        "Lacjarak"
    ],
    "name:fra_x_preferred":[
        "La\u0107arak"
    ],
    "name:hrv_x_preferred":[
        "La\u0107arak"
    ],
    "name:hun_x_preferred":[
        "Latyarak"
    ],
    "name:msa_x_preferred":[
        "La\u0107arak"
    ],
    "name:pol_x_preferred":[
        "La\u0107arak"
    ],
    "name:rus_x_preferred":[
        "\u041b\u0430\u0447\u0430\u0440\u0430\u043a"
    ],
    "name:slv_x_preferred":[
        "La\u0107arak"
    ],
    "name:srp_x_preferred":[
        "La\u0107arak"
    ],
    "name:srp_x_variant":[
        "\u041b\u0430\u045b\u0430\u0440\u0430\u043a"
    ],
    "name:und_x_variant":[
        "Pa\u0107arak",
        "Ladjarak"
    ],
    "name:urd_x_preferred":[
        "\u0644\u0627\u06a9\u0627\u0631\u0627\u06a9"
    ],
    "name:zho_x_preferred":[
        "\u62c9\u67e5\u62c9\u514b"
    ],
    "wof:name":"Lacarak",
    "wof:placetype":"locality"
},
  "geometry": {"coordinates":[19.56987,44.99703],"type":"Point"}
}