{
  "type": "Feature",
  "properties": {
    "gn:admin1_code":"SE",
    "gn:admin2_code":"21",
    "gn:asciiname":"Prekorage",
    "gn:country_code":"RS",
    "gn:dem":812,
    "gn:feature_class":"P",
    "gn:feature_code":"PPL",
    "gn:name":"Prekora\u0111e",
    "gn:population":0,
    "gn:timezone":"Europe/Belgrade",
    "iso:country":"RS",
    "name:srp_x_preferred":[
        "Prekora\u0111e"
    ],
    "name:und_x_variant":[
        "Prekoro\u0107e",
        "Prekor\u00f6\u0107e",
        "Prekoradje"
    ],
    "wof:name":"Prekorage",
    "wof:placetype":"locality"
},
  "geometry": {"coordinates":[21.34845,42.94519],"type":"Point"}
}