{
  "type": "Feature",
  "properties": {
    "gn:country":"RS",
    "gn:fcode":"PPL",
    "gn:pop":324,
    "iso:country":"RS",
    "name:eng_x_preferred":[
        "Poto\u010di\u0107"
    ],
    "name:fra_x_preferred":[
        "Poto\u010di\u0107"
    ],
    "name:msa_x_preferred":[
        "Poto\u010di\u0107"
    ],
    "name:nld_x_preferred":[
        "Poto\u010di\u0107"
    ],
    "name:por_x_preferred":[
        "Poto\u010di\u0107"
    ],
    "name:slv_x_preferred":[
        "Poto\u010di\u0107"
    ],
    "name:srp_x_preferred":[
        "Poto\u010di\u0107"
    ],
    "qs:name":"Poto\u010di\u0107",
    "qs:photos_9r":0,
    "qs:photos_sr":0,
    "qs:pop_sr":"2",
    "wd:wordcount":69,
    "wof:name":"Poto\u010di\u0107",
    "wof:placetype":"locality",
    "wof:population":324
},
  "geometry": {"coordinates":[21.49392,43.24496],"type":"Point"}
}