{
  "type": "Feature",
  "properties": {
    "gn:country":"RS",
    "gn:fcode":"PPL",
    "gn:population":324,
    "iso:country":"RS",
    "name:ceb_x_preferred":[
        "Poto\u010di\u0107"
    ],
    "name:eng_x_preferred":[
        "Poto\u010di\u0107"
    ],
    "name:fas_x_preferred":[
        "\u067e\u0648\u062a\u0648\u0686\u06cc\u0686"
    ],
    "name:fra_x_preferred":[
        "Poto\u010di\u0107"
    ],
    "name:msa_x_preferred":[
        "Poto\u010di\u0107"
    ],
    "name:nld_x_preferred":[
        "Poto\u010di\u0107"
    ],
    "name:pol_x_preferred":[
        "Poto\u010di\u0107"
    ],
    "name:por_x_preferred":[
        "Poto\u010di\u0107"
    ],
    "name:slv_x_preferred":[
        "Poto\u010di\u0107"
    ],
    "name:srp_x_preferred":[
        "Poto\u010di\u0107"
    ],
    "name:srp_x_variant":[
        "\u041f\u043e\u0442\u043e\u0447\u0438\u045b"
    ],
    "qs:name":"Poto\u010di\u0107",
    "qs:photos_9r":0,
    "qs:photos_sr":0,
    "qs:pop_sr":"2",
    "wd:wordcount":69,
    "wof:name":"Poto\u010di\u0107",
    "wof:placetype":"locality",
    "wof:population":324
},
  "geometry": {"coordinates":[21.49392,43.24496],"type":"Point"}
}