{
  "type": "Feature",
  "properties": {
    "gn:admin1_code":"SE",
    "gn:admin2_code":"8",
    "gn:asciiname":"Brda",
    "gn:country_code":"RS",
    "gn:dem":158,
    "gn:feature_class":"P",
    "gn:feature_code":"PPL",
    "gn:name":"Brda",
    "gn:population":0,
    "gn:timezone":"Europe/Belgrade",
    "iso:country":"RS",
    "name:bos_x_preferred":[
        "Brda"
    ],
    "name:ceb_x_preferred":[
        "Brda"
    ],
    "name:ces_x_preferred":[
        "Brda"
    ],
    "name:deu_x_preferred":[
        "Brda"
    ],
    "name:fra_x_preferred":[
        "Brda"
    ],
    "name:hrv_x_preferred":[
        "Brda"
    ],
    "name:ita_x_preferred":[
        "Brda"
    ],
    "name:nld_x_preferred":[
        "Brda"
    ],
    "name:pol_x_preferred":[
        "Brda"
    ],
    "name:ron_x_preferred":[
        "Brda"
    ],
    "name:rus_x_preferred":[
        "\u0411\u0440\u0434\u0430"
    ],
    "name:slv_x_preferred":[
        "Brda"
    ],
    "name:srp_x_preferred":[
        "Brda"
    ],
    "name:srp_x_variant":[
        "\u0411\u0440\u0434\u0430"
    ],
    "name:swe_x_preferred":[
        "Brda"
    ],
    "name:vie_x_preferred":[
        "Brda"
    ],
    "wof:name":"Brda",
    "wof:placetype":"locality"
},
  "geometry": {"coordinates":[19.6723,44.48925],"type":"Point"}
}