{
  "type": "Feature",
  "properties": {
    "gn:admin1_code":"SE",
    "gn:admin2_code":"22",
    "gn:asciiname":"Smilovci",
    "gn:country_code":"RS",
    "gn:dem":735,
    "gn:feature_class":"P",
    "gn:feature_code":"PPL",
    "gn:name":"Smilovci",
    "gn:population":0,
    "gn:timezone":"Europe/Belgrade",
    "iso:country":"RS",
    "name:bul_x_preferred":[
        "\u0421\u043c\u0438\u043b\u043e\u0432\u0446\u0438"
    ],
    "name:ceb_x_preferred":[
        "Smilovci"
    ],
    "name:fra_x_preferred":[
        "Smilovci"
    ],
    "name:msa_x_preferred":[
        "Smilovci"
    ],
    "name:por_x_preferred":[
        "Smilovci"
    ],
    "name:slv_x_preferred":[
        "Smilovci"
    ],
    "name:srp_x_preferred":[
        "Smilovci"
    ],
    "name:srp_x_variant":[
        "\u0421\u043c\u0438\u043b\u043e\u0432\u0446\u0438"
    ],
    "wof:name":"Smilovci",
    "wof:placetype":"locality"
},
  "geometry": {"coordinates":[22.85123,43.08527],"type":"Point"}
}