{
  "type": "Feature",
  "properties": {
    "gn:admin1_code":"SE",
    "gn:admin2_code":"22",
    "gn:asciiname":"Smilovci",
    "gn:country_code":"RS",
    "gn:dem":735,
    "gn:feature_class":"P",
    "gn:feature_code":"PPL",
    "gn:name":"Smilovci",
    "gn:population":0,
    "gn:timezone":"Europe/Belgrade",
    "iso:country":"RS",
    "name:srp_x_preferred":[
        "Smilovci"
    ],
    "wof:name":"Smilovci",
    "wof:placetype":"locality"
},
  "geometry": {"coordinates":[22.85123,43.08527],"type":"Point"}
}