{
  "type": "Feature",
  "properties": {
    "gn:admin1_code":"SE",
    "gn:admin2_code":"9",
    "gn:asciiname":"Bogdanovica",
    "gn:country_code":"RS",
    "gn:dem":90,
    "gn:feature_class":"P",
    "gn:feature_code":"PPL",
    "gn:name":"Bogdanovica",
    "gn:population":0,
    "gn:timezone":"Europe/Belgrade",
    "iso:country":"RS",
    "name:srp_x_preferred":[
        "Bogdanovica"
    ],
    "wof:name":"Bogdanovica",
    "wof:placetype":"locality"
},
  "geometry": {"coordinates":[20.08194,44.475],"type":"Point"}
}