{
  "type": "Feature",
  "properties": {
    "gn:admin1_code":"SE",
    "gn:admin2_code":"9",
    "gn:asciiname":"Bogdanovica",
    "gn:country_code":"RS",
    "gn:dem":90,
    "gn:feature_class":"P",
    "gn:feature_code":"PPL",
    "gn:name":"Bogdanovica",
    "gn:population":0,
    "gn:timezone":"Europe/Belgrade",
    "iso:country":"RS",
    "name:ceb_x_preferred":[
        "Bogdanovica"
    ],
    "name:fas_x_preferred":[
        "\u0628\u0648\u06af\u062f\u0627\u0646\u0648\u06cc\u062a\u0633\u0627"
    ],
    "name:fra_x_preferred":[
        "Bogdanovica"
    ],
    "name:msa_x_preferred":[
        "Bogdanovica"
    ],
    "name:nld_x_preferred":[
        "Bogdanovica"
    ],
    "name:por_x_preferred":[
        "Bogdanovica"
    ],
    "name:slv_x_preferred":[
        "Bogdanovica"
    ],
    "name:srp_x_preferred":[
        "Bogdanovica"
    ],
    "name:srp_x_variant":[
        "\u0411\u043e\u0433\u0434\u0430\u043d\u043e\u0432\u0438\u0446\u0430"
    ],
    "wof:name":"Bogdanovica",
    "wof:placetype":"locality"
},
  "geometry": {"coordinates":[20.08194,44.475],"type":"Point"}
}