{
  "type": "Feature",
  "properties": {
    "gn:admin1_code":"SE",
    "gn:admin2_code":"19",
    "gn:asciiname":"Pakasnica",
    "gn:country_code":"RS",
    "gn:dem":187,
    "gn:feature_class":"P",
    "gn:feature_code":"PPL",
    "gn:name":"Paka\u0161nica",
    "gn:population":0,
    "gn:timezone":"Europe/Belgrade",
    "iso:country":"RS",
    "name:ceb_x_preferred":[
        "Paka\u0161nica"
    ],
    "name:fra_x_preferred":[
        "Paka\u0161nica"
    ],
    "name:msa_x_preferred":[
        "Paka\u0161nica"
    ],
    "name:por_x_preferred":[
        "Paka\u0161nica"
    ],
    "name:slv_x_preferred":[
        "Paka\u0161nica"
    ],
    "name:srp_x_preferred":[
        "\u041f\u0430\u043a\u0430\u0448\u043d\u0438\u0446\u0430"
    ],
    "wof:name":"Pakasnica",
    "wof:placetype":"locality"
},
  "geometry": {"coordinates":[21.30775,43.56145],"type":"Point"}
}