{
  "type": "Feature",
  "properties": {
    "gn:admin1_code":"SE",
    "gn:admin2_code":"19",
    "gn:asciiname":"Pakasnica",
    "gn:country_code":"RS",
    "gn:dem":187,
    "gn:feature_class":"P",
    "gn:feature_code":"PPL",
    "gn:name":"Paka\u0161nica",
    "gn:population":0,
    "gn:timezone":"Europe/Belgrade",
    "iso:country":"RS",
    "name:und_x_variant":[
        "Paka\u0161nica"
    ],
    "wof:name":"Pakasnica",
    "wof:placetype":"locality"
},
  "geometry": {"coordinates":[21.30775,43.56145],"type":"Point"}
}