{
  "type": "Feature",
  "properties": {
    "gn:admin1_code":"SE",
    "gn:admin2_code":"23",
    "gn:asciiname":"Nomanica",
    "gn:country_code":"RS",
    "gn:dem":235,
    "gn:feature_class":"P",
    "gn:feature_code":"PPL",
    "gn:name":"Nomanica",
    "gn:population":0,
    "gn:timezone":"Europe/Belgrade",
    "iso:country":"RS",
    "name:ceb_x_preferred":[
        "Nomanica"
    ],
    "name:fra_x_preferred":[
        "Nomanica"
    ],
    "name:msa_x_preferred":[
        "Nomanica"
    ],
    "name:por_x_preferred":[
        "Nomanica"
    ],
    "name:slv_x_preferred":[
        "Nomanica"
    ],
    "name:srp_x_preferred":[
        "Nomanica"
    ],
    "name:srp_x_variant":[
        "\u041d\u043e\u043c\u0430\u043d\u0438\u0446\u0430"
    ],
    "wof:name":"Nomanica",
    "wof:placetype":"locality"
},
  "geometry": {"coordinates":[22.02975,42.97605],"type":"Point"}
}