{
  "type": "Feature",
  "properties": {
    "gn:admin1_code":"SE",
    "gn:admin2_code":"23",
    "gn:asciiname":"Miljine",
    "gn:country_code":"RS",
    "gn:dem":1121,
    "gn:feature_class":"P",
    "gn:feature_code":"PPL",
    "gn:name":"Miljine",
    "gn:population":0,
    "gn:timezone":"Europe/Belgrade",
    "iso:country":"RS",
    "name:srp_x_preferred":[
        "Miljine"
    ],
    "wof:name":"Miljine",
    "wof:placetype":"locality"
},
  "geometry": {"coordinates":[22.2791,42.83876],"type":"Point"}
}