{
  "type": "Feature",
  "properties": {
    "gn:admin1_code":"SE",
    "gn:admin2_code":"19",
    "gn:asciiname":"Novo Selo",
    "gn:country_code":"RS",
    "gn:dem":220,
    "gn:feature_class":"P",
    "gn:feature_code":"PPL",
    "gn:name":"Novo Selo",
    "gn:population":0,
    "gn:timezone":"Europe/Belgrade",
    "iso:country":"RS",
    "wof:name":"Novo Selo",
    "wof:placetype":"locality"
},
  "geometry": {"coordinates":[21.44766,43.56567],"type":"Point"}
}