{
  "type": "Feature",
  "properties": {
    "gn:admin1_code":"SE",
    "gn:admin2_code":"19",
    "gn:asciiname":"Donji Stepos",
    "gn:country_code":"RS",
    "gn:dem":195,
    "gn:feature_class":"P",
    "gn:feature_code":"PPL",
    "gn:name":"Donji Stepo\u0161",
    "gn:population":0,
    "gn:timezone":"Europe/Belgrade",
    "iso:country":"RS",
    "name:srp_x_preferred":[
        "Donji Stepo\u0161"
    ],
    "wof:name":"Donji Stepos",
    "wof:placetype":"locality"
},
  "geometry": {"coordinates":[21.31269,43.52135],"type":"Point"}
}