{
  "type": "Feature",
  "properties": {
    "gn:admin1_code":"SE",
    "gn:admin2_code":"19",
    "gn:asciiname":"Donji Stepos",
    "gn:country_code":"RS",
    "gn:dem":195,
    "gn:feature_class":"P",
    "gn:feature_code":"PPL",
    "gn:name":"Donji Stepo\u0161",
    "gn:population":0,
    "gn:timezone":"Europe/Belgrade",
    "iso:country":"RS",
    "name:ceb_x_preferred":[
        "Donji Stepo\u0161"
    ],
    "name:deu_x_preferred":[
        "Donji Stepo\u0161"
    ],
    "name:fra_x_preferred":[
        "Donji Stepo\u0161"
    ],
    "name:msa_x_preferred":[
        "Donji Stepo\u0161"
    ],
    "name:por_x_preferred":[
        "Donji Stepo\u0161"
    ],
    "name:slv_x_preferred":[
        "Donji Stepo\u0161"
    ],
    "name:srp_x_preferred":[
        "Donji Stepo\u0161"
    ],
    "name:srp_x_variant":[
        "\u0414\u043e\u045a\u0438 \u0421\u0442\u0435\u043f\u043e\u0448"
    ],
    "wof:name":"Donji Stepos",
    "wof:placetype":"locality"
},
  "geometry": {"coordinates":[21.31269,43.52135],"type":"Point"}
}