{
  "type": "Feature",
  "properties": {
    "gn:admin1_code":"SE",
    "gn:admin2_code":"12",
    "gn:asciiname":"Oplanic",
    "gn:country_code":"RS",
    "gn:dem":352,
    "gn:feature_class":"P",
    "gn:feature_code":"PPL",
    "gn:name":"Oplani\u0107",
    "gn:population":0,
    "gn:timezone":"Europe/Belgrade",
    "iso:country":"RS",
    "name:ceb_x_preferred":[
        "Oplani\u0107"
    ],
    "name:fra_x_preferred":[
        "Oplani\u0107"
    ],
    "name:msa_x_preferred":[
        "Oplani\u0107"
    ],
    "name:por_x_preferred":[
        "Oplani\u0107"
    ],
    "name:slv_x_preferred":[
        "Ljuljaci"
    ],
    "name:srp_x_preferred":[
        "\u041e\u043f\u043b\u0430\u043d\u0438\u045b"
    ],
    "name:und_x_variant":[
        "Oplani\u0107"
    ],
    "wof:name":"Oplanic",
    "wof:placetype":"locality"
},
  "geometry": {"coordinates":[20.67845,43.98634000000001],"type":"Point"}
}