{
  "type": "Feature",
  "properties": {
    "gn:admin1_code":"SE",
    "gn:admin2_code":"15",
    "gn:asciiname":"Selacka",
    "gn:country_code":"RS",
    "gn:dem":268,
    "gn:feature_class":"P",
    "gn:feature_code":"PPL",
    "gn:name":"Sela\u010dka",
    "gn:population":0,
    "gn:timezone":"Europe/Belgrade",
    "iso:country":"RS",
    "name:ceb_x_preferred":[
        "Sela\u010dka"
    ],
    "name:fra_x_preferred":[
        "Sela\u010dka"
    ],
    "name:msa_x_preferred":[
        "Sela\u010dka"
    ],
    "name:nld_x_preferred":[
        "Sela\u010dka"
    ],
    "name:por_x_preferred":[
        "Sela\u010dka"
    ],
    "name:slv_x_preferred":[
        "Sela\u010dka"
    ],
    "name:srp_x_preferred":[
        "Sela\u010dka"
    ],
    "name:srp_x_variant":[
        "\u0421\u0435\u043b\u0430\u0447\u043a\u0430"
    ],
    "wof:name":"Selacka",
    "wof:placetype":"locality"
},
  "geometry": {"coordinates":[22.32253,43.70017],"type":"Point"}
}