{
  "type": "Feature",
  "properties": {
    "gn:admin1_code":"SE",
    "gn:admin2_code":"16",
    "gn:asciiname":"Durgevici",
    "gn:country_code":"RS",
    "gn:dem":763,
    "gn:feature_class":"P",
    "gn:feature_code":"PPL",
    "gn:name":"\u00d0ur\u0111evi\u0107i",
    "gn:population":0,
    "gn:timezone":"Europe/Belgrade",
    "iso:country":"RS",
    "name:srp_x_preferred":[
        "\u00d0ur\u0111evi\u0107i"
    ],
    "wof:name":"Durgevici",
    "wof:placetype":"locality"
},
  "geometry": {"coordinates":[20.06399,43.6347],"type":"Point"}
}