{
  "type": "Feature",
  "properties": {
    "gn:admin1_code":"SE",
    "gn:admin2_code":"24",
    "gn:asciiname":"Kiselicka Mahala",
    "gn:country_code":"RS",
    "gn:dem":1110,
    "gn:feature_class":"P",
    "gn:feature_code":"PPL",
    "gn:name":"Kiseli\u010dka Mahala",
    "gn:population":0,
    "gn:timezone":"Europe/Belgrade",
    "iso:country":"RS",
    "name:srp_x_preferred":[
        "Kiseli\u010dka Mahala"
    ],
    "name:und_x_variant":[
        "Kiselica"
    ],
    "wof:name":"Kiselicka Mahala",
    "wof:placetype":"locality"
},
  "geometry": {"coordinates":[22.40061,42.37011],"type":"Point"}
}