{
  "type": "Feature",
  "properties": {
    "gn:admin1_code":"SE",
    "gn:admin2_code":"18",
    "gn:asciiname":"Milakovac",
    "gn:country_code":"RS",
    "gn:dem":233,
    "gn:feature_class":"P",
    "gn:feature_code":"PPL",
    "gn:name":"Milakovac",
    "gn:population":0,
    "gn:timezone":"Europe/Belgrade",
    "iso:country":"RS",
    "wof:name":"Milakovac",
    "wof:placetype":"locality"
},
  "geometry": {"coordinates":[20.80884,43.78345],"type":"Point"}
}