{
  "type": "Feature",
  "properties": {
    "gn:admin1_code":"SE",
    "gn:admin2_code":"18",
    "gn:asciiname":"Kulizice",
    "gn:country_code":"RS",
    "gn:dem":1089,
    "gn:feature_class":"P",
    "gn:feature_code":"PPL",
    "gn:name":"Kulizi\u0107e",
    "gn:population":0,
    "gn:timezone":"Europe/Belgrade",
    "iso:country":"RS",
    "name:srp_x_preferred":[
        "Kulizi\u0107e"
    ],
    "wof:name":"Kulizice",
    "wof:placetype":"locality"
},
  "geometry": {"coordinates":[20.60806,43.06972],"type":"Point"}
}