{
  "type": "Feature",
  "properties": {
    "gn:admin1_code":"SE",
    "gn:admin2_code":"12",
    "gn:asciiname":"Knezevac",
    "gn:country_code":"RS",
    "gn:dem":384,
    "gn:feature_class":"P",
    "gn:feature_code":"PPL",
    "gn:name":"Kne\u017eevac",
    "gn:population":0,
    "gn:timezone":"Europe/Belgrade",
    "iso:country":"RS",
    "name:srp_x_preferred":[
        "Kne\u017eevac"
    ],
    "wof:name":"Knezevac",
    "wof:placetype":"locality"
},
  "geometry": {"coordinates":[20.66996,44.05827],"type":"Point"}
}