{
  "type": "Feature",
  "properties": {
    "gn:admin1_code":"SE",
    "gn:admin2_code":"10",
    "gn:asciiname":"Grcac",
    "gn:country_code":"RS",
    "gn:dem":167,
    "gn:feature_class":"P",
    "gn:feature_code":"PPLL",
    "gn:name":"Gr\u010dac",
    "gn:population":0,
    "gn:timezone":"Europe/Belgrade",
    "iso:country":"RS",
    "name:ceb_x_preferred":[
        "Gr\u010dac"
    ],
    "name:fra_x_preferred":[
        "Gr\u010dac"
    ],
    "name:msa_x_preferred":[
        "Gr\u010dac"
    ],
    "name:por_x_preferred":[
        "Gr\u010dac"
    ],
    "name:slv_x_preferred":[
        "Gr\u010dac"
    ],
    "name:srp_x_preferred":[
        "Gr\u010dac"
    ],
    "name:srp_x_variant":[
        "\u0413\u0440\u0447\u0430\u0446"
    ],
    "wof:name":"Grcac",
    "wof:placetype":"locality"
},
  "geometry": {"coordinates":[20.9517,44.42215],"type":"Point"}
}