{
  "type": "Feature",
  "properties": {
    "gn:admin1_code":"SE",
    "gn:admin2_code":"24",
    "gn:asciiname":"Depce",
    "gn:country_code":"RS",
    "gn:dem":786,
    "gn:feature_class":"P",
    "gn:feature_code":"PPLL",
    "gn:name":"Depce",
    "gn:population":0,
    "gn:timezone":"Europe/Belgrade",
    "iso:country":"RS",
    "name:bul_x_preferred":[
        "\u0414\u0435\u043f\u0446\u0435"
    ],
    "name:ceb_x_preferred":[
        "Depce"
    ],
    "name:fra_x_preferred":[
        "Depce"
    ],
    "name:mkd_x_preferred":[
        "\u0414\u0435\u043f\u0446\u0435"
    ],
    "name:msa_x_preferred":[
        "Depce"
    ],
    "name:por_x_preferred":[
        "Depce"
    ],
    "name:slv_x_preferred":[
        "Depce"
    ],
    "name:sqi_x_preferred":[
        "Depca"
    ],
    "name:srp_x_preferred":[
        "Depce"
    ],
    "name:srp_x_variant":[
        "\u0414\u0435\u043f\u0446\u0435"
    ],
    "wof:name":"Depce",
    "wof:placetype":"locality"
},
  "geometry": {"coordinates":[21.55564,42.35671],"type":"Point"}
}