{
  "type": "Feature",
  "properties": {
    "gn:admin1_code":"SE",
    "gn:admin2_code":"17",
    "gn:asciiname":"Radojicici",
    "gn:country_code":"RS",
    "gn:dem":933,
    "gn:feature_class":"P",
    "gn:feature_code":"PPL",
    "gn:name":"Radoji\u010di\u0107i",
    "gn:population":0,
    "gn:timezone":"Europe/Belgrade",
    "iso:country":"RS",
    "name:srp_x_preferred":[
        "Radoji\u010di\u0107i"
    ],
    "wof:name":"Radojicici",
    "wof:placetype":"locality"
},
  "geometry": {"coordinates":[20.0775,43.56306],"type":"Point"}
}