{
  "type": "Feature",
  "properties": {
    "gn:admin1_code":"SE",
    "gn:admin2_code":"22",
    "gn:asciiname":"Gornja Glama",
    "gn:country_code":"RS",
    "gn:dem":693,
    "gn:feature_class":"P",
    "gn:feature_code":"PPL",
    "gn:name":"Gornja Glama",
    "gn:population":0,
    "gn:timezone":"Europe/Belgrade",
    "iso:country":"RS",
    "name:fra_x_preferred":[
        "Gornja Glama"
    ],
    "name:msa_x_preferred":[
        "Gornja Glama"
    ],
    "name:por_x_preferred":[
        "Gornja Glama"
    ],
    "name:slv_x_preferred":[
        "Gornja Glama"
    ],
    "name:srp_x_preferred":[
        "Gornja Glama"
    ],
    "name:srp_x_variant":[
        "\u0413\u043e\u0440\u045a\u0430 \u0413\u043b\u0430\u043c\u0430"
    ],
    "name:und_x_variant":[
        "Glama"
    ],
    "wof:name":"Gornja Glama",
    "wof:placetype":"locality"
},
  "geometry": {"coordinates":[22.36824,43.27805],"type":"Point"}
}