{
  "type": "Feature",
  "properties": {
    "gn:admin1_code":"SE",
    "gn:admin2_code":"22",
    "gn:asciiname":"Carev Del",
    "gn:country_code":"RS",
    "gn:dem":1029,
    "gn:feature_class":"P",
    "gn:feature_code":"PPL",
    "gn:name":"Carev Del",
    "gn:population":0,
    "gn:timezone":"Europe/Belgrade",
    "iso:country":"RS",
    "name:srp_x_preferred":[
        "Carev Del"
    ],
    "wof:name":"Carev Del",
    "wof:placetype":"locality"
},
  "geometry": {"coordinates":[22.56588,43.01181],"type":"Point"}
}