{
  "type": "Feature",
  "properties": {
    "gn:country":"RS",
    "gn:fcode":"PPL",
    "gn:population":53,
    "iso:country":"RS",
    "name:eng_x_preferred":[
        "Rankova Reka"
    ],
    "name:fas_x_preferred":[
        "\u0631\u0627\u0646\u06a9\u0648\u0648\u0627 \u0631\u06a9\u0627"
    ],
    "name:fra_x_preferred":[
        "Rankova Reka"
    ],
    "name:msa_x_preferred":[
        "Rankova Reka"
    ],
    "name:nld_x_preferred":[
        "Rankova Reka"
    ],
    "name:pol_x_preferred":[
        "Rankova Reka"
    ],
    "name:por_x_preferred":[
        "Rankova Reka"
    ],
    "name:slv_x_preferred":[
        "Rankova Reka"
    ],
    "name:srp_x_preferred":[
        "Rankova Reka"
    ],
    "name:srp_x_variant":[
        "\u0420\u0430\u043d\u043a\u043e\u0432\u0430 \u0420\u0435\u043a\u0430"
    ],
    "qs:name":"Rankova Reka",
    "qs:photos_9r":0,
    "qs:photos_sr":0,
    "qs:pop_sr":"1",
    "wd:wordcount":70,
    "wof:name":"Rankova Reka",
    "wof:placetype":"locality",
    "wof:population":53
},
  "geometry": {"coordinates":[21.53895,43.07698],"type":"Point"}
}