{
  "type": "Feature",
  "properties": {
    "gn:country":"RS",
    "gn:fcode":"PPL",
    "gn:pop":53,
    "iso:country":"RS",
    "name:eng_x_preferred":[
        "Rankova Reka"
    ],
    "name:fra_x_preferred":[
        "Rankova Reka"
    ],
    "name:msa_x_preferred":[
        "Rankova Reka"
    ],
    "name:nld_x_preferred":[
        "Rankova Reka"
    ],
    "name:por_x_preferred":[
        "Rankova Reka"
    ],
    "name:slv_x_preferred":[
        "Rankova Reka"
    ],
    "name:srp_x_preferred":[
        "Rankova Reka"
    ],
    "qs:name":"Rankova Reka",
    "qs:photos_9r":0,
    "qs:photos_sr":0,
    "qs:pop_sr":"1",
    "wd:wordcount":70,
    "wof:name":"Rankova Reka",
    "wof:placetype":"locality",
    "wof:population":53
},
  "geometry": {"coordinates":[21.53895,43.07698],"type":"Point"}
}