{
  "type": "Feature",
  "properties": {
    "gn:admin1_code":"00",
    "gn:asciiname":"Rogota",
    "gn:country_code":"RS",
    "gn:dem":190,
    "gn:feature_class":"P",
    "gn:feature_code":"PPL",
    "gn:name":"Rogota",
    "gn:population":0,
    "gn:timezone":"Europe/Belgrade",
    "iso:country":"RS",
    "name:srp_x_preferred":[
        "Rogota"
    ],
    "wof:name":"Rogota",
    "wof:placetype":"locality"
},
  "geometry": {"coordinates":[19.42584,44.15175],"type":"Point"}
}