{
  "type": "Feature",
  "properties": {
    "gn:admin1_code":"SE",
    "gn:admin2_code":"16",
    "gn:asciiname":"Kosnice",
    "gn:country_code":"RS",
    "gn:dem":827,
    "gn:feature_class":"P",
    "gn:feature_code":"PPL",
    "gn:name":"Ko\u0161nice",
    "gn:population":0,
    "gn:timezone":"Europe/Belgrade",
    "iso:country":"RS",
    "name:srp_x_preferred":[
        "Ko\u0161nice"
    ],
    "wof:name":"Kosnice",
    "wof:placetype":"locality"
},
  "geometry": {"coordinates":[19.57447,43.50683],"type":"Point"}
}