{
  "type": "Feature",
  "properties": {
    "gn:admin1_code":"SE",
    "gn:admin2_code":"21",
    "gn:asciiname":"Maros",
    "gn:country_code":"RS",
    "gn:dem":895,
    "gn:feature_class":"P",
    "gn:feature_code":"PPL",
    "gn:name":"Maro\u0161",
    "gn:population":0,
    "gn:timezone":"Europe/Belgrade",
    "iso:country":"RS",
    "name:deu_x_preferred":[
        "Maros"
    ],
    "name:mlg_x_preferred":[
        "Maros"
    ],
    "name:nld_x_preferred":[
        "Maros"
    ],
    "name:srp_x_preferred":[
        "Maro\u0161"
    ],
    "name:zho_x_preferred":[
        "\u9a6c\u7f57\u65af"
    ],
    "wof:name":"Maros",
    "wof:placetype":"locality"
},
  "geometry": {"coordinates":[21.15011,43.17601],"type":"Point"}
}