{
  "type": "Feature",
  "properties": {
    "gn:admin1_code":"SE",
    "gn:admin2_code":"17",
    "gn:asciiname":"Milatovici",
    "gn:country_code":"RS",
    "gn:dem":481,
    "gn:feature_class":"P",
    "gn:feature_code":"PPLL",
    "gn:name":"Milatovi\u0107i",
    "gn:population":0,
    "gn:timezone":"Europe/Belgrade",
    "iso:country":"RS",
    "name:ceb_x_preferred":[
        "Milatovi\u0107i"
    ],
    "name:fas_x_preferred":[
        "\u0645\u06cc\u0644\u0627\u062a\u0648\u0648\u06cc\u0633\u06cc"
    ],
    "name:fra_x_preferred":[
        "Milatovi\u0107i"
    ],
    "name:msa_x_preferred":[
        "Milatovi\u0107i"
    ],
    "name:por_x_preferred":[
        "Milatovi\u0107i"
    ],
    "name:slv_x_preferred":[
        "Milatovi\u0107i"
    ],
    "name:srp_x_preferred":[
        "Milatovi\u0107i"
    ],
    "name:srp_x_variant":[
        "\u041c\u0438\u043b\u0430\u0442\u043e\u0432\u0438\u045b\u0438"
    ],
    "name:und_x_variant":[
        "Milatovi\u0107"
    ],
    "wof:name":"Milatovici",
    "wof:placetype":"locality"
},
  "geometry": {"coordinates":[20.36326,43.72879],"type":"Point"}
}