{
  "type": "Feature",
  "properties": {
    "gn:admin1_code":"SE",
    "gn:admin2_code":"17",
    "gn:asciiname":"Milatovici",
    "gn:country_code":"RS",
    "gn:dem":481,
    "gn:feature_class":"P",
    "gn:feature_code":"PPLL",
    "gn:name":"Milatovi\u0107i",
    "gn:population":0,
    "gn:timezone":"Europe/Belgrade",
    "iso:country":"RS",
    "name:srp_x_preferred":[
        "Milatovi\u0107i"
    ],
    "name:und_x_variant":[
        "Milatovi\u0107"
    ],
    "wof:name":"Milatovici",
    "wof:placetype":"locality"
},
  "geometry": {"coordinates":[20.36326,43.72879],"type":"Point"}
}