{
  "type": "Feature",
  "properties": {
    "gn:admin1_code":"SE",
    "gn:admin2_code":"16",
    "gn:asciiname":"Budakovac",
    "gn:country_code":"RS",
    "gn:dem":1056,
    "gn:feature_class":"P",
    "gn:feature_code":"PPL",
    "gn:name":"Budakovac",
    "gn:population":0,
    "gn:timezone":"Europe/Belgrade",
    "iso:country":"RS",
    "name:srp_x_preferred":[
        "Budakovac"
    ],
    "wof:name":"Budakovac",
    "wof:placetype":"locality"
},
  "geometry": {"coordinates":[20.23827,43.28954],"type":"Point"}
}