{
  "type": "Feature",
  "properties": {
    "gn:country":"RS",
    "gn:fcode":"PPL",
    "gn:pop":103,
    "iso:country":"RS",
    "name:ceb_x_preferred":[
        "Gornji Statovac"
    ],
    "name:eng_x_preferred":[
        "Gornji Statovac"
    ],
    "name:fra_x_preferred":[
        "Gornji Statovac"
    ],
    "name:msa_x_preferred":[
        "Gornji Statovac"
    ],
    "name:nld_x_preferred":[
        "Gornji Statovac"
    ],
    "name:por_x_preferred":[
        "Gornji Statovac"
    ],
    "name:slv_x_preferred":[
        "Gornji Statovac"
    ],
    "name:sqi_x_preferred":[
        "Statovci"
    ],
    "name:srp_x_preferred":[
        "Gornji Statovac"
    ],
    "name:srp_x_variant":[
        "\u0413\u043e\u0440\u045a\u0438 \u0421\u0442\u0430\u0442\u043e\u0432\u0430\u0446"
    ],
    "qs:name":"Gornji Statovac",
    "qs:photos_9r":0,
    "qs:photos_sr":0,
    "qs:pop_sr":"1",
    "wd:wordcount":71,
    "wof:name":"Gornji Statovac",
    "wof:placetype":"locality",
    "wof:population":103
},
  "geometry": {"coordinates":[21.49371,43.08208],"type":"Point"}
}