{
  "type": "Feature",
  "properties": {
    "gn:admin1_code":"SE",
    "gn:admin2_code":"17",
    "gn:asciiname":"Dostanici",
    "gn:country_code":"RS",
    "gn:dem":395,
    "gn:feature_class":"P",
    "gn:feature_code":"PPL",
    "gn:name":"Dostani\u0107i",
    "gn:population":0,
    "gn:timezone":"Europe/Belgrade",
    "iso:country":"RS",
    "wof:name":"Dostanici",
    "wof:placetype":"locality"
},
  "geometry": {"coordinates":[20.23439,43.79322],"type":"Point"}
}