{
  "type": "Feature",
  "properties": {
    "gn:admin1_code":"SE",
    "gn:admin2_code":"8",
    "gn:asciiname":"Ozorci",
    "gn:country_code":"RS",
    "gn:dem":729,
    "gn:feature_class":"P",
    "gn:feature_code":"PPL",
    "gn:name":"Ozorci",
    "gn:population":0,
    "gn:timezone":"Europe/Belgrade",
    "iso:country":"RS",
    "name:srp_x_preferred":[
        "Ozorci"
    ],
    "wof:name":"Ozorci",
    "wof:placetype":"locality"
},
  "geometry": {"coordinates":[19.50356,44.16034000000001],"type":"Point"}
}