{
  "type": "Feature",
  "properties": {
    "gn:admin1_code":"SE",
    "gn:admin2_code":"18",
    "gn:asciiname":"Kuzmanci",
    "gn:country_code":"RS",
    "gn:dem":499,
    "gn:feature_class":"P",
    "gn:feature_code":"PPL",
    "gn:name":"Kuzmanci",
    "gn:population":0,
    "gn:timezone":"Europe/Belgrade",
    "iso:country":"RS",
    "name:srp_x_preferred":[
        "Kuzmanci"
    ],
    "wof:name":"Kuzmanci",
    "wof:placetype":"locality"
},
  "geometry": {"coordinates":[20.62,43.4825],"type":"Point"}
}