{
  "type": "Feature",
  "properties": {
    "gn:admin1_code":"SE",
    "gn:admin2_code":"18",
    "gn:asciiname":"Todorica",
    "gn:country_code":"RS",
    "gn:dem":933,
    "gn:feature_class":"P",
    "gn:feature_code":"PPL",
    "gn:name":"Todorica",
    "gn:population":0,
    "gn:timezone":"Europe/Belgrade",
    "iso:country":"RS",
    "name:srp_x_preferred":[
        "Todorica"
    ],
    "wof:name":"Todorica",
    "wof:placetype":"locality"
},
  "geometry": {"coordinates":[20.43,43.26389],"type":"Point"}
}