{
  "type": "Feature",
  "properties": {
    "gn:admin1_code":"SE",
    "gn:admin2_code":"18",
    "gn:asciiname":"Jasenovik",
    "gn:country_code":"RS",
    "gn:dem":583,
    "gn:feature_class":"P",
    "gn:feature_code":"PPL",
    "gn:name":"Jasenovik",
    "gn:population":0,
    "gn:timezone":"Europe/Belgrade",
    "iso:country":"RS",
    "name:ceb_x_preferred":[
        "Jasenovik"
    ],
    "name:ell_x_preferred":[
        "\u0393\u03b9\u03b1\u03c3\u03ad\u03bd\u03bf\u03b2\u03b9\u03ba"
    ],
    "name:fra_x_preferred":[
        "Jasenovik"
    ],
    "name:msa_x_preferred":[
        "Jasenovik"
    ],
    "name:por_x_preferred":[
        "Jasenovik"
    ],
    "name:slv_x_preferred":[
        "Jasenovik"
    ],
    "name:srp_x_preferred":[
        "Jasenovik"
    ],
    "name:srp_x_variant":[
        "\u0408\u0430\u0441\u0435\u043d\u043e\u0432\u0438\u043a"
    ],
    "name:urd_x_preferred":[
        "\u062c\u0633\u0646\u0648\u0648\u06cc\u06a9"
    ],
    "wof:name":"Jasenovik",
    "wof:placetype":"locality"
},
  "geometry": {"coordinates":[20.41395,43.16096],"type":"Point"}
}