{
  "type": "Feature",
  "properties": {
    "gn:admin1_code":"SE",
    "gn:admin2_code":"24",
    "gn:asciiname":"Vodenicari",
    "gn:country_code":"RS",
    "gn:dem":1080,
    "gn:feature_class":"P",
    "gn:feature_code":"PPL",
    "gn:name":"Vodeni\u010dari",
    "gn:population":0,
    "gn:timezone":"Europe/Belgrade",
    "iso:country":"RS",
    "wof:name":"Vodenicari",
    "wof:placetype":"locality"
},
  "geometry": {"coordinates":[22.2971,42.64096],"type":"Point"}
}