{
  "type": "Feature",
  "properties": {
    "gn:admin1_code":"SE",
    "gn:admin2_code":"8",
    "gn:asciiname":"Gornje Koslje",
    "gn:country_code":"RS",
    "gn:dem":861,
    "gn:feature_class":"P",
    "gn:feature_code":"PPL",
    "gn:name":"Gornje Ko\u0161lje",
    "gn:population":0,
    "gn:timezone":"Europe/Belgrade",
    "iso:country":"RS",
    "name:ceb_x_preferred":[
        "Gornje Ko\u0161lje"
    ],
    "name:deu_x_preferred":[
        "Gornje Ko\u0161lje"
    ],
    "name:fas_x_preferred":[
        "\u06af\u0648\u0631\u0646\u06cc\u0647 \u06a9\u0648\u0634\u0644\u06cc\u0647"
    ],
    "name:fra_x_preferred":[
        "Gornje Ko\u0161lje"
    ],
    "name:msa_x_preferred":[
        "Gornje Ko\u0161lje"
    ],
    "name:nld_x_preferred":[
        "Gornje Ko\u0161lje"
    ],
    "name:por_x_preferred":[
        "Gornje Ko\u0161lje"
    ],
    "name:slv_x_preferred":[
        "Gornje Ko\u0161lje"
    ],
    "name:srp_x_preferred":[
        "Gornje Ko\u0161lje"
    ],
    "name:srp_x_variant":[
        "\u0413\u043e\u0440\u045a\u0435 \u041a\u043e\u0448\u0459\u0435"
    ],
    "wof:name":"Gornje Koslje",
    "wof:placetype":"locality"
},
  "geometry": {"coordinates":[19.56939,44.15358],"type":"Point"}
}