{
  "type": "Feature",
  "properties": {
    "gn:admin1_code":"SE",
    "gn:admin2_code":"8",
    "gn:asciiname":"Gornje Koslje",
    "gn:country_code":"RS",
    "gn:dem":861,
    "gn:feature_class":"P",
    "gn:feature_code":"PPL",
    "gn:name":"Gornje Ko\u0161lje",
    "gn:population":0,
    "gn:timezone":"Europe/Belgrade",
    "iso:country":"RS",
    "name:srp_x_preferred":[
        "Gornje Ko\u0161lje"
    ],
    "wof:name":"Gornje Koslje",
    "wof:placetype":"locality"
},
  "geometry": {"coordinates":[19.56939,44.15358],"type":"Point"}
}