{
  "type": "Feature",
  "properties": {
    "gn:admin1_code":"SE",
    "gn:admin2_code":"19",
    "gn:asciiname":"Bugarci",
    "gn:country_code":"RS",
    "gn:dem":422,
    "gn:feature_class":"P",
    "gn:feature_code":"PPL",
    "gn:name":"Bugarci",
    "gn:population":0,
    "gn:timezone":"Europe/Belgrade",
    "iso:country":"RS",
    "name:srp_x_preferred":[
        "Bugarci"
    ],
    "wof:name":"Bugarci",
    "wof:placetype":"locality"
},
  "geometry": {"coordinates":[21.0516,43.36724],"type":"Point"}
}