{
  "type": "Feature",
  "properties": {
    "gn:admin1_code":"SE",
    "gn:admin2_code":"24",
    "gn:asciiname":"Kozoder",
    "gn:country_code":"RS",
    "gn:dem":544,
    "gn:feature_class":"P",
    "gn:feature_code":"PPL",
    "gn:name":"Kozoder",
    "gn:population":0,
    "gn:timezone":"Europe/Belgrade",
    "iso:country":"RS",
    "wof:name":"Kozoder",
    "wof:placetype":"locality"
},
  "geometry": {"coordinates":[22.13032,42.66123],"type":"Point"}
}