{
  "type": "Feature",
  "properties": {
    "gn:admin1_code":"SE",
    "gn:admin2_code":"15",
    "gn:asciiname":"Marinovac",
    "gn:country_code":"RS",
    "gn:dem":450,
    "gn:feature_class":"P",
    "gn:feature_code":"PPL",
    "gn:name":"Marinovac",
    "gn:population":0,
    "gn:timezone":"Europe/Belgrade",
    "iso:country":"RS",
    "name:srp_x_preferred":[
        "Marinovac"
    ],
    "wof:name":"Marinovac",
    "wof:placetype":"locality"
},
  "geometry": {"coordinates":[22.21081,43.74249],"type":"Point"}
}