{
  "type": "Feature",
  "properties": {
    "gn:admin1_code":"SE",
    "gn:admin2_code":"8",
    "gn:asciiname":"Ravnica",
    "gn:country_code":"RS",
    "gn:dem":84,
    "gn:feature_class":"P",
    "gn:feature_code":"PPL",
    "gn:name":"Ravnica",
    "gn:population":0,
    "gn:timezone":"Europe/Belgrade",
    "iso:country":"RS",
    "wof:name":"Ravnica",
    "wof:placetype":"locality"
},
  "geometry": {"coordinates":[19.90628,44.65983],"type":"Point"}
}