{
  "type": "Feature",
  "properties": {
    "gn:admin1_code":"SE",
    "gn:admin2_code":"16",
    "gn:asciiname":"Avdovi",
    "gn:country_code":"RS",
    "gn:dem":662,
    "gn:feature_class":"P",
    "gn:feature_code":"PPL",
    "gn:name":"Avdovi",
    "gn:population":0,
    "gn:timezone":"Europe/Belgrade",
    "iso:country":"RS",
    "wof:name":"Avdovi",
    "wof:placetype":"locality"
},
  "geometry": {"coordinates":[19.61611,43.4275],"type":"Point"}
}