{
  "type": "Feature",
  "properties": {
    "gn:admin1_code":"SE",
    "gn:admin2_code":"19",
    "gn:asciiname":"Odzaci",
    "gn:country_code":"RS",
    "gn:dem":186,
    "gn:feature_class":"P",
    "gn:feature_code":"PPLL",
    "gn:name":"Od\u017eaci",
    "gn:population":0,
    "gn:timezone":"Europe/Belgrade",
    "iso:country":"RS",
    "name:srp_x_preferred":[
        "Od\u017eaci"
    ],
    "wof:name":"Odzaci",
    "wof:placetype":"locality"
},
  "geometry": {"coordinates":[21.03602,43.59799],"type":"Point"}
}