{
  "type": "Feature",
  "properties": {
    "gn:admin1_code":"SE",
    "gn:admin2_code":"8",
    "gn:asciiname":"Mesarci",
    "gn:country_code":"RS",
    "gn:dem":118,
    "gn:feature_class":"P",
    "gn:feature_code":"PPLL",
    "gn:name":"Mesarci",
    "gn:population":0,
    "gn:timezone":"Europe/Belgrade",
    "iso:country":"RS",
    "name:srp_x_preferred":[
        "Mesarci"
    ],
    "wof:name":"Mesarci",
    "wof:placetype":"locality"
},
  "geometry": {"coordinates":[19.93168,44.61735],"type":"Point"}
}