{
  "type": "Feature",
  "properties": {
    "gn:admin1_code":"SE",
    "gn:admin2_code":"21",
    "gn:asciiname":"Bublica",
    "gn:country_code":"RS",
    "gn:dem":463,
    "gn:feature_class":"P",
    "gn:feature_code":"PPL",
    "gn:name":"Bublica",
    "gn:population":0,
    "gn:timezone":"Europe/Belgrade",
    "iso:country":"RS",
    "name:srp_x_preferred":[
        "Bublica"
    ],
    "wof:name":"Bublica",
    "wof:placetype":"locality"
},
  "geometry": {"coordinates":[21.59972,43.05951],"type":"Point"}
}