{
  "type": "Feature",
  "properties": {
    "gn:admin1_code":"SE",
    "gn:admin2_code":"24",
    "gn:asciiname":"Tegoviste",
    "gn:country_code":"RS",
    "gn:dem":512,
    "gn:feature_class":"P",
    "gn:feature_code":"PPLL",
    "gn:name":"Tegovi\u0161te",
    "gn:population":0,
    "gn:timezone":"Europe/Belgrade",
    "iso:country":"RS",
    "name:srp_x_preferred":[
        "Tegovi\u0161te"
    ],
    "wof:name":"Tegoviste",
    "wof:placetype":"locality"
},
  "geometry": {"coordinates":[22.07274,42.75988],"type":"Point"}
}