{
  "type": "Feature",
  "properties": {
    "gn:admin1_code":"SE",
    "gn:admin2_code":"15",
    "gn:asciiname":"Bovan",
    "gn:country_code":"RS",
    "gn:dem":234,
    "gn:feature_class":"P",
    "gn:feature_code":"PPL",
    "gn:name":"Bovan",
    "gn:population":0,
    "gn:timezone":"Europe/Belgrade",
    "iso:country":"RS",
    "name:bos_x_preferred":[
        "Bovan"
    ],
    "name:ceb_x_preferred":[
        "Bovan"
    ],
    "name:fra_x_preferred":[
        "Bovan"
    ],
    "name:slv_x_preferred":[
        "Bovan"
    ],
    "name:srp_x_preferred":[
        "Bovan"
    ],
    "name:srp_x_variant":[
        "\u0411\u043e\u0432\u0430\u043d"
    ],
    "name:swe_x_preferred":[
        "Bovan"
    ],
    "wof:name":"Bovan",
    "wof:placetype":"locality"
},
  "geometry": {"coordinates":[21.71934,43.63464000000001],"type":"Point"}
}