{
  "type": "Feature",
  "properties": {
    "gn:admin1_code":"SE",
    "gn:admin2_code":"14",
    "gn:asciiname":"Dupljane",
    "gn:country_code":"RS",
    "gn:dem":197,
    "gn:feature_class":"P",
    "gn:feature_code":"PPL",
    "gn:name":"Dupljane",
    "gn:population":0,
    "gn:timezone":"Europe/Belgrade",
    "iso:country":"RS",
    "name:deu_x_preferred":[
        "Dupljane"
    ],
    "name:fra_x_preferred":[
        "Dupljane"
    ],
    "name:msa_x_preferred":[
        "Dupljane"
    ],
    "name:por_x_preferred":[
        "Dupljane"
    ],
    "name:slv_x_preferred":[
        "Dupljane"
    ],
    "name:srp_x_preferred":[
        "Dupljane"
    ],
    "name:srp_x_variant":[
        "\u0414\u0443\u043f\u0459\u0430\u043d\u0435"
    ],
    "name:und_x_variant":[
        "Dupljani"
    ],
    "wof:name":"Dupljane",
    "wof:placetype":"locality"
},
  "geometry": {"coordinates":[22.45876,44.3039],"type":"Point"}
}