{
  "type": "Feature",
  "properties": {
    "gn:admin1_code":"SE",
    "gn:admin2_code":"21",
    "gn:asciiname":"Igriste",
    "gn:country_code":"RS",
    "gn:dem":986,
    "gn:feature_class":"P",
    "gn:feature_code":"PPL",
    "gn:name":"Igri\u0161te",
    "gn:population":0,
    "gn:timezone":"Europe/Belgrade",
    "iso:country":"RS",
    "name:srp_x_preferred":[
        "Igri\u0161te"
    ],
    "wof:name":"Igriste",
    "wof:placetype":"locality"
},
  "geometry": {"coordinates":[21.12732,43.17828],"type":"Point"}
}