{
  "type": "Feature",
  "properties": {
    "gn:admin1_code":"SE",
    "gn:admin2_code":"21",
    "gn:asciiname":"Matarova",
    "gn:country_code":"RS",
    "gn:dem":601,
    "gn:feature_class":"P",
    "gn:feature_code":"PPLL",
    "gn:name":"Matarova",
    "gn:population":0,
    "gn:timezone":"Europe/Belgrade",
    "iso:country":"RS",
    "name:bul_x_preferred":[
        "\u041c\u0430\u0442\u0430\u0440\u043e\u0432\u0430"
    ],
    "name:fra_x_preferred":[
        "Matarova"
    ],
    "name:msa_x_preferred":[
        "Matarova"
    ],
    "name:por_x_preferred":[
        "Matarova"
    ],
    "name:slv_x_preferred":[
        "Matarova"
    ],
    "name:sqi_x_preferred":[
        "Matarova"
    ],
    "name:srp_x_preferred":[
        "Matarova"
    ],
    "name:srp_x_variant":[
        "\u041c\u0430\u0442\u0430\u0440\u043e\u0432\u0430"
    ],
    "name:und_x_variant":[
        "Matorovo"
    ],
    "wof:name":"Matarova",
    "wof:placetype":"locality"
},
  "geometry": {"coordinates":[21.25554,42.9637],"type":"Point"}
}