{
  "type": "Feature",
  "properties": {
    "iso:country":"RS",
    "name:eng_x_preferred":[
        "Blok 66a"
    ],
    "name:srp_cyr_x_preferred":[
        "\u0431\u043b\u043e\u043a 66a"
    ],
    "name:srp_x_preferred":[
        "\u0431\u043b\u043e\u043a 66a"
    ],
    "wof:name":"Blok 66a",
    "wof:placetype":"neighbourhood"
},
  "geometry": {"coordinates":[20.40413387550418,44.81061012395903],"type":"Point"}
}