{
  "type": "Feature",
  "properties": {
    "gn:admin1_code":"SE",
    "gn:admin2_code":"22",
    "gn:asciiname":"Poljska Rzana",
    "gn:country_code":"RS",
    "gn:dem":382,
    "gn:feature_class":"P",
    "gn:feature_code":"PPL",
    "gn:name":"Poljska R\u017eana",
    "gn:population":0,
    "gn:timezone":"Europe/Belgrade",
    "iso:country":"RS",
    "name:ceb_x_preferred":[
        "Poljska R\u017eana"
    ],
    "name:fra_x_preferred":[
        "Poljska R\u017eana"
    ],
    "name:msa_x_preferred":[
        "Poljska R\u017eana"
    ],
    "name:por_x_preferred":[
        "Poljska R\u017eana"
    ],
    "name:slv_x_preferred":[
        "Poljska R\u017eana"
    ],
    "name:srp_x_preferred":[
        "Poljska R\u017eana"
    ],
    "name:srp_x_variant":[
        "\u041f\u043e\u0459\u0441\u043a\u0430 \u0420\u0436\u0430\u043d\u0430"
    ],
    "wof:name":"Poljska Rzana",
    "wof:placetype":"locality"
},
  "geometry": {"coordinates":[22.62716,43.12726],"type":"Point"}
}