{
  "type": "Feature",
  "properties": {
    "gn:admin1_code":"SE",
    "gn:admin2_code":"0",
    "gn:asciiname":"Ritopek",
    "gn:country_code":"RS",
    "gn:dem":93,
    "gn:feature_class":"P",
    "gn:feature_code":"PPL",
    "gn:name":"Ritopek",
    "gn:population":0,
    "gn:timezone":"Europe/Belgrade",
    "iso:country":"RS",
    "name:srp_x_preferred":[
        "Ritopek"
    ],
    "name:und_x_variant":[
        "Ritovel",
        "Ritopele"
    ],
    "wof:name":"Ritopek",
    "wof:placetype":"locality"
},
  "geometry": {"coordinates":[20.65525,44.7382],"type":"Point"}
}