{
  "type": "Feature",
  "properties": {
    "gn:admin1_code":"SE",
    "gn:admin2_code":"9",
    "gn:asciiname":"Majinovic",
    "gn:country_code":"RS",
    "gn:dem":366,
    "gn:feature_class":"P",
    "gn:feature_code":"PPLL",
    "gn:name":"Majinovi\u0107",
    "gn:population":0,
    "gn:timezone":"Europe/Belgrade",
    "iso:country":"RS",
    "name:srp_x_preferred":[
        "Majinovi\u0107"
    ],
    "name:und_x_variant":[
        "Majinovi\u0107i"
    ],
    "wof:name":"Majinovic",
    "wof:placetype":"locality"
},
  "geometry": {"coordinates":[19.71927,44.28553],"type":"Point"}
}