{
  "type": "Feature",
  "properties": {
    "gn:admin1_code":"SE",
    "gn:admin2_code":"9",
    "gn:asciiname":"Majinovic",
    "gn:country_code":"RS",
    "gn:dem":366,
    "gn:feature_class":"P",
    "gn:feature_code":"PPLL",
    "gn:name":"Majinovi\u0107",
    "gn:population":0,
    "gn:timezone":"Europe/Belgrade",
    "iso:country":"RS",
    "name:ell_x_preferred":[
        "\u039c\u03b1\u03b3\u03af\u03bd\u03bf\u03b2\u03b9\u03c4\u03c2"
    ],
    "name:fra_x_preferred":[
        "Majinovi\u0107"
    ],
    "name:msa_x_preferred":[
        "Majinovi\u0107"
    ],
    "name:nld_x_preferred":[
        "Majinovi\u0107"
    ],
    "name:por_x_preferred":[
        "Majinovi\u0107"
    ],
    "name:slv_x_preferred":[
        "Majinovi\u0107"
    ],
    "name:srp_x_preferred":[
        "Majinovi\u0107"
    ],
    "name:srp_x_variant":[
        "\u041c\u0430\u0458\u0438\u043d\u043e\u0432\u0438\u045b"
    ],
    "name:und_x_variant":[
        "Majinovi\u0107i"
    ],
    "wof:name":"Majinovic",
    "wof:placetype":"locality"
},
  "geometry": {"coordinates":[19.71927,44.28553],"type":"Point"}
}