{
  "type": "Feature",
  "properties": {
    "gn:country":"RS",
    "gn:fcode":"PPL",
    "gn:pop":3864,
    "iso:country":"RS",
    "name:eng_x_preferred":[
        "Ba\u0161aid"
    ],
    "name:epo_x_preferred":[
        "Ba\u015daid"
    ],
    "name:fra_x_preferred":[
        "Ba\u0161aid"
    ],
    "name:hun_x_preferred":[
        "Basah\u00edd"
    ],
    "name:msa_x_preferred":[
        "Ba\u0161aid"
    ],
    "name:nld_x_preferred":[
        "Ba\u0161aid"
    ],
    "name:ron_x_preferred":[
        "Ba\u0161aid"
    ],
    "name:rus_x_preferred":[
        "\u0411\u0430\u0448\u0430\u0438\u0434"
    ],
    "name:slv_x_preferred":[
        "Ba\u0161aid"
    ],
    "name:srp_x_preferred":[
        "Ba\u0161aid"
    ],
    "name:unk_x_variant":[
        "Klein-Kikinda"
    ],
    "qs:name":"Ba\u0161aid",
    "qs:photos_9r":0,
    "qs:photos_sr":0,
    "qs:pop_sr":"4",
    "wd:wordcount":112,
    "wof:name":"Ba\u0161aid",
    "wof:placetype":"locality",
    "wof:population":3864
},
  "geometry": {"coordinates":[20.41434,45.64102],"type":"Point"}
}