{
  "type": "Feature",
  "properties": {
    "gn:admin1_code":"SE",
    "gn:admin2_code":"18",
    "gn:asciiname":"Vever",
    "gn:country_code":"RS",
    "gn:dem":911,
    "gn:feature_class":"P",
    "gn:feature_code":"PPL",
    "gn:name":"Vever",
    "gn:population":0,
    "gn:timezone":"Europe/Belgrade",
    "iso:country":"RS",
    "name:fra_x_preferred":[
        "Vever"
    ],
    "name:hun_x_preferred":[
        "Vever"
    ],
    "name:msa_x_preferred":[
        "Vever"
    ],
    "name:nld_x_preferred":[
        "Vever"
    ],
    "name:por_x_preferred":[
        "Vever"
    ],
    "name:slv_x_preferred":[
        "Vever"
    ],
    "name:srp_x_preferred":[
        "Vever"
    ],
    "name:srp_x_variant":[
        "\u0412\u0435\u0432\u0435\u0440"
    ],
    "wof:name":"Vever",
    "wof:placetype":"locality"
},
  "geometry": {"coordinates":[20.37689,43.18707],"type":"Point"}
}