{
  "type": "Feature",
  "properties": {
    "gn:admin1_code":"SE",
    "gn:admin2_code":"16",
    "gn:asciiname":"Vrtace",
    "gn:country_code":"RS",
    "gn:dem":720,
    "gn:feature_class":"P",
    "gn:feature_code":"PPL",
    "gn:name":"Vrta\u010de",
    "gn:population":0,
    "gn:timezone":"Europe/Belgrade",
    "iso:country":"RS",
    "name:srp_x_preferred":[
        "Vrta\u010de"
    ],
    "wof:name":"Vrtace",
    "wof:placetype":"locality"
},
  "geometry": {"coordinates":[19.23194,43.49806],"type":"Point"}
}