{
  "type": "Feature",
  "properties": {
    "gn:admin1_code":"SE",
    "gn:admin2_code":"16",
    "gn:asciiname":"Masnice",
    "gn:country_code":"RS",
    "gn:dem":513,
    "gn:feature_class":"P",
    "gn:feature_code":"PPL",
    "gn:name":"Masnice",
    "gn:population":0,
    "gn:timezone":"Europe/Belgrade",
    "iso:country":"RS",
    "name:srp_x_preferred":[
        "Masnice"
    ],
    "wof:name":"Masnice",
    "wof:placetype":"locality"
},
  "geometry": {"coordinates":[19.38873,43.51794],"type":"Point"}
}