{
  "type": "Feature",
  "properties": {
    "gn:admin1_code":"SE",
    "gn:admin2_code":"8",
    "gn:asciiname":"Veliko Selo",
    "gn:country_code":"RS",
    "gn:dem":209,
    "gn:feature_class":"P",
    "gn:feature_code":"PPL",
    "gn:name":"Veliko Selo",
    "gn:population":0,
    "gn:timezone":"Europe/Belgrade",
    "iso:country":"RS",
    "name:srp_x_preferred":[
        "Veliko Selo"
    ],
    "wof:name":"Veliko Selo",
    "wof:placetype":"locality"
},
  "geometry": {"coordinates":[19.38534,44.55086],"type":"Point"}
}