{
  "type": "Feature",
  "properties": {
    "gn:admin1_code":"SE",
    "gn:admin2_code":"18",
    "gn:asciiname":"Dolovo",
    "gn:country_code":"RS",
    "gn:dem":1009,
    "gn:feature_class":"P",
    "gn:feature_code":"PPLL",
    "gn:name":"Dolovo",
    "gn:population":0,
    "gn:timezone":"Europe/Belgrade",
    "iso:country":"RS",
    "name:bos_x_preferred":[
        "Dolovo"
    ],
    "name:fra_x_preferred":[
        "Dolovo"
    ],
    "name:hrv_x_preferred":[
        "Dolovo"
    ],
    "name:hun_x_preferred":[
        "Dolovo"
    ],
    "name:msa_x_preferred":[
        "Dolovo"
    ],
    "name:nld_x_preferred":[
        "Dolovo"
    ],
    "name:slv_x_preferred":[
        "Dolovo"
    ],
    "name:srp_x_preferred":[
        "Dolovo"
    ],
    "name:srp_x_variant":[
        "\u0414\u043e\u043b\u043e\u0432\u043e"
    ],
    "wof:name":"Dolovo",
    "wof:placetype":"locality"
},
  "geometry": {"coordinates":[20.22605,42.97282],"type":"Point"}
}