{
  "type": "Feature",
  "properties": {
    "gn:admin1_code":"SE",
    "gn:admin2_code":"23",
    "gn:asciiname":"Jabukovik",
    "gn:country_code":"RS",
    "gn:dem":976,
    "gn:feature_class":"P",
    "gn:feature_code":"PPL",
    "gn:name":"Jabukovik",
    "gn:population":0,
    "gn:timezone":"Europe/Belgrade",
    "iso:country":"RS",
    "name:srp_x_preferred":[
        "Jabukovik"
    ],
    "wof:name":"Jabukovik",
    "wof:placetype":"locality"
},
  "geometry": {"coordinates":[22.36917,42.90556],"type":"Point"}
}