{
  "type": "Feature",
  "properties": {
    "gn:admin1_code":"SE",
    "gn:admin2_code":"23",
    "gn:asciiname":"Jabukovik",
    "gn:country_code":"RS",
    "gn:dem":976,
    "gn:feature_class":"P",
    "gn:feature_code":"PPL",
    "gn:name":"Jabukovik",
    "gn:population":0,
    "gn:timezone":"Europe/Belgrade",
    "iso:country":"RS",
    "name:fra_x_preferred":[
        "Jabukovik"
    ],
    "name:hun_x_preferred":[
        "Jabukovik"
    ],
    "name:msa_x_preferred":[
        "Jabukovik"
    ],
    "name:por_x_preferred":[
        "Jabukovik"
    ],
    "name:slv_x_preferred":[
        "Jabukovik"
    ],
    "name:srp_x_preferred":[
        "Jabukovik"
    ],
    "name:srp_x_variant":[
        "\u0408\u0430\u0431\u0443\u043a\u043e\u0432\u0438\u043a"
    ],
    "name:urd_x_preferred":[
        "\u062c\u0628\u06a9\u0648\u0648\u06cc\u06a9"
    ],
    "wof:name":"Jabukovik",
    "wof:placetype":"locality"
},
  "geometry": {"coordinates":[22.36917,42.90556],"type":"Point"}
}