{
  "type": "Feature",
  "properties": {
    "gn:admin1_code":"SE",
    "gn:admin2_code":"11",
    "gn:asciiname":"Mustapic",
    "gn:country_code":"RS",
    "gn:dem":163,
    "gn:feature_class":"P",
    "gn:feature_code":"PPL",
    "gn:name":"Mustapi\u0107",
    "gn:population":0,
    "gn:timezone":"Europe/Belgrade",
    "iso:country":"RS",
    "name:srp_x_preferred":[
        "Mustapi\u0107"
    ],
    "wof:name":"Mustapic",
    "wof:placetype":"locality"
},
  "geometry": {"coordinates":[21.53808,44.53116],"type":"Point"}
}