{
  "type": "Feature",
  "properties": {
    "gn:admin1_code":"SE",
    "gn:admin2_code":"11",
    "gn:asciiname":"Mustapic",
    "gn:country_code":"RS",
    "gn:dem":163,
    "gn:feature_class":"P",
    "gn:feature_code":"PPL",
    "gn:name":"Mustapi\u0107",
    "gn:population":0,
    "gn:timezone":"Europe/Belgrade",
    "iso:country":"RS",
    "name:ceb_x_preferred":[
        "Mustapi\u0107"
    ],
    "name:fra_x_preferred":[
        "Mustapi\u0107"
    ],
    "name:msa_x_preferred":[
        "Mustapi\u0107"
    ],
    "name:por_x_preferred":[
        "Mustapi\u0107"
    ],
    "name:slv_x_preferred":[
        "Mustapi\u0107"
    ],
    "name:srp_x_preferred":[
        "Mustapi\u0107"
    ],
    "name:srp_x_variant":[
        "\u041c\u0443\u0441\u0442\u0430\u043f\u0438\u045b"
    ],
    "wof:name":"Mustapic",
    "wof:placetype":"locality"
},
  "geometry": {"coordinates":[21.53808,44.53116],"type":"Point"}
}