{
  "type": "Feature",
  "properties": {
    "gn:admin1_code":"SE",
    "gn:admin2_code":"24",
    "gn:asciiname":"Angelkovska Mahala",
    "gn:country_code":"RS",
    "gn:dem":453,
    "gn:feature_class":"P",
    "gn:feature_code":"PPL",
    "gn:name":"An\u0111elkovska Mahala",
    "gn:population":0,
    "gn:timezone":"Europe/Belgrade",
    "iso:country":"RS",
    "wof:name":"Angelkovska Mahala",
    "wof:placetype":"locality"
},
  "geometry": {"coordinates":[21.96827,42.51026],"type":"Point"}
}