{
  "type": "Feature",
  "properties": {
    "gn:admin1_code":"SE",
    "gn:admin2_code":"14",
    "gn:asciiname":"Kladusnica",
    "gn:country_code":"RS",
    "gn:dem":47,
    "gn:feature_class":"P",
    "gn:feature_code":"PPL",
    "gn:name":"Kladu\u0161nica",
    "gn:population":0,
    "gn:timezone":"Europe/Belgrade",
    "iso:country":"RS",
    "name:ceb_x_preferred":[
        "Kladu\u0161nica"
    ],
    "name:deu_x_preferred":[
        "Kladu\u0161nica"
    ],
    "name:fra_x_preferred":[
        "Kladu\u0161nica"
    ],
    "name:mkd_x_preferred":[
        "\u041a\u043b\u0430\u0434\u0443\u0448\u043d\u0438\u0446\u0430"
    ],
    "name:msa_x_preferred":[
        "Kladu\u0161nica"
    ],
    "name:por_x_preferred":[
        "Kladu\u0161nica"
    ],
    "name:slv_x_preferred":[
        "Kladu\u0161nica"
    ],
    "name:srp_x_preferred":[
        "Kladu\u0161nica"
    ],
    "name:srp_x_variant":[
        "\u041a\u043b\u0430\u0434\u0443\u0448\u043d\u0438\u0446\u0430"
    ],
    "wof:name":"Kladusnica",
    "wof:placetype":"locality"
},
  "geometry": {"coordinates":[22.57074,44.63069],"type":"Point"}
}