{
  "type": "Feature",
  "properties": {
    "gn:admin1_code":"SE",
    "gn:admin2_code":"22",
    "gn:asciiname":"Preseka",
    "gn:country_code":"RS",
    "gn:dem":838,
    "gn:feature_class":"P",
    "gn:feature_code":"PPL",
    "gn:name":"Preseka",
    "gn:population":0,
    "gn:timezone":"Europe/Belgrade",
    "iso:country":"RS",
    "name:srp_x_preferred":[
        "Preseka"
    ],
    "wof:name":"Preseka",
    "wof:placetype":"locality"
},
  "geometry": {"coordinates":[22.53361,42.95083],"type":"Point"}
}