{
  "type": "Feature",
  "properties": {
    "gn:admin1_code":"SE",
    "gn:admin2_code":"19",
    "gn:asciiname":"Osaonica",
    "gn:country_code":"RS",
    "gn:dem":178,
    "gn:feature_class":"P",
    "gn:feature_code":"PPLL",
    "gn:name":"Osaonica",
    "gn:population":0,
    "gn:timezone":"Europe/Belgrade",
    "iso:country":"RS",
    "name:fra_x_preferred":[
        "Osaonica"
    ],
    "name:hrv_x_preferred":[
        "Osaonica"
    ],
    "name:nld_x_preferred":[
        "Osaonica"
    ],
    "name:slv_x_preferred":[
        "Osaonica"
    ],
    "name:srp_x_preferred":[
        "Osaonica"
    ],
    "name:srp_x_variant":[
        "\u041e\u0441\u0430\u043e\u043d\u0438\u0446\u0430"
    ],
    "wof:name":"Osaonica",
    "wof:placetype":"locality"
},
  "geometry": {"coordinates":[20.97733,43.62026],"type":"Point"}
}