{
  "type": "Feature",
  "properties": {
    "gn:admin1_code":"SE",
    "gn:admin2_code":"8",
    "gn:asciiname":"Misar",
    "gn:country_code":"RS",
    "gn:dem":78,
    "gn:feature_class":"P",
    "gn:feature_code":"PPLL",
    "gn:name":"Mi\u0161ar",
    "gn:population":0,
    "gn:timezone":"Europe/Belgrade",
    "iso:country":"RS",
    "name:ceb_x_preferred":[
        "Mi\u0161ar"
    ],
    "name:fra_x_preferred":[
        "Mi\u0161ar"
    ],
    "name:msa_x_preferred":[
        "Mi\u0161ar"
    ],
    "name:por_x_preferred":[
        "Mi\u0161ar"
    ],
    "name:slv_x_preferred":[
        "Mi\u0161ar"
    ],
    "name:srp_x_preferred":[
        "Mi\u0161ar"
    ],
    "name:srp_x_variant":[
        "\u041c\u0438\u0448\u0430\u0440"
    ],
    "wof:name":"Misar",
    "wof:placetype":"locality"
},
  "geometry": {"coordinates":[19.75471,44.73456],"type":"Point"}
}