{
  "type": "Feature",
  "properties": {
    "gn:admin1_code":"SE",
    "gn:admin2_code":"20",
    "gn:asciiname":"Camurlija",
    "gn:country_code":"RS",
    "gn:dem":242,
    "gn:feature_class":"P",
    "gn:feature_code":"PPL",
    "gn:name":"\u010camurlija",
    "gn:population":0,
    "gn:timezone":"Europe/Belgrade",
    "iso:country":"RS",
    "name:ceb_x_preferred":[
        "\u010camurlija"
    ],
    "name:fra_x_preferred":[
        "\u010camurlija"
    ],
    "name:msa_x_preferred":[
        "\u010camurlija"
    ],
    "name:por_x_preferred":[
        "\u010camurlija"
    ],
    "name:slv_x_preferred":[
        "\u010camurlija"
    ],
    "name:srp_x_preferred":[
        "\u010camurlija"
    ],
    "name:srp_x_variant":[
        "\u0427\u0430\u043c\u0443\u0440\u043b\u0438\u0458\u0430"
    ],
    "wof:name":"Camurlija",
    "wof:placetype":"locality"
},
  "geometry": {"coordinates":[21.84699,43.3653],"type":"Point"}
}