{
  "type": "Feature",
  "properties": {
    "gn:admin1_code":"SE",
    "gn:admin2_code":"18",
    "gn:asciiname":"Kremice",
    "gn:country_code":"RS",
    "gn:dem":829,
    "gn:feature_class":"P",
    "gn:feature_code":"PPL",
    "gn:name":"Kremi\u0107e",
    "gn:population":0,
    "gn:timezone":"Europe/Belgrade",
    "iso:country":"RS",
    "name:srp_x_preferred":[
        "Kremi\u0107e"
    ],
    "name:und_x_variant":[
        "Kremi\u0107i"
    ],
    "wof:name":"Kremice",
    "wof:placetype":"locality"
},
  "geometry": {"coordinates":[20.69275,43.34948],"type":"Point"}
}