{
  "type": "Feature",
  "properties": {
    "gn:admin1_code":"VO",
    "gn:admin2_code":"6",
    "gn:asciiname":"Radicevic",
    "gn:country_code":"RS",
    "gn:dem":78,
    "gn:feature_class":"P",
    "gn:feature_code":"PPL",
    "gn:name":"Radi\u010devi\u0107",
    "gn:population":0,
    "gn:timezone":"Europe/Belgrade",
    "iso:country":"RS",
    "name:ceb_x_preferred":[
        "Radi\u010devi\u0107"
    ],
    "name:epo_x_preferred":[
        "Radi\u0109evicj"
    ],
    "name:fra_x_preferred":[
        "Radi\u010devi\u0107"
    ],
    "name:hrv_x_preferred":[
        "Radi\u010devi\u0107"
    ],
    "name:hun_x_preferred":[
        "Csik\u00e9riapuszta"
    ],
    "name:msa_x_preferred":[
        "Radi\u010devi\u0107"
    ],
    "name:slv_x_preferred":[
        "Radi\u010devi\u0107"
    ],
    "name:srp_x_preferred":[
        "\u0420\u0430\u0434\u0438\u0447\u0435\u0432\u0438\u045b"
    ],
    "name:ukr_x_preferred":[
        "\u0420\u0430\u0434\u0438\u0447\u0435\u0432\u0438\u0447"
    ],
    "name:und_x_variant":[
        "Radi\u010devi\u0107"
    ],
    "wof:name":"Radicevic",
    "wof:placetype":"locality"
},
  "geometry": {"coordinates":[19.91667,45.58194],"type":"Point"}
}