{
  "type": "Feature",
  "properties": {
    "gn:admin1_code":"SE",
    "gn:admin2_code":"20",
    "gn:asciiname":"Nova Bozurna",
    "gn:country_code":"RS",
    "gn:dem":343,
    "gn:feature_class":"P",
    "gn:feature_code":"PPL",
    "gn:name":"Nova Bo\u017eurna",
    "gn:population":0,
    "gn:timezone":"Europe/Belgrade",
    "iso:country":"RS",
    "name:ceb_x_preferred":[
        "Nova Bo\u017eurna"
    ],
    "name:fra_x_preferred":[
        "Nova Bo\u017eurna"
    ],
    "name:msa_x_preferred":[
        "Nova Bo\u017eurna"
    ],
    "name:por_x_preferred":[
        "Nova Bo\u017eurna"
    ],
    "name:slv_x_preferred":[
        "Nova Bo\u017eurna"
    ],
    "name:srp_x_preferred":[
        "Nova Bo\u017eurna"
    ],
    "name:srp_x_variant":[
        "\u041d\u043e\u0432\u0430 \u0411\u043e\u0436\u0443\u0440\u043d\u0430"
    ],
    "name:und_x_variant":[
        "Nova Bo\u017eurnja"
    ],
    "wof:name":"Nova Bozurna",
    "wof:placetype":"locality"
},
  "geometry": {"coordinates":[21.63521,43.24748],"type":"Point"}
}