{
  "type": "Feature",
  "properties": {
    "iso:country":"RS",
    "name:eng_x_preferred":[
        "Rudo"
    ],
    "name:srp_cyr_x_preferred":[
        "\u0420\u0443\u0434\u043e"
    ],
    "name:srp_x_preferred":[
        "\u0420\u0443\u0434\u043e"
    ],
    "wof:name":"Rudo",
    "wof:placetype":"neighbourhood"
},
  "geometry": {"coordinates":[20.51185194247357,44.78465452634814],"type":"Point"}
}