{
  "type": "Feature",
  "properties": {
    "gn:admin1_code":"SE",
    "gn:admin2_code":"11",
    "gn:admin3_code":"70807.0",
    "gn:asciiname":"Aljudovo",
    "gn:country_code":"RS",
    "gn:dem":129,
    "gn:feature_class":"P",
    "gn:feature_code":"PPL",
    "gn:name":"Aljudovo",
    "gn:population":0,
    "gn:timezone":"Europe/Belgrade",
    "iso:country":"RS",
    "name:ceb_x_preferred":[
        "Aljudovo"
    ],
    "name:fas_x_preferred":[
        "\u0627\u0644\u062c\u0627\u062f\u0627\u0648"
    ],
    "name:fra_x_preferred":[
        "Aljudovo"
    ],
    "name:msa_x_preferred":[
        "Aljudovo"
    ],
    "name:por_x_preferred":[
        "Aljudovo"
    ],
    "name:slv_x_preferred":[
        "Aljudovo"
    ],
    "name:srp_x_preferred":[
        "Aljudovo"
    ],
    "name:srp_x_variant":[
        "\u0410\u0459\u0443\u0434\u043e\u0432\u043e"
    ],
    "wof:name":"Aljudovo",
    "wof:placetype":"locality"
},
  "geometry": {"coordinates":[21.42763,44.50725],"type":"Point"}
}