{
  "type": "Feature",
  "properties": {
    "gn:admin1_code":"SE",
    "gn:admin2_code":"20",
    "gn:asciiname":"Lalinac",
    "gn:country_code":"RS",
    "gn:dem":434,
    "gn:feature_class":"P",
    "gn:feature_code":"PPL",
    "gn:name":"Lalinac",
    "gn:population":0,
    "gn:timezone":"Europe/Belgrade",
    "iso:country":"RS",
    "name:srp_x_preferred":[
        "Lalinac"
    ],
    "wof:name":"Lalinac",
    "wof:placetype":"locality"
},
  "geometry": {"coordinates":[22.01766,43.44456],"type":"Point"}
}