{
  "type": "Feature",
  "properties": {
    "gn:admin1_code":"SE",
    "gn:admin2_code":"20",
    "gn:admin3_code":"71064.0",
    "gn:asciiname":"Beloinje",
    "gn:country_code":"RS",
    "gn:dem":415,
    "gn:feature_class":"P",
    "gn:feature_code":"PPL",
    "gn:name":"Beloinje",
    "gn:population":0,
    "gn:timezone":"Europe/Belgrade",
    "iso:country":"RS",
    "name:ceb_x_preferred":[
        "Beloinje"
    ],
    "name:fra_x_preferred":[
        "Beloinje"
    ],
    "name:msa_x_preferred":[
        "Beloinje"
    ],
    "name:por_x_preferred":[
        "Beloinje"
    ],
    "name:slv_x_preferred":[
        "Beloinje"
    ],
    "name:srp_x_preferred":[
        "Beloinje"
    ],
    "name:srp_x_variant":[
        "\u0411\u0435\u043b\u043e\u0438\u045a\u0435"
    ],
    "wof:name":"Beloinje",
    "wof:placetype":"locality"
},
  "geometry": {"coordinates":[22.16513,43.39075],"type":"Point"}
}