{
  "type": "Feature",
  "properties": {
    "gn:admin1_code":"SE",
    "gn:admin2_code":"19",
    "gn:asciiname":"Albanija",
    "gn:country_code":"RS",
    "gn:dem":313,
    "gn:feature_class":"P",
    "gn:feature_code":"PPL",
    "gn:name":"Albanija",
    "gn:population":0,
    "gn:timezone":"Europe/Belgrade",
    "iso:country":"RS",
    "name:srp_x_preferred":[
        "Albanija"
    ],
    "wof:name":"Albanija",
    "wof:placetype":"locality"
},
  "geometry": {"coordinates":[21.17626,43.39112],"type":"Point"}
}