{
  "type": "Feature",
  "properties": {
    "gn:admin1_code":"SE",
    "gn:admin2_code":"9",
    "gn:asciiname":"Prijezdic",
    "gn:country_code":"RS",
    "gn:dem":404,
    "gn:feature_class":"P",
    "gn:feature_code":"PPL",
    "gn:name":"Prijezdi\u0107",
    "gn:population":0,
    "gn:timezone":"Europe/Belgrade",
    "iso:country":"RS",
    "name:ceb_x_preferred":[
        "Prijezdi\u0107"
    ],
    "name:fra_x_preferred":[
        "Prijezdi\u0107"
    ],
    "name:msa_x_preferred":[
        "Prijezdi\u0107"
    ],
    "name:nld_x_preferred":[
        "Prijezdi\u0107"
    ],
    "name:por_x_preferred":[
        "Prijezdi\u0107"
    ],
    "name:slv_x_preferred":[
        "Prijezdi\u0107"
    ],
    "name:srp_x_preferred":[
        "Prijezdi\u0107"
    ],
    "name:srp_x_variant":[
        "\u041f\u0440\u0438\u0458\u0435\u0437\u0434\u0438\u045b"
    ],
    "name:und_x_variant":[
        "Prijezdi\u0107i"
    ],
    "wof:name":"Prijezdic",
    "wof:placetype":"locality"
},
  "geometry": {"coordinates":[19.93459,44.19681],"type":"Point"}
}