{
  "type": "Feature",
  "properties": {
    "gn:admin1_code":"SE",
    "gn:admin2_code":"17",
    "gn:asciiname":"Popovici",
    "gn:country_code":"RS",
    "gn:dem":508,
    "gn:feature_class":"P",
    "gn:feature_code":"PPL",
    "gn:name":"Popovi\u0107i",
    "gn:population":0,
    "gn:timezone":"Europe/Belgrade",
    "iso:country":"RS",
    "name:heb_x_preferred":[
        "\u05e4\u05d5\u05e4\u05d5\u05d1\u05d9\u05e5'"
    ],
    "wof:name":"Popovici",
    "wof:placetype":"locality"
},
  "geometry": {"coordinates":[20.20389,43.87583],"type":"Point"}
}