{
  "type": "Feature",
  "properties": {
    "gn:admin1_code":"SE",
    "gn:admin2_code":"24",
    "gn:asciiname":"Kocura",
    "gn:country_code":"RS",
    "gn:dem":1125,
    "gn:feature_class":"P",
    "gn:feature_code":"PPLL",
    "gn:name":"Ko\u0107ura",
    "gn:population":0,
    "gn:timezone":"Europe/Belgrade",
    "iso:country":"RS",
    "name:bul_x_preferred":[
        "\u041a\u043e\u0447\u0443\u0440\u0430"
    ],
    "name:ceb_x_preferred":[
        "Ko\u0107ura"
    ],
    "name:fra_x_preferred":[
        "Ko\u0107ura"
    ],
    "name:msa_x_preferred":[
        "Ko\u0107ura"
    ],
    "name:nld_x_preferred":[
        "Ko\u0107ura"
    ],
    "name:por_x_preferred":[
        "Ko\u0107ura"
    ],
    "name:slv_x_preferred":[
        "Ko\u0107ura"
    ],
    "name:srp_x_preferred":[
        "Ko\u0107ura"
    ],
    "name:srp_x_variant":[
        "\u041a\u043e\u045b\u0443\u0440\u0430"
    ],
    "wof:name":"Kocura",
    "wof:placetype":"locality"
},
  "geometry": {"coordinates":[22.06933,42.42751],"type":"Point"}
}