{
  "type": "Feature",
  "properties": {
    "gn:admin1_code":"SE",
    "gn:admin2_code":"23",
    "gn:asciiname":"Gazdare",
    "gn:country_code":"RS",
    "gn:dem":394,
    "gn:feature_class":"P",
    "gn:feature_code":"PPL",
    "gn:name":"Gazdare",
    "gn:population":0,
    "gn:timezone":"Europe/Belgrade",
    "iso:country":"RS",
    "name:fra_x_preferred":[
        "Gazdare"
    ],
    "name:hun_x_preferred":[
        "Gazdare"
    ],
    "name:msa_x_preferred":[
        "Gazdare"
    ],
    "name:por_x_preferred":[
        "Gazdare"
    ],
    "name:slv_x_preferred":[
        "Gazdare"
    ],
    "name:sqi_x_preferred":[
        "Gazdara"
    ],
    "name:srp_x_preferred":[
        "Gazdare"
    ],
    "name:srp_x_variant":[
        "\u0413\u0430\u0437\u0434\u0430\u0440\u0435"
    ],
    "name:und_x_variant":[
        "Gazdari"
    ],
    "wof:name":"Gazdare",
    "wof:placetype":"locality"
},
  "geometry": {"coordinates":[21.5716,42.88436],"type":"Point"}
}