{
  "type": "Feature",
  "properties": {
    "gn:admin1_code":"SE",
    "gn:admin2_code":"17",
    "gn:asciiname":"Karadak",
    "gn:country_code":"RS",
    "gn:dem":1105,
    "gn:feature_class":"P",
    "gn:feature_code":"PPL",
    "gn:name":"Karadak",
    "gn:population":0,
    "gn:timezone":"Europe/Belgrade",
    "iso:country":"RS",
    "name:fra_x_preferred":[
        "Karadak"
    ],
    "name:msa_x_preferred":[
        "Karadak"
    ],
    "name:nld_x_preferred":[
        "Karadak"
    ],
    "name:por_x_preferred":[
        "Karadak"
    ],
    "name:slv_x_preferred":[
        "Karadak"
    ],
    "name:sqi_x_preferred":[
        "Karadaku"
    ],
    "name:srp_x_preferred":[
        "Karadak"
    ],
    "name:srp_x_variant":[
        "\u041a\u0430\u0440\u0430\u0434\u0430\u043a"
    ],
    "wof:name":"Karadak",
    "wof:placetype":"locality"
},
  "geometry": {"coordinates":[20.3606,43.36822],"type":"Point"}
}