{
  "type": "Feature",
  "properties": {
    "gn:admin1_code":"SE",
    "gn:admin2_code":"16",
    "gn:asciiname":"Cukavci",
    "gn:country_code":"RS",
    "gn:dem":594,
    "gn:feature_class":"P",
    "gn:feature_code":"PPL",
    "gn:name":"\u010cukavci",
    "gn:population":0,
    "gn:timezone":"Europe/Belgrade",
    "iso:country":"RS",
    "name:srp_x_preferred":[
        "\u010cukavci"
    ],
    "wof:name":"Cukavci",
    "wof:placetype":"locality"
},
  "geometry": {"coordinates":[19.93004,43.92957],"type":"Point"}
}