{
  "type": "Feature",
  "properties": {
    "gn:admin1_code":"SE",
    "gn:admin2_code":"24",
    "gn:asciiname":"Kukavica",
    "gn:country_code":"RS",
    "gn:dem":1259,
    "gn:feature_class":"P",
    "gn:feature_code":"PPL",
    "gn:name":"Kukavica",
    "gn:population":0,
    "gn:timezone":"Europe/Belgrade",
    "iso:country":"RS",
    "name:bul_x_preferred":[
        "\u041a\u0443\u043a\u0430\u0432\u0438\u0446\u0430"
    ],
    "name:fra_x_preferred":[
        "Kukavica"
    ],
    "name:nld_x_preferred":[
        "Kukavica"
    ],
    "name:srp_x_preferred":[
        "Kukavica"
    ],
    "name:srp_x_variant":[
        "\u041a\u0443\u043a\u0430\u0432\u0438\u0446\u0430"
    ],
    "wof:name":"Kukavica",
    "wof:placetype":"locality"
},
  "geometry": {"coordinates":[21.96948,42.75343],"type":"Point"}
}