{
  "type": "Feature",
  "properties": {
    "gn:admin1_code":"SE",
    "gn:admin2_code":"18",
    "gn:asciiname":"Dobra Bukva",
    "gn:country_code":"RS",
    "gn:dem":628,
    "gn:feature_class":"P",
    "gn:feature_code":"PPL",
    "gn:name":"Dobra Bukva",
    "gn:population":0,
    "gn:timezone":"Europe/Belgrade",
    "iso:country":"RS",
    "name:srp_x_preferred":[
        "Dobra Bukva"
    ],
    "wof:name":"Dobra Bukva",
    "wof:placetype":"locality"
},
  "geometry": {"coordinates":[20.6935,43.46815],"type":"Point"}
}