{
  "type": "Feature",
  "properties": {
    "gn:country":"RS",
    "gn:fcode":"PPL",
    "gn:pop":5,
    "iso:country":"RS",
    "qs:name":"Brezova",
    "qs:photos_9r":0,
    "qs:photos_sr":0,
    "qs:pop_sr":"1",
    "wd:wordcount":31,
    "wof:name":"Brezova",
    "wof:placetype":"locality",
    "wof:population":5
},
  "geometry": {"coordinates":[20.48806,43.51417],"type":"Point"}
}