{
  "type": "Feature",
  "properties": {
    "gn:country":"RS",
    "gn:fcode":"PPL",
    "gn:population":5,
    "iso:country":"RS",
    "name:bos_x_preferred":[
        "Brezova"
    ],
    "name:ceb_x_preferred":[
        "Brezova"
    ],
    "name:deu_x_preferred":[
        "Brezova"
    ],
    "name:eng_x_preferred":[
        "Brezova"
    ],
    "name:fra_x_preferred":[
        "Brezova"
    ],
    "name:hrv_x_preferred":[
        "Brezova"
    ],
    "name:hun_x_preferred":[
        "Brezova"
    ],
    "name:nld_x_preferred":[
        "Brezova"
    ],
    "name:por_x_preferred":[
        "Brezova"
    ],
    "name:slv_x_preferred":[
        "Brezova"
    ],
    "name:srp_x_preferred":[
        "\u0411\u0440\u0435\u0437\u043e\u0432\u0430"
    ],
    "name:swe_x_preferred":[
        "Brezova"
    ],
    "qs:name":"Brezova",
    "qs:photos_9r":0,
    "qs:photos_sr":0,
    "qs:pop_sr":"1",
    "wd:wordcount":31,
    "wof:name":"Brezova",
    "wof:placetype":"locality",
    "wof:population":5
},
  "geometry": {"coordinates":[20.48806,43.51417],"type":"Point"}
}