{
  "type": "Feature",
  "properties": {
    "gn:admin1_code":"SE",
    "gn:admin2_code":"11",
    "gn:asciiname":"Oreovica",
    "gn:country_code":"RS",
    "gn:dem":92,
    "gn:feature_class":"P",
    "gn:feature_code":"PPL",
    "gn:name":"Oreovica",
    "gn:population":0,
    "gn:timezone":"Europe/Belgrade",
    "iso:country":"RS",
    "name:ceb_x_preferred":[
        "Oreovica"
    ],
    "name:fra_x_preferred":[
        "Oreovica"
    ],
    "name:msa_x_preferred":[
        "Oreovica"
    ],
    "name:por_x_preferred":[
        "Oreovica"
    ],
    "name:slv_x_preferred":[
        "Oreovica"
    ],
    "name:srp_x_preferred":[
        "Oreovica"
    ],
    "name:srp_x_variant":[
        "\u041e\u0440\u0435\u043e\u0432\u0438\u0446\u0430"
    ],
    "wof:name":"Oreovica",
    "wof:placetype":"locality"
},
  "geometry": {"coordinates":[21.20778,44.42694],"type":"Point"}
}