{
  "type": "Feature",
  "properties": {
    "gn:admin1_code":"SE",
    "gn:admin2_code":"11",
    "gn:asciiname":"Sljivovac",
    "gn:country_code":"RS",
    "gn:dem":185,
    "gn:feature_class":"P",
    "gn:feature_code":"PPL",
    "gn:name":"\u0160ljivovac",
    "gn:population":0,
    "gn:timezone":"Europe/Belgrade",
    "iso:country":"RS",
    "name:srp_x_preferred":[
        "\u0160ljivovac"
    ],
    "name:und_x_variant":[
        "\u0160livovac"
    ],
    "wof:name":"Sljivovac",
    "wof:placetype":"locality"
},
  "geometry": {"coordinates":[21.2234,44.54065],"type":"Point"}
}