{
  "type": "Feature",
  "properties": {
    "gn:admin1_code":"SE",
    "gn:admin2_code":"8",
    "gn:asciiname":"Budimlija",
    "gn:country_code":"RS",
    "gn:dem":318,
    "gn:feature_class":"P",
    "gn:feature_code":"PPL",
    "gn:name":"Budimlija",
    "gn:population":0,
    "gn:timezone":"Europe/Belgrade",
    "iso:country":"RS",
    "name:srp_x_preferred":[
        "Budimlija"
    ],
    "wof:name":"Budimlija",
    "wof:placetype":"locality"
},
  "geometry": {"coordinates":[19.22076,44.49028],"type":"Point"}
}