{
  "type": "Feature",
  "properties": {
    "gn:admin1_code":"SE",
    "gn:admin2_code":"16",
    "gn:asciiname":"Cikote",
    "gn:country_code":"RS",
    "gn:dem":584,
    "gn:feature_class":"P",
    "gn:feature_code":"PPL",
    "gn:name":"Cikote",
    "gn:population":0,
    "gn:timezone":"Europe/Belgrade",
    "iso:country":"RS",
    "name:bos_x_preferred":[
        "Cikote"
    ],
    "name:fra_x_preferred":[
        "Cikote"
    ],
    "name:hrv_x_preferred":[
        "Cikote"
    ],
    "name:nld_x_preferred":[
        "Cikote"
    ],
    "name:slv_x_preferred":[
        "Cikote"
    ],
    "name:srp_x_preferred":[
        "Cikote"
    ],
    "name:srp_x_variant":[
        "\u0426\u0438\u043a\u043e\u0442\u0435"
    ],
    "name:und_x_variant":[
        "Cikoti"
    ],
    "wof:name":"Cikote",
    "wof:placetype":"locality"
},
  "geometry": {"coordinates":[19.8549,44.00762],"type":"Point"}
}