{
  "type": "Feature",
  "properties": {
    "gn:admin1_code":"SE",
    "gn:admin2_code":"9",
    "gn:asciiname":"Marjanovici",
    "gn:country_code":"RS",
    "gn:dem":597,
    "gn:feature_class":"P",
    "gn:feature_code":"PPL",
    "gn:name":"Marjanovi\u0107i",
    "gn:population":0,
    "gn:timezone":"Europe/Belgrade",
    "iso:country":"RS",
    "name:srp_x_preferred":[
        "Marjanovi\u0107i"
    ],
    "wof:name":"Marjanovici",
    "wof:placetype":"locality"
},
  "geometry": {"coordinates":[19.61194,44.26611],"type":"Point"}
}