{
  "type": "Feature",
  "properties": {
    "gn:admin1_code":"SE",
    "gn:admin2_code":"17",
    "gn:asciiname":"Bedina Varos",
    "gn:country_code":"RS",
    "gn:dem":622,
    "gn:feature_class":"P",
    "gn:feature_code":"PPL",
    "gn:name":"Bedina Varo\u0161",
    "gn:population":0,
    "gn:timezone":"Europe/Belgrade",
    "iso:country":"RS",
    "name:ceb_x_preferred":[
        "Bedina Varo\u0161"
    ],
    "name:fra_x_preferred":[
        "Bedina Varo\u0161"
    ],
    "name:msa_x_preferred":[
        "Bedina Varo\u0161"
    ],
    "name:nld_x_preferred":[
        "Bedina Varo\u0161"
    ],
    "name:por_x_preferred":[
        "Bedina Varo\u0161"
    ],
    "name:slv_x_preferred":[
        "Bedina Varo\u0161"
    ],
    "name:srp_x_preferred":[
        "Bedina Varo\u0161"
    ],
    "name:srp_x_variant":[
        "\u0411\u0435\u0434\u0438\u043d\u0430 \u0412\u0430\u0440\u043e\u0448"
    ],
    "wof:name":"Bedina Varos",
    "wof:placetype":"locality"
},
  "geometry": {"coordinates":[20.22949,43.57268],"type":"Point"}
}