{
  "type": "Feature",
  "properties": {
    "gn:admin1_code":"SE",
    "gn:admin2_code":"17",
    "gn:asciiname":"Bedina Varos",
    "gn:country_code":"RS",
    "gn:dem":622,
    "gn:feature_class":"P",
    "gn:feature_code":"PPL",
    "gn:name":"Bedina Varo\u0161",
    "gn:population":0,
    "gn:timezone":"Europe/Belgrade",
    "iso:country":"RS",
    "name:srp_x_preferred":[
        "Bedina Varo\u0161"
    ],
    "wof:name":"Bedina Varos",
    "wof:placetype":"locality"
},
  "geometry": {"coordinates":[20.22949,43.57268],"type":"Point"}
}