{
  "type": "Feature",
  "properties": {
    "gn:admin1_code":"SE",
    "gn:admin2_code":"8",
    "gn:asciiname":"Kostajnik",
    "gn:country_code":"RS",
    "gn:dem":534,
    "gn:feature_class":"P",
    "gn:feature_code":"PPLL",
    "gn:name":"Kostajnik",
    "gn:population":0,
    "gn:timezone":"Europe/Belgrade",
    "iso:country":"RS",
    "name:fra_x_preferred":[
        "Kostajnik"
    ],
    "name:msa_x_preferred":[
        "Kostajnik"
    ],
    "name:nld_x_preferred":[
        "Kostajnik"
    ],
    "name:por_x_preferred":[
        "Kostajnik"
    ],
    "name:slv_x_preferred":[
        "Kostajnik"
    ],
    "name:srp_x_preferred":[
        "Kostajnik"
    ],
    "name:srp_x_variant":[
        "\u041a\u043e\u0441\u0442\u0430\u0458\u043d\u0438\u043a"
    ],
    "wof:name":"Kostajnik",
    "wof:placetype":"locality"
},
  "geometry": {"coordinates":[19.29942,44.43257],"type":"Point"}
}