{
  "type": "Feature",
  "properties": {
    "gn:admin1_code":"SE",
    "gn:admin2_code":"20",
    "gn:asciiname":"Stupnica",
    "gn:country_code":"RS",
    "gn:dem":661,
    "gn:feature_class":"P",
    "gn:feature_code":"PPLL",
    "gn:name":"Stupnica",
    "gn:population":0,
    "gn:timezone":"Europe/Belgrade",
    "iso:country":"RS",
    "name:srp_x_preferred":[
        "Stupnica"
    ],
    "wof:name":"Stupnica",
    "wof:placetype":"locality"
},
  "geometry": {"coordinates":[22.12443,43.08428],"type":"Point"}
}