{
  "type": "Feature",
  "properties": {
    "gn:admin1_code":"SE",
    "gn:admin2_code":"17",
    "gn:asciiname":"Donje Rzinje",
    "gn:country_code":"RS",
    "gn:dem":819,
    "gn:feature_class":"P",
    "gn:feature_code":"PPL",
    "gn:name":"Donje Rzinje",
    "gn:population":0,
    "gn:timezone":"Europe/Belgrade",
    "iso:country":"RS",
    "name:srp_x_preferred":[
        "Donje Rzinje"
    ],
    "wof:name":"Donje Rzinje",
    "wof:placetype":"locality"
},
  "geometry": {"coordinates":[20.30413,43.57456],"type":"Point"}
}