{
  "type": "Feature",
  "properties": {
    "gn:admin1_code":"SE",
    "gn:admin2_code":"24",
    "gn:asciiname":"Lazarovci",
    "gn:country_code":"RS",
    "gn:dem":1349,
    "gn:feature_class":"P",
    "gn:feature_code":"PPL",
    "gn:name":"Lazarovci",
    "gn:population":0,
    "gn:timezone":"Europe/Belgrade",
    "iso:country":"RS",
    "wof:name":"Lazarovci",
    "wof:placetype":"locality"
},
  "geometry": {"coordinates":[22.36034,42.40766],"type":"Point"}
}