{
  "type": "Feature",
  "properties": {
    "gn:admin1_code":"SE",
    "gn:admin2_code":"16",
    "gn:asciiname":"Milakovici",
    "gn:country_code":"RS",
    "gn:dem":592,
    "gn:feature_class":"P",
    "gn:feature_code":"PPL",
    "gn:name":"Milakovi\u0107i",
    "gn:population":0,
    "gn:timezone":"Europe/Belgrade",
    "iso:country":"RS",
    "name:srp_x_preferred":[
        "Milakovi\u0107i"
    ],
    "wof:name":"Milakovici",
    "wof:placetype":"locality"
},
  "geometry": {"coordinates":[19.98861,43.99361],"type":"Point"}
}