{
  "type": "Feature",
  "properties": {
    "gn:admin1_code":"SE",
    "gn:admin2_code":"13",
    "gn:asciiname":"Velika Krusevica",
    "gn:country_code":"RS",
    "gn:dem":283,
    "gn:feature_class":"P",
    "gn:feature_code":"PPL",
    "gn:name":"Velika Kru\u0161evica",
    "gn:population":0,
    "gn:timezone":"Europe/Belgrade",
    "iso:country":"RS",
    "name:srp_x_preferred":[
        "Velika Kru\u0161evica"
    ],
    "wof:name":"Velika Krusevica",
    "wof:placetype":"locality"
},
  "geometry": {"coordinates":[21.07963,43.84773],"type":"Point"}
}