{
  "type": "Feature",
  "properties": {
    "gn:admin1_code":"SE",
    "gn:admin2_code":"20",
    "gn:asciiname":"Tijovac",
    "gn:country_code":"RS",
    "gn:dem":648,
    "gn:feature_class":"P",
    "gn:feature_code":"PPL",
    "gn:name":"Tijovac",
    "gn:population":0,
    "gn:timezone":"Europe/Belgrade",
    "iso:country":"RS",
    "name:fra_x_preferred":[
        "Tijovac"
    ],
    "name:slv_x_preferred":[
        "Tijovac"
    ],
    "name:srp_x_preferred":[
        "Tijovac"
    ],
    "name:srp_x_variant":[
        "\u0422\u0438\u0458\u043e\u0432\u0430\u0446"
    ],
    "wof:name":"Tijovac",
    "wof:placetype":"locality"
},
  "geometry": {"coordinates":[22.22872000000001,43.4434],"type":"Point"}
}