{
  "type": "Feature",
  "properties": {
    "gn:admin1_code":"SE",
    "gn:admin2_code":"24",
    "gn:asciiname":"Sopovi",
    "gn:country_code":"RS",
    "gn:dem":585,
    "gn:feature_class":"P",
    "gn:feature_code":"PPL",
    "gn:name":"\u0160opovi",
    "gn:population":0,
    "gn:timezone":"Europe/Belgrade",
    "iso:country":"RS",
    "wof:name":"Sopovi",
    "wof:placetype":"locality"
},
  "geometry": {"coordinates":[21.98102,42.5106],"type":"Point"}
}