{
  "type": "Feature",
  "properties": {
    "gn:country":"RS",
    "gn:fcode":"PPL",
    "gn:population":1658,
    "iso:country":"RS",
    "name:ceb_x_preferred":[
        "Samo\u0161"
    ],
    "name:eng_x_preferred":[
        "Samo\u0161"
    ],
    "name:epo_x_preferred":[
        "Samo\u015d"
    ],
    "name:fra_x_preferred":[
        "Samo\u0161"
    ],
    "name:hun_x_preferred":[
        "Sz\u00e1mos"
    ],
    "name:msa_x_preferred":[
        "Samo\u0161"
    ],
    "name:nld_x_preferred":[
        "Samo\u0161"
    ],
    "name:ron_x_preferred":[
        "Samo\u0161"
    ],
    "name:rus_x_preferred":[
        "\u0421\u0430\u043c\u043e\u0448"
    ],
    "name:slv_x_preferred":[
        "Samo\u0161"
    ],
    "name:srp_x_preferred":[
        "Samo\u0161"
    ],
    "name:srp_x_variant":[
        "\u0421\u0430\u043c\u043e\u0448"
    ],
    "qs:name":"Samo\u0161",
    "qs:photos_9r":0,
    "qs:photos_sr":0,
    "qs:pop_sr":"3",
    "wd:wordcount":102,
    "wof:name":"Samo\u0161",
    "wof:placetype":"locality",
    "wof:population":1658
},
  "geometry": {"coordinates":[20.77392,45.20255],"type":"Point"}
}