{
  "type": "Feature",
  "properties": {
    "gn:admin1_code":"SE",
    "gn:admin2_code":"16",
    "gn:asciiname":"Mala Drenova",
    "gn:country_code":"RS",
    "gn:dem":560,
    "gn:feature_class":"P",
    "gn:feature_code":"PPL",
    "gn:name":"Mala Drenova",
    "gn:population":0,
    "gn:timezone":"Europe/Belgrade",
    "iso:country":"RS",
    "name:ceb_x_preferred":[
        "Mala Drenova"
    ],
    "name:ell_x_preferred":[
        "\u039c\u03ac\u03bb\u03b1 \u039d\u03c4\u03c1\u03ad\u03bd\u03bf\u03b2\u03b1"
    ],
    "name:fra_x_preferred":[
        "Mala Drenova"
    ],
    "name:msa_x_preferred":[
        "Mala Drenova"
    ],
    "name:por_x_preferred":[
        "Mala Drenova"
    ],
    "name:slv_x_preferred":[
        "Mala Drenova"
    ],
    "name:srp_x_preferred":[
        "\u041c\u0430\u043b\u0430 \u0414\u0440\u0435\u043d\u043e\u0432\u0430"
    ],
    "wof:name":"Mala Drenova",
    "wof:placetype":"locality"
},
  "geometry": {"coordinates":[19.64917,43.39528],"type":"Point"}
}