{
  "type": "Feature",
  "properties": {
    "gn:admin1_code":"SE",
    "gn:admin2_code":"19",
    "gn:asciiname":"Konjuh",
    "gn:country_code":"RS",
    "gn:dem":192,
    "gn:feature_class":"P",
    "gn:feature_code":"PPL",
    "gn:name":"Konjuh",
    "gn:population":0,
    "gn:timezone":"Europe/Belgrade",
    "iso:country":"RS",
    "name:bos_x_preferred":[
        "Konjuh"
    ],
    "name:ceb_x_preferred":[
        "Konjuh"
    ],
    "name:deu_x_preferred":[
        "Konjuh"
    ],
    "name:fra_x_preferred":[
        "Konjuh"
    ],
    "name:hrv_x_preferred":[
        "Konjuh"
    ],
    "name:nld_x_preferred":[
        "Konjuh"
    ],
    "name:srp_x_preferred":[
        "\u041a\u043e\u045a\u0443\u0445"
    ],
    "name:swe_x_preferred":[
        "Konjuh"
    ],
    "wof:name":"Konjuh",
    "wof:placetype":"locality"
},
  "geometry": {"coordinates":[21.1814,43.64333],"type":"Point"}
}