{
  "type": "Feature",
  "properties": {
    "gn:admin1_code":"SE",
    "gn:admin2_code":"24",
    "gn:asciiname":"Curcijska Mahala",
    "gn:country_code":"RS",
    "gn:dem":975,
    "gn:feature_class":"P",
    "gn:feature_code":"PPL",
    "gn:name":"\u0106ur\u010dijska Mahala",
    "gn:population":0,
    "gn:timezone":"Europe/Belgrade",
    "iso:country":"RS",
    "wof:name":"Curcijska Mahala",
    "wof:placetype":"locality"
},
  "geometry": {"coordinates":[22.45977,42.41516],"type":"Point"}
}