{
  "type": "Feature",
  "properties": {
    "gn:admin1_code":"SE",
    "gn:admin2_code":"18",
    "gn:asciiname":"Cvetke",
    "gn:country_code":"RS",
    "gn:dem":263,
    "gn:feature_class":"P",
    "gn:feature_code":"PPL",
    "gn:name":"Cvetke",
    "gn:population":0,
    "gn:timezone":"Europe/Belgrade",
    "iso:country":"RS",
    "wof:name":"Cvetke",
    "wof:placetype":"locality"
},
  "geometry": {"coordinates":[20.62675,43.81303],"type":"Point"}
}