{
  "type": "Feature",
  "properties": {
    "gn:admin1_code":"SE",
    "gn:admin2_code":"18",
    "gn:asciiname":"Cvetke",
    "gn:country_code":"RS",
    "gn:dem":263,
    "gn:feature_class":"P",
    "gn:feature_code":"PPL",
    "gn:name":"Cvetke",
    "gn:population":0,
    "gn:timezone":"Europe/Belgrade",
    "iso:country":"RS",
    "name:ceb_x_preferred":[
        "Cvetke"
    ],
    "name:fra_x_preferred":[
        "Cvetke"
    ],
    "name:hun_x_preferred":[
        "Cvetke"
    ],
    "name:msa_x_preferred":[
        "Cvetke"
    ],
    "name:nld_x_preferred":[
        "Cvetke"
    ],
    "name:por_x_preferred":[
        "Cvetke"
    ],
    "name:slv_x_preferred":[
        "Cvetke"
    ],
    "name:srp_x_preferred":[
        "\u0426\u0432\u0435\u0442\u043a\u0435"
    ],
    "wof:name":"Cvetke",
    "wof:placetype":"locality"
},
  "geometry": {"coordinates":[20.62675,43.81303],"type":"Point"}
}