{
  "type": "Feature",
  "properties": {
    "gn:admin1_code":"SE",
    "gn:admin2_code":"22",
    "gn:asciiname":"Izvor",
    "gn:country_code":"RS",
    "gn:dem":393,
    "gn:feature_class":"P",
    "gn:feature_code":"PPL",
    "gn:name":"Izvor",
    "gn:population":0,
    "gn:timezone":"Europe/Belgrade",
    "iso:country":"RS",
    "name:srp_x_preferred":[
        "Izvor"
    ],
    "wof:name":"Izvor",
    "wof:placetype":"locality"
},
  "geometry": {"coordinates":[22.63502,43.14762],"type":"Point"}
}