{
  "type": "Feature",
  "properties": {
    "gn:admin1_code":"SE",
    "gn:admin2_code":"0",
    "gn:asciiname":"Mala Polja",
    "gn:country_code":"RS",
    "gn:dem":285,
    "gn:feature_class":"P",
    "gn:feature_code":"PPL",
    "gn:name":"Mala Polja",
    "gn:population":0,
    "gn:timezone":"Europe/Belgrade",
    "iso:country":"RS",
    "wof:name":"Mala Polja",
    "wof:placetype":"locality"
},
  "geometry": {"coordinates":[20.51333,44.57222],"type":"Point"}
}