{
  "type": "Feature",
  "properties": {
    "gn:admin1_code":"SE",
    "gn:admin2_code":"13",
    "gn:asciiname":"Supska",
    "gn:country_code":"RS",
    "gn:dem":123,
    "gn:feature_class":"P",
    "gn:feature_code":"PPL",
    "gn:name":"Supska",
    "gn:population":0,
    "gn:timezone":"Europe/Belgrade",
    "iso:country":"RS",
    "name:srp_x_preferred":[
        "Supska"
    ],
    "wof:name":"Supska",
    "wof:placetype":"locality"
},
  "geometry": {"coordinates":[21.36783,43.97483],"type":"Point"}
}