{
  "type": "Feature",
  "properties": {
    "gn:admin1_code":"SE",
    "gn:admin2_code":"13",
    "gn:asciiname":"Supska",
    "gn:country_code":"RS",
    "gn:dem":123,
    "gn:feature_class":"P",
    "gn:feature_code":"PPL",
    "gn:name":"Supska",
    "gn:population":0,
    "gn:timezone":"Europe/Belgrade",
    "iso:country":"RS",
    "name:ceb_x_preferred":[
        "Supska"
    ],
    "name:deu_x_preferred":[
        "Supska"
    ],
    "name:fas_x_preferred":[
        "\u0633\u0648\u067e\u0633\u06a9\u0627"
    ],
    "name:fra_x_preferred":[
        "Supska"
    ],
    "name:msa_x_preferred":[
        "Supska"
    ],
    "name:por_x_preferred":[
        "Supska"
    ],
    "name:slv_x_preferred":[
        "Supska"
    ],
    "name:srp_x_preferred":[
        "Supska"
    ],
    "name:srp_x_variant":[
        "\u0421\u0443\u043f\u0441\u043a\u0430"
    ],
    "wof:name":"Supska",
    "wof:placetype":"locality"
},
  "geometry": {"coordinates":[21.36783,43.97483],"type":"Point"}
}