{
  "type": "Feature",
  "properties": {
    "gn:country":"RS",
    "gn:fcode":"PPL",
    "gn:population":4,
    "iso:country":"RS",
    "name:srp_x_preferred":[
        "\u010citluk"
    ],
    "qs:name":"\u010citluk",
    "qs:photos_9r":0,
    "qs:photos_sr":0,
    "qs:pop_sr":"1",
    "wof:name":"\u010citluk",
    "wof:placetype":"locality",
    "wof:population":4
},
  "geometry": {"coordinates":[21.27194,43.59404],"type":"Point"}
}