{
  "type": "Feature",
  "properties": {
    "gn:admin1_code":"SE",
    "gn:admin2_code":"12",
    "gn:asciiname":"Ravni Gaj",
    "gn:country_code":"RS",
    "gn:dem":281,
    "gn:feature_class":"P",
    "gn:feature_code":"PPL",
    "gn:name":"Ravni Gaj",
    "gn:population":0,
    "gn:timezone":"Europe/Belgrade",
    "iso:country":"RS",
    "wof:name":"Ravni Gaj",
    "wof:placetype":"locality"
},
  "geometry": {"coordinates":[20.77861,43.93472],"type":"Point"}
}