{
  "type": "Feature",
  "properties": {
    "gn:admin1_code":"SE",
    "gn:admin2_code":"18",
    "gn:asciiname":"Gluhavica",
    "gn:country_code":"RS",
    "gn:dem":885,
    "gn:feature_class":"P",
    "gn:feature_code":"PPL",
    "gn:name":"Gluhavica",
    "gn:population":0,
    "gn:timezone":"Europe/Belgrade",
    "iso:country":"RS",
    "name:bul_x_preferred":[
        "\u0413\u043b\u0443\u0445\u0430\u0432\u0438\u0446\u0430"
    ],
    "name:ceb_x_preferred":[
        "Gluhavica"
    ],
    "name:fra_x_preferred":[
        "Gluhavica"
    ],
    "name:hun_x_preferred":[
        "Gluhavica"
    ],
    "name:msa_x_preferred":[
        "Gluhavica"
    ],
    "name:nld_x_preferred":[
        "Gluhavica"
    ],
    "name:por_x_preferred":[
        "Gluhavica"
    ],
    "name:slv_x_preferred":[
        "Gluhavica"
    ],
    "name:srp_x_preferred":[
        "Gluhavica"
    ],
    "name:srp_x_variant":[
        "\u0413\u043b\u0443\u0445\u0430\u0432\u0438\u0446\u0430"
    ],
    "name:und_x_variant":[
        "Gluavica"
    ],
    "wof:name":"Gluhavica",
    "wof:placetype":"locality"
},
  "geometry": {"coordinates":[20.38691,43.06045],"type":"Point"}
}