{
  "type": "Feature",
  "properties": {
    "gn:admin1_code":"SE",
    "gn:admin2_code":"18",
    "gn:asciiname":"Gluhavica",
    "gn:country_code":"RS",
    "gn:dem":885,
    "gn:feature_class":"P",
    "gn:feature_code":"PPL",
    "gn:name":"Gluhavica",
    "gn:population":0,
    "gn:timezone":"Europe/Belgrade",
    "iso:country":"RS",
    "name:srp_x_preferred":[
        "Gluhavica"
    ],
    "name:und_x_variant":[
        "Gluavica"
    ],
    "wof:name":"Gluhavica",
    "wof:placetype":"locality"
},
  "geometry": {"coordinates":[20.38691,43.06045],"type":"Point"}
}