{
  "type": "Feature",
  "properties": {
    "gn:admin1_code":"SE",
    "gn:admin2_code":"16",
    "gn:asciiname":"Iglici",
    "gn:country_code":"RS",
    "gn:dem":929,
    "gn:feature_class":"P",
    "gn:feature_code":"PPL",
    "gn:name":"Igli\u0107i",
    "gn:population":0,
    "gn:timezone":"Europe/Belgrade",
    "iso:country":"RS",
    "name:srp_x_preferred":[
        "Igli\u0107i"
    ],
    "wof:name":"Iglici",
    "wof:placetype":"locality"
},
  "geometry": {"coordinates":[19.58194,43.89833],"type":"Point"}
}