{
  "type": "Feature",
  "properties": {
    "gn:admin1_code":"SE",
    "gn:admin2_code":"13",
    "gn:asciiname":"Donja Mutnica",
    "gn:country_code":"RS",
    "gn:dem":246,
    "gn:feature_class":"P",
    "gn:feature_code":"PPL",
    "gn:name":"Donja Mutnica",
    "gn:population":0,
    "gn:timezone":"Europe/Belgrade",
    "iso:country":"RS",
    "name:ceb_x_preferred":[
        "Donja Mutnica"
    ],
    "name:fra_x_preferred":[
        "Donja Mutnica"
    ],
    "name:msa_x_preferred":[
        "Donja Mutnica"
    ],
    "name:por_x_preferred":[
        "Donja Mutnica"
    ],
    "name:slv_x_preferred":[
        "Donja Mutnica"
    ],
    "name:srp_x_preferred":[
        "Donja Mutnica"
    ],
    "name:srp_x_variant":[
        "\u0414\u043e\u045a\u0430 \u041c\u0443\u0442\u043d\u0438\u0446\u0430"
    ],
    "wof:name":"Donja Mutnica",
    "wof:placetype":"locality"
},
  "geometry": {"coordinates":[21.56128,43.85174],"type":"Point"}
}