{
  "type": "Feature",
  "properties": {
    "gn:admin1_code":"SE",
    "gn:admin2_code":"8",
    "gn:asciiname":"Milicici",
    "gn:country_code":"RS",
    "gn:dem":871,
    "gn:feature_class":"P",
    "gn:feature_code":"PPL",
    "gn:name":"Mili\u010di\u0107i",
    "gn:population":0,
    "gn:timezone":"Europe/Belgrade",
    "iso:country":"RS",
    "name:srp_x_preferred":[
        "Mili\u010di\u0107i"
    ],
    "wof:name":"Milicici",
    "wof:placetype":"locality"
},
  "geometry": {"coordinates":[19.50691,44.16469],"type":"Point"}
}