{
  "type": "Feature",
  "properties": {
    "gn:admin1_code":"SE",
    "gn:admin2_code":"17",
    "gn:asciiname":"Tisovica",
    "gn:country_code":"RS",
    "gn:dem":1189,
    "gn:feature_class":"P",
    "gn:feature_code":"PPLL",
    "gn:name":"Tisovica",
    "gn:population":0,
    "gn:timezone":"Europe/Belgrade",
    "iso:country":"RS",
    "name:fra_x_preferred":[
        "Tisovica"
    ],
    "name:msa_x_preferred":[
        "Tisovica"
    ],
    "name:nld_x_preferred":[
        "Tisovica"
    ],
    "name:por_x_preferred":[
        "Tisovica"
    ],
    "name:slv_x_preferred":[
        "Tisovica"
    ],
    "name:srp_x_preferred":[
        "Tisovica"
    ],
    "name:srp_x_variant":[
        "\u0422\u0438\u0441\u043e\u0432\u0438\u0446\u0430"
    ],
    "name:und_x_variant":[
        "Gornja Tisovica"
    ],
    "wof:name":"Tisovica",
    "wof:placetype":"locality"
},
  "geometry": {"coordinates":[20.03313,43.46302],"type":"Point"}
}