{
  "type": "Feature",
  "properties": {
    "gn:admin1_code":"SE",
    "gn:admin2_code":"20",
    "gn:asciiname":"Donja Rasovaca",
    "gn:country_code":"RS",
    "gn:dem":267,
    "gn:feature_class":"P",
    "gn:feature_code":"PPL",
    "gn:name":"Donja Rasova\u010da",
    "gn:population":0,
    "gn:timezone":"Europe/Belgrade",
    "iso:country":"RS",
    "name:ceb_x_preferred":[
        "Donja Rasova\u010da"
    ],
    "name:fra_x_preferred":[
        "Donja Rasova\u010da"
    ],
    "name:msa_x_preferred":[
        "Donja Rasova\u010da"
    ],
    "name:por_x_preferred":[
        "Donja Rasova\u010da"
    ],
    "name:slv_x_preferred":[
        "Donja Rasova\u010da"
    ],
    "name:sqi_x_preferred":[
        "Rasova\u00e7a e Poshtme"
    ],
    "name:srp_x_preferred":[
        "Donja Rasova\u010da"
    ],
    "name:srp_x_variant":[
        "\u0414\u043e\u045a\u0430 \u0420\u0430\u0441\u043e\u0432\u0430\u0447\u0430"
    ],
    "wof:name":"Donja Rasovaca",
    "wof:placetype":"locality"
},
  "geometry": {"coordinates":[21.68625,43.23477000000001],"type":"Point"}
}