{
  "type": "Feature",
  "properties": {
    "gn:admin1_code":"VO",
    "gn:admin2_code":"4",
    "gn:asciiname":"Bavaniste",
    "gn:country_code":"RS",
    "gn:dem":81,
    "gn:feature_class":"P",
    "gn:feature_code":"PPL",
    "gn:name":"Bavani\u0161te",
    "gn:population":0,
    "gn:timezone":"Europe/Belgrade",
    "iso:country":"RS",
    "name:srp_x_preferred":[
        "Bavani\u0161te"
    ],
    "name:und_x_variant":[
        "Homokb\u00e1lv\u00e1nyos",
        "Balvanyesti",
        "Balvanjestie",
        "Bawanischte"
    ],
    "wof:name":"Bavaniste",
    "wof:placetype":"locality"
},
  "geometry": {"coordinates":[20.87654,44.81907],"type":"Point"}
}