{
  "type": "Feature",
  "properties": {
    "gn:admin1_code":"VO",
    "gn:admin2_code":"4",
    "gn:asciiname":"Bavaniste",
    "gn:country_code":"RS",
    "gn:dem":81,
    "gn:feature_class":"P",
    "gn:feature_code":"PPL",
    "gn:name":"Bavani\u0161te",
    "gn:population":0,
    "gn:timezone":"Europe/Belgrade",
    "iso:country":"RS",
    "name:ara_x_preferred":[
        "\u0628\u0627\u0641\u0627\u0646\u064a\u0634\u062a\u064a"
    ],
    "name:ceb_x_preferred":[
        "Bavani\u0161te"
    ],
    "name:epo_x_preferred":[
        "Bavani\u015dte"
    ],
    "name:fra_x_preferred":[
        "Bavani\u0161te"
    ],
    "name:hun_x_preferred":[
        "Homokb\u00e1lv\u00e1nyos"
    ],
    "name:msa_x_preferred":[
        "Bavani\u0161te"
    ],
    "name:ron_x_preferred":[
        "Bavani\u0161te"
    ],
    "name:slv_x_preferred":[
        "Bavani\u0161te"
    ],
    "name:srp_x_preferred":[
        "Bavani\u0161te"
    ],
    "name:srp_x_variant":[
        "\u0411\u0430\u0432\u0430\u043d\u0438\u0448\u0442\u0435"
    ],
    "name:und_x_variant":[
        "Balvanyesti",
        "Balvanjestie",
        "Bawanischte"
    ],
    "wof:name":"Bavaniste",
    "wof:placetype":"locality"
},
  "geometry": {"coordinates":[20.87654,44.81907],"type":"Point"}
}