{
  "type": "Feature",
  "properties": {
    "gn:admin1_code":"SE",
    "gn:admin2_code":"0",
    "gn:asciiname":"Padinska Skela",
    "gn:country_code":"RS",
    "gn:dem":68,
    "gn:feature_class":"P",
    "gn:feature_code":"PPL",
    "gn:name":"Padinska Skela",
    "gn:population":0,
    "gn:timezone":"Europe/Belgrade",
    "iso:country":"RS",
    "name:ceb_x_preferred":[
        "Padinska Skela"
    ],
    "name:fra_x_preferred":[
        "Padinska Skela"
    ],
    "name:msa_x_preferred":[
        "Padinska Skela"
    ],
    "name:pol_x_preferred":[
        "Padinska Skela"
    ],
    "name:por_x_preferred":[
        "Padinska Skela"
    ],
    "name:ron_x_preferred":[
        "Padinska Skela"
    ],
    "name:slv_x_preferred":[
        "Padinska Skela"
    ],
    "name:srp_x_preferred":[
        "\u041f\u0430\u0434\u0438\u043d\u0441\u043a\u0430 \u0421\u043a\u0435\u043b\u0430"
    ],
    "wof:name":"Padinska Skela",
    "wof:placetype":"locality"
},
  "geometry": {"coordinates":[20.42549,44.94291],"type":"Point"}
}