{
  "type": "Feature",
  "properties": {
    "gn:admin1_code":"SE",
    "gn:admin2_code":"0",
    "gn:asciiname":"Padinska Skela",
    "gn:country_code":"RS",
    "gn:dem":68,
    "gn:feature_class":"P",
    "gn:feature_code":"PPL",
    "gn:name":"Padinska Skela",
    "gn:population":0,
    "gn:timezone":"Europe/Belgrade",
    "iso:country":"RS",
    "wof:name":"Padinska Skela",
    "wof:placetype":"locality"
},
  "geometry": {"coordinates":[20.42549,44.94291],"type":"Point"}
}