{
  "type": "Feature",
  "properties": {
    "gn:admin1_code":"SE",
    "gn:admin2_code":"24",
    "gn:asciiname":"Nuiska Mahala",
    "gn:country_code":"RS",
    "gn:dem":856,
    "gn:feature_class":"P",
    "gn:feature_code":"PPL",
    "gn:name":"Nuiska Mahala",
    "gn:population":0,
    "gn:timezone":"Europe/Belgrade",
    "iso:country":"RS",
    "wof:name":"Nuiska Mahala",
    "wof:placetype":"locality"
},
  "geometry": {"coordinates":[21.60769,42.30685],"type":"Point"}
}