{
  "type": "Feature",
  "properties": {
    "gn:admin1_code":"SE",
    "gn:admin2_code":"18",
    "gn:asciiname":"Bapsko Polje",
    "gn:country_code":"RS",
    "gn:dem":205,
    "gn:feature_class":"P",
    "gn:feature_code":"PPL",
    "gn:name":"Bapsko Polje",
    "gn:population":0,
    "gn:timezone":"Europe/Belgrade",
    "iso:country":"RS",
    "name:ceb_x_preferred":[
        "Bapsko Polje"
    ],
    "name:fra_x_preferred":[
        "Bapsko Polje"
    ],
    "name:hun_x_preferred":[
        "Bapsko Polje"
    ],
    "name:msa_x_preferred":[
        "Bapsko Polje"
    ],
    "name:nld_x_preferred":[
        "Bapsko Polje"
    ],
    "name:por_x_preferred":[
        "Bapsko Polje"
    ],
    "name:slv_x_preferred":[
        "Bapsko Polje"
    ],
    "name:srp_x_preferred":[
        "Bapsko Polje"
    ],
    "name:srp_x_variant":[
        "\u0411\u0430\u043f\u0441\u043a\u043e \u041f\u043e\u0459\u0435"
    ],
    "wof:name":"Bapsko Polje",
    "wof:placetype":"locality"
},
  "geometry": {"coordinates":[20.55763,43.78817],"type":"Point"}
}