{
  "type": "Feature",
  "properties": {
    "gn:admin1_code":"SE",
    "gn:admin2_code":"18",
    "gn:asciiname":"Bapsko Polje",
    "gn:country_code":"RS",
    "gn:dem":205,
    "gn:feature_class":"P",
    "gn:feature_code":"PPL",
    "gn:name":"Bapsko Polje",
    "gn:population":0,
    "gn:timezone":"Europe/Belgrade",
    "iso:country":"RS",
    "name:srp_x_preferred":[
        "Bapsko Polje"
    ],
    "wof:name":"Bapsko Polje",
    "wof:placetype":"locality"
},
  "geometry": {"coordinates":[20.55763,43.78817],"type":"Point"}
}