{
  "type": "Feature",
  "properties": {
    "iso:country":"RS",
    "name:eng_x_preferred":[
        "Dunavac"
    ],
    "name:srp_cyr_x_preferred":[
        "\u0414\u0443\u043d\u0430\u0432\u0430\u0446"
    ],
    "wof:name":"Dunavac",
    "wof:placetype":"neighbourhood"
},
  "geometry": {"coordinates":[20.38525906572657,45.06873002551337],"type":"Point"}
}