{
  "type": "Feature",
  "properties": {
    "gn:admin1_code":"SE",
    "gn:admin2_code":"17",
    "gn:asciiname":"Macani",
    "gn:country_code":"RS",
    "gn:dem":478,
    "gn:feature_class":"P",
    "gn:feature_code":"PPL",
    "gn:name":"Ma\u010dani",
    "gn:population":0,
    "gn:timezone":"Europe/Belgrade",
    "iso:country":"RS",
    "name:und_x_variant":[
        "Gora\u010di\u0107i",
        "Gora\u010di\u0107",
        "Ma\u010dani"
    ],
    "wof:name":"Macani",
    "wof:placetype":"locality"
},
  "geometry": {"coordinates":[20.30965,43.7995],"type":"Point"}
}