{
  "type": "Feature",
  "properties": {
    "gn:admin1_code":"SE",
    "gn:admin2_code":"24",
    "gn:asciiname":"Sarkovci",
    "gn:country_code":"RS",
    "gn:dem":1205,
    "gn:feature_class":"P",
    "gn:feature_code":"PPL",
    "gn:name":"\u0160arkovci",
    "gn:population":0,
    "gn:timezone":"Europe/Belgrade",
    "iso:country":"RS",
    "wof:name":"Sarkovci",
    "wof:placetype":"locality"
},
  "geometry": {"coordinates":[22.15306,42.42917],"type":"Point"}
}