{
  "type": "Feature",
  "properties": {
    "gn:admin1_code":"SE",
    "gn:admin2_code":"24",
    "gn:asciiname":"Marjanica",
    "gn:country_code":"RS",
    "gn:dem":1423,
    "gn:feature_class":"P",
    "gn:feature_code":"PPL",
    "gn:name":"Marjanica",
    "gn:population":0,
    "gn:timezone":"Europe/Belgrade",
    "iso:country":"RS",
    "wof:name":"Marjanica",
    "wof:placetype":"locality"
},
  "geometry": {"coordinates":[22.34425,42.35688],"type":"Point"}
}