{
  "type": "Feature",
  "properties": {
    "gn:admin1_code":"SE",
    "gn:admin2_code":"19",
    "gn:asciiname":"Milovancevici",
    "gn:country_code":"RS",
    "gn:dem":949,
    "gn:feature_class":"P",
    "gn:feature_code":"PPL",
    "gn:name":"Milovan\u010devi\u0107i",
    "gn:population":0,
    "gn:timezone":"Europe/Belgrade",
    "iso:country":"RS",
    "name:srp_x_preferred":[
        "Milovan\u010devi\u0107i"
    ],
    "wof:name":"Milovancevici",
    "wof:placetype":"locality"
},
  "geometry": {"coordinates":[20.91073,43.4081],"type":"Point"}
}