{
  "type": "Feature",
  "properties": {
    "gn:admin1_code":"SE",
    "gn:admin2_code":"24",
    "gn:asciiname":"Konopljarci",
    "gn:country_code":"RS",
    "gn:dem":607,
    "gn:feature_class":"P",
    "gn:feature_code":"PPL",
    "gn:name":"Konopljarci",
    "gn:population":0,
    "gn:timezone":"Europe/Belgrade",
    "iso:country":"RS",
    "wof:name":"Konopljarci",
    "wof:placetype":"locality"
},
  "geometry": {"coordinates":[21.96212,42.60666],"type":"Point"}
}