{
  "type": "Feature",
  "properties": {
    "gn:admin1_code":"SE",
    "gn:admin2_code":"24",
    "gn:asciiname":"Doganci",
    "gn:country_code":"RS",
    "gn:dem":493,
    "gn:feature_class":"P",
    "gn:feature_code":"PPL",
    "gn:name":"\u00d0oganci",
    "gn:population":0,
    "gn:timezone":"Europe/Belgrade",
    "iso:country":"RS",
    "name:und_x_variant":[
        "Djoganci"
    ],
    "wof:name":"Doganci",
    "wof:placetype":"locality"
},
  "geometry": {"coordinates":[21.88694,42.44194],"type":"Point"}
}