{
  "type": "Feature",
  "properties": {
    "gn:admin1_code":"SE",
    "gn:admin2_code":"16",
    "gn:asciiname":"Orasac",
    "gn:country_code":"RS",
    "gn:dem":788,
    "gn:feature_class":"P",
    "gn:feature_code":"PPLL",
    "gn:name":"Ora\u0161ac",
    "gn:population":0,
    "gn:timezone":"Europe/Belgrade",
    "iso:country":"RS",
    "name:srp_x_preferred":[
        "Ora\u0161ac"
    ],
    "wof:name":"Orasac",
    "wof:placetype":"locality"
},
  "geometry": {"coordinates":[19.61583,43.53835],"type":"Point"}
}