{
  "type": "Feature",
  "properties": {
    "gn:admin1_code":"SE",
    "gn:admin2_code":"18",
    "gn:asciiname":"Kucevici",
    "gn:country_code":"RS",
    "gn:dem":1176,
    "gn:feature_class":"P",
    "gn:feature_code":"PPL",
    "gn:name":"Ku\u010devi\u0107i",
    "gn:population":0,
    "gn:timezone":"Europe/Belgrade",
    "iso:country":"RS",
    "name:srp_x_preferred":[
        "Ku\u010devi\u0107i"
    ],
    "wof:name":"Kucevici",
    "wof:placetype":"locality"
},
  "geometry": {"coordinates":[20.445,43.30111],"type":"Point"}
}