{
  "type": "Feature",
  "properties": {
    "gn:admin1_code":"SE",
    "gn:admin2_code":"18",
    "gn:asciiname":"Istocni Mojstir",
    "gn:country_code":"RS",
    "gn:dem":1126,
    "gn:feature_class":"P",
    "gn:feature_code":"PPL",
    "gn:name":"Isto\u010dni Mojstir",
    "gn:population":0,
    "gn:timezone":"Europe/Belgrade",
    "iso:country":"RS",
    "name:srp_x_preferred":[
        "Isto\u010dni Mojstir"
    ],
    "name:und_x_variant":[
        "Mojstir Hristijan",
        "Mojstir-Isto\u010dni"
    ],
    "wof:name":"Istocni Mojstir",
    "wof:placetype":"locality"
},
  "geometry": {"coordinates":[20.44213,42.91515],"type":"Point"}
}