{
  "type": "Feature",
  "properties": {
    "gn:admin1_code":"SE",
    "gn:admin2_code":"18",
    "gn:asciiname":"Istocni Mojstir",
    "gn:country_code":"RS",
    "gn:dem":1126,
    "gn:feature_class":"P",
    "gn:feature_code":"PPL",
    "gn:name":"Isto\u010dni Mojstir",
    "gn:population":0,
    "gn:timezone":"Europe/Belgrade",
    "iso:country":"RS",
    "name:ceb_x_preferred":[
        "Isto\u010dni Mojstir"
    ],
    "name:fra_x_preferred":[
        "Isto\u010dni Mojstir"
    ],
    "name:hun_x_preferred":[
        "Isto\u010dni Mojstir"
    ],
    "name:msa_x_preferred":[
        "Isto\u010dni Mojstir"
    ],
    "name:nld_x_preferred":[
        "Isto\u010dni Mojstir"
    ],
    "name:por_x_preferred":[
        "Isto\u010dni Mojstir"
    ],
    "name:slv_x_preferred":[
        "Isto\u010dni Mojstir"
    ],
    "name:srp_x_preferred":[
        "Isto\u010dni Mojstir"
    ],
    "name:srp_x_variant":[
        "\u0418\u0441\u0442\u043e\u0447\u043d\u0438 \u041c\u043e\u0458\u0441\u0442\u0438\u0440"
    ],
    "name:und_x_variant":[
        "Mojstir Hristijan",
        "Mojstir-Isto\u010dni"
    ],
    "wof:name":"Istocni Mojstir",
    "wof:placetype":"locality"
},
  "geometry": {"coordinates":[20.44213,42.91515],"type":"Point"}
}