{
  "type": "Feature",
  "properties": {
    "gn:admin1_code":"SE",
    "gn:admin2_code":"11",
    "gn:asciiname":"Veliko Selo",
    "gn:country_code":"RS",
    "gn:dem":97,
    "gn:feature_class":"P",
    "gn:feature_code":"PPL",
    "gn:name":"Veliko Selo",
    "gn:population":0,
    "gn:timezone":"Europe/Belgrade",
    "iso:country":"RS",
    "name:fas_x_preferred":[
        "\u0648\u0644\u06cc\u06a9\u0648 \u0633\u0644\u0648"
    ],
    "name:fra_x_preferred":[
        "Veliko Selo"
    ],
    "name:msa_x_preferred":[
        "Veliko Selo"
    ],
    "name:por_x_preferred":[
        "Veliko Selo"
    ],
    "name:slv_x_preferred":[
        "Veliko Selo"
    ],
    "name:srp_x_preferred":[
        "Veliko Selo"
    ],
    "name:srp_x_variant":[
        "\u0412\u0435\u043b\u0438\u043a\u043e \u0421\u0435\u043b\u043e"
    ],
    "wof:name":"Veliko Selo",
    "wof:placetype":"locality"
},
  "geometry": {"coordinates":[21.29407,44.49192],"type":"Point"}
}