{
  "type": "Feature",
  "properties": {
    "gn:admin1_code":"SE",
    "gn:admin2_code":"11",
    "gn:asciiname":"Veliko Selo",
    "gn:country_code":"RS",
    "gn:dem":97,
    "gn:feature_class":"P",
    "gn:feature_code":"PPL",
    "gn:name":"Veliko Selo",
    "gn:population":0,
    "gn:timezone":"Europe/Belgrade",
    "iso:country":"RS",
    "name:srp_x_preferred":[
        "Veliko Selo"
    ],
    "wof:name":"Veliko Selo",
    "wof:placetype":"locality"
},
  "geometry": {"coordinates":[21.29407,44.49192],"type":"Point"}
}