{
  "type": "Feature",
  "properties": {
    "gn:admin1_code":"SE",
    "gn:admin2_code":"20",
    "gn:asciiname":"Cubura",
    "gn:country_code":"RS",
    "gn:dem":492,
    "gn:feature_class":"P",
    "gn:feature_code":"PPL",
    "gn:name":"\u010cubura",
    "gn:population":0,
    "gn:timezone":"Europe/Belgrade",
    "iso:country":"RS",
    "name:srp_x_preferred":[
        "\u010cubura"
    ],
    "wof:name":"Cubura",
    "wof:placetype":"locality"
},
  "geometry": {"coordinates":[21.61816,43.33163],"type":"Point"}
}