{
  "type": "Feature",
  "properties": {
    "gn:admin1_code":"SE",
    "gn:admin2_code":"23",
    "gn:asciiname":"Bocevica",
    "gn:country_code":"RS",
    "gn:dem":611,
    "gn:feature_class":"P",
    "gn:feature_code":"PPL",
    "gn:name":"Bo\u0107evica",
    "gn:population":0,
    "gn:timezone":"Europe/Belgrade",
    "iso:country":"RS",
    "name:ceb_x_preferred":[
        "Bo\u0107evica"
    ],
    "name:fra_x_preferred":[
        "Bo\u0107evica"
    ],
    "name:msa_x_preferred":[
        "Bo\u0107evica"
    ],
    "name:por_x_preferred":[
        "Bo\u0107evica"
    ],
    "name:slv_x_preferred":[
        "Bo\u0107evica"
    ],
    "name:srp_x_preferred":[
        "Bo\u0107evica"
    ],
    "name:srp_x_variant":[
        "\u0411\u043e\u045b\u0435\u0432\u0438\u0446\u0430"
    ],
    "name:und_x_variant":[
        "Bo\u0107eva Mahala"
    ],
    "wof:name":"Bocevica",
    "wof:placetype":"locality"
},
  "geometry": {"coordinates":[22.12111,42.87744],"type":"Point"}
}