{
  "type": "Feature",
  "properties": {
    "gn:country":"RS",
    "gn:fcode":"PPL",
    "gn:pop":121,
    "iso:country":"RS",
    "name:srp_x_preferred":[
        "Smrdan"
    ],
    "qs:name":"Smrdan",
    "qs:photos_9r":0,
    "qs:photos_sr":0,
    "qs:pop_sr":"1",
    "wof:name":"Smrdan",
    "wof:placetype":"locality",
    "wof:population":121
},
  "geometry": {"coordinates":[21.4715,43.22497],"type":"Point"}
}