{
  "type": "Feature",
  "properties": {
    "gn:admin1_code":"SE",
    "gn:admin2_code":"15",
    "gn:asciiname":"Lasovo",
    "gn:country_code":"RS",
    "gn:dem":357,
    "gn:feature_class":"P",
    "gn:feature_code":"PPL",
    "gn:name":"Lasovo",
    "gn:population":0,
    "gn:timezone":"Europe/Belgrade",
    "iso:country":"RS",
    "name:srp_x_preferred":[
        "Lasovo"
    ],
    "wof:name":"Lasovo",
    "wof:placetype":"locality"
},
  "geometry": {"coordinates":[22.12099,43.75961],"type":"Point"}
}