{
  "type": "Feature",
  "properties": {
    "gn:admin1_code":"SE",
    "gn:admin2_code":"24",
    "gn:asciiname":"Donje Zapsko",
    "gn:country_code":"RS",
    "gn:dem":482,
    "gn:feature_class":"P",
    "gn:feature_code":"PPL",
    "gn:name":"Donje \u017dapsko",
    "gn:population":0,
    "gn:timezone":"Europe/Belgrade",
    "iso:country":"RS",
    "name:bul_x_preferred":[
        "\u0414\u043e\u043b\u043d\u043e \u0416\u0430\u0431\u0441\u043a\u043e"
    ],
    "name:ceb_x_preferred":[
        "Donje \u017dapsko"
    ],
    "name:fra_x_preferred":[
        "Donje \u017dapsko"
    ],
    "name:msa_x_preferred":[
        "Donje \u017dapsko"
    ],
    "name:nld_x_preferred":[
        "Donje \u017dapsko"
    ],
    "name:por_x_preferred":[
        "Donje \u017dapsko"
    ],
    "name:slv_x_preferred":[
        "Donje \u017dapsko"
    ],
    "name:sqi_x_preferred":[
        "Zhapska e Poshtme"
    ],
    "name:srp_x_preferred":[
        "Donje \u017dapsko"
    ],
    "name:srp_x_variant":[
        "\u0414\u043e\u045a\u0435 \u0416\u0430\u043f\u0441\u043a\u043e"
    ],
    "wof:name":"Donje Zapsko",
    "wof:placetype":"locality"
},
  "geometry": {"coordinates":[21.89722,42.45833],"type":"Point"}
}