{
  "type": "Feature",
  "properties": {
    "gn:country":"RS",
    "gn:fcode":"PPL",
    "gn:pop":2836,
    "iso:country":"RS",
    "name:ceb_x_preferred":[
        "Sefkerin"
    ],
    "name:deu_x_preferred":[
        "Sefkerin"
    ],
    "name:eng_x_preferred":[
        "Sefkerin"
    ],
    "name:epo_x_preferred":[
        "Sefkerin"
    ],
    "name:fra_x_preferred":[
        "Sefkerin"
    ],
    "name:hrv_x_preferred":[
        "Sefkerin"
    ],
    "name:hun_x_preferred":[
        "Szeker\u00e9ny"
    ],
    "name:msa_x_preferred":[
        "Sefkerin"
    ],
    "name:nld_x_preferred":[
        "Sefkerin"
    ],
    "name:ron_x_preferred":[
        "Sefkerin"
    ],
    "name:slv_x_preferred":[
        "Sefkerin"
    ],
    "name:srp_x_preferred":[
        "Sefkerin"
    ],
    "name:srp_x_variant":[
        "\u0421\u0435\u0444\u043a\u0435\u0440\u0438\u043d"
    ],
    "name:unk_x_variant":[
        "Szeker\u00e9ny"
    ],
    "qs:name":"Sefkerin",
    "qs:name_adm0":"Serbia",
    "qs:name_adm1":"Juzhni Banat",
    "qs:photos_9k":1,
    "qs:photos_9r":1,
    "qs:photos_all":12,
    "qs:photos_sr":0,
    "qs:placetype":"Town",
    "qs:pop_sr":"4",
    "wd:wordcount":61,
    "wof:name":"Sefkerin",
    "wof:placetype":"locality",
    "wof:population":2836
},
  "geometry": {"coordinates":[20.48256,45.00501],"type":"Point"}
}