{
  "type": "Feature",
  "properties": {
    "gn:admin1_code":"SE",
    "gn:admin2_code":"24",
    "gn:asciiname":"Prolesje",
    "gn:country_code":"RS",
    "gn:dem":1319,
    "gn:feature_class":"P",
    "gn:feature_code":"PPLL",
    "gn:name":"Prolesje",
    "gn:population":0,
    "gn:timezone":"Europe/Belgrade",
    "iso:country":"RS",
    "name:srp_x_preferred":[
        "Prolesje"
    ],
    "name:und_x_variant":[
        "Prelesje"
    ],
    "wof:name":"Prolesje",
    "wof:placetype":"locality"
},
  "geometry": {"coordinates":[22.27286,42.37899],"type":"Point"}
}