{
  "type": "Feature",
  "properties": {
    "gn:admin1_code":"SE",
    "gn:admin2_code":"0",
    "gn:asciiname":"Veliki Crljeni",
    "gn:country_code":"RS",
    "gn:dem":99,
    "gn:feature_class":"P",
    "gn:feature_code":"PPL",
    "gn:name":"Veliki Crljeni",
    "gn:population":0,
    "gn:timezone":"Europe/Belgrade",
    "iso:country":"RS",
    "name:ara_x_preferred":[
        "\u0641\u064a\u0644\u064a\u0643\u064a \u062a\u0633\u0631\u0644\u064a\u064a\u0646\u064a"
    ],
    "name:ceb_x_preferred":[
        "Veliki Crljeni"
    ],
    "name:fas_x_preferred":[
        "\u0648\u0644\u06cc\u06a9\u06cc \u06a9\u0631\u0644\u062c\u0646\u06cc"
    ],
    "name:fra_x_preferred":[
        "Veliki Crljeni"
    ],
    "name:msa_x_preferred":[
        "Veliki Crljeni"
    ],
    "name:por_x_preferred":[
        "Veliki Crljeni"
    ],
    "name:rus_x_preferred":[
        "\u0412\u0435\u043b\u0438\u043a\u0438-\u0426\u0440\u043b\u0435\u043d\u0438"
    ],
    "name:slv_x_preferred":[
        "Veliki Crljeni"
    ],
    "name:srp_x_preferred":[
        "Veliki Crljeni"
    ],
    "name:srp_x_variant":[
        "\u0412\u0435\u043b\u0438\u043a\u0438 \u0426\u0440\u0459\u0435\u043d\u0438"
    ],
    "name:und_x_variant":[
        "Crljeni"
    ],
    "wof:name":"Veliki Crljeni",
    "wof:placetype":"locality"
},
  "geometry": {"coordinates":[20.29073,44.47223],"type":"Point"}
}