{
  "type": "Feature",
  "properties": {
    "gn:admin1_code":"SE",
    "gn:admin2_code":"8",
    "gn:asciiname":"Delici",
    "gn:country_code":"RS",
    "gn:dem":392,
    "gn:feature_class":"P",
    "gn:feature_code":"PPL",
    "gn:name":"Deli\u0107i",
    "gn:population":0,
    "gn:timezone":"Europe/Belgrade",
    "iso:country":"RS",
    "name:srp_x_preferred":[
        "Deli\u0107i"
    ],
    "wof:name":"Delici",
    "wof:placetype":"locality"
},
  "geometry": {"coordinates":[19.44173,44.16285],"type":"Point"}
}