{
  "type": "Feature",
  "properties": {
    "gn:admin1_code":"SE",
    "gn:admin2_code":"24",
    "gn:asciiname":"Gornji Stajevac",
    "gn:country_code":"RS",
    "gn:dem":1141,
    "gn:feature_class":"P",
    "gn:feature_code":"PPLL",
    "gn:name":"Gornji Stajevac",
    "gn:population":0,
    "gn:timezone":"Europe/Belgrade",
    "iso:country":"RS",
    "wof:name":"Gornji Stajevac",
    "wof:placetype":"locality"
},
  "geometry": {"coordinates":[22.21306,42.38944],"type":"Point"}
}