{
  "type": "Feature",
  "properties": {
    "gn:admin1_code":"SE",
    "gn:admin2_code":"18",
    "gn:asciiname":"Pope",
    "gn:country_code":"RS",
    "gn:dem":869,
    "gn:feature_class":"P",
    "gn:feature_code":"PPL",
    "gn:name":"Pope",
    "gn:population":0,
    "gn:timezone":"Europe/Belgrade",
    "iso:country":"RS",
    "name:srp_x_preferred":[
        "Pope"
    ],
    "wof:name":"Pope",
    "wof:placetype":"locality"
},
  "geometry": {"coordinates":[20.37921,43.18042],"type":"Point"}
}