{
  "type": "Feature",
  "properties": {
    "gn:admin1_code":"SE",
    "gn:admin2_code":"11",
    "gn:asciiname":"Ticevac",
    "gn:country_code":"RS",
    "gn:dem":149,
    "gn:feature_class":"P",
    "gn:feature_code":"PPL",
    "gn:name":"Ti\u0107evac",
    "gn:population":0,
    "gn:timezone":"Europe/Belgrade",
    "iso:country":"RS",
    "name:ceb_x_preferred":[
        "Ti\u0107evac"
    ],
    "name:fra_x_preferred":[
        "Ti\u0107evac"
    ],
    "name:msa_x_preferred":[
        "Ti\u0107evac"
    ],
    "name:por_x_preferred":[
        "Ti\u0107evac"
    ],
    "name:slv_x_preferred":[
        "Ti\u0107evac"
    ],
    "name:srp_x_preferred":[
        "Ti\u0107evac"
    ],
    "name:srp_x_variant":[
        "\u0422\u0438\u045b\u0435\u0432\u0430\u0446"
    ],
    "wof:name":"Ticevac",
    "wof:placetype":"locality"
},
  "geometry": {"coordinates":[21.25661,44.45993],"type":"Point"}
}