{
  "type": "Feature",
  "properties": {
    "iso:country":"RS",
    "name:eng_x_preferred":[
        "Blok 51"
    ],
    "name:srp_cyr_x_preferred":[
        "\u0431\u043b\u043e\u043a 51"
    ],
    "name:srp_x_preferred":[
        "\u0431\u043b\u043e\u043a 51"
    ],
    "wof:name":"Blok 51",
    "wof:placetype":"neighbourhood"
},
  "geometry": {"coordinates":[20.3848219608801,44.82337568637263],"type":"Point"}
}