{
  "type": "Feature",
  "properties": {
    "gn:admin1_code":"SE",
    "gn:admin2_code":"14",
    "gn:asciiname":"Bukovce",
    "gn:country_code":"RS",
    "gn:dem":57,
    "gn:feature_class":"P",
    "gn:feature_code":"PPL",
    "gn:name":"Bukov\u010de",
    "gn:population":0,
    "gn:timezone":"Europe/Belgrade",
    "iso:country":"RS",
    "name:ceb_x_preferred":[
        "Bukov\u010de"
    ],
    "name:deu_x_preferred":[
        "Bukov\u010de"
    ],
    "name:fra_x_preferred":[
        "Bukov\u010de"
    ],
    "name:msa_x_preferred":[
        "Bukov\u010de"
    ],
    "name:por_x_preferred":[
        "Bukov\u010de"
    ],
    "name:slv_x_preferred":[
        "Bukov\u010de"
    ],
    "name:srp_x_preferred":[
        "Bukov\u010de"
    ],
    "name:srp_x_variant":[
        "\u0411\u0443\u043a\u043e\u0432\u0447\u0435"
    ],
    "name:und_x_variant":[
        "Bukov\u010da"
    ],
    "wof:name":"Bukovce",
    "wof:placetype":"locality"
},
  "geometry": {"coordinates":[22.60083,44.20278],"type":"Point"}
}