{
  "type": "Feature",
  "properties": {
    "gn:country":"RS",
    "gn:fcode":"PPL",
    "gn:pop":1189,
    "iso:country":"RS",
    "name:dut_x_preferred":[
        "Ku\u0161tilj"
    ],
    "name:eng_x_preferred":[
        "Ku\u0161tilj"
    ],
    "name:epo_x_preferred":[
        "Ku\u015dtilj"
    ],
    "name:fre_x_preferred":[
        "Ku\u0161tilj"
    ],
    "name:hun_x_preferred":[
        "M\u00e9lykast\u00e9ly"
    ],
    "name:may_x_preferred":[
        "Ku\u0161tilj"
    ],
    "name:rum_x_preferred":[
        "Co\u0219tei"
    ],
    "name:rus_x_preferred":[
        "\u041a\u0443\u0448\u0442\u0438\u043b\u044c"
    ],
    "name:slv_x_preferred":[
        "Ku\u0161tilj"
    ],
    "name:srp_x_preferred":[
        "Ku\u0161tilj"
    ],
    "name:unk_x_variant":[
        "Co\u015fteiu"
    ],
    "qs:name":"Ku\u0161tilj",
    "qs:photos_9r":0,
    "qs:photos_sr":0,
    "qs:pop_sr":"3",
    "wd:wordcount":55,
    "wof:name":"Ku\u0161tilj",
    "wof:placetype":"locality",
    "wof:population":1189
},
  "geometry": {"coordinates":[21.37988,45.03487],"type":"Point"}
}