{
  "type": "Feature",
  "properties": {
    "gn:admin1_code":"SE",
    "gn:admin2_code":"17",
    "gn:asciiname":"Teocin",
    "gn:country_code":"RS",
    "gn:dem":660,
    "gn:feature_class":"P",
    "gn:feature_code":"PPL",
    "gn:name":"Teo\u010din",
    "gn:population":0,
    "gn:timezone":"Europe/Belgrade",
    "iso:country":"RS",
    "name:ceb_x_preferred":[
        "Teo\u010din"
    ],
    "name:fra_x_preferred":[
        "Teo\u010din"
    ],
    "name:msa_x_preferred":[
        "Teo\u010din"
    ],
    "name:por_x_preferred":[
        "Teo\u010din"
    ],
    "name:slv_x_preferred":[
        "Teo\u010din"
    ],
    "name:srp_x_preferred":[
        "Teo\u010din"
    ],
    "name:srp_x_variant":[
        "\u0422\u0435\u043e\u0447\u0438\u043d"
    ],
    "wof:name":"Teocin",
    "wof:placetype":"locality"
},
  "geometry": {"coordinates":[20.24497,44.07908],"type":"Point"}
}