{
  "type": "Feature",
  "properties": {
    "gn:admin1_code":"SE",
    "gn:admin2_code":"8",
    "gn:asciiname":"Gornja Koviljaca",
    "gn:country_code":"RS",
    "gn:dem":214,
    "gn:feature_class":"P",
    "gn:feature_code":"PPL",
    "gn:name":"Gornja Kovilja\u010da",
    "gn:population":0,
    "gn:timezone":"Europe/Belgrade",
    "iso:country":"RS",
    "name:srp_x_preferred":[
        "Gornja Kovilja\u010da"
    ],
    "wof:name":"Gornja Koviljaca",
    "wof:placetype":"locality"
},
  "geometry": {"coordinates":[19.14286,44.50708],"type":"Point"}
}