{
  "type": "Feature",
  "properties": {
    "gn:admin1_code":"SE",
    "gn:admin2_code":"8",
    "gn:asciiname":"Gornja Koviljaca",
    "gn:country_code":"RS",
    "gn:dem":214,
    "gn:feature_class":"P",
    "gn:feature_code":"PPL",
    "gn:name":"Gornja Kovilja\u010da",
    "gn:population":0,
    "gn:timezone":"Europe/Belgrade",
    "iso:country":"RS",
    "name:ceb_x_preferred":[
        "Gornja Kovilja\u010da"
    ],
    "name:fra_x_preferred":[
        "Gornja Kovilja\u010da"
    ],
    "name:hrv_x_preferred":[
        "Gornja Kovilja\u010da"
    ],
    "name:msa_x_preferred":[
        "Gornja Kovilja\u010da"
    ],
    "name:nld_x_preferred":[
        "Gornja Kovilja\u010da"
    ],
    "name:por_x_preferred":[
        "Gornja Kovilja\u010da"
    ],
    "name:slv_x_preferred":[
        "Gornja Kovilja\u010da"
    ],
    "name:srp_x_preferred":[
        "Gornja Kovilja\u010da"
    ],
    "name:srp_x_variant":[
        "\u0413\u043e\u0440\u045a\u0430 \u041a\u043e\u0432\u0438\u0459\u0430\u0447\u0430"
    ],
    "wof:name":"Gornja Koviljaca",
    "wof:placetype":"locality"
},
  "geometry": {"coordinates":[19.14286,44.50708],"type":"Point"}
}