{
  "type": "Feature",
  "properties": {
    "gn:admin1_code":"SE",
    "gn:admin2_code":"17",
    "gn:asciiname":"Bojovici",
    "gn:country_code":"RS",
    "gn:dem":928,
    "gn:feature_class":"P",
    "gn:feature_code":"PPL",
    "gn:name":"Bojovi\u0107i",
    "gn:population":0,
    "gn:timezone":"Europe/Belgrade",
    "iso:country":"RS",
    "name:srp_x_preferred":[
        "Bojovi\u0107i"
    ],
    "wof:name":"Bojovici",
    "wof:placetype":"locality"
},
  "geometry": {"coordinates":[20.19843,43.45185],"type":"Point"}
}