{
  "type": "Feature",
  "properties": {
    "iso:country":"RS",
    "name:eng_x_preferred":[
        "Bezanija"
    ],
    "name:srp_cyr_x_preferred":[
        "\u0411\u0435\u0436\u0430\u043d\u0438\u0458\u0430"
    ],
    "name:srp_lat_x_preferred":[
        "Be\u017eanija"
    ],
    "name:srp_x_preferred":[
        "\u0411\u0435\u0436\u0430\u043d\u0438\u0458\u0430"
    ],
    "wof:name":"Bezanija",
    "wof:placetype":"neighbourhood"
},
  "geometry": {"coordinates":[20.37672015288781,44.81443097525803],"type":"Point"}
}