{
  "type": "Feature",
  "properties": {
    "gn:admin1_code":"SE",
    "gn:admin2_code":"18",
    "gn:asciiname":"Crvanj",
    "gn:country_code":"RS",
    "gn:dem":819,
    "gn:feature_class":"P",
    "gn:feature_code":"PPLL",
    "gn:name":"Crvanj",
    "gn:population":0,
    "gn:timezone":"Europe/Belgrade",
    "iso:country":"RS",
    "name:srp_x_preferred":[
        "Crvanj"
    ],
    "wof:name":"Crvanj",
    "wof:placetype":"locality"
},
  "geometry": {"coordinates":[20.71756,43.47045],"type":"Point"}
}