{
  "type": "Feature",
  "properties": {
    "gn:admin1_code":"SE",
    "gn:admin2_code":"18",
    "gn:asciiname":"Crvanj",
    "gn:country_code":"RS",
    "gn:dem":819,
    "gn:feature_class":"P",
    "gn:feature_code":"PPLL",
    "gn:name":"Crvanj",
    "gn:population":0,
    "gn:timezone":"Europe/Belgrade",
    "iso:country":"RS",
    "name:bos_x_preferred":[
        "Crvanj"
    ],
    "name:ceb_x_preferred":[
        "Crvanj"
    ],
    "name:fra_x_preferred":[
        "Crvanj"
    ],
    "name:hrv_x_preferred":[
        "Crvanj"
    ],
    "name:rus_x_preferred":[
        "\u0426\u0440\u0432\u0430\u043d\u044c"
    ],
    "name:srp_x_preferred":[
        "Crvanj"
    ],
    "name:srp_x_variant":[
        "\u0426\u0440\u0432\u0430\u045a"
    ],
    "name:swe_x_preferred":[
        "Crvanj"
    ],
    "wof:name":"Crvanj",
    "wof:placetype":"locality"
},
  "geometry": {"coordinates":[20.71756,43.47045],"type":"Point"}
}