{
  "type": "Feature",
  "properties": {
    "gn:admin1_code":"VO",
    "gn:admin2_code":"1",
    "gn:asciiname":"Jagodnjak",
    "gn:country_code":"RS",
    "gn:dem":104,
    "gn:feature_class":"P",
    "gn:feature_code":"PPL",
    "gn:name":"Jagodnjak",
    "gn:population":0,
    "gn:timezone":"Europe/Belgrade",
    "iso:country":"RS",
    "wof:name":"Jagodnjak",
    "wof:placetype":"locality"
},
  "geometry": {"coordinates":[19.56806,45.85583],"type":"Point"}
}