{
  "type": "Feature",
  "properties": {
    "gn:admin1_code":"VO",
    "gn:admin2_code":"1",
    "gn:asciiname":"Jagodnjak",
    "gn:country_code":"RS",
    "gn:dem":104,
    "gn:feature_class":"P",
    "gn:feature_code":"PPL",
    "gn:name":"Jagodnjak",
    "gn:population":0,
    "gn:timezone":"Europe/Belgrade",
    "iso:country":"RS",
    "name:bos_x_preferred":[
        "Jagodnjak"
    ],
    "name:ceb_x_preferred":[
        "Jagodnjak"
    ],
    "name:cym_x_preferred":[
        "Jagodnjak"
    ],
    "name:deu_x_preferred":[
        "Jagodnjak"
    ],
    "name:epo_x_preferred":[
        "Jagodnjak"
    ],
    "name:fra_x_preferred":[
        "Jagodnjak"
    ],
    "name:hrv_x_preferred":[
        "Jagodnjak"
    ],
    "name:hun_x_preferred":[
        "K\u00e1csfalu"
    ],
    "name:ita_x_preferred":[
        "Jagodnjak"
    ],
    "name:nld_x_preferred":[
        "Jagodnjak"
    ],
    "name:pol_x_preferred":[
        "Gmina Jagodnjak"
    ],
    "name:ron_x_preferred":[
        "Comuna Jagodnjak"
    ],
    "name:rus_x_preferred":[
        "\u042f\u0433\u043e\u0434\u043d\u044f\u043a"
    ],
    "name:srp_x_preferred":[
        "\u0408\u0430\u0433\u043e\u0434\u045a\u0430\u043a"
    ],
    "name:swe_x_preferred":[
        "Jagodnjak"
    ],
    "name:ukr_x_preferred":[
        "\u042f\u0433\u043e\u0434\u043d\u044f\u043a"
    ],
    "name:urd_x_preferred":[
        "\u062c\u06af\u0648\u062f\u0646\u062c\u06a9"
    ],
    "name:war_x_preferred":[
        "Jagodnjak"
    ],
    "wof:name":"Jagodnjak",
    "wof:placetype":"locality"
},
  "geometry": {"coordinates":[19.56806,45.85583],"type":"Point"}
}