{
  "type": "Feature",
  "properties": {
    "gn:admin1_code":"SE",
    "gn:admin2_code":"24",
    "gn:asciiname":"Toskinci",
    "gn:country_code":"RS",
    "gn:dem":1256,
    "gn:feature_class":"P",
    "gn:feature_code":"PPL",
    "gn:name":"To\u0161kinci",
    "gn:population":0,
    "gn:timezone":"Europe/Belgrade",
    "iso:country":"RS",
    "wof:name":"Toskinci",
    "wof:placetype":"locality"
},
  "geometry": {"coordinates":[22.18167,42.37667],"type":"Point"}
}