{
  "type": "Feature",
  "properties": {
    "gn:admin1_code":"SE",
    "gn:admin2_code":"16",
    "gn:asciiname":"Borja",
    "gn:country_code":"RS",
    "gn:dem":1152,
    "gn:feature_class":"P",
    "gn:feature_code":"PPL",
    "gn:name":"Borja",
    "gn:population":0,
    "gn:timezone":"Europe/Belgrade",
    "iso:country":"RS",
    "name:bre_x_preferred":[
        "Borja"
    ],
    "name:cat_x_preferred":[
        "Borja"
    ],
    "name:ceb_x_preferred":[
        "Borja"
    ],
    "name:deu_x_preferred":[
        "Borja"
    ],
    "name:fra_x_preferred":[
        "Borja"
    ],
    "name:hrv_x_preferred":[
        "Borja"
    ],
    "name:ita_x_preferred":[
        "Borja"
    ],
    "name:jpn_x_preferred":[
        "\u30dc\u30eb\u30cf"
    ],
    "name:kor_x_preferred":[
        "\ubcf4\ub974\ud558"
    ],
    "name:pol_x_preferred":[
        "Borja"
    ],
    "name:rus_x_preferred":[
        "\u0411\u043e\u0440\u0445\u0430"
    ],
    "name:spa_x_preferred":[
        "Borja"
    ],
    "name:srp_x_preferred":[
        "Borja"
    ],
    "name:srp_x_variant":[
        "\u0411\u043e\u0440\u0458\u0430"
    ],
    "name:swe_x_preferred":[
        "Borja"
    ],
    "name:ukr_x_preferred":[
        "\u0411\u043e\u0440\u0445\u0430"
    ],
    "wof:name":"Borja",
    "wof:placetype":"locality"
},
  "geometry": {"coordinates":[19.91869,43.47832],"type":"Point"}
}