{
  "type": "Feature",
  "properties": {
    "iso:country":"RS",
    "name:eng_x_preferred":[
        "Vuk"
    ],
    "name:srp_cyr_x_preferred":[
        "\u0412\u0443\u043a"
    ],
    "name:srp_cyr_x_variant":[
        "\u0412\u0443\u043a\u043e\u0432 \u0421\u043f\u043e\u043c\u0435\u043d\u0438\u043a"
    ],
    "name:srp_lat_x_variant":[
        "Vukov Spomenik"
    ],
    "name:srp_x_preferred":[
        "\u0412\u0443\u043a"
    ],
    "wof:name":"Vuk",
    "wof:placetype":"neighbourhood"
},
  "geometry": {"coordinates":[20.47708027820602,44.80491384692591],"type":"Point"}
}