{
  "type": "Feature",
  "properties": {
    "gn:country":"RS",
    "gn:fcode":"PPL",
    "gn:pop":3186,
    "iso:country":"RS",
    "name:ceb_x_preferred":[
        "Ri\u0111ica"
    ],
    "name:deu_x_preferred":[
        "Ri\u0111ica"
    ],
    "name:eng_x_preferred":[
        "Ri\u0111ica"
    ],
    "name:epo_x_preferred":[
        "Ridjica"
    ],
    "name:fra_x_preferred":[
        "Ri\u0111ica"
    ],
    "name:hrv_x_preferred":[
        "Ri\u0111ica"
    ],
    "name:hun_x_preferred":[
        "Reg\u0151ce"
    ],
    "name:msa_x_preferred":[
        "Ri\u0111ica"
    ],
    "name:nld_x_preferred":[
        "Ri\u0111ica"
    ],
    "name:slv_x_preferred":[
        "Ri\u0111ica"
    ],
    "name:srp_x_preferred":[
        "Ri\u0111ica"
    ],
    "name:srp_x_variant":[
        "\u0420\u0438\u0452\u0438\u0446\u0430"
    ],
    "name:ukr_x_preferred":[
        "\u0420\u0438\u0434\u0436\u0438\u0446\u044f"
    ],
    "name:unk_x_variant":[
        "Deutsch-Baja"
    ],
    "qs:name":"Ri\u00f0ica",
    "qs:name_adm0":"Serbia",
    "qs:name_adm1":"Zapadna Bachka",
    "qs:photos_9k":1,
    "qs:photos_9r":1,
    "qs:photos_all":1,
    "qs:photos_sr":0,
    "qs:placetype":"Town",
    "qs:pop_sr":"4",
    "wd:wordcount":262,
    "wof:name":"Ri\u00f0ica",
    "wof:placetype":"locality",
    "wof:population":3186
},
  "geometry": {"coordinates":[19.10635,45.99088],"type":"Point"}
}