{
  "type": "Feature",
  "properties": {
    "gn:admin1_code":"SE",
    "gn:admin2_code":"9",
    "gn:asciiname":"Tugin",
    "gn:country_code":"RS",
    "gn:dem":366,
    "gn:feature_class":"P",
    "gn:feature_code":"PPLL",
    "gn:name":"Tu\u0111in",
    "gn:population":0,
    "gn:timezone":"Europe/Belgrade",
    "iso:country":"RS",
    "name:srp_x_preferred":[
        "Tu\u0111in"
    ],
    "wof:name":"Tugin",
    "wof:placetype":"locality"
},
  "geometry": {"coordinates":[19.67651,44.36704],"type":"Point"}
}