{
  "type": "Feature",
  "properties": {
    "gn:admin1_code":"SE",
    "gn:admin2_code":"12",
    "gn:asciiname":"Gornja Bresnica",
    "gn:country_code":"RS",
    "gn:dem":321,
    "gn:feature_class":"P",
    "gn:feature_code":"PPL",
    "gn:name":"Gornja Bresnica",
    "gn:population":0,
    "gn:timezone":"Europe/Belgrade",
    "iso:country":"RS",
    "name:ceb_x_preferred":[
        "Gornja Bresnica"
    ],
    "name:fra_x_preferred":[
        "Gornja Bresnica"
    ],
    "name:msa_x_preferred":[
        "Gornja Bresnica"
    ],
    "name:por_x_preferred":[
        "Gornja Bresnica"
    ],
    "name:slv_x_preferred":[
        "Gornja Bresnica"
    ],
    "name:sqi_x_preferred":[
        "Breznica e Ep\u00ebrme"
    ],
    "name:srp_x_preferred":[
        "\u0413\u043e\u0440\u045a\u0430 \u0411\u0440\u0435\u0441\u043d\u0438\u0446\u0430"
    ],
    "wof:name":"Gornja Bresnica",
    "wof:placetype":"locality"
},
  "geometry": {"coordinates":[20.58332,43.90742],"type":"Point"}
}