{
  "type": "Feature",
  "properties": {
    "gn:admin1_code":"SE",
    "gn:admin2_code":"12",
    "gn:asciiname":"Gornja Bresnica",
    "gn:country_code":"RS",
    "gn:dem":321,
    "gn:feature_class":"P",
    "gn:feature_code":"PPL",
    "gn:name":"Gornja Bresnica",
    "gn:population":0,
    "gn:timezone":"Europe/Belgrade",
    "iso:country":"RS",
    "wof:name":"Gornja Bresnica",
    "wof:placetype":"locality"
},
  "geometry": {"coordinates":[20.58332,43.90742],"type":"Point"}
}