{
  "type": "Feature",
  "properties": {
    "gn:admin1_code":"SE",
    "gn:admin2_code":"23",
    "gn:asciiname":"Jasunja",
    "gn:country_code":"RS",
    "gn:dem":287,
    "gn:feature_class":"P",
    "gn:feature_code":"PPL",
    "gn:name":"Ja\u0161unja",
    "gn:population":0,
    "gn:timezone":"Europe/Belgrade",
    "iso:country":"RS",
    "name:ceb_x_preferred":[
        "Ja\u0161unja"
    ],
    "name:fra_x_preferred":[
        "Ja\u0161unja"
    ],
    "name:msa_x_preferred":[
        "Ja\u0161unja"
    ],
    "name:por_x_preferred":[
        "Ja\u0161unja"
    ],
    "name:slv_x_preferred":[
        "Ja\u0161unja"
    ],
    "name:srp_x_preferred":[
        "Ja\u0161unja"
    ],
    "name:srp_x_variant":[
        "\u0408\u0430\u0448\u0443\u045a\u0430"
    ],
    "name:urd_x_preferred":[
        "\u062c\u0627\u0634\u0627\u0646\u062c\u0627"
    ],
    "wof:name":"Jasunja",
    "wof:placetype":"locality"
},
  "geometry": {"coordinates":[22.02002,43.06707],"type":"Point"}
}