{
  "type": "Feature",
  "properties": {
    "gn:admin1_code":"SE",
    "gn:admin2_code":"23",
    "gn:asciiname":"Kapit",
    "gn:country_code":"RS",
    "gn:dem":611,
    "gn:feature_class":"P",
    "gn:feature_code":"PPL",
    "gn:name":"Kapit",
    "gn:population":0,
    "gn:timezone":"Europe/Belgrade",
    "iso:country":"RS",
    "name:ceb_x_preferred":[
        "Kapit"
    ],
    "name:fra_x_preferred":[
        "Kapit"
    ],
    "name:msa_x_preferred":[
        "Kapit"
    ],
    "name:por_x_preferred":[
        "Kapit"
    ],
    "name:slv_x_preferred":[
        "Kapit"
    ],
    "name:sqi_x_preferred":[
        "Kapiti"
    ],
    "name:srp_x_preferred":[
        "Kapit"
    ],
    "name:srp_x_variant":[
        "\u041a\u0430\u043f\u0438\u0442"
    ],
    "wof:name":"Kapit",
    "wof:placetype":"locality"
},
  "geometry": {"coordinates":[21.61607,42.84101],"type":"Point"}
}