{
  "type": "Feature",
  "properties": {
    "gn:admin1_code":"SE",
    "gn:admin2_code":"10",
    "gn:asciiname":"Cerovac",
    "gn:country_code":"RS",
    "gn:dem":134,
    "gn:feature_class":"P",
    "gn:feature_code":"PPL",
    "gn:name":"Cerovac",
    "gn:population":0,
    "gn:timezone":"Europe/Belgrade",
    "iso:country":"RS",
    "name:fra_x_preferred":[
        "Cerovac"
    ],
    "name:msa_x_preferred":[
        "Cerovac"
    ],
    "name:por_x_preferred":[
        "Cerovac"
    ],
    "name:slv_x_preferred":[
        "Cerovac"
    ],
    "name:srp_x_preferred":[
        "Cerovac"
    ],
    "name:srp_x_variant":[
        "\u0426\u0435\u0440\u043e\u0432\u0430\u0446"
    ],
    "wof:name":"Cerovac",
    "wof:placetype":"locality"
},
  "geometry": {"coordinates":[20.86687,44.32911],"type":"Point"}
}