{
  "type": "Feature",
  "properties": {
    "gn:admin1_code":"SE",
    "gn:admin2_code":"18",
    "gn:asciiname":"Zukici",
    "gn:country_code":"RS",
    "gn:dem":1201,
    "gn:feature_class":"P",
    "gn:feature_code":"PPL",
    "gn:name":"\u017duki\u0107i",
    "gn:population":0,
    "gn:timezone":"Europe/Belgrade",
    "iso:country":"RS",
    "name:srp_x_preferred":[
        "\u017duki\u0107i"
    ],
    "name:und_x_variant":[
        "Erci"
    ],
    "wof:name":"Zukici",
    "wof:placetype":"locality"
},
  "geometry": {"coordinates":[20.44584,43.41944],"type":"Point"}
}