{
  "type": "Feature",
  "properties": {
    "gn:country":"RS",
    "gn:fcode":"PPL",
    "gn:pop":1284,
    "iso:country":"RS",
    "name:bul_x_preferred":[
        "\u0416\u0443\u0438\u043d\u0446\u0435"
    ],
    "name:ceb_x_preferred":[
        "\u017dujince"
    ],
    "name:eng_x_preferred":[
        "\u017dujince"
    ],
    "name:fra_x_preferred":[
        "\u017dujince"
    ],
    "name:mkd_x_preferred":[
        "\u0416\u0443\u0438\u043d\u0446\u0435"
    ],
    "name:msa_x_preferred":[
        "\u017dujince"
    ],
    "name:nld_x_preferred":[
        "Zjujince"
    ],
    "name:por_x_preferred":[
        "\u017dujince"
    ],
    "name:slv_x_preferred":[
        "\u017dujince"
    ],
    "name:sqi_x_preferred":[
        "Zhunic\u00eb"
    ],
    "name:sqi_x_variant":[
        "Zhunica"
    ],
    "name:srp_x_preferred":[
        "\u017dujince"
    ],
    "name:srp_x_variant":[
        "\u0416\u0443\u0458\u0438\u043d\u0446\u0435"
    ],
    "name:unk_x_variant":[
        "\u017duince"
    ],
    "qs:name":"\u017dujince",
    "qs:photos_9r":0,
    "qs:photos_sr":0,
    "qs:pop_sr":"3",
    "wd:wordcount":69,
    "wof:name":"\u017dujince",
    "wof:placetype":"locality",
    "wof:population":1284
},
  "geometry": {"coordinates":[21.70212,42.31568],"type":"Point"}
}