{
  "type": "Feature",
  "properties": {
    "gn:admin1_code":"SE",
    "gn:admin2_code":"18",
    "gn:asciiname":"Kuline",
    "gn:country_code":"RS",
    "gn:dem":948,
    "gn:feature_class":"P",
    "gn:feature_code":"PPL",
    "gn:name":"Kuline",
    "gn:population":0,
    "gn:timezone":"Europe/Belgrade",
    "iso:country":"RS",
    "name:srp_x_preferred":[
        "Kuline"
    ],
    "wof:name":"Kuline",
    "wof:placetype":"locality"
},
  "geometry": {"coordinates":[20.37025,43.19127],"type":"Point"}
}