{
  "type": "Feature",
  "properties": {
    "gn:country":"RS",
    "gn:fcode":"PPL",
    "gn:pop":5,
    "iso:country":"RS",
    "name:srp_x_preferred":[
        "Grai\u0107i"
    ],
    "qs:name":"Grai\u0107i",
    "qs:photos_9r":0,
    "qs:photos_sr":0,
    "qs:pop_sr":"1",
    "wof:name":"Grai\u0107i",
    "wof:placetype":"locality",
    "wof:population":5
},
  "geometry": {"coordinates":[20.42719,43.52205],"type":"Point"}
}