{
  "type": "Feature",
  "properties": {
    "gn:admin1_code":"SE",
    "gn:admin2_code":"19",
    "gn:asciiname":"Batote",
    "gn:country_code":"RS",
    "gn:dem":616,
    "gn:feature_class":"P",
    "gn:feature_code":"PPL",
    "gn:name":"Batote",
    "gn:population":0,
    "gn:timezone":"Europe/Belgrade",
    "iso:country":"RS",
    "name:ceb_x_preferred":[
        "Batote"
    ],
    "name:fra_x_preferred":[
        "Batote"
    ],
    "name:hye_x_preferred":[
        "\u0532\u0561\u0562\u0578\u057f\u0565"
    ],
    "name:msa_x_preferred":[
        "Batote"
    ],
    "name:nld_x_preferred":[
        "Batote"
    ],
    "name:por_x_preferred":[
        "Batote"
    ],
    "name:slv_x_preferred":[
        "Batote"
    ],
    "name:spa_x_preferred":[
        "Batote"
    ],
    "name:srp_x_preferred":[
        "Batote"
    ],
    "name:srp_x_variant":[
        "\u0411\u0430\u0442\u043e\u0442\u0435"
    ],
    "wof:name":"Batote",
    "wof:placetype":"locality"
},
  "geometry": {"coordinates":[21.09236,43.29099],"type":"Point"}
}