{
  "type": "Feature",
  "properties": {
    "gn:admin1_code":"SE",
    "gn:admin2_code":"9",
    "gn:asciiname":"Susica",
    "gn:country_code":"RS",
    "gn:dem":321,
    "gn:feature_class":"P",
    "gn:feature_code":"PPL",
    "gn:name":"Su\u0161ica",
    "gn:population":0,
    "gn:timezone":"Europe/Belgrade",
    "iso:country":"RS",
    "name:srp_x_preferred":[
        "Su\u0161ica"
    ],
    "wof:name":"Susica",
    "wof:placetype":"locality"
},
  "geometry": {"coordinates":[19.74611,44.22778],"type":"Point"}
}