{
  "type": "Feature",
  "properties": {
    "gn:admin1_code":"SE",
    "gn:admin2_code":"12",
    "gn:asciiname":"Badnjevac",
    "gn:country_code":"RS",
    "gn:dem":135,
    "gn:feature_class":"P",
    "gn:feature_code":"PPL",
    "gn:name":"Badnjevac",
    "gn:population":0,
    "gn:timezone":"Europe/Belgrade",
    "iso:country":"RS",
    "name:srp_x_preferred":[
        "Badnjevac"
    ],
    "wof:name":"Badnjevac",
    "wof:placetype":"locality"
},
  "geometry": {"coordinates":[20.98241,44.13175],"type":"Point"}
}