{
  "type": "Feature",
  "properties": {
    "gn:admin1_code":"SE",
    "gn:admin2_code":"12",
    "gn:asciiname":"Badnjevac",
    "gn:country_code":"RS",
    "gn:dem":135,
    "gn:feature_class":"P",
    "gn:feature_code":"PPL",
    "gn:name":"Badnjevac",
    "gn:population":0,
    "gn:timezone":"Europe/Belgrade",
    "iso:country":"RS",
    "name:ceb_x_preferred":[
        "Badnjevac"
    ],
    "name:fra_x_preferred":[
        "Badnjevac"
    ],
    "name:lit_x_preferred":[
        "Badnevacas"
    ],
    "name:msa_x_preferred":[
        "Badnjevac"
    ],
    "name:pol_x_preferred":[
        "Badnjevac"
    ],
    "name:por_x_preferred":[
        "Badnjevac"
    ],
    "name:slv_x_preferred":[
        "Badnjevac"
    ],
    "name:srp_x_preferred":[
        "Badnjevac"
    ],
    "name:srp_x_variant":[
        "\u0411\u0430\u0434\u045a\u0435\u0432\u0430\u0446"
    ],
    "wof:name":"Badnjevac",
    "wof:placetype":"locality"
},
  "geometry": {"coordinates":[20.98241,44.13175],"type":"Point"}
}