{
  "type": "Feature",
  "properties": {
    "gn:admin1_code":"SE",
    "gn:admin2_code":"17",
    "gn:asciiname":"Opaljenik",
    "gn:country_code":"RS",
    "gn:dem":828,
    "gn:feature_class":"P",
    "gn:feature_code":"PPLL",
    "gn:name":"Opaljenik",
    "gn:population":0,
    "gn:timezone":"Europe/Belgrade",
    "iso:country":"RS",
    "name:srp_x_preferred":[
        "Opaljenik"
    ],
    "wof:name":"Opaljenik",
    "wof:placetype":"locality"
},
  "geometry": {"coordinates":[20.12798,43.51895],"type":"Point"}
}