{
  "type": "Feature",
  "properties": {
    "gn:admin1_code":"SE",
    "gn:admin2_code":"17",
    "gn:asciiname":"Opaljenik",
    "gn:country_code":"RS",
    "gn:dem":828,
    "gn:feature_class":"P",
    "gn:feature_code":"PPLL",
    "gn:name":"Opaljenik",
    "gn:population":0,
    "gn:timezone":"Europe/Belgrade",
    "iso:country":"RS",
    "name:ceb_x_preferred":[
        "Opaljenik"
    ],
    "name:fas_x_preferred":[
        "\u0627\u0648\u067e\u0627\u0644\u06cc\u0646\u06cc\u06a9"
    ],
    "name:fra_x_preferred":[
        "Opaljenik"
    ],
    "name:msa_x_preferred":[
        "Opaljenik"
    ],
    "name:por_x_preferred":[
        "Opaljenik"
    ],
    "name:slv_x_preferred":[
        "Opaljenik"
    ],
    "name:srp_x_preferred":[
        "Opaljenik"
    ],
    "name:srp_x_variant":[
        "\u041e\u043f\u0430\u0459\u0435\u043d\u0438\u043a"
    ],
    "wof:name":"Opaljenik",
    "wof:placetype":"locality"
},
  "geometry": {"coordinates":[20.12798,43.51895],"type":"Point"}
}