{
  "type": "Feature",
  "properties": {
    "gn:admin1_code":"SE",
    "gn:admin2_code":"24",
    "gn:asciiname":"Rupe",
    "gn:country_code":"RS",
    "gn:dem":955,
    "gn:feature_class":"P",
    "gn:feature_code":"PPL",
    "gn:name":"Rupe",
    "gn:population":0,
    "gn:timezone":"Europe/Belgrade",
    "iso:country":"RS",
    "name:und_x_variant":[
        "Rupe Mahala",
        "Rupe"
    ],
    "wof:name":"Rupe",
    "wof:placetype":"locality"
},
  "geometry": {"coordinates":[22.4324,42.37256],"type":"Point"}
}