{
  "type": "Feature",
  "properties": {
    "gn:admin1_code":"SE",
    "gn:admin2_code":"24",
    "gn:asciiname":"Rupe",
    "gn:country_code":"RS",
    "gn:dem":955,
    "gn:feature_class":"P",
    "gn:feature_code":"PPL",
    "gn:name":"Rupe",
    "gn:population":0,
    "gn:timezone":"Europe/Belgrade",
    "iso:country":"RS",
    "name:bos_x_preferred":[
        "Rupe"
    ],
    "name:ceb_x_preferred":[
        "Rupe"
    ],
    "name:deu_x_preferred":[
        "Rupe"
    ],
    "name:nld_x_preferred":[
        "Rupe"
    ],
    "name:pol_x_preferred":[
        "Rupe"
    ],
    "name:slv_x_preferred":[
        "Rupe"
    ],
    "name:srp_x_preferred":[
        "\u0420\u0443\u043f\u0435"
    ],
    "name:swe_x_preferred":[
        "Rupe"
    ],
    "name:und_x_variant":[
        "Rupe Mahala",
        "Rupe"
    ],
    "wof:name":"Rupe",
    "wof:placetype":"locality"
},
  "geometry": {"coordinates":[22.4324,42.37256],"type":"Point"}
}