{
  "type": "Feature",
  "properties": {
    "gn:country":"RS",
    "gn:fcode":"PPLL",
    "gn:population":1214,
    "iso:country":"RS",
    "name:ceb_x_preferred":[
        "Tr\u0161i\u0107"
    ],
    "name:ces_x_preferred":[
        "Tr\u0161i\u0107"
    ],
    "name:ell_x_preferred":[
        "\u03a4\u03c1\u03c3\u03b9\u03c4\u03c2 \u039b\u03bf\u03b6\u03bd\u03af\u03c4\u03c3\u03b1\u03c2"
    ],
    "name:eng_x_preferred":[
        "Tr\u0161i\u0107"
    ],
    "name:fas_x_preferred":[
        "\u062a\u0631\u0634\u06cc\u0686"
    ],
    "name:fra_x_preferred":[
        "Tr\u0161i\u0107"
    ],
    "name:hye_x_preferred":[
        "\u054f\u0580\u0577\u056b\u0579"
    ],
    "name:mkd_x_preferred":[
        "\u0422\u0440\u0448\u0438\u045c"
    ],
    "name:msa_x_preferred":[
        "Tr\u0161i\u0107"
    ],
    "name:nld_x_preferred":[
        "Tr\u0161i\u0107"
    ],
    "name:pol_x_preferred":[
        "Tr\u0161i\u0107"
    ],
    "name:por_x_preferred":[
        "Tr\u0161i\u0107"
    ],
    "name:ron_x_preferred":[
        "Tr\u0161i\u0107"
    ],
    "name:rus_x_preferred":[
        "\u0422\u0440\u0448\u0438\u0447"
    ],
    "name:slv_x_preferred":[
        "Tr\u0161i\u0107"
    ],
    "name:srp_x_preferred":[
        "Tr\u0161i\u0107"
    ],
    "name:srp_x_variant":[
        "\u0422\u0440\u0448\u0438\u045b"
    ],
    "name:swe_x_preferred":[
        "Tr\u0161i\u0107"
    ],
    "name:ukr_x_preferred":[
        "\u0422\u0440\u0448\u0438\u0447"
    ],
    "qs:name":"Tr\u0161i\u0107",
    "qs:photos_9r":0,
    "qs:photos_sr":0,
    "qs:pop_sr":"3",
    "wd:wordcount":422,
    "wof:name":"Tr\u0161i\u0107",
    "wof:placetype":"locality",
    "wof:population":1214
},
  "geometry": {"coordinates":[19.2649,44.49502],"type":"Point"}
}