{
  "type": "Feature",
  "properties": {
    "gn:country":"RS",
    "gn:fcode":"PPLL",
    "gn:pop":1214,
    "iso:country":"RS",
    "name:srp_x_preferred":[
        "Tr\u0161i\u0107"
    ],
    "qs:name":"Tr\u0161i\u0107",
    "qs:photos_9r":0,
    "qs:photos_sr":0,
    "qs:pop_sr":"3",
    "wd:wordcount":422,
    "wof:name":"Tr\u0161i\u0107",
    "wof:placetype":"locality",
    "wof:population":1214
},
  "geometry": {"coordinates":[19.2649,44.49502],"type":"Point"}
}