{
  "type": "Feature",
  "properties": {
    "gn:admin1_code":"SE",
    "gn:admin2_code":"18",
    "gn:asciiname":"Crnovrsam",
    "gn:country_code":"RS",
    "gn:dem":791,
    "gn:feature_class":"P",
    "gn:feature_code":"PPLL",
    "gn:name":"Crnovr\u0161am",
    "gn:population":0,
    "gn:timezone":"Europe/Belgrade",
    "iso:country":"RS",
    "name:srp_x_preferred":[
        "Crnovr\u0161am"
    ],
    "wof:name":"Crnovrsam",
    "wof:placetype":"locality"
},
  "geometry": {"coordinates":[20.43222,43.09583],"type":"Point"}
}