{
  "type": "Feature",
  "properties": {
    "gn:admin1_code":"SE",
    "gn:admin2_code":"23",
    "gn:asciiname":"Pecenjevce",
    "gn:country_code":"RS",
    "gn:dem":217,
    "gn:feature_class":"P",
    "gn:feature_code":"PPL",
    "gn:name":"Pe\u010denjevce",
    "gn:population":0,
    "gn:timezone":"Europe/Belgrade",
    "iso:country":"RS",
    "name:bul_x_preferred":[
        "\u041f\u0435\u0447\u0435\u043d\u0435\u0432\u0446\u0435"
    ],
    "name:ceb_x_preferred":[
        "Pe\u010denjevce"
    ],
    "name:fra_x_preferred":[
        "Pe\u010denjevce"
    ],
    "name:msa_x_preferred":[
        "Pe\u010denjevce"
    ],
    "name:por_x_preferred":[
        "Pe\u010denjevce"
    ],
    "name:slv_x_preferred":[
        "Pe\u010denjevce"
    ],
    "name:srp_x_preferred":[
        "Pe\u010denjevce"
    ],
    "name:srp_x_variant":[
        "\u041f\u0435\u0447\u0435\u045a\u0435\u0432\u0446\u0435"
    ],
    "name:und_x_variant":[
        "Pe\u010denjevci"
    ],
    "wof:name":"Pecenjevce",
    "wof:placetype":"locality"
},
  "geometry": {"coordinates":[21.91431,43.09862],"type":"Point"}
}