{
  "type": "Feature",
  "properties": {
    "gn:admin1_code":"SE",
    "gn:admin2_code":"16",
    "gn:asciiname":"Latvica",
    "gn:country_code":"RS",
    "gn:dem":463,
    "gn:feature_class":"P",
    "gn:feature_code":"PPLL",
    "gn:name":"Latvica",
    "gn:population":0,
    "gn:timezone":"Europe/Belgrade",
    "iso:country":"RS",
    "name:ceb_x_preferred":[
        "Latvica"
    ],
    "name:fra_x_preferred":[
        "Latvica"
    ],
    "name:msa_x_preferred":[
        "Latvica"
    ],
    "name:nld_x_preferred":[
        "Latvica"
    ],
    "name:por_x_preferred":[
        "Latvica"
    ],
    "name:slv_x_preferred":[
        "Latvica"
    ],
    "name:srp_x_preferred":[
        "Latvica"
    ],
    "name:srp_x_variant":[
        "\u041b\u0430\u0442\u0432\u0438\u0446\u0430"
    ],
    "name:urd_x_preferred":[
        "\u0644\u0627\u062a\u0648\u06cc\u06a9\u0627"
    ],
    "wof:name":"Latvica",
    "wof:placetype":"locality"
},
  "geometry": {"coordinates":[20.09417,43.70111],"type":"Point"}
}