{
  "type": "Feature",
  "properties": {
    "gn:admin1_code":"SE",
    "gn:admin2_code":"15",
    "gn:asciiname":"Vlasko Polje",
    "gn:country_code":"RS",
    "gn:dem":767,
    "gn:feature_class":"P",
    "gn:feature_code":"PPL",
    "gn:name":"Vla\u0161ko Polje",
    "gn:population":0,
    "gn:timezone":"Europe/Belgrade",
    "iso:country":"RS",
    "name:ceb_x_preferred":[
        "Vla\u0161ko Polje"
    ],
    "name:fra_x_preferred":[
        "Vla\u0161ko Polje"
    ],
    "name:msa_x_preferred":[
        "Vla\u0161ko Polje"
    ],
    "name:por_x_preferred":[
        "Vla\u0161ko Polje"
    ],
    "name:slv_x_preferred":[
        "Vla\u0161ko Polje"
    ],
    "name:srp_x_preferred":[
        "Vla\u0161ko Polje"
    ],
    "name:srp_x_variant":[
        "\u0412\u043b\u0430\u0448\u043a\u043e \u041f\u043e\u0459\u0435"
    ],
    "wof:name":"Vlasko Polje",
    "wof:placetype":"locality"
},
  "geometry": {"coordinates":[22.07275,43.69968],"type":"Point"}
}