{
  "type": "Feature",
  "properties": {
    "gn:admin1_code":"SE",
    "gn:admin2_code":"16",
    "gn:asciiname":"Macevine",
    "gn:country_code":"RS",
    "gn:dem":400,
    "gn:feature_class":"P",
    "gn:feature_code":"PPL",
    "gn:name":"Ma\u0107evine",
    "gn:population":0,
    "gn:timezone":"Europe/Belgrade",
    "iso:country":"RS",
    "name:srp_x_preferred":[
        "Ma\u0107evine"
    ],
    "name:und_x_variant":[
        "Ma\u0107evina"
    ],
    "wof:name":"Macevine",
    "wof:placetype":"locality"
},
  "geometry": {"coordinates":[19.55351,43.95024],"type":"Point"}
}