{
  "type": "Feature",
  "properties": {
    "gn:admin1_code":"SE",
    "gn:admin2_code":"24",
    "gn:asciiname":"Visevce",
    "gn:country_code":"RS",
    "gn:dem":928,
    "gn:feature_class":"P",
    "gn:feature_code":"PPLL",
    "gn:name":"Vi\u0161evce",
    "gn:population":0,
    "gn:timezone":"Europe/Belgrade",
    "iso:country":"RS",
    "name:bul_x_preferred":[
        "\u0412\u0438\u0448\u0435\u0432\u0446\u0435"
    ],
    "name:fra_x_preferred":[
        "Vi\u0161evce"
    ],
    "name:msa_x_preferred":[
        "Vi\u0161evce"
    ],
    "name:por_x_preferred":[
        "Vi\u0161evce"
    ],
    "name:slv_x_preferred":[
        "Vi\u0161evce"
    ],
    "name:srp_x_preferred":[
        "Vi\u0161evce"
    ],
    "name:srp_x_variant":[
        "\u0412\u0438\u0448\u0435\u0432\u0446\u0435"
    ],
    "wof:name":"Visevce",
    "wof:placetype":"locality"
},
  "geometry": {"coordinates":[22.01637,42.47224],"type":"Point"}
}