{
  "type": "Feature",
  "properties": {
    "gn:admin1_code":"SE",
    "gn:admin2_code":"13",
    "gn:asciiname":"Bukovac",
    "gn:country_code":"RS",
    "gn:dem":215,
    "gn:feature_class":"P",
    "gn:feature_code":"PPL",
    "gn:name":"Bukovac",
    "gn:population":0,
    "gn:timezone":"Europe/Belgrade",
    "iso:country":"RS",
    "name:bos_x_preferred":[
        "Bukovac"
    ],
    "name:ceb_x_preferred":[
        "Bukovac"
    ],
    "name:deu_x_preferred":[
        "Bukovac"
    ],
    "name:fra_x_preferred":[
        "Bukovac"
    ],
    "name:hrv_x_preferred":[
        "Bukovac"
    ],
    "name:slv_x_preferred":[
        "Bukovac"
    ],
    "name:srp_x_preferred":[
        "Bukovac"
    ],
    "name:srp_x_variant":[
        "\u0411\u0443\u043a\u043e\u0432\u0430\u0446"
    ],
    "name:swe_x_preferred":[
        "Bukovac"
    ],
    "name:ukr_x_preferred":[
        "\u0411\u0443\u043a\u043e\u0432\u0430\u0446"
    ],
    "wof:name":"Bukovac",
    "wof:placetype":"locality"
},
  "geometry": {"coordinates":[21.47014,44.1173],"type":"Point"}
}