{
  "type": "Feature",
  "properties": {
    "gn:admin1_code":"SE",
    "gn:admin2_code":"11",
    "gn:asciiname":"Stamnica",
    "gn:country_code":"RS",
    "gn:dem":246,
    "gn:feature_class":"P",
    "gn:feature_code":"PPL",
    "gn:name":"Stamnica",
    "gn:population":0,
    "gn:timezone":"Europe/Belgrade",
    "iso:country":"RS",
    "name:ceb_x_preferred":[
        "Stamnica"
    ],
    "name:fra_x_preferred":[
        "Stamnica"
    ],
    "name:msa_x_preferred":[
        "Stamnica"
    ],
    "name:por_x_preferred":[
        "Stamnica"
    ],
    "name:slv_x_preferred":[
        "Stamnica"
    ],
    "name:srp_x_preferred":[
        "Stamnica"
    ],
    "name:srp_x_variant":[
        "\u0421\u0442\u0430\u043c\u043d\u0438\u0446\u0430"
    ],
    "wof:name":"Stamnica",
    "wof:placetype":"locality"
},
  "geometry": {"coordinates":[21.51857,44.355],"type":"Point"}
}