{
  "type": "Feature",
  "properties": {
    "gn:admin1_code":"SE",
    "gn:admin2_code":"22",
    "gn:asciiname":"Krupac",
    "gn:country_code":"RS",
    "gn:dem":396,
    "gn:feature_class":"P",
    "gn:feature_code":"PPL",
    "gn:name":"Krupac",
    "gn:population":0,
    "gn:timezone":"Europe/Belgrade",
    "iso:country":"RS",
    "name:srp_x_preferred":[
        "Krupac"
    ],
    "wof:name":"Krupac",
    "wof:placetype":"locality"
},
  "geometry": {"coordinates":[22.67236,43.12217],"type":"Point"}
}