{
  "type": "Feature",
  "properties": {
    "gn:admin1_code":"SE",
    "gn:admin2_code":"24",
    "gn:asciiname":"Velicovi",
    "gn:country_code":"RS",
    "gn:dem":1315,
    "gn:feature_class":"P",
    "gn:feature_code":"PPL",
    "gn:name":"Velicovi",
    "gn:population":0,
    "gn:timezone":"Europe/Belgrade",
    "iso:country":"RS",
    "name:und_x_variant":[
        "Veli\u010deva",
        "Velicovi"
    ],
    "wof:name":"Velicovi",
    "wof:placetype":"locality"
},
  "geometry": {"coordinates":[22.31562000000001,42.7067],"type":"Point"}
}