{
  "type": "Feature",
  "properties": {
    "gn:admin1_code":"SE",
    "gn:admin2_code":"16",
    "gn:asciiname":"Mijani",
    "gn:country_code":"RS",
    "gn:dem":875,
    "gn:feature_class":"P",
    "gn:feature_code":"PPL",
    "gn:name":"Mijani",
    "gn:population":0,
    "gn:timezone":"Europe/Belgrade",
    "iso:country":"RS",
    "name:fra_x_preferred":[
        "Mijani"
    ],
    "name:msa_x_preferred":[
        "Mijani"
    ],
    "name:nld_x_preferred":[
        "Mijani"
    ],
    "name:por_x_preferred":[
        "Mijani"
    ],
    "name:slv_x_preferred":[
        "Mijani"
    ],
    "name:srp_x_preferred":[
        "Mijani"
    ],
    "name:srp_x_variant":[
        "\u041c\u0438\u0458\u0430\u043d\u0438"
    ],
    "wof:name":"Mijani",
    "wof:placetype":"locality"
},
  "geometry": {"coordinates":[19.60987,43.32682],"type":"Point"}
}