{
  "type": "Feature",
  "properties": {
    "gn:admin1_code":"SE",
    "gn:admin2_code":"9",
    "gn:asciiname":"Tadici",
    "gn:country_code":"RS",
    "gn:dem":546,
    "gn:feature_class":"P",
    "gn:feature_code":"PPL",
    "gn:name":"Tadi\u0107i",
    "gn:population":0,
    "gn:timezone":"Europe/Belgrade",
    "iso:country":"RS",
    "name:srp_x_preferred":[
        "Tadi\u0107i"
    ],
    "wof:name":"Tadici",
    "wof:placetype":"locality"
},
  "geometry": {"coordinates":[19.44348,44.26183],"type":"Point"}
}