{
  "type": "Feature",
  "properties": {
    "gn:admin1_code":"SE",
    "gn:admin2_code":"17",
    "gn:asciiname":"Stranjanci",
    "gn:country_code":"RS",
    "gn:dem":646,
    "gn:feature_class":"P",
    "gn:feature_code":"PPL",
    "gn:name":"Stranjanci",
    "gn:population":0,
    "gn:timezone":"Europe/Belgrade",
    "iso:country":"RS",
    "wof:name":"Stranjanci",
    "wof:placetype":"locality"
},
  "geometry": {"coordinates":[20.34944,43.78333],"type":"Point"}
}