{
  "type": "Feature",
  "properties": {
    "gn:admin1_code":"SE",
    "gn:admin2_code":"0",
    "gn:asciiname":"Arnajevo",
    "gn:country_code":"RS",
    "gn:dem":173,
    "gn:feature_class":"P",
    "gn:feature_code":"PPL",
    "gn:name":"Arnajevo",
    "gn:population":0,
    "gn:timezone":"Europe/Belgrade",
    "iso:country":"RS",
    "name:srp_x_preferred":[
        "Arnajevo"
    ],
    "wof:name":"Arnajevo",
    "wof:placetype":"locality"
},
  "geometry": {"coordinates":[20.37571,44.4978],"type":"Point"}
}