{
  "type": "Feature",
  "properties": {
    "gn:admin1_code":"SE",
    "gn:admin2_code":"0",
    "gn:asciiname":"Arnajevo",
    "gn:country_code":"RS",
    "gn:dem":173,
    "gn:feature_class":"P",
    "gn:feature_code":"PPL",
    "gn:name":"Arnajevo",
    "gn:population":0,
    "gn:timezone":"Europe/Belgrade",
    "iso:country":"RS",
    "name:bul_x_preferred":[
        "\u0410\u0440\u043d\u0430\u0435\u0432\u043e"
    ],
    "name:ceb_x_preferred":[
        "Arnajevo"
    ],
    "name:fra_x_preferred":[
        "Arnajevo"
    ],
    "name:msa_x_preferred":[
        "Arnajevo"
    ],
    "name:nld_x_preferred":[
        "Arnajevo"
    ],
    "name:por_x_preferred":[
        "Arnajevo"
    ],
    "name:slv_x_preferred":[
        "Arnajevo"
    ],
    "name:sqi_x_preferred":[
        "Arnajevo"
    ],
    "name:srp_x_preferred":[
        "Arnajevo"
    ],
    "name:srp_x_variant":[
        "\u0410\u0440\u043d\u0430\u0458\u0435\u0432\u043e"
    ],
    "wof:name":"Arnajevo",
    "wof:placetype":"locality"
},
  "geometry": {"coordinates":[20.37571,44.4978],"type":"Point"}
}