{
  "type": "Feature",
  "properties": {
    "iso:country":"RS",
    "name:eng_x_preferred":[
        "Blok 59"
    ],
    "name:srp_cyr_x_preferred":[
        "\u0431\u043b\u043e\u043a 59"
    ],
    "name:srp_x_preferred":[
        "\u0431\u043b\u043e\u043a 59"
    ],
    "wof:name":"Blok 59",
    "wof:placetype":"neighbourhood"
},
  "geometry": {"coordinates":[20.37858492771262,44.81765284253527],"type":"Point"}
}