{
  "type": "Feature",
  "properties": {
    "gn:admin1_code":"SE",
    "gn:admin2_code":"19",
    "gn:asciiname":"Donja Zleginja",
    "gn:country_code":"RS",
    "gn:dem":257,
    "gn:feature_class":"P",
    "gn:feature_code":"PPL",
    "gn:name":"Donja Zleginja",
    "gn:population":0,
    "gn:timezone":"Europe/Belgrade",
    "iso:country":"RS",
    "name:srp_x_preferred":[
        "Donja Zleginja"
    ],
    "name:und_x_variant":[
        "Donja Zleginje"
    ],
    "wof:name":"Donja Zleginja",
    "wof:placetype":"locality"
},
  "geometry": {"coordinates":[21.16944,43.45164000000001],"type":"Point"}
}