{
  "type": "Feature",
  "properties": {
    "gn:admin1_code":"SE",
    "gn:admin2_code":"11",
    "gn:asciiname":"Branicevo",
    "gn:country_code":"RS",
    "gn:dem":79,
    "gn:feature_class":"P",
    "gn:feature_code":"PPL",
    "gn:name":"Brani\u010devo",
    "gn:population":0,
    "gn:timezone":"Europe/Belgrade",
    "iso:country":"RS",
    "name:ceb_x_preferred":[
        "Brani\u010devo"
    ],
    "name:fra_x_preferred":[
        "Brani\u010devo"
    ],
    "name:msa_x_preferred":[
        "Brani\u010devo"
    ],
    "name:por_x_preferred":[
        "Brani\u010devo"
    ],
    "name:slv_x_preferred":[
        "Brani\u010devo"
    ],
    "name:srp_x_preferred":[
        "Brani\u010devo"
    ],
    "name:srp_x_variant":[
        "\u0411\u0440\u0430\u043d\u0438\u0447\u0435\u0432\u043e"
    ],
    "wof:name":"Branicevo",
    "wof:placetype":"locality"
},
  "geometry": {"coordinates":[21.53833,44.705],"type":"Point"}
}