{
  "type": "Feature",
  "properties": {
    "gn:country":"RS",
    "gn:fcode":"PPL",
    "gn:pop":1550,
    "iso:country":"RS",
    "name:eng_x_preferred":[
        "Margita"
    ],
    "name:epo_x_preferred":[
        "Margita"
    ],
    "name:fra_x_preferred":[
        "Margita"
    ],
    "name:hun_x_preferred":[
        "Nagymargita"
    ],
    "name:msa_x_preferred":[
        "Margita"
    ],
    "name:nld_x_preferred":[
        "Margita"
    ],
    "name:ron_x_preferred":[
        "M\u0103rghita"
    ],
    "name:slv_x_preferred":[
        "Margita"
    ],
    "name:srp_x_preferred":[
        "Margita"
    ],
    "name:unk_x_variant":[
        "Gross-Margit"
    ],
    "qs:name":"Margita",
    "qs:photos_9r":0,
    "qs:photos_sr":0,
    "qs:pop_sr":"3",
    "wd:wordcount":23,
    "wof:name":"Margita",
    "wof:placetype":"locality",
    "wof:population":1550
},
  "geometry": {"coordinates":[21.17527,45.21598],"type":"Point"}
}