{
  "type": "Feature",
  "properties": {
    "gn:country":"RS",
    "gn:fcode":"PPL",
    "gn:population":1550,
    "iso:country":"RS",
    "name:ceb_x_preferred":[
        "Margita"
    ],
    "name:che_x_preferred":[
        "\u041c\u0430\u0440\u0433\u0438\u0442\u0430"
    ],
    "name:deu_x_preferred":[
        "Margita"
    ],
    "name:eng_x_preferred":[
        "Margita"
    ],
    "name:epo_x_preferred":[
        "Margita"
    ],
    "name:fas_x_preferred":[
        "\u0645\u0627\u0631\u06af\u06cc\u062a\u0627"
    ],
    "name:fra_x_preferred":[
        "Margita"
    ],
    "name:hun_x_preferred":[
        "Nagymargita"
    ],
    "name:msa_x_preferred":[
        "Margita"
    ],
    "name:nld_x_preferred":[
        "Margita"
    ],
    "name:pol_x_preferred":[
        "Margita"
    ],
    "name:ron_x_preferred":[
        "M\u0103rghita"
    ],
    "name:slv_x_preferred":[
        "Margita"
    ],
    "name:srp_x_preferred":[
        "Margita"
    ],
    "name:srp_x_variant":[
        "\u041c\u0430\u0440\u0433\u0438\u0442\u0430"
    ],
    "name:tat_x_preferred":[
        "\u041c\u0430\u0440\u0433\u0438\u0442\u0430"
    ],
    "name:und_x_variant":[
        "Gross-Margit"
    ],
    "qs:name":"Margita",
    "qs:photos_9r":0,
    "qs:photos_sr":0,
    "qs:pop_sr":"3",
    "wd:wordcount":23,
    "wof:name":"Margita",
    "wof:placetype":"locality",
    "wof:population":1550
},
  "geometry": {"coordinates":[21.17527,45.21598],"type":"Point"}
}