{
  "type": "Feature",
  "properties": {
    "gn:admin1_code":"SE",
    "gn:admin2_code":"20",
    "gn:asciiname":"Manastir",
    "gn:country_code":"RS",
    "gn:dem":414,
    "gn:feature_class":"P",
    "gn:feature_code":"PPL",
    "gn:name":"Manastir",
    "gn:population":0,
    "gn:timezone":"Europe/Belgrade",
    "iso:country":"RS",
    "name:srp_x_preferred":[
        "Manastir"
    ],
    "wof:name":"Manastir",
    "wof:placetype":"locality"
},
  "geometry": {"coordinates":[22.06191,43.32046],"type":"Point"}
}