{
  "type": "Feature",
  "properties": {
    "gn:country":"RS",
    "gn:fcode":"PPL",
    "gn:population":2536,
    "iso:country":"RS",
    "name:ceb_x_preferred":[
        "Gornji Breg"
    ],
    "name:eng_x_preferred":[
        "Gornji Breg"
    ],
    "name:epo_x_preferred":[
        "Gornji Breg"
    ],
    "name:fra_x_preferred":[
        "Gornji Breg"
    ],
    "name:hun_x_preferred":[
        "Fels\u0151hegy"
    ],
    "name:msa_x_preferred":[
        "Gornji Breg"
    ],
    "name:nld_x_preferred":[
        "Gornji Breg"
    ],
    "name:ron_x_preferred":[
        "Gornji Breg"
    ],
    "name:rus_x_preferred":[
        "\u0413\u043e\u0440\u043d\u0438-\u0411\u0440\u0435\u0433"
    ],
    "name:slv_x_preferred":[
        "Gornji Breg"
    ],
    "name:srp_x_preferred":[
        "Gornji Breg"
    ],
    "name:srp_x_variant":[
        "\u0413\u043e\u0440\u045a\u0438 \u0411\u0440\u0435\u0433"
    ],
    "name:ukr_x_preferred":[
        "\u0413\u043e\u0440\u043d\u0438\u0439 \u0411\u0440\u0435\u0433"
    ],
    "qs:name":"Gornji Breg",
    "qs:photos_9r":0,
    "qs:photos_sr":0,
    "qs:pop_sr":"4",
    "wd:wordcount":28,
    "wof:name":"Gornji Breg",
    "wof:placetype":"locality",
    "wof:population":2536
},
  "geometry": {"coordinates":[20.01766,45.91995],"type":"Point"}
}