{
  "type": "Feature",
  "properties": {
    "gn:admin1_code":"SE",
    "gn:admin2_code":"16",
    "gn:asciiname":"Raspogance",
    "gn:country_code":"RS",
    "gn:dem":1116,
    "gn:feature_class":"P",
    "gn:feature_code":"PPL",
    "gn:name":"Raspogan\u010de",
    "gn:population":0,
    "gn:timezone":"Europe/Belgrade",
    "iso:country":"RS",
    "name:srp_x_preferred":[
        "Raspogan\u010de"
    ],
    "wof:name":"Raspogance",
    "wof:placetype":"locality"
},
  "geometry": {"coordinates":[20.16603,43.2775],"type":"Point"}
}