{
  "type": "Feature",
  "properties": {
    "gn:admin1_code":"SE",
    "gn:admin2_code":"21",
    "gn:asciiname":"Donje Svarce",
    "gn:country_code":"RS",
    "gn:dem":363,
    "gn:feature_class":"P",
    "gn:feature_code":"PPL",
    "gn:name":"Donje Svar\u010de",
    "gn:population":0,
    "gn:timezone":"Europe/Belgrade",
    "iso:country":"RS",
    "name:ceb_x_preferred":[
        "Donje Svar\u010de"
    ],
    "name:fra_x_preferred":[
        "Donje Svar\u010de"
    ],
    "name:msa_x_preferred":[
        "Donje Svar\u010de"
    ],
    "name:por_x_preferred":[
        "Donje Svar\u010de"
    ],
    "name:slv_x_preferred":[
        "Donje Svar\u010de"
    ],
    "name:sqi_x_preferred":[
        "Sfar\u00e7a e Poshtme"
    ],
    "name:srp_x_preferred":[
        "Donje Svar\u010de"
    ],
    "name:srp_x_variant":[
        "\u0414\u043e\u045a\u0435 \u0421\u0432\u0430\u0440\u0447\u0435"
    ],
    "name:und_x_variant":[
        "Donja Svar\u010da"
    ],
    "wof:name":"Donje Svarce",
    "wof:placetype":"locality"
},
  "geometry": {"coordinates":[21.38195,43.28435],"type":"Point"}
}