{
  "type": "Feature",
  "properties": {
    "gn:admin1_code":"SE",
    "gn:admin2_code":"21",
    "gn:asciiname":"Donje Svarce",
    "gn:country_code":"RS",
    "gn:dem":363,
    "gn:feature_class":"P",
    "gn:feature_code":"PPL",
    "gn:name":"Donje Svar\u010de",
    "gn:population":0,
    "gn:timezone":"Europe/Belgrade",
    "iso:country":"RS",
    "name:srp_x_preferred":[
        "Donje Svar\u010de"
    ],
    "name:und_x_variant":[
        "Donja Svar\u010da"
    ],
    "wof:name":"Donje Svarce",
    "wof:placetype":"locality"
},
  "geometry": {"coordinates":[21.38195,43.28435],"type":"Point"}
}