{
  "type": "Feature",
  "properties": {
    "gn:admin1_code":"SE",
    "gn:admin2_code":"15",
    "gn:asciiname":"Gornje Zunice",
    "gn:country_code":"RS",
    "gn:dem":233,
    "gn:feature_class":"P",
    "gn:feature_code":"PPL",
    "gn:name":"Gornje Zuni\u010de",
    "gn:population":0,
    "gn:timezone":"Europe/Belgrade",
    "iso:country":"RS",
    "name:srp_x_preferred":[
        "Gornje Zuni\u010de"
    ],
    "wof:name":"Gornje Zunice",
    "wof:placetype":"locality"
},
  "geometry": {"coordinates":[22.2796,43.59973],"type":"Point"}
}