{
  "type": "Feature",
  "properties": {
    "gn:admin1_code":"SE",
    "gn:admin2_code":"15",
    "gn:asciiname":"Gornje Zunice",
    "gn:country_code":"RS",
    "gn:dem":233,
    "gn:feature_class":"P",
    "gn:feature_code":"PPL",
    "gn:name":"Gornje Zuni\u010de",
    "gn:population":0,
    "gn:timezone":"Europe/Belgrade",
    "iso:country":"RS",
    "name:ceb_x_preferred":[
        "Gornje Zuni\u010de"
    ],
    "name:fra_x_preferred":[
        "Gornje Zuni\u010de"
    ],
    "name:msa_x_preferred":[
        "Gornje Zuni\u010de"
    ],
    "name:por_x_preferred":[
        "Gornje Zuni\u010de"
    ],
    "name:slv_x_preferred":[
        "Gornje Zuni\u010de"
    ],
    "name:srp_x_preferred":[
        "Gornje Zuni\u010de"
    ],
    "name:srp_x_variant":[
        "\u0413\u043e\u0440\u045a\u0435 \u0417\u0443\u043d\u0438\u0447\u0435"
    ],
    "wof:name":"Gornje Zunice",
    "wof:placetype":"locality"
},
  "geometry": {"coordinates":[22.2796,43.59973],"type":"Point"}
}