{
  "type": "Feature",
  "properties": {
    "gn:admin1_code":"SE",
    "gn:admin2_code":"24",
    "gn:asciiname":"Dorinci",
    "gn:country_code":"RS",
    "gn:dem":1275,
    "gn:feature_class":"P",
    "gn:feature_code":"PPL",
    "gn:name":"\u00d0orinci",
    "gn:population":0,
    "gn:timezone":"Europe/Belgrade",
    "iso:country":"RS",
    "wof:name":"Dorinci",
    "wof:placetype":"locality"
},
  "geometry": {"coordinates":[22.13028,42.44889000000001],"type":"Point"}
}