{
  "type": "Feature",
  "properties": {
    "gn:admin1_code":"SE",
    "gn:admin2_code":"16",
    "gn:asciiname":"Kotline",
    "gn:country_code":"RS",
    "gn:dem":720,
    "gn:feature_class":"P",
    "gn:feature_code":"PPL",
    "gn:name":"Kotline",
    "gn:population":0,
    "gn:timezone":"Europe/Belgrade",
    "iso:country":"RS",
    "name:fra_x_preferred":[
        "Kotline"
    ],
    "name:ron_x_preferred":[
        "Kotline"
    ],
    "name:slv_x_preferred":[
        "Kotline"
    ],
    "name:srp_x_preferred":[
        "Kotline"
    ],
    "name:srp_x_variant":[
        "\u041a\u043e\u0442\u043b\u0438\u043d\u0435"
    ],
    "wof:name":"Kotline",
    "wof:placetype":"locality"
},
  "geometry": {"coordinates":[19.67543,43.24847000000001],"type":"Point"}
}