{
  "type": "Feature",
  "properties": {
    "gn:admin1_code":"SE",
    "gn:admin2_code":"10",
    "gn:asciiname":"Donja Raca",
    "gn:country_code":"RS",
    "gn:dem":137,
    "gn:feature_class":"P",
    "gn:feature_code":"PPL",
    "gn:name":"Donja Ra\u010da",
    "gn:population":0,
    "gn:timezone":"Europe/Belgrade",
    "iso:country":"RS",
    "name:srp_x_preferred":[
        "Donja Ra\u010da"
    ],
    "wof:name":"Donja Raca",
    "wof:placetype":"locality"
},
  "geometry": {"coordinates":[21.02563,44.22418],"type":"Point"}
}