{
  "type": "Feature",
  "properties": {
    "gn:admin1_code":"SE",
    "gn:admin2_code":"10",
    "gn:asciiname":"Donja Raca",
    "gn:country_code":"RS",
    "gn:dem":137,
    "gn:feature_class":"P",
    "gn:feature_code":"PPL",
    "gn:name":"Donja Ra\u010da",
    "gn:population":0,
    "gn:timezone":"Europe/Belgrade",
    "iso:country":"RS",
    "name:ceb_x_preferred":[
        "Donja Ra\u010da"
    ],
    "name:fra_x_preferred":[
        "Donja Ra\u010da"
    ],
    "name:msa_x_preferred":[
        "Donja Ra\u010da"
    ],
    "name:por_x_preferred":[
        "Donja Ra\u010da"
    ],
    "name:slv_x_preferred":[
        "Donja Ra\u010da"
    ],
    "name:srp_x_preferred":[
        "Donja Ra\u010da"
    ],
    "name:srp_x_variant":[
        "\u0414\u043e\u045a\u0430 \u0420\u0430\u0447\u0430"
    ],
    "wof:name":"Donja Raca",
    "wof:placetype":"locality"
},
  "geometry": {"coordinates":[21.02563,44.22418],"type":"Point"}
}