{
  "type": "Feature",
  "properties": {
    "gn:admin1_code":"SE",
    "gn:admin2_code":"9",
    "gn:asciiname":"Ivanovci",
    "gn:country_code":"RS",
    "gn:dem":184,
    "gn:feature_class":"P",
    "gn:feature_code":"PPL",
    "gn:name":"Ivanovci",
    "gn:population":0,
    "gn:timezone":"Europe/Belgrade",
    "iso:country":"RS",
    "name:srp_x_preferred":[
        "Ivanovci"
    ],
    "wof:name":"Ivanovci",
    "wof:placetype":"locality"
},
  "geometry": {"coordinates":[20.28931,44.22104],"type":"Point"}
}