{
  "type": "Feature",
  "properties": {
    "gn:admin1_code":"SE",
    "gn:admin2_code":"24",
    "gn:asciiname":"Partljevica",
    "gn:country_code":"RS",
    "gn:dem":1041,
    "gn:feature_class":"P",
    "gn:feature_code":"PPL",
    "gn:name":"Partljevica",
    "gn:population":0,
    "gn:timezone":"Europe/Belgrade",
    "iso:country":"RS",
    "wof:name":"Partljevica",
    "wof:placetype":"locality"
},
  "geometry": {"coordinates":[22.07024,42.49385],"type":"Point"}
}