{
  "type": "Feature",
  "properties": {
    "gn:admin1_code":"SE",
    "gn:admin2_code":"21",
    "gn:asciiname":"Besolica",
    "gn:country_code":"RS",
    "gn:dem":998,
    "gn:feature_class":"P",
    "gn:feature_code":"PPL",
    "gn:name":"Besolica",
    "gn:population":0,
    "gn:timezone":"Europe/Belgrade",
    "iso:country":"RS",
    "name:srp_x_preferred":[
        "Besolica"
    ],
    "wof:name":"Besolica",
    "wof:placetype":"locality"
},
  "geometry": {"coordinates":[21.15655,43.08812],"type":"Point"}
}