{
  "type": "Feature",
  "properties": {
    "gn:admin1_code":"SE",
    "gn:admin2_code":"11",
    "gn:asciiname":"Mrckovac",
    "gn:country_code":"RS",
    "gn:dem":201,
    "gn:feature_class":"P",
    "gn:feature_code":"PPL",
    "gn:name":"Mr\u010dkovac",
    "gn:population":0,
    "gn:timezone":"Europe/Belgrade",
    "iso:country":"RS",
    "name:srp_x_preferred":[
        "Mr\u010dkovac"
    ],
    "wof:name":"Mrckovac",
    "wof:placetype":"locality"
},
  "geometry": {"coordinates":[21.54129,44.61575],"type":"Point"}
}