{
  "type": "Feature",
  "properties": {
    "gn:admin1_code":"SE",
    "gn:admin2_code":"18",
    "gn:asciiname":"Keljevici",
    "gn:country_code":"RS",
    "gn:dem":1043,
    "gn:feature_class":"P",
    "gn:feature_code":"PPL",
    "gn:name":"Keljevi\u0107i",
    "gn:population":0,
    "gn:timezone":"Europe/Belgrade",
    "iso:country":"RS",
    "name:srp_x_preferred":[
        "Keljevi\u0107i"
    ],
    "wof:name":"Keljevici",
    "wof:placetype":"locality"
},
  "geometry": {"coordinates":[20.52194,43.00583],"type":"Point"}
}