{
  "type": "Feature",
  "properties": {
    "gn:admin1_code":"SE",
    "gn:admin2_code":"13",
    "gn:asciiname":"Vojska",
    "gn:country_code":"RS",
    "gn:dem":114,
    "gn:feature_class":"P",
    "gn:feature_code":"PPL",
    "gn:name":"Vojska",
    "gn:population":0,
    "gn:timezone":"Europe/Belgrade",
    "iso:country":"RS",
    "name:ceb_x_preferred":[
        "Vojska"
    ],
    "name:fas_x_preferred":[
        "\u0648\u0648\u06cc\u0633\u06a9\u0627"
    ],
    "name:fra_x_preferred":[
        "Vojska"
    ],
    "name:msa_x_preferred":[
        "Vojska"
    ],
    "name:por_x_preferred":[
        "Vojska"
    ],
    "name:slv_x_preferred":[
        "Vojska"
    ],
    "name:srp_x_preferred":[
        "Vojska"
    ],
    "name:srp_x_variant":[
        "\u0412\u043e\u0458\u0441\u043a\u0430"
    ],
    "wof:name":"Vojska",
    "wof:placetype":"locality"
},
  "geometry": {"coordinates":[21.21605,44.09086],"type":"Point"}
}