{
  "type": "Feature",
  "properties": {
    "gn:admin1_code":"SE",
    "gn:admin2_code":"13",
    "gn:asciiname":"Vojska",
    "gn:country_code":"RS",
    "gn:dem":114,
    "gn:feature_class":"P",
    "gn:feature_code":"PPL",
    "gn:name":"Vojska",
    "gn:population":0,
    "gn:timezone":"Europe/Belgrade",
    "iso:country":"RS",
    "name:srp_x_preferred":[
        "Vojska"
    ],
    "wof:name":"Vojska",
    "wof:placetype":"locality"
},
  "geometry": {"coordinates":[21.21605,44.09086],"type":"Point"}
}