{
  "type": "Feature",
  "properties": {
    "gn:admin1_code":"SE",
    "gn:admin2_code":"16",
    "gn:asciiname":"Kostici",
    "gn:country_code":"RS",
    "gn:dem":865,
    "gn:feature_class":"P",
    "gn:feature_code":"PPL",
    "gn:name":"Kosti\u0107i",
    "gn:population":0,
    "gn:timezone":"Europe/Belgrade",
    "iso:country":"RS",
    "wof:name":"Kostici",
    "wof:placetype":"locality"
},
  "geometry": {"coordinates":[19.66897,43.88172],"type":"Point"}
}