{
  "type": "Feature",
  "properties": {
    "gn:admin1_code":"SE",
    "gn:admin2_code":"8",
    "gn:asciiname":"Kovacevac",
    "gn:country_code":"RS",
    "gn:dem":293,
    "gn:feature_class":"P",
    "gn:feature_code":"PPL",
    "gn:name":"Kova\u010devac",
    "gn:population":0,
    "gn:timezone":"Europe/Belgrade",
    "iso:country":"RS",
    "name:srp_x_preferred":[
        "Kova\u010devac"
    ],
    "wof:name":"Kovacevac",
    "wof:placetype":"locality"
},
  "geometry": {"coordinates":[19.4493,44.3628],"type":"Point"}
}