{
  "type": "Feature",
  "properties": {
    "gn:admin1_code":"SE",
    "gn:admin2_code":"19",
    "gn:asciiname":"Boranci",
    "gn:country_code":"RS",
    "gn:dem":872,
    "gn:feature_class":"P",
    "gn:feature_code":"PPL",
    "gn:name":"Boranci",
    "gn:population":0,
    "gn:timezone":"Europe/Belgrade",
    "iso:country":"RS",
    "name:fra_x_preferred":[
        "Boranci"
    ],
    "name:hye_x_preferred":[
        "\u0532\u0578\u0580\u0561\u0576\u0581\u056b"
    ],
    "name:msa_x_preferred":[
        "Boranci"
    ],
    "name:nld_x_preferred":[
        "Boranci"
    ],
    "name:por_x_preferred":[
        "Boranci"
    ],
    "name:slv_x_preferred":[
        "Boranci"
    ],
    "name:spa_x_preferred":[
        "Boranci"
    ],
    "name:srp_x_preferred":[
        "Boranci"
    ],
    "name:srp_x_variant":[
        "\u0411\u043e\u0440\u0430\u043d\u0446\u0438"
    ],
    "name:und_x_variant":[
        "Borance"
    ],
    "wof:name":"Boranci",
    "wof:placetype":"locality"
},
  "geometry": {"coordinates":[20.91664,43.19849],"type":"Point"}
}