{
  "type": "Feature",
  "properties": {
    "gn:admin1_code":"SE",
    "gn:admin2_code":"19",
    "gn:asciiname":"Boranci",
    "gn:country_code":"RS",
    "gn:dem":872,
    "gn:feature_class":"P",
    "gn:feature_code":"PPL",
    "gn:name":"Boranci",
    "gn:population":0,
    "gn:timezone":"Europe/Belgrade",
    "iso:country":"RS",
    "name:srp_x_preferred":[
        "Boranci"
    ],
    "name:und_x_variant":[
        "Borance"
    ],
    "wof:name":"Boranci",
    "wof:placetype":"locality"
},
  "geometry": {"coordinates":[20.91664,43.19849],"type":"Point"}
}