{
  "type": "Feature",
  "properties": {
    "gn:admin1_code":"SE",
    "gn:admin2_code":"24",
    "gn:asciiname":"Begovi",
    "gn:country_code":"RS",
    "gn:dem":1307,
    "gn:feature_class":"P",
    "gn:feature_code":"PPL",
    "gn:name":"Begovi",
    "gn:population":0,
    "gn:timezone":"Europe/Belgrade",
    "iso:country":"RS",
    "name:und_x_variant":[
        "Begovi Mahala",
        "Begovi"
    ],
    "wof:name":"Begovi",
    "wof:placetype":"locality"
},
  "geometry": {"coordinates":[22.29316,42.71085],"type":"Point"}
}