{
  "type": "Feature",
  "properties": {
    "gn:admin1_code":"SE",
    "gn:admin2_code":"20",
    "gn:admin3_code":"70025.0",
    "gn:asciiname":"Zitkovac",
    "gn:country_code":"RS",
    "gn:dem":168,
    "gn:feature_class":"P",
    "gn:feature_code":"PPL",
    "gn:name":"\u017ditkovac",
    "gn:population":0,
    "gn:timezone":"Europe/Belgrade",
    "iso:country":"RS",
    "name:ceb_x_preferred":[
        "\u017ditkovac"
    ],
    "name:fra_x_preferred":[
        "\u017ditkovac"
    ],
    "name:hrv_x_preferred":[
        "\u017ditkovac"
    ],
    "name:msa_x_preferred":[
        "\u017ditkovac"
    ],
    "name:nld_x_preferred":[
        "\u017ditkovac"
    ],
    "name:por_x_preferred":[
        "\u017ditkovac"
    ],
    "name:slv_x_preferred":[
        "\u017ditkovac"
    ],
    "name:srp_x_preferred":[
        "\u017ditkovac"
    ],
    "name:srp_x_variant":[
        "\u0416\u0438\u0442\u043a\u043e\u0432\u0430\u0446"
    ],
    "wof:name":"Zitkovac",
    "wof:placetype":"locality"
},
  "geometry": {"coordinates":[21.69234,43.51144],"type":"Point"}
}