{
  "type": "Feature",
  "properties": {
    "gn:admin1_code":"SE",
    "gn:admin2_code":"16",
    "gn:asciiname":"Loret",
    "gn:country_code":"RS",
    "gn:dem":659,
    "gn:feature_class":"P",
    "gn:feature_code":"PPL",
    "gn:name":"Loret",
    "gn:population":0,
    "gn:timezone":"Europe/Belgrade",
    "iso:country":"RS",
    "name:fra_x_preferred":[
        "Loret"
    ],
    "name:msa_x_preferred":[
        "Loret"
    ],
    "name:nld_x_preferred":[
        "Loret"
    ],
    "name:por_x_preferred":[
        "Loret"
    ],
    "name:slv_x_preferred":[
        "Loret"
    ],
    "name:srp_x_preferred":[
        "Loret"
    ],
    "name:srp_x_variant":[
        "\u041b\u043e\u0440\u0435\u0442"
    ],
    "wof:name":"Loret",
    "wof:placetype":"locality"
},
  "geometry": {"coordinates":[20.06075,43.89823],"type":"Point"}
}