{
  "type": "Feature",
  "properties": {
    "gn:admin1_code":"SE",
    "gn:admin2_code":"8",
    "gn:asciiname":"Tomici",
    "gn:country_code":"RS",
    "gn:dem":158,
    "gn:feature_class":"P",
    "gn:feature_code":"PPL",
    "gn:name":"Tomi\u0107i",
    "gn:population":0,
    "gn:timezone":"Europe/Belgrade",
    "iso:country":"RS",
    "name:srp_x_preferred":[
        "Tomi\u0107i"
    ],
    "wof:name":"Tomici",
    "wof:placetype":"locality"
},
  "geometry": {"coordinates":[19.36016,44.5141],"type":"Point"}
}