{
  "type": "Feature",
  "properties": {
    "gn:admin1_code":"SE",
    "gn:admin2_code":"18",
    "gn:asciiname":"Cvijetnje",
    "gn:country_code":"RS",
    "gn:dem":712,
    "gn:feature_class":"P",
    "gn:feature_code":"PPL",
    "gn:name":"Cvijetnje",
    "gn:population":0,
    "gn:timezone":"Europe/Belgrade",
    "iso:country":"RS",
    "name:srp_x_preferred":[
        "Cvijetnje"
    ],
    "wof:name":"Cvijetnje",
    "wof:placetype":"locality"
},
  "geometry": {"coordinates":[20.52142000000001,43.10329],"type":"Point"}
}