{
  "type": "Feature",
  "properties": {
    "gn:admin1_code":"SE",
    "gn:admin2_code":"18",
    "gn:asciiname":"Becvari",
    "gn:country_code":"RS",
    "gn:dem":702,
    "gn:feature_class":"P",
    "gn:feature_code":"PPL",
    "gn:name":"Be\u010dvari",
    "gn:population":0,
    "gn:timezone":"Europe/Belgrade",
    "iso:country":"RS",
    "name:srp_x_preferred":[
        "Be\u010dvari"
    ],
    "wof:name":"Becvari",
    "wof:placetype":"locality"
},
  "geometry": {"coordinates":[20.55728,43.38175],"type":"Point"}
}