{
  "type": "Feature",
  "properties": {
    "gn:admin1_code":"SE",
    "gn:admin2_code":"22",
    "gn:asciiname":"Vlasi",
    "gn:country_code":"RS",
    "gn:dem":520,
    "gn:feature_class":"P",
    "gn:feature_code":"PPL",
    "gn:name":"Vlasi",
    "gn:population":0,
    "gn:timezone":"Europe/Belgrade",
    "iso:country":"RS",
    "name:bul_x_preferred":[
        "\u0412\u043b\u0430\u0441\u0438"
    ],
    "name:fra_x_preferred":[
        "Vlasi"
    ],
    "name:msa_x_preferred":[
        "Vlasi"
    ],
    "name:por_x_preferred":[
        "Vlasi"
    ],
    "name:slv_x_preferred":[
        "Vlasi"
    ],
    "name:srp_x_preferred":[
        "Vlasi"
    ],
    "name:srp_x_variant":[
        "\u0412\u043b\u0430\u0441\u0438"
    ],
    "wof:name":"Vlasi",
    "wof:placetype":"locality"
},
  "geometry": {"coordinates":[22.63173,42.99733],"type":"Point"}
}