{
  "type": "Feature",
  "properties": {
    "gn:admin1_code":"SE",
    "gn:admin2_code":"17",
    "gn:asciiname":"Martinovici",
    "gn:country_code":"RS",
    "gn:dem":1218,
    "gn:feature_class":"P",
    "gn:feature_code":"PPLL",
    "gn:name":"Martinovi\u0107i",
    "gn:population":0,
    "gn:timezone":"Europe/Belgrade",
    "iso:country":"RS",
    "name:srp_x_preferred":[
        "Martinovi\u0107i"
    ],
    "wof:name":"Martinovici",
    "wof:placetype":"locality"
},
  "geometry": {"coordinates":[20.10752,43.38471],"type":"Point"}
}