{
  "type": "Feature",
  "properties": {
    "gn:admin1_code":"SE",
    "gn:admin2_code":"21",
    "gn:asciiname":"Gornja Mala",
    "gn:country_code":"RS",
    "gn:dem":354,
    "gn:feature_class":"P",
    "gn:feature_code":"PPL",
    "gn:name":"Gornja Mala",
    "gn:population":0,
    "gn:timezone":"Europe/Belgrade",
    "iso:country":"RS",
    "wof:name":"Gornja Mala",
    "wof:placetype":"locality"
},
  "geometry": {"coordinates":[21.37028,43.17944],"type":"Point"}
}