{
  "type": "Feature",
  "properties": {
    "gn:admin1_code":"SE",
    "gn:admin2_code":"20",
    "gn:asciiname":"Donja Toponica",
    "gn:country_code":"RS",
    "gn:dem":177,
    "gn:feature_class":"P",
    "gn:feature_code":"PPL",
    "gn:name":"Donja Toponica",
    "gn:population":0,
    "gn:timezone":"Europe/Belgrade",
    "iso:country":"RS",
    "name:srp_x_preferred":[
        "Donja Toponica"
    ],
    "wof:name":"Donja Toponica",
    "wof:placetype":"locality"
},
  "geometry": {"coordinates":[21.78562,43.41334000000001],"type":"Point"}
}