{
  "type": "Feature",
  "properties": {
    "gn:admin1_code":"SE",
    "gn:admin2_code":"16",
    "gn:asciiname":"Prisoje",
    "gn:country_code":"RS",
    "gn:dem":807,
    "gn:feature_class":"P",
    "gn:feature_code":"PPL",
    "gn:name":"Prisoje",
    "gn:population":0,
    "gn:timezone":"Europe/Belgrade",
    "iso:country":"RS",
    "wof:name":"Prisoje",
    "wof:placetype":"locality"
},
  "geometry": {"coordinates":[19.76528,43.46333],"type":"Point"}
}