{
  "type": "Feature",
  "properties": {
    "gn:admin1_code":"SE",
    "gn:admin2_code":"20",
    "gn:asciiname":"Maletina",
    "gn:country_code":"RS",
    "gn:dem":164,
    "gn:feature_class":"P",
    "gn:feature_code":"PPL",
    "gn:name":"Maletina",
    "gn:population":0,
    "gn:timezone":"Europe/Belgrade",
    "iso:country":"RS",
    "name:ceb_x_preferred":[
        "Maletina"
    ],
    "name:fra_x_preferred":[
        "Maletina"
    ],
    "name:msa_x_preferred":[
        "Maletina"
    ],
    "name:por_x_preferred":[
        "Maletina"
    ],
    "name:slv_x_preferred":[
        "Maletina"
    ],
    "name:srp_x_preferred":[
        "Maletina"
    ],
    "name:srp_x_variant":[
        "\u041c\u0430\u043b\u0435\u0442\u0438\u043d\u0430"
    ],
    "wof:name":"Maletina",
    "wof:placetype":"locality"
},
  "geometry": {"coordinates":[21.49763,43.61625],"type":"Point"}
}