{
  "type": "Feature",
  "properties": {
    "gn:admin1_code":"SE",
    "gn:admin2_code":"15",
    "gn:asciiname":"Mala Jasikova",
    "gn:country_code":"RS",
    "gn:dem":341,
    "gn:feature_class":"P",
    "gn:feature_code":"PPL",
    "gn:name":"Mala Jasikova",
    "gn:population":0,
    "gn:timezone":"Europe/Belgrade",
    "iso:country":"RS",
    "name:ceb_x_preferred":[
        "Mala Jasikova"
    ],
    "name:fra_x_preferred":[
        "Mala Jasikova"
    ],
    "name:msa_x_preferred":[
        "Mala Jasikova"
    ],
    "name:por_x_preferred":[
        "Mala Jasikova"
    ],
    "name:slv_x_preferred":[
        "Mala Jasikova"
    ],
    "name:srp_x_preferred":[
        "Mala Jasikova"
    ],
    "name:srp_x_variant":[
        "\u041c\u0430\u043b\u0430 \u0408\u0430\u0441\u0438\u043a\u043e\u0432\u0430"
    ],
    "wof:name":"Mala Jasikova",
    "wof:placetype":"locality"
},
  "geometry": {"coordinates":[22.30945,44.08404],"type":"Point"}
}