{
  "type": "Feature",
  "properties": {
    "gn:admin1_code":"SE",
    "gn:admin2_code":"16",
    "gn:asciiname":"Dolovi",
    "gn:country_code":"RS",
    "gn:dem":1143,
    "gn:feature_class":"P",
    "gn:feature_code":"PPL",
    "gn:name":"Dolovi",
    "gn:population":0,
    "gn:timezone":"Europe/Belgrade",
    "iso:country":"RS",
    "wof:name":"Dolovi",
    "wof:placetype":"locality"
},
  "geometry": {"coordinates":[19.60389,43.27639],"type":"Point"}
}