{
  "type": "Feature",
  "properties": {
    "gn:admin1_code":"SE",
    "gn:admin2_code":"16",
    "gn:asciiname":"Paramun",
    "gn:country_code":"RS",
    "gn:dem":753,
    "gn:feature_class":"P",
    "gn:feature_code":"PPL",
    "gn:name":"Paramun",
    "gn:population":0,
    "gn:timezone":"Europe/Belgrade",
    "iso:country":"RS",
    "name:bul_x_preferred":[
        "\u041f\u0430\u0440\u0430\u043c\u0443\u043d"
    ],
    "name:fas_x_preferred":[
        "\u067e\u0627\u0631\u0627\u0645\u0648\u0646"
    ],
    "name:fra_x_preferred":[
        "Paramun"
    ],
    "name:kat_x_preferred":[
        "\u10de\u10d0\u10e0\u10d0\u10db\u10e3\u10dc\u10d8"
    ],
    "name:kaz_x_preferred":[
        "\u041f\u0430\u0440\u0430\u043c\u0443\u043d"
    ],
    "name:msa_x_preferred":[
        "Paramun"
    ],
    "name:nld_x_preferred":[
        "Paramun"
    ],
    "name:por_x_preferred":[
        "Paramun"
    ],
    "name:ron_x_preferred":[
        "Paramun"
    ],
    "name:rus_x_preferred":[
        "\u041f\u0430\u0440\u0430\u043c\u0443\u043d"
    ],
    "name:slv_x_preferred":[
        "Paramun"
    ],
    "name:srp_x_preferred":[
        "\u041f\u0430\u0440\u0430\u043c\u0443\u043d"
    ],
    "name:ukr_x_preferred":[
        "\u041f\u0430\u0440\u0430\u043c\u0443\u043d"
    ],
    "name:und_x_variant":[
        "Paramum",
        "Paramun"
    ],
    "wof:name":"Paramun",
    "wof:placetype":"locality"
},
  "geometry": {"coordinates":[19.82803,44.05714],"type":"Point"}
}