{
  "type": "Feature",
  "properties": {
    "gn:admin1_code":"SE",
    "gn:admin2_code":"0",
    "gn:asciiname":"Mali Mokri Lug",
    "gn:country_code":"RS",
    "gn:dem":217,
    "gn:feature_class":"P",
    "gn:feature_code":"PPL",
    "gn:name":"Mali Mokri Lug",
    "gn:population":0,
    "gn:timezone":"Europe/Belgrade",
    "iso:country":"RS",
    "name:srp_x_preferred":[
        "Mali Mokri Lug"
    ],
    "name:und_x_variant":[
        "Mokri Lug"
    ],
    "wof:name":"Mali Mokri Lug",
    "wof:placetype":"neighbourhood"
},
  "geometry": {"coordinates":[20.5283,44.77726],"type":"Point"}
}