{
  "type": "Feature",
  "properties": {
    "gn:admin1_code":"SE",
    "gn:admin2_code":"16",
    "gn:asciiname":"Cestobrodica",
    "gn:country_code":"RS",
    "gn:dem":534,
    "gn:feature_class":"P",
    "gn:feature_code":"PPLL",
    "gn:name":"\u010cestobrodica",
    "gn:population":0,
    "gn:timezone":"Europe/Belgrade",
    "iso:country":"RS",
    "name:srp_x_preferred":[
        "\u010cestobrodica"
    ],
    "name:und_x_variant":[
        "\u010cestobradica"
    ],
    "wof:name":"Cestobrodica",
    "wof:placetype":"locality"
},
  "geometry": {"coordinates":[20.01601,43.91792],"type":"Point"}
}