{
  "type": "Feature",
  "properties": {
    "gn:admin1_code":"SE",
    "gn:admin2_code":"16",
    "gn:asciiname":"Cestobrodica",
    "gn:country_code":"RS",
    "gn:dem":534,
    "gn:feature_class":"P",
    "gn:feature_code":"PPLL",
    "gn:name":"\u010cestobrodica",
    "gn:population":0,
    "gn:timezone":"Europe/Belgrade",
    "iso:country":"RS",
    "name:ceb_x_preferred":[
        "\u010cestobrodica"
    ],
    "name:deu_x_preferred":[
        "\u010cestobrodica"
    ],
    "name:fra_x_preferred":[
        "\u010cestobrodica"
    ],
    "name:msa_x_preferred":[
        "\u010cestobrodica"
    ],
    "name:nld_x_preferred":[
        "\u010cestobrodica"
    ],
    "name:por_x_preferred":[
        "\u010cestobrodica"
    ],
    "name:slv_x_preferred":[
        "\u010cestobrodica"
    ],
    "name:srp_x_preferred":[
        "\u010cestobrodica"
    ],
    "name:srp_x_variant":[
        "\u0427\u0435\u0441\u0442\u043e\u0431\u0440\u043e\u0434\u0438\u0446\u0430"
    ],
    "name:und_x_variant":[
        "\u010cestobradica"
    ],
    "wof:name":"Cestobrodica",
    "wof:placetype":"locality"
},
  "geometry": {"coordinates":[20.01601,43.91792],"type":"Point"}
}