{
  "type": "Feature",
  "properties": {
    "iso:country":"RS",
    "name:eng_x_preferred":[
        "Crveni Barjak"
    ],
    "name:srp_cyr_x_preferred":[
        "\u0426\u0440\u0432\u0435\u043d\u0438 \u0411\u0430\u0440\u0458\u0430\u043a"
    ],
    "name:srp_x_preferred":[
        "\u0426\u0440\u0432\u0435\u043d\u0438 \u0411\u0430\u0440\u0458\u0430\u043a"
    ],
    "wof:name":"Crveni Barjak",
    "wof:placetype":"neighbourhood"
},
  "geometry": {"coordinates":[20.29176714263591,44.8964644225938],"type":"Point"}
}