{
  "type": "Feature",
  "properties": {
    "gn:admin1_code":"SE",
    "gn:admin2_code":"18",
    "gn:asciiname":"Trnavci",
    "gn:country_code":"RS",
    "gn:dem":644,
    "gn:feature_class":"P",
    "gn:feature_code":"PPL",
    "gn:name":"Trnavci",
    "gn:population":0,
    "gn:timezone":"Europe/Belgrade",
    "iso:country":"RS",
    "name:ceb_x_preferred":[
        "Trnavci"
    ],
    "name:fra_x_preferred":[
        "Trnavci"
    ],
    "name:hye_x_preferred":[
        "\u054f\u0580\u0576\u0561\u057e\u0581\u056b"
    ],
    "name:msa_x_preferred":[
        "Trnavci"
    ],
    "name:nld_x_preferred":[
        "Trnavci"
    ],
    "name:por_x_preferred":[
        "Trnavci"
    ],
    "name:slv_x_preferred":[
        "Trnavci"
    ],
    "name:spa_x_preferred":[
        "Trnavci"
    ],
    "name:srp_x_preferred":[
        "Trnavci"
    ],
    "name:srp_x_variant":[
        "\u0422\u0440\u043d\u0430\u0432\u0446\u0438"
    ],
    "wof:name":"Trnavci",
    "wof:placetype":"locality"
},
  "geometry": {"coordinates":[20.55611,43.18891],"type":"Point"}
}