{
  "type": "Feature",
  "properties": {
    "gn:admin1_code":"SE",
    "gn:admin2_code":"18",
    "gn:asciiname":"Trnavci",
    "gn:country_code":"RS",
    "gn:dem":644,
    "gn:feature_class":"P",
    "gn:feature_code":"PPL",
    "gn:name":"Trnavci",
    "gn:population":0,
    "gn:timezone":"Europe/Belgrade",
    "iso:country":"RS",
    "name:srp_x_preferred":[
        "Trnavci"
    ],
    "wof:name":"Trnavci",
    "wof:placetype":"locality"
},
  "geometry": {"coordinates":[20.55611,43.18891],"type":"Point"}
}