{
  "type": "Feature",
  "properties": {
    "gn:admin1_code":"SE",
    "gn:admin2_code":"18",
    "gn:asciiname":"Prcenova",
    "gn:country_code":"RS",
    "gn:dem":731,
    "gn:feature_class":"P",
    "gn:feature_code":"PPLL",
    "gn:name":"Pr\u0107enova",
    "gn:population":0,
    "gn:timezone":"Europe/Belgrade",
    "iso:country":"RS",
    "name:srp_x_preferred":[
        "Pr\u0107enova"
    ],
    "name:und_x_variant":[
        "Pr\u010danova"
    ],
    "wof:name":"Prcenova",
    "wof:placetype":"locality"
},
  "geometry": {"coordinates":[20.51064,43.18314],"type":"Point"}
}