{
  "type": "Feature",
  "properties": {
    "gn:admin1_code":"SE",
    "gn:admin2_code":"13",
    "gn:asciiname":"Kupinovac",
    "gn:country_code":"RS",
    "gn:dem":166,
    "gn:feature_class":"P",
    "gn:feature_code":"PPL",
    "gn:name":"Kupinovac",
    "gn:population":0,
    "gn:timezone":"Europe/Belgrade",
    "iso:country":"RS",
    "name:bos_x_preferred":[
        "Kupinovac"
    ],
    "name:ceb_x_preferred":[
        "Kupinovac"
    ],
    "name:hrv_x_preferred":[
        "Kupinovac"
    ],
    "name:hun_x_preferred":[
        "Kupinovac"
    ],
    "name:msa_x_preferred":[
        "Kupinovac"
    ],
    "name:nld_x_preferred":[
        "Kupinovac"
    ],
    "name:slv_x_preferred":[
        "Kupinovac"
    ],
    "name:spa_x_preferred":[
        "Kupinovac"
    ],
    "name:srp_x_preferred":[
        "Kupinovac"
    ],
    "name:srp_x_variant":[
        "\u041a\u0443\u043f\u0438\u043d\u043e\u0432\u0430\u0446"
    ],
    "name:swe_x_preferred":[
        "Kupinovac"
    ],
    "name:ukr_x_preferred":[
        "\u041a\u0443\u043f\u0438\u043d\u043e\u0432\u0430\u0446\u044c"
    ],
    "wof:name":"Kupinovac",
    "wof:placetype":"locality"
},
  "geometry": {"coordinates":[21.33036,44.20838],"type":"Point"}
}