{
  "type": "Feature",
  "properties": {
    "gn:admin1_code":"SE",
    "gn:admin2_code":"13",
    "gn:asciiname":"Kupinovac",
    "gn:country_code":"RS",
    "gn:dem":166,
    "gn:feature_class":"P",
    "gn:feature_code":"PPL",
    "gn:name":"Kupinovac",
    "gn:population":0,
    "gn:timezone":"Europe/Belgrade",
    "iso:country":"RS",
    "name:srp_x_preferred":[
        "Kupinovac"
    ],
    "wof:name":"Kupinovac",
    "wof:placetype":"locality"
},
  "geometry": {"coordinates":[21.33036,44.20838],"type":"Point"}
}