{
  "type": "Feature",
  "properties": {
    "gn:country":"RS",
    "gn:fcode":"PPL",
    "gn:population":5,
    "iso:country":"RS",
    "qs:name":"\u00d0ur\u0111i\u0107i",
    "qs:photos_9r":0,
    "qs:photos_sr":0,
    "qs:pop_sr":"1",
    "wof:name":"\u00d0ur\u0111i\u0107i",
    "wof:placetype":"locality",
    "wof:population":5
},
  "geometry": {"coordinates":[20.8496,43.65746],"type":"Point"}
}