{
  "type": "Feature",
  "properties": {
    "gn:admin1_code":"SE",
    "gn:admin2_code":"16",
    "gn:asciiname":"Pridoli",
    "gn:country_code":"RS",
    "gn:dem":611,
    "gn:feature_class":"P",
    "gn:feature_code":"PPL",
    "gn:name":"Pridoli",
    "gn:population":0,
    "gn:timezone":"Europe/Belgrade",
    "iso:country":"RS",
    "name:srp_x_preferred":[
        "Pridoli"
    ],
    "wof:name":"Pridoli",
    "wof:placetype":"locality"
},
  "geometry": {"coordinates":[19.62851,43.97801],"type":"Point"}
}