{
  "type": "Feature",
  "properties": {
    "gn:admin1_code":"SE",
    "gn:admin2_code":"12",
    "gn:asciiname":"Belosevac",
    "gn:country_code":"RS",
    "gn:dem":216,
    "gn:feature_class":"P",
    "gn:feature_code":"PPLL",
    "gn:name":"Belo\u0161evac",
    "gn:population":0,
    "gn:timezone":"Europe/Belgrade",
    "iso:country":"RS",
    "wof:name":"Belosevac",
    "wof:placetype":"locality"
},
  "geometry": {"coordinates":[20.92801,43.98496],"type":"Point"}
}