{
  "type": "Feature",
  "properties": {
    "gn:admin1_code":"SE",
    "gn:admin2_code":"18",
    "gn:asciiname":"Stupnicani",
    "gn:country_code":"RS",
    "gn:dem":583,
    "gn:feature_class":"P",
    "gn:feature_code":"PPL",
    "gn:name":"Stupni\u010dani",
    "gn:population":0,
    "gn:timezone":"Europe/Belgrade",
    "iso:country":"RS",
    "name:srp_x_preferred":[
        "Stupni\u010dani"
    ],
    "wof:name":"Stupnicani",
    "wof:placetype":"locality"
},
  "geometry": {"coordinates":[20.58333,43.33722],"type":"Point"}
}