{
  "type": "Feature",
  "properties": {
    "gn:admin1_code":"VO",
    "gn:admin2_code":"1",
    "gn:asciiname":"Pavlovac",
    "gn:country_code":"RS",
    "gn:dem":111,
    "gn:feature_class":"P",
    "gn:feature_code":"PPL",
    "gn:name":"Pavlovac",
    "gn:population":0,
    "gn:timezone":"Europe/Belgrade",
    "iso:country":"RS",
    "name:bos_x_preferred":[
        "Pavlovac"
    ],
    "name:ceb_x_preferred":[
        "Pavlovac"
    ],
    "name:fra_x_preferred":[
        "Pavlovac"
    ],
    "name:hrv_x_preferred":[
        "Pavlovac"
    ],
    "name:hun_x_preferred":[
        "Pavlovac"
    ],
    "name:nld_x_preferred":[
        "Pavlovac"
    ],
    "name:rus_x_preferred":[
        "\u041f\u0430\u0432\u043b\u043e\u0432\u0430\u0446"
    ],
    "name:slv_x_preferred":[
        "Pavlovac"
    ],
    "name:spa_x_preferred":[
        "Pavlovac"
    ],
    "name:srp_x_preferred":[
        "Pavlovac"
    ],
    "name:srp_x_variant":[
        "\u041f\u0430\u0432\u043b\u043e\u0432\u0430\u0446"
    ],
    "name:swe_x_preferred":[
        "Pavlovac"
    ],
    "wof:name":"Pavlovac",
    "wof:placetype":"locality"
},
  "geometry": {"coordinates":[19.53674,45.99066],"type":"Point"}
}