{
  "type": "Feature",
  "properties": {
    "gn:admin1_code":"SE",
    "gn:admin2_code":"8",
    "gn:asciiname":"Mitrovici",
    "gn:country_code":"RS",
    "gn:dem":113,
    "gn:feature_class":"P",
    "gn:feature_code":"PPL",
    "gn:name":"Mitrovi\u0107i",
    "gn:population":0,
    "gn:timezone":"Europe/Belgrade",
    "iso:country":"RS",
    "name:srp_x_preferred":[
        "Mitrovi\u0107i"
    ],
    "wof:name":"Mitrovici",
    "wof:placetype":"locality"
},
  "geometry": {"coordinates":[19.3034,44.59686],"type":"Point"}
}