{
  "type": "Feature",
  "properties": {
    "gn:admin1_code":"SE",
    "gn:admin2_code":"21",
    "gn:asciiname":"Ljutova",
    "gn:country_code":"RS",
    "gn:dem":778,
    "gn:feature_class":"P",
    "gn:feature_code":"PPL",
    "gn:name":"Ljutova",
    "gn:population":0,
    "gn:timezone":"Europe/Belgrade",
    "iso:country":"RS",
    "name:bul_x_preferred":[
        "\u041b\u044e\u0442\u043e\u0432\u0430"
    ],
    "name:fra_x_preferred":[
        "Ljutova"
    ],
    "name:msa_x_preferred":[
        "Ljutova"
    ],
    "name:por_x_preferred":[
        "Ljutova"
    ],
    "name:slv_x_preferred":[
        "Ljutova"
    ],
    "name:srp_x_preferred":[
        "Ljutova"
    ],
    "name:srp_x_variant":[
        "\u0409\u0443\u0442\u043e\u0432\u0430"
    ],
    "wof:name":"Ljutova",
    "wof:placetype":"locality"
},
  "geometry": {"coordinates":[21.0938,43.18297000000001],"type":"Point"}
}