{
  "type": "Feature",
  "properties": {
    "gn:admin1_code":"SE",
    "gn:admin2_code":"19",
    "gn:asciiname":"Markovina",
    "gn:country_code":"RS",
    "gn:dem":370,
    "gn:feature_class":"P",
    "gn:feature_code":"PPL",
    "gn:name":"Markovina",
    "gn:population":0,
    "gn:timezone":"Europe/Belgrade",
    "iso:country":"RS",
    "name:srp_x_preferred":[
        "Markovina"
    ],
    "wof:name":"Markovina",
    "wof:placetype":"locality"
},
  "geometry": {"coordinates":[21.07664,43.46726],"type":"Point"}
}