{
  "type": "Feature",
  "properties": {
    "gn:admin1_code":"SE",
    "gn:admin2_code":"20",
    "gn:asciiname":"Locika",
    "gn:country_code":"RS",
    "gn:dem":215,
    "gn:feature_class":"P",
    "gn:feature_code":"PPL",
    "gn:name":"Lo\u0107ika",
    "gn:population":0,
    "gn:timezone":"Europe/Belgrade",
    "iso:country":"RS",
    "name:srp_x_preferred":[
        "Lo\u0107ika"
    ],
    "wof:name":"Locika",
    "wof:placetype":"locality"
},
  "geometry": {"coordinates":[21.69927,43.43855],"type":"Point"}
}