{
  "type": "Feature",
  "properties": {
    "gn:admin1_code":"SE",
    "gn:admin2_code":"24",
    "gn:asciiname":"Bistar",
    "gn:country_code":"RS",
    "gn:dem":849,
    "gn:feature_class":"P",
    "gn:feature_code":"PPL",
    "gn:name":"Bistar",
    "gn:population":0,
    "gn:timezone":"Europe/Belgrade",
    "iso:country":"RS",
    "name:bul_x_preferred":[
        "\u0411\u0438\u0441\u0442\u044a\u0440"
    ],
    "name:ceb_x_preferred":[
        "Bistar"
    ],
    "name:fra_x_preferred":[
        "Bistar"
    ],
    "name:hun_x_preferred":[
        "Bistar"
    ],
    "name:msa_x_preferred":[
        "Bistar"
    ],
    "name:nld_x_preferred":[
        "Bistar"
    ],
    "name:por_x_preferred":[
        "Bistar"
    ],
    "name:slv_x_preferred":[
        "Bistar"
    ],
    "name:srp_x_preferred":[
        "Bistar"
    ],
    "name:srp_x_variant":[
        "\u0411\u0438\u0441\u0442\u0430\u0440"
    ],
    "name:und_x_variant":[
        "Bistr"
    ],
    "wof:name":"Bistar",
    "wof:placetype":"locality"
},
  "geometry": {"coordinates":[22.43944,42.37444],"type":"Point"}
}