{
  "type": "Feature",
  "properties": {
    "gn:admin1_code":"SE",
    "gn:admin2_code":"24",
    "gn:asciiname":"Bistar",
    "gn:country_code":"RS",
    "gn:dem":849,
    "gn:feature_class":"P",
    "gn:feature_code":"PPL",
    "gn:name":"Bistar",
    "gn:population":0,
    "gn:timezone":"Europe/Belgrade",
    "iso:country":"RS",
    "name:srp_x_preferred":[
        "Bistar"
    ],
    "name:und_x_variant":[
        "Bistr"
    ],
    "wof:name":"Bistar",
    "wof:placetype":"locality"
},
  "geometry": {"coordinates":[22.43944,42.37444],"type":"Point"}
}