{
  "type": "Feature",
  "properties": {
    "gn:admin1_code":"SE",
    "gn:admin2_code":"24",
    "gn:asciiname":"Garvanica",
    "gn:country_code":"RS",
    "gn:dem":359,
    "gn:feature_class":"P",
    "gn:feature_code":"PPL",
    "gn:name":"Garvanica",
    "gn:population":0,
    "gn:timezone":"Europe/Belgrade",
    "iso:country":"RS",
    "wof:name":"Garvanica",
    "wof:placetype":"locality"
},
  "geometry": {"coordinates":[22.01987,42.61785],"type":"Point"}
}