{
  "type": "Feature",
  "properties": {
    "gn:admin1_code":"SE",
    "gn:admin2_code":"24",
    "gn:asciiname":"Dosljaci",
    "gn:country_code":"RS",
    "gn:dem":442,
    "gn:feature_class":"P",
    "gn:feature_code":"PPL",
    "gn:name":"Do\u0161ljaci",
    "gn:population":0,
    "gn:timezone":"Europe/Belgrade",
    "iso:country":"RS",
    "wof:name":"Dosljaci",
    "wof:placetype":"locality"
},
  "geometry": {"coordinates":[21.879,42.44564],"type":"Point"}
}