{
  "type": "Feature",
  "properties": {
    "gn:admin1_code":"SE",
    "gn:admin2_code":"24",
    "gn:asciiname":"Gradiste Mahala",
    "gn:country_code":"RS",
    "gn:dem":1041,
    "gn:feature_class":"P",
    "gn:feature_code":"PPL",
    "gn:name":"Gradi\u0161te Mahala",
    "gn:population":0,
    "gn:timezone":"Europe/Belgrade",
    "iso:country":"RS",
    "wof:name":"Gradiste Mahala",
    "wof:placetype":"locality"
},
  "geometry": {"coordinates":[22.43717,42.38774],"type":"Point"}
}