{
  "type": "Feature",
  "properties": {
    "gn:admin1_code":"SE",
    "gn:admin2_code":"24",
    "gn:asciiname":"Strezovce",
    "gn:country_code":"RS",
    "gn:dem":514,
    "gn:feature_class":"P",
    "gn:feature_code":"PPLL",
    "gn:name":"Strezovce",
    "gn:population":0,
    "gn:timezone":"Europe/Belgrade",
    "iso:country":"RS",
    "name:bul_x_preferred":[
        "\u0421\u0442\u0440\u0435\u0437\u043e\u0432\u0446\u0435"
    ],
    "name:ceb_x_preferred":[
        "Strezovce"
    ],
    "name:deu_x_preferred":[
        "Strezovce"
    ],
    "name:fra_x_preferred":[
        "Strezovce"
    ],
    "name:msa_x_preferred":[
        "Strezovce"
    ],
    "name:por_x_preferred":[
        "Strezovce"
    ],
    "name:slv_x_preferred":[
        "Strezovce"
    ],
    "name:sqi_x_preferred":[
        "Strezovc"
    ],
    "name:sqi_x_variant":[
        "Strezoci"
    ],
    "name:srp_x_preferred":[
        "Strezovce"
    ],
    "name:srp_x_variant":[
        "\u0421\u0442\u0440\u0435\u0437\u043e\u0432\u0446\u0435"
    ],
    "name:und_x_variant":[
        "Strezovc"
    ],
    "wof:name":"Strezovce",
    "wof:placetype":"locality"
},
  "geometry": {"coordinates":[21.73713,42.28437],"type":"Point"}
}