{
  "type": "Feature",
  "properties": {
    "gn:admin1_code":"VO",
    "gn:admin2_code":"3",
    "gn:asciiname":"Totovo Selo",
    "gn:country_code":"RS",
    "gn:dem":100,
    "gn:feature_class":"P",
    "gn:feature_code":"PPL",
    "gn:name":"Totovo Selo",
    "gn:population":0,
    "gn:timezone":"Europe/Belgrade",
    "iso:country":"RS",
    "name:ceb_x_preferred":[
        "Totovo Selo"
    ],
    "name:epo_x_preferred":[
        "Totovo Selo"
    ],
    "name:est_x_preferred":[
        "T\u00f3thfalu"
    ],
    "name:fra_x_preferred":[
        "Totovo Selo"
    ],
    "name:hun_x_preferred":[
        "T\u00f3thfalu"
    ],
    "name:hun_x_variant":[
        "T\u00f3tfalu"
    ],
    "name:msa_x_preferred":[
        "Totovo Selo"
    ],
    "name:rus_x_preferred":[
        "\u0422\u043e\u0442\u043e\u0432\u043e-\u0421\u0435\u043b\u043e"
    ],
    "name:slv_x_preferred":[
        "Totovo Selo"
    ],
    "name:srp_x_preferred":[
        "Totovo Selo"
    ],
    "name:srp_x_variant":[
        "\u0422\u043e\u0442\u043e\u0432\u043e \u0421\u0435\u043b\u043e"
    ],
    "name:ukr_x_preferred":[
        "\u0422\u043e\u0442\u043e\u0432\u0435 \u0421\u0435\u043b\u043e"
    ],
    "wof:name":"Totovo Selo",
    "wof:placetype":"locality"
},
  "geometry": {"coordinates":[19.91736,45.96383],"type":"Point"}
}