{
  "type": "Feature",
  "properties": {
    "gn:admin1_code":"SE",
    "gn:admin2_code":"22",
    "gn:asciiname":"Telovac",
    "gn:country_code":"RS",
    "gn:dem":656,
    "gn:feature_class":"P",
    "gn:feature_code":"PPL",
    "gn:name":"Telovac",
    "gn:population":0,
    "gn:timezone":"Europe/Belgrade",
    "iso:country":"RS",
    "name:srp_x_preferred":[
        "Telovac"
    ],
    "name:und_x_variant":[
        "Tijelovac"
    ],
    "wof:name":"Telovac",
    "wof:placetype":"locality"
},
  "geometry": {"coordinates":[22.40842,43.19647],"type":"Point"}
}