{
  "type": "Feature",
  "properties": {
    "gn:admin1_code":"SE",
    "gn:admin2_code":"23",
    "gn:asciiname":"Mala Grabovnica",
    "gn:country_code":"RS",
    "gn:dem":266,
    "gn:feature_class":"P",
    "gn:feature_code":"PPL",
    "gn:name":"Mala Grabovnica",
    "gn:population":0,
    "gn:timezone":"Europe/Belgrade",
    "iso:country":"RS",
    "name:fra_x_preferred":[
        "Mala Grabovnica"
    ],
    "name:hrv_x_preferred":[
        "Mala Grabovnica"
    ],
    "name:nld_x_preferred":[
        "Mala Grabovnica"
    ],
    "name:slv_x_preferred":[
        "Mala Grabovnica"
    ],
    "name:srp_x_preferred":[
        "Mala Grabovnica"
    ],
    "name:srp_x_variant":[
        "\u041c\u0430\u043b\u0430 \u0413\u0440\u0430\u0431\u043e\u0432\u043d\u0438\u0446\u0430"
    ],
    "name:und_x_variant":[
        "Grabovnica Mala",
        "Mala Grabnica"
    ],
    "wof:name":"Mala Grabovnica",
    "wof:placetype":"locality"
},
  "geometry": {"coordinates":[21.99667,42.92556],"type":"Point"}
}