{
  "type": "Feature",
  "properties": {
    "gn:admin1_code":"SE",
    "gn:admin2_code":"9",
    "gn:asciiname":"Bebici",
    "gn:country_code":"RS",
    "gn:dem":576,
    "gn:feature_class":"P",
    "gn:feature_code":"PPL",
    "gn:name":"Bebi\u0107i",
    "gn:population":0,
    "gn:timezone":"Europe/Belgrade",
    "iso:country":"RS",
    "name:srp_x_preferred":[
        "Bebi\u0107i"
    ],
    "wof:name":"Bebici",
    "wof:placetype":"locality"
},
  "geometry": {"coordinates":[19.69242,44.18876],"type":"Point"}
}