{
  "type": "Feature",
  "properties": {
    "gn:admin1_code":"SE",
    "gn:admin2_code":"17",
    "gn:asciiname":"Donji Branetici",
    "gn:country_code":"RS",
    "gn:dem":444,
    "gn:feature_class":"P",
    "gn:feature_code":"PPL",
    "gn:name":"Donji Braneti\u0107i",
    "gn:population":0,
    "gn:timezone":"Europe/Belgrade",
    "iso:country":"RS",
    "name:ceb_x_preferred":[
        "Donji Braneti\u0107i"
    ],
    "name:fra_x_preferred":[
        "Donji Braneti\u0107i"
    ],
    "name:msa_x_preferred":[
        "Donji Braneti\u0107i"
    ],
    "name:por_x_preferred":[
        "Donji Braneti\u0107i"
    ],
    "name:slv_x_preferred":[
        "Donji Braneti\u0107i"
    ],
    "name:srp_x_preferred":[
        "Donji Braneti\u0107i"
    ],
    "name:srp_x_variant":[
        "\u0414\u043e\u045a\u0438 \u0411\u0440\u0430\u043d\u0435\u0442\u0438\u045b\u0438"
    ],
    "wof:name":"Donji Branetici",
    "wof:placetype":"locality"
},
  "geometry": {"coordinates":[20.33911,44.08758],"type":"Point"}
}