{
  "type": "Feature",
  "properties": {
    "gn:country":"RS",
    "gn:fcode":"PPL",
    "gn:population":1765,
    "iso:country":"RS",
    "name:ceb_x_preferred":[
        "Seleu\u0161"
    ],
    "name:eng_x_preferred":[
        "Seleu\u0161"
    ],
    "name:epo_x_preferred":[
        "Seleu\u015d"
    ],
    "name:fra_x_preferred":[
        "Seleu\u0161"
    ],
    "name:hrv_x_preferred":[
        "Seleu\u0161"
    ],
    "name:hun_x_preferred":[
        "Kevisz\u00f6ll\u0151s"
    ],
    "name:ita_x_preferred":[
        "Seleu\u0161"
    ],
    "name:msa_x_preferred":[
        "Seleu\u0161"
    ],
    "name:nld_x_preferred":[
        "Seleu\u0161"
    ],
    "name:ron_x_preferred":[
        "Seleu\u0219"
    ],
    "name:rus_x_preferred":[
        "\u0421\u0435\u043b\u0435\u0443\u0448"
    ],
    "name:slv_x_preferred":[
        "Seleu\u0161"
    ],
    "name:srp_x_preferred":[
        "Seleu\u0161"
    ],
    "name:srp_x_variant":[
        "\u0421\u0435\u043b\u0435\u0443\u0448"
    ],
    "name:und_x_variant":[
        "Kevisz\u0151l\u0151s"
    ],
    "name:vie_x_preferred":[
        "Seleus"
    ],
    "qs:name":"Seleu\u0161",
    "qs:photos_9r":0,
    "qs:photos_sr":0,
    "qs:pop_sr":"3",
    "wd:wordcount":95,
    "wof:name":"Seleu\u0161",
    "wof:placetype":"locality",
    "wof:population":1765
},
  "geometry": {"coordinates":[20.91461,45.1277],"type":"Point"}
}