{
  "type": "Feature",
  "properties": {
    "gn:admin1_code":"SE",
    "gn:admin2_code":"13",
    "gn:asciiname":"Brainovac",
    "gn:country_code":"RS",
    "gn:dem":273,
    "gn:feature_class":"P",
    "gn:feature_code":"PPL",
    "gn:name":"Brainovac",
    "gn:population":0,
    "gn:timezone":"Europe/Belgrade",
    "iso:country":"RS",
    "name:und_x_variant":[
        "Brajinovac",
        "Brainovac"
    ],
    "wof:name":"Brainovac",
    "wof:placetype":"locality"
},
  "geometry": {"coordinates":[21.12959,43.77884],"type":"Point"}
}