{
  "type": "Feature",
  "properties": {
    "gn:admin1_code":"SE",
    "gn:admin2_code":"16",
    "gn:asciiname":"Braticevici",
    "gn:country_code":"RS",
    "gn:dem":655,
    "gn:feature_class":"P",
    "gn:feature_code":"PPL",
    "gn:name":"Brati\u010devi\u0107i",
    "gn:population":0,
    "gn:timezone":"Europe/Belgrade",
    "iso:country":"RS",
    "name:srp_x_preferred":[
        "Brati\u010devi\u0107i"
    ],
    "wof:name":"Braticevici",
    "wof:placetype":"locality"
},
  "geometry": {"coordinates":[19.68667,44.03417],"type":"Point"}
}