{
  "type": "Feature",
  "properties": {
    "gn:admin1_code":"SE",
    "gn:admin2_code":"20",
    "gn:asciiname":"Drzanovac",
    "gn:country_code":"RS",
    "gn:dem":221,
    "gn:feature_class":"P",
    "gn:feature_code":"PPL",
    "gn:name":"Dr\u017eanovac",
    "gn:population":0,
    "gn:timezone":"Europe/Belgrade",
    "iso:country":"RS",
    "name:srp_x_preferred":[
        "Dr\u017eanovac"
    ],
    "wof:name":"Drzanovac",
    "wof:placetype":"locality"
},
  "geometry": {"coordinates":[21.77355,43.22794],"type":"Point"}
}