{
  "type": "Feature",
  "properties": {
    "gn:admin1_code":"SE",
    "gn:admin2_code":"18",
    "gn:asciiname":"Mitrova Reka",
    "gn:country_code":"RS",
    "gn:dem":614,
    "gn:feature_class":"P",
    "gn:feature_code":"PPL",
    "gn:name":"Mitrova Reka",
    "gn:population":0,
    "gn:timezone":"Europe/Belgrade",
    "iso:country":"RS",
    "name:srp_x_preferred":[
        "Mitrova Reka"
    ],
    "wof:name":"Mitrova Reka",
    "wof:placetype":"locality"
},
  "geometry": {"coordinates":[20.45264,43.21827],"type":"Point"}
}