{
  "type": "Feature",
  "properties": {
    "gn:admin1_code":"SE",
    "gn:admin2_code":"16",
    "gn:asciiname":"Bambaci",
    "gn:country_code":"RS",
    "gn:dem":609,
    "gn:feature_class":"P",
    "gn:feature_code":"PPL",
    "gn:name":"Bambaci",
    "gn:population":0,
    "gn:timezone":"Europe/Belgrade",
    "iso:country":"RS",
    "wof:name":"Bambaci",
    "wof:placetype":"locality"
},
  "geometry": {"coordinates":[19.56883,43.92747],"type":"Point"}
}