{
  "type": "Feature",
  "properties": {
    "gn:admin1_code":"SE",
    "gn:admin2_code":"13",
    "gn:asciiname":"Tresnjevica",
    "gn:country_code":"RS",
    "gn:dem":131,
    "gn:feature_class":"P",
    "gn:feature_code":"PPL",
    "gn:name":"Tre\u0161njevica",
    "gn:population":0,
    "gn:timezone":"Europe/Belgrade",
    "iso:country":"RS",
    "name:srp_x_preferred":[
        "Tre\u0161njevica"
    ],
    "wof:name":"Tresnjevica",
    "wof:placetype":"locality"
},
  "geometry": {"coordinates":[21.32512,43.86999],"type":"Point"}
}