{
  "type": "Feature",
  "properties": {
    "gn:admin1_code":"VO",
    "gn:admin2_code":"7",
    "gn:asciiname":"Satrinci",
    "gn:country_code":"RS",
    "gn:dem":127,
    "gn:feature_class":"P",
    "gn:feature_code":"PPL",
    "gn:name":"\u0160atrinci",
    "gn:population":0,
    "gn:timezone":"Europe/Belgrade",
    "iso:country":"RS",
    "name:ceb_x_preferred":[
        "\u0160atrinci"
    ],
    "name:epo_x_preferred":[
        "\u015catrinci"
    ],
    "name:fra_x_preferred":[
        "\u0160atrinci"
    ],
    "name:hun_x_preferred":[
        "Satrinca"
    ],
    "name:msa_x_preferred":[
        "\u0160atrinci"
    ],
    "name:rus_x_preferred":[
        "\u0428\u0430\u0442\u0440\u0438\u043d\u0446\u0438"
    ],
    "name:slv_x_preferred":[
        "\u0160atrinci"
    ],
    "name:srp_x_preferred":[
        "\u0160atrinci"
    ],
    "name:srp_x_variant":[
        "\u0428\u0430\u0442\u0440\u0438\u043d\u0446\u0438"
    ],
    "name:und_x_variant":[
        "Satrinca",
        "Satrince"
    ],
    "wof:name":"Satrinci",
    "wof:placetype":"locality"
},
  "geometry": {"coordinates":[19.9225,45.06247000000001],"type":"Point"}
}