{
  "type": "Feature",
  "properties": {
    "gn:admin1_code":"SE",
    "gn:admin2_code":"24",
    "gn:asciiname":"Goles",
    "gn:country_code":"RS",
    "gn:dem":1271,
    "gn:feature_class":"P",
    "gn:feature_code":"PPL",
    "gn:name":"Gole\u0161",
    "gn:population":0,
    "gn:timezone":"Europe/Belgrade",
    "iso:country":"RS",
    "name:srp_x_preferred":[
        "Gole\u0161"
    ],
    "wof:name":"Goles",
    "wof:placetype":"locality"
},
  "geometry": {"coordinates":[22.33225,42.33076],"type":"Point"}
}