{
  "type": "Feature",
  "properties": {
    "gn:admin1_code":"SE",
    "gn:admin2_code":"9",
    "gn:asciiname":"Rajkovic",
    "gn:country_code":"RS",
    "gn:dem":312,
    "gn:feature_class":"P",
    "gn:feature_code":"PPL",
    "gn:name":"Rajkovi\u0107",
    "gn:population":0,
    "gn:timezone":"Europe/Belgrade",
    "iso:country":"RS",
    "name:srp_x_preferred":[
        "Rajkovi\u0107"
    ],
    "wof:name":"Rajkovic",
    "wof:placetype":"locality"
},
  "geometry": {"coordinates":[20.01312,44.22479000000001],"type":"Point"}
}