{
  "type": "Feature",
  "properties": {
    "gn:admin1_code":"SE",
    "gn:admin2_code":"16",
    "gn:asciiname":"Zeljine",
    "gn:country_code":"RS",
    "gn:dem":874,
    "gn:feature_class":"P",
    "gn:feature_code":"PPLL",
    "gn:name":"\u017deljine",
    "gn:population":0,
    "gn:timezone":"Europe/Belgrade",
    "iso:country":"RS",
    "name:ceb_x_preferred":[
        "\u017deljine"
    ],
    "name:fra_x_preferred":[
        "\u017deljine"
    ],
    "name:msa_x_preferred":[
        "\u017deljine"
    ],
    "name:nld_x_preferred":[
        "\u017deljine"
    ],
    "name:por_x_preferred":[
        "\u017deljine"
    ],
    "name:slv_x_preferred":[
        "\u017deljine"
    ],
    "name:srp_x_preferred":[
        "\u017deljine"
    ],
    "name:srp_x_variant":[
        "\u0416\u0435\u0459\u0438\u043d\u0435"
    ],
    "name:und_x_variant":[
        "\u017deline"
    ],
    "wof:name":"Zeljine",
    "wof:placetype":"locality"
},
  "geometry": {"coordinates":[19.88802,43.65585],"type":"Point"}
}