{
  "type": "Feature",
  "properties": {
    "gn:admin1_code":"SE",
    "gn:admin2_code":"8",
    "gn:asciiname":"Postenje",
    "gn:country_code":"RS",
    "gn:dem":412,
    "gn:feature_class":"P",
    "gn:feature_code":"PPL",
    "gn:name":"Postenje",
    "gn:population":0,
    "gn:timezone":"Europe/Belgrade",
    "iso:country":"RS",
    "name:bul_x_preferred":[
        "\u041f\u043e\u0441\u0442\u0435\u043d\u0435"
    ],
    "name:fra_x_preferred":[
        "Postenje"
    ],
    "name:hun_x_preferred":[
        "Postenje"
    ],
    "name:msa_x_preferred":[
        "Postenje"
    ],
    "name:nld_x_preferred":[
        "Postenje"
    ],
    "name:por_x_preferred":[
        "Postenje"
    ],
    "name:slv_x_preferred":[
        "Postenje"
    ],
    "name:srp_x_preferred":[
        "Postenje"
    ],
    "name:srp_x_variant":[
        "\u041f\u043e\u0441\u0442\u0435\u045a\u0435"
    ],
    "wof:name":"Postenje",
    "wof:placetype":"locality"
},
  "geometry": {"coordinates":[19.38756,44.28043],"type":"Point"}
}