{
  "type": "Feature",
  "properties": {
    "gn:admin1_code":"SE",
    "gn:admin2_code":"18",
    "gn:asciiname":"Rudno",
    "gn:country_code":"RS",
    "gn:dem":1099,
    "gn:feature_class":"P",
    "gn:feature_code":"PPL",
    "gn:name":"Rudno",
    "gn:population":0,
    "gn:timezone":"Europe/Belgrade",
    "iso:country":"RS",
    "name:srp_x_preferred":[
        "Rudno"
    ],
    "wof:name":"Rudno",
    "wof:placetype":"locality"
},
  "geometry": {"coordinates":[20.48179,43.41473],"type":"Point"}
}