{
  "type": "Feature",
  "properties": {
    "gn:admin1_code":"SE",
    "gn:admin2_code":"18",
    "gn:asciiname":"Rudno",
    "gn:country_code":"RS",
    "gn:dem":1099,
    "gn:feature_class":"P",
    "gn:feature_code":"PPL",
    "gn:name":"Rudno",
    "gn:population":0,
    "gn:timezone":"Europe/Belgrade",
    "iso:country":"RS",
    "name:bos_x_preferred":[
        "Rudno"
    ],
    "name:ceb_x_preferred":[
        "Rudno"
    ],
    "name:deu_x_preferred":[
        "Rudno"
    ],
    "name:epo_x_preferred":[
        "Rudno"
    ],
    "name:fra_x_preferred":[
        "Rudno"
    ],
    "name:pol_x_preferred":[
        "Rudno"
    ],
    "name:slv_x_preferred":[
        "Rudno"
    ],
    "name:srp_x_preferred":[
        "Rudno"
    ],
    "name:srp_x_variant":[
        "\u0420\u0443\u0434\u043d\u043e"
    ],
    "name:swe_x_preferred":[
        "Rudno"
    ],
    "name:ukr_x_preferred":[
        "\u0420\u0443\u0434\u043d\u043e"
    ],
    "wof:name":"Rudno",
    "wof:placetype":"locality"
},
  "geometry": {"coordinates":[20.48179,43.41473],"type":"Point"}
}