{
  "type": "Feature",
  "properties": {
    "gn:admin1_code":"00",
    "gn:asciiname":"Vranovice",
    "gn:country_code":"RS",
    "gn:dem":925,
    "gn:feature_class":"P",
    "gn:feature_code":"PPL",
    "gn:name":"Vranovi\u0107e",
    "gn:population":0,
    "gn:timezone":"Europe/Belgrade",
    "iso:country":"RS",
    "name:ceb_x_preferred":[
        "Vranovice"
    ],
    "name:ces_x_preferred":[
        "Vranovice"
    ],
    "name:deu_x_preferred":[
        "Vranovice"
    ],
    "name:fra_x_preferred":[
        "Vranovice"
    ],
    "name:ita_x_preferred":[
        "Vranovice"
    ],
    "name:nld_x_preferred":[
        "Vranovice"
    ],
    "name:pol_x_preferred":[
        "Vranovice"
    ],
    "name:slk_x_preferred":[
        "Vranovice"
    ],
    "name:srp_x_preferred":[
        "Vranovi\u0107e"
    ],
    "name:srp_x_variant":[
        "\u0412\u0440\u0430\u043d\u043e\u0432\u0438\u0446\u0435"
    ],
    "name:swe_x_preferred":[
        "Vranovice"
    ],
    "name:und_x_variant":[
        "Drainovi\u0107e",
        "Vranovi\u0107i"
    ],
    "wof:name":"Vranovice",
    "wof:placetype":"locality"
},
  "geometry": {"coordinates":[20.55111,42.98373],"type":"Point"}
}