{
  "type": "Feature",
  "properties": {
    "gn:admin1_code":"SE",
    "gn:admin2_code":"21",
    "gn:asciiname":"Spasovici",
    "gn:country_code":"RS",
    "gn:dem":345,
    "gn:feature_class":"P",
    "gn:feature_code":"PPL",
    "gn:name":"Spasovi\u0107i",
    "gn:population":0,
    "gn:timezone":"Europe/Belgrade",
    "iso:country":"RS",
    "wof:name":"Spasovici",
    "wof:placetype":"locality"
},
  "geometry": {"coordinates":[21.46694,43.17139],"type":"Point"}
}