{
  "type": "Feature",
  "properties": {
    "gn:admin1_code":"SE",
    "gn:admin2_code":"24",
    "gn:asciiname":"Pejina Mahala",
    "gn:country_code":"RS",
    "gn:dem":1007,
    "gn:feature_class":"P",
    "gn:feature_code":"PPL",
    "gn:name":"Pejina Mahala",
    "gn:population":0,
    "gn:timezone":"Europe/Belgrade",
    "iso:country":"RS",
    "wof:name":"Pejina Mahala",
    "wof:placetype":"locality"
},
  "geometry": {"coordinates":[22.40337,42.74348],"type":"Point"}
}