{
  "type": "Feature",
  "properties": {
    "gn:admin1_code":"SE",
    "gn:admin2_code":"16",
    "gn:asciiname":"Brajkovac",
    "gn:country_code":"RS",
    "gn:dem":1267,
    "gn:feature_class":"P",
    "gn:feature_code":"PPL",
    "gn:name":"Brajkovac",
    "gn:population":0,
    "gn:timezone":"Europe/Belgrade",
    "iso:country":"RS",
    "name:ceb_x_preferred":[
        "Brajkovac"
    ],
    "name:fra_x_preferred":[
        "Brajkovac"
    ],
    "name:hrv_x_preferred":[
        "Brajkovac"
    ],
    "name:nld_x_preferred":[
        "Brajkovac"
    ],
    "name:slv_x_preferred":[
        "Brajkovac"
    ],
    "name:srp_x_preferred":[
        "Brajkovac"
    ],
    "name:srp_x_variant":[
        "\u0411\u0440\u0430\u0458\u043a\u043e\u0432\u0430\u0446"
    ],
    "name:swe_x_preferred":[
        "Brajkovac"
    ],
    "wof:name":"Brajkovac",
    "wof:placetype":"locality"
},
  "geometry": {"coordinates":[19.59333,43.24833],"type":"Point"}
}