{
  "type": "Feature",
  "properties": {
    "gn:admin1_code":"SE",
    "gn:admin2_code":"11",
    "gn:asciiname":"Dubravica",
    "gn:country_code":"RS",
    "gn:dem":71,
    "gn:feature_class":"P",
    "gn:feature_code":"PPL",
    "gn:name":"Dubravica",
    "gn:population":0,
    "gn:timezone":"Europe/Belgrade",
    "iso:country":"RS",
    "name:ceb_x_preferred":[
        "Dubravica"
    ],
    "name:deu_x_preferred":[
        "Dubravica"
    ],
    "name:fra_x_preferred":[
        "Dubravica"
    ],
    "name:msa_x_preferred":[
        "Dubravica"
    ],
    "name:nld_x_preferred":[
        "Dubravica"
    ],
    "name:por_x_preferred":[
        "Dubravica"
    ],
    "name:ron_x_preferred":[
        "Dubravica"
    ],
    "name:slv_x_preferred":[
        "Dubravica"
    ],
    "name:srp_x_preferred":[
        "Dubravica"
    ],
    "name:srp_x_variant":[
        "\u0414\u0443\u0431\u0440\u0430\u0432\u0438\u0446\u0430"
    ],
    "wof:name":"Dubravica",
    "wof:placetype":"locality"
},
  "geometry": {"coordinates":[21.08017000000001,44.69637],"type":"Point"}
}