{
  "type": "Feature",
  "properties": {
    "gn:admin1_code":"SE",
    "gn:admin2_code":"8",
    "gn:asciiname":"Lipenovic",
    "gn:country_code":"RS",
    "gn:dem":428,
    "gn:feature_class":"P",
    "gn:feature_code":"PPL",
    "gn:name":"Lipenovi\u0107",
    "gn:population":0,
    "gn:timezone":"Europe/Belgrade",
    "iso:country":"RS",
    "name:ceb_x_preferred":[
        "Lipenovi\u0107"
    ],
    "name:fra_x_preferred":[
        "Lipenovi\u0107"
    ],
    "name:msa_x_preferred":[
        "Lipenovi\u0107"
    ],
    "name:nld_x_preferred":[
        "Lipenovi\u0107"
    ],
    "name:por_x_preferred":[
        "Lipenovi\u0107"
    ],
    "name:slv_x_preferred":[
        "Lipenovi\u0107"
    ],
    "name:srp_x_preferred":[
        "Lipenovi\u0107"
    ],
    "name:srp_x_variant":[
        "\u041b\u0438\u043f\u0435\u043d\u043e\u0432\u0438\u045b"
    ],
    "name:und_x_variant":[
        "Lipinovi\u0107"
    ],
    "wof:name":"Lipenovic",
    "wof:placetype":"locality"
},
  "geometry": {"coordinates":[19.37425,44.37583],"type":"Point"}
}