{
  "type": "Feature",
  "properties": {
    "gn:admin1_code":"SE",
    "gn:admin2_code":"17",
    "gn:asciiname":"Mrcajevci",
    "gn:country_code":"RS",
    "gn:dem":232,
    "gn:feature_class":"P",
    "gn:feature_code":"PPL",
    "gn:name":"Mr\u010dajevci",
    "gn:population":0,
    "gn:timezone":"Europe/Belgrade",
    "iso:country":"RS",
    "name:ceb_x_preferred":[
        "Mr\u010dajevci"
    ],
    "name:fas_x_preferred":[
        "\u0645\u0631\u0686\u0627\u06cc\u0648\u062a\u0633\u06cc"
    ],
    "name:fra_x_preferred":[
        "Mr\u010dajevci"
    ],
    "name:hrv_x_preferred":[
        "Mr\u010dajevci"
    ],
    "name:msa_x_preferred":[
        "Mr\u010dajevci"
    ],
    "name:por_x_preferred":[
        "Mr\u010dajevci"
    ],
    "name:slv_x_preferred":[
        "Mr\u010dajevci"
    ],
    "name:srp_x_preferred":[
        "\u041c\u0440\u0447\u0430\u0458\u0435\u0432\u0446\u0438"
    ],
    "name:und_x_variant":[
        "Mr\u010dajevci"
    ],
    "wof:name":"Mrcajevci",
    "wof:placetype":"locality"
},
  "geometry": {"coordinates":[20.52694,43.86801],"type":"Point"}
}