{
  "type": "Feature",
  "properties": {
    "gn:admin1_code":"SE",
    "gn:admin2_code":"17",
    "gn:asciiname":"Savinac",
    "gn:country_code":"RS",
    "gn:dem":341,
    "gn:feature_class":"P",
    "gn:feature_code":"PPL",
    "gn:name":"Savinac",
    "gn:population":0,
    "gn:timezone":"Europe/Belgrade",
    "iso:country":"RS",
    "name:fra_x_preferred":[
        "Savinac"
    ],
    "wof:name":"Savinac",
    "wof:placetype":"locality"
},
  "geometry": {"coordinates":[20.36041,44.02435],"type":"Point"}
}