{
  "type": "Feature",
  "properties": {
    "gn:admin1_code":"SE",
    "gn:admin2_code":"24",
    "gn:asciiname":"Cerovac",
    "gn:country_code":"RS",
    "gn:dem":640,
    "gn:feature_class":"P",
    "gn:feature_code":"PPL",
    "gn:name":"Cerovac",
    "gn:population":0,
    "gn:timezone":"Europe/Belgrade",
    "iso:country":"RS",
    "name:bos_x_preferred":[
        "Cerovac"
    ],
    "name:ceb_x_preferred":[
        "Cerovac"
    ],
    "name:fra_x_preferred":[
        "Cerovac"
    ],
    "name:hrv_x_preferred":[
        "Cerovac"
    ],
    "name:hun_x_preferred":[
        "Cerovac"
    ],
    "name:nld_x_preferred":[
        "Cerovac"
    ],
    "name:slv_x_preferred":[
        "Cerovac"
    ],
    "name:srp_x_preferred":[
        "\u0426\u0435\u0440\u043e\u0432\u0430\u0446"
    ],
    "name:swe_x_preferred":[
        "Cerovac"
    ],
    "name:und_x_variant":[
        "Cerovici",
        "Cerovac"
    ],
    "wof:name":"Cerovac",
    "wof:placetype":"locality"
},
  "geometry": {"coordinates":[21.87358,42.35859],"type":"Point"}
}