{
  "type": "Feature",
  "properties": {
    "gn:admin1_code":"SE",
    "gn:admin2_code":"24",
    "gn:asciiname":"Cerovac",
    "gn:country_code":"RS",
    "gn:dem":640,
    "gn:feature_class":"P",
    "gn:feature_code":"PPL",
    "gn:name":"Cerovac",
    "gn:population":0,
    "gn:timezone":"Europe/Belgrade",
    "iso:country":"RS",
    "name:und_x_variant":[
        "Cerovici",
        "Cerovac"
    ],
    "wof:name":"Cerovac",
    "wof:placetype":"locality"
},
  "geometry": {"coordinates":[21.87358,42.35859],"type":"Point"}
}