{
  "type": "Feature",
  "properties": {
    "gn:admin1_code":"SE",
    "gn:admin2_code":"16",
    "gn:asciiname":"Sinanovici",
    "gn:country_code":"RS",
    "gn:dem":926,
    "gn:feature_class":"P",
    "gn:feature_code":"PPL",
    "gn:name":"Sinanovi\u0107i",
    "gn:population":0,
    "gn:timezone":"Europe/Belgrade",
    "iso:country":"RS",
    "name:srp_x_preferred":[
        "Sinanovi\u0107i"
    ],
    "wof:name":"Sinanovici",
    "wof:placetype":"locality"
},
  "geometry": {"coordinates":[19.28622,43.57081],"type":"Point"}
}