{
  "type": "Feature",
  "properties": {
    "gn:admin1_code":"SE",
    "gn:admin2_code":"19",
    "gn:asciiname":"Ravniste",
    "gn:country_code":"RS",
    "gn:dem":1078,
    "gn:feature_class":"P",
    "gn:feature_code":"PPLL",
    "gn:name":"Ravni\u0161te",
    "gn:population":0,
    "gn:timezone":"Europe/Belgrade",
    "iso:country":"RS",
    "name:srp_x_preferred":[
        "Ravni\u0161te"
    ],
    "wof:name":"Ravniste",
    "wof:placetype":"locality"
},
  "geometry": {"coordinates":[20.8776,43.26505],"type":"Point"}
}