{
  "type": "Feature",
  "properties": {
    "gn:admin1_code":"SE",
    "gn:admin2_code":"20",
    "gn:asciiname":"Gare",
    "gn:country_code":"RS",
    "gn:dem":584,
    "gn:feature_class":"P",
    "gn:feature_code":"PPL",
    "gn:name":"Gare",
    "gn:population":0,
    "gn:timezone":"Europe/Belgrade",
    "iso:country":"RS",
    "name:srp_x_preferred":[
        "Gare"
    ],
    "name:und_x_variant":[
        "Gornje Gare"
    ],
    "wof:name":"Gare",
    "wof:placetype":"locality"
},
  "geometry": {"coordinates":[22.0736,43.15968],"type":"Point"}
}