{
  "type": "Feature",
  "properties": {
    "gn:admin1_code":"SE",
    "gn:admin2_code":"24",
    "gn:asciiname":"Kopiste",
    "gn:country_code":"RS",
    "gn:dem":892,
    "gn:feature_class":"P",
    "gn:feature_code":"PPL",
    "gn:name":"Kopi\u0161te",
    "gn:population":0,
    "gn:timezone":"Europe/Belgrade",
    "iso:country":"RS",
    "name:srp_x_preferred":[
        "Kopi\u0161te"
    ],
    "name:und_x_variant":[
        "Seli\u0161te"
    ],
    "wof:name":"Kopiste",
    "wof:placetype":"locality"
},
  "geometry": {"coordinates":[22.49111,42.42],"type":"Point"}
}