{
  "type": "Feature",
  "properties": {
    "gn:admin1_code":"SE",
    "gn:admin2_code":"0",
    "gn:asciiname":"Strazarija",
    "gn:country_code":"RS",
    "gn:dem":262,
    "gn:feature_class":"P",
    "gn:feature_code":"PPL",
    "gn:name":"Stra\u017earija",
    "gn:population":0,
    "gn:timezone":"Europe/Belgrade",
    "iso:country":"RS",
    "wof:name":"Strazarija",
    "wof:placetype":"locality"
},
  "geometry": {"coordinates":[20.46253,44.59486],"type":"Point"}
}