{
  "type": "Feature",
  "properties": {
    "gn:admin1_code":"SE",
    "gn:admin2_code":"16",
    "gn:asciiname":"Gornje Pravosevo",
    "gn:country_code":"RS",
    "gn:dem":1299,
    "gn:feature_class":"P",
    "gn:feature_code":"PPL",
    "gn:name":"Gornje Pravo\u0161evo",
    "gn:population":0,
    "gn:timezone":"Europe/Belgrade",
    "iso:country":"RS",
    "wof:name":"Gornje Pravosevo",
    "wof:placetype":"locality"
},
  "geometry": {"coordinates":[19.79111,43.39139],"type":"Point"}
}