{
  "type": "Feature",
  "properties": {
    "gn:admin1_code":"SE",
    "gn:admin2_code":"14",
    "gn:asciiname":"Cubra",
    "gn:country_code":"RS",
    "gn:dem":118,
    "gn:feature_class":"P",
    "gn:feature_code":"PPL",
    "gn:name":"\u010cubra",
    "gn:population":0,
    "gn:timezone":"Europe/Belgrade",
    "iso:country":"RS",
    "name:ceb_x_preferred":[
        "\u010cubra"
    ],
    "name:deu_x_preferred":[
        "\u010cubra"
    ],
    "name:fra_x_preferred":[
        "\u010cubra"
    ],
    "name:msa_x_preferred":[
        "\u010cubra"
    ],
    "name:por_x_preferred":[
        "\u010cubra"
    ],
    "name:slv_x_preferred":[
        "\u010cubra"
    ],
    "name:srp_x_preferred":[
        "\u010cubra"
    ],
    "name:srp_x_variant":[
        "\u0427\u0443\u0431\u0440\u0430"
    ],
    "wof:name":"Cubra",
    "wof:placetype":"locality"
},
  "geometry": {"coordinates":[22.46763,44.19003],"type":"Point"}
}