{
  "type": "Feature",
  "properties": {
    "gn:admin1_code":"SE",
    "gn:admin2_code":"23",
    "gn:asciiname":"Sirovicine",
    "gn:country_code":"RS",
    "gn:dem":997,
    "gn:feature_class":"P",
    "gn:feature_code":"PPL",
    "gn:name":"Sirovi\u010dine",
    "gn:population":0,
    "gn:timezone":"Europe/Belgrade",
    "iso:country":"RS",
    "name:srp_x_preferred":[
        "Sirovi\u010dine"
    ],
    "name:und_x_variant":[
        "Sirovi\u010dane"
    ],
    "wof:name":"Sirovicine",
    "wof:placetype":"locality"
},
  "geometry": {"coordinates":[22.27853,42.86996],"type":"Point"}
}