{
  "type": "Feature",
  "properties": {
    "gn:country":"RS",
    "gn:fcode":"PPLA3",
    "gn:population":2232,
    "iso:country":"RS",
    "name:afr_x_preferred":[
        "Pe\u0107inci"
    ],
    "name:ara_x_preferred":[
        "\u0628\u06cc\u0633\u0646\u062c\u064a"
    ],
    "name:ara_x_variant":[
        "\u0628\u064a\u0633\u0646\u062c\u064a"
    ],
    "name:arz_x_preferred":[
        "\u0628\u064a\u0633\u0646\u062c\u0649"
    ],
    "name:bos_x_preferred":[
        "Pe\u0107inci"
    ],
    "name:ceb_x_preferred":[
        "Pe\u0107inci"
    ],
    "name:ces_x_preferred":[
        "Pe\u0107inci"
    ],
    "name:deu_x_preferred":[
        "Op\u0161tina Pe\u0107inci"
    ],
    "name:deu_x_variant":[
        "Pe\u0107inci"
    ],
    "name:eng_x_preferred":[
        "Pe\u0107inci"
    ],
    "name:epo_x_preferred":[
        "Pecjinci"
    ],
    "name:epo_x_variant":[
        "Pe\u0109inci"
    ],
    "name:fas_x_preferred":[
        "\u067e\u0686\u06cc\u0646\u062a\u0633\u06cc"
    ],
    "name:fra_x_preferred":[
        "Pe\u0107inci"
    ],
    "name:hbs_x_preferred":[
        "Op\u0161tina Pe\u0107inci"
    ],
    "name:heb_x_preferred":[
        "\u05e4\u05e6\u05d9\u05e0\u05e6\u05d9"
    ],
    "name:hin_x_preferred":[
        "\u092a\u0947c\u0907\u0928\u094dc\u0907"
    ],
    "name:hrv_x_preferred":[
        "Pe\u0107inci"
    ],
    "name:hun_x_preferred":[
        "Pecsince"
    ],
    "name:ita_x_preferred":[
        "Pe\u0107inci"
    ],
    "name:jpn_x_preferred":[
        "\u30da\u30c1\u30f3\u30c4\u30a3"
    ],
    "name:kor_x_preferred":[
        "\ud398\uce5c\uce58"
    ],
    "name:lit_x_preferred":[
        "Pe\u010dinsai"
    ],
    "name:msa_x_preferred":[
        "Pe\u0107inci"
    ],
    "name:nld_x_preferred":[
        "Pe\u0107inci"
    ],
    "name:pnb_x_preferred":[
        "\u067e\u06cc\u0633\u0646\u0686\u06cc"
    ],
    "name:pol_x_preferred":[
        "Pe\u0107inci"
    ],
    "name:rus_x_preferred":[
        "\u041f\u0435\u0447\u0438\u043d\u0446\u0438"
    ],
    "name:slk_x_preferred":[
        "Pe\u0107inci"
    ],
    "name:slv_x_preferred":[
        "Pe\u0107inci"
    ],
    "name:spa_x_preferred":[
        "Pe\u0107inci"
    ],
    "name:srp_x_preferred":[
        "Pe\u0107inci"
    ],
    "name:srp_x_variant":[
        "\u041e\u043f\u0448\u0442\u0438\u043d\u0430 \u041f\u0435\u045b\u0438\u043d\u0446\u0438"
    ],
    "name:tat_x_preferred":[
        "\u041f\u0435\u0447\u0438\u043d\u0441\u0438"
    ],
    "name:tur_x_preferred":[
        "Pe\u0107inci"
    ],
    "name:und_x_variant":[
        "Pe\u0107inei"
    ],
    "name:urd_x_preferred":[
        "\u0628\u06cc\u0633\u0646\u062c\u064a"
    ],
    "name:zho_x_preferred":[
        "\u4f69\u6b3d\u9f4a"
    ],
    "qs:name":"Pe\u0107inci",
    "qs:photos_9r":0,
    "qs:photos_sr":0,
    "qs:pop_sr":"4",
    "wd:wordcount":559,
    "wof:name":"Pe\u0107inci",
    "wof:placetype":"locality",
    "wof:population":2232
},
  "geometry": {"coordinates":[19.96639,44.90889],"type":"Point"}
}