{
  "type": "Feature",
  "properties": {
    "gn:admin1_code":"SE",
    "gn:admin2_code":"0",
    "gn:asciiname":"Smrdan",
    "gn:country_code":"RS",
    "gn:dem":221,
    "gn:feature_class":"P",
    "gn:feature_code":"PPL",
    "gn:name":"Smrdan",
    "gn:population":0,
    "gn:timezone":"Europe/Belgrade",
    "iso:country":"RS",
    "name:ceb_x_preferred":[
        "Smrdan"
    ],
    "name:fra_x_preferred":[
        "Smrdan"
    ],
    "name:hrv_x_preferred":[
        "Smrdan"
    ],
    "name:slv_x_preferred":[
        "Smrdan"
    ],
    "name:srp_x_preferred":[
        "\u0421\u043c\u0440\u0434\u0430\u043d"
    ],
    "name:swe_x_preferred":[
        "Smrdan"
    ],
    "wof:name":"Smrdan",
    "wof:placetype":"locality"
},
  "geometry": {"coordinates":[20.5375,44.64611],"type":"Point"}
}