{
  "type": "Feature",
  "properties": {
    "gn:admin1_code":"VO",
    "gn:admin2_code":"1",
    "gn:asciiname":"Srednji Salas",
    "gn:country_code":"RS",
    "gn:dem":110,
    "gn:feature_class":"P",
    "gn:feature_code":"PPL",
    "gn:name":"Srednji Sala\u0161",
    "gn:population":0,
    "gn:timezone":"Europe/Belgrade",
    "iso:country":"RS",
    "name:srp_x_preferred":[
        "Srednji Sala\u0161"
    ],
    "name:und_x_variant":[
        "Generalski Ili\u0107",
        "Srednji Sala\u0161i"
    ],
    "wof:name":"Srednji Salas",
    "wof:placetype":"locality"
},
  "geometry": {"coordinates":[19.47838,45.75031],"type":"Point"}
}