{
  "type": "Feature",
  "properties": {
    "gn:admin1_code":"VO",
    "gn:admin2_code":"1",
    "gn:asciiname":"Srednji Salas",
    "gn:country_code":"RS",
    "gn:dem":110,
    "gn:feature_class":"P",
    "gn:feature_code":"PPL",
    "gn:name":"Srednji Sala\u0161",
    "gn:population":0,
    "gn:timezone":"Europe/Belgrade",
    "iso:country":"RS",
    "name:ceb_x_preferred":[
        "Srednji Sala\u0161"
    ],
    "name:epo_x_preferred":[
        "Srednji Sala\u015d"
    ],
    "name:fra_x_preferred":[
        "Srednji Sala\u0161"
    ],
    "name:hrv_x_preferred":[
        "Srednji Sala\u0161"
    ],
    "name:hun_x_preferred":[
        "Szurkos"
    ],
    "name:ita_x_preferred":[
        "Srednji Sala\u0161"
    ],
    "name:msa_x_preferred":[
        "Srednji Sala\u0161"
    ],
    "name:rus_x_preferred":[
        "\u0421\u0440\u0435\u0434\u043d\u0438-\u0421\u0430\u043b\u0430\u0448"
    ],
    "name:slv_x_preferred":[
        "Srednji Sala\u0161"
    ],
    "name:srp_x_preferred":[
        "Srednji Sala\u0161"
    ],
    "name:srp_x_variant":[
        "\u0421\u0440\u0435\u0434\u045a\u0438 \u0421\u0430\u043b\u0430\u0448"
    ],
    "name:ukr_x_preferred":[
        "\u0421\u0435\u0440\u0435\u0434\u043d\u0456\u0439 \u0421\u0430\u043b\u0430\u0448"
    ],
    "name:und_x_variant":[
        "Generalski Ili\u0107",
        "Srednji Sala\u0161i"
    ],
    "wof:name":"Srednji Salas",
    "wof:placetype":"locality"
},
  "geometry": {"coordinates":[19.47838,45.75031],"type":"Point"}
}