{
  "type": "Feature",
  "properties": {
    "gn:country":"RS",
    "gn:fcode":"PPLL",
    "gn:population":303,
    "iso:country":"RS",
    "name:bul_x_preferred":[
        "\u0412\u0438\u0441\u043e\u043a\u0430"
    ],
    "name:eng_x_preferred":[
        "Visoka"
    ],
    "name:fra_x_preferred":[
        "Visoka"
    ],
    "name:msa_x_preferred":[
        "Visoka"
    ],
    "name:nld_x_preferred":[
        "Visoka"
    ],
    "name:por_x_preferred":[
        "Visoka"
    ],
    "name:slv_x_preferred":[
        "Visoka"
    ],
    "name:sqi_x_preferred":[
        "Visoka"
    ],
    "name:srp_x_preferred":[
        "Visoka"
    ],
    "name:srp_x_variant":[
        "\u0412\u0438\u0441\u043e\u043a\u0430"
    ],
    "name:und_x_variant":[
        "Visoko"
    ],
    "qs:name":"Visoka",
    "qs:photos_9r":0,
    "qs:photos_sr":0,
    "qs:pop_sr":"2",
    "wd:wordcount":68,
    "wof:name":"Visoka",
    "wof:placetype":"locality",
    "wof:population":303
},
  "geometry": {"coordinates":[21.28444,43.10574],"type":"Point"}
}