{
  "type": "Feature",
  "properties": {
    "iso:country":"RS",
    "name:eng_x_preferred":[
        "Banovo Brdo"
    ],
    "name:srp_cyr_x_preferred":[
        "\u0411\u0430\u043d\u043e\u0432\u043e \u0431\u0440\u0434\u043e"
    ],
    "name:srp_x_preferred":[
        "\u0411\u0430\u043d\u043e\u0432\u043e \u0431\u0440\u0434\u043e"
    ],
    "wof:name":"Banovo Brdo",
    "wof:placetype":"neighbourhood"
},
  "geometry": {"coordinates":[20.41873838321429,44.77730648514776],"type":"Point"}
}