{
  "type": "Feature",
  "properties": {
    "gn:admin1_code":"SE",
    "gn:admin2_code":"18",
    "gn:asciiname":"Gosevo",
    "gn:country_code":"RS",
    "gn:dem":1012,
    "gn:feature_class":"P",
    "gn:feature_code":"PPL",
    "gn:name":"Go\u0161evo",
    "gn:population":0,
    "gn:timezone":"Europe/Belgrade",
    "iso:country":"RS",
    "name:srp_x_preferred":[
        "Go\u0161evo"
    ],
    "wof:name":"Gosevo",
    "wof:placetype":"locality"
},
  "geometry": {"coordinates":[20.35133,43.219],"type":"Point"}
}