{
  "type": "Feature",
  "properties": {
    "gn:admin1_code":"SE",
    "gn:admin2_code":"16",
    "gn:asciiname":"Debelja",
    "gn:country_code":"RS",
    "gn:dem":1128,
    "gn:feature_class":"P",
    "gn:feature_code":"PPLL",
    "gn:name":"Debelja",
    "gn:population":0,
    "gn:timezone":"Europe/Belgrade",
    "iso:country":"RS",
    "name:srp_x_preferred":[
        "Debelja"
    ],
    "wof:name":"Debelja",
    "wof:placetype":"locality"
},
  "geometry": {"coordinates":[19.92864,43.47534],"type":"Point"}
}