{
  "type": "Feature",
  "properties": {
    "gn:admin1_code":"SE",
    "gn:admin2_code":"16",
    "gn:asciiname":"Bakionica",
    "gn:country_code":"RS",
    "gn:dem":373,
    "gn:feature_class":"P",
    "gn:feature_code":"PPL",
    "gn:name":"Bakionica",
    "gn:population":0,
    "gn:timezone":"Europe/Belgrade",
    "iso:country":"RS",
    "name:ceb_x_preferred":[
        "Bakionica"
    ],
    "name:fra_x_preferred":[
        "Bakionica"
    ],
    "name:msa_x_preferred":[
        "Bakionica"
    ],
    "name:nld_x_preferred":[
        "Bakionica"
    ],
    "name:por_x_preferred":[
        "Bakionica"
    ],
    "name:slv_x_preferred":[
        "Bakionica"
    ],
    "name:srp_x_preferred":[
        "Bakionica"
    ],
    "name:srp_x_variant":[
        "\u0411\u0430\u043a\u0438\u043e\u043d\u0438\u0446\u0430"
    ],
    "wof:name":"Bakionica",
    "wof:placetype":"locality"
},
  "geometry": {"coordinates":[20.04316,43.85829],"type":"Point"}
}