{
  "type": "Feature",
  "properties": {
    "gn:admin1_code":"SE",
    "gn:admin2_code":"21",
    "gn:asciiname":"Dake",
    "gn:country_code":"RS",
    "gn:dem":955,
    "gn:feature_class":"P",
    "gn:feature_code":"PPL",
    "gn:name":"Dake",
    "gn:population":0,
    "gn:timezone":"Europe/Belgrade",
    "iso:country":"RS",
    "name:deu_x_preferred":[
        "Dake"
    ],
    "name:srp_x_preferred":[
        "Dake"
    ],
    "wof:name":"Dake",
    "wof:placetype":"locality"
},
  "geometry": {"coordinates":[21.42119,43.00107],"type":"Point"}
}