{
  "type": "Feature",
  "properties": {
    "gn:admin1_code":"SE",
    "gn:admin2_code":"23",
    "gn:asciiname":"Brvenik",
    "gn:country_code":"RS",
    "gn:dem":845,
    "gn:feature_class":"P",
    "gn:feature_code":"PPL",
    "gn:name":"Brvenik",
    "gn:population":0,
    "gn:timezone":"Europe/Belgrade",
    "iso:country":"RS",
    "name:fra_x_preferred":[
        "Brvenik"
    ],
    "name:hun_x_preferred":[
        "Brvenik"
    ],
    "name:msa_x_preferred":[
        "Brvenik"
    ],
    "name:nld_x_preferred":[
        "Brvenik"
    ],
    "name:por_x_preferred":[
        "Brvenik"
    ],
    "name:slv_x_preferred":[
        "Brvenik"
    ],
    "name:srp_x_preferred":[
        "Brvenik"
    ],
    "name:srp_x_variant":[
        "\u0411\u0440\u0432\u0435\u043d\u0438\u043a"
    ],
    "wof:name":"Brvenik",
    "wof:placetype":"locality"
},
  "geometry": {"coordinates":[21.42673,42.81186],"type":"Point"}
}