{
  "type": "Feature",
  "properties": {
    "gn:country":"RS",
    "gn:fcode":"PPL",
    "gn:pop":2569,
    "iso:country":"RS",
    "name:deu_x_preferred":[
        "Boto\u0161"
    ],
    "name:eng_x_preferred":[
        "Botos"
    ],
    "name:epo_x_preferred":[
        "Boto\u015d"
    ],
    "name:fra_x_preferred":[
        "Botos"
    ],
    "name:glg_x_preferred":[
        "Botos"
    ],
    "name:hrv_x_preferred":[
        "Boto\u0161"
    ],
    "name:hun_x_preferred":[
        "B\u00f3tos"
    ],
    "name:msa_x_preferred":[
        "Boto\u0161"
    ],
    "name:nld_x_preferred":[
        "Boto\u0161"
    ],
    "name:pms_x_preferred":[
        "Botos"
    ],
    "name:ron_x_preferred":[
        "Boto\u0161"
    ],
    "name:rus_x_preferred":[
        "\u0411\u043e\u0442\u043e\u0448"
    ],
    "name:slv_x_preferred":[
        "Boto\u0161"
    ],
    "name:spa_x_preferred":[
        "Botos"
    ],
    "name:srp_x_preferred":[
        "Boto\u0161"
    ],
    "name:srp_x_variant":[
        "\u0411\u043e\u0442\u043e\u0448"
    ],
    "name:unk_x_variant":[
        "Botosch"
    ],
    "qs:name":"Boto\u0161",
    "qs:photos_9r":0,
    "qs:photos_sr":0,
    "qs:pop_sr":"4",
    "wd:wordcount":122,
    "wof:name":"Boto\u0161",
    "wof:placetype":"locality",
    "wof:population":2569
},
  "geometry": {"coordinates":[20.63514,45.30837],"type":"Point"}
}