{
  "type": "Feature",
  "properties": {
    "gn:admin1_code":"SE",
    "gn:admin2_code":"16",
    "gn:asciiname":"Dedovac",
    "gn:country_code":"RS",
    "gn:dem":729,
    "gn:feature_class":"P",
    "gn:feature_code":"PPL",
    "gn:name":"\u00d0edovac",
    "gn:population":0,
    "gn:timezone":"Europe/Belgrade",
    "iso:country":"RS",
    "name:srp_x_preferred":[
        "\u00d0edovac"
    ],
    "wof:name":"Dedovac",
    "wof:placetype":"locality"
},
  "geometry": {"coordinates":[19.91247000000001,43.63994],"type":"Point"}
}