{
  "type": "Feature",
  "properties": {
    "gn:admin1_code":"SE",
    "gn:admin2_code":"8",
    "gn:asciiname":"Ignjatovici",
    "gn:country_code":"RS",
    "gn:dem":168,
    "gn:feature_class":"P",
    "gn:feature_code":"PPL",
    "gn:name":"Ignjatovi\u0107i",
    "gn:population":0,
    "gn:timezone":"Europe/Belgrade",
    "iso:country":"RS",
    "name:srp_x_preferred":[
        "Ignjatovi\u0107i"
    ],
    "wof:name":"Ignjatovici",
    "wof:placetype":"locality"
},
  "geometry": {"coordinates":[19.29562,44.5537],"type":"Point"}
}