{
  "type": "Feature",
  "properties": {
    "gn:admin1_code":"SE",
    "gn:admin2_code":"12",
    "gn:asciiname":"Lipar",
    "gn:country_code":"RS",
    "gn:dem":247,
    "gn:feature_class":"P",
    "gn:feature_code":"PPL",
    "gn:name":"Lipar",
    "gn:population":0,
    "gn:timezone":"Europe/Belgrade",
    "iso:country":"RS",
    "name:ceb_x_preferred":[
        "Lipar"
    ],
    "name:epo_x_preferred":[
        "Lipar"
    ],
    "name:fra_x_preferred":[
        "Lipar"
    ],
    "name:hrv_x_preferred":[
        "Lipar"
    ],
    "name:hun_x_preferred":[
        "B\u00e1csistenseg\u00edts"
    ],
    "name:msa_x_preferred":[
        "Lipar"
    ],
    "name:ron_x_preferred":[
        "Lipar"
    ],
    "name:slv_x_preferred":[
        "Lipar"
    ],
    "name:srp_x_preferred":[
        "Lipar"
    ],
    "name:srp_x_variant":[
        "\u041b\u0438\u043f\u0430\u0440"
    ],
    "name:ukr_x_preferred":[
        "\u041b\u0456\u043f\u0430\u0440"
    ],
    "wof:name":"Lipar",
    "wof:placetype":"locality"
},
  "geometry": {"coordinates":[20.62889,44.32444],"type":"Point"}
}