{
  "type": "Feature",
  "properties": {
    "gn:admin1_code":"SE",
    "gn:admin2_code":"16",
    "gn:asciiname":"Kokosice",
    "gn:country_code":"RS",
    "gn:dem":1114,
    "gn:feature_class":"P",
    "gn:feature_code":"PPL",
    "gn:name":"Koko\u0161i\u0107e",
    "gn:population":0,
    "gn:timezone":"Europe/Belgrade",
    "iso:country":"RS",
    "name:ceb_x_preferred":[
        "Koko\u0161i\u0107e"
    ],
    "name:fra_x_preferred":[
        "Koko\u0161i\u0107e"
    ],
    "name:msa_x_preferred":[
        "Koko\u0161i\u0107e"
    ],
    "name:nld_x_preferred":[
        "Koko\u0161i\u0107e"
    ],
    "name:por_x_preferred":[
        "Koko\u0161i\u0107e"
    ],
    "name:slv_x_preferred":[
        "Koko\u0161i\u0107e"
    ],
    "name:srp_x_preferred":[
        "Koko\u0161i\u0107e"
    ],
    "name:srp_x_variant":[
        "\u041a\u043e\u043a\u043e\u0448\u0438\u045b\u0435"
    ],
    "wof:name":"Kokosice",
    "wof:placetype":"locality"
},
  "geometry": {"coordinates":[20.14023,43.26084],"type":"Point"}
}