{
  "type": "Feature",
  "properties": {
    "gn:country":"RS",
    "gn:fcode":"PPL",
    "gn:pop":4,
    "iso:country":"RS",
    "name:srp_x_preferred":[
        "Dedina"
    ],
    "qs:name":"Dedina",
    "qs:photos_9r":0,
    "qs:photos_sr":0,
    "qs:pop_sr":"1",
    "wd:wordcount":69,
    "wof:name":"Dedina",
    "wof:placetype":"locality",
    "wof:population":4
},
  "geometry": {"coordinates":[21.36075,43.58928],"type":"Point"}
}