{
  "type": "Feature",
  "properties": {
    "gn:country":"RS",
    "gn:fcode":"PPL",
    "gn:population":4,
    "iso:country":"RS",
    "name:ceb_x_preferred":[
        "Dedina"
    ],
    "name:deu_x_preferred":[
        "Dedina"
    ],
    "name:eng_x_preferred":[
        "Dedina"
    ],
    "name:fra_x_preferred":[
        "Dedina"
    ],
    "name:hye_x_preferred":[
        "\u0534\u0565\u0564\u056b\u0576\u0561"
    ],
    "name:msa_x_preferred":[
        "Dedina"
    ],
    "name:nld_x_preferred":[
        "Dedina"
    ],
    "name:por_x_preferred":[
        "Dedina"
    ],
    "name:slv_x_preferred":[
        "Dedina"
    ],
    "name:srp_x_preferred":[
        "Dedina"
    ],
    "name:srp_x_variant":[
        "\u0414\u0435\u0434\u0438\u043d\u0430"
    ],
    "qs:name":"Dedina",
    "qs:photos_9r":0,
    "qs:photos_sr":0,
    "qs:pop_sr":"1",
    "wd:wordcount":69,
    "wof:name":"Dedina",
    "wof:placetype":"locality",
    "wof:population":4
},
  "geometry": {"coordinates":[21.36075,43.58928],"type":"Point"}
}