{
  "type": "Feature",
  "properties": {
    "gn:country":"RS",
    "gn:fcode":"PPL",
    "gn:population":2694,
    "iso:country":"RS",
    "name:ceb_x_preferred":[
        "Kupusina"
    ],
    "name:ces_x_preferred":[
        "Kupusina"
    ],
    "name:eng_x_preferred":[
        "Kupusina"
    ],
    "name:epo_x_preferred":[
        "Kupusina"
    ],
    "name:fas_x_preferred":[
        "\u06a9\u0648\u067e\u0648\u0633\u06cc\u0646\u0627"
    ],
    "name:fra_x_preferred":[
        "Kupusina"
    ],
    "name:hrv_x_preferred":[
        "Kupusina"
    ],
    "name:hun_x_preferred":[
        "B\u00e1cskertes"
    ],
    "name:ita_x_preferred":[
        "Kupusina"
    ],
    "name:msa_x_preferred":[
        "Kupusina"
    ],
    "name:nld_x_preferred":[
        "Kupusina"
    ],
    "name:pol_x_preferred":[
        "Kupusina"
    ],
    "name:slv_x_preferred":[
        "Kupusina"
    ],
    "name:spa_x_preferred":[
        "Kupusina"
    ],
    "name:srp_x_preferred":[
        "Kupusina"
    ],
    "name:srp_x_variant":[
        "\u041a\u0443\u043f\u0443\u0441\u0438\u043d\u0430"
    ],
    "name:ukr_x_preferred":[
        "\u041a\u0443\u043f\u0443\u0441\u0438\u043d\u0430"
    ],
    "qs:name":"Kupusina",
    "qs:photos_9r":0,
    "qs:photos_sr":0,
    "qs:pop_sr":"4",
    "wd:wordcount":185,
    "wof:name":"Kupusina",
    "wof:placetype":"locality",
    "wof:population":2694
},
  "geometry": {"coordinates":[19.01082,45.73759],"type":"Point"}
}