{
  "type": "Feature",
  "properties": {
    "gn:country":"RS",
    "gn:fcode":"PPL",
    "gn:pop":2694,
    "iso:country":"RS",
    "name:dut_x_preferred":[
        "Kupusina"
    ],
    "name:eng_x_preferred":[
        "Kupusina"
    ],
    "name:epo_x_preferred":[
        "Kupusina"
    ],
    "name:fre_x_preferred":[
        "Kupusina"
    ],
    "name:hrv_x_preferred":[
        "Kupusina"
    ],
    "name:hun_x_preferred":[
        "B\u00e1cskertes"
    ],
    "name:ita_x_preferred":[
        "Kupusina"
    ],
    "name:may_x_preferred":[
        "Kupusina"
    ],
    "name:slv_x_preferred":[
        "Kupusina"
    ],
    "name:srp_x_preferred":[
        "Kupusina"
    ],
    "name:ukr_x_preferred":[
        "\u041a\u0443\u043f\u0443\u0441\u0438\u043d\u0430"
    ],
    "name:unk_x_variant":[
        "B\u00e1cskertes"
    ],
    "qs:name":"Kupusina",
    "qs:photos_9r":0,
    "qs:photos_sr":0,
    "qs:pop_sr":"4",
    "wd:wordcount":185,
    "wof:name":"Kupusina",
    "wof:placetype":"locality",
    "wof:population":2694
},
  "geometry": {"coordinates":[19.01082,45.73759],"type":"Point"}
}