{
  "type": "Feature",
  "properties": {
    "gn:admin1_code":"SE",
    "gn:admin2_code":"21",
    "gn:asciiname":"Bumburek",
    "gn:country_code":"RS",
    "gn:dem":308,
    "gn:feature_class":"P",
    "gn:feature_code":"PPL",
    "gn:name":"Bumburek",
    "gn:population":0,
    "gn:timezone":"Europe/Belgrade",
    "iso:country":"RS",
    "name:srp_x_preferred":[
        "Bumburek"
    ],
    "wof:name":"Bumburek",
    "wof:placetype":"locality"
},
  "geometry": {"coordinates":[21.55354,43.25315],"type":"Point"}
}