{
  "type": "Feature",
  "properties": {
    "gn:admin1_code":"SE",
    "gn:admin2_code":"24",
    "gn:asciiname":"Cvalikari",
    "gn:country_code":"RS",
    "gn:dem":1069,
    "gn:feature_class":"P",
    "gn:feature_code":"PPL",
    "gn:name":"Cvalikari",
    "gn:population":0,
    "gn:timezone":"Europe/Belgrade",
    "iso:country":"RS",
    "wof:name":"Cvalikari",
    "wof:placetype":"locality"
},
  "geometry": {"coordinates":[22.25462000000001,42.70089],"type":"Point"}
}