{
  "type": "Feature",
  "properties": {
    "gn:admin1_code":"VO",
    "gn:admin2_code":"7",
    "gn:asciiname":"Besenovo",
    "gn:country_code":"RS",
    "gn:dem":154,
    "gn:feature_class":"P",
    "gn:feature_code":"PPL",
    "gn:name":"Be\u0161enovo",
    "gn:population":0,
    "gn:timezone":"Europe/Belgrade",
    "iso:country":"RS",
    "name:ceb_x_preferred":[
        "Be\u0161enovo"
    ],
    "name:epo_x_preferred":[
        "Be\u015denovo"
    ],
    "name:fra_x_preferred":[
        "Be\u0161enovo"
    ],
    "name:hrv_x_preferred":[
        "Be\u0161enovo"
    ],
    "name:hun_x_preferred":[
        "Beseny\u0151"
    ],
    "name:msa_x_preferred":[
        "Be\u0161enovo"
    ],
    "name:rus_x_preferred":[
        "\u0411\u0435\u0448\u0435\u043d\u043e\u0432\u043e"
    ],
    "name:slv_x_preferred":[
        "Be\u0161enovo"
    ],
    "name:srp_x_preferred":[
        "Be\u0161enovo"
    ],
    "name:srp_x_variant":[
        "\u0411\u0435\u0448\u0435\u043d\u043e\u0432\u043e"
    ],
    "name:und_x_variant":[
        "Beseny\u0151",
        "Beshenovo",
        "Bessenovo"
    ],
    "wof:name":"Besenovo",
    "wof:placetype":"locality"
},
  "geometry": {"coordinates":[19.70408,45.08364],"type":"Point"}
}