{
  "type": "Feature",
  "properties": {
    "gn:admin1_code":"SE",
    "gn:admin2_code":"16",
    "gn:asciiname":"Malo Polje",
    "gn:country_code":"RS",
    "gn:dem":1005,
    "gn:feature_class":"P",
    "gn:feature_code":"PPL",
    "gn:name":"Malo Polje",
    "gn:population":0,
    "gn:timezone":"Europe/Belgrade",
    "iso:country":"RS",
    "name:bos_x_preferred":[
        "Malo Polje"
    ],
    "name:fra_x_preferred":[
        "Malo Polje"
    ],
    "name:hrv_x_preferred":[
        "Malo Polje"
    ],
    "name:hun_x_preferred":[
        "Malo Polje"
    ],
    "name:nld_x_preferred":[
        "Malo Polje"
    ],
    "name:slv_x_preferred":[
        "Malo Polje"
    ],
    "name:srp_x_preferred":[
        "Malo Polje"
    ],
    "name:srp_x_variant":[
        "\u041c\u0430\u043b\u043e \u041f\u043e\u0459\u0435"
    ],
    "wof:name":"Malo Polje",
    "wof:placetype":"locality"
},
  "geometry": {"coordinates":[19.56573,43.74204],"type":"Point"}
}