{
  "type": "Feature",
  "properties": {
    "gn:country":"RS",
    "gn:fcode":"PPL",
    "gn:pop":5,
    "iso:country":"RS",
    "qs:name":"Tr\u0161ljice",
    "qs:photos_9r":0,
    "qs:photos_sr":0,
    "qs:pop_sr":"1",
    "wof:name":"Tr\u0161ljice",
    "wof:placetype":"locality",
    "wof:population":5
},
  "geometry": {"coordinates":[20.54111,43.62556],"type":"Point"}
}