{
  "type": "Feature",
  "properties": {
    "gn:admin1_code":"SE",
    "gn:admin2_code":"17",
    "gn:asciiname":"Knezevici",
    "gn:country_code":"RS",
    "gn:dem":510,
    "gn:feature_class":"P",
    "gn:feature_code":"PPL",
    "gn:name":"Kne\u017eevi\u0107i",
    "gn:population":0,
    "gn:timezone":"Europe/Belgrade",
    "iso:country":"RS",
    "wof:name":"Knezevici",
    "wof:placetype":"locality"
},
  "geometry": {"coordinates":[20.33667,43.7825],"type":"Point"}
}