{
  "type": "Feature",
  "properties": {
    "iso:country":"RS",
    "name:eng_x_preferred":[
        "Visnjica"
    ],
    "name:srp_cyr_x_preferred":[
        "\u0412\u0438\u0448\u045a\u0438\u0446\u0430"
    ],
    "name:srp_lat_x_preferred":[
        "Vi\u0161njica"
    ],
    "wof:name":"Visnjica",
    "wof:placetype":"neighbourhood"
},
  "geometry": {"coordinates":[20.54689476798385,44.82643333444461],"type":"Point"}
}