{
  "type": "Feature",
  "properties": {
    "gn:admin1_code":"SE",
    "gn:admin2_code":"19",
    "gn:asciiname":"Trecak",
    "gn:country_code":"RS",
    "gn:dem":836,
    "gn:feature_class":"P",
    "gn:feature_code":"PPL",
    "gn:name":"Tre\u0107ak",
    "gn:population":0,
    "gn:timezone":"Europe/Belgrade",
    "iso:country":"RS",
    "name:bul_x_preferred":[
        "\u0422\u0440\u0435\u0447\u0430\u043a"
    ],
    "name:fra_x_preferred":[
        "Tre\u0107ak"
    ],
    "name:msa_x_preferred":[
        "Tre\u0107ak"
    ],
    "name:por_x_preferred":[
        "Tre\u0107ak"
    ],
    "name:slv_x_preferred":[
        "Tre\u0107ak"
    ],
    "name:sqi_x_preferred":[
        "Treqaku"
    ],
    "name:srp_x_preferred":[
        "Tre\u0107ak"
    ],
    "name:srp_x_variant":[
        "\u0422\u0440\u0435\u045b\u0430\u043a"
    ],
    "wof:name":"Trecak",
    "wof:placetype":"locality"
},
  "geometry": {"coordinates":[21.015,43.26111],"type":"Point"}
}