{
  "type": "Feature",
  "properties": {
    "gn:admin1_code":"SE",
    "gn:admin2_code":"19",
    "gn:asciiname":"Trecak",
    "gn:country_code":"RS",
    "gn:dem":836,
    "gn:feature_class":"P",
    "gn:feature_code":"PPL",
    "gn:name":"Tre\u0107ak",
    "gn:population":0,
    "gn:timezone":"Europe/Belgrade",
    "iso:country":"RS",
    "name:srp_x_preferred":[
        "Tre\u0107ak"
    ],
    "wof:name":"Trecak",
    "wof:placetype":"locality"
},
  "geometry": {"coordinates":[21.015,43.26111],"type":"Point"}
}