{
  "type": "Feature",
  "properties": {
    "gn:admin1_code":"SE",
    "gn:admin2_code":"16",
    "gn:asciiname":"Marici",
    "gn:country_code":"RS",
    "gn:dem":1127,
    "gn:feature_class":"P",
    "gn:feature_code":"PPL",
    "gn:name":"Mari\u0107i",
    "gn:population":0,
    "gn:timezone":"Europe/Belgrade",
    "iso:country":"RS",
    "name:srp_x_preferred":[
        "Mari\u0107i"
    ],
    "wof:name":"Marici",
    "wof:placetype":"locality"
},
  "geometry": {"coordinates":[19.36514,43.85851],"type":"Point"}
}