{
  "type": "Feature",
  "properties": {
    "gn:admin1_code":"SE",
    "gn:admin2_code":"16",
    "gn:asciiname":"Culici",
    "gn:country_code":"RS",
    "gn:dem":824,
    "gn:feature_class":"P",
    "gn:feature_code":"PPL",
    "gn:name":"\u010culi\u0107i",
    "gn:population":0,
    "gn:timezone":"Europe/Belgrade",
    "iso:country":"RS",
    "name:srp_x_preferred":[
        "\u010culi\u0107i"
    ],
    "wof:name":"Culici",
    "wof:placetype":"locality"
},
  "geometry": {"coordinates":[19.55361,43.84306],"type":"Point"}
}