{
  "type": "Feature",
  "properties": {
    "gn:admin1_code":"SE",
    "gn:admin2_code":"23",
    "gn:asciiname":"Nova Topola",
    "gn:country_code":"RS",
    "gn:dem":305,
    "gn:feature_class":"P",
    "gn:feature_code":"PPLL",
    "gn:name":"Nova Topola",
    "gn:population":0,
    "gn:timezone":"Europe/Belgrade",
    "iso:country":"RS",
    "name:srp_x_preferred":[
        "Nova Topola"
    ],
    "wof:name":"Nova Topola",
    "wof:placetype":"locality"
},
  "geometry": {"coordinates":[21.77233,42.98585],"type":"Point"}
}