{
  "type": "Feature",
  "properties": {
    "gn:admin1_code":"SE",
    "gn:admin2_code":"16",
    "gn:asciiname":"Lukici",
    "gn:country_code":"RS",
    "gn:dem":760,
    "gn:feature_class":"P",
    "gn:feature_code":"PPL",
    "gn:name":"Luki\u0107i",
    "gn:population":0,
    "gn:timezone":"Europe/Belgrade",
    "iso:country":"RS",
    "name:srp_x_preferred":[
        "Luki\u0107i"
    ],
    "wof:name":"Lukici",
    "wof:placetype":"locality"
},
  "geometry": {"coordinates":[19.97329,43.67684000000001],"type":"Point"}
}