{
  "type": "Feature",
  "properties": {
    "gn:admin1_code":"SE",
    "gn:admin2_code":"18",
    "gn:asciiname":"Rovace",
    "gn:country_code":"RS",
    "gn:dem":807,
    "gn:feature_class":"P",
    "gn:feature_code":"PPL",
    "gn:name":"Rova\u010de",
    "gn:population":0,
    "gn:timezone":"Europe/Belgrade",
    "iso:country":"RS",
    "name:srp_x_preferred":[
        "Rova\u010de"
    ],
    "wof:name":"Rovace",
    "wof:placetype":"locality"
},
  "geometry": {"coordinates":[20.55917,43.41306],"type":"Point"}
}