{
  "type": "Feature",
  "properties": {
    "gn:admin1_code":"SE",
    "gn:admin2_code":"12",
    "gn:asciiname":"Radmilovici",
    "gn:country_code":"RS",
    "gn:dem":326,
    "gn:feature_class":"P",
    "gn:feature_code":"PPL",
    "gn:name":"Radmilovi\u0107i",
    "gn:population":0,
    "gn:timezone":"Europe/Belgrade",
    "iso:country":"RS",
    "wof:name":"Radmilovici",
    "wof:placetype":"locality"
},
  "geometry": {"coordinates":[20.63306,43.93697],"type":"Point"}
}