{
  "type": "Feature",
  "properties": {
    "gn:admin1_code":"SE",
    "gn:admin2_code":"17",
    "gn:asciiname":"Osonica",
    "gn:country_code":"RS",
    "gn:dem":836,
    "gn:feature_class":"P",
    "gn:feature_code":"PPLL",
    "gn:name":"Osonica",
    "gn:population":0,
    "gn:timezone":"Europe/Belgrade",
    "iso:country":"RS",
    "name:srp_x_preferred":[
        "Osonica"
    ],
    "wof:name":"Osonica",
    "wof:placetype":"locality"
},
  "geometry": {"coordinates":[20.33517,43.59551],"type":"Point"}
}