{
  "type": "Feature",
  "properties": {
    "gn:admin1_code":"SE",
    "gn:admin2_code":"17",
    "gn:asciiname":"Osonica",
    "gn:country_code":"RS",
    "gn:dem":836,
    "gn:feature_class":"P",
    "gn:feature_code":"PPLL",
    "gn:name":"Osonica",
    "gn:population":0,
    "gn:timezone":"Europe/Belgrade",
    "iso:country":"RS",
    "name:ceb_x_preferred":[
        "Osonica"
    ],
    "name:fas_x_preferred":[
        "\u0627\u0648\u0633\u0648\u0646\u06cc\u062a\u0633\u0627"
    ],
    "name:fra_x_preferred":[
        "Osonica"
    ],
    "name:msa_x_preferred":[
        "Osonica"
    ],
    "name:por_x_preferred":[
        "Osonica"
    ],
    "name:slv_x_preferred":[
        "Osonica"
    ],
    "name:srp_x_preferred":[
        "Osonica"
    ],
    "name:srp_x_variant":[
        "\u041e\u0441\u043e\u043d\u0438\u0446\u0430"
    ],
    "wof:name":"Osonica",
    "wof:placetype":"locality"
},
  "geometry": {"coordinates":[20.33517,43.59551],"type":"Point"}
}