{
  "type": "Feature",
  "properties": {
    "gn:admin1_code":"SE",
    "gn:admin2_code":"16",
    "gn:asciiname":"Sare",
    "gn:country_code":"RS",
    "gn:dem":1017,
    "gn:feature_class":"P",
    "gn:feature_code":"PPL",
    "gn:name":"\u0160are",
    "gn:population":0,
    "gn:timezone":"Europe/Belgrade",
    "iso:country":"RS",
    "name:srp_x_preferred":[
        "\u0160are"
    ],
    "wof:name":"Sare",
    "wof:placetype":"locality"
},
  "geometry": {"coordinates":[20.23987,43.27826],"type":"Point"}
}