{
  "type": "Feature",
  "properties": {
    "gn:admin1_code":"00",
    "gn:asciiname":"Dolinci",
    "gn:country_code":"RS",
    "gn:dem":552,
    "gn:feature_class":"P",
    "gn:feature_code":"PPL",
    "gn:name":"Dolinci",
    "gn:population":0,
    "gn:timezone":"Europe/Belgrade",
    "iso:country":"RS",
    "name:und_x_variant":[
        "Dolinska Maala",
        "Dolinska Mahala",
        "Dolinci"
    ],
    "wof:name":"Dolinci",
    "wof:placetype":"locality"
},
  "geometry": {"coordinates":[21.75836,42.27452],"type":"Point"}
}