{
  "type": "Feature",
  "properties": {
    "gn:admin1_code":"SE",
    "gn:admin2_code":"15",
    "gn:asciiname":"Radenkovac",
    "gn:country_code":"RS",
    "gn:dem":697,
    "gn:feature_class":"P",
    "gn:feature_code":"PPL",
    "gn:name":"Radenkovac",
    "gn:population":0,
    "gn:timezone":"Europe/Belgrade",
    "iso:country":"RS",
    "name:srp_x_preferred":[
        "Radenkovac"
    ],
    "wof:name":"Radenkovac",
    "wof:placetype":"locality"
},
  "geometry": {"coordinates":[21.93221,43.5487],"type":"Point"}
}