{
  "type": "Feature",
  "properties": {
    "gn:admin1_code":"SE",
    "gn:admin2_code":"24",
    "gn:asciiname":"Prestojceva Mahala",
    "gn:country_code":"RS",
    "gn:dem":1281,
    "gn:feature_class":"P",
    "gn:feature_code":"PPL",
    "gn:name":"Prestoj\u010deva Mahala",
    "gn:population":0,
    "gn:timezone":"Europe/Belgrade",
    "iso:country":"RS",
    "wof:name":"Prestojceva Mahala",
    "wof:placetype":"locality"
},
  "geometry": {"coordinates":[22.31786,42.74818],"type":"Point"}
}