{
  "type": "Feature",
  "properties": {
    "gn:admin1_code":"SE",
    "gn:admin2_code":"16",
    "gn:asciiname":"Strmecica",
    "gn:country_code":"RS",
    "gn:dem":958,
    "gn:feature_class":"P",
    "gn:feature_code":"PPL",
    "gn:name":"Strme\u010dica",
    "gn:population":0,
    "gn:timezone":"Europe/Belgrade",
    "iso:country":"RS",
    "name:srp_x_preferred":[
        "Strme\u010dica"
    ],
    "wof:name":"Strmecica",
    "wof:placetype":"locality"
},
  "geometry": {"coordinates":[19.54313,43.65729],"type":"Point"}
}