{
  "type": "Feature",
  "properties": {
    "gn:admin1_code":"SE",
    "gn:admin2_code":"10",
    "gn:asciiname":"Drugovac",
    "gn:country_code":"RS",
    "gn:dem":224,
    "gn:feature_class":"P",
    "gn:feature_code":"PPL",
    "gn:name":"Drugovac",
    "gn:population":0,
    "gn:timezone":"Europe/Belgrade",
    "iso:country":"RS",
    "name:ell_x_preferred":[
        "\u039d\u03c4\u03c1\u03bf\u03cd\u03b3\u03ba\u03bf\u03b2\u03b1\u03c4\u03c2"
    ],
    "name:fra_x_preferred":[
        "Drugovac"
    ],
    "name:msa_x_preferred":[
        "Drugovac"
    ],
    "name:por_x_preferred":[
        "Drugovac"
    ],
    "name:slv_x_preferred":[
        "Drugovac"
    ],
    "name:srp_x_preferred":[
        "Drugovac"
    ],
    "name:srp_x_variant":[
        "\u0414\u0440\u0443\u0433\u043e\u0432\u0430\u0446"
    ],
    "wof:name":"Drugovac",
    "wof:placetype":"locality"
},
  "geometry": {"coordinates":[20.83164,44.54606],"type":"Point"}
}