{
  "type": "Feature",
  "properties": {
    "gn:admin1_code":"SE",
    "gn:admin2_code":"10",
    "gn:asciiname":"Drugovac",
    "gn:country_code":"RS",
    "gn:dem":224,
    "gn:feature_class":"P",
    "gn:feature_code":"PPL",
    "gn:name":"Drugovac",
    "gn:population":0,
    "gn:timezone":"Europe/Belgrade",
    "iso:country":"RS",
    "name:srp_x_preferred":[
        "Drugovac"
    ],
    "wof:name":"Drugovac",
    "wof:placetype":"locality"
},
  "geometry": {"coordinates":[20.83164,44.54606],"type":"Point"}
}