{
  "type": "Feature",
  "properties": {
    "iso:country":"RS",
    "name:eng_x_preferred":[
        "Pretok"
    ],
    "name:srp_cyr_x_preferred":[
        "\u041f\u0440\u0435\u0442\u043e\u043a"
    ],
    "name:srp_x_preferred":[
        "\u041f\u0440\u0435\u0442\u043e\u043a"
    ],
    "wof:name":"Pretok",
    "wof:placetype":"neighbourhood"
},
  "geometry": {"coordinates":[20.46675534544013,44.89202716446862],"type":"Point"}
}