{
  "type": "Feature",
  "properties": {
    "gn:admin1_code":"SE",
    "gn:admin2_code":"21",
    "gn:asciiname":"Zlata",
    "gn:country_code":"RS",
    "gn:dem":321,
    "gn:feature_class":"P",
    "gn:feature_code":"PPL",
    "gn:name":"Zlata",
    "gn:population":0,
    "gn:timezone":"Europe/Belgrade",
    "iso:country":"RS",
    "name:ces_x_preferred":[
        "Zlata"
    ],
    "name:deu_x_preferred":[
        "Zlata"
    ],
    "name:ell_x_preferred":[
        "\u0396\u03bb\u03ac\u03c4\u03b1"
    ],
    "name:msa_x_preferred":[
        "Zlata"
    ],
    "name:nor_x_preferred":[
        "Zlata"
    ],
    "name:rus_x_preferred":[
        "\u0417\u043b\u0430\u0442\u0430"
    ],
    "name:slv_x_preferred":[
        "Zlata"
    ],
    "name:spa_x_preferred":[
        "Zlata"
    ],
    "name:srp_x_preferred":[
        "Zlata"
    ],
    "name:srp_x_variant":[
        "\u0417\u043b\u0430\u0442\u0430"
    ],
    "name:ukr_x_preferred":[
        "\u0417\u043b\u0430\u0442\u0430"
    ],
    "wof:name":"Zlata",
    "wof:placetype":"locality"
},
  "geometry": {"coordinates":[21.65396,43.07286],"type":"Point"}
}