{
  "type": "Feature",
  "properties": {
    "gn:admin1_code":"SE",
    "gn:admin2_code":"24",
    "gn:asciiname":"Kumica",
    "gn:country_code":"RS",
    "gn:dem":1016,
    "gn:feature_class":"P",
    "gn:feature_code":"PPL",
    "gn:name":"Kumica",
    "gn:population":0,
    "gn:timezone":"Europe/Belgrade",
    "iso:country":"RS",
    "name:und_x_variant":[
        "Kumica Mahala",
        "Kumica"
    ],
    "wof:name":"Kumica",
    "wof:placetype":"locality"
},
  "geometry": {"coordinates":[22.48058,42.40444],"type":"Point"}
}