{
  "type": "Feature",
  "properties": {
    "gn:admin1_code":"SE",
    "gn:admin2_code":"16",
    "gn:asciiname":"Potocari",
    "gn:country_code":"RS",
    "gn:dem":462,
    "gn:feature_class":"P",
    "gn:feature_code":"PPL",
    "gn:name":"Poto\u010dari",
    "gn:population":0,
    "gn:timezone":"Europe/Belgrade",
    "iso:country":"RS",
    "name:srp_x_preferred":[
        "Poto\u010dari"
    ],
    "wof:name":"Potocari",
    "wof:placetype":"locality"
},
  "geometry": {"coordinates":[19.63393,43.93382],"type":"Point"}
}