{
  "type": "Feature",
  "properties": {
    "gn:admin1_code":"SE",
    "gn:admin2_code":"16",
    "gn:asciiname":"Gornja Crvica",
    "gn:country_code":"RS",
    "gn:dem":305,
    "gn:feature_class":"P",
    "gn:feature_code":"PPLL",
    "gn:name":"Gornja Crvica",
    "gn:population":0,
    "gn:timezone":"Europe/Belgrade",
    "iso:country":"RS",
    "name:srp_x_preferred":[
        "Gornja Crvica"
    ],
    "wof:name":"Gornja Crvica",
    "wof:placetype":"locality"
},
  "geometry": {"coordinates":[19.58867,43.99791],"type":"Point"}
}