{
  "type": "Feature",
  "properties": {
    "gn:admin1_code":"SE",
    "gn:admin2_code":"19",
    "gn:asciiname":"Malo Krusince",
    "gn:country_code":"RS",
    "gn:dem":354,
    "gn:feature_class":"P",
    "gn:feature_code":"PPL",
    "gn:name":"Malo Kru\u0161ince",
    "gn:population":0,
    "gn:timezone":"Europe/Belgrade",
    "iso:country":"RS",
    "name:ceb_x_preferred":[
        "Malo Kru\u0161ince"
    ],
    "name:fra_x_preferred":[
        "Malo Kru\u0161ince"
    ],
    "name:msa_x_preferred":[
        "Malo Kru\u0161ince"
    ],
    "name:por_x_preferred":[
        "Malo Kru\u0161ince"
    ],
    "name:slv_x_preferred":[
        "Malo Kru\u0161ince"
    ],
    "name:srp_x_preferred":[
        "Malo Kru\u0161ince"
    ],
    "name:srp_x_variant":[
        "\u041c\u0430\u043b\u043e \u041a\u0440\u0443\u0448\u0438\u043d\u0446\u0435"
    ],
    "wof:name":"Malo Krusince",
    "wof:placetype":"locality"
},
  "geometry": {"coordinates":[21.52611,43.45896],"type":"Point"}
}