{
  "type": "Feature",
  "properties": {
    "gn:admin1_code":"SE",
    "gn:admin2_code":"19",
    "gn:asciiname":"Pavlovo Brdo",
    "gn:country_code":"RS",
    "gn:dem":352,
    "gn:feature_class":"P",
    "gn:feature_code":"PPL",
    "gn:name":"Pavlovo Brdo",
    "gn:population":0,
    "gn:timezone":"Europe/Belgrade",
    "iso:country":"RS",
    "name:srp_x_preferred":[
        "Pavlovo Brdo"
    ],
    "wof:name":"Pavlovo Brdo",
    "wof:placetype":"locality"
},
  "geometry": {"coordinates":[21.07938,43.49554000000001],"type":"Point"}
}