{
  "type": "Feature",
  "properties": {
    "gn:admin1_code":"SE",
    "gn:admin2_code":"19",
    "gn:asciiname":"Donji Dubic",
    "gn:country_code":"RS",
    "gn:dem":381,
    "gn:feature_class":"P",
    "gn:feature_code":"PPL",
    "gn:name":"Donji Dubi\u010d",
    "gn:population":0,
    "gn:timezone":"Europe/Belgrade",
    "iso:country":"RS",
    "name:ceb_x_preferred":[
        "Donji Dubi\u010d"
    ],
    "name:fra_x_preferred":[
        "Donji Dubi\u010d"
    ],
    "name:msa_x_preferred":[
        "Donji Dubi\u010d"
    ],
    "name:por_x_preferred":[
        "Donji Dubi\u010d"
    ],
    "name:slv_x_preferred":[
        "Donji Dubi\u010d"
    ],
    "name:srp_x_preferred":[
        "Donji Dubi\u010d"
    ],
    "name:srp_x_variant":[
        "\u0414\u043e\u045a\u0438 \u0414\u0443\u0431\u0438\u0447"
    ],
    "wof:name":"Donji Dubic",
    "wof:placetype":"locality"
},
  "geometry": {"coordinates":[21.01332,43.71495],"type":"Point"}
}