{
  "type": "Feature",
  "properties": {
    "gn:admin1_code":"SE",
    "gn:admin2_code":"17",
    "gn:asciiname":"Kostunici",
    "gn:country_code":"RS",
    "gn:dem":608,
    "gn:feature_class":"P",
    "gn:feature_code":"PPL",
    "gn:name":"Ko\u0161tuni\u0107i",
    "gn:population":0,
    "gn:timezone":"Europe/Belgrade",
    "iso:country":"RS",
    "name:ceb_x_preferred":[
        "Ko\u0161tuni\u0107i"
    ],
    "name:fas_x_preferred":[
        "\u06a9\u0648\u0634\u062a\u0648\u0646\u06cc\u0686\u06cc"
    ],
    "name:fra_x_preferred":[
        "Ko\u0161tuni\u0107i"
    ],
    "name:msa_x_preferred":[
        "Ko\u0161tuni\u0107i"
    ],
    "name:por_x_preferred":[
        "Ko\u0161tuni\u0107i"
    ],
    "name:slv_x_preferred":[
        "Ko\u0161tuni\u0107i"
    ],
    "name:srp_x_preferred":[
        "Ko\u0161tuni\u0107i"
    ],
    "name:srp_x_variant":[
        "\u041a\u043e\u0448\u0442\u0443\u043d\u0438\u045b\u0438"
    ],
    "wof:name":"Kostunici",
    "wof:placetype":"locality"
},
  "geometry": {"coordinates":[20.19719,44.08186],"type":"Point"}
}