{
  "type": "Feature",
  "properties": {
    "gn:admin1_code":"SE",
    "gn:admin2_code":"19",
    "gn:asciiname":"Leskovica",
    "gn:country_code":"RS",
    "gn:dem":694,
    "gn:feature_class":"P",
    "gn:feature_code":"PPL",
    "gn:name":"Leskovica",
    "gn:population":0,
    "gn:timezone":"Europe/Belgrade",
    "iso:country":"RS",
    "name:ceb_x_preferred":[
        "Leskovica"
    ],
    "name:fra_x_preferred":[
        "Leskovica"
    ],
    "name:hye_x_preferred":[
        "\u053c\u0565\u057d\u056f\u0578\u057e\u056b\u0581\u0561"
    ],
    "name:msa_x_preferred":[
        "Leskovica"
    ],
    "name:por_x_preferred":[
        "Leskovica"
    ],
    "name:slv_x_preferred":[
        "Leskovica"
    ],
    "name:spa_x_preferred":[
        "Leskovica"
    ],
    "name:srp_x_preferred":[
        "Leskovica"
    ],
    "name:srp_x_variant":[
        "\u041b\u0435\u0441\u043a\u043e\u0432\u0438\u0446\u0430"
    ],
    "wof:name":"Leskovica",
    "wof:placetype":"locality"
},
  "geometry": {"coordinates":[21.01139,43.52426],"type":"Point"}
}