{
  "type": "Feature",
  "properties": {
    "gn:admin1_code":"SE",
    "gn:admin2_code":"19",
    "gn:asciiname":"Leskovica",
    "gn:country_code":"RS",
    "gn:dem":694,
    "gn:feature_class":"P",
    "gn:feature_code":"PPL",
    "gn:name":"Leskovica",
    "gn:population":0,
    "gn:timezone":"Europe/Belgrade",
    "iso:country":"RS",
    "name:srp_x_preferred":[
        "Leskovica"
    ],
    "wof:name":"Leskovica",
    "wof:placetype":"locality"
},
  "geometry": {"coordinates":[21.01139,43.52426],"type":"Point"}
}