{
  "type": "Feature",
  "properties": {
    "gn:admin1_code":"SE",
    "gn:admin2_code":"16",
    "gn:asciiname":"Donje Goracice",
    "gn:country_code":"RS",
    "gn:dem":1205,
    "gn:feature_class":"P",
    "gn:feature_code":"PPL",
    "gn:name":"Donje Gora\u010di\u0107e",
    "gn:population":0,
    "gn:timezone":"Europe/Belgrade",
    "iso:country":"RS",
    "name:fra_x_preferred":[
        "Donje Gora\u010di\u0107e"
    ],
    "name:msa_x_preferred":[
        "Donje Gora\u010di\u0107e"
    ],
    "name:nld_x_preferred":[
        "Donje Gora\u010di\u0107e"
    ],
    "name:por_x_preferred":[
        "Donje Gora\u010di\u0107e"
    ],
    "name:slv_x_preferred":[
        "Donje Gora\u010di\u0107e"
    ],
    "name:srp_x_preferred":[
        "Donje Gora\u010di\u0107e"
    ],
    "name:srp_x_variant":[
        "\u0414\u043e\u045a\u0435 \u0413\u043e\u0440\u0430\u0447\u0438\u045b\u0435"
    ],
    "name:und_x_variant":[
        "Donji Gora\u010di\u0107i"
    ],
    "wof:name":"Donje Goracice",
    "wof:placetype":"locality"
},
  "geometry": {"coordinates":[19.89077,43.33862],"type":"Point"}
}