{
  "type": "Feature",
  "properties": {
    "gn:admin1_code":"SE",
    "gn:admin2_code":"18",
    "gn:asciiname":"Rsovci",
    "gn:country_code":"RS",
    "gn:dem":348,
    "gn:feature_class":"P",
    "gn:feature_code":"PPL",
    "gn:name":"Rsovci",
    "gn:population":0,
    "gn:timezone":"Europe/Belgrade",
    "iso:country":"RS",
    "name:fra_x_preferred":[
        "Rsavci"
    ],
    "name:hun_x_preferred":[
        "Rsavci"
    ],
    "name:msa_x_preferred":[
        "Rsavci"
    ],
    "name:nld_x_preferred":[
        "Rsavci"
    ],
    "name:por_x_preferred":[
        "Rsavci"
    ],
    "name:slv_x_preferred":[
        "Rsavci"
    ],
    "name:srp_x_preferred":[
        "Rsovci"
    ],
    "name:srp_x_variant":[
        "\u0420\u0441\u0430\u0432\u0446\u0438"
    ],
    "wof:name":"Rsovci",
    "wof:placetype":"locality"
},
  "geometry": {"coordinates":[20.83223,43.6198],"type":"Point"}
}