{
  "type": "Feature",
  "properties": {
    "gn:admin1_code":"SE",
    "gn:admin2_code":"11",
    "gn:asciiname":"Izvor",
    "gn:country_code":"RS",
    "gn:dem":150,
    "gn:feature_class":"P",
    "gn:feature_code":"PPL",
    "gn:name":"Izvor",
    "gn:population":0,
    "gn:timezone":"Europe/Belgrade",
    "iso:country":"RS",
    "wof:name":"Izvor",
    "wof:placetype":"locality"
},
  "geometry": {"coordinates":[21.32222,44.26306],"type":"Point"}
}